[
    {
        "source": "LinkedIn",
        "company": "La Javaness",
        "location": "Paris, √éle-de-France, France",
        "link": "https://fr.linkedin.com/jobs/view/data-architect-at-la-javaness-3646114499?position=2&pageNum=0&refId=a5rwPua%2FMvx%2F2M%2FPSF0oPA%3D%3D&trackingId=Yk0NP1kjoSKWXhEqbeXfPA%3D%3D&trk=public_jobs_jserp-result_search-card",
        "description": "En 5 ans, La Javaness s'est impos√©e comme leader fran√ßais de l'IA pour les entreprises (BtoB). Sans tambour ni trompettes (mais avec beaucoup de R&D !), nous avons concentr√© nos forces √† d√©ployer l'Intelligence Artificielle √† grande √©chelle au sein d'organisations publiques et priv√©es en France et en Europe.\nMais pas n'importe comment ! Nous croyons en une IA √©thique, responsable, au service des salari√©s et des citoyens europ√©ens. Nous militons pour la souverainet√© des donn√©es et l'ind√©pendance des entreprises europ√©ennes.\nPragmatiques et rationnels, nous d√©ployons quotidiennement nos solutions ¬´ pr√™t-IA-porter ¬ª √† un niveau industriel. Nous faisons aussi de la haute couture en d√©veloppant des solutions IA sur-mesure pour r√©pondre aux d√©fis de certains de nos clients. Notre R&D bout sans rel√¢che pour inventer, tester et d√©ployer l'IA de demain.\nEn d'autres termes, dans la boutique de La Javaness, tu trouveras : Conseil data & IA, acc√©l√©ration par le design, d√©veloppement front & back de pointe, d√©fis business dans un joyeux mix exigeant d'intelligences. Avec ce super cocktail d'expertises et de cr√©ativit√©, nous intervenons sur tous les secteurs d'activit√© pour cracker les probl√®mes de nos clients !\nNous sommes le partenaire Data et IA de r√©f√©rence pour l'AMF, LCL, la Banque de France ou encore P√¥le Emploi. Nous acc√©l√©rons √©galement des projets d'innovation digitale pour la Soci√©t√© G√©n√©rale, Facebook, Enedis, Saint Gobain, Louvre H√¥tels Group...\nComment √ßa marche au quotidien ?\nNos expertises Design, IT, Data, Delivery & Business, travaillent ensemble sur tous les projets afin de concevoir et d√©ployer des solutions compl√®tes et innovantes r√©pondant aux besoins de nos clients.\nFort d'un collectif unique, la Javaness investit sans cesse dans des talents pointus, atypiques et compl√©mentaires qui lui conf√®rent une force de frappe hors norme. Et parce qu'on est pas que des machines, la \"Fullstackerie\" s'exprime aussi joyeusement lors de nos fameux ap√©ros au d√©bott√© et de notre s√©minaire annuel.\nSi √ßa te semble une aventure √† ta mesure, c'est par ici pour nous rejoindre !\nDescriptif du poste:\nVos missions:\nAnalyser les √©tapes du cycle de vie des donn√©es manipul√©es par les processus m√©tier de nos clients\nConcevoir, ou transformer apr√®s analyse pr√©liminaire, les processus et outillages technologiques qui sous-tendent les processus m√©tier, en fonction des besoins et contraintes m√©tier et techniques\nCommuniquer les d√©cisions d'architecture aux √©quipes\nParticiper √† l'√©laboration du r√©f√©rentiel de technologies, outils, proc√©dures, normes, vocabulaire, s√©curit√© des syst√®mes d'information\nParticiper √† l'effort de veille technologique\nParticiper aux phases d'avant-vente par des √©tudes de faisabilit√© et d'impact, d'architecture, de choix technologiques et d'estimations de charges\nEtre en support de la phase de delivery des projets\nCollaborer avec les autres comp√©tences Data science, D√©veloppeurs, Op√©rations, UX/UI, PM/PO, Business, de La Javaness\nParticiper au d√©veloppement de La Javaness via le recrutement, la structuration et animation interne, le networking, l'√©v√©nementiel, ..\nRequirements\nVous poss√©dez une solide exp√©rience:\nde l'appr√©hension du cycle de vie de la donn√©e et des processus m√©tier associ√©s,\nde l'√©laboration d'architectures de donn√©es et de l'industrialisation de solutions de data management par leur int√©gration dans un SI complexe et s√©curis√©,\ndes technologies de data management et data engineering (ETL/ELT, DQM, portail de donn√©es, data preparation, data virtualization, data catalog, data lineage, BI),\ndes architectures de donn√©es et de leurs syst√®mes de gestion (Datawarehouse, Data Lake),\ndes exigences que font peser les architectures de donn√©es sur les infrastructures syst√®me et r√©seau\nde data science et machine learning (frameworks, librairies),\nde veille technologique. Vous √™tes p√©dagogue, avez un bon relationnel et surtout, un esprit entrepreneurial !\nVous pouvez justifier d'expeÃÅriences significatives (7 - 10 ans) dans ce type de poste, et en particulier en gestion de projets et accompagnements de solutions Big Data et IA.\nAnglais requis.\nBenefits\nAmbition et innovation\nPackage attractif : compl√©mentaire sant√©, prime d√©jeuner 98‚Ç¨/mois, Navigo 100%, 25 jours de cong√©s pay√©s par an, RTT\nParis Bonne Nouvelle\nShow more\nShow less",
        "details": {
            "JobDetail": [
                "Full"
            ],
            "TypeContract": "",
            "Salary": "98",
            "Level": "",
            "Experience": "5 an(s)"
        },
        "title": "data architect",
        "skills": {
            "ProgLanguage": [
                "R"
            ],
            "DataAnalytics": [
                "R"
            ],
            "Other": [
                "Machine Learning",
                "Big Data"
            ]
        }
    },
    {
        "source": "LinkedIn",
        "company": "Ippon Technologies",
        "location": "Paris, √éle-de-France, France",
        "link": "https://fr.linkedin.com/jobs/view/architecte-data-at-ippon-technologies-3851530940?position=3&pageNum=0&refId=a5rwPua%2FMvx%2F2M%2FPSF0oPA%3D%3D&trackingId=WUE05ZbK1%2BRSQiee2Y2X%2BA%3D%3D&trk=public_jobs_jserp-result_search-card",
        "description": "Ippon : cabinet de conseil et d'expertise en technologie, international et ind√©pendant.\nVous int√©grerez notre communaut√© data\n, compos√©e d‚Äôune √©quipe de\n70 experts sur 9 agences en France.\nNotre sp√©cialit√© est de\nconstruire des data platforms dans le cloud public avec les meilleures technos du moment.\nLa data chez Ippon, c‚Äôest d√©j√† plus de\n250 certifications AWS, GCP et AZURE,\ndes\nspeakers √† l‚ÄôAWS Summit, des partenariats avec Snowflake, Databricks, DBT, un blog technique\navec des publications r√©guli√®res.\nDescriptif du poste :\nCe poste est un vrai challenge aussi bien en termes de\nd√©fis techniques que de gestion d‚Äô√©quipe.\nLa r√©ussite de vos projets sera port√©e par votre capacit√© √† vous adapter et √† monopoliser un large panel de comp√©tences techniques.\nVous devrez √™tre le/la leader de votre √©quipe en gardant √† l‚Äôesprit l‚Äôensemble des\nbonnes pratiques d'architectes\n, de s√©curit√© et d‚Äôautomatisation n√©cessaires √† la r√©ussite du projet.\nEn tant que\nrepr√©sentant(e) de l‚Äôengagement d‚ÄôIppon\nsur les sujets qui vous seront confi√©s, vous serez amen√©(e) √†\ntravailler avec notre √©quipe commerciale\nd√®s les phases de qualification\net lors de la validation de jalons de la roadmap que vous aurez pr√©alablement valid√© avec le client. Vous interviendrez √©galement dans la s√©lection de l‚Äô√©quipe qui sera affect√©e √† votre projet.\nVotre r√¥le :\nGr√¢ce √† votre position d‚Äôarchitecte vous avez une vision experte et syst√©mique de l‚Äôensemble des composants d‚Äôune Modern Data Platform.\nVous ma√Ætrisez le panel des exigences fonctionnelles et non fonctionnelles √† collecter afin d‚Äôassurer l‚Äôefficience op√©rationnelle et la p√©rennit√© de la data platform.\nVous √™tes expert(e) et ma√Ætrisez tous les outils et services d‚Äôau moins un √©cosyst√®me parmi les 3 principaux leaders du march√© (AWS, Azure et GCP) et avez des facilit√©s pour √©tendre votre champ de comp√©tences.\nVous √™tes proactif/ve sur la veille technique et la capitalisation et veillez √† garder toujours un temps d‚Äôavance sur l‚Äô√©tat de l‚Äôart du secteur afin de pouvoir guider vos clients.\nEn tant qu‚Äôarchitecte exp√©riment√©(e) vous pouvez indiff√©remment intervenir sur des missions de delivery pour concevoir la solution cible ou en phase de cadrage amont pour guider les choix et construire les roadmaps.\nVous √™tes p√©dagogue et savez communiquer et vulgariser des r√©flexions complexes pour les rendre accessibles √† tous.\nNotre √©co-syst√®me technique :\nCloud : AWS, GCP, Azure\nLangage de programmation data : Python, SQL, Scala\nApproche Data Warehouse : Redshift, Snowflake, BigQuery\nApproche Data Lakehouse : Databricks, Starburst, Glue-Athena-S3\nIngestion : AWS Glue, Airbyte, dbt\nStockage : AWS S3, Google Cloud Storage, Azure Blob Storage\nOrchestration : Airflow, AWS Step function\nGouvernance : cataloging, s√©curit√©, scope d'acc√®s\nBatch et Streaming : Kafka, Amazon Kinesis, Google DataFlow\nOutil de visualisation : Tableau, Power BI, Metabase, Superset\nVotre √©volution chez Ippon :\nVous serez accompagn√©(e) dans votre mont√©e en comp√©tences aussi bien technique que leadership gr√¢ce √†\nnotre programme BlackBelt\n(programme de formation continue : mentoring, formations, certifications).\nEn tant que membre d‚Äôune communaut√©,\nvous pouvez avoir diff√©rents r√¥les :\nCelui de manager technique (MT) : manager d‚Äôune √©quipe de 7 ing√©nieur(e)s Ippon (onboarding, suivis, accompagnement, mise en place d‚Äôobjectifs‚Ä¶). Vous conduirez les entretiens techniques en bin√¥me\nResponsable de l‚Äôaccomplissement d‚Äôune ou plusieurs actions strat√©giques de la Core Team Data\nDevenir speaker lors de Meetup, Summit, Talks internes, aupr√®s des √©coles ‚Ä¶\nDevenir formateur(trice) et accompagner la nouvelle g√©n√©ration d‚ÄôIppon dans leur mont√©e en comp√©tences\nVous avez d‚Äôautres souhaits, pas de soucis, nous en discuterons durant notre √©change et r√©pondrons √† toutes vos questions.\nPr√©sentiel ou t√©l√©-travail ?\nLes deux !\nLa plupart de nos clients sont en hybride et notre politique de t√©l√©travail est classique : 3 jours pr√©sentiel / 2 jours TT.\nNotre processus de recrutement :\nUn call RH (20 min)\nPuis un entretien RH et Commerce pour que nous puissions √©changer sur ce que vous recherchez et ce que nous pouvons vous proposer (1h)\nEnfin, un entretien technique avec un r√©f√©rent technique (1h)\nSi vous √™tes int√©ress√©(e) mais que vous avez encore des questions, n'h√©sitez pas √† nous contacter sur LinkedIn\nSinon il ne vous reste plus qu‚Äô√† cliquer sur\nPostuler\nShow more\nShow less",
        "details": {
            "JobDetail": [
                "Hybride"
            ],
            "TypeContract": "",
            "Salary": "",
            "Level": "",
            "Experience": null
        },
        "title": "data architect",
        "skills": {
            "ProgLanguage": [
                "Scala",
                "Python"
            ],
            "DataBase": [
                "SQL"
            ],
            "BigData": [
                "Databricks"
            ],
            "DataVisualisation": [
                "Power BI",
                "Tableau"
            ],
            "CloudComputing": [
                "GCP",
                "AWS",
                "Azure"
            ],
            "DBMS": [
                "BigQuery",
                "Snowflake"
            ],
            "Automation": [
                "Airflow"
            ],
            "Other": [
                "Cloud"
            ],
            "EnSoftSkils": [
                "Leadership"
            ]
        }
    },
    {
        "source": "LinkedIn",
        "company": "MCA",
        "location": "Marseille, Provence-Alpes-C√¥te d'Azur, France",
        "link": "https://fr.linkedin.com/jobs/view/data-architect-at-mca-3907802841?position=4&pageNum=0&refId=a5rwPua%2FMvx%2F2M%2FPSF0oPA%3D%3D&trackingId=AqBqXAtI3a6pEmFBU%2Bm1cQ%3D%3D&trk=public_jobs_jserp-result_search-card",
        "description": "MCA est un Groupe de Conseil en Ing√©nierie et Hautes Technologies qui compte 1500 collaborateurs en France et √† l‚ÄôInternational.\nFort de nos 30 ans d‚Äôexp√©rience, nous accompagnons nos clients dans la r√©alisation de leurs projets.\nNous rejoindre, c'est int√©grer une entreprise dynamique qui a √† c≈ìur d‚Äôaccompagner ses collaborateurs.\nVous b√©n√©ficiez d'un suivi personnalis√© et r√©gulier ainsi que de nombreuses formations qui participeront √† votre mont√©e en comp√©tences.\nD√©tail projet :\nDate de d√©marrage :\nASAP\nExp√©rience n√©cessaire :\n6 - 9 ans\nLangue :\nfran√ßais et anglais\n(Niveau C1)\nContexte de la mission\n:\nNous cherchons un Data Architect qui aura la responsabilit√© compl√®te de l'architecture.\nNous recherchons une personne ayant une bonne compr√©hension globale des services disponibles d‚ÄôAzure Analytics.\nCette personne travaillera en collaboration avec plusieurs √©quipes Produits. Il aura en charge l‚Äôarchitecture des donn√©es, et viendra en soutien aux √©quipes dans l‚Äôint√©gralit√© du cycle de vie de la gestion des donn√©es.\nLe consultant devra par ailleurs avoir une exp√©rience op√©rationnelle afin d‚Äô√™tre en mesure de configurer diff√©rents environnements et services.\nIl/Elle devra faire preuve de leadership dans le but d'endosser le r√¥le de Leader Technique, et point d‚Äôentr√©e avec les parties prenantes de l‚Äôentreprise\nUsage quotidien de l‚Äôanglais comme langue de communication dans la fonction\nT√¢ches √† r√©aliser\n:\nVous assurez le leadership technique, participez au d√©veloppement, et repr√©sentez les ressources internes et externes de la plateforme\nVous serez un membre actif de l‚Äô√©quipe des architectes, afin de superviser le processus de gestion des donn√©es et fournir des conseils et orientations aux √©quipes de d√©veloppement\nVous serez responsable de la conception, et de la documentation de la solution dans votre domaine\nComp√©tences recherch√©es :\nObligatoires\n:\nExp√©rience dans le d√©veloppement, la documentation et la maintenance de mod√®les de donn√©es logiques et physiques\nExp√©rience sur Databricks, ADLS storage, SQL DB, ADF et Power BI\nExp√©rience dans la d√©finition et la ma√Ætrise d'une architecture de donn√©es √©volutive de bout en bout, en tenant compte de l'architecture de l'entreprise et des normes industrielles.\nParticipation √† l'√©laboration d'architectures, strat√©gies et politiques en mati√®re de donn√©es, y compris la s√©curit√© des donn√©es\nLangage SQL Writing et mod√©lisation de donn√©es\nData Architecture\nPower BI\nAzure ADFv2, Databricks, Synapse, Delta Lake\nEnvironnement et technologie Azure Advanced Analytics\nPython, Pyspark\nMicrosoft cloud bas√© sur mod√®le Delivery\nData Management, Data Governance et Data Quality\nD√©ploiement d‚ÄôAPIs et micro-services\nDevSecOps\nAgile\nExp√©rience professionnelle dans un environnement international\nOptionnelles :\nExp√©rience dans le secteur automobile\nVos perspectives d‚Äô√©volution :\nNotre objectif premier est de vous donner toutes les cl√©s pour r√©ussir et ainsi acc√©der aux diff√©rentes √©volutions que nous proposons.\n√Ä terme, vous pourrez √©voluer sur d'autres secteurs d'activit√©s, mais aussi vous projeter en interne sur des postes en France ou √† l'international.\nCe poste est ouvert aux personnes en situation de handicap.\nShow more\nShow less",
        "details": {
            "JobDetail": [],
            "TypeContract": "",
            "Salary": "",
            "Level": "",
            "Experience": "30 an(s)"
        },
        "title": "data architect",
        "skills": {
            "ProgLanguage": [
                "Python"
            ],
            "DataBase": [
                "SQL"
            ],
            "BigData": [
                "Databricks"
            ],
            "DataVisualisation": [
                "Power BI"
            ],
            "CloudComputing": [
                "Azure"
            ],
            "Other": [
                "Cloud"
            ],
            "EnSoftSkils": [
                "Leadership",
                "Communication",
                "Collaboration"
            ]
        }
    },
    {
        "source": "LinkedIn",
        "company": "CEVA Logistics",
        "location": "Marseille, Provence-Alpes-C√¥te d'Azur, France",
        "link": "https://fr.linkedin.com/jobs/view/senior-data-architect-at-ceva-logistics-3919628481?position=5&pageNum=0&refId=a5rwPua%2FMvx%2F2M%2FPSF0oPA%3D%3D&trackingId=0HGOhEn7s5L%2BPwRgFdatBw%3D%3D&trk=public_jobs_jserp-result_search-card",
        "description": "DATA FACTORY MANAGER / SENIOR DATA ARCHITECT\nBased in France (Marseille or Puteaux).\nWHAT ARE YOU GOING TO DO?\nThe Senior Data Architect will join the Global IT Data and Digital organization at CEVA Logistics within the Global CIO organization and will report to the Head of the CEVA Global Data Factory.\nThis role operates in complex decision-making environments impacting the CEVA enterprise, works with senior management from IT, BD and Operations to ensure the best possible global solutions are available for our customers and CEVA employees alike.\nThe data architect will operate in the context of the set of the new Cloud Data Platform of CEVA and will contribute to its set up, development and growth and built up of the internal teams and resources of data architects and data analysts.\nMain Responsabilities:\n¬∑ Developing and implementing an overall organizational data strategy in line with business processes. The strategy includes data model designs, database development standards, implementation and management of data warehouses and data analytics systems.\n¬∑ Identifying data sources, both internal and external, and working out a plan for data management that is aligned with organizational data strategy.\n¬∑ Coordinating and collaborating with cross-functional teams, stakeholders, and vendors for the smooth functioning of the enterprise data system.\n¬∑ Managing end-to-end data architecture, from selecting the platform, designing the technical architecture, and developing the application to finally testing and implementing the proposed solution.\n¬∑ Planning and execution of big data solutions using appropriate technologies and ensure their full lifecycle and interoperability.\n¬∑ Defining and managing the flow of data and dissemination of information within the organization.\n¬∑ Integrating technical functionality, ensuring data accessibility, accuracy, and security.\n¬∑ Conducting a continuous audit of data management system performance, refine whenever required, and report immediately any breach or loopholes to the stakeholders.\nWHAT ARE WE LOOKING FOR?\nMaster's degree in computer science or equivalent work experience\nMinimum of 10 years of experience in IT systems design or development.\nMinimum 5 years of experience gained in data architecture and delivering large scale analytics data platforms environments.\nKnowledge of systems development, including system development life cycle, project management approaches and requirements, design and testing techniques\nProven experience in design and building data models, data domains and understanding business data products (proficiency in data modeling and design, including SQL development and database administration).\nUnderstanding of predictive modeling, AI models and technologies, Data mining, visualization and Machine Learning\nAbility to implement common data management and reporting technologies, as well as the basics of columnar and NoSQL databases, data visualization, unstructured data, and predictive analytics.\nStrong and broad knowledge of latest technology stacks and trends, cloud-based data platforms and data lakes (preferably AWS and Snowflake technologies)\nExperience with data integration methods and technologies (e.g., ETL, Data Virtualization, Master Data Management, Data Warehouse/Lakehouse).\nUnderstanding of business strategy and ability to deliver recommendations in sync with key objectives and experience in developing and driving IT roadmaps.\nCapacity to coordinate and collaborate with users, system designers, and developers in their day-to-day functions. As such, soft skills like effective communication, team management, problem-solving, and leadership are highly desirable.\nStrong analytical skills and business acumen, ideally in the logistics sector.\nFluent English and proven practice.\nWHAT DO WE HAVE TO OFFER?\nPermanent contract.\nHybrid work: 4 days at the office and 1 remote.\nCompetitive salary.\nYou will work for one of the world 's leading logistics operators that will help you in your career development by offering you multiple opportunities.\nYou will receive on the job training that help you to better understand operational processes.\nABOUT TOMORROW\nWe offer professional opportunities for you to develop in CEVA. We value your professional and personal growth.\nJoin CEVA for a challenging carrer.\nCEVA Iberia is committed to attracting, acquiring and retaining the best possible candidates in an equitable and inclusive manner that is consistent with labor laws and best practices.\n#LI-SP1\nShow more\nShow less",
        "details": {
            "JobDetail": [
                "Remote",
                "Full",
                "Senior"
            ],
            "TypeContract": "",
            "Salary": "Salary",
            "Level": "",
            "Experience": null
        },
        "title": "data architect",
        "skills": {
            "DataBase": [
                "SQL",
                "NoSQL"
            ],
            "CloudComputing": [
                "AWS"
            ],
            "DBMS": [
                "Snowflake"
            ],
            "Collaboration": [
                "Teams"
            ],
            "Other": [
                "Machine Learning",
                "Cloud",
                "Big Data"
            ],
            "EnSoftSkils": [
                "Leadership",
                "Communication",
                "Organization"
            ]
        }
    },
    {
        "source": "LinkedIn",
        "company": "Airswift",
        "location": "Paris",
        "link": "https://fr.linkedin.com/jobs/view/solutions-architect-at-airswift-3919714188?position=6&pageNum=0&refId=a5rwPua%2FMvx%2F2M%2FPSF0oPA%3D%3D&trackingId=b3MGM2D190q9EWNC%2FP5I3A%3D%3D&trk=public_jobs_jserp-result_search-card",
        "description": "üöÄ\nNow Hiring: Data-Cloud Solution Architect - FREELANCE\nüìç Location: On-site near Paris (3 days a week)\nAre you ready to join a cutting-edge Data Transformation initiative? We are seeking a talented\nData-Cloud Solution Architect\nto play a pivotal role in shaping the future of our client's data capabilities. This role offers an exciting opportunity to work on a complete set of data functionalities, from architecture and engineering to visualization and warehousing.\nRole & Responsibilities:\nProvide technical guidance and establish best practices for Snowflake account setup and configuration.\nManage Infrastructure-as-code and maximize automation.\nLead enhancements and deployments to support a fully federated Platform.\nAct as a Subject Matter Expert (SME) for all Snowflake-related queries.\nOwn platform-specific Snowflake documentation, including decisions and best practices.\nDesign the cloud environment holistically to meet all functional and non-functional requirements.\nExecute deployment, maintenance, monitoring, and management tasks.\nOversee cloud security for the account.\nComplete the integration of new applications into the cloud environment.\nRequirements:\nHigher education completed, preferably with a degree in Computer Sciences.\n5 to 10 years of experience in implementing Data Platforms in a cloud environment.\nFluent in French & English (must).\nDeep expertise in Snowflake.\nStrong skills in platform architecture, DBA, and cloud database administration.\nProficiency in AWS Architecture and cloud networking.\nExcellent communication, coordination, and collaboration skills.\nAbility to manage stakeholders, mitigate risks, and demonstrate leadership.\nOpen-mindedness and willingness to take on challenges.\nHighly motivated, adaptable, and flexible.\nThis is a contract position lasting until the end of 2024, with the possibility of extension. Join us in driving innovation and shaping the future of data! #DataArchitect #Snowflake #AWS #CloudComputing #ParisJobs #TechJobs\nShow more\nShow less",
        "details": {
            "JobDetail": [
                "Full"
            ],
            "TypeContract": "",
            "Salary": "",
            "Level": "",
            "Experience": null
        },
        "title": "data architect",
        "skills": {
            "CloudComputing": [
                "AWS"
            ],
            "DBMS": [
                "Snowflake"
            ],
            "Other": [
                "Cloud"
            ],
            "EnSoftSkils": [
                "Initiative",
                "Leadership",
                "Communication",
                "Collaboration"
            ]
        }
    },
    {
        "source": "LinkedIn",
        "company": "Micropole",
        "location": "Levallois-Perret, √éle-de-France, France",
        "link": "https://fr.linkedin.com/jobs/view/data-architect-f-h-at-micropole-3652819338?position=7&pageNum=0&refId=a5rwPua%2FMvx%2F2M%2FPSF0oPA%3D%3D&trackingId=yzPwOD7STCK0AuX%2BJ6fjKg%3D%3D&trk=public_jobs_jserp-result_search-card",
        "description": "Rejoignez le Groupe Micropole. Devenez un #InnovativePeople !\nMission\nEn R√©sum√©\nLocalit√© : Levallois-Perret\nType de contrat : CDI\nNiveau d‚Äôexp√©rience : au moins 7 ans\nAccord de t√©l√©travail & Flex office\nVous √™tes\npassionn√©(e) par la data\n? Vous √™tes convaincus que l‚Äôoptimisation du\npatrimoine data des entreprises\nest la cl√© de leur performance ? Vous voulez\nrendre les entreprises data intelligentes\net les aider √† se transformer pour pr√©parer d√®s √† pr√©sent leur futur ?\nVous souhaitez rejoindre un groupe pionnier des grandes innovations data et digitales ?\nSi vous avez\nr√©pondu ¬´‚ÄØOui‚ÄØ¬ª\n√† chacune de ces questions alors devenez Data Architect pour l‚Äôun de\nnos clients grands-comptes.\nPr√™t(e) √† rejoindre l‚Äôaventure Micropole ? N‚Äôattendez plus !\nAu sein de Micropole, nous vous proposons de rejoindre notre practice ¬´ Data Governance et Architecture ¬ª, compos√©e de 80 #InnovativePeople et reconnue comme leader europ√©en de la Gouvernance des donn√©es.\nEn Tant Qu' Architect\nLes donn√©es en entreprise sont trop souvent organis√©es en silos ne laissant aux m√©tiers qu'une vision parcellaire de l'information.\nAfin d'amener une plus grande valeur et de l'efficacit√© au niveau des processus op√©rationnels et d√©cisionnels de l'entreprise, nous accompagnons nos clients dans la gouvernance de leurs donn√©es en les hi√©rarchisant au sein du syst√®me d'information. Nous abordons ainsi, le cycle de vie de la donn√©e produit depuis la R&D jusqu'au Digital.\nAu sein de Micropole, nous vous proposons de rejoindre notre practice ¬´ Data Gouvernance et Architecture ¬ª bas√©e √† Levallois-Perret, compos√©e de 80 #InnovativePeople et reconnue comme leader europ√©en de la Gouvernance des donn√©es.\nDans Vos Missions Quotidiennes, Vous √ätes Amen√©(e)s √†\n√ätre l‚Äôinterface entre le client et l‚Äô√©quipe projet :\nPrise en compte des enjeux m√©tier afin d‚Äôaligner l‚Äôarchitecture sur la strat√©gie de l‚Äôentreprise notamment vis-√†-vis de la transformation digitale des entreprises et des enjeux r√©glementaires ;\nD√©finir la roadmap de mise en ≈ìuvre ;\nD√©finir les principes d‚Äôurbanisation autour des donn√©es ;\nCadrer les projets : r√©f√©rentiels (MDM), Data Hub, Big Data, gouvernance des donn√©es, √©change (ETL/ESB/IPaaS) ;\nAuditer les architectures existantes sur les axes qualit√©, et urbanisation des donn√©es ;\nAnimer les workshops de conception dans le cadre de projets d‚Äôimpl√©mentation ;\nAccompagner sur les phases de cadrage √† la d√©finition des mod√®les de donn√©es et des processus de gouvernance op√©rationnelle ;\nR√©aliser la conception technique et fonctionnelle des interfaces d‚Äô√©change.\nParticiper activement aux avant-ventes et d√©marche de validation de concepts :\nParticipation aux phases de r√©ponses √† appel d‚Äôoffre ;\nParticipation sur la production de d√©monstrateur en lien avec nos partenaires √©diteurs ;\nAnimation de s√©minaires d‚Äôacculturation √† la data.\nProfil\nVos Comp√©tences Techniques\nVous maitrisez au moins une solution du march√© li√©e √† la gouvernance des donn√©es (MDM, Data Catalogue, DQM, Data Fabric, IPaaS, ETL/ESB).\nVos Atouts\nVous avez au moins 7 ans d‚Äôexp√©rience professionnelle sur la d√©finition d‚Äôarchitecture data ;\nVous ma√Ætrisez les concepts de la gouvernance des donn√©es, et disposez d‚Äôune d‚Äôexp√©rience projet sur une des solutions leaders du march√© ;\nV√©ritable co√©quipier(e), vous avez √† c≈ìur de contribuer √† la mont√©e en comp√©tence de votre √©quipe ;\nVous disposez d‚Äôun bon niveau de fran√ßais et d‚Äôanglais, √† l‚Äôoral comme √† l‚Äô√©crit.\nLa Vie Chez Micropole, C‚Äôest\nUne vie interne rythm√©e pour se familiariser √† la culture d‚Äôentreprise et aux valeurs de Micropole ;\nDes √©v√®nements internes r√©guliers pour partager les connaissances aussi bien techniques que fonctionnelles ;\nUne politique de formation attractive et √©clectique ;\nUn travail en √©quipe valoris√© pour une meilleure coh√©sion ;\nLa participation √† des projets internes sur la base du volontariat.\nDevenir #INNOVATIVEPEOPLE, c‚Äôest :\nInt√©grer une communaut√© de 1100 experts passionn√©s r√©partis entre la France, la Belgique, le Luxembourg, la Suisse, l‚ÄôEspagne et la Chine ;\nConstruire ensemble les solutions strat√©giques et innovantes de demain pour accompagner nos clients dans leur transformation data et digitale ;\nParticiper au d√©veloppement de nos 4 centres d‚Äôexcellences cloud : AWS, Microsoft Azure, Salesforce, GCP ;\nEvoluer continuellement au travers de formations et de certifications sur les plus grandes technologies gr√¢ce √† Micropole Campus ;\nS‚Äôassurer d‚Äôune innovation continue gr√¢ce √† : notre √©cosyst√®me de partenaires technologiques ; notre acc√©l√©rateur de start‚Äôup databoost‚ÄôR ; nos lieux d‚Äôinnovations ¬´ innovativeSpaces ¬ª et de co-construction avec les clients ; notre management par les talents naturels.\nProcessus De Recrutement\nChez Micropole, le processus de recrutement est r√©actif et transparent.\nEtape 1 ‚Äì Si votre profil correspond √† nos besoins, vous √™tes recontact√©s dans les 72 heures qui suivent votre candidature par Victoria notre Talent Business Partner d√©di√©e √† Data Gouvernance & Architecture pour une qualification t√©l√©phonique ainsi qu'un premier entretien en visio ;\nEtape 2 ‚Äì Vous rencontrez un manager avec l‚Äôun de nos experts comme Aur√©lien, R√©gis ou Jofrey.\nEn fonction du poste, vous pouvez passer des √©tapes suppl√©mentaires (entretien ou test technique).\n√Ä PROPOS DU GROUPE MICROPOLE\nGroupe international de conseil et technologies innovantes, MICROPOLE est sp√©cialis√© dans les domaines de la Data & Digital. Depuis ses 14 agences situ√©es en Europe et en Chine, les 1200 #INNOVATIVE PEOPLE du Groupe (consultants, Data scientists, architectes IT, experts m√©tiers, ing√©nieurs, UX designers‚Ä¶) accompagnent leurs clients partout dans le monde sur l'ensemble des phases de leurs projets, du conseil √† leur r√©alisation, et sur la conduite du changement.\nMICROPOLE r√©alise 35% de son chiffre d‚Äôaffaires √† l‚Äôinternational et est cot√© sur le march√© Eurolist compartiment C d‚ÄôEuronext Paris, segment Next Economy.\nPour en savoir plus : https://www.linkedin.com/company/micropole/\nInfos pratiques\nA 200m, le m√©tro Anatole France (Ligne 3) et un acc√®s √† l'ensemble des commerce du centre ville de Levallois-Perret √† moins de 2 min √† pied.\nMot du Manager\nFace √† des enjeux de compliance toujours plus exigeants et rigoureux, la gouvernance des donn√©es devient absolument indispensable pour garantir la coh√©rence, maitriser la qualit√© et la connaissance du socle des donn√©es des entreprises et assurer leur bonne mise en conformit√©.\nShow more\nShow less",
        "details": {
            "JobDetail": [],
            "TypeContract": "CDI",
            "Salary": "",
            "Level": "",
            "Experience": "7 an(s)"
        },
        "title": "data architect",
        "skills": {
            "ProgLanguage": [
                "R"
            ],
            "DataAnalytics": [
                "R"
            ],
            "CloudComputing": [
                "GCP",
                "AWS",
                "Azure"
            ],
            "Other": [
                "Cloud",
                "Big Data"
            ]
        }
    },
    {
        "source": "LinkedIn",
        "company": "AXA",
        "location": "Paris",
        "link": "https://fr.linkedin.com/jobs/view/enterprise-architect-digital-workplace-at-axa-3845642526?position=8&pageNum=0&refId=a5rwPua%2FMvx%2F2M%2FPSF0oPA%3D%3D&trackingId=1QxAWv6oNOBK0QHumiAgPA%3D%3D&trk=public_jobs_jserp-result_search-card",
        "description": "AXA GROUP OPERATIONS\nAXA is becoming a sustainable tech-led company and at AXA Group Operations we are one of the major catalysts for this transformation.\nWe set the tone by triggering and empowering the evolution of our insurance business model through technology and innovation, driving its concrete implementation globally at speed, with a high quality of advisory and execution.\nWe are present across 17 countries with committed, highly qualified teams. We leverage technology, data, sourcing, security and investment allocation in a global way, but also achieve economies of scale and synergies when necessary.\nAt\nAXA Group Operations\n, we want to be recognized in three fields of action:\nState-of-the-art Data Technology to drive customer experience\nState-of-the-art Procurement & Sourcing to drive efficiency and better manage risks\nHigh-Performing Global Team for stronger partnerships with AXA entities\nWorking as part the Group‚Äôs Technology Office, the\nDigital Workplace Entrerprise Architect,\nis responsible for providing architecture, vision, governance, problem anticipation and solving for IT on a transversal architectural level. This transversal scope of the architecture covers business, security, data, application and technology architecture.\nHe manages and coordinates, for his areas of responsibility ‚Äì here transversal Workplace topics ‚Äì , the work carried out by the other Architects cross-domains and Chief Architects / Chief Technology Officers from AXA Group Operations and AXA entities in close collaboration with GO departments for the global assets, with Group Security for the Security part, and with Business Partnership and the Markets/Entities for the entities related part.\nTransversal\nWorkplace topics\nscope will cover this non exhaustive list:\nDevice Management\nApplication delivery\nCollaboration & Productivity\nUX / QoS Monitoring\nWorkplace interaction with other domains (Security, IAM, Network, Cloud, Compliance‚Ä¶)\nThe\nDigital Workplace Entrerprise Architect\n's role is to\nsteer the Architecture evolution\nacross AXA to ensure the\nproper implementation\nof the IT Strategy and to be able to adopt new technologies and new market solutions in line with the business priorities, the foundations of the products structure and with the aim support AXA to become a Tech Led Company.\nThe individual in this position understands the Group business strategy, the Information Systems (IS) of the Group and anticipates future directions of the IT industry to relate them to future business needs and initiatives. The Lead Architect Expert produces\nkey architecture deliverables\n, leads international workgroups and studies to\nestablish IT directions\nfor the Group and is responsible for the architecture review of projects related to technologies in his domain of responsibility.\nMAIN MISSIONS :\nThe objective of architecture is to ensure that we build sustainable, robust and secured Information Systems at the right cost and that bring business value to support the corporate business and lines of business strategies.\nThe Digital Workplace Entrerprise Architect main activity is to craft the IT Strategy of the Group and act as a change agent to implement this IT Strategy through the Target Enterprise Architecture of the Group, and of individual countries within the Group. He may also be called upon to directly support PMs on some key projects.\nThe core activities of the Lead Architect Expert include the following for his own area of responsibility :\n1- Vision and Strategy\nSupport the definition and management of the company Technology vision, strategies and plans with focus on domains related to his role\n2- Contribute to Technology/Architecture CTO Community and Technology Governance of the Group:\nTo cover global and local dimensions, which includes ensuring design and solution choices made in the entities are conform to Group Strategy in order to secure Group interests over the long-term (Architecture boards‚Ä¶)\nTo share technological visions, opportunities, and risks company-wide, and in particular interact with senior business and IT executives\n3- Define, build and maintain architecture & design patterns, jointly with Product engineering teams aiming to minimize technical complexity and leverage convergence opportunities:\nArchitecture landscape\nArchitecture Model & Maturity\nArchitecture evolution and product design blueprints, HLD\nSupporting LLD delivery with Product teams\n4- Market Watch:\nParticipate to forums of leading companies (cross-industries) and vendors in order to use and/or influence technology evolutions\nIn particular, study industry trends and technologies in close collaboration with Group Data & Technology Innovation\nManage evaluation, development, and deployment of relevant technologies (technology lifecycle & roadmaps)\n5- Provide support to all Group IT supporting functions, in particular for Procurement and Finance for large negotiations or assets\nPROFILE\nExperience :\nStrong experience in IT Strategy, enterprise and solution architecture (10+ years)\nExperience on solutions architecture designs for very large projects/environments in particular in Workplace (both Device management and Collaboration)\nStrong change management skills with practical experience of transformation in an international environment\nFinancials (princiles, business cases, budgeting, business-planning, savings)\nStrives for excellence with deliverables of high quality and ability to work in sometimes tight planning\nDemonstrates to be a strong team member with an open and collaborative mind-set.\nSoft skills :\nThe person will have to interact and collaborate with multiple global and local stakeholders and different levels (peers, managers, experts, C-Levels‚Ä¶). To succeed in his role, this can be achieved through:\nLeadership ‚Äì Exhibits strong results orientation, change leadership, adaptability and the ability to drive collaborative behaviour.\nOpenness and reaching out ‚Äì Strong human relationship skills, exhibit curiosity and can see opportunities in situations, not just problems.\nCommunication skills ‚Äì Exhibits strong skills in listening, spoken and written communication, collaboration and the ability to work in a global team. Lead Architect Experts are expected to have the ability to understand and discuss with both senior managers and IT, and explain in clear language complicated architectural concepts and strategies.\nVision ‚Äì Lead Architecture Expert demonstrates architectural vision and beliefs and is able to express them clearly, champion them, and debate his point of view in on-line forums or in-person workshops.\nEmbracing of the new AXA values and new ways of working with courage to promote them against tradition\nOpenness to different opinions and creation of consensus\nProblem solving orientation and strong analytical, logical and interpretive ability to interpret scenarios, express concepts or models with several dimensions: architecture, business value, procurement, program approach ‚Ä¶\nHas a deep understanding of the organizational structures, in order to be in a position to better identify improvement points\nInternational profile ‚Äì A proven ability to work effectively in an international environment. In addition, exhibits a strong proficiency in English.\nTechnical skills :\nExpert knowledge in IT strategy focusing on Workplace Architecture with related infrastructure good practices\nExpertise in Workplace with critical thinking and decision making, information systems knowledge, innovation, knowledge of emerging technology, planning, risk management, systems thinking, application rationalization/TCO, IT Security and technical problem solving.\nGood expertise in the practice of Architecture (frameworks) to deliver a holistic view (architecture model)\nShow more\nShow less",
        "details": {
            "JobDetail": [
                "Senior"
            ],
            "TypeContract": "",
            "Salary": "",
            "Level": "",
            "Experience": null
        },
        "title": "data architect",
        "skills": {
            "Collaboration": [
                "Teams"
            ],
            "Other": [
                "Cloud"
            ],
            "EnSoftSkils": [
                "Leadership",
                "Collaboration",
                "Problem Solving",
                "Adaptability",
                "Communication",
                "Critical Thinking"
            ]
        }
    },
    {
        "source": "LinkedIn",
        "company": "VISEO",
        "location": "Boulogne-Billancourt, √éle-de-France, France",
        "link": "https://fr.linkedin.com/jobs/view/data-architect-cloud-f-h-at-viseo-3904217803?position=9&pageNum=0&refId=a5rwPua%2FMvx%2F2M%2FPSF0oPA%3D%3D&trackingId=267fBpZ5knn1TQJTgrSw8g%3D%3D&trk=public_jobs_jserp-result_search-card",
        "description": "Rejoignez\nVISEO\net explorez un univers de possibilit√©s o√π\nl'Humain\n, le\nCollectif\net le\nChallenge\nsont au c≈ìur de notre ADN.\nQui √™tes-vous ?\nSi pour vous √™tre\nArchitecte Cloud & Data\n, c'est :\nInt√©grer une √©quipe d'experts en solutions cloud et en gestion de donn√©es ;\nConcevoir et d√©ployer des architectures cloud scalables et s√©curis√©es sur Google Cloud Platform et/ou Azure ;\nMa√Ætriser les services GCP (BigQuery, Cloud Composer, Cloud Functions , Cloud Run) et/ou Azure (Synapse , Data Factory , ADLS , SQL Database)\nMaitriser les pratiques DevOps (CI/CD, monitoring, logging) ;\nMaitriser Python et ses biblioth√®ques data\nD√©couvrir et tester les nouvelles plateformes data (Exemple : Microsoft Fabric)\nOptimiser les co√ªts et les performances des solutions cloud pour garantir une efficacit√© maximale ;\nCollaborer avec les √©quipes de d√©veloppement pour int√©grer les meilleures pratiques de gestion des donn√©es et d'analytique...\nAlors, vous √™tes la personne que nous recherchons !\nSi vous avez une exp√©rience significative en\narchitecture cloud et data\net que vous √™tes pr√™t √† relever de nouveaux\nd√©fis\net √† enrichir votre parcours professionnel, c'est le moment id√©al pour nous rejoindre.\nCe que nous allons faire ensemble ?\nD√©couvrez comment votre quotidien sera r√©volutionn√© en int√©grant notre √©quipe bas√©e √† Paris. Vous pourrez :\n√ätre acteur dans la conception des solutions cloud et data, en apportant votre expertise technique ;\nAssurer la qualit√© et la s√©curit√© des infrastructures cloud (conformit√©, r√©silience, performance) ;\nPartager vos connaissances et innover au sein d'un collectif passionn√© par les technologies de pointe.\nCe que nous avons √† vous offrir ?\nDes formations avanc√©es, des certifications GCP et un accompagnement personnalis√© pour votre d√©veloppement professionnel ;\nUn cadre de travail dynamique, flexible et agile pour une carri√®re sans fronti√®res ;\nUn engagement profond pour l'environnement, la soci√©t√©, l'√©galit√© et l'inclusion ;\nUn accord t√©l√©travail pour une harmonie parfaite entre vie professionnelle et personnelle.\nCe qui nous diff√©rencie ?\nUne communaut√© active d'experts en cloud et data : des ateliers r√©guliers, la participation √† des conf√©rences sp√©cialis√©es ;\nDes dispositifs d'√©pargne salariale attractifs (PEE et PERECO) et l'opportunit√© de devenir actionnaire de VISEO ;\nUn partenariat √©troit avec Google & Microsoft, offrant un acc√®s privil√©gi√© aux derni√®res innovations et technologies cloud.\nEnvie de nous rejoindre ? Contactez-nous et adoptez le #VISEOspirit\nEn tant qu'employeur, VISEO s'engage en faveur de la diversit√© et de l'inclusion.\n√Ä propos de VISEO\nAvec 3 000 collaborateurs pr√©sents sur 5 continents, VISEO combine agilit√© et expertise pour transformer le num√©rique en un v√©ritable levier de comp√©titivit√© et de performance.\n#PositiveDigitalMakers\nGDPR MESSAGE:\nOur privacy policy has been updated to comply with the new regulations. We invite you to consult it by clicking here: https://www.viseo.com/fr/politique-de-confidentialite. The VISEO Group uses the data collected as part of your application to assess your suitability for the job in question. We use the Jazz HR tool to help us in our recruitment process. This tool complies with current regulations on the protection of personal data. The tool is hosted in the United States and is PrivacyShield certified for HR data. In all cases, we may keep your file for 5 years so that we can contact you again if another position matches your profile. You may, of course, object to this. To find out more about how your data is used and how you can exercise your rights, please consult our privacy policy https://www.viseo.com/fr/politique-de-confidentialite.\nShow more\nShow less",
        "details": {
            "JobDetail": [],
            "TypeContract": "",
            "Salary": "",
            "Level": "",
            "Experience": null
        },
        "title": "data architect",
        "skills": {
            "ProgLanguage": [
                "Python"
            ],
            "DataBase": [
                "SQL"
            ],
            "CloudComputing": [
                "GCP",
                "Google Cloud Platform",
                "Azure"
            ],
            "DBMS": [
                "BigQuery"
            ],
            "Other": [
                "Cloud",
                "DevOps",
                "CI/CD"
            ]
        }
    },
    {
        "source": "LinkedIn",
        "company": "PROXIAD",
        "location": "Lyon, Auvergne-Rh√¥ne-Alpes, France",
        "link": "https://fr.linkedin.com/jobs/view/data-architect-h-f-at-proxiad-3908705011?position=10&pageNum=0&refId=a5rwPua%2FMvx%2F2M%2FPSF0oPA%3D%3D&trackingId=5T%2Ftx9Gs0LAlbOyht9BGDw%3D%3D&trk=public_jobs_jserp-result_search-card",
        "description": "Dans le cadre de notre d√©veloppement, nous recrutons pour int√©grer notre √©quipe sur Lyon (69) :\nData Architect (H/F)\nVos missions, si vous les acceptez :\nVous assurez le leadership technique, participez au d√©veloppement, et repr√©sentez les ressources internes et externes de la plateforme\nVous serez un membre actif de l‚Äô√©quipe des architectes, afin de superviser le processus de gestion des donn√©es et fournir des conseils et orientations aux √©quipes de d√©veloppement\nVous serez responsable de la conception, et de la documentation de la solution dans votre domaine\nVous aurez la responsabilit√© compl√®te de l‚Äôarchitecture\nVous serez support aux √©quipes techniques dans l‚Äôint√©gralit√© du cycle de vie de la gestion des donn√©es.\nEnvironnement Technique :\nExp√©rience dans le d√©veloppement, la documentation et la maintenance de mod√®les de donn√©es logiques et physiques\nExp√©rience sur Databricks, ADLS storage, SQL DB, ADF et Power BI\nExp√©rience dans la d√©finition et la ma√Ætrise d'une architecture de donn√©es √©volutive de bout en bout, en tenant compte de l'architecture de l'entreprise et des normes industrielles.\nParticipation √† l'√©laboration d'architectures, strat√©gies et politiques en mati√®re de donn√©es, y compris la s√©curit√© des donn√©es\nLangage SQL Writing et mod√©lisation de donn√©es\nData Architecture\nPower BI\nAzure ADFv2, Databricks, Synapse, Delta Lake\nEnvironnement et technologie Azure Advanced Analytics\nPython, Pyspark\nMicrosoft cloud bas√© sur mod√®le Delivery\nData Management, Data Governance et Data Quality\nD√©ploiement d‚ÄôAPIs et micro-services\nDevSecOps\nAgile\nExp√©rience professionnelle dans un environnement international\nLe profil que nous recherchons :\nDe formation informatique, vous poss√©dez une exp√©rience significative d‚Äôau moins 4 ans minimum en tant que Data Architect.\nVous avez le sens de l‚Äô√©coute, une bonne gestion des priorit√©s, vous avez un bon relationnel et de la rigueur.\nVous disposez d‚Äôune excellente communication.\nVous vous reconnaissez dans cette description ? Echangeons !\nPourquoi nous rejoindre ?\nL‚Äôinnovation, la qualit√© et l‚Äôagilit√© sont au c≈ìur du d√©veloppement de nos activit√©s IT, encadr√©es et assur√©es par nos 850 collaborateurs et collaboratrices fran√ßais(es) et bulgares !\nNotre savoir-faire ?\nConseil, D√©veloppement, Analyse et Expertise Informatique pour accompagner nos clients dans l'√©volution et la transformation de leur SI.\nEn plus de notre ma√Ætrise des technologies PHP, JavaEE et .Net qui sont des composantes fortes de notre savoir-faire, nous mettons en avant une expertise d√©di√©e aux applications mobiles et XNet (Inter, Intra et Extranet) et au d√©veloppement de notre offre infrastructure (syst√®mes, r√©seaux, cybers√©curit√©‚Ä¶).\nNos valeurs ?\nL‚Äôengagement, le pragmatisme, la proximit√©, l‚Äô√©volution et le partage. Aussi bien avec nos clients qu‚Äôavec nos collaborateurs (F/H).\nR√©sultats ?\nUne entreprise en pleine croissance avec des collaborateurs (F/H) √©panouis et reconnus au quotidien ! Des clients fid√®les et reconnaissants de la qualit√© des prestations fournies !\nNos collaborateurs ≈ìuvrent chaque jour √† satisfaire et concr√©tiser les id√©es les plus folles et innovantes de nos clients !... N‚Äôattendez plus et tentez l‚Äôexp√©rience PROXIAD !\nToutes les demandes seront trait√©es avec la plus stricte confidentialit√©. Seuls les candidats retenus seront contact√©s.\nShow more\nShow less",
        "details": {
            "JobDetail": [],
            "TypeContract": "",
            "Salary": "",
            "Level": "",
            "Experience": "4 an(s)"
        },
        "title": "data architect",
        "skills": {
            "ProgLanguage": [
                "Python"
            ],
            "DataBase": [
                "SQL"
            ],
            "BigData": [
                "Databricks"
            ],
            "DataVisualisation": [
                "Power BI"
            ],
            "CloudComputing": [
                "Azure"
            ],
            "Other": [
                "Cloud"
            ],
            "EnSoftSkils": [
                "Leadership",
                "Communication"
            ]
        }
    },
    {
        "source": "LinkedIn",
        "company": "Coders Connect",
        "location": "Paris, √éle-de-France, France",
        "link": "https://fr.linkedin.com/jobs/view/solutions-architect-digital-data-at-coders-connect-3889484245?position=11&pageNum=0&refId=a5rwPua%2FMvx%2F2M%2FPSF0oPA%3D%3D&trackingId=wYBT2jbq5kAyS9RkDIEUCw%3D%3D&trk=public_jobs_jserp-result_search-card",
        "description": "Coders Connect\nand\nSanofi\nare joining forces to bring an electrifying twist to the biopharmaceutical world!\nWork with a rhythm that suits your style (2 days remote and 3 days onsite magic).\nLanguage:\nProficiency in English is required for this role to ensure effective communication within our diverse, global team.\nAbout Sanofi:\nWe're not just a company; we're a global movement, focused on human health and making a real difference. Our mission? To battle pain, ease suffering, and sprinkle a little bit of magic in the process by developing life-changing medicines and vaccines through breakthrough science and wizard-level technology.\nDigital & Data: The Pulse of Our Mission\nAt the heart of our quest lies our digital and data powerhouse. Think of us as the digital healthcare platform of your dreams, where innovation meets speed, and technology shakes hands with medicine. With our scale, deep-rooted connections in health ecosystems worldwide, and a knack for pushing boundaries, we're here to revolutionize medicine, one digital solution at a time.\nYour Mission as a Solution Architect:\n‚Äã\nAs our Solution Architect, you're the master planner of our digital architecture, crafting scalable and sustainable solutions that power advanced analytics, AI, and ML initiatives. You'll design the blueprint for our data platforms and technology stacks, ensuring they align with our strategic goals and adhere to the highest standards of quality and innovation.\nRequirements\nCloud Mastery:\nDeep expertise in cloud-based services, particularly AWS managed services, to architect scalable and resilient solutions.\nAgile and DevOps:\nA solid foundation in Agile development processes and DevOps principles, including proficiency with GIT (GitHub), CI/CD practices (GitHub Actions), and Infrastructure as Code (Terraform).\nTech Stack Expertise\n: Hands-on experience with Linux, containers (Kubernetes), serverless architectures, and programming skills in JavaScript, Node.js, React, and Flutter.\nData Engineering:\nKnowledge of SQL, relational databases (AWS RDS), and familiarity with data warehousing solutions like Snowflake and AWS Redshift. Integration Services experience (Informatica Cloud, Airflow) is a significant plus.\nMessaging and Integration:\nCompetency in messaging solutions (EventBridge, SNS, SQS, Rabbit MQ, Kafka) to ensure seamless data flow and integration across systems.\nCompliance and Security:\nAwareness of compliance and cybersecurity requirements in the healthcare industry, with experience in navigating quality, regulatory data privacy (GxP, SOX) standards.\nCertifications:\nRelevant cloud certifications (AWS, Azure, Snowflake) are highly regarded, reflecting a commitment to staying at the forefront of technology.\nThe Reward:\nA chance to play a crucial role in a collaboration that's redefining healthcare through digital transformation.\nA seat at the round table of diversity and inclusion, where different backgrounds and experiences conjure the richness of our culture.\nAn endless horizon of professional growth, learning opportunities, and the chance to contribute to a future where better health is a global reality.\nThe Call to Adventure:\nIf you're ready to join a quest for better ‚Äì better treatments, better outcomes, and better science ‚Äì and believe in the magic of bringing diverse talents together to make miracles happen, we want you. Let's embark on this journey together and transform the future of healthcare.\nBetter is out there. Are you ready to find it with us?\nShow more\nShow less",
        "details": {
            "JobDetail": [
                "Remote"
            ],
            "TypeContract": "",
            "Salary": "",
            "Level": "",
            "Experience": null
        },
        "title": "data architect",
        "skills": {
            "DataBase": [
                "SQL"
            ],
            "CloudComputing": [
                "AWS",
                "Azure"
            ],
            "DevTools": [
                "Git"
            ],
            "OS": [
                "Linux"
            ],
            "DBMS": [
                "Snowflake"
            ],
            "Automation": [
                "Airflow",
                "Kubernetes"
            ],
            "InfrastructureAsCode": [
                "Terraform"
            ],
            "Containers": [
                "Kubernetes"
            ],
            "Other": [
                "ML",
                "Cloud",
                "DevOps",
                "CI/CD"
            ],
            "EnSoftSkils": [
                "Communication",
                "Collaboration"
            ]
        }
    },
    {
        "source": "LinkedIn",
        "company": "Capgemini",
        "location": "Lyon",
        "link": "https://fr.linkedin.com/jobs/view/architecte-big-data-cloud-lyon-at-capgemini-3907764355?position=12&pageNum=0&refId=a5rwPua%2FMvx%2F2M%2FPSF0oPA%3D%3D&trackingId=7dtgcERGKyLxdC5FPR81ng%3D%3D&trk=public_jobs_jserp-result_search-card",
        "description": "√Ä propos de l‚Äôoffre d‚Äôemploi\nCapgemini en quelques mots\nChoisir Capgemini, c'est choisir une entreprise o√π vous serez en mesure de fa√ßonner votre carri√®re selon vos aspirations, o√π vous serez soutenu et inspir√© par une communaut√© d‚Äôexperts dans le monde entier, o√π vous pourrez r√©√©crire votre futur. Rejoignez-nous pour red√©finir les limites de ce qui est possible, contribuer √† lib√©rer la valeur de la technologie pour les plus grandes organisations et participez √† la construction d‚Äôun monde plus durable et inclusif.\nVos missions :\nVous r√©pondez aux probl√©matiques de nos clients en proposant des\nsolutions big data ¬´ on premise ¬ª et/ou dans le cloud (MS Azure, AWS et GCP).\nVous adaptez chaque architecture en fonction du contexte gr√¢ce √† votre maitrise des caract√©ristiques fondamentales de chaque solution (catalogue des offres de services manag√©s, performance, s√©curit√©, d√©ploiement des data centers ‚Ä¶).\nVous utilisez les solutions d‚Äôint√©gration associ√©es et les solutions d√©cisionnelles ainsi qu‚Äôanalytiques qui viennent consommer les donn√©es manipul√©es.\nVous √™tes en mesure d‚Äôencadrer les √©quipes de data engineers dans la mise en place des architectures pr√©conis√©es et/ ou des plateformes Big Data.\nVous √™tes en mesure d‚Äôappuyer les √©quipes commerciales dans les r√©ponses aux appels d‚Äôoffres Big Data.\nVotre profil :\nFormation Bac + 5 en √©cole d‚Äôing√©nieur ou √©quivalent universitaire avec une sp√©cialisation Big Data,\nA partir de 7 ans d‚Äôexp√©rience,\nVous √™tes un(e) passionn√©(e) de la Data et maitrisez aussi bien Linux et Spark que Script shell\nHadoop (cloudera/Hortonworks/MapR) n'a pas de secret pour vous mais vous avez pris le virage du cloud (AWS, GCP, MS Azure ),\nEnglish speaker, because we are French but also international.\n3 raisons de nous rejoindre :\nQualit√© de vie au travail :\naccord de t√©l√©travail en France et √† l‚Äôinternational, accord sur l‚Äô√©galit√© professionnelle, la parentalit√©, l‚Äô√©quilibre des temps et la mobilit√© durable.\nApprentissage en continu :\ncertifications et formations en libre acc√®s, accompagnement sur mesure avec votre carreer manager, parcours d‚Äôint√©gration sur 9 mois.\nAvantages groupe & CSE :\nplan actionnariat, activit√©s √† tarifs pr√©f√©rentiels, remboursement partiel vacances, remboursement de votre abonnement sportif ou culturel.\nNos engagements et priorit√©s :\nLe groupe Capgemini encourage une\nculture inclusive dans un cadre multiculturel et handi-accueillant.\nEn nous rejoignant, vous int√©grez un collectif qui valorise la diversit√©, d√©veloppe le potentiel de ses talents, s‚Äôengage dans des\ninitiatives solidaires avec ses partenaires, et se mobilise pour r√©duire son impact environnemental sur tous ses sites et aupr√®s de ses clients.\nCapgemini\nest un\nleader mondial,\nresponsable et multiculturel, regroupant pr√®s de 350 000 personnes dans plus de 50 pays. Fort de\n55 ans d‚Äôexp√©rience\n, nous sommes un partenaire strat√©gique des entreprises pour la transformation de leurs activit√©s en tirant profit de toute la puissance de la technologie et des innovations dans les domaines en perp√©tuelle √©volution tels que\nle cloud, la data, l‚ÄôIntelligence Artificielle, la connectivit√©, les logiciels, l‚Äôing√©nierie digitale ou les plateformes.\nGet The Future You Want* | www.capgemini.com/fr-fr\n*Capgemini, le futur que vous voulez\nShow more\nShow less",
        "details": {
            "JobDetail": [],
            "TypeContract": "",
            "Salary": "",
            "Level": "",
            "Experience": "7 an(s)"
        },
        "title": "data architect",
        "skills": {
            "BigData": [
                "Hadoop",
                "Spark"
            ],
            "CloudComputing": [
                "GCP",
                "AWS",
                "Azure"
            ],
            "OS": [
                "Linux"
            ],
            "Other": [
                "Cloud",
                "Big Data"
            ]
        }
    },
    {
        "source": "LinkedIn",
        "company": "ANFSI - Agence du num√©rique des forces de s√©curit√© int√©rieure",
        "location": "Issy-les-Moulineaux, √éle-de-France, France",
        "link": "https://fr.linkedin.com/jobs/view/architecte-data-at-anfsi-agence-du-num%C3%A9rique-des-forces-de-s%C3%A9curit%C3%A9-int%C3%A9rieure-3907477086?position=13&pageNum=0&refId=a5rwPua%2FMvx%2F2M%2FPSF0oPA%3D%3D&trackingId=Y3Rnq%2BGRbOfIeubfaQbhvg%3D%3D&trk=public_jobs_jserp-result_search-card",
        "description": "Vos activit√©s principales\nConception et Strat√©gie\n‚Ä¢ Analyse des besoins m√©tiers pour les syst√®mes de collecte et de stockage de donn√©es √† un niveau strat√©gique.\n‚Ä¢ Conception des architectures globales de donn√©es pour la collecte et le stockage de donn√©es, y compris l'int√©gration via des API au travers de solutions on-premise et cloud.\n‚Ä¢ Supervision des tests et de l'int√©gration pour garantir l'efficacit√© et la fiabilit√© des syst√®mes.\n‚Ä¢ Strat√©gie globales d'automatisation pour l'automatisation des traitements.\nGouvernance\n‚Ä¢ Politiques de nettoyage de donn√©es en s'alignant sur les objectifs de l'administration.\n‚Ä¢ Gestion strat√©gique des bases de donn√©es incluant des strat√©gies pour l'int√©gration de donn√©es diverses.\n‚Ä¢ Conformit√© et s√©curit√© des donn√©es dans le respect de normes comme le RGPD.\n‚Ä¢ Planification de la maintenance et du suivi des syst√®mes de donn√©es.\nDirection des Projets\n‚Ä¢ D√©finition des standards techniques et des meilleures pratiques pour les projets de d√©veloppement de donn√©es.\n‚Ä¢ Coordination et reporting : se coordonner avec les chefs de projet et les √©quipes techniques en vue de l'alignement architectural des projets.\n‚Ä¢Accompagner et coacher les autres experts et d√©veloppeurs, afin qu'ils\nmontent en comp√©tences sur les sujets li√©s √† l'int√©gration et √† la\ngouvernance des donn√©es.\nLeadership et Innovation\n‚Ä¢ Veille strat√©gique.\n‚Ä¢ Leadership en documentation : D√©finir les standards pour la documentation technique, incluant la gestion des connaissances et le partage des meilleures pratiques.\nVotre environnement professionnel\nActivit√©s du service\nL‚ÄôAgence du Num√©rique des Forces de S√©curit√© Int√©rieure (ANFSI) est charg√©e de piloter et de conduire les projets de syst√®mes d‚Äôinformation, de communication, de commandement et des moyens technologiques connexes d√©di√©s aux utilisateurs de la s√©curit√© int√©rieure.\nComposition et effectifs du service\nL‚ÄôANFSI est compos√©e de six directions : la Direction des Supports Op√©rationnels (DSO), la Direction de la s√©curit√© et de l‚Äôarchitecture (DSA), la Direction de l‚Äôappui √† l‚Äôinvestigation (DAI), la Direction des applications d‚Äôappui au commandement (DAAC), la Direction des communications tactiques (DCT), et la Direction de la proximit√© et de l‚Äôappui √† l‚Äôinnovation (DPAI). Son effectif est compos√©de personnels de la police et de la gendarmerie nationales ainsi que de contractuels.\nLa Section de mise √† disposition des donn√©es, o√π le poste est ouvert, est compos√©e de 9 personnes. Vous serez l‚Äôadjoint du chef de section qui est un ing√©nieur officier de gendarmerie. L‚Äôactivit√© principale de la section consiste √† r√©cup√©rer les donn√©es m√©tier des logiciels de r√©daction de proc√©dures des FSI et √† les mettre √† disposition d‚Äôapplications tierces, comme le fichier des personnes recherch√©es, le fichier des objets et v√©hicules vol√©s, ou le traitement des ant√©c√©dents judiciaires. L‚Äôarchitecte apporte son exp√©rience dans la mise en ≈ìuvre d‚ÄôETL et/ou d‚ÄôESB, et API manager.\nVos comp√©tences principales mises en ≈ìuvre :\nConnaissances techniques\nAvoir des comp√©tences en informatique - bureautique niveau ma√Ætrise requis\nConna√Ætre l'environnement professionnel niveau ma√Ætrise √† acqu√©rir\nSavoir-faire\nSavoir analyser niveau expert requis\nSavoir manager niveau ma√Ætrise requis\nSavoir r√©diger niveau pratique requis\nAvoir l'esprit de synth√®se niveau ma√Ætrise requis\nSavoir s'organiser niveau ma√Ætrise requis\nSavoir travailler en √©quipe niveau ma√Ætrise requis\nSavoir-√™tre\navoir le sens des relations humaines niveau ma√Ætrise requis\nsavoir s'adapter niveau expert requis\nsavoir communiquer niveau ma√Ætrise √† acqu√©rir\nsavoir s'exprimer oralement niveau ma√Ætrise √† acqu√©rir\nProfil recherch√© :\nTitulaire d'un dipl√¥me d'ing√©nieur (Bac +5) ou √©quivalent, votre passion pour la technologie vous rend apte √† r√©soudre des d√©fis complexes li√©s √† la Data. Avec au moins cinq ans d'exp√©rience en technologies ETL/ESB, message broker et API management, vous ma√Ætrisez ces domaines. Une exp√©rience approfondie dans la conception d'architectures de plateformes d'√©changes est essentielle. Une connaissance de la plateforme Mulesoft est un plus.\nVos perspectives\n:\nDans un contexte d‚Äôacc√©l√©ration de l'√©volution du num√©rique et des besoins de r√©activit√© associ√©s : enrichissement du r√©seau professionnel, approfondissement des connaissances et exp√©rience professionnelles, ma√Ætrise des proc√©dures et comp√©tences ¬´ m√©tier ¬ª de la GN/PN. Implication dans la mise en place de projets innovants (PN/GN) et transverses. S‚Äôouvrir aux nouvelles m√©thodologies de conduite de projet.\nDur√©e attendue sur le poste\n:\n3 ans\nSp√©cificit√©s du poste / Contraintes / Suj√©tions :\n39 heures hebdomadaires - 25 jours CA -22 jours de RTT\nLes candidat.e.s pourront √™tre soumis √† une enqu√™te administrative de s√©curit√© sur le fondement de l'article L.114-1 du code de la s√©curit√© int√©rieure.\nLocalisation g√©ographique :\n4, rue Claude Bernard ‚Äì 92130 Issy-les-Moulineaux\nShow more\nShow less",
        "details": {
            "JobDetail": [],
            "TypeContract": "",
            "Salary": "",
            "Level": "",
            "Experience": "3 an(s)"
        },
        "title": "data architect",
        "skills": {
            "Automation": [
                "Chef"
            ],
            "Other": [
                "Cloud"
            ],
            "EnSoftSkils": [
                "Leadership",
                "Communication"
            ]
        }
    },
    {
        "source": "LinkedIn",
        "company": "Capgemini",
        "location": "Issy-les-Moulineaux, √éle-de-France, France",
        "link": "https://fr.linkedin.com/jobs/view/architecte-big-data-cloud-at-capgemini-3902965293?position=14&pageNum=0&refId=a5rwPua%2FMvx%2F2M%2FPSF0oPA%3D%3D&trackingId=AwEXZKzHyJPYvt0z8HzQVw%3D%3D&trk=public_jobs_jserp-result_search-card",
        "description": "Capgemini en quelques mots\nChoisir Capgemini, c'est choisir une entreprise o√π vous serez en mesure de fa√ßonner votre carri√®re selon vos aspirations, o√π vous serez soutenu et inspir√© par une communaut√© d‚Äôexperts dans le monde entier, o√π vous pourrez r√©√©crire votre futur. Rejoignez-nous pour red√©finir les limites de ce qui est possible, contribuer √† lib√©rer la valeur de la technologie pour les plus grandes organisations et participez √† la construction d‚Äôun monde plus durable et inclusif.\nVos missions :\nVous r√©pondez aux probl√©matiques de nos clients en proposant des\nsolutions big data ¬´ on premise ¬ª et/ou dans le cloud (MS Azure, AWS et GCP).\nVous adaptez chaque architecture en fonction du contexte gr√¢ce √† votre maitrise des caract√©ristiques fondamentales de chaque solution (catalogue des offres de services manag√©s, performance, s√©curit√©, d√©ploiement des data centers ‚Ä¶).\nVous utilisez les solutions d‚Äôint√©gration associ√©es et les solutions d√©cisionnelles ainsi qu‚Äôanalytiques qui viennent consommer les donn√©es manipul√©es.\nVous √™tes en mesure d‚Äôencadrer les √©quipes de data engineers dans la mise en place des architectures pr√©conis√©es et/ ou des plateformes Big Data.\nVous √™tes en mesure d‚Äôappuyer les √©quipes commerciales dans les r√©ponses aux appels d‚Äôoffres Big Data.\nVotre profil :\nFormation Bac + 5 en √©cole d‚Äôing√©nieur ou √©quivalent universitaire avec une sp√©cialisation Big Data,\nA partir de 7 ans d‚Äôexp√©rience,\nVous √™tes un(e) passionn√©(e) de la Data et maitrisez aussi bien Linux et Spark que Script shell\nHadoop (cloudera/Hortonworks/MapR) n'a pas de secret pour vous mais vous avez pris le virage du cloud (AWS, GCP, MS Azure ),\nEnglish speaker, because we are French but also international.\n3 raisons de nous rejoindre :\nQualit√© de vie au travail :\naccord de t√©l√©travail en France et √† l‚Äôinternational, accord sur l‚Äô√©galit√© professionnelle, la parentalit√©, l‚Äô√©quilibre des temps et la mobilit√© durable.\nApprentissage en continu :\ncertifications et formations en libre acc√®s, accompagnement sur mesure avec votre carreer manager, parcours d‚Äôint√©gration sur 9 mois.\nAvantages groupe & CSE :\nplan actionnariat, activit√©s √† tarifs pr√©f√©rentiels, remboursement partiel vacances, remboursement de votre abonnement sportif ou culturel.\nNos engagements et priorit√©s :\nLe groupe Capgemini encourage une\nculture inclusive dans un cadre multiculturel et handi-accueillant.\nEn nous rejoignant, vous int√©grez un collectif qui valorise la diversit√©, d√©veloppe le potentiel de ses talents, s‚Äôengage dans des\ninitiatives solidaires avec ses partenaires, et se mobilise pour r√©duire son impact environnemental sur tous ses sites et aupr√®s de ses clients.\nCapgemini\nest un\nleader mondial,\nresponsable et multiculturel, regroupant pr√®s de 350 000 personnes dans plus de 50 pays. Fort de\n55 ans d‚Äôexp√©rience\n, nous sommes un partenaire strat√©gique des entreprises pour la transformation de leurs activit√©s en tirant profit de toute la puissance de la technologie et des innovations dans les domaines en perp√©tuelle √©volution tels que\nle cloud, la data, l‚ÄôIntelligence Artificielle, la connectivit√©, les logiciels, l‚Äôing√©nierie digitale ou les plateformes.\nGet The Future You Want* | www.capgemini.com/fr-fr\n*Capgemini, le futur que vous voulez\nShow more\nShow less",
        "details": {
            "JobDetail": [],
            "TypeContract": "",
            "Salary": "",
            "Level": "",
            "Experience": "7 an(s)"
        },
        "title": "data architect",
        "skills": {
            "BigData": [
                "Hadoop",
                "Spark"
            ],
            "CloudComputing": [
                "GCP",
                "AWS",
                "Azure"
            ],
            "OS": [
                "Linux"
            ],
            "Other": [
                "Cloud",
                "Big Data"
            ]
        }
    },
    {
        "source": "LinkedIn",
        "company": "Harnham",
        "location": "Paris, √éle-de-France, France",
        "link": "https://fr.linkedin.com/jobs/view/data-architect-at-harnham-3907820245?position=15&pageNum=0&refId=a5rwPua%2FMvx%2F2M%2FPSF0oPA%3D%3D&trackingId=safltM8yfEOH1tQrs0R5zw%3D%3D&trk=public_jobs_jserp-result_search-card",
        "description": "DATA ARCHITECT\nPARIS (75) / LILLE (59)\n50-55K EUR\nUne nouvelle opportunit√© s‚Äôouvre pour un Data Architecte dans le domaine de l‚Äôassurance. Une entreprise qui combine l‚Äôexpertise des grands groupes et l‚Äôagilit√© d‚Äôune start-up, qui vous permettra d‚Äôinnover ! Si vous recherchez un d√©fi stimulant dans un environnement qui encourage les nouvelles id√©es, cette opportunit√© est faite pour vous.\nVOTRE MISSION :\nElaborer et Concevoir l‚Äôarchitecture des donn√©es en r√©ponse aux besoins m√©tiers\nCollaboration pour comprendre les exigences des parties prenantes et les traduire en solutions architecturales\nConcevoir et impl√©menter des mod√®les de donn√©es efficaces et √©volutifs\nAssurer la coh√©rence et l‚Äôint√©grit√© des donn√©es √† travers tout le syst√®me.\nFournir des recommandations pour assurer une gestion efficace des donn√©es\nVOTRE PROFIL :\n4 ans d‚Äôexp√©rience dans un r√¥le similaire\nComp√©tences solides en Python, Cloud AWS, Tableau\nComp√©tencesavec le Machine Learning\nAnglais: Fluent obligatoire\nN‚Äôh√©sitez plus pour postuler !\nShow more\nShow less",
        "details": {
            "JobDetail": [],
            "TypeContract": "",
            "Salary": "",
            "Level": "",
            "Experience": "4 an(s)"
        },
        "title": "data architect",
        "skills": {
            "ProgLanguage": [
                "Python"
            ],
            "DataVisualisation": [
                "Tableau"
            ],
            "CloudComputing": [
                "AWS"
            ],
            "Other": [
                "Machine Learning",
                "Cloud"
            ],
            "EnSoftSkils": [
                "Collaboration"
            ]
        }
    },
    {
        "source": "LinkedIn",
        "company": "Vallum Associates",
        "location": "Paris, √éle-de-France, France",
        "link": "https://fr.linkedin.com/jobs/view/data-cloud-solution-architect-at-vallum-associates-3916589273?position=16&pageNum=0&refId=a5rwPua%2FMvx%2F2M%2FPSF0oPA%3D%3D&trackingId=4Zq3y89MIEfOPdGqnw0nGg%3D%3D&trk=public_jobs_jserp-result_search-card",
        "description": "Skills:\nFluent in French & English\n(must)\nDeep Snowflake expertise\nPlatform architecture\nDBA experience\nCloud database admin\nAWS Architecture\nCloud networking specialist\nExcellence in communication, coordination & collaboration, stakeholder & risk management and especially with drive & leadership\nOpen minded and accepting challenges\nHighly motivated, adaptable and flexible. Willing to integrate an existing environment and an existing project team\nShow more\nShow less",
        "details": {
            "JobDetail": [],
            "TypeContract": "",
            "Salary": "",
            "Level": "",
            "Experience": null
        },
        "title": "data architect",
        "skills": {
            "CloudComputing": [
                "AWS"
            ],
            "DBMS": [
                "Snowflake"
            ],
            "Other": [
                "Cloud"
            ],
            "EnSoftSkils": [
                "Leadership",
                "Communication",
                "Collaboration"
            ]
        }
    },
    {
        "source": "LinkedIn",
        "company": "Agyla.Cloud",
        "location": "France",
        "link": "https://fr.linkedin.com/jobs/view/data-architect-h-f-at-agyla-cloud-3885512739?position=17&pageNum=0&refId=a5rwPua%2FMvx%2F2M%2FPSF0oPA%3D%3D&trackingId=iq1NzP0cg3me9Ol5f2LP2A%3D%3D&trk=public_jobs_jserp-result_search-card",
        "description": "Agyla est depuis le 1er Juillet, LA r√©f√©rence en cloud public du groupe IBM Consulting.\nNous sommes un cabinet de conseil informatique sp√©cialis√© en Cloud & DevOps. Ce sont 90 experts qui interviennent au c≈ìur de la transformation technologique de nos clients, de la conception √† la s√©curisation en production.\nNos technologies cl√©s: AWS, Azure, GCP/Kubernetes, HashiCorp, tout sur la CICD, Cloud Security, cloud native developpement.\nFaire partie d‚ÄôAgyla c‚Äôest booster sa carri√®re et rejoindre notre communaut√© d‚Äôexperts, recrut√©s pour leurs talents.\nNos experts sont accompagn√©s dans leur carri√®re et renforcent leurs expertises √† travers des certifications techniques pour une mont√©e en comp√©tence constante. Ils participent au collectif en partageant leur savoir et en faisant grandir l‚Äôentreprise aupr√®s de ses clients.\nNous recrutons notre futur(e) Data Architect ! Vous souhaitez rejoindre une mission passionnante dans le secteur du retail ? Alors c'est par ici que √ßa se passe :\nVos t√¢ches :\nAccompagner et conseiller l'√©quipe notamment dans le cadre de mod√©lisation de donn√©es\n√âtablir et faciliter un forum d'architecture des donn√©es, o√π les options d'architecture des donn√©es sont examin√©es et discut√©es avec l'√©quipe.\nVeiller √† ce que la documentation appropri√©e soit cr√©√©e au fil du temps (suivi des d√©cisions du forum d'architecture des donn√©es, v√©rification que l'architecture des donn√©es pour chaque livraison r√©alis√©e par les √©quipes soit correctement document√©e).\nRepr√©senter les int√©r√™ts de l'√©quipe dans certains projets men√©s par d'autres √©quipes\nVos qualifications :\nExp√©rience en mod√©lisation de donn√©es.\nCapacit√© √† influencer les autres (pour soutenir mais aussi remettre en question les conceptions des produits de donn√©es r√©alis√©es).\nApp√©tence pour les processus/documentation, car l'id√©e est de renforcer la mani√®re de documenter et de gouverner l'architecture des donn√©es.\nMa√Ætrise d'un cloud public (Azure ou GCP)\nNB : La mission se d√©roule en full remote.\nAgyla.cloud a b√¢ti sa croissance sur la puissance de son √©quipe. Vous deviendrez un membre actif du succ√®s collectif.\nVous avez l‚Äôattitude d‚Äôun consultant : √† l‚Äô√©coute, bienveillant, vous partagez votre exp√©rience et faites grandir le client. Vous savez prendre des initiatives et avec une excellente communication orale et √©crite.\nAgyla-D√©claration sp√©cifique de confidentialit√©\nAgyla est une filiale IBM qui a √©t√© acquise par IBM et qui sera int√©gr√©e √† l'organisation IBM. Agyla sera l'entit√© d'embauche. En proc√©dant √† cette candidature, vous comprenez qu'Agyla partagera vos informations personnelles avec IBM et d'autres filiales IBM impliqu√©es dans votre processus de recrutement, o√π qu'elles se trouvent. Plus d'informations sur la fa√ßon dont IBM prot√®ge vos informations personnelles, y compris les garanties en cas de transfert de donn√©es transfronti√®re, sont disponibles ici:\nhttps://www.ibm.com/fr-fr/privacy\nShow more\nShow less",
        "details": {
            "JobDetail": [
                "Remote",
                "Full"
            ],
            "TypeContract": "",
            "Salary": "",
            "Level": "",
            "Experience": null
        },
        "title": "data architect",
        "skills": {
            "CloudComputing": [
                "GCP",
                "AWS",
                "Azure"
            ],
            "Automation": [
                "Kubernetes"
            ],
            "Containers": [
                "Kubernetes"
            ],
            "Other": [
                "Cloud",
                "DevOps"
            ],
            "EnSoftSkils": [
                "Communication"
            ]
        }
    },
    {
        "source": "LinkedIn",
        "company": "INSEAD",
        "location": "Fontainebleau, √éle-de-France, France",
        "link": "https://fr.linkedin.com/jobs/view/solution-architect-at-insead-3868439514?position=18&pageNum=0&refId=a5rwPua%2FMvx%2F2M%2FPSF0oPA%3D%3D&trackingId=Y%2F3BfUWMhpQ%2Bmh97Cx%2FrVA%3D%3D&trk=public_jobs_jserp-result_search-card",
        "description": "INSEAD brings together people, cultures and ideas from around the world to educate leaders who transform business and society. As a mission-driven school, INSEAD focuses on three values: open, rigorous, and entrepreneurial. As one of the world‚Äôs leading and largest graduate business schools, With campuses in Europe (France), Asia (Singapore), Middle East (Abu Dhabi) and an American Hub (San Francisco), INSEAD‚Äôs business and research spans four continents.\nWe are currently looking for a\nSolution Architect\nto join our Data & Enterprise Architecture team in the IT department. This is a permanent and full-time position, based either on our\nAsia Campus in Singapore\nor on our\nEurope Campus in Fontainebleau, France\n. A hybrid working model is in place ‚Äì 3 days on campus, 2 days from home.\nThe Solution Architect will analyse the current state of the enterprise environment from a technical and functional point of view. He/she will develop and design the future state architecture and the roadmap to reach it, balancing risks in terms of timeline and costs while meeting business requirements and enabling capability. The Solution Architect will devise technical or functional solutions to achieve enterprise and business objectives, this effort will consistently align with the IT strategy.\nKey Responsibilities include:\n‚Ä¢ Support large project implementation: (1) Formulate the solutions in which business and IT viewpoints are synthesised into a solution. (2) Develop the digital interoperability for new platforms to embed the INSEAD eco-system (3) Setup the plan for state-of-the-art operationalisation and maintenance of the new platform.\n‚Ä¢ Develop continuous integration & delivery practices in IT. Work out the best possible optimisation and automation of tasks and process(es), costing time and energy to the organisation.\n‚Ä¢ Formulate the architecture strategy and govern it: (1) Develop and communicate architectural standards (2) Add architecture consideration into business discussions to develop roadmaps and implementation plans considering a sustainable IT portfolio. (T.I.M.E from Gartner)\n‚Ä¢ Understand the enterprise needs and anticipate a major technology shift from the industry. This encompasses the need to educate/ inform the IT and school senior leadership about it so they can better prepare for the near future. It means driving the cost versus benefits, risks, impact, and technology priorities.\nWe are looking for a hands-on candidate who meets the following profile:\n‚Ä¢ A minimum of 5 years of professional experience with application development.\n‚Ä¢ Expert with DevSecOps practices. Hand‚Äôs on with suite of CI/CD platforms and utilities.\n‚Ä¢ Track record of enterprise architecture application (certify TOGAF is a plus).\n‚Ä¢ Expertise in process design as well as Data modelling (certify ArchiMate is a plus).\n‚Ä¢ Knowledge of Salesforce, Oracle Cloud and ServiceNow is a plus.\n‚Ä¢ Demonstrated polished consulting skills with a keen awareness of sensitive client topics, and the ability to navigate client messaging and recommendations tactfully.\n‚Ä¢ Proven ability to establish credibility with Senior Executives, team members and external partners, with excellent analytical and problem-solving skills for managing large and small projects.\n‚Ä¢ Strong prioritization skills with attention to detail, and the capability to quickly define dependencies, issues, and mitigation plans against risks.\n‚Ä¢ Effective communication skills bridging technology and business communities, with a consistent track record of business-building successes.\n‚Ä¢ Fluency in English, with proficiency in French is advantageous.\n‚Ä¢ Enthusiasm for exploring unknown technological territories and a strong technical curiosity to understand how things work.\nWe are happy to receive your resume and cover letter for this exciting opportunity. Please send your application to Talent Acquisition Europe talent.acquisition@insead.edu\nDiversity is one of INSEAD‚Äôs founding values and as such we commit to cultivating a community that pursues equity, exemplifies inclusion and cherishes diversity in all its dimensions. Our jobs are open to all talents, so apply and join us!\nWe regret that only shortlisted candidates will be contacted.\nShow more\nShow less",
        "details": {
            "JobDetail": [
                "Full",
                "Senior"
            ],
            "TypeContract": "",
            "Salary": "",
            "Level": "",
            "Experience": null
        },
        "title": "data architect",
        "skills": {
            "Other": [
                "Cloud",
                "CI/CD"
            ],
            "EnSoftSkils": [
                "Leadership",
                "Communication"
            ]
        }
    },
    {
        "source": "LinkedIn",
        "company": "Capgemini",
        "location": "Lille, Hauts-de-France, France",
        "link": "https://fr.linkedin.com/jobs/view/architecte-big-data-cloud-lille-at-capgemini-3861939159?position=19&pageNum=0&refId=a5rwPua%2FMvx%2F2M%2FPSF0oPA%3D%3D&trackingId=Rii39Sm%2BCo0XrM2FDDa1DA%3D%3D&trk=public_jobs_jserp-result_search-card",
        "description": "Capgemini en quelques mots\nChoisir Capgemini, c'est choisir une entreprise o√π vous serez en mesure de fa√ßonner votre carri√®re selon vos aspirations, o√π vous serez soutenu et inspir√© par une communaut√© d‚Äôexperts dans le monde entier, o√π vous pourrez r√©√©crire votre futur. Rejoignez-nous pour red√©finir les limites de ce qui est possible, contribuer √† lib√©rer la valeur de la technologie pour les plus grandes organisations et participez √† la construction d‚Äôun monde plus durable et inclusif.\nVos missions\nInteragir au plus proche de nos clients, des partenaires pour concevoir et mettre en ≈ìuvre des solutions/projets innovants et comp√©titifs\nR√©pondre aux probl√©matiques de nos clients en proposant la meilleure plateforme data dans un environnement Agile\nAdapter chaque architecture en fonction du contexte gr√¢ce √† votre maitrise des caract√©ristiques fondamentales de chaque solution (catalogue des offres de services manag√©s, performance, s√©curit√©, d√©ploiement des data centers ‚Ä¶)\nUtiliser les solutions d‚Äôint√©gration associ√©es et les solutions d√©cisionnelles ainsi qu‚Äôanalytiques qui viennent consommer les donn√©es manipul√©es\nEncadrer les √©quipes dans la mise en place des architectures pr√©conis√©es et/ ou des plateformes Data.\nVotre profil\nAu moins 6 ans d‚Äôexp√©rience (au sein d‚Äôune ESN ou chez un int√©grateur) en conseil client√®le\nUne solide culture technologique\nUn bon niveau d‚Äôanglais\nDes qualit√©s de p√©dagogue et un int√©r√™t pour la phase d‚Äôavant-vente.\n3 raisons de nous rejoindre\nQualit√© de vie au travail :\naccord de t√©l√©travail en France et √† l‚Äôinternational, accord sur l‚Äô√©galit√©\nprofessionnelle, la parentalit√©, l‚Äô√©quilibre des temps et la mobilit√© durable.\nApprentissage en continu :\ncertifications et formations en libre acc√®s, accompagnement sur mesure avec\nvotre carreer manager, parcours d‚Äôint√©gration sur 9 mois.\nAvantages groupe & CSE :\nplan actionnariat, activit√©s √† tarifs pr√©f√©rentiels, remboursement partiel\nvacances, remboursement de votre abonnement sportif ou culturel\nNos engagements et priorit√©s\nLe groupe Capgemini encourage une\nculture inclusive dans un cadre multiculturel et handi-accueillant.\nEn nous rejoignant, vous int√©grez un collectif qui valorise la diversit√©, d√©veloppe le potentiel de ses talents, s‚Äôengage dans des\ninitiatives solidaires avec ses partenaires, et se mobilise pour r√©duire son impact environnemental sur tous ses sites et aupr√®s de ses clients.\nCapgemini\nest un\nleader mondial\n, responsable et multiculturel, regroupant pr√®s de 350 000 personnes dans plus de 50 pays. Fort de\n55 ans d‚Äôexp√©rience,\nnous sommes un partenaire strat√©gique des entreprises pour la transformation de leurs activit√©s en tirant profit de toute la puissance de la technologie et des innovations dans les domaines en perp√©tuelle √©volution tels que le\ncloud, la data, l‚ÄôIntelligence Artificielle, la connectivit√©, les logiciels, l‚Äôing√©nierie digitale ou les plateformes.\nGet The Future You Want* | www.capgemini.com/fr-fr\n*Capgemini, le futur que vous voulez\nShow more\nShow less",
        "details": {
            "JobDetail": [],
            "TypeContract": "",
            "Salary": "",
            "Level": "",
            "Experience": "6 an(s)"
        },
        "title": "data architect",
        "skills": {
            "Other": [
                "Cloud"
            ]
        }
    },
    {
        "source": "LinkedIn",
        "company": "LEM",
        "location": "Lyon, Auvergne-Rh√¥ne-Alpes, France",
        "link": "https://fr.linkedin.com/jobs/view/it-data-architect-at-lem-3916801738?position=20&pageNum=0&refId=a5rwPua%2FMvx%2F2M%2FPSF0oPA%3D%3D&trackingId=KptAY1vG1vOswIxM2PaP3Q%3D%3D&trk=public_jobs_jserp-result_search-card",
        "description": "LEM ‚Äì Life Energy Motion\nAt LEM, we help our customers and society accelerate the transition to a sustainable future.\nOur global team of 1,700 professionals which spans over 15 countries is dedicated to converting technology potential into powerful solutions, which enable the decarbonization of the world.\nA leading company in electrical measurement, LEM engineers the best solutions for energy efficiency and electrical mobility, ensuring our customers, systems are optimized, reliable and safe.\nLEM is listed on the SIX Swiss Exchange since 1986, with the ticker symbol LEHN.\nThe future needs our ingenuity, we need your Spark.\n#BringYourSpar\nIn order to build the analytic team, we are looking for an IT DATA architect.\nThis is an exciting new opportunity working as part of the Corporate IT team to develop new capabilities and establish a supportable model of platform and applications, growing the companies use of modern technologies.\nThe IT Data architect is responsible for defining policies, procedures, models, and technologies that will be used to collect, organize, store, and retrieve information for the organization.\nHe / she understands how data drives the development of applications and business requirements through appropriate design principles, methodologies, and tools.\nHe / she sets the rules and structure for the data strategy, choosing the ETL approach and setting additional requirements.\nThe main tasks will be related to:\nApplication Design\nData model definition: Define the data architecture, data contract interfaces, data quality into the systems, best practices,\nData flow overview: Take the ownership of the current and future data flows. Take responsibilities for data quality and timeliness,\n& ensure the evolution of data flows, using the global data standards and business rules to input data into the systems,\nQuality assurance: Perform data quality checks for correctness and completeness according to defined business rules,\nMaster Data System: maintain accurate & up to date data for assigned business processes,\nto continuous improvements of systems and processes. Ensure data alignment between contract documentation and customer master data,\nup to date process documentation and training material,\nSupport: Ensure issues are identified, tracked, reported on and resolved in a timely manner.\nDevelopment & maintenance\nRole of expert for the designated product or product domain.\nDeals with user requests, service tickets, incidents, modifications\nAssume the 3rd level support activities\nWrites and maintains the documentation\nParticipates in creating user guides\nEnsures that knowhow of domain is transferred to team members.\nEnsures compliance with data security at all times.\nEvaluates applications and databases performance and enhances when possible\nCarry out or supervise development and system integration activities.\nProject management\nLead data related projects as IT representative\nDefines scope of the project, plans and follows project developments and deployments of applications.\nSupervise external resources during project phase.\nSkills required:\nCustomer driven approach\nExperience working in azure DF, Synapse, AWS, or other\nworking with Agile methodologies\nproblem solving, ability to work under pressure and able to prioritise\nand ability to work independently with limited supervision\ncommunication and interpersonal skills, ability to work effectively with remote teams\ngood oral and written communication\nin English\nDate of Employment: ASAP\nShow more\nShow less",
        "details": {
            "JobDetail": [
                "Remote"
            ],
            "TypeContract": "",
            "Salary": "",
            "Level": "",
            "Experience": null
        },
        "title": "data architect",
        "skills": {
            "BigData": [
                "Spark"
            ],
            "CloudComputing": [
                "AWS",
                "Azure"
            ],
            "Collaboration": [
                "Teams"
            ],
            "EnSoftSkils": [
                "Problem Solving",
                "Communication",
                "Organization",
                "Interpersonal Skills"
            ]
        }
    },
    {
        "source": "LinkedIn",
        "company": "JSS ASSOCIATES",
        "location": "Paris, √éle-de-France, France",
        "link": "https://fr.linkedin.com/jobs/view/senior-data-architect-consultant-at-jss-associates-3912573427?position=21&pageNum=0&refId=a5rwPua%2FMvx%2F2M%2FPSF0oPA%3D%3D&trackingId=ksX%2FYtGaX9xFT9xx8JPlNw%3D%3D&trk=public_jobs_jserp-result_search-card",
        "description": "Senior Data Architect / Consultant\nFor one of my leading clients focused in data advisory, we are looking for an experienced Data Architect / Consultant to join their dynamic team based in an affluent and upscale suburb west of Paris.\nMy client is renowned by industry experts for its commitment to empowering its clients in establishing robust data frameworks. Offering bespoke solutions span from fostering cultural shifts and technological empowerment to ensuring data consistency, security, and precision. With expertise in Data Advisory, Architecture, Academy, and Green Data, as well as proficiency in implementing Platform Data solutions such as Data Preparation and Integration. My client caters to diverse clients across the world. Driven by core values, they strive for sustainable consulting services, leveraging innovation and pragmatism in their data-centric approach.\nRole Overview:\nReporting to either the Data Advisory Manager or the Director of the Data Advisory Business Line, you will collaborate with clients on multifaceted missions. You will participate in pre-sales activities, response to calls for tenders and support and participate in internal projects related to the development of my clients business interests.\nCommercial aspect:\nParticipate in pre-sales activities, response to calls for tenders and support, all of the entrusted activities are carried out in compliance with my clients quality level. Participate in internal projects related to the development of my clients business interests.\nManagement responsibilities:\nSupervise and develop the skills of consultants within your scope.\nEnsure the skills development of junior/confirmed consultants, coaching and monitoring\nData Architecture section:\nSupport audit or urbanization missions of data platforms and tools responding to the company's new challenges: definition of the scope, estimation of costs, planning and organization, promotion of the methodology.\nBe responsible for the quality of project deliverables/documentation;\nLead meetings and write reports;\nSupport and advise the client in defining their data architectures;\nValidate the company's expectations in terms of functionality and functional and non-functional coverage of the solutions;\nLead and arbitrate debates defining architectural orientations;\nConduct individual interviews with the various mission contacts for Coaching or Audit;\nProject management: lead a project independently from start to finish under the supervision of your project director;\nDefinition of feedback, self-criticism and retrospectives of milestones.\nIn addition you will support a project to set up a ‚ÄúData Academy‚Äù organization: definition of the scope, estimation of costs, planning and organization, promotion of the methodology.\nBe responsible for the quality of project deliverables;\nLead meetings and write reports;\nSupport and advise the client in managing change in their organization to support implementation;\nValidate the company's expectations in terms of acculturation and maturity around data;\nLead and arbitrate debates defining strategic orientations;\nConduct individual interviews with the various project stakeholders for Coaching or Audit;\nProject management: lead a project independently from start to finish under the supervision of your project director;\nDefinition of feedback, self-criticism and retrospectives of milestones.\nData governance component:\nFramework a governance initiative: identification of use cases, customer needs in terms of data governance, and the appropriate methodology;\nDesign and implement a data governance solution: glossary, business, metadata, processes, roles and responsibilities, lineage.\nDefine the roadmap to improve governance.\nYour profile:\nRequired skills:\nA Data Architect profile with a functional/technical background capable of:\nParticipate in pre-sales/proposals and the definition and audit of the architecture;\nPrepare and lead various Workshop committees;\nSupport Architects and Data Advisors;\nHave solid experience in enterprise architecture and consulting activities, be able to advise the best typical model according to needs.\nMinimum of Bac+5 training within a major engineering or IT school, you have at least 5 years of experience in this type of role;\nYou have worked in the field of information management in the company, data governance, or the implementation of Data solutions (MDM, DQM, Data Catalog Data Science, Data Preparation);\nDynamic and enthusiastic, you like teamwork and you want to actively participate in the development of our company and the training of consultants. Your thirst for entrepreneurship and your desire to participate in our development will be determining elements;\nThanks to your good level of English, you will participate with ease in international missions;\nYou will work in a very motivating and friendly context and you will benefit from significant freedom over the missions you will have to accomplish.\nShow more\nShow less",
        "details": {
            "JobDetail": [
                "Confirmed",
                "Junior",
                "Senior"
            ],
            "TypeContract": "",
            "Salary": "",
            "Level": "Bac+5",
            "Experience": null
        },
        "title": "data architect",
        "skills": {
            "EnSoftSkils": [
                "Initiative",
                "Teamwork",
                "Organization"
            ]
        }
    },
    {
        "source": "LinkedIn",
        "company": "Lincoln France",
        "location": "Boulogne-Billancourt, √éle-de-France, France",
        "link": "https://fr.linkedin.com/jobs/view/data-architect-senior-h-f-at-lincoln-france-3909573086?position=22&pageNum=0&refId=a5rwPua%2FMvx%2F2M%2FPSF0oPA%3D%3D&trackingId=e90%2FpCVUztPl3zl6iZg0KA%3D%3D&trk=public_jobs_jserp-result_search-card",
        "description": "Poste CDI : Data Architect Senior - H/F\nüìä 8 ans minimum\nLincoln Pure Player Data\nüí°: R√©inventant l'analyse\ndepuis 30 ans\n. Experts en Modern BI, Big Data et Science des donn√©es üìä. Nous transformons vos donn√©es en solutions pour les grands comptes, des secteurs bancaire, retail, t√©l√©coms, industriel, sant√©, et plus encore üíº.\nDescription du poste :\nNous recherchons un\nData Architect\nexp√©riment√© pour rejoindre notre √©quipe dynamique. Vous int√©grerez\nla direction Conseil Innovation et D√©veloppement de Lincoln\nau sein de laquelle vous pourrez d√©velopper tout votre savoir\nüéØ\nMissions\n:\nConcevoir et d√©velopper\nl'architecture de donn√©es\n, en alignant les besoins de l'entreprise avec les meilleures pratiques du secteur. (Savoir utiliser les services cloud / outils pour r√©pondre aux besoin de l‚Äôentreprise)\nCollaborer avec\nles √©quipes techniques et m√©tiers\npour d√©finir les exigences et les objectifs en mati√®re de donn√©es.\nD√©finir et maintenir\nles normes et les directives de gouvernance des donn√©es\n.\nConcevoir et mettre en ≈ìuvre des\nsolutions de s√©curit√© des donn√©es pour prot√©ger l'int√©grit√© et la confidentialit√© des informations sensibles\n.\nG√©rer les\nprocessus d'int√©gration, de transformation et de migration\ndes donn√©es.\n√âvaluer et s√©lectionner les outils et les technologies adapt√©s √† l'architecture de donn√©es de l'entreprise.\nParticiper √†\nl'√©valuation des risques et √† la planification de la continuit√© des activit√©s\nli√©es aux donn√©es.\nParticiper √† la r√©alisation de missions de conseil\n(audit, √©tude de migration de plateforme, design d‚Äôarchitecture DATA‚Ä¶)\nConcevoir et superviser l'architecture de donn√©es du client\n, en veillant √† ce qu'elle r√©ponde aux besoins actuels et futurs de l'organisation\nParticiper aux r√©ponses aux\nappels d‚Äôoffre\nSupport technique\nau partenariat √©diteur de Lincoln\nR√©aliser de\nla veille technologiques\n(solution DATA, cloud/on premise)\nüîç\nPr√©requis\n:\nExp√©rience av√©r√©e en tant que Data Architect ou dans un r√¥le similaire.\nConnaissance approfondie des concepts et des principes de l'architecture de donn√©es.\nTr√®s bonne connaissance des environnements de cloud (sp√©cialiste sur au moins une technologie ‚Äì GCP, Azure, Aws, Snowflake, Databricks‚Ä¶)\nMa√Ætrise des technologies et des outils de gestion de donn√©es, tels que les bases de donn√©es relationnelles, les entrep√¥ts de donn√©es, les outils ETL, etc.\nSolide compr√©hension des principes de s√©curit√© des donn√©es et de la conformit√© aux r√©glementations en vigueur.\nExcellentes comp√©tences analytiques et de r√©solution de probl√®mes.\nCapacit√© √† travailler efficacement en √©quipe et √† communiquer clairement avec des interlocuteurs techniques et non techniques.\nDipl√¥me d‚Äôing√©nieur ou universitaire en informatique, en science des donn√©es ou dans un domaine connexe (un atout).\nConnaissance de mod√©lisation des donn√©es (3FN, √©toile, flocon)\nEnvironnements techniques :\nEnvironnement de cloud (GCP, Azure, AWS) vs On premises (Hadoop, Cloudera)\nBases de donn√©es relationnelles et base de donn√©es NoSql (MySQL, Oracle, SQL Server, PostgreSQL, Mango DB, Cassandra, GCP Big query, Snowflake, Redshift)\nLangage : Python, Pyspark, SQL\nOutils ETL / ELT: Informatica, Talend, IBM DataStage, DBT\nüåü\nAvantages :\nEnvironnement collaboratif et innovant\nFormations certifiantes et accompagnement individualis√©\nT√©l√©travail et horaires flexibles\nR√©mun√©ration comp√©titive avec avantages sociaux attrayants\nPossibilit√© de mobilit√© √† Lille, Lyon ou Aix-en-Provence\n‚ú®\nProcessus de recrutement\n: 2 entretiens (RH et technique)\nSi vous √™tes passionn√© par les d√©fis de la Data et que vous souhaitez rejoindre une √©quipe dynamique et innovante,\npostulez d√®s maintenant et contribuez √† red√©finir l'avenir de l'analyse de donn√©es chez Lincoln! üòâ\nShow more\nShow less",
        "details": {
            "JobDetail": [
                "Senior"
            ],
            "TypeContract": "CDI",
            "Salary": "",
            "Level": "",
            "Experience": "8 an(s)"
        },
        "title": "data architect",
        "skills": {
            "ProgLanguage": [
                "Python"
            ],
            "DataBase": [
                "SQL",
                "Cassandra",
                "NoSQL"
            ],
            "BigData": [
                "Databricks",
                "Hadoop"
            ],
            "CloudComputing": [
                "GCP",
                "AWS",
                "Azure"
            ],
            "DBMS": [
                "SQL Server",
                "MySQL",
                "Big Query",
                "PostgreSQL",
                "Snowflake"
            ],
            "SoftBigDataProcessing": [
                "Cassandra"
            ],
            "Other": [
                "Cloud",
                "Big Data"
            ]
        }
    },
    {
        "source": "LinkedIn",
        "company": "Akkodis",
        "location": "France",
        "link": "https://fr.linkedin.com/jobs/view/data-architect-h-f-at-akkodis-3894683359?position=23&pageNum=0&refId=a5rwPua%2FMvx%2F2M%2FPSF0oPA%3D%3D&trackingId=I9eYsNqP6O%2FDAy8ljoEwxA%3D%3D&trk=public_jobs_jserp-result_search-card",
        "description": "La ligne de service Consulting & Solutions d Akkodis France renforce ses √©quipes et recrute\nun Data Architect H/F\nen CDI dans l‚Äôun de nos sites principaux en Ile de France ou en Province.\nDescription de la mission :\nL‚Äôoffre data intelligence d‚ÄôAKKODIS fait partie des 7 expertises internationales du Groupe. Elle adresse aujourd‚Äôhui des projets sur de nombreux secteurs d‚Äôactivit√© : A√©ronautique, Transport, Energie, Banque & Assurance, D√©fense.\nSon objectif est d‚Äôaider nos clients √† am√©liorer leurs processus op√©rationnels, leur time-to-market et leur prise de d√©cision en permettant :\n- la mise en place de la continuit√© digitale\n- de gagner en maturit√© dans l‚Äôutilisation et la valorisation des donn√©es\nvia la mise en ≈ìuvre de technologies et plateformes data et l‚Äôutilisation data sciences et de l‚ÄôIA.\nNotre strat√©gie de croissance nous am√®ne aujourd‚Äôhui √† renforcer nos comp√©tences m√©tier dans le domaine de la Data Intelligence et dans ce cadre nous recherchons un(e) Data Architect capable d‚Äôapporter son expertise sur les projets pr√©sents dans notre portefeuille actuel et aupr√®s des consultants Akkodis tout en travaillant sur les sujets d‚Äôavant-vente et de construction d‚Äôoffre afin d‚Äô√©largir notre scope d‚Äôintervention.\nInt√©gr√©(e) √† l‚Äô√©quipe Data Intelligence, vous travaillerez en collaboration avec une √©quipe d‚Äôune trentaine de personnes et participerez au d√©veloppement de projets innovants (Jumeau num√©rique, Industrie 4.0, maintenance pr√©dictive, IA g√©n√©rative,..)\nVous vous verrez confier les missions suivantes :\n¬∑ Participer √† la conception de l'architecture de notre plateforme Data ainsi qu‚Äô√† celles de nos clients (On Premise, Cloud, Hybride)\n¬∑ Participer √† la veille technologique et prendre en charge l'exp√©rimentation de nouvelles solutions du march√©\n¬∑ R√©aliser des missions d‚Äôaudit et conseil en architecture pour nos clients ; impl√©mentation de projets data\nDipl√¥m√©(e) d'un Bac + 3/+5 en informatique, vous justifiez d‚Äôune exp√©rience de 10 ans minimum dans les domaines de la Data et maitrisez les technologies Python, PySpark, Kafla, Spark et l‚Äôenvironnement Linux.\nVous disposez exp√©riences probantes dans l‚Äôimpl√©mentation de projets data au sein de cloud providers (MS Azure, GCP ou AWS) et √™tes en capacit√© de benchmarker les solutions propos√©es, de conseiller nos clients sur les architectures et outils √† mettre en place. Vous avez de bonnes capacit√©s de synth√®se et savez convaincre. Vous avez le sens du relationnel et faites preuve d'adaptabilit√© et de flexibilit√©. Vous √™tes curieux et imaginatif pour trouver des solutions adapt√©es.\nAlors n'h√©sitez plus, rejoignez-nous en nous transmettant votre CV !\nA comp√©tences √©gales, le poste est ouvert aux personnes en situation de handicap.\nEn int√©grant AKKODIS vous rejoindrez une entreprise dans laquelle votre savoir-√™tre et votre savoir-faire feront la diff√©rence pour inventer le futur de nos clients. Votre r√¥le s‚Äôinscrit dans un v√©ritable projet d'entreprise.\nAkkodis accompagne ses clients dans la mondialisation de leurs projets, aussi un anglais courant est requis pour l ensemble de nos collaborateurs.\nChez Akkodis nous sommes convaincus que de l‚Äôintelligence collective na√Æt le succ√®s. Il n‚Äôexiste pas qu‚Äôun mod√®le, nous valorisons l‚Äôagilit√© et l‚Äôexcellence, l‚Äôaudace et la cr√©ativit√©.\nEt si nous parlions ensemble de vos ambitions pour les prochaines ann√©es ?\nAkkodis est une entreprise handi-engag√©e et inclusive. Tous nos postes sont ouverts aux handicaps et √† la diversit√©. Tous diff√©rents, tous comp√©tents !\nAkkodis, est un acteur mondial de l‚Äôing√©nierie et de l‚ÄôIT et un leader dans la smart industrie. Nous accompagnons nos clients dans leurs projets de transformation digitale via 4 lignes de service : Consulting, Solutions, Talent et Academy. Akkodis est un partenaire technologique de confiance pour ses clients √† l‚Äô√©chelle internationale. Nous co-cr√©ons et nous imaginons des solutions de pointe pour r√©pondre aux d√©fis majeurs de notre soci√©t√©, qu'il s'agisse d'acc√©l√©rer la transition √©nerg√©tique et de d√©velopper la mobilit√© verte, ou encore de construire des approches centr√©es sur les utilisateurs.\nDot√©s d‚Äôune forte culture de l‚Äôinclusion et de la diversit√©, nos 50 000 experts en IT et en ing√©nierie, pr√©sents dans 30 pays, allient les meilleures comp√©tences technologiques √† une connaissance transverse de toutes les industries pour fa√ßonner un futur plus durable. Nous sommes passionn√©s par l‚Äôid√©e d‚Äôinventer ensemble un avenir meilleur.\nAkkodis en France, ce sont pr√®s de 9.000 experts en IT et en ing√©nierie r√©partis sur l'ensemble du territoire, des collaborateurs partageant des valeurs fortes d'honn√™tet√©, de respect, d'√©quit√© et d'inclusion. Notre engagement : leur permettre au quotidien d'√™tre eux-m√™mes au travail, et acteurs de leur vie et de leur d√©veloppement au sein d'Akkodis..\nAkkodis est la marque technologique de The Adecco Group\n*Akkodis est une marque commerciale sous laquelle les entit√©s AKKA et Modis op√®rent\nShow more\nShow less",
        "details": {
            "JobDetail": [
                "Hybride"
            ],
            "TypeContract": "CDI",
            "Salary": "",
            "Level": "",
            "Experience": "10 an(s)"
        },
        "title": "data architect",
        "skills": {
            "ProgLanguage": [
                "Python"
            ],
            "BigData": [
                "Spark"
            ],
            "CloudComputing": [
                "GCP",
                "AWS",
                "Azure"
            ],
            "OS": [
                "Linux"
            ],
            "Other": [
                "Cloud"
            ],
            "EnSoftSkils": [
                "Collaboration"
            ]
        }
    },
    {
        "source": "LinkedIn",
        "company": "Schneider Electric",
        "location": "Lattes, Occitanie, France",
        "link": "https://fr.linkedin.com/jobs/view/data-model-architect-f-h-at-schneider-electric-3864654667?position=24&pageNum=0&refId=a5rwPua%2FMvx%2F2M%2FPSF0oPA%3D%3D&trackingId=v3%2F141hz7OHIAN2jbFJZAA%3D%3D&trk=public_jobs_jserp-result_search-card",
        "description": "Missions\nAs a Data Architect, you will play a crucial role in shaping and optimizing our product's data infrastructure. You will be responsible for designing, implementing, and maintaining scalable and efficient data solutions that meet business needs. This role requires a deep understanding of data management and a strategic mindset to align data architecture with overall business strategies:\nData Modeling and Design:\nEnsure compliance with industry standards such as IEC61850\nDevelop and maintain conceptual, logical, and physical data models\nDesign data structures and relationships that support business requirements and enable efficient data retrieval\nData Governance:\nEstablish and enforce data governance policies and procedures\nDefine data standards, naming conventions, and data quality rules\nData Integration:\nDesign and implement data integration solutions to ensure seamless flow of information across systems\nCollaborate with other IT teams to integrate data sources and maintain data consistency\nCollaboration and Communication:\nWork closely with business stakeholders to understand their data needs and translate them into effective data solutions\nCollaborate with cross-functional teams including analysts and developers\nSecurity and Compliance:\nImplement data security measures to protect sensitive information\nProvide leadership, analysis, and design tasks related to the development or upgrade of a solution to ensure the application provides expected business value. Provide architecture guidance and support on activities performed to maintain, improve, or support applications.\nProfile\nBachelor's or Master's degree in Computer Science, Information Technology, or a related field\nMinimum of 5 years of experience as a Data Architect or in a similar role\nKnowledge of IEC61850\nStrong knowledge of database management systems and data modeling techniques\nUnderstanding of agile methods and processes, and the capability of supporting agile project teams\nAnalytical and strategic thinking\nExcellent communication and collaboration skills\nProblem-solving and troubleshooting abilities\nStay updated on emerging trends and technologies in data management\nWhy us?\nSchneider Electric is leading the digital transformation of energy management and automation. Our technologies enable the world to use energy in a safe, efficient and sustainable manner. We strive to promote a global economy that is both ecologically viable and highly productive.\n‚Ç¨34bn global revenue\n128 000+ employees in 100+ countries\n45% of revenue from IoT\n5% of revenue devoted for R&D\nYou must submit an online application to be considered for any position with us. This position will be posted until filled\nIt is the policy of Schneider Electric to provide equal employment and advancement opportunities in the areas of recruiting, hiring, training, transferring, and promoting all qualified individuals regardless of race, religion, color, gender, disability, national origin, ancestry, age, military status, sexual orientation, marital status, or any other legally protected characteristic or conduct. Concerning agencies: Schneider Electric does not accept unsolicited resumes and will not be responsible for fees related to such.\nShow more\nShow less",
        "details": {
            "JobDetail": [],
            "TypeContract": "",
            "Salary": "",
            "Level": "",
            "Experience": null
        },
        "title": "data architect",
        "skills": {
            "ProgLanguage": [
                "R"
            ],
            "DataAnalytics": [
                "R"
            ],
            "Collaboration": [
                "Teams"
            ],
            "EnSoftSkils": [
                "Leadership",
                "Communication",
                "Collaboration"
            ]
        }
    },
    {
        "source": "LinkedIn",
        "company": "Harnham",
        "location": "Paris",
        "link": "https://fr.linkedin.com/jobs/view/data-architect-at-harnham-3911912252?position=25&pageNum=0&refId=a5rwPua%2FMvx%2F2M%2FPSF0oPA%3D%3D&trackingId=%2BTxN4OcYZuigrD5W0hnoCQ%3D%3D&trk=public_jobs_jserp-result_search-card",
        "description": "DATA ARCHITECT\nPARIS (75)\nUP TO 65K‚Ç¨ FIXE\nAWS - Tableau - Pyspark - Data Modeling\nVous √™tes √† la recherche d'un nouveau challenge de Data Architect dans le domaine de l'assurance ? Ne cherchez plus, voici l'opportunit√© de vos r√™ves ! Une entreprise sp√©cialis√©e dans l'assurance automobile des particuliers, recherche un Data Architect dans le cadre de la cr√©ation d'une nouvelle plateforme data en Europe.\nLE POSTE\nEn tant que Data Architect, vous allez d√©finir les architectures et les normes pour la strat√©gie de donn√©es. Vous d√©finirez la vision et les lignes directrices pour la livraison des produits de donn√©es.\nVoici vos responsabilit√©s au quotidien :\nD√©finir l'architecture cible\nCommuniquer avec les Product Owner pour atteindre l'objectif du wagon\nTravailler en √©troite collaboration avec les data scientists pour op√©rationnaliser les mod√®les ML au sein de la plateforme de donn√©es\nTravailler en √©troite collaboration avec les data engineer et data ops pour le suivi de l'architecture cible\nTravailler en mode agile au quotidien\nVOTRE PROFIL\nDipl√¥me d'ing√©nieur en computer engineering ou math√©matiques\n5 ans d'exp√©rience en architecture data\nConnaissance des architectures de plateformes de donn√©es op√©rationnelles\nConnaissance de la mod√©lisation de donn√©es et bases de donn√©es\nConnaissance du cloud AWS\nConnaissance d'outils BI principalement Tableau\nBilingue (fan√ßais et anglais)\nNice to have : connaissance en Machine Learning\nPOUR POSTULER\nMerci de me faire part de votre CV et je vous recontacterai au plus vite.\nShow more\nShow less",
        "details": {
            "JobDetail": [],
            "TypeContract": "",
            "Salary": "",
            "Level": "",
            "Experience": "5 an(s)"
        },
        "title": "data architect",
        "skills": {
            "DataVisualisation": [
                "Tableau"
            ],
            "CloudComputing": [
                "AWS"
            ],
            "Other": [
                "Machine Learning",
                "Cloud",
                "ML"
            ],
            "EnSoftSkils": [
                "Collaboration"
            ]
        }
    },
    {
        "source": "LinkedIn",
        "company": "FRG Technology Consulting",
        "location": "Paris, √éle-de-France, France",
        "link": "https://fr.linkedin.com/jobs/view/architecte-data-at-frg-technology-consulting-3917370845?position=26&pageNum=0&refId=a5rwPua%2FMvx%2F2M%2FPSF0oPA%3D%3D&trackingId=mFbs%2FJJcyFdi2JyuXmjTDA%3D%3D&trk=public_jobs_jserp-result_search-card",
        "description": "Notre client, entreprise renomm√©e dans le secteur du luxe et des cosm√©tiques, bas√© sur Paris, est √† la recherche de son/sa futur(e) Architecte Data.\nEn tant que membre de la DSI, votre r√¥le est de participer √† la transformation digitale de l‚Äôentreprise, par une meilleure capture, analyse et exploitation des donn√©es clients.\nPrincipales missions :\nAnalyse et r√©ponses aux besoins des m√©tiers (BI, analyses externes, etc.),\nConception de nouveaux mod√®les de donn√©es\nConstruction des pipelines de donn√©es\nTransformation de donn√©es (Pyspark) et le stockage de donn√©es dans le Data Lake / Data Warehouse du Groupe\nRun et le suivi de la TMA\nDescription du profil :\nTitulaire Bac +5 informatique ou dipl√¥me ing√©nieur\n6 ann√©es minimum en expertise Data\nUne bonne ma√Ætrise des outils suivants : Azure, SQL, Snowflake, Databricks, Spark, Python, ELK,..\nUne bonne affinit√© avec les best practices DevOps, CI/CD, unit-testing et m√©thodologies de travail agile\nDes notions en data science sur l‚Äôentra√Ænement, la validation et le d√©ploiement de mod√®les ML supervis√©s et non-supervis√©s serait un plus.\nQualit√©s requises : Bon esprit analytique et de synth√®se, rigoureux, autonome, bonne communication, curieux, force de proposition, vulgarisation des probl√©matiques techniques aupr√®s du m√©tier\nAvantages :\nPackage (variable / participation / int√©ressement) + avantages attractifs\n√âquipe Data √† taille humaine (tr√®s bon accompagnement en interne)\nForte valeur ajout√©e des projets\nT√©l√©travail\nCandidatures confidentielles\nShow more\nShow less",
        "details": {
            "JobDetail": [],
            "TypeContract": "",
            "Salary": "Package",
            "Level": "",
            "Experience": null
        },
        "title": "data architect",
        "skills": {
            "ProgLanguage": [
                "Python"
            ],
            "DataBase": [
                "SQL"
            ],
            "BigData": [
                "Databricks",
                "Spark"
            ],
            "CloudComputing": [
                "Azure"
            ],
            "DBMS": [
                "Snowflake"
            ],
            "Other": [
                "ML",
                "DevOps",
                "CI/CD"
            ],
            "EnSoftSkils": [
                "Communication"
            ]
        }
    },
    {
        "source": "LinkedIn",
        "company": "Ippon Technologies",
        "location": "Lyon",
        "link": "https://fr.linkedin.com/jobs/view/architecte-data-f-h-at-ippon-technologies-3893256404?position=27&pageNum=0&refId=a5rwPua%2FMvx%2F2M%2FPSF0oPA%3D%3D&trackingId=6CvjRcGeId%2FV7kMGgeTUyg%3D%3D&trk=public_jobs_jserp-result_search-card",
        "description": "Qui sommes-nous ?\nIppon\n, c'est l‚Äô√©nergie du collectif au service de la technologie ! Nous sommes un cabinet de conseil et d‚Äôexpertise technique. Nos √©quipes ont pour leitmotive de transformer des id√©es innovantes en solutions logicielles de haute qualit√© avec un focus particulier sur la valeur apport√©e aux utilisateurs.\nCr√©√©e en 2017, l‚Äôagence de Lyon, ce sont des passionn√©s intervenant sur des projets √† forte technicit√© ou en conseil et architecture : Fullstack, Data, DevOps, Cloud, Agile, Design et ne compte pas s‚Äôarr√™ter en si bon chemin !\nLa pluridisciplinarit√©, l‚Äôexpertise, l‚Äô√©coute, l‚Äôadaptabilit√© mais aussi le partage de connaissances fondent notre engagement au service de nos partenariats.\nVous int√©grerez notre Communaut√© Data\n, compos√©e d‚Äôune √©quipe de\n80 experts sur 10 agences en France.\nNotre sp√©cialit√© est de\nconstruire des data platforms dans le Cloud public avec les meilleures technos du moment.\nLa\nData chez Ippon, c‚Äôest d√©j√† plus de\n250 certifications AWS, GCP et AZURE,\ndes\nspeakers √† l‚ÄôAWS Summit, des partenariats avec Snowflake, Databricks, DBT, un blog technique\navec des publications r√©guli√®res.\nCe poste est un vrai challenge aussi bien en termes de\nd√©fis techniques que de gestion d'√©quipe.\nLa\nr√©ussite de vos projets sera port√©e par votre capacit√© √† vous adapter et √† monopoliser un large panel de comp√©tences techniques. Vous devrez √™tre le/la leader de votre √©quipe en gardant √† l‚Äôesprit l‚Äôensemble des\nbonnes pratiques d'architectes\n, de s√©curit√© et d‚Äôautomatisation n√©cessaires √† la r√©ussite du projet. En tant que\nrepr√©sentant(e) de l‚Äôengagement d‚ÄôIppon\nsur les sujets qui vous seront confi√©s, vous serez amen√©(e) √†\ntravailler avec notre √©quipe Commerce d√®s les phases de qualification\net lors de la validation de jalons de la roadmap que vous aurez pr√©alablement valid√© avec le client. Vous interviendrez √©galement dans la s√©lection de l‚Äô√©quipe qui sera affect√©e √† votre projet.\nVotre r√¥le :\n- Gr√¢ce √† votre position d‚Äôarchitecte vous avez une vision experte et syst√©mique de l‚Äôensemble des composants d‚Äôune Modern Data Platform.\n- Vous ma√Ætrisez le panel des exigences fonctionnelles et non fonctionnelles √† collecter afin d‚Äôassurer l‚Äôefficience op√©rationnelle et la p√©rennit√© de la data platform.\n- Vous √™tes expert(e) et ma√Ætrisez tous les outils et services d‚Äôau moins un √©cosyst√®me parmi les 3 principaux leaders du march√© (AWS, Azure et GCP) et avez des facilit√©s pour √©tendre votre champ de comp√©tences.\n- Vous √™tes proactif/ve sur la veille technique et la capitalisation et veillez √† garder toujours un temps d‚Äôavance sur l‚Äô√©tat de l‚Äôart du secteur afin de pouvoir guider vos clients.\n- En tant qu‚Äôarchitecte exp√©riment√©(e) vous pouvez indiff√©remment intervenir sur des missions de delivery pour concevoir la solution cible ou en phase de cadrage amont pour guider les choix et construire les roadmaps.\n- Vous √™tes p√©dagogue et savez communiquer et vulgariser des r√©flexions complexes pour les rendre accessibles √† tous.\nNotre √©co-syst√®me technique :\n- Cloud : AWS, GCP, Azure\n- Langage de programmation data : Python, SQL, Scala\n- Approche Data Warehouse : Redshift, Snowflake, BigQuery\n- Approche Data Lakehouse : Databricks, Starburst, Glue-Athena-S3Ingestion : AWS Glue, Airbyte, dbt Stockage : AWS S3, Google Cloud Storage, Azure Blob Storage\n- Orchestration : Airflow, AWS Step function\n- Gouvernance : cataloging, s√©curit√©, scope d'acc√®sBatch et Streaming : Kafka, Amazon Kinesis, Google DataFlow\n- Outil de visualisation : Tableau, Power BI, Metabase, Superset\nVotre √©volution chez Ippon :\nVous serez accompagn√©(e) dans votre mont√©e en comp√©tences aussi bien technique que leadership gr√¢ce √†\nnotre programme BlackBelt\n(programme de formation continue : mentoring, formations, certifications).\nEn tant que membre d‚Äôune communaut√©,\nvous pouvez avoir diff√©rents r√¥les :\n- Celui de Manager Technique (MT) : manager d‚Äôune √©quipe de 7 ing√©nieur(e)s Ippon (onboarding, suivis, accompagnement, mise en place d‚Äôobjectifs‚Ä¶). Vous conduirez les entretiens techniques en bin√¥me\n- Responsable de l‚Äôaccomplissement d‚Äôune ou plusieurs actions strat√©giques de la CoreTeam Data\n- Devenir speaker lors de Meetup, Summit, Talks internes, aupr√®s des √©coles ‚Ä¶\n- Devenir formateur(trice) et accompagner la nouvelle g√©n√©ration d‚ÄôIppon dans leur mont√©e en comp√©tencesVous avez d‚Äôautres souhaits, pas de soucis, nous en discuterons durant notre √©change et r√©pondrons √† toutes vos questions.\nLes Next Steps :\n1 Echange RH\n1 Echange Technique\n1 Echange avec la Direction\nSi le match est bon des deux c√¥t√©s : Vous vous lancerez sur le tatami Ippon !\nShow more\nShow less",
        "details": {
            "JobDetail": [
                "Full"
            ],
            "TypeContract": "",
            "Salary": "",
            "Level": "",
            "Experience": null
        },
        "title": "data architect",
        "skills": {
            "ProgLanguage": [
                "Scala",
                "Python"
            ],
            "DataBase": [
                "SQL"
            ],
            "BigData": [
                "Databricks"
            ],
            "DataVisualisation": [
                "Power BI",
                "Tableau"
            ],
            "CloudComputing": [
                "GCP",
                "AWS",
                "Azure"
            ],
            "DBMS": [
                "BigQuery",
                "Snowflake"
            ],
            "Automation": [
                "Airflow"
            ],
            "Other": [
                "Cloud",
                "DevOps"
            ],
            "EnSoftSkils": [
                "Leadership"
            ]
        }
    },
    {
        "source": "LinkedIn",
        "company": "Akademija Oxford",
        "location": "Boulogne-Billancourt, √éle-de-France, France",
        "link": "https://fr.linkedin.com/jobs/view/data-analyst-junior-h-f-at-akademija-oxford-3917871112?position=28&pageNum=0&refId=a5rwPua%2FMvx%2F2M%2FPSF0oPA%3D%3D&trackingId=f1yl%2BuAsrVAr6V%2FZJ%2F13UQ%3D%3D&trk=public_jobs_jserp-result_search-card",
        "description": "Notre entreprise partenaire, sp√©cialiste de la vente de m√©dicaments et produits de sant√©, recherche un apprenti Data Analyst (H/F) pr√©parant un bac +4/+5 en fili√®re Big Data pour la rentr√©e de Septembre 2021.\nShow more\nShow less",
        "details": {
            "JobDetail": [],
            "TypeContract": "",
            "Salary": "",
            "Level": "",
            "Experience": null
        },
        "title": "data analyst",
        "skills": {
            "Other": [
                "Big Data"
            ]
        }
    },
    {
        "source": "LinkedIn",
        "company": "FRG Technology Consulting",
        "location": "Paris, √éle-de-France, France",
        "link": "https://fr.linkedin.com/jobs/view/data-architect-azure-at-frg-technology-consulting-3902057360?position=29&pageNum=0&refId=a5rwPua%2FMvx%2F2M%2FPSF0oPA%3D%3D&trackingId=zMsO%2FBb3IByPj0twNDoAAQ%3D%3D&trk=public_jobs_jserp-result_search-card",
        "description": "FRG Consulting recrute pour l'un de ses clients, une soci√©t√© finale renomm√©e dans le secteur du luxe et des cosm√©tiques, un Data Architect expert en Azure. Nich√© au c≈ìur de Paris, vous aurez l'opportunit√© de travailler au sein d'une √©quipe passionn√©e par la recherche et l'innovation, √©voluant dans un environnement stimulant et cr√©atif.\nVos missions captivantes :\nContribuer √† l'√©volution de nos syst√®mes en d√©veloppant de nouveaux connecteurs et pipelines pour l'extraction de donn√©es, qu'il s'agisse de batch (utilisant Sqoop, scripts bash, Java ou des API) ou de streaming (via Kafka, ELK).\nParticiper activement √† la transformation des donn√©es √† l'aide de Pyspark, ainsi qu'au stockage dans notre Data Lake et notre Data Warehouse.\nConcevoir de nouveaux mod√®les de donn√©es et mettre √† disposition des tables ad-hoc sur Snowflake et Impala, r√©pondant ainsi aux besoins m√©tier en termes de BI et d'analyses externes.\nAssurer le bon fonctionnement et le suivi de la TMA du Data Lake, garantissant ainsi la fiabilit√© et la performance de nos syst√®mes.\nProfil recherch√© :\nVous b√©n√©ficiez d'au moins 8 ans d'exp√©rience dans le domaine.\nVous ma√Ætrisez les outils et frameworks de notre stack technique Big Data : Azure, SQL, Snowflake, Databricks, Spark, Python, ELK.\nVous √™tes familier des best practices DevOps, CI/CD, et des m√©thodologies de travail agile.\nDes comp√©tences en data science, notamment sur l'entra√Ænement, la validation et le d√©ploiement de mod√®les ML supervis√©s et non-supervis√©s, seraient grandement appr√©ci√©es.\nLa ma√Ætrise de l'anglais est indispensable pour √©voluer dans un environnement international et dynamique.\nShow more\nShow less",
        "details": {
            "JobDetail": [],
            "TypeContract": "",
            "Salary": "",
            "Level": "",
            "Experience": "8 an(s)"
        },
        "title": "data architect",
        "skills": {
            "ProgLanguage": [
                "Java",
                "Bash",
                "Python"
            ],
            "DataBase": [
                "SQL"
            ],
            "BigData": [
                "Databricks",
                "Spark"
            ],
            "CloudComputing": [
                "Azure"
            ],
            "DBMS": [
                "Snowflake"
            ],
            "Other": [
                "ML",
                "Big Data",
                "DevOps",
                "CI/CD"
            ]
        }
    },
    {
        "source": "LinkedIn",
        "company": "TeamWork Corporate",
        "location": "Saint-Priest, Auvergne-Rh√¥ne-Alpes, France",
        "link": "https://fr.linkedin.com/jobs/view/data-architect-senior-freelance-h-f-at-teamwork-corporate-3916528778?position=30&pageNum=0&refId=a5rwPua%2FMvx%2F2M%2FPSF0oPA%3D%3D&trackingId=K%2BcSw9XhUoNNd0%2BsEaReTg%3D%3D&trk=public_jobs_jserp-result_search-card",
        "description": "Description de l'entreprise\nTeamWork est un acteur majeur du conseil, de l‚Äôint√©gration technologique et de l‚Äôinnovation, implant√© en Europe, en Asie et en Am√©rique du Nord.\nAu travers de ses univers, SAP Business Solutions, Data Analytics, Technology Platform et Salesforce, nous sommes reconnus par nos clients pour accro√Ætre leur performance op√©rationnelle.\nLa transformation digitale est un enjeu majeur pour toute organisation.\nLa n√©cessit√© de digitaliser ses processus, d‚Äôimaginer de nouvelles fa√ßons d‚Äôinteragir avec ses clients, d‚Äôen conqu√©rir de nouveaux et de proposer de nouveaux outils pour anticiper les besoins de pilotage‚ÄØn‚Äôa jamais √©t√© aussi forte.\nL‚Äôunivers Data Analytics de TeamWork accompagne les organisations autour de :\nLa r√©flexion et identification de cas d‚Äôusage pour les transformer en trajectoires moyen et long terme\nLe design et l‚Äôimpl√©mentation de plateforme de donn√©es et des outils p√©riph√©riques (data ingestion/int√©gration)\nLa mise en place des premi√®res solutions‚ÄØd‚ÄôAnalytics (Business Intelligence, EPM,)\nSupport, extension et optimisation des solutions\nDans le cadre du d√©veloppement de ces activit√©s, nous recrutons un\nData Architect Senior (H/F)\nen Freelance pour une mission entre 2 √† 3 mois.\nDescription du poste\nEn tant qu‚ÄôArchitecte Data vous intervenez dans le cadre de projets et missions qui r√©pondent aux enjeux clients d‚Äôexploitation des donn√©es. Vous participez aux phases d‚Äôavant-vente, aux √©tudes d‚Äôarchitecture, et √† la r√©alisation des solutions avec une responsabilit√© d‚Äôencadrement technique des projets (tant sur des forfaits que des missions clients). Vous aurez des missions avec de r√©elles responsabilit√©s et tr√®s diversifi√©es (secteurs d‚Äôactivit√©s vari√©s).\nVos principales missions s‚Äôarticulent autour de :\nL‚Äôanalyse et la qualification des besoins et probl√©matiques ¬´ m√©tiers ¬ª de nos clients\nAssurer la conception, le d√©veloppement et la mise en oeuvre de l'architecture des donn√©es sur la plateforme Databricks\nLa d√©finition et mise en ≈ìuvre des architectures Data adapt√©es aux contextes des projets : Modern Datawarehouse, LakeHouse, DataMesh etc.\nL‚Äôaccompagnement des Consultants et des Ing√©nieurs sp√©cialistes Data sur les projets. Vous ≈ìuvrez √† qualit√© de leurs r√©alisations et des livrables.\nLa collaboration sur tous les domaines d‚Äôactivit√©s DATA : BI, Big Data, IoT, IA\nL‚Äôapport d‚Äôun regard critique et la capacit√© √† conseiller sur le choix des technologies Data\nLa participation √† la d√©finition des bonnes pratiques de mises en ≈ìuvres techniques et la veille √† leurs applications selon les m√©thodes en vigueur (Zero Trust Security, DataOps, Infra-as-Code, Tests automatis√©s etc.)\nQualifications\nTechniques :\nVous avez :\nTr√®s bonnes connaissances de Databricks\nLa capacit√© √† r√©aliser la conception et l‚Äôimpl√©mentation de solutions d‚Äôanalytique √† l‚Äô√©chelle de l‚Äôentreprise ; SQL\nLa connaissance d‚Äôun ou plusieurs outils ETL (Azure Data Factory ou autres) et Data Visualisation (PowerBI par exemple)\nLa capacit√© √† mettre en place une solution Data end-to-end La connaissances des typologies d‚Äôarchitectures (Modern Datawarehouse, LakeHouse ou DataMesh)\nVous connaissez l‚Äôenvironnement Azure, MSBI, SQL Server ou si vous avez des notions dans l‚ÄôIA (Python, R, Machine Learning)\nMaitrise le traitement et l'analyse des donn√©es en Python (Exp√©rience dans la conception et le d√©veloppement de processus ETL/ELT)\nMaitrise d‚Äôoutils de traitement et de stockage distribu√©s parmi Hadoop, Spark, Databricks, Snowflake et/ou Kafka\nConnaissance des bonnes pratiques de conception d‚Äôarchitecture data (s√©curit√©, disponibilit√©, scalabilit√©, confidentialit√©) et des principes d‚Äôune architecture Data Mesh.\nCapacit√© √† concevoir des architectures bas√©es sur les services d‚Äôune plateforme Cloud : AWS ou Azure\nSoft Skills\n:\nVous √™tes proactif et appr√©ciez travailler dans un environnement ambitieux et innovant.\nVous aimez ne pas rester sur vos acquis et toujours apprendre par le biais de formations, votre veille technologique ou encore par la participation aux √©v√©nements communautaires.\nHabitu√© √† travailler aussi bien de fa√ßon autonome qu‚Äô√† collaborer en √©quipe\nConnaissance des m√©thodologies Agile (SCRUM ou autres)\nEnvie d‚Äôapprendre et de partager vos savoir-faire\nCuriosit√©\nLangues :\nFran√ßais (Courant)\nAnglais (A l‚Äôaise en communication orale et √©crite)\nFormation\n:\nV√©ritable passionn√© par la DATA et dipl√¥m√© d‚Äôune √©cole d‚Äôing√©nieur (Bac+3 minimum) ou d'une formation sp√©cifique orient√©e Data avec une exp√©rience significative en Data Engineering et architecture.\nVous avez une exp√©rience de plus de 7 ans en environnement informatique, dont 3 √† 4 ans minimum sur un poste senior en environnement Databricks (Team Lead, Architecte ou encore Consultant Senior).\nNous attacherons davantage d‚Äôimportance √† votre capacit√© √† vouloir apprendre et progresser et votre motivation qu‚Äô√† votre dipl√¥me.\nInformations suppl√©mentaires\nTeamWork, o√π votre √©panouissement professionnel est cl√©. R√©compens√©s par le label 'Great Place to Work 2023', nous pla√ßons l'humain au c≈ìur de notre entreprise.\nAu-del√† des comp√©tences, nous valorisons les personnalit√©s qui partagent nos valeurs de solidarit√© et d'esprit d'√©quipe.\nSi ces principes vous parlent, rejoignez-nous ! Nous sommes d√©di√©s √† l'√©quit√© et √† la diversit√©, ouvrant nos portes √† tous les talents, y compris aux personnes en situation de handicap.\nPostulez et devenez un acteur de notre r√©ussite collective chez TeamWork.\nShow more\nShow less",
        "details": {
            "JobDetail": [
                "Senior"
            ],
            "TypeContract": "",
            "Salary": "",
            "Level": "Bac+3",
            "Experience": "7 an(s)"
        },
        "title": "data architect",
        "skills": {
            "ProgLanguage": [
                "R",
                "Python"
            ],
            "DataBase": [
                "SQL"
            ],
            "DataAnalytics": [
                "R"
            ],
            "BigData": [
                "Databricks",
                "Hadoop",
                "Spark"
            ],
            "CloudComputing": [
                "AWS",
                "Azure"
            ],
            "DBMS": [
                "SQL Server",
                "Snowflake"
            ],
            "Other": [
                "Machine Learning",
                "Cloud",
                "Big Data"
            ],
            "EnSoftSkils": [
                "Teamwork",
                "Communication",
                "Collaboration"
            ]
        }
    },
    {
        "source": "LinkedIn",
        "company": "Airbus",
        "location": "Saint-Nazaire",
        "link": "https://fr.linkedin.com/jobs/view/airbus-atlantic-architecte-data-all-gender-at-airbus-3916426275?position=31&pageNum=0&refId=a5rwPua%2FMvx%2F2M%2FPSF0oPA%3D%3D&trackingId=gQfwmP6313P%2BMZbEabRRXA%3D%3D&trk=public_jobs_jserp-result_search-card",
        "description": "Job Description\nEt si VOTRE aventure avec NOUS commen√ßait ?!\nNous vous proposons de travailler chez Airbus Atlantic, nouveau champion de dimension mondiale, n¬∞2 des a√©rostructures, n¬∞1 des si√®ges pilotes et dans le Top 3 des fauteuils passagers Premium.\nNotre site Airbus Atlantic bas√©\n√† Toulouse (possibilit√© de travailler √† Montoir de Bretagne)\nrecherche son futur\nArchitecte Data (All Gender)\nLe poste d‚Äôarchitecte Data est rattach√© au domaine ¬´ Architecture ¬ª au sein du d√©partement ¬´ Architecture Digital & S√©curit√© ¬ª.\nVous serez en interface avec les architectes du Syst√®me d'Information et les diff√©rents m√©tiers consommateurs des architectures.\nVos Principales Missions Seront Les Suivantes\nFixer les orientations et d√©finir des politiques concernant la mod√©lisation des donn√©es, en collaboration avec les autres architectes,\nCr√©er des mod√®les de donn√©es logiques et physiques en utilisant les meilleures pratiques pour garantir une qualit√© √©lev√©e des donn√©es et une r√©duction de leur redondance,\nInstancier, impl√©menter, construire, tester et maintenir les architectures data d√©finies\nAnalyser, √©valuer, tester et recommander les briques technologiques n√©cessaires pour l‚Äôacquisition, l‚Äôanalyse et l‚Äôimpl√©mentation des donn√©es,\nAnalyser les probl√®mes d'int√©gration des syst√®mes li√©s aux donn√©es et proposer des solutions appropri√©es,\nD√©terminer les ¬´ Data set process ¬ª c‚Äôest √† dire comment les donn√©es sont int√©gr√©es et transform√©es pour qu‚Äôelles soient pr√™tes √† √™tre analys√©es (ex : ETL)\nParticiper aux processus d'extraction performants et qualitatifs des donn√©es des sources requises afin de r√©pondre aux besoins de l'entreprise\nMaintenir les mod√®les de donn√©es conceptuels, logiques et physiques ainsi que les m√©tadonn√©es correspondantes (pour la data gouvernance).\nD√©velopper les meilleures pratiques pour les conventions de d√©nomination standard et les pratiques de codage afin d'assurer la coh√©rence des mod√®les de donn√©es,\nRespecter les normes de s√©curit√© des donn√©es, de contr√¥le des exportations et de protection des donn√©es.\nConstruire les pipelines qui permettront aux Data Scientist/Analysts/Developers de mettre leurs mod√®les en production\nEtre garant de la fiabilit√©, de la qualit√© et de l‚Äôefficacit√© du traitement des donn√©es\nMaintenir les mod√®les cr√©√©s.\nParticiper aux id√©ations et proposer des innovations aux services.\nDocumenter ses activit√©s et mettre √† jour le r√©f√©rentiel documentaire.\nParlons de vous !\nVous disposez d'une\ne\nxp\n√©rience de minimum 5 ans en Data & Informatique sur un poste similaire.\nLes comp√©tences techniques √† d√©tenir pour le poste :\nL‚Äôoptimisation et les standards Qualit√© des donn√©es informatiques\nComprendre et savoir mettre en place les diff√©rentes Structure et stockage de donn√©es\nGestion des probl√®mes li√© √† la donn√©e, l'architecture\nId√©alement, l'exp√©rience des technologies suivantes serait un plus : Ressources & services data MS Azure (Databricks, Azure ML ‚Ä¶), SGBD (SQL, MongoDB, PostGreSQL, redis), Outils ETL (Qlik replicate, Alteryx, ‚Ä¶), Outils BI (PowerBI, Qlik, Grafana ...),\nLangages de programmation (python, SCALA, R, DAX)\nLes certifications de Azure (DP-203, AZ-300, AZ-303, AZ-304, AZ-400, AI-900) seraient un plus,\nVotre Personnalit√©\nFort volont√© de travailler en √©quipe\nBonnes habitudes de documentation\nNiveau avanc√© en Fran√ßais et en Anglais (niveau minimum B1)\nFaire preuve d‚Äôinnovation et √™tre source de proposition\nSavoir exprimer ses id√©es de mani√®re claire et concise\nEtre √† l'√©coute\nParlons de nous !\nEnvironnement & Conditions De Travail\nAirbus Atlantic c‚Äôest aussi :\nPrendre part √† des projets ambitieux, √† la pointe de la technologie pour construire l‚Äôavion de demain, en lien avec les enjeux environnementaux.\nUn environnement qui valorise la proximit√© et la dimension humaine, au sein d‚Äôun collectif engag√© et solidaire.\nL‚Äôopportunit√© d‚Äôapprendre et d‚Äô√©voluer tout au long de votre parcours, en √©tant accompagn√© dans votre d√©veloppement pour une carri√®re sur-mesure.\nAvoir la libert√© d‚Äôentreprendre et de laisser libre court √† vos initiatives.\nSes conditions de travail attractives et ses avantages : restaurant d‚Äôentreprise sur site, CSE (avantages loisirs & famille), parking entreprise, mutuelle d‚Äôentreprise (famille).\nSa politique de diversit√© et d'inclusion : Airbus Atlantic s‚Äôengage en faveur de l‚Äô√©galit√© des chances pour tous.\nSon plan d'actionnariat salari√© et son plan d‚Äô√©pargne salariale.\nNotre Processus De Recrutement\nNous avons √† c≈ìur de mieux vous conna√Ætre et de comprendre ce qui vous motive √† nous rejoindre. Aussi, notre process de recrutement se d√©roule en plusieurs √©tapes apr√®s analyse de votre candidature :\nEntretien vid√©o diff√©r√© via la plateforme Hirevue\nEntretien avec le Manager Recruteur\nEntretien avec le/la Charg√©(e) de Recrutement qui peut √™tre compl√©t√© par un questionnaire de personnalit√©\nEntretien avec le/la Human Resources Business Partner.\nThis job requires an awareness of any potential compliance risks and a commitment to act with integrity, as the foundation for the Company‚Äôs success, reputation and sustainable growth.\nCompany\nAirbus Atlantic\nContract Type\nPermanent\nClasse Emploi (France): Classe G13\nExperience Level\nProfessional\nJob Family\nDigital\nBy submitting your CV or application you are consenting to Airbus using and storing information about you for monitoring purposes relating to your application or future employment. This information will only be used by Airbus.\nAirbus is committed to achieving workforce diversity and creating an inclusive working environment. We welcome all applications irrespective of social and cultural background, age, gender, disability, sexual orientation or religious belief.\nAirbus is, and always has been, committed to equal opportunities for all. As such, we will never ask for any type of monetary exchange in the frame of a recruitment process. Any impersonation of Airbus to do so should be reported to emsom@airbus.com.\nAt Airbus, we support you to work, connect and collaborate more easily and flexibly. Wherever possible, we foster flexible working arrangements to stimulate innovative thinking.\nShow more\nShow less",
        "details": {
            "JobDetail": [],
            "TypeContract": "",
            "Salary": "",
            "Level": "",
            "Experience": "5 an(s)"
        },
        "title": "data architect",
        "skills": {
            "ProgLanguage": [
                "R",
                "Scala",
                "Python"
            ],
            "DataBase": [
                "SQL",
                "MongoDB"
            ],
            "DataAnalytics": [
                "R"
            ],
            "BigData": [
                "Databricks"
            ],
            "CloudComputing": [
                "Azure"
            ],
            "DBMS": [
                "PostgreSQL"
            ],
            "Other": [
                "ML"
            ],
            "EnSoftSkils": [
                "Collaboration"
            ]
        }
    },
    {
        "source": "LinkedIn",
        "company": "Capgemini",
        "location": "Nantes, Pays de la Loire, France",
        "link": "https://fr.linkedin.com/jobs/view/architecte-technique-bi-big-data-nantes-at-capgemini-3803994992?position=32&pageNum=0&refId=a5rwPua%2FMvx%2F2M%2FPSF0oPA%3D%3D&trackingId=fUq1PzQau5f0BciSOTZc7A%3D%3D&trk=public_jobs_jserp-result_search-card",
        "description": "Capgemini\nChoisir Capgemini, c'est choisir une entreprise o√π vous serez en mesure de fa√ßonner votre carri√®re selon vos aspirations, o√π vous serez soutenu et inspir√© par une communaut√© d‚Äôexperts dans le monde entier, o√π vous pourrez r√©√©crire votre futur. Rejoignez-nous pour red√©finir les limites de ce qui est possible, contribuer √† lib√©rer la valeur de la technologie pour les plus grandes organisations et participez √† la construction d‚Äôun monde plus durable et inclusif.\nVos missions :\nInt√©gr√©(e) au sein d'une √©quipe projets intervenant pour des clients dans des secteurs d'activit√©s vari√©es, vous serez notamment en charge des missions suivantes :\nInteragir avec nos clients, nos partenaires pour concevoir et mettre en ≈ìuvre des solutions/projets innovants et comp√©titifs\nR√©pondre aux probl√©matiques de nos clients en proposant la meilleure plateforme data dans un environnement Agile\nAdapter chaque architecture en fonction du contexte gr√¢ce √† votre ma√Ætrise des caract√©ristiques fondamentales de chaque solution (catalogue des offres de services manag√©s, performance, s√©curit√©, d√©ploiement des data centers ‚Ä¶)\nUtiliser les solutions d‚Äôint√©gration associ√©es et les solutions d√©cisionnelles ainsi qu‚Äôanalytiques qui viennent consommer les donn√©es manipul√©es\nEncadrer les √©quipes dans la mise en place des architectures pr√©conis√©es et/ ou des plateformes Data\nVous avez acquis de l‚Äôexp√©rience sur les cadres de r√©f√©rence et patterns d‚Äôarchitecture Data, DevOps.\nVotre profil :\nDipl√¥me d‚Äôing√©nieur ou √©quivalent universitaire\nMinimum 6 ans d'exp√©rience\nAnglais courant\nExpertise dans la conception d‚Äôarchitecture, la mise en ≈ìuvre et/ou le support d‚Äôapplications hautement distribu√©es\nSensibilisation √† la m√©thode devops et connaissance d‚Äôun outil de de Continuous Integration/Continuous Delivery (CI-CD)\nExpertise sur les services Cloud Data suivants (Azure, AWS, GCP)\nGrande aisance dans la communication orale et √©crite, leadership afin de f√©d√©rer des √©quipes\n3 raisons de nous rejoindre :\nQualit√© de vie au travail : accord de t√©l√©travail en France et √† l‚Äôinternational, accord sur l‚Äô√©galit√©\nprofessionnelle, la parentalit√©, l‚Äô√©quilibre des temps et la mobilit√© durable.\nApprentissage en continu : certifications et formations en libre acc√®s, accompagnement sur mesure avec votre carreer manager, parcours d‚Äôint√©gration sur 9 mois.\nAvantages groupe & CSE : plan actionnariat, activit√©s √† tarifs pr√©f√©rentiels, remboursement partiel\nvacances, remboursement de votre abonnement sportif ou culturel.\nNos engagements et priorit√©s :\nLe groupe Capgemini encourage une culture inclusive dans un cadre multiculturel et handi-accueillant. En nous rejoignant, vous int√©grez un collectif qui valorise la diversit√©, d√©veloppe le potentiel de ses talents, s‚Äôengage dans des initiatives solidaires avec ses partenaires, et se mobilise pour r√©duire son impact environnemental sur tous ses sites et aupr√®s de ses clients.\nCapgemini\nCapgemini est un leader mondial, responsable et multiculturel, regroupant pr√®s de 350 000 personnes dans plus de 50 pays. Fort de 55 ans d‚Äôexp√©rience, nous sommes un partenaire strat√©gique des entreprises pour la transformation de leurs activit√©s en tirant profit de toute la puissance de la technologie et des innovations dans les domaines en perp√©tuelle √©volution tels que le cloud, la data, l‚ÄôIntelligence Artificielle, la connectivit√©, les logiciels, l‚Äôing√©nierie digitale ou les plateformes.\nGet The Future You Want* | www.capgemini.com/fr-fr\n*Capgemini, le futur que vous voulez\nShow more\nShow less",
        "details": {
            "JobDetail": [],
            "TypeContract": "",
            "Salary": "",
            "Level": "",
            "Experience": "6 an(s)"
        },
        "title": "data architect",
        "skills": {
            "CloudComputing": [
                "GCP",
                "AWS",
                "Azure"
            ],
            "Other": [
                "Cloud",
                "DevOps"
            ],
            "EnSoftSkils": [
                "Leadership",
                "Communication"
            ]
        }
    },
    {
        "source": "LinkedIn",
        "company": "EXAKIS NELITE",
        "location": "Grenoble, Auvergne-Rh√¥ne-Alpes, France",
        "link": "https://fr.linkedin.com/jobs/view/architecte-conseil-data-h-f-at-exakis-nelite-3813458944?position=33&pageNum=0&refId=a5rwPua%2FMvx%2F2M%2FPSF0oPA%3D%3D&trackingId=hL5G3DbYXckmlMW9KGBYrA%3D%3D&trk=public_jobs_jserp-result_search-card",
        "description": "Exakis Nelite, entit√© du groupe\nMagellan Partners\n, est le\n1er partenaire pure-player Microsoft\nind√©pendant en France avec l‚Äôambition de devenir le premier partenaire Europ√©en et en Afrique Francophone avec sa forte pr√©sence au Maroc.\nN√©s du rapprochement de 2 leaders sp√©cialistes de l‚Äôint√©gration des solutions Microsoft, nous allions expertise technique et fonctionnelle pour r√©pondre concr√®tement aux enjeux de demain : acc√©l√©ration de la transformation digitale,\nCyberS√©curit√©, Intelligence Artificielle, IoT, Data, transformation vers le cloud Azure, Services Cognitifs ‚Ä¶\nEn rejoignant la communaut√© Exakis Nelite dans l‚Äôune de nos 12 agences (680 collaborateurs), vous int√©grerez une √©quipe passionn√©e et impliqu√©e dans les projets les plus innovants. Vous rejoindrez une structure construite autour de valeurs tourn√©es vers ses collaborateurs : intelligence collective, convivialit√© et bienveillance.\nExakis Nelite a re√ßu la certification\nGreat Place to Work\net se place\n3√®me de sa cat√©gorie\nen 2024 parmi les entreprises o√π il fait bon travailler en France !\n√Ä quoi ressembleront vos futures missions ?\nEn tant qu‚ÄôArchitecte et Conseil, dans les domaines Data et Business Intelligence, vous serez amen√© √† travailler sur des projets d‚Äôenvergure mettant √† l‚Äô√©preuve votre exp√©rience des syst√®mes de donn√©es et votre ouverture vers les technologies de BI moderne et cloud.\nVotre r√¥le d‚Äôarchitecte et de conseil aupr√®s de nos clients trouvera son sens dans la comp√©tence que pourrez apporter autour des solutions Microsoft (Power BI, Azure‚Ä¶), et aussi dans la connaissance globale que vous aurez acquise par vos exp√©riences vari√©es. Cette combinaison comp√©tence/exp√©rience aura pour but d‚Äôorchestrer l‚Äôimpl√©mentation des technologies Microsoft dans des syst√®mes d‚Äôinformation et d√©cisionnels technologiquement h√©t√©rog√®nes.\nVotre passion, votre curiosit√© et votre envie sont les ma√Ætres mots pour r√©ussir dans ce poste. Vous √™tes motiv√© pour travailler dans un environnement dynamique o√π la donn√©e se d√©cline autour de nos projets innovants (IoT, Industrie 4.0, IA‚Ä¶). Vous avez une vision claire des enjeux actuels autour de la donn√©e.\nDescription du poste\nSelon les missions vous serez amen√© √† :\nAccompagner nos clients dans leur strat√©gie digitale\nAnimer des ateliers d‚Äôarchitecture technique\nAppr√©hender les besoins fonctionnels et les contraintes techniques du client\nPr√©coniser des architectures complexes pour r√©pondre √† une probl√©matique ou un besoin m√©tier\nD√©finir et am√©liorer les standards, patterns d‚Äôarchitecture et le catalogue de services\nSuperviser et mettre en ≈ìuvre, dans le cadre des projets, les pr√©conisations techniques √©tablies dans le cadre des cahiers des charges\nR√©aliser l‚Äôarchitecture de donn√©es dans des environnements on Premise\nIntervenir sur l‚Äôarchitecture Azure data\nR√©diger les documents associ√©s (HLD, LLD, etc.)\nPiloter des projets et des hommes\nIntervenir en toute autonomie sur les phases de cadrage technique et/ou avant ventes\nAssurer une veille technologique\nProfil\nFort d‚Äôune exp√©rience de 3 √† 15 ans dans les domaines, Data, BI et Big Data, vous portez de l‚Äôint√©r√™t aux technologies du Cloud, aux approches de BI moderne et √† leur d√©veloppement. Vous √™tes un professionnel aguerri des environnements Data, de l‚Äôarchitecture et de l‚Äôutilisation des technologies Cloud.\nLa connaissance des environnements Microsoft (Power BI, SQL Server, Azure‚Ä¶) est un plus mais n‚Äôest pas une obligation. La diversit√© de vos exp√©riences dans le champ d‚Äôactivit√© Data/BI est le facteur clef de succ√®s de ce poste.\nCurieux et dynamique, vous avez le gout du challenge et souhaitez prendre part au d√©veloppement important d‚ÄôExakis Nelite et de Magellan Partners dans le domaine des Data-sciences.\nShow more\nShow less",
        "details": {
            "JobDetail": [],
            "TypeContract": "",
            "Salary": "",
            "Level": "",
            "Experience": "15 an(s)"
        },
        "title": "data architect",
        "skills": {
            "DataBase": [
                "SQL"
            ],
            "DataVisualisation": [
                "Power BI"
            ],
            "CloudComputing": [
                "Azure"
            ],
            "DBMS": [
                "SQL Server"
            ],
            "Other": [
                "Cloud",
                "Big Data"
            ]
        }
    },
    {
        "source": "LinkedIn",
        "company": "SIBIOS",
        "location": "Lyon, Auvergne-Rh√¥ne-Alpes, France",
        "link": "https://fr.linkedin.com/jobs/view/data-architect-manager-at-sibios-3881612188?position=34&pageNum=0&refId=a5rwPua%2FMvx%2F2M%2FPSF0oPA%3D%3D&trackingId=BeZElBp3vNJZRE6yKafYDg%3D%3D&trk=public_jobs_jserp-result_search-card",
        "description": "SIBIOS recherche un consultant Senior DATA / ARCHITECT Manager avec minium 10 ans d'exp√©rience pour un nouveau projet dans le secteur industriel.\nUne bonne connaissance d'architecture fonctionnelle et l'urbanisation data, ainsi que des r√®gles de s√©curit√©.\nVous avez une ma√Ætrise de la gestion des donn√©es et des outils/langages correspondants (SQL, Power BI, mod√©lisation et visualisation des donn√©es, ...)\nDiriger des projets Data sur divers domaines fonctionnels (M√©tier et IT) pour d√©finir les feuilles de route.\nD√©finir la gouvernance de chaque projet et suivre le planning, le budget, la qualit√© et les risques sur chaque projet\nPiloter la gestion du changement et communiquer autour des projets\nIndustrialisation des innovations digitales : gouvernance, socle technique, documentation et support\nPour un entretien imm√©diat, merci de nous faire suivre votre cv mis √° jour en word format ainsi que votre date de disponibilit√© et TJM.\nShow more\nShow less",
        "details": {
            "JobDetail": [
                "Senior"
            ],
            "TypeContract": "",
            "Salary": "",
            "Level": "",
            "Experience": "10 an(s)"
        },
        "title": "data architect",
        "skills": {
            "DataBase": [
                "SQL"
            ],
            "DataVisualisation": [
                "Power BI"
            ]
        }
    },
    {
        "source": "LinkedIn",
        "company": "Darwin Recruitment",
        "location": "Paris, √éle-de-France, France",
        "link": "https://fr.linkedin.com/jobs/view/aws-full-stack-solution-architect-at-darwin-recruitment-3918853578?position=35&pageNum=0&refId=a5rwPua%2FMvx%2F2M%2FPSF0oPA%3D%3D&trackingId=VNRlrafCbgn7Z%2FzxGie1uQ%3D%3D&trk=public_jobs_jserp-result_search-card",
        "description": "Data Cloud Full Stack Solution Architect - 9 Months + extensions\nJob:\nData Cloud Full Stack Solution Architect\nClient Location:\nParis, France\nHybrid structure:\n3 days per week onsite with 2 days remote.\nContract Length:\n9 months + possibility for extensions\nRole and responsibilities:\nAs part of a significant Data Transformation initiative encompassing our entire spectrum of data capabilities-from Data Architecture and Engineering to Data Modelling, Storage for Data & Analytics, Data Visualization, Data Science, Data Integration, Metadata Management, and Data Storage and Warehousing-this role will support the future technical architecture activities of our Data Foundation platform. Key responsibilities include:\nProviding technical guidance and establishing best practices for Snowflake account setup and configuration.\nManaging Infrastructure-as-code to maximize automation and efficiency.\nOverseeing enhancements and deployments to bolster a fully federated Platform.\nServing as the Subject Matter Expert (SME) for all Snowflake-related queries on the project.\nMaintaining platform-specific Snowflake documentation, including decisions, best practices, and features.\nCommunicating and demonstrating new features to relevant stakeholders.\nDesigning the cloud environment comprehensively to ensure alignment with functional and non-functional requirements.\nConducting deployment, maintenance, monitoring, and management tasks.\nOverseeing cloud security for the account.\nFacilitating the integration of new applications into the cloud environment.\nRequirements:\nEducation: Completion of higher education with a degree in Computer Sciences or related field.\nExperience: 5 to 10 years of experience, including a proven track record in implementing Data Platforms in a cloud environment.\nSkills:\nFluency in both French and English (mandatory).\nDeep expertise in Snowflake.\nStrong understanding of platform architecture.\nExperience as a Database Administrator (DBA) and Cloud Database Administrator.\nProficiency in AWS Architecture and cloud networking.\nExcellent communication, coordination, collaboration, stakeholder management, and risk management skills, coupled with strong leadership abilities.\nOpen-mindedness and willingness to tackle challenges.\nHigh motivation, adaptability, and flexibility, with a readiness to integrate into existing environments and project teams.\nIf this role is of interest, please send an up to date CV to\ntaylor.lewis@darwinrecruitment.com\nDarwin Recruitment AG is a Zurich based, SECO licensed, privately owned subsidiary of Darwin Professional Staffing Group Ltd (a Global IT Recruitment Consultancy).\nDarwin Recruitment AG manages client relationships whilst also utilising Darwin Professional Staffing Group databases and networks to source Candidates and fulfil client requests.\nWe do not ask for a placement fee from Candidates/Employees.\nIf you wish to contact a specialist regarding this role, or your job search in general, please contact +41 (0)43 456 29 09\nShow more\nShow less",
        "details": {
            "JobDetail": [
                "Remote",
                "Full"
            ],
            "TypeContract": "",
            "Salary": "",
            "Level": "",
            "Experience": null
        },
        "title": "data architect",
        "skills": {
            "CloudComputing": [
                "AWS"
            ],
            "DBMS": [
                "Snowflake"
            ],
            "Collaboration": [
                "Teams"
            ],
            "Other": [
                "Cloud"
            ],
            "EnSoftSkils": [
                "Leadership",
                "Collaboration",
                "Flexibility",
                "Initiative",
                "Adaptability",
                "Communication"
            ]
        }
    },
    {
        "source": "LinkedIn",
        "company": "Sibylone",
        "location": "Paris, √éle-de-France, France",
        "link": "https://fr.linkedin.com/jobs/view/architecte-data-at-sibylone-3888828561?position=36&pageNum=0&refId=a5rwPua%2FMvx%2F2M%2FPSF0oPA%3D%3D&trackingId=2yYnTKdQk5RoeQD6oXhgJw%3D%3D&trk=public_jobs_jserp-result_search-card",
        "description": "SIBYLONE, soci√©t√© de conseil sp√©cialis√©e dans les syst√®mes d‚Äôinformation de synth√®se et de pilotage, aide ses clients √† tirer toute la valeur de leur patrimoine de donn√©es, levier strat√©gique majeur de d√©veloppement et de rentabilit√©.\nNotre ambition : rendre les diff√©rents acteurs de l‚Äôentreprise autonomes dans l‚Äôexploitation des donn√©es, lib√©rer les usages M√©tier, pour qu‚Äôils soient en mesure de relever les d√©fis de performance, de couverture de risque, de financement, de conqu√™te client, de RSE‚Ä¶ qui s‚Äôimposent √† eux.\nSp√©cialistes reconnus, nos consultants s‚Äôappuient pour cela sur une connaissance approfondie de l‚Äôactivit√© business de nos clients, en lien avec nos trois piliers que sont le M√©tier, la Data et le Projet.\nVos missions\nR√©aliser\nles √©tudes de faisabilit√© technique et proposer une\nmigration vers le Cloud.\nAssister et conseiller\nles √©quipes dans les diff√©rentes √©tapes des projets\nPrendre en charge\nles instructions d‚Äô√©tudes techniques (r√©alisation des livrables correspondant, coordination des contributeurs techniques)\nConstruire\nl‚Äôarchitecture technique et de s√©curit√© des applications concern√©s\nD√©finir et concevoir\nles architectures techniques des projets m√©tiers\nGarantir\nl‚Äôexploitabilit√©, l‚Äô√©volutivit√© et la performance des architectures propos√©es\nCollaborer et animer\nla communaut√© d‚Äôexperts techniques pour d√©finir les bonnes pratiques d‚Äôarchitecture et d‚Äôexploitabilit√© des solutions\nDocumenter et partager\nles modes op√©ratoires suite aux migrations effectu√©es.\nR√©diger et pr√©senter\nles dossiers d‚Äôarchitecture devant les diff√©rents comit√©s de validation\nR√©aliser la veille technologique\nsur les outils et pratiques de d√©veloppement\nAssurer\nla coh√©rence et l‚Äôindustrialisation du SI\nOptimiser\nle design de l‚Äôarchitecture et le dimensionnement des infrastructures en fonction des √©volutions des besoins\nVous √©voluerez dans un environnement technique n√©cessitant une\nbonne ma√Ætrise des architectures n-tiers, des probl√©matiques li√©es au Cloud, des API (Management, REST) et webservices.\nPourquoi pas vous ?\nFormation sup√©rieure Bac +5 en informatique\nExp√©rience r√©ussie de migration de workflow on premise vers le Cloud.\nConnaissances techniques dans certains des domaines suivants : design de blueprint Cloud, architecture de bases de donn√©es, technologies Big Data Analytics, Machine Learning, virtualisation, architecture de stockage, s√©curit√©.\nPremi√®re bonne exp√©rience r√©ussie dans un ou des projets de transformation et de transitions vers le Cloud.\nExp√©rience > 6 ans en conception d‚Äôapplications au sens large\nUne exp√©rience dans un environnement agile est un plus\nLes + Sibylone !\nEvoluer au sein d‚Äôune soci√©t√© qui exige le meilleur de ses collaborateurs tout en cultivant la coh√©sion et l‚Äôesprit d‚Äô√©quipe !\nS‚Äôengager dans une politique RSE exigeante : labellisation Ecovadis\nAvoir un Partenariat EcoTree France : 1 recrutement = 1 arbre plant√© !\nUn Lab RSE ouvert √† tous, pour am√©liorer la qualit√© de vie au travail des collaborateurs et nos engagements environnementaux au sein de SIBYLONE\nContribuer activement au bien-√™tre de ses collaborateurs : participation aux frais d‚Äôabonnements activit√©s ou achat 2 roues\nAvoir de nombreux moments de convivialit√©s : s√©minaires, afterworks, conf√©rences et petits d√©jeuners, sports en groupe via l‚Äôapplication Gymlib\nLes actions et missions solidaires : notre partenariat avec la start-up sp√©cialis√©e en RSE Vendredi permet √† nos collaborateurs de r√©aliser des missions aupr√®s d‚Äôassociations\nDonner une offre de formation innovante et √† la pointe des nouvelles technologies\nAccord de t√©l√©travail en vigueur\nVous vous reconnaissez dans la description du poste ?\nVous souhaitez travailler dans un environnement stimulant et dynamique ?\nVous souhaitez rejoindre une soci√©t√© ambitieuse ?\nVous souhaitez comprendre l‚Äôorigine de Sibylone ?\nVenez-nous rencontrer : Notre Team Talent Acquisition\nsera ravie d‚Äô√©changer avec vous !\nCe poste est ouvert aux personnes en situation de handicap.\nShow more\nShow less",
        "details": {
            "JobDetail": [],
            "TypeContract": "",
            "Salary": "",
            "Level": "",
            "Experience": "6 an(s)"
        },
        "title": "data architect",
        "skills": {
            "Other": [
                "Machine Learning",
                "Cloud",
                "Big Data"
            ]
        }
    },
    {
        "source": "LinkedIn",
        "company": "Airbus",
        "location": "Toulouse, Occitanie, France",
        "link": "https://fr.linkedin.com/jobs/view/airbus-atlantic-architecte-data-all-gender-at-airbus-3916426276?position=37&pageNum=0&refId=a5rwPua%2FMvx%2F2M%2FPSF0oPA%3D%3D&trackingId=qkxCD4D6DkGDb8EneBG3mw%3D%3D&trk=public_jobs_jserp-result_search-card",
        "description": "Job Description\nEt si VOTRE aventure avec NOUS commen√ßait ?!\nNous vous proposons de travailler chez Airbus Atlantic, nouveau champion de dimension mondiale, n¬∞2 des a√©rostructures, n¬∞1 des si√®ges pilotes et dans le Top 3 des fauteuils passagers Premium.\nNotre site Airbus Atlantic bas√©\n√† Toulouse (possibilit√© de travailler √† Montoir de Bretagne)\nrecherche son futur\nArchitecte Data (All Gender)\nLe poste d‚Äôarchitecte Data est rattach√© au domaine ¬´ Architecture ¬ª au sein du d√©partement ¬´ Architecture Digital & S√©curit√© ¬ª.\nVous serez en interface avec les architectes du Syst√®me d'Information et les diff√©rents m√©tiers consommateurs des architectures.\nVos Principales Missions Seront Les Suivantes\nFixer les orientations et d√©finir des politiques concernant la mod√©lisation des donn√©es, en collaboration avec les autres architectes,\nCr√©er des mod√®les de donn√©es logiques et physiques en utilisant les meilleures pratiques pour garantir une qualit√© √©lev√©e des donn√©es et une r√©duction de leur redondance,\nInstancier, impl√©menter, construire, tester et maintenir les architectures data d√©finies\nAnalyser, √©valuer, tester et recommander les briques technologiques n√©cessaires pour l‚Äôacquisition, l‚Äôanalyse et l‚Äôimpl√©mentation des donn√©es,\nAnalyser les probl√®mes d'int√©gration des syst√®mes li√©s aux donn√©es et proposer des solutions appropri√©es,\nD√©terminer les ¬´ Data set process ¬ª c‚Äôest √† dire comment les donn√©es sont int√©gr√©es et transform√©es pour qu‚Äôelles soient pr√™tes √† √™tre analys√©es (ex : ETL)\nParticiper aux processus d'extraction performants et qualitatifs des donn√©es des sources requises afin de r√©pondre aux besoins de l'entreprise\nMaintenir les mod√®les de donn√©es conceptuels, logiques et physiques ainsi que les m√©tadonn√©es correspondantes (pour la data gouvernance).\nD√©velopper les meilleures pratiques pour les conventions de d√©nomination standard et les pratiques de codage afin d'assurer la coh√©rence des mod√®les de donn√©es,\nRespecter les normes de s√©curit√© des donn√©es, de contr√¥le des exportations et de protection des donn√©es.\nConstruire les pipelines qui permettront aux Data Scientist/Analysts/Developers de mettre leurs mod√®les en production\nEtre garant de la fiabilit√©, de la qualit√© et de l‚Äôefficacit√© du traitement des donn√©es\nMaintenir les mod√®les cr√©√©s.\nParticiper aux id√©ations et proposer des innovations aux services.\nDocumenter ses activit√©s et mettre √† jour le r√©f√©rentiel documentaire.\nParlons de vous !\nVous disposez d'une\ne\nxp\n√©rience de minimum 5 ans en Data & Informatique sur un poste similaire.\nLes comp√©tences techniques √† d√©tenir pour le poste :\nL‚Äôoptimisation et les standards Qualit√© des donn√©es informatiques\nComprendre et savoir mettre en place les diff√©rentes Structure et stockage de donn√©es\nGestion des probl√®mes li√© √† la donn√©e, l'architecture\nId√©alement, l'exp√©rience des technologies suivantes serait un plus : Ressources & services data MS Azure (Databricks, Azure ML ‚Ä¶), SGBD (SQL, MongoDB, PostGreSQL, redis), Outils ETL (Qlik replicate, Alteryx, ‚Ä¶), Outils BI (PowerBI, Qlik, Grafana ...),\nLangages de programmation (python, SCALA, R, DAX)\nLes certifications de Azure (DP-203, AZ-300, AZ-303, AZ-304, AZ-400, AI-900) seraient un plus,\nVotre Personnalit√©\nFort volont√© de travailler en √©quipe\nBonnes habitudes de documentation\nNiveau avanc√© en Fran√ßais et en Anglais (niveau minimum B1)\nFaire preuve d‚Äôinnovation et √™tre source de proposition\nSavoir exprimer ses id√©es de mani√®re claire et concise\nEtre √† l'√©coute\nParlons de nous !\nEnvironnement & Conditions De Travail\nAirbus Atlantic c‚Äôest aussi :\nPrendre part √† des projets ambitieux, √† la pointe de la technologie pour construire l‚Äôavion de demain, en lien avec les enjeux environnementaux.\nUn environnement qui valorise la proximit√© et la dimension humaine, au sein d‚Äôun collectif engag√© et solidaire.\nL‚Äôopportunit√© d‚Äôapprendre et d‚Äô√©voluer tout au long de votre parcours, en √©tant accompagn√© dans votre d√©veloppement pour une carri√®re sur-mesure.\nAvoir la libert√© d‚Äôentreprendre et de laisser libre court √† vos initiatives.\nSes conditions de travail attractives et ses avantages : restaurant d‚Äôentreprise sur site, CSE (avantages loisirs & famille), parking entreprise, mutuelle d‚Äôentreprise (famille).\nSa politique de diversit√© et d'inclusion : Airbus Atlantic s‚Äôengage en faveur de l‚Äô√©galit√© des chances pour tous.\nSon plan d'actionnariat salari√© et son plan d‚Äô√©pargne salariale.\nNotre Processus De Recrutement\nNous avons √† c≈ìur de mieux vous conna√Ætre et de comprendre ce qui vous motive √† nous rejoindre. Aussi, notre process de recrutement se d√©roule en plusieurs √©tapes apr√®s analyse de votre candidature :\nEntretien vid√©o diff√©r√© via la plateforme Hirevue\nEntretien avec le Manager Recruteur\nEntretien avec le/la Charg√©(e) de Recrutement qui peut √™tre compl√©t√© par un questionnaire de personnalit√©\nEntretien avec le/la Human Resources Business Partner.\nThis job requires an awareness of any potential compliance risks and a commitment to act with integrity, as the foundation for the Company‚Äôs success, reputation and sustainable growth.\nCompany\nAirbus Atlantic\nContract Type\nPermanent\nClasse Emploi (France): Classe G13\nExperience Level\nProfessional\nJob Family\nDigital\nBy submitting your CV or application you are consenting to Airbus using and storing information about you for monitoring purposes relating to your application or future employment. This information will only be used by Airbus.\nAirbus is committed to achieving workforce diversity and creating an inclusive working environment. We welcome all applications irrespective of social and cultural background, age, gender, disability, sexual orientation or religious belief.\nAirbus is, and always has been, committed to equal opportunities for all. As such, we will never ask for any type of monetary exchange in the frame of a recruitment process. Any impersonation of Airbus to do so should be reported to emsom@airbus.com.\nAt Airbus, we support you to work, connect and collaborate more easily and flexibly. Wherever possible, we foster flexible working arrangements to stimulate innovative thinking.\nShow more\nShow less",
        "details": {
            "JobDetail": [],
            "TypeContract": "",
            "Salary": "",
            "Level": "",
            "Experience": "5 an(s)"
        },
        "title": "data architect",
        "skills": {
            "ProgLanguage": [
                "R",
                "Scala",
                "Python"
            ],
            "DataBase": [
                "SQL",
                "MongoDB"
            ],
            "DataAnalytics": [
                "R"
            ],
            "BigData": [
                "Databricks"
            ],
            "CloudComputing": [
                "Azure"
            ],
            "DBMS": [
                "PostgreSQL"
            ],
            "Other": [
                "ML"
            ],
            "EnSoftSkils": [
                "Collaboration"
            ]
        }
    },
    {
        "source": "LinkedIn",
        "company": "E.Leclerc",
        "location": "Ivry-sur-Seine, √éle-de-France, France",
        "link": "https://fr.linkedin.com/jobs/view/lead-data-architect-h-f-at-e-leclerc-3688059702?position=38&pageNum=0&refId=a5rwPua%2FMvx%2F2M%2FPSF0oPA%3D%3D&trackingId=m6aEKnUwuFaLecnTTcpZRA%3D%3D&trk=public_jobs_jserp-result_search-card",
        "description": "Description\nAu sein de la Direction Support et Organisation, la DSI est compos√©e de 5 services :\nService Solutions Finance & Qualit√©,\nService Solutions Client,\nService Solutions Offre,\nService Support Utilisateurs,\nService TECH,\nLe Service TECH a Pour Mission\nD‚Äôanimer les constructions strat√©giques SI et technologies,\nD‚Äôexplorer et d‚Äôinnover en technologie,\nDe fournir et d‚Äôop√©rer des infrastructures s√©curis√©es,\nD‚Äôapporter de l‚Äôexpertise aux d√©veloppeurs,\nD‚Äôop√©rer la s√©curit√©,\nNous recherchons pour le Service Tech un(e) Lead Data Architect.\nLe Lead Data Architect est responsable de la conception et de la gestion de l'architecture des donn√©es sur la plateforme GCP. Son r√¥le consiste √† d√©finir l'architecture des donn√©es, √† √©tablir les normes, standards et les bonnes pratiques de d√©veloppement des traitements de donn√©es. Il/elle collabore aussi √©troitement avec les √©quipes de Data Architects et de Data Engineers de l‚Äôint√©grateur ainsi qu‚Äôavec les architectes Cloud GCP afin de s‚Äôassurer que les solutions de traitement des donn√©es mises en place sur la plateforme soient robustes, scalables et s√©curis√©es. Enfin, il/elle encadre fonctionnellement une √©quipe interne constitu√©e d‚Äôun Data Architect et de deux Data Engineers.\nRattach√©(e) au Responsable D√©veloppement, vos responsabilit√©s sont les suivantes :\nConception de l'architecture des donn√©es : D√©finir l'architecture des donn√©es et des traitements de donn√©es en tenant compte des besoins fonctionnels et non fonctionnels, des exigences de performance, de scalabilit√©, de s√©curit√© et de conformit√©. Concevoir des mod√®les et des pipelines de donn√©es en s‚Äôappuyant sur DBT ;\nS√©lection et configuration des services GCP : √âvaluer et s√©lectionner les services et les outils de GCP tels que BigQuery, Cloud Storage, Composer, Pub/Sub, etc. les mieux adapt√©s aux besoins de chaque usage m√©tier.\nGestion des donn√©es : Concevoir les solutions pour la gestion des donn√©es en streaming et en batch. √âtablir et maintenir les normes, les standards et les bonnes pratiques de d√©veloppement en s‚Äôappuyant sur l‚Äôint√©grateur. Contribuer √† la mise en place et √† la maintenance des pipelines de donn√©es pour la collecte, le traitement et l'analyse des donn√©es. Assister et supporter les Data Engineers dans cette t√¢che ;\nS√©curit√© et gouvernance des donn√©es : D√©finir des m√©canismes de s√©curit√© et de gouvernance des donn√©es sur GCP pour garantir la confidentialit√©, l'int√©grit√© et la conformit√© r√©glementaire (RGPD). D√©finir les contr√¥les d'acc√®s, les politiques de s√©curit√© des donn√©es et les m√©canismes de tra√ßabilit√© √† mettre en ≈ìuvre ;\nIndustrialisation et d√©ploiement : Mettre en place des pipelines CI/CD pour automatiser le d√©ploiement, les tests, et la gestion des d√©veloppements. Automatiser la cr√©ation et la configuration des ressources sur GCP n√©cessaires en utilisant l‚ÄôIaC/Terraform pour d√©finir et g√©rer l'infrastructure de mani√®re programmable et reproductible ;\nCollaboration avec les √©quipes : Travailler en √©troite collaboration avec les √©quipes de l‚Äôint√©grateur (Data Architects et Data Engineers), les squads big data pour proposer les solutions techniques adapt√©es aux besoins des m√©tiers et assurer la mise en ≈ìuvre r√©ussie des projets data sur GCP ;\nVeille technologique : Rester √† jour sur les derni√®res avanc√©es technologiques et les tendances du march√© sur GCP et autres. √âvaluer et recommander de nouvelles solutions ou des am√©liorations aux solutions existantes.\nProfil\nVous √™tes issu(e) de formation sup√©rieure en statistiques/marketing/informatique et vous justifiez d'une exp√©rience significative en tant que data architect sur Google Cloud Platform (GCP). Vous avez de solides comp√©tences en conception de pipelines de donn√©es et en mod√©lisation de bases de donn√©es structur√©es et non structur√©es. Vous avez une connaissance approfondie des services GCP, tels que BigQuery, Cloud Storage, Cloud Composer, Pub/Sub, etc et des frameworks de d√©veloppement tels que DBT.\nVous avez une exp√©rience pratique en DevOps, CI/CD, avec une bonne compr√©hension des principes et des pratiques de g√©nie logiciel (Azure DevOps, Jenkins, GitLab,..). Vous avez une connaissance de l'IaC (Infrastructure as Code) et utilisation d'outils tels que Terraform. Vous avez une compr√©hension des r√©glementations relatives √† la protection des donn√©es et de la confidentialit√©, telles que le RGPD.\nVous avez une exp√©rience en encadrement d‚Äô√©quipes techniques.\nDot√©(e) d'une grande aisance relationnelle, vous avez le sens de l'√©coute et de la diplomatie. Vous √™tes rigoureux(se), vous avez un bon sens relationnel, une bonne capacit√© de communication et r√©dactionnelle.\nEnfin, vous avez une capacit√© √† vous maintenir √† jour sur les technologies data.\nNous recherchons des personnalit√©s dynamiques, sachant prendre des initiatives et qui souhaitent s‚Äôimpliquer dans les √©volutions de notre secteur et du mouvement. Il est important que nos candidats d√©montrent un r√©el engagement, des valeurs communes aux valeurs fortes port√©es par le mouvement Leclerc depuis sa fondation.\nEn rejoignant le Galec, vous pourrez valoriser et d√©montrer votre potentiel, d√©velopper vos comp√©tences et acqu√©rir une exp√©rience enrichissante, √† travers des passerelles entre les diff√©rents march√©s et entit√©s du Mouvement !\nEnvie de challenge ? Vous souhaitez tenter l'aventure dans un univers dynamique, enrichissant, au plus pr√®s des entrepreneurs ?\nMieux nous connaitre\nLe Mouvement E.LECLERC est un groupement coop√©ratif dont les adh√©rents sont les propri√©taires de magasins, soit 592 entrepreneurs, dont Michel-Edouard Leclerc est le porte-parole. Le Mouvement E.leclerc compte 133 000 collaborateurs, qui travaillent collectivement √† la r√©ussite de nos 721 magasins (hypers, supers et express), 690 Drives et 2 541 enseignes sp√©cialis√©es.\nLe Galec est l'entit√© au c≈ìur du syst√®me, c'est m√™me le r√©acteur ! Le Galec conjugue les talents d‚Äôune √©quipe de plus de 824 collaborateurs qui travaillent ensemble au service du front de vente omnicanal de l‚ÄôEnseigne, c‚Äôest-√†-dire les hyper/supermarch√©s, les magasins sp√©cialis√©s, le drive, le site marchand E.Leclerc et E.Leclerc relais.\nShow more\nShow less",
        "details": {
            "JobDetail": [],
            "TypeContract": "",
            "Salary": "",
            "Level": "",
            "Experience": null
        },
        "title": "data architect",
        "skills": {
            "CloudComputing": [
                "GCP",
                "Google Cloud Platform",
                "Azure"
            ],
            "DevTools": [
                "Jenkins"
            ],
            "DBMS": [
                "BigQuery"
            ],
            "InfrastructureAsCode": [
                "Terraform"
            ],
            "Other": [
                "CI/CD",
                "Big Data",
                "Statistiques",
                "Cloud",
                "DevOps"
            ],
            "EnSoftSkils": [
                "Communication",
                "Collaboration"
            ]
        }
    },
    {
        "source": "LinkedIn",
        "company": "PROPULSE IT",
        "location": "Massy, √éle-de-France, France",
        "link": "https://fr.linkedin.com/jobs/view/architecte-data-power-bi-azure-at-propulse-it-3902536487?position=39&pageNum=0&refId=a5rwPua%2FMvx%2F2M%2FPSF0oPA%3D%3D&trackingId=XOow3ZIRcrdBggn90nLaPw%3D%3D&trk=public_jobs_jserp-result_search-card",
        "description": "PROPULSE IT accompagne ses clients grands comptes et PME dans la mise en ≈ìuvre des projets It et digitaux.\nPROPULSE IT est un r√©seau de consultants √† forte valeur ajout√©e, compl√®tement associ√© √† notre d√©marche qualit√© de suivi des besoins et projets de nos clients.\nA ce jour, le r√©seau de freelance PROPULSE IT comporte plus de 18000 consultants sur toute la France, et couvre l'ensemble des besoins IT et digitaux.\nEn constituant ce r√©seau par cooptation de clients ou de consultants, nous avons privil√©gi√© la constance dans le savoir-faire technique et le savoir-√™tre, pour devenir un v√©ritable partenaire privil√©gi√© de nos clients.\nParall√®lement, nous avons d√©velopp√© un r√©seau de partenaires s√©lectionn√©es pour leur expertise technique, et l'adh√©sion aux valeurs de notre entreprise.\nAujourd'hui PROPULSE IT est une soci√©t√© en pleine croissance organique, Champion de la Croissance du journal Les Echos 4 ann√©es cons√©cutives.\nCe d√©veloppement s'appuie sur la qualit√© et la p√©rennit√© des missions r√©alis√©es.\nLa satisfaction client est ainsi li√©e √† l'√©panouissement des consultants !\nAlors, n'h√©sitez pas √† postuler !\nLe Poste\nNous recherchons un(e) DATA ARCHITECTE POWER BI / AZURE\nDans le respect de la strat√©gie IT √©tablie par le DSI, votre mission consiste √† :\nResponsabilit√©s\nAnalyser les besoins fonctionnels.\nLocaliser les donn√©es de production.\nD√©terminer les sp√©cifications techniques.\nD√©finir l'architecture.\nMod√©liser les datawarehouse (entrep√¥ts de donn√©es) et les datamarts (magasins de donn√©es) d√©di√©s √† une fonction particuli√®re dans l'entreprise.\nAccompagner le client dans la r√©alisation du projet.\nMaintenir les sources de donn√©es √† jour\nMettre √† disposition les donn√©es aux m√©tiers\nSuperviser les flux de donn√©es et en contr√¥ler l'int√©grit√©\nProfil\nStack Technique :\nPower BI / DAX / Langage M\nAzure Data Factory\nAzure Synapse\nData Lake, Logical Datawarehouse\nMicrosoft Fabric\nInt√©gration et la livraison continue (CI/CD)\nSavoir-faire\nRigueur\nShow more\nShow less",
        "details": {
            "JobDetail": [],
            "TypeContract": "",
            "Salary": "",
            "Level": "",
            "Experience": null
        },
        "title": "data architect",
        "skills": {
            "DataVisualisation": [
                "Power BI"
            ],
            "CloudComputing": [
                "Azure"
            ],
            "Other": [
                "CI/CD"
            ]
        }
    },
    {
        "source": "LinkedIn",
        "company": "Fieldbox",
        "location": "Bordeaux, Nouvelle-Aquitaine, France",
        "link": "https://fr.linkedin.com/jobs/view/cloud-solution-architect-paris-bordeaux-remote-at-fieldbox-3881559118?position=40&pageNum=0&refId=a5rwPua%2FMvx%2F2M%2FPSF0oPA%3D%3D&trackingId=BfoYE0VTuCfRtXGAWXoRVg%3D%3D&trk=public_jobs_jserp-result_search-card",
        "description": "Our business:\nWe help industrial companies to accelerate their digital transformation and dramatically improve their operational efficiency and competitiveness with data, software and AI. Our clients include CAC 40 companies, as well as small and medium-sized companies on five continents and over 150 industrial sites.\nWhat makes us special:\nWe offer a complete range of services, combined with the use of latest technologies, covering the entire lifecycle of data-driven solutions, from ideation, business value assessment, industrialized solution development, to deployment, run and scale.\nOur positioning:\nWe seek long term partnership-relation with our clients. We can help them define their digital strategy and AI roadmap, build & run a solution, train, and transfer skills, set up and professionalize R&D or innovation units or digital & AI factories.\nOur teams:\nA virtuous combination of three areas of expertise:\nBusiness expertise: industrial operations & engineering.\nTechnical expertise: data science, software engineering & devops.\nDelivery management expertise: managing digital projects and setting digital factories.\nYour missions:\nAs a Cloud Architect,you will design and participate in the implementation of cloud solutions to support the digital transformation of our clients. You will work in agile mode, in an international context, on industrial projects.\nYour main missions :\nSupport pre-sales technical activities by translating client‚Äôs requirements into state-of-the-art architectures, while guiding customers through their digital transformation journey in the cloud :\nLead workshops to study and define customer requirements\nImagine and define the architecture that would best meet the specifications provided while taking in account the financial and security constraints of the client.\nHandle and resolve technical questions and challenges encountered by clients during the first phases of their projects\nDefine deployment methodologies and integration of the solution into the existing client‚Äôs ecosystem.\nParticipate in pre-sales meeting with clients to present the envisioned architectures\nLead end-to-end architecture projects (web applications, data engineering & processing pipelines) involving intensive use of industrial data, with a focus on performance, scalability and security issues\nSupervise the deployment and industrialization of the target architectures\nEnsure the security and reliability of deployed environments\nWork in collaboration with multidisciplinary teams, including DevOps, back-end, front-end, data, product and business skills to make every project a success.\nExperience and skills required:\nAt least 2 years' experience in Architect or tech lead full stack role\nYou have experience with the following technologies:\nCloud: Azure, Google Cloud, AWS, OVH\nDatabases & storage : PostgreSQL, TimeScaleDB, Redis, InfluxDB, S3 and alike\nProcessing and scheduling: Azure Data Factory, Azure Functions, Azure Synapse, Airflow, Argo, AWS Batch, AWS Step\nStreaming: Kafka, RabbitMQ, Kinesis, SQS\nDevops: Docker, Kubernetes\nMoreover :\nYou have proven experience in cloud or hybrid architectures\nYou love architecture diagrams ! (Excalidraw, Draw.io)\nYou demonstrate technical leadership and are able to communicate complex ideas effectively.\nYou know how to challenge customer requirements and Fieldbox objectives in order to optimize the proposed architecture.\nYou successfully manage the complex constraints of a production application through analysis and resolution.\nYou are customer and solution-oriented and have excellent interpersonal skills.\nFluency in English\nKnowledge of an industrial sector is a plus\nKnowledge in python is a plus\nAdvantage and benefits:\nFull remote possible (Metropolitan France only)\nWhat about our offices\nBordeaux: meet with your colleagues in a peaceful and calm space with an amazing view on ‚ÄúLes bassins √† flots‚Äù\nParis: enjoy a coworking space on the top of the Montparnasse tower with a 360 view of Paris\nWhat about our values :\nJoin a company which values care where everyone is in position to reach their full potential\nYou will work within an energetic team with a strong technical skill. Weekly engineering are organized every week to present and discuss technical topics\nCreate immediate impact on the company\nA quiz is sent every month in order to improve your comfort at work\nFun Activity:\nAfterwork every month with different theme ( bowling , board game , darts, beers bar, etc. )\nLunch break : outside lunchs, board game parties, and sport! (running, badminton, darts, yoga)\nCTFs\nTypical process includes 3 steps :\nHR interview\nInterview with operational team, aiming at testing your fit to the specific job,\nInterview with one or several founders to validate the application\nShow more\nShow less",
        "details": {
            "JobDetail": [
                "Remote",
                "Full"
            ],
            "TypeContract": "",
            "Salary": "",
            "Level": "",
            "Experience": null
        },
        "title": "data architect",
        "skills": {
            "ProgLanguage": [
                "R",
                "Python"
            ],
            "DataAnalytics": [
                "R"
            ],
            "CloudComputing": [
                "AWS",
                "Azure"
            ],
            "DevTools": [
                "Docker"
            ],
            "DBMS": [
                "PostgreSQL"
            ],
            "Automation": [
                "Airflow",
                "Kubernetes"
            ],
            "Containers": [
                "Docker",
                "Kubernetes"
            ],
            "Collaboration": [
                "Teams"
            ],
            "Other": [
                "Cloud",
                "DevOps"
            ],
            "EnSoftSkils": [
                "Leadership",
                "Interpersonal Skills",
                "Collaboration"
            ]
        }
    },
    {
        "source": "LinkedIn",
        "company": "Amadeus",
        "location": "Nice, Provence-Alpes-C√¥te d'Azur, France",
        "link": "https://fr.linkedin.com/jobs/view/data-architect-at-amadeus-3796958716?position=41&pageNum=0&refId=a5rwPua%2FMvx%2F2M%2FPSF0oPA%3D%3D&trackingId=ljKoPwTz1epZhroaEEkg%2Fw%3D%3D&trk=public_jobs_jserp-result_search-card",
        "description": "Job Title\nData Architect\nDigital Transformation Services (DTS) Is Committed To Drive Positive Change In Amadeus By Assembling, Leveraging, And Managing Digital And Transformation Services To Internal Customers Along Two Service Areas, Business Transformation Services And Enterprise Digital Services, Aiming To\nSpeed up and simplify business agility, value perception and compliance.\nGrow business value guided by the Amadeus Evolution Principles.\nDeliver end-to-end services and transformation programs to Amadeus.\nEngage, empower and develop a global team, proficient and engaged and nurturing our culture.\nDTS Solutions Architects and IBS Engineering Principal Specialists drive activities of developing a direction for managing a suit of solutions -including systems (applications and underlying IT stacks), processes and information, shared infrastructure services, and shared application services and components- in order to better match business requirements.\nAs such, DTS Solutions Architects act as leaders, with deep understanding of business goals, processes and enterprise architecture, to conceptualize and assemble technology solution architecture‚Äôs designs. These designs optimize the response to business needs (i.e.: cost, time to market, usability, continuity, etc.), while ensuring and improving architecture consistency.\nIn This Role You‚Äôll / Your Main Responsibilities\nAs a Data Architect, you will play a crucial role in shaping and optimizing our organization's data infrastructure. You will be responsible for designing, implementing, and maintaining scalable and efficient data solutions that meet business needs. This role requires a deep understanding of data management, database technologies, and a strategic mindset to align data architecture with overall business strategies.\nKey Responsibilities\nData Modeling and Design:\nDevelop and maintain conceptual, logical, and physical data models.\nDesign data structures and relationships that support business requirements and enable efficient data retrieval.\nDatabase Management:\nSelect and implement appropriate database technologies based on project requirements.\nOptimize database performance and ensure data integrity.\nData Governance:\nEstablish and enforce data governance policies and procedures.\nDefine data standards, naming conventions, and data quality rules.\nData Integration:\nDesign and implement data integration solutions to ensure seamless flow of information across systems.\nCollaborate with other IT teams to integrate data sources and maintain data consistency.\nCollaboration and Communication:\nWork closely with business stakeholders to understand their data needs and translate them into effective data solutions.\nCollaborate with cross-functional teams including data scientists, analysts, and developers.\nSecurity and Compliance:\nImplement data security measures to protect sensitive information.\nEnsure compliance with data privacy regulations and industry standards.\nUse and leverage new technology solutions, to enable the organization's future-state business capabilities, facilitating and orchestrating the delivery of targeted business outcomes.\nProvide leadership, analysis and design tasks related to the development or upgrade of a solution to ensure application provides expected business value.\nProvide architecture guidance and support on activities performed to maintain, improve or support applications.\nAbout The Ideal Candidate\nBachelor's or Master's degree in Computer Science, Information Technology, or related field.\nProven experience as a Data Architect or in a similar role.\nStrong knowledge of database management systems, data warehousing, and data modeling techniques.\nProficiency in SQL and other query languages.\nFamiliarity with middleware, cloud-based data platforms and big data technologies.\nUnderstanding of agile methods and processes, and capability of supporting agile project teams.\nAnalytical and strategic thinking.\nExcellent communication and collaboration skills.\nProblem-solving and troubleshooting abilities.\nStay updated on emerging trends and technologies in data management.\nWhat we can offer you\nAn Extensive Range Of Benefits Including\nYou will be part of a multi-cultural team with international scope.\nYou will benefit from a permanent contract and a competitive employee benefits package such as pension plan, travel, life and healthcare insurance as well as lunch allowance.\nSkill development and career path.\nExperience in one of the world‚Äôs top IT companies.\nYou will be based in our Nice office (Hybrid Model, 3 days office 2 days work from home).\nApplication process\nThe application process takes no longer than 10 minutes! Create your candidate profile, upload your CV and apply. Once we‚Äôve received your application, one of our recruiters may get in touch with you to arrange a telephone interview.\nAre you the one we‚Äôre looking for? Apply now!\nDiversity & Inclusion\nWe are an Equal Opportunity Employer and seek to hire the best candidate regardless of age, beliefs, disability, ethnicity, gender or sexual orientation.\nShow more\nShow less",
        "details": {
            "JobDetail": [],
            "TypeContract": "",
            "Salary": "3",
            "Level": "",
            "Experience": null
        },
        "title": "data architect",
        "skills": {
            "DataBase": [
                "SQL"
            ],
            "Collaboration": [
                "Teams"
            ],
            "Other": [
                "Cloud",
                "Big Data"
            ],
            "EnSoftSkils": [
                "Leadership",
                "Communication",
                "Organization",
                "Collaboration"
            ]
        }
    },
    {
        "source": "LinkedIn",
        "company": "Capgemini",
        "location": "Toulouse, Occitanie, France",
        "link": "https://fr.linkedin.com/jobs/view/architecte-big-data-cloud-toulouse-at-capgemini-3810332150?position=42&pageNum=0&refId=a5rwPua%2FMvx%2F2M%2FPSF0oPA%3D%3D&trackingId=d9gP0d9GUsgTzuxm6aSX1w%3D%3D&trk=public_jobs_jserp-result_search-card",
        "description": "Capgemini en quelques mots\nChoisir Capgemini, c'est choisir une entreprise o√π vous serez en mesure de fa√ßonner votre carri√®re selon vos aspirations, o√π vous serez soutenu et inspir√© par une communaut√© d‚Äôexperts dans le monde entier, o√π vous pourrez r√©√©crire votre futur. Rejoignez-nous pour red√©finir les limites de ce qui est possible, contribuer √† lib√©rer la valeur de la technologie pour les plus grandes organisations et participez √† la construction d‚Äôun monde plus durable et inclusif.\nVos missions\nVous int√©grez une communaut√© d‚Äôexperts passionn√©s reconnus par nos clients sur des technologies de pointe (Google Cloud Platform, Azure, AWS)\nVous interagissez au plus proche de nos clients, des partenaires pour concevoir et mettre en ≈ìuvre des solutions/projets innovants et comp√©titifs\nVous r√©pondez aux probl√©matiques de nos clients en proposant la meilleure plateforme data dans un environnement Agile\nVous avez acquis de l‚Äôexp√©rience sur les cadres de r√©f√©rence et patterns d‚Äôarchitecture Data, DevOps\nVous adaptez chaque architecture en fonction du contexte gr√¢ce √† votre maitrise des caract√©ristiques fondamentales de chaque solution (catalogue des offres de services manag√©s, performance, s√©curit√©, d√©ploiement des data centers ‚Ä¶)\nVous utilisez les solutions d‚Äôint√©gration associ√©es et les solutions d√©cisionnelles ainsi qu‚Äôanalytiques qui viennent consommer les donn√©es manipul√©es\nVous √™tes en mesure d‚Äôencadrer les √©quipes dans la mise en place des architectures pr√©conis√©es et/ ou des plateformes Data\nVotre profil\nDe formation Bac + 5 en √©cole d‚Äôing√©nieur ou √©quivalent universitaire\nAu moins 6 ans d‚Äôexp√©rience\nBon niveau d'anglais\nQualit√©s de p√©dagogue, transmission de comp√©tences\nLa phase d'avant-vente vous int√©resse\n3 raisons de nous rejoindre\nQualit√© de vie au travail :\naccord de t√©l√©travail en France et √† l‚Äôinternational, accord sur l‚Äô√©galit√©\nprofessionnelle, la parentalit√©, l‚Äô√©quilibre des temps et la mobilit√© durable.\nApprentissage en continu :\ncertifications et formations en libre acc√®s, accompagnement sur mesure avec\nvotre carreer manager, parcours d‚Äôint√©gration sur 9 mois.\nAvantages groupe & CSE :\nplan actionnariat, activit√©s √† tarifs pr√©f√©rentiels, remboursement partiel\nvacances, remboursement de votre abonnement sportif ou culturel\nNos engagements et priorit√©s\nLe groupe Capgemini encourage une\nculture inclusive dans un cadre multiculturel et handi-accueillant.\nEn nous rejoignant, vous int√©grez un collectif qui valorise la diversit√©, d√©veloppe le potentiel de ses talents, s‚Äôengage dans des\ninitiatives solidaires avec ses partenaires, et se mobilise pour r√©duire son impact environnemental sur tous ses sites et aupr√®s de ses clients.\nCapgemini\nest un\nleader mondial\n, responsable et multiculturel, regroupant pr√®s de 350 000 personnes dans plus de 50 pays. Fort de\n55 ans d‚Äôexp√©rience\n, nous sommes un partenaire strat√©gique des entreprises pour la transformation de leurs activit√©s en tirant profit de toute la puissance de la technologie et des innovations dans les domaines en perp√©tuelle √©volution tels que\nle cloud, la data, l‚ÄôIntelligence Artificielle, la connectivit√©, les logiciels, l‚Äôing√©nierie digitale ou les plateformes.\nGet The Future You Want* | www.capgemini.com/fr-fr\n*Capgemini, le futur que vous voulez\nShow more\nShow less",
        "details": {
            "JobDetail": [],
            "TypeContract": "",
            "Salary": "",
            "Level": "",
            "Experience": "6 an(s)"
        },
        "title": "data architect",
        "skills": {
            "CloudComputing": [
                "AWS",
                "Google Cloud Platform",
                "Azure"
            ],
            "Other": [
                "Cloud",
                "DevOps"
            ]
        }
    },
    {
        "source": "LinkedIn",
        "company": "Cyborg Intelligence",
        "location": "Lyon, Auvergne-Rh√¥ne-Alpes, France",
        "link": "https://fr.linkedin.com/jobs/view/data-architect-agile-at-cyborg-intelligence-3913820683?position=43&pageNum=0&refId=a5rwPua%2FMvx%2F2M%2FPSF0oPA%3D%3D&trackingId=QfZxY%2F2KgP%2BSZeHlfhURMA%3D%3D&trk=public_jobs_jserp-result_search-card",
        "description": "Pour l'un de nos clients suisses de prestige - L'anglais et le fran√ßais sont des imp√©ratifs incontournables pour ce poste en CDI\nResponsabilit√©s\nL'architecte des donn√©es informatiques est responsable de la d√©finition des politiques, des proc√©dures, des mod√®les et\ntechnologies qui seront utilis√©es pour collecter, organiser, stocker et r√©cup√©rer des informations pour\nl'organisation.\nIl/elle comprend comment les donn√©es d√©terminent le d√©veloppement d'applications et\nexigences commerciales gr√¢ce √† des principes de conception, des m√©thodologies et des\noutils.\nIl/elle fixe les r√®gles et la structure de la strat√©gie data, en choisissant l'ETL\napproche et d√©finition d‚Äôexigences suppl√©mentaires\nD√©finition du mod√®le de donn√©es¬†: d√©finir l'architecture des donn√©es, les interfaces des contrats de donn√©es, les donn√©es\nqualit√© dans les syst√®mes, les meilleures pratiques,\nAper√ßu des flux de donn√©es : devenez propri√©taire des flux de donn√©es actuels et futurs.\nAssumer la responsabilit√© de la qualit√© et de l'actualit√© des donn√©es,\nMaintenir et assurer l'√©volution des flux de donn√©es, en utilisant les standards mondiaux de donn√©es\net des r√®gles m√©tier pour saisir les donn√©es dans les syst√®mes,\nAssurance qualit√©¬†: effectuer des contr√¥les de qualit√© des donn√©es pour v√©rifier leur exactitude et\nl'exhaustivit√© selon des r√®gles m√©tier d√©finies,\nSyst√®me de donn√©es principal¬†: maintenir des donn√©es pr√©cises et √† jour pour les activit√©s assign√©es\nprocessus,\nContribuer √† l‚Äôam√©lioration continue des syst√®mes et des processus. Garantir les donn√©es\nalignement entre la documentation contractuelle et les donn√©es de base client,\nMaintenir √† jour la documentation des processus et le mat√©riel de formation,\nAssistance¬†: assurez-vous que les probl√®mes sont identifi√©s, suivis, signal√©s et r√©solus de mani√®re rapide.\nen temps opportun.\nD√©veloppement & maintenance\nR√¥le d'expert pour le produit ou le domaine de produit d√©sign√©.\n1. Traite les demandes des utilisateurs, les tickets de service, les incidents, les modifications\n2. Assumer les activit√©s de support de 3√®me niveau\n3. R√©dige et maintient la documentation\n4. Participe √† la cr√©ation des guides d'utilisation\nS'assure que le savoir-faire du domaine est transf√©r√© aux membres de l'√©quipe.\n5. Assure le respect de la s√©curit√© des donn√©es √† tout moment.\n6. √âvalue les performances des applications et des bases de donn√©es et les am√©liore lorsque cela est possible\n7. R√©aliser ou superviser les activit√©s de d√©veloppement et d'int√©gration de syst√®mes.\nGestion de projet\n1. Diriger des projets li√©s aux donn√©es en tant que repr√©sentant informatique\n2. D√©finit la port√©e du projet, planifie et suit les d√©veloppements du projet et\nd√©ploiements d'applications.\n3. Superviser les ressources externes pendant la phase du projet.\nQualifications\nApproche ax√©e sur le client\n‚Ä¢ Exp√©rience de travail dans Azure DF, Synapse, AWS ou autre\n‚Ä¢ Exp√©rience de travail avec les m√©thodologies Agile\n‚Ä¢ Forte r√©solution de probl√®mes, capacit√© √† travailler sous pression et capacit√© √† √©tablir des priorit√©s.\n‚Ä¢ Autogestion et capacit√© √† travailler de mani√®re ind√©pendante avec une supervision limit√©e\n‚Ä¢ Bonnes comp√©tences en communication et en relations interpersonnelles, capacit√© √† travailler efficacement avec\n√©quipes √† distance\n‚Ä¢ Tr√®s bonne communication orale et √©crite\n‚Ä¢ Anglais courant\nShow more\nShow less",
        "details": {
            "JobDetail": [],
            "TypeContract": "CDI",
            "Salary": "",
            "Level": "",
            "Experience": null
        },
        "title": "data architect",
        "skills": {
            "CloudComputing": [
                "AWS",
                "Azure"
            ],
            "EnSoftSkils": [
                "Communication"
            ]
        }
    },
    {
        "source": "LinkedIn",
        "company": "ENGIE",
        "location": "Courbevoie, √éle-de-France, France",
        "link": "https://fr.linkedin.com/jobs/view/get-data-architect-m-f-at-engie-3596026403?position=44&pageNum=0&refId=a5rwPua%2FMvx%2F2M%2FPSF0oPA%3D%3D&trackingId=5EGkaG7PyxLRHfA4k%2BzyOw%3D%3D&trk=public_jobs_jserp-result_search-card",
        "description": "Come join one of the most ambitious Transformation Program of Engie\nENGIE's strategy to drive the energy transition and to industrialize the company, making it simpler,\nfaster, and more integrated, is set.\nGET, Global Enterprise Transformation\n, is the Program decided by ENGIE to accelerate and standardize the ERP system as well as the effectiveness of processes, embarking the Company on a centrally steered and business-led transformation focused on making ENGIE an integrated industrial company.\nTherefore, GET Program is among the top 5 ENGIE priorities with genuine ExCom sponsorship.\nBe part of the Change and come build the Future at one of the most ambitious Transformation Program of the moment.\nWith a view to harmonization, ENGIE has embarked on a major program to transform its processes and IT tools. This project, which extends over several years, concerns all the entities of the group and requires a sustained support.\nTo implement this support, we are looking to recruit a :\nGET ‚Äì\nData Architect (M/F)\nThe head office is based in Courbevoie (La D√©fense), but the physical presence on the head office is not mandatory. We are also looking for international profiles.\nThe GET program aims to deliver the future business and IT core model with a central ‚Äúone ERP / One ARIBA‚Äù platform. The functional context of the program covers a set of functional areas including accounting, controlling and procurement as main areas.\nThe GET program offers a unique opportunity to onboard on one of the most ambitious and strategic Enterprise transformation programs with a very high IT footprint with S/4 & SAP ARIBA as central IT components. Innovation is at the heart of GET Program with an ambition to implement a best in class processes & solution.\nThe\nGET Data Architect\nrole is proposed to reinforce the internal team supporting the core model delivery and coordinating the pilots/rollouts.\nThis role will be N-2 to GET IT Lead and directly reporting to the core model IT lead.\nJob Responsibilities:\nBring high level expertise on MDM and especially SAP MDG\nHelp the business teams in business requirement definition and ensure coherence with the SAP capabilities\nResponsible for reviewing the integrator delivery and challenge the proposed solutions\nAlign with the business team to ensure the proposed solution is aligned with the core model and the program guidelines\nWork with the integrator teams and SAP teams to secure design authority presentations for arbitrations\nSecure testing phases and ensure quality of test delivery by the IT integrator\nDrive discussions in multi-cultural / global context with multiple stakeholders\nPosition Requirements\nVery good knowledge of the SAP MDG and overall the MDM area.\nUnderstanding the process of translating business requirements and processes into data collection and usage principles in MDG.\nAt least 5 years experience in similar position\nGood references in the previous experiences with other customers\nFluent English (oral/written)\nMay require national & international mobility.\n\"Priority position reserved for ENGIE SA Corporate employees whose position is removed and for DTR employees\".\nShow more\nShow less",
        "details": {
            "JobDetail": [],
            "TypeContract": "",
            "Salary": "",
            "Level": "",
            "Experience": null
        },
        "title": "data architect",
        "skills": {
            "Collaboration": [
                "Teams"
            ]
        }
    },
    {
        "source": "LinkedIn",
        "company": "SOFTEAM",
        "location": "√éle-de-France, France",
        "link": "https://fr.linkedin.com/jobs/view/data-architect-solution-azure-f-h-at-softeam-3839977121?position=45&pageNum=0&refId=a5rwPua%2FMvx%2F2M%2FPSF0oPA%3D%3D&trackingId=nJC8wyzoJbZwI7vYjHDuaw%3D%3D&trk=public_jobs_jserp-result_search-card",
        "description": "Vous √©voluez dans le domaine de la\nData\net souhaitez int√©grer un leader de la transformation num√©rique sp√©cialis√© dans les secteurs de la\nBanque, du Luxe, de l'Assurance, de la Finance, de l'Energie\net la possibilit√© d'√©voluer au sein du\nGroupe Docaposte\n!\nSofteam\nest labellis√© \"\nHappyIndex¬Æ AtWork\n\" 2022 pour la\n5√®me\nann√©e cons√©cutive !\nNos collaborateurs travaillent en ¬´ mode projet ¬ª autour des\nModern DATA Platform\n‚òÅ et\ntechnologies Big Data AWS Cloud / On premise\net autre \"playeur\" du march√©. Nous accompagnons de bout en bout nos clients sur des probl√©matiques de\nGouvernance, d‚ÄôInt√©gration, de Visualisation et d‚ÄôIA.\nCE QUE NOUS RECHERCHONS\nData Architect Solution Azure\nF/H, disposant de l‚Äôexp√©rience dans la mise en place des\nModern Data Platform\ndans\nAzure\n.\nCE QUE NOUS ATTENDONS DE VOUS\nEn tant que\nData Architect Solution Azure\nF/H, vous intervenez sur nos projets et contribuer au d√©veloppement de notre activit√©.\nVOS MISSIONS DETAILLEES\nAccompagner et conseiller le client dans son adoption des Modern Data Platform dans Azure (Etude d‚Äôarchitecture, pr√©paration des DAT, FinOps, DevOps)\nConcevoir des architectures Cloud Data exploitant efficacement les services de donn√©es manag√©s d'Azure\nConduire des projets de d√©ploiement des Modern Data Platform (Applications Cloud Native, Migration d‚Äôapplications existantes) et participer √† la mise en ≈ìuvre\nEtablir des relations de confiance avec les d√©cisionnaires techniques et m√©tiers afin de favoriser l‚Äôadoption du Cloud Azure √† long terme au sein de l‚Äôentreprise.\nFournir une expertise technique approfondie aux √©quipes projets\nAssister et former le client sur les usages et outils Data du Cloud Azure\nR√©aliser une veille technologique permanente sur les tendances du march√© et les perspectives concurrentielles\nVOUS ETES\nIng√©nieur(e) de formation, vous disposez d'une expertise reconnue et d'une exp√©rience de 5 ans dans un r√¥le d‚ÄôùêÄùê´ùêúùê°ùê¢ùê≠ùêûùêúùê≠ùêû ùêíùê®ùê•ùêÆùê≠ùê¢ùê®ùêß ùêÇùê•ùê®ùêÆùêù ùêÉùêöùê≠ùêö ou ùêìùêûùêúùê° ùêãùêûùêöùêù ùêÉùêöùê≠ùêö, avec une exp√©rience significative sur Azure.\nVous avez des comp√©tences approfondies dans un ou plusieurs de ces domaines : Op√©rations / Gestion des syst√®mes, Conception ou d√©veloppement de logiciels, Processus DevOps et outillage, Strat√©gie d'entreprise, Infrastructure Cloud (virtualisation, mise en r√©seau, stockage, base de donn√©es), S√©curit√© et conformit√©.\nVous √™tes sensibilis√© √† la d√©marche DevOps et connaissez au moins un outil pour la mise en ≈ìuvre de Continuous Integration/Continuous Delivery (CI-CD)\nLa possession de certifications sur des services Azure est un plus.\nNOUS VOUS OFFRONS\nDes missions engageantes aupr√®s des grands acteurs du march√©.\nUn management de proximit√© avec Gilles SALVADOR, Directeur du Centre d'Expertise Data, toujours bienveillant et √† l'√©coute et avec qui vous pourrez √©changer au quotidien sur les enjeux de votre mission et √©voquer vos futurs projets afin que nous puissions vous aider √† les r√©aliser.\nLa possibilit√© d‚Äô√©voluer et de monter en comp√©tences gr√¢ce √† des formations et √† des certifications aupr√®s de nos clients et de nos consultants, des 12@13, notre Entit√© Softeam Institute, Organisme de formation interne de renomm√© qui d√©livre des formations aupr√®s de nos clients...\nQUI SOMMES-NOUS ?\nSOFTEAM DATA est une marque de DOCAPOSTE sp√©cialis√©e dans l'informatique d√©cisionnelle et les nouvelles technologies. Nous apportons notre expertise √† nos clients, principalement des Grands Comptes de la place financi√®re fran√ßaise, dans des projets de transformation digitale et cognitive.\n2000 Softeamien.nes sont d√©di√©.es √† la transformation m√©tier et digitale de nos clients et ont g√©n√©r√© 200 M‚Ç¨ de chiffre d‚Äôaffaires en 2020.\nSOFTEAM SPIRIT\nDes communaut√©s d'expertises sur les sujets de la Data ;\nDe super nouveaux locaux qui sont en plus accessibles facilement ;\nUne √©cole de formation int√©gr√©e ;\nDes √©v√®nements : des soir√©es avec les consultants, des 12@13... ;\nUne entreprise labellis√©e \"Happy at Work\" pour la 5√®me ann√©e cons√©cutive.\nN‚Äôattendez plus, rejoignez SOFTEAM et venez nous rencontrer dans nos nouveaux locaux situ√©s √† la D√©fense #DevenezSofteamien !\nShow more\nShow less",
        "details": {
            "JobDetail": [],
            "TypeContract": "",
            "Salary": "",
            "Level": "",
            "Experience": "5 an(s)"
        },
        "title": "data architect",
        "skills": {
            "CloudComputing": [
                "AWS",
                "Azure"
            ],
            "Other": [
                "Cloud",
                "Big Data",
                "DevOps"
            ]
        }
    },
    {
        "source": "LinkedIn",
        "company": "HP",
        "location": "Hauts de Bienne, France",
        "link": "https://fr.linkedin.com/jobs/view/principal-data-architect-at-hp-3902461217?position=46&pageNum=0&refId=a5rwPua%2FMvx%2F2M%2FPSF0oPA%3D%3D&trackingId=oNBWg9krxvuDIl9%2BoJg16A%3D%3D&trk=public_jobs_jserp-result_search-card",
        "description": "HP is a Fortune 100 technology company with $58+ Billion in revenue, with over 50,000 employees operating in more than 170 countries around the world. We provide technology and services that help people and companies address their problems and challenges, and realize their possibilities, aspirations, and dreams. We apply new thinking and ideas to create simpler, more valuable, and trusted experiences with technology, continuously improving the way our customers live and work.\nIn the GTM advanced analytics COE, our mission is to deliver impact by building machine learning (ML) products to optimize pricing, marketing investments and provide guidance to sales and other HP teams.\nWe're looking for a principal data architect to join our data engineering team.\nQualifications\nTypically 5+ years of experience in software or data engineering.\nExtensive experience in data modeling, data integration and processing of structured and unstructured data.\nHighly proficient in one or more programming languages (Python preferred).\nStrong SQL proficiency (experience with NoSQL ‚Äì advantage).\nHighly experienced with Apache Spark / pyspark\nExcellent communication skills; mastery in English and local language.\nAbility to effectively communicate product architectures, design and change proposals.\nFamiliar with best practices of the data and software engineering lifecycle and/or best practices of the above platforms and tools.\nAdditional Preferred Qualifications / Advantages\nDatabricks\nPandas\nDataiku DSS\nShow more\nShow less",
        "details": {
            "JobDetail": [],
            "TypeContract": "",
            "Salary": "",
            "Level": "",
            "Experience": null
        },
        "title": "data architect",
        "skills": {
            "ProgLanguage": [
                "Python"
            ],
            "DataBase": [
                "SQL",
                "NoSQL"
            ],
            "DataAnalytics": [
                "Pandas"
            ],
            "BigData": [
                "Databricks",
                "Spark"
            ],
            "Collaboration": [
                "Teams"
            ],
            "Other": [
                "Machine Learning",
                "ML"
            ],
            "EnSoftSkils": [
                "Communication"
            ]
        }
    },
    {
        "source": "LinkedIn",
        "company": "EXAKIS NELITE",
        "location": "Aix-en-Provence, Provence-Alpes-C√¥te d'Azur, France",
        "link": "https://fr.linkedin.com/jobs/view/architecte-cloud-azure-data-h-f-at-exakis-nelite-3904805434?position=47&pageNum=0&refId=a5rwPua%2FMvx%2F2M%2FPSF0oPA%3D%3D&trackingId=%2Fb%2F4oxKpQrWu%2F5dO2fGNpg%3D%3D&trk=public_jobs_jserp-result_search-card",
        "description": "Exakis Nelite, entit√© du groupe Magellan Partners, est le premier partenaire pure-player Microsoft ind√©pendant en France avec l‚Äôambition de devenir le premier partenaire Europ√©en et en Afrique Francophone avec sa forte pr√©sence au Maroc.\nN√©s du rapprochement de 2 leaders sp√©cialistes de l‚Äôint√©gration des solutions Microsoft, nous allions expertise technique et fonctionnelle pour r√©pondre concr√®tement aux enjeux de demain : acc√©l√©ration de la transformation digitale, CyberS√©curit√©, Intelligence Artificielle, IoT, Data, transformation vers le cloud Azure, Services Cognitifs et Intelligence Artificielle‚Ä¶\nEn rejoignant la communaut√© Exakis Nelite dans l‚Äôune de nos 15 agences, vous int√©grerez une √©quipe passionn√©e et impliqu√©e dans les projets les plus innovants. Vous rejoindrez une structure construite autour de valeurs tourn√©es vers ses collaborateurs : intelligence collective, convivialit√© et bienveillance.\nA la pointe des nouvelles technologies, vous int√©grerez la communaut√© Modern Apps pour accompagner les grands comptes d'Aix-en-Provence dans leur strat√©gie digitale et l‚Äôadoption du cloud qui en d√©coule.\nPoste et missions:\nEn tant qu‚ÄôArchitecte Cloud Azure H/F, votre autonomie et votre force de proposition prendront toute leur ampleur en prenant en charge des missions d‚Äôexpertise ou des projets de plusieurs centaines de jours.\nVous travaillerez dans une ambiance conviviale, constructive, sereine, laissant une grande place √† l‚Äôinitiative et au d√©veloppement personnel.\nSelon les missions vous serez amen√©(e) √† :\nAccompagner nos clients dans leur strat√©gie digitale\nAnimer des ateliers d‚Äôarchitecture technique\nAppr√©hender les besoins fonctionnels et les contraintes techniques du client\nPr√©coniser des architectures complexes pour r√©pondre √† une probl√©matique ou un besoin m√©tier\nD√©finir et am√©liorer les standards, patterns d‚Äôarchitecture et le catalogue de services\nSuperviser et mettre en ≈ìuvre, dans le cadre des projets, les pr√©conisations techniques √©tablies dans le cadre des cahiers des charges\nR√©diger les documents associ√©s (HLD, LLD, etc.)\nPiloter des projets et des hommes\nIntervenir en toute autonomie sur les phases de cadrage technique et/ou avant ventes\nAssurer une veille technologique\nComp√©tences techniques attendues :\nBonne connaissance de la plateforme Azure dans son ensemble et de l‚Äô√©cosyst√®me associ√©.\nPlut√¥t DATA ?\nConnaissances requises :\nServices DATA dans Azure (DataFactory, Azure Synapse, Spark, Hadoop, etc.)\nBases de donn√©es (SQL, MYSQL,\nDes probl√©matiques de stockage et traitement de la donn√©e dans Azure (Storage Account, Datalake store, Data Factory, Logic App)\n¬´ Securit√© ¬ª de la donn√©e dans Azure\nLa connaissance de la gestion des donn√©es li√©es √† l‚ÄôIOT dans Azure est un plus\nProfil :\nDe formation BAC+5, vous justifiez d'une exp√©rience significative dans l'infrastructure informatique en cloud et notamment sur la plateforme Azure.\nBon(ne) communicant(e), vous √™tes capable de vous adapter √† la fois au travail en √©quipe et aux projets de nos clients.\nUne certaine aisance orale est indispensable. Un r√©dactionnel de qualit√© est obligatoire. Une bonne maitrise de l‚Äôanglais est obligatoire.\nExp√©rience: minimum 5 ans\nAvantages :\nMutuelle prise en charge √† 100%, t√©l√©travail, remboursement du titre de transport √† 100%, primes de cong√©s d'√©t√©, participation/int√©ressement, avantages CSE.\nVous vous reconnaissez dans cette annonce? N'h√©sitez pas √† postuler! Nous avons h√¢te de vous rencontrer!\nShow more\nShow less",
        "details": {
            "JobDetail": [],
            "TypeContract": "",
            "Salary": "",
            "Level": "Bac+5",
            "Experience": "5 an(s)"
        },
        "title": "data architect",
        "skills": {
            "DataBase": [
                "SQL"
            ],
            "BigData": [
                "Hadoop",
                "Spark"
            ],
            "CloudComputing": [
                "Azure"
            ],
            "DBMS": [
                "MySQL"
            ],
            "Other": [
                "Cloud"
            ],
            "EnSoftSkils": [
                "Initiative"
            ]
        }
    },
    {
        "source": "LinkedIn",
        "company": "Groupement des Mousquetaires",
        "location": "Vitr√©, Brittany, France",
        "link": "https://fr.linkedin.com/jobs/view/architecte-data-h-f-at-groupement-des-mousquetaires-3889132514?position=48&pageNum=0&refId=a5rwPua%2FMvx%2F2M%2FPSF0oPA%3D%3D&trackingId=cmkYqYRJ7JbipE08px2xQQ%3D%3D&trk=public_jobs_jserp-result_search-card",
        "description": "Description De L'entreprise\nLe Groupement Les Mousquetaires, ce sont 7 enseignes de la grande distribution port√©es haut et fort par plus de 3 000 chefs d‚Äôentreprise ind√©pendants ! Ce sont aussi 150 000 collaborateurs mobilis√©s autour de notre mod√®le ¬´ Producteurs et commer√ßants ¬ª.\nDans toutes les fonctions au service des points de vente, de la logistique √† l‚Äôimmobilier, en passant par l‚Äôindustrie agroalimentaire ou l‚Äôinformatique, nos √©quipes font nos succ√®s.\nAgromousquetaires est le p√¥le industriel du Groupement Les Mousquetaires. Premier fabricant de marques de distributeurs en France.\nAgromousquetaires c'est avant tout 11 000 hommes et femmes aux sensibilit√©s diverses, regroup√©s au sein de 70 sites industriels et logistiques, dont une cinquantaine d'usines, et 6 P√¥les de Performance.\nNous rejoindre, c'est partager une culture commune, celle de l'entrepreneuriat et de l'engagement c‚Äôest √™tre ¬´ Producteurs et Commer√ßants ¬ª !\nAlors, pr√™t √† vous lancer au service du ¬´ Mieux Produire pour Mieux Vivre ¬ª ?\nAgroM Services h√©berge √† l'AgroHub (35), √† Lanester (56) et au Parc de Tr√©ville (91), l'ensemble des m√©tiers transverses ayant vocation √† accompagner et r√©pondre aux besoins op√©rationnels de nos 6 p√¥les.\nVous souhaitez participer au d√©veloppement d'un acteur majeur de la Grande Distribution en Europe sur un poste qui offre une forte exposition pour l'avenir du Groupe ? Alors cette opportunit√© pourrait vous int√©resser. Seul distributeur √† √™tre √† la fois ¬´ Producteurs et Commer√ßants ¬ª avec des gammes de produits de qualit√©, dans des secteurs vari√©s et 100% made in France.\nDescription Du Poste\nNous recherchons\nun(e) Architecte Data (H/F)\nPoste √† pourvoir en CDI sur notre site bas√© √† Vitr√© (35)\nRattach√©(e) au Responsable D√©partement Data & Analytics, vous serez en charge de concevoir, d√©velopper et maintenir notre architecture de donn√©es, en veillant √† garantir l‚Äôint√©grit√©, la disponibilit√© et la confidentialit√© des donn√©es.\nVos missions seront les suivantes :\nD√©finir notre strat√©gie d‚Äôarchitecture des donn√©es sur l‚Äôalimentation, la transformation, la mod√©lisation, jusqu‚Äô√† l‚Äôexposition des donn√©es pour les usages tiers (BI notamment)\n√ätre garant de la mod√©lisation de notre patrimoine de donn√©es au sein de la plateforme data Cloud\nAdministrer notre plateforme de donn√©es sous GCP\nD√©finir et mettre en ≈ìuvre une strat√©gie FinOps\nD√©velopper ou faire d√©velopper √† l‚Äô√©quipe Flux Inter-Applicatifs les jobs ETL d‚Äôalimentation et de transformation de donn√©es sous Talend\nD√©finir les missions et piloter les Prestataires informatiques intervenant sur notre plateforme de donn√©es\nCommuniquer notre strat√©gie data au sein de l‚Äôentreprise\nDocumenter ou s‚Äôassurer que la documentation a √©t√© r√©alis√©e\nCollaborer sur les diff√©rents projets applicatifs n√©cessitant de stocker de la donn√©e\nContribuer au plan de transformation sur la gouvernance de la donn√©e, comprenant le traitement de la qualit√© des donn√©es\nPrendre en compte les contraintes cybers√©curit√© et de conformit√© r√©glementaire (RGPD) dans la conception des architectures\nS‚Äôassurer que toute solution mise en ≈ìuvre respecte la strat√©gie du d√©partement Data & Analytics, et plus g√©n√©ralement de la DSI\nRespecter les m√©thodologies projet en vigueur et √©tablies par le d√©partement SI Gouvernance\nAssurer une veille technologique autour des sujets traitant de la donn√©e et √™tre force de proposition sur la transformation de nos usages data\nQualifications\nVous avez :\nUne formation sup√©rieure de niveau Bac +5 en informatique ou sciences des donn√©es, de type Master ou Dipl√¥me d'Ing√©nieur.\nVous disposez d'une exp√©rience similaire de minimum 3 ans.\nVous devrez :\nAvoir de solides connaissances sur la plateforme Google Cloud Platform (Big Query, GCS notamment)\nMa√Ætriser des outils et technologies li√©s √† la gestion des donn√©es, tels que les bases de donn√©es, les entrep√¥ts de donn√©es, les outils ETL (Talend de pr√©f√©rence), ‚Ä¶\nUtiliser des m√©thodes de mod√©lisations (UML, BPMN ou √©quivalent).\nSavoir travailler en √©quipe, et collaboration avec les parties prenantes,\nR√©diger de mani√®re claire et concise,\nAvoir une bonne communication orale et √©crite\nVotre rigueur, votre adaptabilit√©, votre sens de l‚Äô√©coute, votre relationnel et votre proactivit√© (et oui rien que √ßa üòä), vous permettront de mener √† bien ces missions !\nInformations suppl√©mentaires\nVous vous reconnaissez sur ce poste ?\nAlors postulez et discutons de votre avenir !\nVous devrez r√©aliser votre travail dans une ambiance agr√©able, accompagn√©s de coll√®gues sympathiques et √ßa en seulement 3 jours de pr√©sence obligatoire sur site (2 jours de t√©l√©travail possible apr√®s 2 mois d‚Äôanciennet√© dans le groupe).\nAGROMOUSQUETAIRES s'engage √† promouvoir la diversit√©, notamment en favorisant l'emploi de Travailleurs en situation de Handicap.\nAGROMOUSQUETAIRESRECRUTE\nShow more\nShow less",
        "details": {
            "JobDetail": [],
            "TypeContract": "CDI",
            "Salary": "",
            "Level": "",
            "Experience": "3 an(s)"
        },
        "title": "data architect",
        "skills": {
            "CloudComputing": [
                "GCP",
                "Google Cloud Platform"
            ],
            "DBMS": [
                "Big Query"
            ],
            "Other": [
                "Cloud"
            ],
            "EnSoftSkils": [
                "Communication",
                "Collaboration"
            ]
        }
    },
    {
        "source": "LinkedIn",
        "company": "Capgemini",
        "location": "Aix-en-Provence, Provence-Alpes-C√¥te d'Azur, France",
        "link": "https://fr.linkedin.com/jobs/view/architecte-data-aix-en-provence-at-capgemini-3822433643?position=49&pageNum=0&refId=a5rwPua%2FMvx%2F2M%2FPSF0oPA%3D%3D&trackingId=ljqGAvYAe8YRObUU%2FcFj8A%3D%3D&trk=public_jobs_jserp-result_search-card",
        "description": "Choisir Capgemini, c'est choisir une entreprise o√π vous serez en mesure de fa√ßonner votre carri√®re selon vos aspirations. Avec le soutien et l'inspiration d‚Äôune communaut√© d‚Äôexperts dans le monde entier, o√π vous pourrez r√©√©crire votre futur. Rejoignez-nous pour red√©finir les limites de ce qui est possible, contribuer √† lib√©rer la valeur de la technologie pour les plus grandes organisations et participer √† la construction d‚Äôun monde plus durable et inclusif.\nVOS MISSIONS\n‚Ä¢ Pr√©coniser une architecture et des technologies\n‚Ä¢ Elaborer des standards technologies internes\n‚Ä¢ Garantir la coh√©rence technique de la solution et son √©volution\n‚Ä¢ Prototyper les solutions techniques pr√©conis√©es\n‚Ä¢ Assister l'√©quipe de d√©veloppement dans la mise en ≈ìuvre des solutions techniques pr√©conis√©es ‚Ä¢ D√©velopper des composants techniques\n‚Ä¢ Encadrer les √©quipes de consultants gr√¢ce √† la formation et le coaching\nDans votre quotidien, vous contribuerez au partage et √† la capitalisation des savoirs et des pratiques au sein de la Communaut√© des Architectes de Capgemini.\nVous participerez √† la construction de points de vue par l'exp√©rience et le savoir-faire reconnu dans un domaine technique\nL‚ÄôENVIRONNEMENT TECHNIQUE\nDataHub :\n‚Ä¢ ETL (Talend, Informatica ou SSIS),\n‚Ä¢ Traitement de donn√©es Spark, Python, Scala‚Ä¶\n‚Ä¢ Bases de donn√©es (Oracle, SQL Server, Postgres),\n‚Ä¢ Datalake / Big Data : Horton Works, Cloudera, ELK,‚Ä¶\nData Viz & IA / Machine Learning :\n‚Ä¢ Qlik, Tableau\n‚Ä¢ Python, R‚Ä¶\nVOTRE PROFIL\n‚Ä¢ De formation sup√©rieure, vous justifiez d'une exp√©rience reconnue (6 √† 10 ans) sur des projets de cadrage ou de mise en ≈ìuvre d‚Äôapplications / d‚Äôarchitectures visant √† collecter, stocker, raffiner et valoriser les donn√©es ;\n‚Ä¢ Vous √™tes habitu√© √† travailler dans des contextes Agile et DevOps.Vous avez c√¥toy√© une/des d√©marches de transformation SI (SOA, CLOUD, BigData, CLIENT/SERVEUR, EIM, ‚Ä¶) et une/des m√©thodologies d'architecture des SI (TOGAF, IAF)\n‚Ä¢ Vous ma√Ætrisez l'anglais √† l'oral et √† l'√©crit\n3 RAISONS DE NOUS REJOINDRE :\nQualit√© de vie au travail\n: accord de t√©l√©travail en France et √† l‚Äôinternational, accord sur l‚Äô√©galit√© professionnelle, la parentalit√©, l‚Äô√©quilibre des temps et la mobilit√© durable.\nApprentissage en continu\n: certifications et formations en libre acc√®s, accompagnement sur mesure avec votre career manager, parcours d‚Äôint√©gration sur 9 mois.\nAvantages groupe & CSE\n: plan actionnariat, tarif pr√©f√©rentiels, remboursement partiel vacances, remboursement de votre abonnement sportif ou culturel.\nNOS ENGAGEMENTS ET PRIORITES :\nLe groupe Capgemini encourage une culture inclusive dans un cadre multiculturel et handi-accueillant. En nous rejoignant, vous int√©grez un collectif qui valorise la diversit√©, d√©veloppe le potentiel de ses talents, s‚Äôengage dans des initiatives solidaires avec ses partenaires, et se mobilise pour r√©duire son impact environnemental sur tous ses sites et aupr√®s de ses clients.\nA PROPOS DE CAPGEMINI :\nCapgemini est un leader mondial, responsable et multiculturel, regroupant pr√®s de 350 000 personnes dans plus de 50 pays. Fort de 55 ans d‚Äôexp√©rience, nous sommes un partenaire strat√©gique des entreprises pour la transformation de leurs activit√©s en tirant profit de toute la puissance de la technologie et des innovations dans les domaines en perp√©tuelle √©volution tels que le cloud, la data, l‚ÄôIntelligence Artificielle, la connectivit√©, les logiciels, l‚Äôing√©nierie digitale ou les plateformes.\nGet The Future You Want* | www.capgemini.com/fr-fr\n*Capgemini, le futur que vous voulez\nShow more\nShow less",
        "details": {
            "JobDetail": [],
            "TypeContract": "",
            "Salary": "",
            "Level": "",
            "Experience": "10 an(s)"
        },
        "title": "data architect",
        "skills": {
            "ProgLanguage": [
                "R",
                "Scala",
                "Python"
            ],
            "DataBase": [
                "SQL"
            ],
            "DataAnalytics": [
                "R"
            ],
            "BigData": [
                "Spark"
            ],
            "DataVisualisation": [
                "Tableau"
            ],
            "DBMS": [
                "SQL Server"
            ],
            "Other": [
                "Machine Learning",
                "Cloud",
                "Big Data",
                "DevOps"
            ]
        }
    },
    {
        "source": "LinkedIn",
        "company": "HP",
        "location": "Grenoble, Auvergne-Rh√¥ne-Alpes, France",
        "link": "https://fr.linkedin.com/jobs/view/data-architect-m-f-at-hp-3903406324?position=50&pageNum=0&refId=a5rwPua%2FMvx%2F2M%2FPSF0oPA%3D%3D&trackingId=40S%2FgOr47a%2BHSzAk7zUjAw%3D%3D&trk=public_jobs_jserp-result_search-card",
        "description": "Who we are?\nHP creates new possibilities for technology to have a meaningful impact on people, businesses, governments and society. The world‚Äôs largest technology company and ranked 10 on the Fortune 500 list for 2012, HP brings together a portfolio that spans printing, personal computing, software, services and IT infrastructure to serve more than 1 billion customers in over 170 countries on six continents.\nHP invents, engineers, and delivers technology solutions that drive business value, create social value, and improve the lives of our clients. At HP, we know that our people and values are the most important elements in this success. And we want you to add your voice and imagination to our mission.\nDiversity drives our innovation engine\nDiverse teams create transformative solutions that better serve our customers and advance how the world works and lives.\nWe‚Äôre reinventing the standard for diversity and inclusion ‚Äî in how we operate as a company and impact society. Diversity is embedded in all we do, and every HP employee at every level plays a part. By valuing differences, we engage top industry talent to drive our company‚Äôs long-term success.\nWhat can we do together?\nIn the GTM advanced analytics COE, our mission is to deliver impact by building machine learning (ML) products to optimize pricing, marketing investments and provide guidance to sales and other HP teams.\nWe are looking for a Data Architect / Senior Data Engineer to join our data engineering team. If you are passionate about solving problems and making improvements through data and technology, we are eager to talk to you. The ideal candidate has both a willingness and desire to work in a dynamic environment, is able to apply Agile methodologies in day-to-day activities, and is a self-motivated developer who also enjoys working in a team environment. Our people have a creative, innovative, fun, and collaborative attitude, and are dedicated to creating new and valuable solutions for HP.\nThe data engineering architect applies developed subject matter knowledge to solve common and complex business issues within established guidelines and recommends appropriate alternatives.\nWorks on problems of diverse complexity and scope.\nMay act as a team or project leader providing direction to team activities and facilitates information validation and team decision making process.\nExercises independent judgment within generally defined policies and practices to identify and select a solution.\nAbility to handle most unique situations.\nMay seek advice in order to make decisions on complex business issues.\nWho you are?\n3+ years of experience in software or data engineering architecture.\nProficient in data modeling, data integration and processing of structured and unstructured data.\nProficient in one or more programming languages (Python preferred).\nStrong SQL proficiency (experience with NoSQL ‚Äì advantage).\nExperienced with Apache Spark / pyspark\nExcellent communication skills; mastery in English and local language.\nAbility to effectively communicate product architectures, design and change proposals.\nAdditional Preferred Qualifications Advantages\nDatabricks\nPandas\nFamiliar with best practices of the data and software engineering lifecycle and/or best practices of the above platforms and tools.\nDataiku DSS\nWhy joining HP France?\nAt HP France, you will be immersed in an inspiring workplace where all our people love to be, collaborate well together and where they can learn, grow and develop professionally as well as personally. We offer empowering responsibilities. You will have the opportunity to evolve through your commitment, your skills and your sense of initiative! This position can be the 1st step in a great career within our teams!\nJoining us also means a great work-life balance and benefits such as meal vouchers, discounts on HP products and more! Driven by a strong corporate culture, our employees are involved in numerous initiatives through internal networks (Next Gen, Women@hp, workplace well-being team, ect.) and external volunteering (Nos Quartiers ont du Talent, Hour of Code).\nHP is also committed to an equal opportunities policy, from recruitment to career development. Job offers are open to all, including people with disabilities.\nOur promise: To create a diverse and inclusive working environment! So, what are you waiting for?\nThis role is based in Grenoble (38) within our international skills and expertise center. We offer a collaborative, stimulating and ultra-connected working environment in the heart of the mountains and just a 10 minute walk from the train station.\nShow more\nShow less",
        "details": {
            "JobDetail": [
                "Senior"
            ],
            "TypeContract": "",
            "Salary": "",
            "Level": "",
            "Experience": null
        },
        "title": "data architect",
        "skills": {
            "ProgLanguage": [
                "Python"
            ],
            "DataBase": [
                "SQL",
                "NoSQL"
            ],
            "DataAnalytics": [
                "Pandas"
            ],
            "BigData": [
                "Databricks",
                "Spark"
            ],
            "Collaboration": [
                "Teams"
            ],
            "Other": [
                "Machine Learning",
                "ML"
            ],
            "EnSoftSkils": [
                "Initiative",
                "Communication"
            ]
        }
    },
    {
        "source": "LinkedIn",
        "company": "Mars",
        "location": "Aimargues, Occitanie, France",
        "link": "https://fr.linkedin.com/jobs/view/frontend-architect-f-m-x-at-mars-3914282604?position=51&pageNum=0&refId=a5rwPua%2FMvx%2F2M%2FPSF0oPA%3D%3D&trackingId=4YR1fYkda7creVM7OiFI5Q%3D%3D&trk=public_jobs_jserp-result_search-card",
        "description": "Job Description\nLocalisation:\nAimargues (30 minutes from Montpellier)\nType of contract:\npermanent contract\nTo achieve its ambition to be the reference in pet health through nutrition, Royal Canin wants to continue to push the barriers of nutrition and individualization.\nThe digital transformation is driving both new opportunities to serve more pets but also new challenges for our existing business models. Join the Royal Canin Digital Factory to participate to this transformation. You will join a multi-cultural, dynamic and caring team working all together and closely on all the digital projects of the brand. Royal Canin's Digital Factory is key in achieving this strategy through the multiplicity of its practices: UX/UI, Development, Product Ownership, Market deployment, Architecture, Governance...\nWhile the team will develop new digitally enabled business models that will shape the future of Royal Canin and Eukanuba, they also support the transformation of our existing business models.\nIn This Digital Acceleration Context, Royal Canin Needs To Reinforce Its Internal Strengths With Digital, User Centric And Data Capabilities. Based In Aimargues, This Job Will Sit In Our Digital Factory, Which Mission Are To\nDevelop our Service-driven and digital platforms supporting ‚ÄúPet Health Guardians‚Äù\nDevelop our key capabilities on Design Thinking, UX, Agile Management, Mobile/Web/Ecommerce development, Digital Platform deployment and Data-driven transformation.\nLeverage those capabilities to design and build our future Business Models\nHelp in acquiring data and driving traffic to our owned assets, which will help transform data collected into digital performance metrics and business insights.\nPush from global to deploy@ scale and pull from local to global synergy\nThe Digital factory, as part of the Direct to Pet Owner organization, works in strong partnership with Marketing and sales team and Innovation team.\nReporting to the Develop Factory Lead, we are hiring a\nFrontend Architect\n, who will define and drive the frontend technology strategy across the Digital Factory to support the organization ambitions.\nWhat are we looking for ?\n7 to 15 years' experience in Frontend Development for digital environment\nManagement of complex technical projects on an international level & in Agile methodology (Scrum, Kanban, SAFe)\nAbility to work with different teams and various team dynamics to achieve challenging delivery objectives\nLead of technical teams with external and internal actors\nFast Learner, Influencing and negotiations skills\nFluent in English\nWhat will be your key responsibilities ?\nThe role of\nFrontend Architect\nfor Supervision Angular/React Developers entails leading, guiding, and supervising multiple development teams working on projects utilizing Node.js, Angular, and/or React technologies. The\nFrontend Architect\nplays a crucial role in designing and implementing robust and scalable technical solutions, ensuring the quality, performance, and consistency of the developed applications.\nLeadership\nAs\nFrontend Architect\n, you will have to:\nHe/she can establish the software architecture of his/her project or steer it in a different direction, in alignment with the technical direction of the project.\nHe/she oversees the quality of what is produced by his/her team.\nHe/she communicates on technical matters, leveraging his/her expertise and contributing to the visibility of his/her team's expertise.\nThe Architect is the technical lead of the project. He/she ensures internal coordination between his teams and other teams involved in the project.\nHe/she ensures the flow of information and validates, if necessary, the various technical actions to be taken.\nHe/she can propose the right design based on functional and business challenges, and he advocates for his choices in front of the stakeholders.\nTechnical Leadership: Lead and mentor multiple development teams in designing, implementing, and maintaining software solutions based on Angular, and/or React.\nSystem Architecture: Design and define the technical architecture of applications, ensuring scalability, security, and performance.\nCollaboration: Collaborate closely with development teams, Delivery Leads, and PO to understand business requirements and define appropriate technical solutions.\nStandards and Best Practices: Establish and enforce coding standards, best practices, and development conventions within the teams.\nRisk Management: Identify and mitigate technical risks throughout the development lifecycle.\nMeetings\nSynchronization with frontend lead devs of all product squads\nTechnical retrospective: Once per sprint, exchange with the entire DEV team on technical improvements => Deliverables are technical tickets to be included in sprints (optional guest), leads must document decisions with CRs\nBack and Front Design Authority (weekly)\nSynchronization with front and back teams (sharing new topics, roadmaps, ..)\nSynchronization with DevOps\nWhat can you expect from Mars?\nAt Mars, we believe in a relationship of mutual trust, dignity and respect between our company and Associates that is more meaningful than the standard employer/employee relationship.\nAs Associates, we can expect to be respected, supported and valued as individuals, to be treated fairly and equitably.\nAn environment where you are empowered to be proactive and to take initiatives to make a difference.\nYou will work in a multicultural environment (more than 40 nationalities) and where your dog will be welcomed by more than 100 other Associates‚Äô dogs at the office!\nA unique and ideal work environment to become the leader in health through nutrition for cats and dogs!\nMars is an equal opportunity employer and all qualified applicants will receive consideration for employment without regard to race, color, religion, sex, sexual orientation, gender identity, national origin, disability status, protected veteran status, or any other characteristic protected by law. If you need assistance or an accommodation during the application process because of a disability, it is available upon request. The company is pleased to provide such assistance, and no applicant will be penalized as a result of such a request.\nShow more\nShow less",
        "details": {
            "JobDetail": [],
            "TypeContract": "",
            "Salary": "",
            "Level": "",
            "Experience": null
        },
        "title": "data architect",
        "skills": {
            "Collaboration": [
                "Teams"
            ],
            "Other": [
                "DevOps"
            ],
            "EnSoftSkils": [
                "Leadership",
                "Organization",
                "Collaboration"
            ]
        }
    },
    {
        "source": "LinkedIn",
        "company": "University of Strasbourg",
        "location": "Strasbourg, Grand Est, France",
        "link": "https://fr.linkedin.com/jobs/view/architecte-data-f-h-syst%C3%A8me-r%C3%A9seaux-donn%C3%A9es-h-f-at-university-of-strasbourg-3912809071?position=52&pageNum=0&refId=a5rwPua%2FMvx%2F2M%2FPSF0oPA%3D%3D&trackingId=RVJPCVX4Zg3%2B7sxclxk9CQ%3D%3D&trk=public_jobs_jserp-result_search-card",
        "description": "Cette offre d‚Äôemploi est fournie par P√¥le emploi\nDescription\nDescriptif du poste: Emploi ouvert aux agents contractuels uniquement CDD de projet de 3 ans √† compter du 10/06/2024 Cat√©gorie : A Corps : Ing√©nieur d'√©tudes R√©mun√©ration selon grille de la Fonction Publique La fiche de poste d√©taill√©e est disponible sur le site de l'Universit√©. Mission : L'architecte data aura pour principale mission d'optimiser les process de collecte de donn√©es issues des syst√®mes d'information des partenaires du P√¥le Universitaire d'Innovation Alsace (PUI-A) et les bases de donn√©es disponibles en ¬´ open data ¬ª, en vue d'assurer le d√©ploiement de la d√©marche de pilotage strat√©gique et op√©rationnel par la donn√©e mise en ≈ìuvre dans le cadre du projet PUI-A. Activit√©s principales : * Cartographier les donn√©es disponibles au sein des syst√®mes d'informations des membres fondateurs du PUI-A et des bases de donn√©es utiles aux activit√©s du PUI-A notamment accessibles en ¬´ open data ¬ª * D√©finir et mettre en place les normes, m√©thodes, proc√©dures, outils et r√©f√©rentiels de collecte et de gestion de donn√©es * Concevoir une approche de regroupement et d'organisation des donn√©es collect√©es. Activit√©s associ√©es : * Contribuer aux travaux d'exploitation des donn√©es * Contribuer √† l'√©laboration des outils de pilotage strat√©gique et op√©rationnel par la donn√©e du PUI-A. Contact pour renseignements sur le poste : David-Alexandre BONNE, Responsable du P√¥le Universitaire d'Innovation Alsace Profil recherch√©: Profil recherch√© : Formation Bac+5 √† Bac+8 dans un des domaines en lien avec le poste (statistique, √©conom√©trie, math√©matiques, informatique, traitement de l'information). Connaissances : * Architecture et environnement technique d'un syst√®me d'information * Outils de gestion (ex. SQL, ETL) et d'exploitation (ex. R, Python) de bases de donn√©es * Techniques statistiques et informatiques de collecte et de traitement de donn√©es * M√©thodes, outils, normes et proc√©dures de la qualit√© * M√©thodologie de conduite de projet * Organisation et fonctionnement de l'enseignement sup√©rieur et de la recherche, ainsi que des √©cosyst√®mes de recherche et d'innovation (en Alsace ou dans d'autres territoires) * Langue anglaise : B2 √† C1 (cadre europ√©en commun de r√©f√©rence pour les langues). Comp√©tences op√©rationnelles : * Piloter un projet * Construire et g√©rer une base de donn√©es * R√©diger la documentation fonctionnelle et technique pour les utilisateurs * G√©rer la s√©curit√© de l'information * Mettre au point ou adapter des techniques nouvelles, notamment d'automatisation * Apporter des r√©ponses √† des besoins sp√©cifiques * Accompagner et conseiller * Communiquer et faire preuve de p√©dagogie * Travailler en √©quipe. Comp√©tences comportementales : * Capacit√© de conceptualisation * Cr√©ativit√© : sens de l'innovation * Sens de l'initiative * Rigueur * Curiosit√© intellectuelle et ouverture d'esprit * Pers√©v√©rance * Capacit√© d'adaptation * Sens de l'organisation * Sens relationnel * Capacit√© d'√©coute.\nPROFIL SOUHAIT√â\nExp√©rience\nD√©butant accept√©\nSource: Pole emploi (https://www.pole-emploi.fr)\nShow more\nShow less",
        "details": {
            "JobDetail": [],
            "TypeContract": "CDD",
            "Salary": "",
            "Level": "Bac+5",
            "Experience": "3 an(s)"
        },
        "title": "data architect",
        "skills": {
            "ProgLanguage": [
                "R",
                "Python"
            ],
            "DataBase": [
                "SQL"
            ],
            "DataAnalytics": [
                "R"
            ],
            "Other": [
                "Statistiques"
            ],
            "EnSoftSkils": [
                "Initiative"
            ]
        }
    },
    {
        "source": "LinkedIn",
        "company": "FRG Technology Consulting",
        "location": "Paris, √éle-de-France, France",
        "link": "https://fr.linkedin.com/jobs/view/data-architect-talend-bi-at-frg-technology-consulting-3908855754?position=53&pageNum=0&refId=a5rwPua%2FMvx%2F2M%2FPSF0oPA%3D%3D&trackingId=mF7ZBqw31ah5zMA856l4cg%3D%3D&trk=public_jobs_jserp-result_search-card",
        "description": "FRG Consulting est √† la recherche d'un Data Architect BI / Talend avec une solide ma√Ætrise de Java pour rejoindre une √©quipe bas√©e dans le sud de Paris. Dans ce r√¥le, vous serez responsable de l'√©valuation de l'architecture des donn√©es et des bases de donn√©es actuelles, ainsi que de la collecte, de l'organisation et de l'agr√©gation des donn√©es internes et externes pour les rendre accessibles.\nResponsabilit√©s :\n√âvaluer l'architecture des donn√©es et les bases de donn√©es actuelles, y compris DataWarehouse, Datamart et les bases de donn√©es tampons.\nCollecter, organiser et agr√©ger les donn√©es internes et externes en utilisant les meilleures pratiques ETL pour l'alimentation du DataWarehouse.\nD√©finir et maintenir la cartographie des donn√©es (applications, flux de donn√©es) et assurer la coh√©rence des donn√©es.\nOptimiser l'utilisation, par les m√©tiers, des services et solutions mis √† disposition par la DSI, en identifiant les opportunit√©s de proposer de nouveaux produits ou services et en participant √† leur d√©finition.\nParticiper √† la mise en place des projets en collectant les besoins exprim√©s par les m√©tiers, en traduisant ces besoins en sp√©cifications techniques, mod√®les de donn√©es et user stories (avec une ma√Ætrise des concepts Agile), et en accompagnant les projets dans la d√©finition des besoins, la description et l'usage des donn√©es en collaboration avec les √©quipes DSI.\nS'assurer que les projets d√©ploy√©s par la DSI s'inscrivent dans la roadmap data et assurer un r√¥le de conseil aupr√®s des √©quipes DSI et m√©tiers.\nR√©aliser un suivi quotidien des performances et de l'efficacit√© des bases de donn√©es.\nQualifications :\nExp√©rience significative dans un poste similaire, avec une solide expertise en Java et Talend.\nConnaissance approfondie des bases de donn√©es, des architectures de donn√©es et des meilleures pratiques ETL.\nComp√©tences avanc√©es en analyse et mod√©lisation de donn√©es.\nExcellentes comp√©tences en communication et en collaboration, avec la capacit√© de travailler efficacement avec des √©quipes interfonctionnelles.\nMa√Ætrise des concepts Agile et capacit√© √† travailler dans un environnement Agile.\nCapacit√© d√©montr√©e √† r√©soudre des probl√®mes complexes et √† prendre des d√©cisions √©clair√©es.\nAutonomie, proactivit√© et capacit√© √† travailler de mani√®re autonome tout en faisant partie d'une √©quipe.\nShow more\nShow less",
        "details": {
            "JobDetail": [],
            "TypeContract": "",
            "Salary": "",
            "Level": "",
            "Experience": null
        },
        "title": "data architect",
        "skills": {
            "ProgLanguage": [
                "Java"
            ],
            "EnSoftSkils": [
                "Communication",
                "Collaboration"
            ]
        }
    },
    {
        "source": "LinkedIn",
        "company": "Schneider Electric",
        "location": "Lattes, Occitanie, France",
        "link": "https://fr.linkedin.com/jobs/view/architecte-data-model-f-h-at-schneider-electric-3864653832?position=54&pageNum=0&refId=a5rwPua%2FMvx%2F2M%2FPSF0oPA%3D%3D&trackingId=FuZ7MUBxPrGA%2B6wwUn0FZQ%3D%3D&trk=public_jobs_jserp-result_search-card",
        "description": "Missions\nEn tant qu‚Äô Architecte Data-Model, vous jouerez un r√¥le crucial dans le fa√ßonnement et l'optimisation de l'infrastructure de donn√©es de notre produit. Vous serez responsable de la conception, de la mise en ≈ìuvre et de la maintenance de solutions de donn√©es √©volutives et efficaces r√©pondant aux besoins de l'entreprise. Ce r√¥le n√©cessite une compr√©hension approfondie de la gestion des donn√©es et une vision strat√©gique pour aligner l'architecture des donn√©es avec les strat√©gies commerciales globales :\nMod√©lisation et Conception de Donn√©es :\nVeiller √† la conformit√© de normes telles que l'IEC61850\nD√©velopper et maintenir des mod√®les de donn√©es conceptuels, logiques et physiques\nConcevoir des structures de donn√©es et des relations qui soutiennent les exigences commerciales et permettent une r√©cup√©ration efficace des donn√©es\nGouvernance des Donn√©es :\n√âtablir et appliquer des politiques et proc√©dures de gouvernance des donn√©es\nD√©finir les normes de donn√©es, les conventions de d√©nomination et les r√®gles de qualit√© des donn√©es\nInt√©gration des Donn√©es :\nConcevoir et mettre en ≈ìuvre des solutions d'int√©gration de donn√©es pour assurer un flux d'informations transparent √† travers les syst√®mes\nCollaborer avec d'autres √©quipes informatiques pour int√©grer les sources de donn√©es\nCollaboration et Communication :\nTravailler en √©troite collaboration avec les parties prenantes m√©tier pour comprendre leurs besoins et les traduire en solutions de donn√©es efficaces\nCollaborer avec des √©quipes pluridisciplinaires, y compris des Analystes et des D√©veloppeurs\nS√©curit√© et Conformit√© :\nMettre en ≈ìuvre des mesures de s√©curit√© des donn√©es pour prot√©ger les informations sensibles\nFournir un leadership, des analyses et des t√¢ches de conception afin de garantir une application en phase avec la valeur commerciale attendue. Fournir des conseils en architecture et un soutien sur les activit√©s r√©alis√©es pour maintenir et am√©liorer les applications.\nProfil\nBac+5 minimum de type Ecole d‚ÄôIng√©nieur ou √©quivalent en informatique, technologie de l'information ou domaine connexe\nAu moins 5 ans d'exp√©rience en tant qu'Architecte de Donn√©es ou dans un r√¥le similaire\nConnaissance de l'IEC61850\nSolide connaissance des syst√®mes de gestion de bases de donn√©es et des techniques de mod√©lisation de donn√©es\nCompr√©hension des m√©thodes et processus agiles, et capacit√© √† soutenir des √©quipes de projet agiles\nCapacit√© d‚Äôanalyse et de synth√®se, bon sens de la communication et de la collaboration\nCapacit√©s de r√©solution de probl√®mes et de d√©pannage\nRester en veille concernant les tendances √©mergentes et technologies en gestion des donn√©es\nPourquoi nous?\nSchneider Electric est la r√©f√©rence en mati√®re de transformation num√©rique de la gestion de l'√©nergie et de l'automatisation. Nos technologies permettent au monde d'utiliser l'√©nergie de mani√®re s√ªre, efficace et durable. Nous nous effor√ßons de promouvoir une √©conomie mondiale √† la fois viable sur le plan √©cologique et hautement productive.\n34 milliards d'euros de chiffre d'affaires global\n128 000+ employ√©s dans plus de 100 pays\n45 % du chiffre d'affaires de l'IoT\n5 % du chiffre d'affaires consacr√© √† la R&D\nVous devez soumettre une demande en ligne pour que votre profil soit pris en consid√©ration pour un poste chez nous. Ce poste sera visible jusqu'√† ce qu'il soit pourvu.\nSchneider Electric a pour politique de fournir des possibilit√©s d'emploi et d'avancement √©gales dans les domaines du recrutement, de l'embauche, de la formation, du transfert et de la promotion de toutes les personnes qualifi√©es, quelle que soit leur race, religion, couleur, sexe, handicap, origine nationale, ascendance, √¢ge, statut militaire, orientation sexuelle, √©tat matrimonial ou toute autre caract√©ristique ou conduite l√©galement prot√©g√©e. Agences concern√©es : Schneider Electric n‚Äôaccepte pas de curriculum vit√¶ soumis de fa√ßon spontan√©e et ne sera pas responsable des frais occasionn√©s par de tels envois.\nShow more\nShow less",
        "details": {
            "JobDetail": [],
            "TypeContract": "",
            "Salary": "",
            "Level": "Bac+5",
            "Experience": "5 an(s)"
        },
        "title": "data architect",
        "skills": {
            "ProgLanguage": [
                "R"
            ],
            "DataAnalytics": [
                "R"
            ],
            "EnSoftSkils": [
                "Leadership",
                "Communication",
                "Collaboration"
            ]
        }
    },
    {
        "source": "LinkedIn",
        "company": "Mars",
        "location": "Haguenau, Grand Est, France",
        "link": "https://fr.linkedin.com/jobs/view/frontend-architect-f-m-x-at-mars-3914284362?position=55&pageNum=0&refId=a5rwPua%2FMvx%2F2M%2FPSF0oPA%3D%3D&trackingId=GlRyZYi%2FaDs%2F1w84FA7kOw%3D%3D&trk=public_jobs_jserp-result_search-card",
        "description": "Job Description\nLocalisation:\nAimargues (30 minutes from Montpellier)\nType of contract:\npermanent contract\nTo achieve its ambition to be the reference in pet health through nutrition, Royal Canin wants to continue to push the barriers of nutrition and individualization.\nThe digital transformation is driving both new opportunities to serve more pets but also new challenges for our existing business models. Join the Royal Canin Digital Factory to participate to this transformation. You will join a multi-cultural, dynamic and caring team working all together and closely on all the digital projects of the brand. Royal Canin's Digital Factory is key in achieving this strategy through the multiplicity of its practices: UX/UI, Development, Product Ownership, Market deployment, Architecture, Governance...\nWhile the team will develop new digitally enabled business models that will shape the future of Royal Canin and Eukanuba, they also support the transformation of our existing business models.\nIn This Digital Acceleration Context, Royal Canin Needs To Reinforce Its Internal Strengths With Digital, User Centric And Data Capabilities. Based In Aimargues, This Job Will Sit In Our Digital Factory, Which Mission Are To\nDevelop our Service-driven and digital platforms supporting ‚ÄúPet Health Guardians‚Äù\nDevelop our key capabilities on Design Thinking, UX, Agile Management, Mobile/Web/Ecommerce development, Digital Platform deployment and Data-driven transformation.\nLeverage those capabilities to design and build our future Business Models\nHelp in acquiring data and driving traffic to our owned assets, which will help transform data collected into digital performance metrics and business insights.\nPush from global to deploy@ scale and pull from local to global synergy\nThe Digital factory, as part of the Direct to Pet Owner organization, works in strong partnership with Marketing and sales team and Innovation team.\nReporting to the Develop Factory Lead, we are hiring a\nFrontend Architect\n, who will define and drive the frontend technology strategy across the Digital Factory to support the organization ambitions.\nWhat are we looking for ?\n7 to 15 years' experience in Frontend Development for digital environment\nManagement of complex technical projects on an international level & in Agile methodology (Scrum, Kanban, SAFe)\nAbility to work with different teams and various team dynamics to achieve challenging delivery objectives\nLead of technical teams with external and internal actors\nFast Learner, Influencing and negotiations skills\nFluent in English\nWhat will be your key responsibilities ?\nThe role of\nFrontend Architect\nfor Supervision Angular/React Developers entails leading, guiding, and supervising multiple development teams working on projects utilizing Node.js, Angular, and/or React technologies. The\nFrontend Architect\nplays a crucial role in designing and implementing robust and scalable technical solutions, ensuring the quality, performance, and consistency of the developed applications.\nLeadership\nAs\nFrontend Architect\n, you will have to:\nHe/she can establish the software architecture of his/her project or steer it in a different direction, in alignment with the technical direction of the project.\nHe/she oversees the quality of what is produced by his/her team.\nHe/she communicates on technical matters, leveraging his/her expertise and contributing to the visibility of his/her team's expertise.\nThe Architect is the technical lead of the project. He/she ensures internal coordination between his teams and other teams involved in the project.\nHe/she ensures the flow of information and validates, if necessary, the various technical actions to be taken.\nHe/she can propose the right design based on functional and business challenges, and he advocates for his choices in front of the stakeholders.\nTechnical Leadership: Lead and mentor multiple development teams in designing, implementing, and maintaining software solutions based on Angular, and/or React.\nSystem Architecture: Design and define the technical architecture of applications, ensuring scalability, security, and performance.\nCollaboration: Collaborate closely with development teams, Delivery Leads, and PO to understand business requirements and define appropriate technical solutions.\nStandards and Best Practices: Establish and enforce coding standards, best practices, and development conventions within the teams.\nRisk Management: Identify and mitigate technical risks throughout the development lifecycle.\nMeetings\nSynchronization with frontend lead devs of all product squads\nTechnical retrospective: Once per sprint, exchange with the entire DEV team on technical improvements => Deliverables are technical tickets to be included in sprints (optional guest), leads must document decisions with CRs\nBack and Front Design Authority (weekly)\nSynchronization with front and back teams (sharing new topics, roadmaps, ..)\nSynchronization with DevOps\nWhat can you expect from Mars?\nAt Mars, we believe in a relationship of mutual trust, dignity and respect between our company and Associates that is more meaningful than the standard employer/employee relationship.\nAs Associates, we can expect to be respected, supported and valued as individuals, to be treated fairly and equitably.\nAn environment where you are empowered to be proactive and to take initiatives to make a difference.\nYou will work in a multicultural environment (more than 40 nationalities) and where your dog will be welcomed by more than 100 other Associates‚Äô dogs at the office!\nA unique and ideal work environment to become the leader in health through nutrition for cats and dogs!\nMars is an equal opportunity employer and all qualified applicants will receive consideration for employment without regard to race, color, religion, sex, sexual orientation, gender identity, national origin, disability status, protected veteran status, or any other characteristic protected by law. If you need assistance or an accommodation during the application process because of a disability, it is available upon request. The company is pleased to provide such assistance, and no applicant will be penalized as a result of such a request.\nShow more\nShow less",
        "details": {
            "JobDetail": [],
            "TypeContract": "",
            "Salary": "",
            "Level": "",
            "Experience": null
        },
        "title": "data architect",
        "skills": {
            "Collaboration": [
                "Teams"
            ],
            "Other": [
                "DevOps"
            ],
            "EnSoftSkils": [
                "Leadership",
                "Organization",
                "Collaboration"
            ]
        }
    },
    {
        "source": "LinkedIn",
        "company": "FRG Technology Consulting",
        "location": "Paris, √éle-de-France, France",
        "link": "https://fr.linkedin.com/jobs/view/data-architect-at-frg-technology-consulting-3837380867?position=56&pageNum=0&refId=a5rwPua%2FMvx%2F2M%2FPSF0oPA%3D%3D&trackingId=kJraF7KaJQuIzQUTGcV6pw%3D%3D&trk=public_jobs_jserp-result_search-card",
        "description": "FRG recrute, pour l'un de ses clients un Data Architect. Notre client est une soci√©t√© de conseil √† taille humaine, en pleine croissance, qui accompagne ses clients dans leur transformation num√©rique.\nMissions principales\nConcevoir et mettre en ≈ìuvre les plateformes Data\nD√©velopper et maintenir l'architecture pour garantir une gestion efficace et s√©curis√©e des informations chez les clients\nMise en ≈ìuvre des strat√©gies de la plateforme Data\nElaboration et mise en ≈ìuvre d'architecture Data\nAutomatisation et optimisation des op√©rations de maintenance pour veiller √† l'am√©lioration continue de l'efficacit√© des ressources sur les plateformes\nContribuer aux missions d'avant-vente : √©tude de faisabilit√©, √©valuation d'impact\nProfil\n8 √† 10 d'exp√©rience dans l'IT dont 5 ans d'exp√©rience sur l'un des Cloud Providers (AWS ; Azure ; GCP)\nExp√©rience confirm√©e dans l'impl√©mentation des pratiques DevOps, la gestion de l'infrastructure et le d√©ploiement de services dans le cloud\nMa√Ætrise des technologies de gestion des donn√©es (ETL...) et de la virtualisation des donn√©es\nCertifications fortement appr√©ci√©es\nBonne communication √† l'oral et √† l'√©crit, anglais courant\nShow more\nShow less",
        "details": {
            "JobDetail": [
                "Confirm√©"
            ],
            "TypeContract": "",
            "Salary": "",
            "Level": "",
            "Experience": "5 an(s)"
        },
        "title": "data architect",
        "skills": {
            "CloudComputing": [
                "GCP",
                "AWS",
                "Azure"
            ],
            "Other": [
                "Cloud",
                "DevOps"
            ],
            "EnSoftSkils": [
                "Communication"
            ]
        }
    },
    {
        "source": "LinkedIn",
        "company": "EXAKIS NELITE",
        "location": "Aix-en-Provence, Provence-Alpes-C√¥te d'Azur, France",
        "link": "https://fr.linkedin.com/jobs/view/architecte-avant-vente-cloud-application-data-innovation-h-f-at-exakis-nelite-3904807120?position=57&pageNum=0&refId=a5rwPua%2FMvx%2F2M%2FPSF0oPA%3D%3D&trackingId=aX0ftkgaybh2MNefSEJg9A%3D%3D&trk=public_jobs_jserp-result_search-card",
        "description": "Exakis Nelite, entit√© du groupe Magellan Partners, est le premier partenaire pure-player Microsoft ind√©pendant en France avec l‚Äôambition de devenir le premier partenaire Europ√©en et en Afrique Francophone avec sa forte pr√©sence au Maroc.\nN√©s du rapprochement de 2 leaders sp√©cialistes de l‚Äôint√©gration des solutions Microsoft, nous allions expertise technique et fonctionnelle pour r√©pondre concr√®tement aux enjeux de demain : acc√©l√©ration de la transformation digitale, transformation vers le cloud Azure, Services Cognitifs et Intelligence Artificielle‚Ä¶\nEn rejoignant la communaut√© Exakis Nelite dans l‚Äôune de nos 15 agences, vous int√©grerez une √©quipe passionn√©e et impliqu√©e dans les projets les plus innovants. Vous rejoindrez une structure construite autour de valeurs tourn√©es vers ses collaborateurs : intelligence collective, convivialit√© et bienveillance.\nPoste et missions:\nVous √©voluerez au sein de l‚ÄôEnterprise Solution Center (ESC) de la r√©gion SUD pour relever de nouveaux d√©fis autour des enjeux de d√©veloppement Cloud et Digital.\nEn tant que Business Architect and Analyst, vous serez amen√© √† suivre et accompagner nos clients grands comptes sur leurs sujets de transformation digitale des processus m√©tiers et sur la valorisation de leurs donn√©es #Data. Vous les accompagnerez √©galement lors des projets de migration vers ces nouvelles plateformes.\nVous accompagnerez le d√©veloppement de la R√©gion SUD sur ces enjeux en d√©finissant les orientations, les offres, et les projets innovants.\nSelon les missions vous serez amen√© √† :\nAborder une posture de conseil pour accompagner nos clients strat√©giques,\nD√©finir les offres et propositions de valeurs qui feront le portefeuille de services autour de la transformation digitale vers le Cloud.\nAssurer le Bid Management des r√©ponses commerciales au client,\nD√©finir, choisir et argumenter des architectures applicatives et techniques,\nImaginer des sc√©narios de valorisation des donn√©es,\nConcevoir une architecture en ad√©quation avec les besoins m√©tier,\nPrendre en consid√©ration les probl√©matiques de performance et de s√©curit√©,\nAccompagner l‚Äôint√©gration des solutions dans le syst√®me d‚Äôinformation,\nR√©aliser de la veille technologique sur les solutions et les innovations.\nAccompagner nos √©quipes de Delivery et nos experts dans la prise en compte des nouveaux enjeux, des projets, et des solutions.\nParticiper et piloter les phases critiques des projets innovants,\nMettre en place des partenariats avec les acteurs cl√©s du march√©.\nProfil:\nDe formation BAC+5 id√©alement en ing√©nierie, vous justifiez d‚Äôune exp√©rience significative dans le d√©veloppement de l‚Äôinfrastructure informatique en cloud et notamment sur la plateforme Azure √† forte valeur ajout√©e.\nVous avez la capacit√© de :\nLeader les avant ventes structurantes\nProposer des orientations strat√©giques autour des applications √† destination du Cloud public et de la gouvernance de la Data\nRelever des d√©fis pour r√©pondre aux enjeux des clients\n√ätre force de proposition\nCoacher, animer, et suivre des consultants passionn√©s\nBonne connaissance de la plateforme Azure dans son ensemble et de l‚Äô√©cosyst√®me associ√©.\nConnaissances requises :\nServices r√©seaux dans Azure (VNet / Subnet, VPN S2S, ExpressRoute, Azure Firewall, Load Balancer, Application Gateway, Traffic Manager)\nAzure AD\nService machine virtuelle\nAutomatisation (mod√®le de d√©ploiement ARM et / ou Terraform, Ansible)\nConteneurisation (docker, Azure Container Instance, Azure Kubernetes Service)\nGouvernance dans Azure (Azure Policy, Azure tags, Azure Cost Management, etc.)\nAspects haute disponibilit√© et reprise d‚Äôactivit√© apr√®s sinistre\nDou√©(e) d‚Äôun bon r√©dactionnel, vous maitrisez l‚Äôanglais √† l‚Äôoral comme √† l‚Äô√©crit.\nUne exp√©rience en ESN est indispensable !\nAvantages :\nMutuelle prise en charge √† 100%, t√©l√©travail, remboursement du titre de transport √† 100%, primes de cong√©s d'√©t√©, participation/int√©ressement, avantages CSE.\nVous vous reconnaissez dans cette annonce? N'h√©sitez pas √† postuler! Nous avons h√¢te de vous rencontrer!\nShow more\nShow less",
        "details": {
            "JobDetail": [],
            "TypeContract": "",
            "Salary": "",
            "Level": "Bac+5",
            "Experience": null
        },
        "title": "data architect",
        "skills": {
            "CloudComputing": [
                "Azure"
            ],
            "DevTools": [
                "Docker"
            ],
            "Automation": [
                "Kubernetes",
                "Ansible"
            ],
            "InfrastructureAsCode": [
                "Terraform"
            ],
            "NetworkSecurty": [
                "Firewall",
                "VPN"
            ],
            "Containers": [
                "Docker",
                "Kubernetes"
            ],
            "Other": [
                "Cloud"
            ]
        }
    },
    {
        "source": "LinkedIn",
        "company": "TotalEnergies",
        "location": "Paris, √éle-de-France, France",
        "link": "https://fr.linkedin.com/jobs/view/data-architect-totalenergies-digital-factory-at-totalenergies-3915417534?position=58&pageNum=0&refId=a5rwPua%2FMvx%2F2M%2FPSF0oPA%3D%3D&trackingId=u97hBoyKUyuCRt2bDzyVOA%3D%3D&trk=public_jobs_jserp-result_search-card",
        "description": "TotalEnergies est une\ncompagnie multi-√©nergies mondiale\nde production et de fourniture d'√©nergies : p√©trole et biocarburants, gaz naturel et gaz verts, renouvelables et √©lectricit√©.\nLa Digital Factory de TotalEnergies est compos√©e de 300 personnes, 30 Squads, 39% de femmes et 25 nationalit√©s. Elle offre un environnement de travail international et interculturel en plein c≈ìur de Paris, engag√© dans la diversit√© et l'inclusion. Elle permet d'\nacc√©l√©rer\nla production interne de\nsolutions digitales\npour les activit√©s de la Compagnie\ndans les 130 pays o√π elle est pr√©sente.\nPour ce faire, elle allie l'\nagilit√©\net l'\nesprit pionnier\nd'une entreprise technologique √† la\nrobustesse\net √† la\nrigueur\nd'une entit√© de production √† grande √©chelle. Elle cr√©e et d√©ploie des solutions digitales sur l'ensemble des sites de la compagnie TotalEnergies afin de fournir une √©nergie propre, fiable et abordable au plus grand nombre.\nRejoins-nous en plein c≈ìur de Paris en tant que Data Architect, tu seras int√©gr√©(e) dans la Tech Authority qui r√©unit environ une vingtaine de personnes (Assurance Qualit√©, S√©curit√©, Architecte Software et Technique...).\nL'√©quipe √©volue dans un contexte agile √† tous les niveaux de l'organisation, en mode it√©ratif et co-constructif, en s'appuyant sur l'intelligence collective. Au sein de la Tech Authority, tu participes √† d√©terminer la gouvernance technique des projets. Tu es √©galement un soutien et un accompagnateur pour les Squads durant les diff√©rentes phases de leur projet.\nNous attendons techniquement de toi que tu :\nD√©finisses l'architecture en phase de framing.\nCo-construises cette architecture avec les Squads en phase build. Tu seras principalement en lien avec les Data Engineers et les Tech Leads. Tu valides √©galement l'architecture lorsque le besoin √©volue. Tu es amen√©(e) √† prendre des d√©cisions d'architecture tout au long de la phase de build.\nValides les mod√©lisations\nEffectues des revues p√©riodiques avec la Squad pour √©tudier le code et sa qualit√©.\nRevois l'architecture de la solution avant le transfert au m√©tier.\nTu devras √©galement faire de la veille et de l'accompagnement. Ainsi, nous attendons de toi que tu :\nD√©finisses les bonnes pratiques en mati√®re d'architecture data et que tu t'assures qu'elles sont bien respect√©es par l'ensemble des Squads.\nTe tiennes inform√©(e) des tendances, des √©volutions technologiques et des innovations en vigueur dans ton domaine d'intervention.\nCoaches les Squads dans les diff√©rentes phases de r√©alisation de leur projet avec les Chapter Lead.\nD√©bloques les Squads si n√©cessaire lorsqu'elles rencontrent un souci avec les architectures data dans les plateformes AWS et Azure.\nAnimes les communaut√©s Tech sur l'architecture au travers des Communities of Practices pr√©sentes √† la Digital Factory de TotalEnergies.\nCe que nous t'offrons:\nLe d√©veloppement de tes comp√©tences avec le support de la Digital Academy et une enveloppe √©quivalente √† environ 10 jours de formations par an que tu peux choisir en toute autonomie (formations externes et internes).\nLa possibilit√© de te certifier sur les plateformes AWS et Azure, DataBricks, ‚Ä¶\nUn programme de mentorat pour t'accompagner.\nUn √©quilibre vie professionnelle et vie personnelle avec le recours possible aux horaires flexibles et au t√©l√©travail √† domicile.\nUn environnement de travail international et interculturel en plein c≈ìur de Paris, engag√© dans la diversit√© et l'inclusion\nTu as une exp√©rience r√©ussie de 10 minimum dans la data dont 4 ans en tant que Data Architect.\nLes comp√©tences qui sont attendues de toi en tant que Data Architect :\nLes m√©thodes de travail Agile vous sont famili√®res.\nTu as une bonne connaissance dans les principes de base de data management, dans les traitements de data flow, dans les standards de data modeling et les bases du machine learning, deeplearning et dans l'industrialisation des architectures datascience.\nLes comp√©tences technologiques qui te seront indispensables :\nCloud (Azure, AWS)\nDevOps\nLangages de scripting (Python, Java...)\nBases de donn√©es SQL et NoSQL\nProcessus et outils ETL ou ELT\nLes certifications suivantes sont √©galement attendues :\nMicrosoft Certified : Azure fundamentals\nAWS certified: Solution Architect Associate\nShow more\nShow less",
        "details": {
            "JobDetail": [],
            "TypeContract": "",
            "Salary": "",
            "Level": "",
            "Experience": "4 an(s)"
        },
        "title": "data architect",
        "skills": {
            "ProgLanguage": [
                "Java",
                "Python"
            ],
            "DataBase": [
                "SQL",
                "NoSQL"
            ],
            "BigData": [
                "Databricks"
            ],
            "CloudComputing": [
                "AWS",
                "Azure"
            ],
            "Other": [
                "Machine Learning",
                "Cloud",
                "DevOps"
            ]
        }
    },
    {
        "source": "LinkedIn",
        "company": "Templeton and Partners - Tech Recruitment",
        "location": "Lyon, Auvergne-Rh√¥ne-Alpes, France",
        "link": "https://fr.linkedin.com/jobs/view/architecte-data-at-templeton-and-partners-tech-recruitment-3904841784?position=59&pageNum=0&refId=a5rwPua%2FMvx%2F2M%2FPSF0oPA%3D%3D&trackingId=RpoZyxSOnAcVD67qvV4WFQ%3D%3D&trk=public_jobs_jserp-result_search-card",
        "description": "Architecte Data\nSecteur\n: Industriel\nD√©marrage:\nASAP\nMission :\nLongue\nCadence :\nFull time\nHybrid :\n3 jours sur site (Est lyonnais)\nNous recherchons un Architecte de Donn√©es qui fera partie de l'√©quipe stable de BI & Analytics, ax√©e sur le Marketing & la Communication.\nLa Mission :\nEn tant qu'Architecte de Donn√©es, vous veillerez √† ce que les produits livr√©s par votre √©quipe stable soient align√©s sur l'architecture cible mondiale du client. Pour soutenir ce poste, nous recherchons un Architecte de Donn√©es Azure avec une bonne compr√©hension g√©n√©rale des services disponibles dans la pile d'analyse Azure.\nCette personne travaillera avec le DPO, l'Analyste de Donn√©es, l'Ing√©nieur de Donn√©es et le Data Scientist de l'√©quipe stable, mais aussi avec la communaut√© des Architectes pour d√©finir une architecture de qualit√©, de valeur commerciale pertinente et de maintenabilit√© √† long terme.\nDe plus, il/elle doit √©galement avoir des comp√©tences en leadership pour assumer le r√¥le de leader technique et discuter avec les Parties Prenantes M√©tier et l'Architecture d'Entreprise.\nVous fournissez un leadership technique, vous participez aux efforts de d√©veloppement et vous repr√©sentez l'ensemble des capacit√©s internes et externes de la plateforme.\nVous serez un membre actif de la guilde des architectes pour superviser le processus de gestion des donn√©es et fournir des orientations aux √©quipes de d√©veloppement.\nVous √™tes responsable de la conception et de la documentation de la solution dans votre domaine.\nVous avez de l'exp√©rience sur Databricks, le stockage ADLS, SQL DB, ADF et Power BI.\nVous avez de l'exp√©rience dans la d√©finition et la possession d'une architecture de donn√©es √©volutive de bout en bout en tenant compte de l'architecture d'entreprise et des normes de l'industrie.\nVous √™tes habitu√© √† d√©velopper, documenter et maintenir des mod√®les de donn√©es logiques et physiques.\nVotre future √©quipe :\nDans le cadre du Marketing & de la Communication, vous rencontrerez de nombreux d√©fis et sujets int√©ressants :\nCr√©er un tableau de bord client 360 bas√© sur les donn√©es CRM et des sources externes pour soutenir le processus marketing.\nCalculer le prix pr√©dictif des produits utilis√©s bas√© sur les donn√©es de l'OCDE gr√¢ce √† un processus d'IA.\nTableau de bord des ventes pour piloter le processus de vente.\nMettre en place un produit de donn√©es pour soutenir l'approche CAST (produit r√©utilisable partag√©) conforme √† la strat√©gie du Groupe Volvo.\nFaire partie de l'√©quipe de maintenance pour assurer la continuit√© des processus m√©tier.\nComp√©tences & Aptitudes Obligatoires :\nL'Architecture de Donn√©es est votre domaine depuis au moins 4 ans.\n√âcrire du SQL et r√©aliser de la mod√©lisation de donn√©es vous est naturel.\nConception d'Architecture de Donn√©es.\nPower BI.\nComposants Azure comme ADFv2, Databricks, Delta Lake.\nTechnologies et cadres d'Analyse Avanc√©e Azure.\nLangage de programmation li√© √† l'Analyse Avanc√©e : Python, Pyspark.\nMod√®le de livraison bas√© sur le Cloud Microsoft.\nGestion des Donn√©es, Gouvernance des Donn√©es et Qualit√© des Donn√©es.\nD√©ploiement d'API ou de microservices.\nDevSecOps.\nAgile.\nVous avez de l'exp√©rience de travail dans un environnement mondial.\nVous avez d'excellentes comp√©tences en communication en fran√ßais et en anglais (niveau C1).\nShow more\nShow less",
        "details": {
            "JobDetail": [
                "Full"
            ],
            "TypeContract": "",
            "Salary": "",
            "Level": "",
            "Experience": "4 an(s)"
        },
        "title": "data architect",
        "skills": {
            "ProgLanguage": [
                "Python"
            ],
            "DataBase": [
                "SQL"
            ],
            "BigData": [
                "Databricks"
            ],
            "DataVisualisation": [
                "Power BI",
                "Tableau"
            ],
            "CloudComputing": [
                "Azure"
            ],
            "Other": [
                "Cloud"
            ],
            "EnSoftSkils": [
                "Leadership",
                "Communication"
            ]
        }
    },
    {
        "source": "LinkedIn",
        "company": "Harnham",
        "location": "Paris",
        "link": "https://fr.linkedin.com/jobs/view/data-architect-at-harnham-3911912252?position=1&pageNum=2&refId=s27%2F43wenQFDag2sabINKw%3D%3D&trackingId=RVF4m9iXGLslJjBwC1Tixw%3D%3D&trk=public_jobs_jserp-result_search-card",
        "description": "DATA ARCHITECT\nPARIS (75)\nUP TO 65K‚Ç¨ FIXE\nAWS - Tableau - Pyspark - Data Modeling\nVous √™tes √† la recherche d'un nouveau challenge de Data Architect dans le domaine de l'assurance ? Ne cherchez plus, voici l'opportunit√© de vos r√™ves ! Une entreprise sp√©cialis√©e dans l'assurance automobile des particuliers, recherche un Data Architect dans le cadre de la cr√©ation d'une nouvelle plateforme data en Europe.\nLE POSTE\nEn tant que Data Architect, vous allez d√©finir les architectures et les normes pour la strat√©gie de donn√©es. Vous d√©finirez la vision et les lignes directrices pour la livraison des produits de donn√©es.\nVoici vos responsabilit√©s au quotidien :\nD√©finir l'architecture cible\nCommuniquer avec les Product Owner pour atteindre l'objectif du wagon\nTravailler en √©troite collaboration avec les data scientists pour op√©rationnaliser les mod√®les ML au sein de la plateforme de donn√©es\nTravailler en √©troite collaboration avec les data engineer et data ops pour le suivi de l'architecture cible\nTravailler en mode agile au quotidien\nVOTRE PROFIL\nDipl√¥me d'ing√©nieur en computer engineering ou math√©matiques\n5 ans d'exp√©rience en architecture data\nConnaissance des architectures de plateformes de donn√©es op√©rationnelles\nConnaissance de la mod√©lisation de donn√©es et bases de donn√©es\nConnaissance du cloud AWS\nConnaissance d'outils BI principalement Tableau\nBilingue (fan√ßais et anglais)\nNice to have : connaissance en Machine Learning\nPOUR POSTULER\nMerci de me faire part de votre CV et je vous recontacterai au plus vite.\nShow more\nShow less",
        "details": {
            "JobDetail": [],
            "TypeContract": "",
            "Salary": "",
            "Level": "",
            "Experience": "5 an(s)"
        },
        "title": "data architect",
        "skills": {
            "DataVisualisation": [
                "Tableau"
            ],
            "CloudComputing": [
                "AWS"
            ],
            "Other": [
                "Machine Learning",
                "Cloud",
                "ML"
            ],
            "EnSoftSkils": [
                "Collaboration"
            ]
        }
    },
    {
        "source": "LinkedIn",
        "company": "FRG Technology Consulting",
        "location": "Paris, √éle-de-France, France",
        "link": "https://fr.linkedin.com/jobs/view/architecte-data-at-frg-technology-consulting-3917370845?position=2&pageNum=2&refId=s27%2F43wenQFDag2sabINKw%3D%3D&trackingId=c%2F%2F%2BmrSZ6WTY%2B99bPhM%2Fjg%3D%3D&trk=public_jobs_jserp-result_search-card",
        "description": "Notre client, entreprise renomm√©e dans le secteur du luxe et des cosm√©tiques, bas√© sur Paris, est √† la recherche de son/sa futur(e) Architecte Data.\nEn tant que membre de la DSI, votre r√¥le est de participer √† la transformation digitale de l‚Äôentreprise, par une meilleure capture, analyse et exploitation des donn√©es clients.\nPrincipales missions :\nAnalyse et r√©ponses aux besoins des m√©tiers (BI, analyses externes, etc.),\nConception de nouveaux mod√®les de donn√©es\nConstruction des pipelines de donn√©es\nTransformation de donn√©es (Pyspark) et le stockage de donn√©es dans le Data Lake / Data Warehouse du Groupe\nRun et le suivi de la TMA\nDescription du profil :\nTitulaire Bac +5 informatique ou dipl√¥me ing√©nieur\n6 ann√©es minimum en expertise Data\nUne bonne ma√Ætrise des outils suivants : Azure, SQL, Snowflake, Databricks, Spark, Python, ELK,..\nUne bonne affinit√© avec les best practices DevOps, CI/CD, unit-testing et m√©thodologies de travail agile\nDes notions en data science sur l‚Äôentra√Ænement, la validation et le d√©ploiement de mod√®les ML supervis√©s et non-supervis√©s serait un plus.\nQualit√©s requises : Bon esprit analytique et de synth√®se, rigoureux, autonome, bonne communication, curieux, force de proposition, vulgarisation des probl√©matiques techniques aupr√®s du m√©tier\nAvantages :\nPackage (variable / participation / int√©ressement) + avantages attractifs\n√âquipe Data √† taille humaine (tr√®s bon accompagnement en interne)\nForte valeur ajout√©e des projets\nT√©l√©travail\nCandidatures confidentielles\nShow more\nShow less",
        "details": {
            "JobDetail": [],
            "TypeContract": "",
            "Salary": "Package",
            "Level": "",
            "Experience": null
        },
        "title": "data architect",
        "skills": {
            "ProgLanguage": [
                "Python"
            ],
            "DataBase": [
                "SQL"
            ],
            "BigData": [
                "Databricks",
                "Spark"
            ],
            "CloudComputing": [
                "Azure"
            ],
            "DBMS": [
                "Snowflake"
            ],
            "Other": [
                "ML",
                "DevOps",
                "CI/CD"
            ],
            "EnSoftSkils": [
                "Communication"
            ]
        }
    },
    {
        "source": "LinkedIn",
        "company": "Ippon Technologies",
        "location": "Lyon",
        "link": "https://fr.linkedin.com/jobs/view/architecte-data-f-h-at-ippon-technologies-3893256404?position=3&pageNum=2&refId=s27%2F43wenQFDag2sabINKw%3D%3D&trackingId=eNgv9c6B5TkdwhMVrnYkxg%3D%3D&trk=public_jobs_jserp-result_search-card",
        "description": "Qui sommes-nous ?\nIppon\n, c'est l‚Äô√©nergie du collectif au service de la technologie ! Nous sommes un cabinet de conseil et d‚Äôexpertise technique. Nos √©quipes ont pour leitmotive de transformer des id√©es innovantes en solutions logicielles de haute qualit√© avec un focus particulier sur la valeur apport√©e aux utilisateurs.\nCr√©√©e en 2017, l‚Äôagence de Lyon, ce sont des passionn√©s intervenant sur des projets √† forte technicit√© ou en conseil et architecture : Fullstack, Data, DevOps, Cloud, Agile, Design et ne compte pas s‚Äôarr√™ter en si bon chemin !\nLa pluridisciplinarit√©, l‚Äôexpertise, l‚Äô√©coute, l‚Äôadaptabilit√© mais aussi le partage de connaissances fondent notre engagement au service de nos partenariats.\nVous int√©grerez notre Communaut√© Data\n, compos√©e d‚Äôune √©quipe de\n80 experts sur 10 agences en France.\nNotre sp√©cialit√© est de\nconstruire des data platforms dans le Cloud public avec les meilleures technos du moment.\nLa\nData chez Ippon, c‚Äôest d√©j√† plus de\n250 certifications AWS, GCP et AZURE,\ndes\nspeakers √† l‚ÄôAWS Summit, des partenariats avec Snowflake, Databricks, DBT, un blog technique\navec des publications r√©guli√®res.\nCe poste est un vrai challenge aussi bien en termes de\nd√©fis techniques que de gestion d'√©quipe.\nLa\nr√©ussite de vos projets sera port√©e par votre capacit√© √† vous adapter et √† monopoliser un large panel de comp√©tences techniques. Vous devrez √™tre le/la leader de votre √©quipe en gardant √† l‚Äôesprit l‚Äôensemble des\nbonnes pratiques d'architectes\n, de s√©curit√© et d‚Äôautomatisation n√©cessaires √† la r√©ussite du projet. En tant que\nrepr√©sentant(e) de l‚Äôengagement d‚ÄôIppon\nsur les sujets qui vous seront confi√©s, vous serez amen√©(e) √†\ntravailler avec notre √©quipe Commerce d√®s les phases de qualification\net lors de la validation de jalons de la roadmap que vous aurez pr√©alablement valid√© avec le client. Vous interviendrez √©galement dans la s√©lection de l‚Äô√©quipe qui sera affect√©e √† votre projet.\nVotre r√¥le :\n- Gr√¢ce √† votre position d‚Äôarchitecte vous avez une vision experte et syst√©mique de l‚Äôensemble des composants d‚Äôune Modern Data Platform.\n- Vous ma√Ætrisez le panel des exigences fonctionnelles et non fonctionnelles √† collecter afin d‚Äôassurer l‚Äôefficience op√©rationnelle et la p√©rennit√© de la data platform.\n- Vous √™tes expert(e) et ma√Ætrisez tous les outils et services d‚Äôau moins un √©cosyst√®me parmi les 3 principaux leaders du march√© (AWS, Azure et GCP) et avez des facilit√©s pour √©tendre votre champ de comp√©tences.\n- Vous √™tes proactif/ve sur la veille technique et la capitalisation et veillez √† garder toujours un temps d‚Äôavance sur l‚Äô√©tat de l‚Äôart du secteur afin de pouvoir guider vos clients.\n- En tant qu‚Äôarchitecte exp√©riment√©(e) vous pouvez indiff√©remment intervenir sur des missions de delivery pour concevoir la solution cible ou en phase de cadrage amont pour guider les choix et construire les roadmaps.\n- Vous √™tes p√©dagogue et savez communiquer et vulgariser des r√©flexions complexes pour les rendre accessibles √† tous.\nNotre √©co-syst√®me technique :\n- Cloud : AWS, GCP, Azure\n- Langage de programmation data : Python, SQL, Scala\n- Approche Data Warehouse : Redshift, Snowflake, BigQuery\n- Approche Data Lakehouse : Databricks, Starburst, Glue-Athena-S3Ingestion : AWS Glue, Airbyte, dbt Stockage : AWS S3, Google Cloud Storage, Azure Blob Storage\n- Orchestration : Airflow, AWS Step function\n- Gouvernance : cataloging, s√©curit√©, scope d'acc√®sBatch et Streaming : Kafka, Amazon Kinesis, Google DataFlow\n- Outil de visualisation : Tableau, Power BI, Metabase, Superset\nVotre √©volution chez Ippon :\nVous serez accompagn√©(e) dans votre mont√©e en comp√©tences aussi bien technique que leadership gr√¢ce √†\nnotre programme BlackBelt\n(programme de formation continue : mentoring, formations, certifications).\nEn tant que membre d‚Äôune communaut√©,\nvous pouvez avoir diff√©rents r√¥les :\n- Celui de Manager Technique (MT) : manager d‚Äôune √©quipe de 7 ing√©nieur(e)s Ippon (onboarding, suivis, accompagnement, mise en place d‚Äôobjectifs‚Ä¶). Vous conduirez les entretiens techniques en bin√¥me\n- Responsable de l‚Äôaccomplissement d‚Äôune ou plusieurs actions strat√©giques de la CoreTeam Data\n- Devenir speaker lors de Meetup, Summit, Talks internes, aupr√®s des √©coles ‚Ä¶\n- Devenir formateur(trice) et accompagner la nouvelle g√©n√©ration d‚ÄôIppon dans leur mont√©e en comp√©tencesVous avez d‚Äôautres souhaits, pas de soucis, nous en discuterons durant notre √©change et r√©pondrons √† toutes vos questions.\nLes Next Steps :\n1 Echange RH\n1 Echange Technique\n1 Echange avec la Direction\nSi le match est bon des deux c√¥t√©s : Vous vous lancerez sur le tatami Ippon !\nShow more\nShow less",
        "details": {
            "JobDetail": [
                "Full"
            ],
            "TypeContract": "",
            "Salary": "",
            "Level": "",
            "Experience": null
        },
        "title": "data architect",
        "skills": {
            "ProgLanguage": [
                "Scala",
                "Python"
            ],
            "DataBase": [
                "SQL"
            ],
            "BigData": [
                "Databricks"
            ],
            "DataVisualisation": [
                "Power BI",
                "Tableau"
            ],
            "CloudComputing": [
                "GCP",
                "AWS",
                "Azure"
            ],
            "DBMS": [
                "BigQuery",
                "Snowflake"
            ],
            "Automation": [
                "Airflow"
            ],
            "Other": [
                "Cloud",
                "DevOps"
            ],
            "EnSoftSkils": [
                "Leadership"
            ]
        }
    },
    {
        "source": "LinkedIn",
        "company": "Akademija Oxford",
        "location": "Boulogne-Billancourt, √éle-de-France, France",
        "link": "https://fr.linkedin.com/jobs/view/data-analyst-junior-h-f-at-akademija-oxford-3917871112?position=4&pageNum=2&refId=s27%2F43wenQFDag2sabINKw%3D%3D&trackingId=A3sTIrvtclaO2d7xjfPfTw%3D%3D&trk=public_jobs_jserp-result_search-card",
        "description": "Notre entreprise partenaire, sp√©cialiste de la vente de m√©dicaments et produits de sant√©, recherche un apprenti Data Analyst (H/F) pr√©parant un bac +4/+5 en fili√®re Big Data pour la rentr√©e de Septembre 2021.\nShow more\nShow less",
        "details": {
            "JobDetail": [],
            "TypeContract": "",
            "Salary": "",
            "Level": "",
            "Experience": null
        },
        "title": "data analyst",
        "skills": {
            "Other": [
                "Big Data"
            ]
        }
    },
    {
        "source": "LinkedIn",
        "company": "FRG Technology Consulting",
        "location": "Paris, √éle-de-France, France",
        "link": "https://fr.linkedin.com/jobs/view/data-architect-azure-at-frg-technology-consulting-3902057360?position=5&pageNum=2&refId=s27%2F43wenQFDag2sabINKw%3D%3D&trackingId=NwAL8xb%2BL044hdpxUUfrXA%3D%3D&trk=public_jobs_jserp-result_search-card",
        "description": "FRG Consulting recrute pour l'un de ses clients, une soci√©t√© finale renomm√©e dans le secteur du luxe et des cosm√©tiques, un Data Architect expert en Azure. Nich√© au c≈ìur de Paris, vous aurez l'opportunit√© de travailler au sein d'une √©quipe passionn√©e par la recherche et l'innovation, √©voluant dans un environnement stimulant et cr√©atif.\nVos missions captivantes :\nContribuer √† l'√©volution de nos syst√®mes en d√©veloppant de nouveaux connecteurs et pipelines pour l'extraction de donn√©es, qu'il s'agisse de batch (utilisant Sqoop, scripts bash, Java ou des API) ou de streaming (via Kafka, ELK).\nParticiper activement √† la transformation des donn√©es √† l'aide de Pyspark, ainsi qu'au stockage dans notre Data Lake et notre Data Warehouse.\nConcevoir de nouveaux mod√®les de donn√©es et mettre √† disposition des tables ad-hoc sur Snowflake et Impala, r√©pondant ainsi aux besoins m√©tier en termes de BI et d'analyses externes.\nAssurer le bon fonctionnement et le suivi de la TMA du Data Lake, garantissant ainsi la fiabilit√© et la performance de nos syst√®mes.\nProfil recherch√© :\nVous b√©n√©ficiez d'au moins 8 ans d'exp√©rience dans le domaine.\nVous ma√Ætrisez les outils et frameworks de notre stack technique Big Data : Azure, SQL, Snowflake, Databricks, Spark, Python, ELK.\nVous √™tes familier des best practices DevOps, CI/CD, et des m√©thodologies de travail agile.\nDes comp√©tences en data science, notamment sur l'entra√Ænement, la validation et le d√©ploiement de mod√®les ML supervis√©s et non-supervis√©s, seraient grandement appr√©ci√©es.\nLa ma√Ætrise de l'anglais est indispensable pour √©voluer dans un environnement international et dynamique.\nShow more\nShow less",
        "details": {
            "JobDetail": [],
            "TypeContract": "",
            "Salary": "",
            "Level": "",
            "Experience": "8 an(s)"
        },
        "title": "data architect",
        "skills": {
            "ProgLanguage": [
                "Java",
                "Bash",
                "Python"
            ],
            "DataBase": [
                "SQL"
            ],
            "BigData": [
                "Databricks",
                "Spark"
            ],
            "CloudComputing": [
                "Azure"
            ],
            "DBMS": [
                "Snowflake"
            ],
            "Other": [
                "ML",
                "Big Data",
                "DevOps",
                "CI/CD"
            ]
        }
    },
    {
        "source": "LinkedIn",
        "company": "TeamWork Corporate",
        "location": "Saint-Priest, Auvergne-Rh√¥ne-Alpes, France",
        "link": "https://fr.linkedin.com/jobs/view/data-architect-senior-freelance-h-f-at-teamwork-corporate-3916528778?position=6&pageNum=2&refId=s27%2F43wenQFDag2sabINKw%3D%3D&trackingId=yaz2%2FJwMWVF6OWDperGC1w%3D%3D&trk=public_jobs_jserp-result_search-card",
        "description": "Description de l'entreprise\nTeamWork est un acteur majeur du conseil, de l‚Äôint√©gration technologique et de l‚Äôinnovation, implant√© en Europe, en Asie et en Am√©rique du Nord.\nAu travers de ses univers, SAP Business Solutions, Data Analytics, Technology Platform et Salesforce, nous sommes reconnus par nos clients pour accro√Ætre leur performance op√©rationnelle.\nLa transformation digitale est un enjeu majeur pour toute organisation.\nLa n√©cessit√© de digitaliser ses processus, d‚Äôimaginer de nouvelles fa√ßons d‚Äôinteragir avec ses clients, d‚Äôen conqu√©rir de nouveaux et de proposer de nouveaux outils pour anticiper les besoins de pilotage‚ÄØn‚Äôa jamais √©t√© aussi forte.\nL‚Äôunivers Data Analytics de TeamWork accompagne les organisations autour de :\nLa r√©flexion et identification de cas d‚Äôusage pour les transformer en trajectoires moyen et long terme\nLe design et l‚Äôimpl√©mentation de plateforme de donn√©es et des outils p√©riph√©riques (data ingestion/int√©gration)\nLa mise en place des premi√®res solutions‚ÄØd‚ÄôAnalytics (Business Intelligence, EPM,)\nSupport, extension et optimisation des solutions\nDans le cadre du d√©veloppement de ces activit√©s, nous recrutons un\nData Architect Senior (H/F)\nen Freelance pour une mission entre 2 √† 3 mois.\nDescription du poste\nEn tant qu‚ÄôArchitecte Data vous intervenez dans le cadre de projets et missions qui r√©pondent aux enjeux clients d‚Äôexploitation des donn√©es. Vous participez aux phases d‚Äôavant-vente, aux √©tudes d‚Äôarchitecture, et √† la r√©alisation des solutions avec une responsabilit√© d‚Äôencadrement technique des projets (tant sur des forfaits que des missions clients). Vous aurez des missions avec de r√©elles responsabilit√©s et tr√®s diversifi√©es (secteurs d‚Äôactivit√©s vari√©s).\nVos principales missions s‚Äôarticulent autour de :\nL‚Äôanalyse et la qualification des besoins et probl√©matiques ¬´ m√©tiers ¬ª de nos clients\nAssurer la conception, le d√©veloppement et la mise en oeuvre de l'architecture des donn√©es sur la plateforme Databricks\nLa d√©finition et mise en ≈ìuvre des architectures Data adapt√©es aux contextes des projets : Modern Datawarehouse, LakeHouse, DataMesh etc.\nL‚Äôaccompagnement des Consultants et des Ing√©nieurs sp√©cialistes Data sur les projets. Vous ≈ìuvrez √† qualit√© de leurs r√©alisations et des livrables.\nLa collaboration sur tous les domaines d‚Äôactivit√©s DATA : BI, Big Data, IoT, IA\nL‚Äôapport d‚Äôun regard critique et la capacit√© √† conseiller sur le choix des technologies Data\nLa participation √† la d√©finition des bonnes pratiques de mises en ≈ìuvres techniques et la veille √† leurs applications selon les m√©thodes en vigueur (Zero Trust Security, DataOps, Infra-as-Code, Tests automatis√©s etc.)\nQualifications\nTechniques :\nVous avez :\nTr√®s bonnes connaissances de Databricks\nLa capacit√© √† r√©aliser la conception et l‚Äôimpl√©mentation de solutions d‚Äôanalytique √† l‚Äô√©chelle de l‚Äôentreprise ; SQL\nLa connaissance d‚Äôun ou plusieurs outils ETL (Azure Data Factory ou autres) et Data Visualisation (PowerBI par exemple)\nLa capacit√© √† mettre en place une solution Data end-to-end La connaissances des typologies d‚Äôarchitectures (Modern Datawarehouse, LakeHouse ou DataMesh)\nVous connaissez l‚Äôenvironnement Azure, MSBI, SQL Server ou si vous avez des notions dans l‚ÄôIA (Python, R, Machine Learning)\nMaitrise le traitement et l'analyse des donn√©es en Python (Exp√©rience dans la conception et le d√©veloppement de processus ETL/ELT)\nMaitrise d‚Äôoutils de traitement et de stockage distribu√©s parmi Hadoop, Spark, Databricks, Snowflake et/ou Kafka\nConnaissance des bonnes pratiques de conception d‚Äôarchitecture data (s√©curit√©, disponibilit√©, scalabilit√©, confidentialit√©) et des principes d‚Äôune architecture Data Mesh.\nCapacit√© √† concevoir des architectures bas√©es sur les services d‚Äôune plateforme Cloud : AWS ou Azure\nSoft Skills\n:\nVous √™tes proactif et appr√©ciez travailler dans un environnement ambitieux et innovant.\nVous aimez ne pas rester sur vos acquis et toujours apprendre par le biais de formations, votre veille technologique ou encore par la participation aux √©v√©nements communautaires.\nHabitu√© √† travailler aussi bien de fa√ßon autonome qu‚Äô√† collaborer en √©quipe\nConnaissance des m√©thodologies Agile (SCRUM ou autres)\nEnvie d‚Äôapprendre et de partager vos savoir-faire\nCuriosit√©\nLangues :\nFran√ßais (Courant)\nAnglais (A l‚Äôaise en communication orale et √©crite)\nFormation\n:\nV√©ritable passionn√© par la DATA et dipl√¥m√© d‚Äôune √©cole d‚Äôing√©nieur (Bac+3 minimum) ou d'une formation sp√©cifique orient√©e Data avec une exp√©rience significative en Data Engineering et architecture.\nVous avez une exp√©rience de plus de 7 ans en environnement informatique, dont 3 √† 4 ans minimum sur un poste senior en environnement Databricks (Team Lead, Architecte ou encore Consultant Senior).\nNous attacherons davantage d‚Äôimportance √† votre capacit√© √† vouloir apprendre et progresser et votre motivation qu‚Äô√† votre dipl√¥me.\nInformations suppl√©mentaires\nTeamWork, o√π votre √©panouissement professionnel est cl√©. R√©compens√©s par le label 'Great Place to Work 2023', nous pla√ßons l'humain au c≈ìur de notre entreprise.\nAu-del√† des comp√©tences, nous valorisons les personnalit√©s qui partagent nos valeurs de solidarit√© et d'esprit d'√©quipe.\nSi ces principes vous parlent, rejoignez-nous ! Nous sommes d√©di√©s √† l'√©quit√© et √† la diversit√©, ouvrant nos portes √† tous les talents, y compris aux personnes en situation de handicap.\nPostulez et devenez un acteur de notre r√©ussite collective chez TeamWork.\nShow more\nShow less",
        "details": {
            "JobDetail": [
                "Senior"
            ],
            "TypeContract": "",
            "Salary": "",
            "Level": "Bac+3",
            "Experience": "7 an(s)"
        },
        "title": "data architect",
        "skills": {
            "ProgLanguage": [
                "R",
                "Python"
            ],
            "DataBase": [
                "SQL"
            ],
            "DataAnalytics": [
                "R"
            ],
            "BigData": [
                "Databricks",
                "Hadoop",
                "Spark"
            ],
            "CloudComputing": [
                "AWS",
                "Azure"
            ],
            "DBMS": [
                "SQL Server",
                "Snowflake"
            ],
            "Other": [
                "Machine Learning",
                "Cloud",
                "Big Data"
            ],
            "EnSoftSkils": [
                "Teamwork",
                "Communication",
                "Collaboration"
            ]
        }
    },
    {
        "source": "LinkedIn",
        "company": "Airbus",
        "location": "Saint-Nazaire",
        "link": "https://fr.linkedin.com/jobs/view/airbus-atlantic-architecte-data-all-gender-at-airbus-3916426275?position=7&pageNum=2&refId=s27%2F43wenQFDag2sabINKw%3D%3D&trackingId=bxP4EpffbA1eb29JFyQBdA%3D%3D&trk=public_jobs_jserp-result_search-card",
        "description": "Job Description\nEt si VOTRE aventure avec NOUS commen√ßait ?!\nNous vous proposons de travailler chez Airbus Atlantic, nouveau champion de dimension mondiale, n¬∞2 des a√©rostructures, n¬∞1 des si√®ges pilotes et dans le Top 3 des fauteuils passagers Premium.\nNotre site Airbus Atlantic bas√©\n√† Toulouse (possibilit√© de travailler √† Montoir de Bretagne)\nrecherche son futur\nArchitecte Data (All Gender)\nLe poste d‚Äôarchitecte Data est rattach√© au domaine ¬´ Architecture ¬ª au sein du d√©partement ¬´ Architecture Digital & S√©curit√© ¬ª.\nVous serez en interface avec les architectes du Syst√®me d'Information et les diff√©rents m√©tiers consommateurs des architectures.\nVos Principales Missions Seront Les Suivantes\nFixer les orientations et d√©finir des politiques concernant la mod√©lisation des donn√©es, en collaboration avec les autres architectes,\nCr√©er des mod√®les de donn√©es logiques et physiques en utilisant les meilleures pratiques pour garantir une qualit√© √©lev√©e des donn√©es et une r√©duction de leur redondance,\nInstancier, impl√©menter, construire, tester et maintenir les architectures data d√©finies\nAnalyser, √©valuer, tester et recommander les briques technologiques n√©cessaires pour l‚Äôacquisition, l‚Äôanalyse et l‚Äôimpl√©mentation des donn√©es,\nAnalyser les probl√®mes d'int√©gration des syst√®mes li√©s aux donn√©es et proposer des solutions appropri√©es,\nD√©terminer les ¬´ Data set process ¬ª c‚Äôest √† dire comment les donn√©es sont int√©gr√©es et transform√©es pour qu‚Äôelles soient pr√™tes √† √™tre analys√©es (ex : ETL)\nParticiper aux processus d'extraction performants et qualitatifs des donn√©es des sources requises afin de r√©pondre aux besoins de l'entreprise\nMaintenir les mod√®les de donn√©es conceptuels, logiques et physiques ainsi que les m√©tadonn√©es correspondantes (pour la data gouvernance).\nD√©velopper les meilleures pratiques pour les conventions de d√©nomination standard et les pratiques de codage afin d'assurer la coh√©rence des mod√®les de donn√©es,\nRespecter les normes de s√©curit√© des donn√©es, de contr√¥le des exportations et de protection des donn√©es.\nConstruire les pipelines qui permettront aux Data Scientist/Analysts/Developers de mettre leurs mod√®les en production\nEtre garant de la fiabilit√©, de la qualit√© et de l‚Äôefficacit√© du traitement des donn√©es\nMaintenir les mod√®les cr√©√©s.\nParticiper aux id√©ations et proposer des innovations aux services.\nDocumenter ses activit√©s et mettre √† jour le r√©f√©rentiel documentaire.\nParlons de vous !\nVous disposez d'une\ne\nxp\n√©rience de minimum 5 ans en Data & Informatique sur un poste similaire.\nLes comp√©tences techniques √† d√©tenir pour le poste :\nL‚Äôoptimisation et les standards Qualit√© des donn√©es informatiques\nComprendre et savoir mettre en place les diff√©rentes Structure et stockage de donn√©es\nGestion des probl√®mes li√© √† la donn√©e, l'architecture\nId√©alement, l'exp√©rience des technologies suivantes serait un plus : Ressources & services data MS Azure (Databricks, Azure ML ‚Ä¶), SGBD (SQL, MongoDB, PostGreSQL, redis), Outils ETL (Qlik replicate, Alteryx, ‚Ä¶), Outils BI (PowerBI, Qlik, Grafana ...),\nLangages de programmation (python, SCALA, R, DAX)\nLes certifications de Azure (DP-203, AZ-300, AZ-303, AZ-304, AZ-400, AI-900) seraient un plus,\nVotre Personnalit√©\nFort volont√© de travailler en √©quipe\nBonnes habitudes de documentation\nNiveau avanc√© en Fran√ßais et en Anglais (niveau minimum B1)\nFaire preuve d‚Äôinnovation et √™tre source de proposition\nSavoir exprimer ses id√©es de mani√®re claire et concise\nEtre √† l'√©coute\nParlons de nous !\nEnvironnement & Conditions De Travail\nAirbus Atlantic c‚Äôest aussi :\nPrendre part √† des projets ambitieux, √† la pointe de la technologie pour construire l‚Äôavion de demain, en lien avec les enjeux environnementaux.\nUn environnement qui valorise la proximit√© et la dimension humaine, au sein d‚Äôun collectif engag√© et solidaire.\nL‚Äôopportunit√© d‚Äôapprendre et d‚Äô√©voluer tout au long de votre parcours, en √©tant accompagn√© dans votre d√©veloppement pour une carri√®re sur-mesure.\nAvoir la libert√© d‚Äôentreprendre et de laisser libre court √† vos initiatives.\nSes conditions de travail attractives et ses avantages : restaurant d‚Äôentreprise sur site, CSE (avantages loisirs & famille), parking entreprise, mutuelle d‚Äôentreprise (famille).\nSa politique de diversit√© et d'inclusion : Airbus Atlantic s‚Äôengage en faveur de l‚Äô√©galit√© des chances pour tous.\nSon plan d'actionnariat salari√© et son plan d‚Äô√©pargne salariale.\nNotre Processus De Recrutement\nNous avons √† c≈ìur de mieux vous conna√Ætre et de comprendre ce qui vous motive √† nous rejoindre. Aussi, notre process de recrutement se d√©roule en plusieurs √©tapes apr√®s analyse de votre candidature :\nEntretien vid√©o diff√©r√© via la plateforme Hirevue\nEntretien avec le Manager Recruteur\nEntretien avec le/la Charg√©(e) de Recrutement qui peut √™tre compl√©t√© par un questionnaire de personnalit√©\nEntretien avec le/la Human Resources Business Partner.\nThis job requires an awareness of any potential compliance risks and a commitment to act with integrity, as the foundation for the Company‚Äôs success, reputation and sustainable growth.\nCompany\nAirbus Atlantic\nContract Type\nPermanent\nClasse Emploi (France): Classe G13\nExperience Level\nProfessional\nJob Family\nDigital\nBy submitting your CV or application you are consenting to Airbus using and storing information about you for monitoring purposes relating to your application or future employment. This information will only be used by Airbus.\nAirbus is committed to achieving workforce diversity and creating an inclusive working environment. We welcome all applications irrespective of social and cultural background, age, gender, disability, sexual orientation or religious belief.\nAirbus is, and always has been, committed to equal opportunities for all. As such, we will never ask for any type of monetary exchange in the frame of a recruitment process. Any impersonation of Airbus to do so should be reported to emsom@airbus.com.\nAt Airbus, we support you to work, connect and collaborate more easily and flexibly. Wherever possible, we foster flexible working arrangements to stimulate innovative thinking.\nShow more\nShow less",
        "details": {
            "JobDetail": [],
            "TypeContract": "",
            "Salary": "",
            "Level": "",
            "Experience": "5 an(s)"
        },
        "title": "data architect",
        "skills": {
            "ProgLanguage": [
                "R",
                "Scala",
                "Python"
            ],
            "DataBase": [
                "SQL",
                "MongoDB"
            ],
            "DataAnalytics": [
                "R"
            ],
            "BigData": [
                "Databricks"
            ],
            "CloudComputing": [
                "Azure"
            ],
            "DBMS": [
                "PostgreSQL"
            ],
            "Other": [
                "ML"
            ],
            "EnSoftSkils": [
                "Collaboration"
            ]
        }
    },
    {
        "source": "LinkedIn",
        "company": "Capgemini",
        "location": "Nantes, Pays de la Loire, France",
        "link": "https://fr.linkedin.com/jobs/view/architecte-technique-bi-big-data-nantes-at-capgemini-3803994992?position=8&pageNum=2&refId=s27%2F43wenQFDag2sabINKw%3D%3D&trackingId=7FHNSEfvjMmvL7Q5xmN9%2FQ%3D%3D&trk=public_jobs_jserp-result_search-card",
        "description": "Capgemini\nChoisir Capgemini, c'est choisir une entreprise o√π vous serez en mesure de fa√ßonner votre carri√®re selon vos aspirations, o√π vous serez soutenu et inspir√© par une communaut√© d‚Äôexperts dans le monde entier, o√π vous pourrez r√©√©crire votre futur. Rejoignez-nous pour red√©finir les limites de ce qui est possible, contribuer √† lib√©rer la valeur de la technologie pour les plus grandes organisations et participez √† la construction d‚Äôun monde plus durable et inclusif.\nVos missions :\nInt√©gr√©(e) au sein d'une √©quipe projets intervenant pour des clients dans des secteurs d'activit√©s vari√©es, vous serez notamment en charge des missions suivantes :\nInteragir avec nos clients, nos partenaires pour concevoir et mettre en ≈ìuvre des solutions/projets innovants et comp√©titifs\nR√©pondre aux probl√©matiques de nos clients en proposant la meilleure plateforme data dans un environnement Agile\nAdapter chaque architecture en fonction du contexte gr√¢ce √† votre ma√Ætrise des caract√©ristiques fondamentales de chaque solution (catalogue des offres de services manag√©s, performance, s√©curit√©, d√©ploiement des data centers ‚Ä¶)\nUtiliser les solutions d‚Äôint√©gration associ√©es et les solutions d√©cisionnelles ainsi qu‚Äôanalytiques qui viennent consommer les donn√©es manipul√©es\nEncadrer les √©quipes dans la mise en place des architectures pr√©conis√©es et/ ou des plateformes Data\nVous avez acquis de l‚Äôexp√©rience sur les cadres de r√©f√©rence et patterns d‚Äôarchitecture Data, DevOps.\nVotre profil :\nDipl√¥me d‚Äôing√©nieur ou √©quivalent universitaire\nMinimum 6 ans d'exp√©rience\nAnglais courant\nExpertise dans la conception d‚Äôarchitecture, la mise en ≈ìuvre et/ou le support d‚Äôapplications hautement distribu√©es\nSensibilisation √† la m√©thode devops et connaissance d‚Äôun outil de de Continuous Integration/Continuous Delivery (CI-CD)\nExpertise sur les services Cloud Data suivants (Azure, AWS, GCP)\nGrande aisance dans la communication orale et √©crite, leadership afin de f√©d√©rer des √©quipes\n3 raisons de nous rejoindre :\nQualit√© de vie au travail : accord de t√©l√©travail en France et √† l‚Äôinternational, accord sur l‚Äô√©galit√©\nprofessionnelle, la parentalit√©, l‚Äô√©quilibre des temps et la mobilit√© durable.\nApprentissage en continu : certifications et formations en libre acc√®s, accompagnement sur mesure avec votre carreer manager, parcours d‚Äôint√©gration sur 9 mois.\nAvantages groupe & CSE : plan actionnariat, activit√©s √† tarifs pr√©f√©rentiels, remboursement partiel\nvacances, remboursement de votre abonnement sportif ou culturel.\nNos engagements et priorit√©s :\nLe groupe Capgemini encourage une culture inclusive dans un cadre multiculturel et handi-accueillant. En nous rejoignant, vous int√©grez un collectif qui valorise la diversit√©, d√©veloppe le potentiel de ses talents, s‚Äôengage dans des initiatives solidaires avec ses partenaires, et se mobilise pour r√©duire son impact environnemental sur tous ses sites et aupr√®s de ses clients.\nCapgemini\nCapgemini est un leader mondial, responsable et multiculturel, regroupant pr√®s de 350 000 personnes dans plus de 50 pays. Fort de 55 ans d‚Äôexp√©rience, nous sommes un partenaire strat√©gique des entreprises pour la transformation de leurs activit√©s en tirant profit de toute la puissance de la technologie et des innovations dans les domaines en perp√©tuelle √©volution tels que le cloud, la data, l‚ÄôIntelligence Artificielle, la connectivit√©, les logiciels, l‚Äôing√©nierie digitale ou les plateformes.\nGet The Future You Want* | www.capgemini.com/fr-fr\n*Capgemini, le futur que vous voulez\nShow more\nShow less",
        "details": {
            "JobDetail": [],
            "TypeContract": "",
            "Salary": "",
            "Level": "",
            "Experience": "6 an(s)"
        },
        "title": "data architect",
        "skills": {
            "CloudComputing": [
                "GCP",
                "AWS",
                "Azure"
            ],
            "Other": [
                "Cloud",
                "DevOps"
            ],
            "EnSoftSkils": [
                "Leadership",
                "Communication"
            ]
        }
    },
    {
        "source": "LinkedIn",
        "company": "EXAKIS NELITE",
        "location": "Grenoble, Auvergne-Rh√¥ne-Alpes, France",
        "link": "https://fr.linkedin.com/jobs/view/architecte-conseil-data-h-f-at-exakis-nelite-3813458944?position=9&pageNum=2&refId=s27%2F43wenQFDag2sabINKw%3D%3D&trackingId=sFkATwbM7Wt2uLFv7VyJuQ%3D%3D&trk=public_jobs_jserp-result_search-card",
        "description": "Exakis Nelite, entit√© du groupe\nMagellan Partners\n, est le\n1er partenaire pure-player Microsoft\nind√©pendant en France avec l‚Äôambition de devenir le premier partenaire Europ√©en et en Afrique Francophone avec sa forte pr√©sence au Maroc.\nN√©s du rapprochement de 2 leaders sp√©cialistes de l‚Äôint√©gration des solutions Microsoft, nous allions expertise technique et fonctionnelle pour r√©pondre concr√®tement aux enjeux de demain : acc√©l√©ration de la transformation digitale,\nCyberS√©curit√©, Intelligence Artificielle, IoT, Data, transformation vers le cloud Azure, Services Cognitifs ‚Ä¶\nEn rejoignant la communaut√© Exakis Nelite dans l‚Äôune de nos 12 agences (680 collaborateurs), vous int√©grerez une √©quipe passionn√©e et impliqu√©e dans les projets les plus innovants. Vous rejoindrez une structure construite autour de valeurs tourn√©es vers ses collaborateurs : intelligence collective, convivialit√© et bienveillance.\nExakis Nelite a re√ßu la certification\nGreat Place to Work\net se place\n3√®me de sa cat√©gorie\nen 2024 parmi les entreprises o√π il fait bon travailler en France !\n√Ä quoi ressembleront vos futures missions ?\nEn tant qu‚ÄôArchitecte et Conseil, dans les domaines Data et Business Intelligence, vous serez amen√© √† travailler sur des projets d‚Äôenvergure mettant √† l‚Äô√©preuve votre exp√©rience des syst√®mes de donn√©es et votre ouverture vers les technologies de BI moderne et cloud.\nVotre r√¥le d‚Äôarchitecte et de conseil aupr√®s de nos clients trouvera son sens dans la comp√©tence que pourrez apporter autour des solutions Microsoft (Power BI, Azure‚Ä¶), et aussi dans la connaissance globale que vous aurez acquise par vos exp√©riences vari√©es. Cette combinaison comp√©tence/exp√©rience aura pour but d‚Äôorchestrer l‚Äôimpl√©mentation des technologies Microsoft dans des syst√®mes d‚Äôinformation et d√©cisionnels technologiquement h√©t√©rog√®nes.\nVotre passion, votre curiosit√© et votre envie sont les ma√Ætres mots pour r√©ussir dans ce poste. Vous √™tes motiv√© pour travailler dans un environnement dynamique o√π la donn√©e se d√©cline autour de nos projets innovants (IoT, Industrie 4.0, IA‚Ä¶). Vous avez une vision claire des enjeux actuels autour de la donn√©e.\nDescription du poste\nSelon les missions vous serez amen√© √† :\nAccompagner nos clients dans leur strat√©gie digitale\nAnimer des ateliers d‚Äôarchitecture technique\nAppr√©hender les besoins fonctionnels et les contraintes techniques du client\nPr√©coniser des architectures complexes pour r√©pondre √† une probl√©matique ou un besoin m√©tier\nD√©finir et am√©liorer les standards, patterns d‚Äôarchitecture et le catalogue de services\nSuperviser et mettre en ≈ìuvre, dans le cadre des projets, les pr√©conisations techniques √©tablies dans le cadre des cahiers des charges\nR√©aliser l‚Äôarchitecture de donn√©es dans des environnements on Premise\nIntervenir sur l‚Äôarchitecture Azure data\nR√©diger les documents associ√©s (HLD, LLD, etc.)\nPiloter des projets et des hommes\nIntervenir en toute autonomie sur les phases de cadrage technique et/ou avant ventes\nAssurer une veille technologique\nProfil\nFort d‚Äôune exp√©rience de 3 √† 15 ans dans les domaines, Data, BI et Big Data, vous portez de l‚Äôint√©r√™t aux technologies du Cloud, aux approches de BI moderne et √† leur d√©veloppement. Vous √™tes un professionnel aguerri des environnements Data, de l‚Äôarchitecture et de l‚Äôutilisation des technologies Cloud.\nLa connaissance des environnements Microsoft (Power BI, SQL Server, Azure‚Ä¶) est un plus mais n‚Äôest pas une obligation. La diversit√© de vos exp√©riences dans le champ d‚Äôactivit√© Data/BI est le facteur clef de succ√®s de ce poste.\nCurieux et dynamique, vous avez le gout du challenge et souhaitez prendre part au d√©veloppement important d‚ÄôExakis Nelite et de Magellan Partners dans le domaine des Data-sciences.\nShow more\nShow less",
        "details": {
            "JobDetail": [],
            "TypeContract": "",
            "Salary": "",
            "Level": "",
            "Experience": "15 an(s)"
        },
        "title": "data architect",
        "skills": {
            "DataBase": [
                "SQL"
            ],
            "DataVisualisation": [
                "Power BI"
            ],
            "CloudComputing": [
                "Azure"
            ],
            "DBMS": [
                "SQL Server"
            ],
            "Other": [
                "Cloud",
                "Big Data"
            ]
        }
    },
    {
        "source": "LinkedIn",
        "company": "SIBIOS",
        "location": "Lyon, Auvergne-Rh√¥ne-Alpes, France",
        "link": "https://fr.linkedin.com/jobs/view/data-architect-manager-at-sibios-3881612188?position=10&pageNum=2&refId=s27%2F43wenQFDag2sabINKw%3D%3D&trackingId=VKlC%2FXFyXvWYWqlKEhzgWw%3D%3D&trk=public_jobs_jserp-result_search-card",
        "description": "SIBIOS recherche un consultant Senior DATA / ARCHITECT Manager avec minium 10 ans d'exp√©rience pour un nouveau projet dans le secteur industriel.\nUne bonne connaissance d'architecture fonctionnelle et l'urbanisation data, ainsi que des r√®gles de s√©curit√©.\nVous avez une ma√Ætrise de la gestion des donn√©es et des outils/langages correspondants (SQL, Power BI, mod√©lisation et visualisation des donn√©es, ...)\nDiriger des projets Data sur divers domaines fonctionnels (M√©tier et IT) pour d√©finir les feuilles de route.\nD√©finir la gouvernance de chaque projet et suivre le planning, le budget, la qualit√© et les risques sur chaque projet\nPiloter la gestion du changement et communiquer autour des projets\nIndustrialisation des innovations digitales : gouvernance, socle technique, documentation et support\nPour un entretien imm√©diat, merci de nous faire suivre votre cv mis √° jour en word format ainsi que votre date de disponibilit√© et TJM.\nShow more\nShow less",
        "details": {
            "JobDetail": [
                "Senior"
            ],
            "TypeContract": "",
            "Salary": "",
            "Level": "",
            "Experience": "10 an(s)"
        },
        "title": "data architect",
        "skills": {
            "DataBase": [
                "SQL"
            ],
            "DataVisualisation": [
                "Power BI"
            ]
        }
    }
]