[
    {
        "source": "LinkedIn",
        "company": "Akademija Oxford",
        "location": "Boulogne-Billancourt, √éle-de-France, France",
        "link": "https://fr.linkedin.com/jobs/view/data-analyst-at-akademija-oxford-3917868480?position=2&pageNum=0&refId=jBvsgtdGm8ta0dsilpa8wg%3D%3D&trackingId=2CwkzoUGCXsijBVJxieuIQ%3D%3D&trk=public_jobs_jserp-result_search-card",
        "description": "Nos collaborateurs travaillent au quotidien avec tous les m√©tiers et avec notre r√©seau international. Et pour √™tre au top de l‚Äôinnovation, on a ce qui se fait de mieux en mati√®re d‚Äôenvironnement de travail et d‚Äôoutils technos : datalab, delta room, intelligence artificielle, machine learning‚Ä¶\nR√©sultats ? Une activit√© multipli√©e par 2 en 3 ans (et ce n‚Äôest pas fini), une expertise reconnue et une position de leader en France.\nBienvenue au c≈ìur du big bang !\nShow more\nShow less",
        "details": {
            "JobDetail": [],
            "TypeContract": "",
            "Salary": "",
            "Level": "",
            "Experience": "3 an(s)"
        },
        "title": "data analyst",
        "skills": {
            "Other": [
                "Machine Learning"
            ]
        }
    },
    {
        "source": "LinkedIn",
        "company": "Akademija Oxford",
        "location": "Ille-et-Vilaine, Brittany, France",
        "link": "https://fr.linkedin.com/jobs/view/data-analyst-at-akademija-oxford-3917868488?position=3&pageNum=0&refId=jBvsgtdGm8ta0dsilpa8wg%3D%3D&trackingId=BNUusJQE4Ycib3V28fZ5xQ%3D%3D&trk=public_jobs_jserp-result_search-card",
        "description": "Dipl√¥m√©(e) d‚Äôun bac+2 dans le secteur informatique et plus pr√©cis√©ment dans le domaine du d√©veloppement.\nDans le cadre d‚Äôun contrat d‚Äôapprentissage de 12 mois, nous recherchons pour l‚Äôun de nos partenaires, un Data Analyst qui souhaite apporter ses comp√©tences techniques tout en faisant preuve d‚Äôun excellent savoir-√™tre.\nShow more\nShow less",
        "details": {
            "JobDetail": [],
            "TypeContract": "",
            "Salary": "",
            "Level": "",
            "Experience": null
        },
        "title": "data analyst",
        "skills": {}
    },
    {
        "source": "LinkedIn",
        "company": "Akademija Oxford",
        "location": "Ille-et-Vilaine, Brittany, France",
        "link": "https://fr.linkedin.com/jobs/view/data-analyst-at-akademija-oxford-3917872056?position=4&pageNum=0&refId=jBvsgtdGm8ta0dsilpa8wg%3D%3D&trackingId=4oROEO4bVfHAu%2BQ%2FoSkdhg%3D%3D&trk=public_jobs_jserp-result_search-card",
        "description": "L‚Äô√©cole Sup de Vinci, Rennes, accompagne l‚Äôune de ses entreprises partenaires dans son projet de recrutement d‚Äôun profil Big Data en alternance pour la rentr√©e de Septembre 2021.\nA noter : Sup de Vinci pr√©sentera √† cette entreprise partenaire uniquement des candidats ayant pass√© les tests d‚Äôadmission et qui seront admissibles dans son √©tablissement.\nShow more\nShow less",
        "details": {
            "JobDetail": [],
            "TypeContract": "",
            "Salary": "",
            "Level": "",
            "Experience": null
        },
        "title": "data analyst",
        "skills": {
            "Other": [
                "Big Data"
            ]
        }
    },
    {
        "source": "LinkedIn",
        "company": "CHANEL",
        "location": "Neuilly-sur-Seine, √éle-de-France, France",
        "link": "https://fr.linkedin.com/jobs/view/alternance-data-analyst-junior-anti-trafic-h-f-septembre-2024-at-chanel-3847615544?position=5&pageNum=0&refId=jBvsgtdGm8ta0dsilpa8wg%3D%3D&trackingId=4b3gXai5MwL697fpwKUrog%3D%3D&trk=public_jobs_jserp-result_search-card",
        "description": "Alternance Data Analyst Junior Anti-trafic (H/F) septembre 2024\nL'activit√© Parfums Beaut√© affirme sa singularit√© √† travers une promesse : celle de r√©v√©ler la beaut√© de chaque femme dans ce qu'elle a de plus singulier √† travers son parfum, son maquillage et ses produits de soin. Cette philosophie est largement h√©rit√©e de Mademoiselle Chanel, qui a toujours ≈ìuvr√© pour affirmer sa propre ind√©pendance et celle de toutes les femmes.\nDescription de l'emploi :\nL‚Äô√©quipe Anti-trafic a pour mission de contribuer √† prot√©ger la marque CHANEL Parfums Beaut√©, ses consommateurs(rices) ainsi que ses distributeurs agr√©√©s en luttant au quotidien contre le march√© gris.\nAu sein de cette √©quipe dynamique √† taille humaine et dot√©e d‚Äôun scope mondial, rattach√©(e) √† la Chef de projet Am√©lioration continue, vous contribuerez au travail d‚Äôinvestigation, de consolidation et de qualification des informations et donn√©es du march√© parall√®le. Plong√©(e) dans l‚Äôenvers du d√©cor d‚Äôune Maison de luxe, vous serez amen√©(e) √† travailler en autonomie et √† √™tre force de proposition sur vos futures missions.\n√Ä ce titre, vos missions sont les suivantes :\nGestion de la qualit√© des donn√©es de nos outils de pilotage et d‚Äôanalyse :\nOutils internes :\nContr√¥le des informations saisies sur nos diff√©rentes bases de donn√©es\nRetraitement des donn√©es : garantir la fiabilit√© et la coh√©rence des donn√©es, r√©aliser les travaux de nettoyage correspondants avant transmission des rapports aux march√©s\nAccompagnement de l‚Äôanalyste produit dans la recherche/compl√©tion des informations manquantes\nOutils externes :\nContr√¥le de l‚Äôint√©grit√© et de la qualit√© des donn√©es fournies\nElaboration de propositions d'optimisation des jeux de donn√©es (format / structure des fichiers‚Ä¶)\nSuivi et d√©veloppements BI\n:\nD√©veloppement/Am√©lioration de rapports PBI en partenariat avec la chef de projet Data Junior\nAppui √† l‚Äôam√©lioration des data set et de la data visualisation\nCr√©ation et r√©daction de guides utilisateurs √† destination de l‚Äô√©quipe et de nos march√©s\nSupport de l‚Äô√©quipe anti-trafic :\nAm√©lioration de la gestion documentaire en collaboration avec nos parties prenantes\nMission support aupr√®s des chef de projet march√©s pour l‚Äôaide au reporting\nParticipation √† la vie de l‚Äô√©quipe\nPROFIL\nVous √™tes en master et poss√©dez les atouts n√©cessaires pour int√©grer un environnement rigoureux et en constante √©volution. Tr√®s organis√©e, la personnalit√© que nous recherchons est √©galement curieuse et pro-active. Vous poss√©dez une r√©elle app√©tence pour l‚Äôop√©rationnel et le croisement des donn√©es qualitatives et quantitatives. Excel et Power BI n‚Äôont plus de secret pour vous et vous √™tes √† l‚Äôaise avec les autres modules de la suite Microsoft. Enfin, vous √™tes √† l‚Äôaise en anglais.\nLa connaissance du domaine et des enjeux de l‚Äôanti-trafic n‚Äôest pas n√©cessaire, vous serez form√©(e) en interne par l‚Äô√©quipe avant de d√©buter vos missions.\nVous pouvez postuler en ligne sur Chanel.com, rubriques Carri√®res\nAlternance d√®s d√©but septembre 2024 bas√©e √† Neuilly-sur-Seine.\nDe la singularit√© de chacun na√Æt la richesse de nos √©quipes. CHANEL valorise la diversit√© sous toutes ses formes.\nShow more\nShow less",
        "details": {
            "JobDetail": [
                "Junior"
            ],
            "TypeContract": "",
            "Salary": "",
            "Level": "",
            "Experience": null
        },
        "title": "data analyst",
        "skills": {
            "DataVisualisation": [
                "Power BI"
            ],
            "Automation": [
                "Chef"
            ],
            "EnSoftSkils": [
                "Collaboration"
            ]
        }
    },
    {
        "source": "LinkedIn",
        "company": "Allianz France",
        "location": "Paris, √éle-de-France, France",
        "link": "https://fr.linkedin.com/jobs/view/data-analyst-f-h-at-allianz-france-3909179361?position=6&pageNum=0&refId=jBvsgtdGm8ta0dsilpa8wg%3D%3D&trackingId=yrNle9v7%2FDyEOFZZYImtFg%3D%3D&trk=public_jobs_jserp-result_search-card",
        "description": "AIM Paris (Allianz Investment Management Paris), l‚Äôunit√© Investissement d‚ÄôAllianz France, a la charge de la gestion des investissements des diff√©rentes entit√©s d‚ÄôAllianz France tant sur les portefeuilles d‚Äôactifs g√©n√©raux qu‚Äôen unit√©s de compte (UC), sur toute la cha√Æne de valeur des investissements, qui couvre la gestion actif-passif, la strat√©gie d'investissement, ainsi que la planification des revenus des investissements, le suivi des risques, le reporting et les op√©rations.\nLe r√¥le de l‚Äô√©quipe :\nPour soutenir ces activit√©s, l‚Äô√©quipe AIM Finance & Op√©rations, en charge des donn√©es d‚Äôinvestissements, des reportings et du suivi des risques des investissements, est √† la recherche d‚Äôun\nData Analyst\n. Ce dernier, rattach√© hi√©rarchiquement √† AIM Finance & Op√©rations, couvrira l‚Äôensemble des besoins des diff√©rentes √©quipes d‚ÄôAIM (AIM Investment Strategy, AIM Asset-Liability Management, AIM Finance) et interviendra de fa√ßon op√©rationnelle sur des projets de transformation locaux et Groupe.\nVoici vos principales missions :\n¬∑\nL‚Äôautomatisation\nde sourcing des donn√©es, des contr√¥les et des r√©conciliations entre diff√©rents syst√®mes d‚Äôinformations\n¬∑\nLe d√©veloppement\nde macros/codes afin d‚Äôautomatiser/optimiser les t√¢ches\n¬∑\nL‚Äôam√©lioration continue\ndes bases de donn√©es Investissements\n¬∑\nLa fiabilisation et l‚Äôam√©lioration\ncontinue des bases de donn√©es\n¬∑\nLa mise en place\nde nouveaux reportings (Power BI)\n¬∑\nLe pilotage de projets\nen lien avec les initiatives groupes et locales\nVous travaillerez en lien √©troit avec les autres √©quipes d'AIM France ainsi que les √©quipes AIM centrales √† Munich. La maitrise de\nl‚Äôanglais\nest alors indispensable.\nVotre parcours :\nDipl√¥m√©(e) en informatique/gestion des donn√©es ou d‚Äôune √©cole d‚Äôing√©nieur (\nBAC +5),\nvous disposez d‚Äôune exp√©rience significative dans la manipulation de donn√©es\n(5-10 ans).\nMa√Ætrise de plusieurs langages de d√©veloppement du type\nPython, VBA, Access, SAS\nBonne ma√Ætrise des outils bureautiques Powerpoint, Excel et VBA, et id√©alement une premi√®re exp√©rience significative dans l‚Äôutilisation d‚Äôoutils de datavisualisation\n(Power BI)\nCapacit√© d‚Äôanalyse et de synth√®se, ouverture d‚Äôesprit, rigueur, organisation et autonomie,\nFran√ßais et\nanglais\nprofessionnel courants indispensables, √† l‚Äô√©crit comme √† l‚Äôoral.\nVous aimez travailler en √©quipe dans une entreprise qui met ses collaborateurs au c≈ìur de sa strat√©gie de d√©veloppement ! Alors rejoignez-nous chez Allianz ! Toute l‚Äô√©quipe de Marwen NAJAR vous y attend !\nEn tant qu‚Äôentreprise reconnue et internationale, nous vous offrons des avantages attractifs tels qu‚Äôune flexibilit√© du temps de travail, le t√©l√©travail (3 jours par semaine), 9 semaines de cong√©s, une restauration sur site, des taux pr√©f√©rentiels collaborateurs, des cong√©s maternit√© et paternit√© √©largis, des places en cr√®che et bien plus encore.\nEn tant qu‚Äôemployeur, nous mettons tout en ≈ìuvre pour vous assurer un bien √™tre propice √† votre √©panouissement.\nAllianz est la 1√®re marque mondiale d'assurance pr√©sente dans 70 pays. Les #Allianzers, c'est 9.000 salari√©s en France qui accompagnent leurs clients tout au long de leur vie, des collaborateurs qui associent innovation, performance et agilit√© pour relever des d√©fis permanents au quotidien. Parce qu'en nous pr√©occupant de l‚Äôavenir de nos collaborateurs, nous pouvons encore mieux nous pr√©occuper de l‚Äôavenir de tous nos clients. Pour cela, Allianz innove et met la technologie aux services des hommes pour pr√©parer leur avenir, un avenir plus s√ªr.\nEn qualit√© d‚Äôemployeur engag√©, Allianz reconna√Æt que sa force se trouve dans la diversit√© de ses collaborateurs. Nous sommes fiers de promouvoir l‚Äôint√©gration et l‚Äô√©galit√© des chances quel que soit le sexe, l‚Äô√¢ge, l‚Äôorigine, la nationalit√©, la religion, le handicap, ou l‚Äôorientation sexuelle de nos collaborateurs.\nAllianz, We secure your future !\nInformations compl√©mentaires :\nPoste base √† PARIS, La D√©fense, M√©tro Esplanade\nShow more\nShow less",
        "details": {
            "JobDetail": [],
            "TypeContract": "",
            "Salary": "",
            "Level": "",
            "Experience": "10 an(s)"
        },
        "title": "data analyst",
        "skills": {
            "ProgLanguage": [
                "Python"
            ],
            "DataVisualisation": [
                "Power BI"
            ]
        }
    },
    {
        "source": "LinkedIn",
        "company": "Akademija Oxford",
        "location": "Paris, √éle-de-France, France",
        "link": "https://fr.linkedin.com/jobs/view/apprenti-e-data-analyst-at-akademija-oxford-3917871082?position=7&pageNum=0&refId=jBvsgtdGm8ta0dsilpa8wg%3D%3D&trackingId=wi9eB%2BVDDbZ4RDKHND%2BNug%3D%3D&trk=public_jobs_jserp-result_search-card",
        "description": "Un acteur du secteur voyage et tourisme bas√© √† Paris recrute un.e Apprenti.e Data Analyst pour renforcer son √©quipe D√©veloppement & Business Strat√©gique. L‚Äôalternant.e sera positionn√©.e sur le suivi et le contr√¥le de l‚Äôactivit√© de la direction. Le contrat commence en octobre 2021 pour une dur√©e de 12 mois.\nShow more\nShow less",
        "details": {
            "JobDetail": [],
            "TypeContract": "",
            "Salary": "",
            "Level": "",
            "Experience": null
        },
        "title": "data analyst",
        "skills": {}
    },
    {
        "source": "LinkedIn",
        "company": "Akademija Oxford",
        "location": "Boulogne-Billancourt, √éle-de-France, France",
        "link": "https://fr.linkedin.com/jobs/view/apprenti-data-analyst-h-f-at-akademija-oxford-3883289604?position=8&pageNum=0&refId=jBvsgtdGm8ta0dsilpa8wg%3D%3D&trackingId=zGSBVf05Ek5Tzxjbr54Bug%3D%3D&trk=public_jobs_jserp-result_search-card",
        "description": "Une de nos structures partenaires, acteur majeur du secteur des T√©l√©communications et situ√© dans les Hauts-De-Seine, recherche un Apprenti Data Analyst (H/F) pr√©parant un bac +4/+5 sp√©cialit√© Big Data √† partir de Septembre 2021 et pour une dur√©e d‚Äôun √† deux ans.\nShow more\nShow less",
        "details": {
            "JobDetail": [],
            "TypeContract": "",
            "Salary": "",
            "Level": "",
            "Experience": null
        },
        "title": "data analyst",
        "skills": {
            "Other": [
                "Big Data"
            ]
        }
    },
    {
        "source": "LinkedIn",
        "company": "Unlimitail",
        "location": "Paris, √éle-de-France, France",
        "link": "https://fr.linkedin.com/jobs/view/data-analyst-junior-at-unlimitail-3912999630?position=9&pageNum=0&refId=jBvsgtdGm8ta0dsilpa8wg%3D%3D&trackingId=ZjOVmytedKcnsKSQ0pQ%2FUQ%3D%3D&trk=public_jobs_jserp-result_search-card",
        "description": "Unlimitail\nis a joint venture between\nCarrefour\nGroup and\nPublicis\nGroup, intending to become the leader of the\nretail media market in Europe and Latin America\n. It combines the power of Carrefour Links' in-store and e-commerce assets and traffic with Publicis\nCitrus Ad and Epsilon's\non-site and off-site retail media technologies. The goal of Unlimitail is to become the premier retail media player in Continental Europe and South America for both in-store and digital channels.\nMissions\nWithin the Product team, your mission will be to participate in the development of Unlimitail‚Äôs analytics capabilities. Your environment will be millions of transactional data coming from major retailers on the market to analyze and improve the performance of online and offline marketing campaigns.\nAs we work with both retailers (providing media inventory) and brands (buying media inventory), you will have the opportunity to gain a deep understanding of the retail media ecosystem.\nYou will work with different teams (Ad Operations, Marketing, Sales) in different countries and on a wide variety of topics:\n- Perform e-commerce campaigns analysis to provide detailed insights\n- Conduct end-to-end ad hoc analysis to help retailers best monetize their inventory\n- Participate in the design and maintenance of databases, using SQL to store and manage data efficiently\n- Work on automating data analysis and data visualization capabilities\n- Work on Unlimitail‚Äôs customer lifetime value calculation capability\n- Participate in the development of new, cutting-edge abilities to create the best\nRequirements\n:\n¬∑ Master's degree in Data Analysis, business analytics, Computer Science, Statistics, Mathematics, Engineering, or a related field.\n¬∑ Data Analysis: Proven ability to analyze large datasets, identify trends, and extract actionable insights through using strong SQL skills for querying and data extraction.\n¬∑ Programming Languages: Python and SQL are mandatory. Any other is a plus\n¬∑ Data Visualization: previous experience in creating interactive and insightful visualizations, using tools like Power BI or Looker is a big plus\n¬∑ Knowledge of GCP or Azure environment is a plus\n¬∑ Problem-solving: Adept at approaching analytical problems and proposing effective solutions.\n¬∑ Good communication skills in English. Another language (Spanish, Portuguese) is a plus.\n¬∑ Strong team player with the ability to collaborate effectively\nBenefits\n:\n¬∑ 2 days of WFH\n¬∑ 90% reimbursement of public transportation fees\n¬∑ Office located in central Paris (Chatelet)\n¬∑ Swile card of 10‚Ç¨/working days\nShow more\nShow less",
        "details": {
            "JobDetail": [],
            "TypeContract": "",
            "Salary": "",
            "Level": "",
            "Experience": null
        },
        "title": "data analyst",
        "skills": {
            "ProgLanguage": [
                "Python"
            ],
            "DataBase": [
                "SQL"
            ],
            "DataVisualisation": [
                "Power BI"
            ],
            "CloudComputing": [
                "GCP",
                "Azure"
            ],
            "Collaboration": [
                "Teams"
            ],
            "EnSoftSkils": [
                "Communication"
            ]
        }
    },
    {
        "source": "LinkedIn",
        "company": "Orange Business",
        "location": "Lille",
        "link": "https://fr.linkedin.com/jobs/view/data-analyst-power-bi-f-h-at-orange-business-3916552634?position=10&pageNum=0&refId=jBvsgtdGm8ta0dsilpa8wg%3D%3D&trackingId=U4KAg6WLRoRLqVSKwDxsYw%3D%3D&trk=public_jobs_jserp-result_search-card",
        "description": "Missions\n:\nOrange Business, recherche pour son site de Lille, son futur Data Analyst Power BI pour rejoindre sa team Data.\nVotre quotidien ?\nEn int√©grant Orange Business, vous pouvez participer √† une grande diversit√© d‚Äôactivit√©s dans la Data. En voici un aper√ßu :\nAu d√©marrage du projet :\nRecueillir et analyser les besoins du client\nR√©diger les sp√©cifications fonctionnelles et techniques\nEstimer les charges\nPendant la phase de r√©alisation :\nConcevoir et d√©velopper des\nsolutions frontend BI √† des fins analytics & dashboarding\nAccompagner les M√©tier dans la\ncompr√©hension des Analytics\net mise en oeuvre de solution \"data driven\"\nMettre en ≈ìuvre des solutions industrielles exploitables, mesurables et op√©rables\nCommuniquer et traduire les r√©sultats complexes et leurs implications aux parties prenantes de l'entreprise\nCapitaliser sur les solutions pour cr√©er de nouveaux produits, de nouveaux services et de nouvelles opportunit√©s de digitalisation, de valorisation de la donn√©e\nCollaborer avec les data scientists et data ops dans la construction d'une culture ax√©e sur les donn√©es\nEn fonction de votre √©volution et de nos enjeux, vous pouvez aussi √©voluer sur des missions transverses (conseil, coaching, avant-vente, formation, audit, etc.). La prise d‚Äôinitiative est toujours la bienvenue !\nProfil\n:\nVous poss√©dez 3 ans d'exp√©rience ou plus autour d‚Äô√©cosyst√®mes BI. Vous maitrisez la cha√Æne de valeur du traitement de la donn√©e, vous savez int√©grer les enjeux de s√©curit√© des donn√©es\nVous\nma√Ætrisez Power BI\non Cloud.\nVous avez acquis de l‚Äôexp√©rience dans les outils BI et\ndata visualisation\n.\nAu-del√† des connaissances techniques, nous recherchons quelqu‚Äôun de :\nDynamique et positif ;\nAyant soif d'apprendre et d'√©voluer ;\nAimant relever les d√©fis et √™tre challeng√© pour progresser ;\nA l'√©coute et aimant le travail collectif ;\nAimant partager avec l‚Äô√©quipe ses expertises et ses questions.\nShow more\nShow less",
        "details": {
            "JobDetail": [],
            "TypeContract": "",
            "Salary": "",
            "Level": "",
            "Experience": "3 an(s)"
        },
        "title": "data analyst",
        "skills": {
            "MachineLearning": [
                "Orange"
            ],
            "DataVisualisation": [
                "Power BI"
            ],
            "Other": [
                "Cloud"
            ],
            "EnSoftSkils": [
                "Initiative"
            ]
        }
    },
    {
        "source": "LinkedIn",
        "company": "Akademija Oxford",
        "location": "Ille-et-Vilaine, Brittany, France",
        "link": "https://fr.linkedin.com/jobs/view/data-analyst-en-alternance-at-akademija-oxford-3917867571?position=11&pageNum=0&refId=jBvsgtdGm8ta0dsilpa8wg%3D%3D&trackingId=n4ufLwBz1rqVmlUhHuwGWQ%3D%3D&trk=public_jobs_jserp-result_search-card",
        "description": "Vous avez envie d‚Äôint√©grer une √©cole √† taille humaine ? Vous √™tes int√©ress√©.es par l‚Äôanalyse et le traitement des donn√©es ? Sup de Vinci propose une formation compl√®te, en bachelor Big Data.\nL‚Äô√©cole Sup de Vinci, Rennes, accompagne l‚Äôune de ses entreprises partenaires dans son projet de recrutement d‚Äôun profil Big Data en alternance pour la rentr√©e de Septembre 2021.\nShow more\nShow less",
        "details": {
            "JobDetail": [],
            "TypeContract": "",
            "Salary": "",
            "Level": "",
            "Experience": null
        },
        "title": "data analyst",
        "skills": {
            "Other": [
                "Big Data"
            ]
        }
    },
    {
        "source": "LinkedIn",
        "company": "Technology & Strategy",
        "location": "Lyon, Auvergne-Rh√¥ne-Alpes, France",
        "link": "https://fr.linkedin.com/jobs/view/data-analyst-h-f-at-technology-strategy-3909691608?position=12&pageNum=0&refId=jBvsgtdGm8ta0dsilpa8wg%3D%3D&trackingId=rIGPfKv%2BBKfXZ19%2BAwYA7A%3D%3D&trk=public_jobs_jserp-result_search-card",
        "description": "D√©couvrez Novencia\n:\nExpert en Data et Intelligence Artificielle, nous aidons nos clients √† exploiter et √† valoriser leurs donn√©es sous toutes ses formes en les accompagnant sur des projets de Data Analyse, Data Gourvernance, Data Architecture, Data Science, et Data Engineering‚Ä¶\nVous avez une solide exp√©rience de minimum 3 ans dans l'analyse des donn√©es et vous √™tes √† la recherche de nouveaux d√©fis ? N'h√©sitez plus, la suite est pour vous !\nType de contrat : CDI\nD√©marrage : D√®s que possible\nLieu : Lyon\nDescription du poste\n:\nNous recherchons un Data Analyst exp√©riment√© pour rejoindre notre √©quipe dynamique en r√©gion lyonnaise. Le candidat id√©al devrait avoir une solide exp√©rience dans l‚Äôanalyse de donn√©es, ainsi que des comp√©tences techniques en SQL, Python et Power BI (ou tout autre outil de visualisation de donn√©es).\nEn qualit√© de Data Anlayst (H/F)*, vous serez en charge de :\nCollecter, nettoyer et analyser des donn√©es commerciales provenant de diff√©rentes sources.\nCr√©er des rapports et des tableaux de bord pertinents pour les √©quipes op√©rationnelles et de gestion.\nIdentifier les tendances, les opportunit√©s et les domaines d‚Äôam√©lioration √† partir des donn√©es.\nCollaborer avec les √©quipes m√©tier pour comprendre leurs besoins et fournir des analyses approfondies.\nPr√©-requis :\nExp√©rience professionnelle de minimum 3 ans en tant que Data Analyst.\nMa√Ætrise des langages SQL et Python pour l‚Äôextraction, la transformation et l‚Äôanalyse des donn√©es.\nConnaissance approfondie de Power BI ou d‚Äôautres outils de visualisation de donn√©es.\nCapacit√© √† travailler de mani√®re autonome et √† communiquer efficacement avec les parties prenantes.\nVous disposez des savoir-√™tre suivants :\nAmbidextre : Agile √† droite, Data √† gauche\nCoordinateur.trice : man≈ìuvre un projet et une √©quipe\nFin.e connaisseur.euse : alimente, reporte et con√ßoit des entrep√¥ts de donn√©es\nDiplomate : r√©sout les in√©vitables complexit√©s de la r√©alisation d‚Äôun projet d‚Äôentreprise\nN√©gociateur.trice : met du tact dans chaque discussion\nTenace : un seul objectif, la satisfaction client\nNotre objectif commun est de co-construire votre carri√®re en fonction de vos aspirations et de vos comp√©tences.\nContactez-moi en message priv√© ou par mail √† s.ziki@technologyandstrategy.com !\nLet's make it possible #together\n*Nos postes sont ouverts aux personnes b√©n√©ficiant d‚Äôune Reconnaissance de la Qualit√© de Travailleur Handicap√© (RQTH). T&S Groupe encourage la diversit√© et l‚Äô√©galit√© sur le lieu de travail. Tous les candidats qualifi√©s H/F/* sont pris en consid√©ration pour un emploi sur un m√™me pied d'√©galit√©.\nShow more\nShow less",
        "details": {
            "JobDetail": [],
            "TypeContract": "CDI",
            "Salary": "",
            "Level": "",
            "Experience": "3 an(s)"
        },
        "title": "data analyst",
        "skills": {
            "ProgLanguage": [
                "Python"
            ],
            "DataBase": [
                "SQL"
            ],
            "DataVisualisation": [
                "Power BI"
            ]
        }
    },
    {
        "source": "LinkedIn",
        "company": "Avanty",
        "location": "Paris, √éle-de-France, France",
        "link": "https://fr.linkedin.com/jobs/view/data-analyst-at-avanty-3908247423?position=13&pageNum=0&refId=jBvsgtdGm8ta0dsilpa8wg%3D%3D&trackingId=JB49bEdTFQzdJuewU%2BcDTA%3D%3D&trk=public_jobs_jserp-result_search-card",
        "description": "Avanty\nrecherche pour sa\nBusiness Unit\n‚Äì\nDigital & Technologique\n, des\nData Analyst\nsp√©cialis√©s dans l‚Äôanalyse de donn√©es, dont le r√¥le sera de comprendre les besoins de nos clients, les traduire via une sp√©cification √† l'attention des d√©veloppeurs, les tester apr√®s d√©veloppement pour finalement les valider avant mise en production.\nAvanty\nadresse l‚Äôensemble des activit√©s de banque, finance et assurance et propose un large p√©rim√®tre de domaines d‚Äôintervention. Nos services s'articulent autour de\nl'expertise fonctionnelle m√©tier\n, de\nl'apport\nm√©thodologique\n, de\nla\nma√Ætrise\nde\nsolution\net de la\nr√©alisation\ntechnologique\n.\nAvanty\nemploie aujourd‚Äôhui\nune\ncentaine\nde\nconsultants\n. Nous intervenons aupr√®s des plus grands comptes (BNP Paribas, Cr√©dit Agricole, Soci√©t√© G√©n√©rale, Natixis, ‚Ä¶), pour les accompagner dans la r√©ussite de leurs projets informatiques.\nNous rejoindre, c‚Äôest l‚Äôopportunit√© de grandir au quotidien au contact de votre consultant manager ou consultant directeur tout en √©tant acteur de votre carri√®re.\nVotre profil :\nDipl√¥m√©(e) Bac +3 √† Bac +5 ayant un parcours ing√©nieur ou de formation Universitaire dans les domaines des statistiques, du traitement de l‚Äôinformation ou du big data, vous disposez d'une premi√®re exp√©rience sur un similaire.\nVous disposez d‚Äôune exp√©rience vari√©e sur diff√©rents domaines et :\nVous √™tes curieux et vous vous int√©ressez aux nouvelles tendances technologiques, √† la digitalisation,\nVous avez d‚Äôexcellentes capacit√©s analytiques et de synth√®se,\nFormation d‚Äôing√©nieur compl√©t√©e d‚Äôune formation data ou business intelligence,\nUne premi√®re exp√©rience dans le domaine banque/finance est un v√©ritable plus,\nVous avez un bon niveau d‚Äôanglais,\nVous √™tes attir√© par le dynamisme d‚Äôune structure en forte croissance,\nVous avez envie d‚Äôentreprendre, de construire et de transmettre aupr√®s d‚Äô√©quipe et de clients √† l‚Äô√©coute.\nVous avez des comp√©tences techniques sur un ou plusieurs domaines ci-dessous :\nExpertise en base de donn√©es et gestion de base de donn√©es (SQL/NoSQL)\nMa√Ætrise des tests et m√©thodes statistiques (segmentation, r√©gression, for√™t al√©atoire)\nMa√Ætrise des langages de programmation (Python, R, C+)\nMa√Ætrise d‚Äôun outil de data visualisation (Tableau, Qlikview, PowerBI)\nMa√Ætrise des outils de fouille et analyse de donn√©es (Dataiku)\nNos missions :\nMise en place de datalake, datawarehouse, base de donn√©es relationnelles,\nExtraction des donn√©es\nMise en forme et structuration des donn√©es\nAnalyse et exploration des donn√©es\nInteraction avec les √©quipes m√©tiers pour recueillir les besoins.\nAide le m√©tier dans sa logique de prise de d√©cision\nVeille technologique sur les outils d‚Äôanalyse de donn√©es\nNos engagements :\nNous vous accompagnerons dans l'atteinte de vos objectifs professionnels en vous proposant un plan de carri√®re sur mesure, alliant mission et formation\nNos managers seront vos coachs pour vous accompagner vers cette transformation\nNos points forts :\nMissions int√©ressantes et diversit√© des comptes couverts.\nAbsence de commerciaux, management assur√© par des consultants exp√©riment√©s\nTous les consultants en mission et sont en connexion avec la r√©alit√© mission.\nStructure √† taille humaine et adossement aux forces du Groupe Ailancy.\nPlan de carri√®re personnalis√© avec conseils de consultants exp√©riment√©s.\nFortes ambitions de croissance et opportunit√©s de promotions internes.\nFormations sur mesure assur√©es par des consultants exp√©riment√©s.\nParticipation au d√©veloppement du cabinet et promotion des initiatives.\nPossibilit√© d'√™tre formateur et vari√©t√© fonctionnelle.\nL‚Äôinter-staffing est une p√©riode id√©ale pour se former ou participer au rayonnement de la structure.\nPossibilit√© de renforcer son expertise et √©voluer √† un grade d‚Äôexpert.\nSensibilisation √† la RSE.\nShow more\nShow less",
        "details": {
            "JobDetail": [],
            "TypeContract": "",
            "Salary": "",
            "Level": "",
            "Experience": null
        },
        "title": "data analyst",
        "skills": {
            "ProgLanguage": [
                "R",
                "Python"
            ],
            "DataBase": [
                "SQL",
                "NoSQL"
            ],
            "DataAnalytics": [
                "R"
            ],
            "DataVisualisation": [
                "Tableau"
            ],
            "Other": [
                "Statistiques",
                "Big Data"
            ]
        }
    },
    {
        "source": "LinkedIn",
        "company": "Coders Connect",
        "location": "Paris, √éle-de-France, France",
        "link": "https://fr.linkedin.com/jobs/view/data-analyst-at-coders-connect-3870416610?position=14&pageNum=0&refId=jBvsgtdGm8ta0dsilpa8wg%3D%3D&trackingId=jYpRadvx5qpmZlADXbNSKQ%3D%3D&trk=public_jobs_jserp-result_search-card",
        "description": "Coders Connect and Sanofi are joining forces to bring an electrifying twist to the biopharmaceutical world!\nWork with a rhythm that suits your style (2 days remote and 3 days onsite magic).\nLanguage:\nProficiency in English is required for this role to ensure effective communication within our diverse, global team.\nAbout Sanofi:\nWe're not just a company; we're a global movement, focused on human health and making a real difference. Our mission? To battle pain, ease suffering, and sprinkle a little bit of magic in the process by developing life-changing medicines and vaccines through breakthrough science and wizard-level technology.\nDigital & Data: The Pulse of Our Mission\nAt the heart of our quest lies our digital and data powerhouse. Think of us as the digital healthcare platform of your dreams, where innovation meets speed, and technology shakes hands with medicine. With our scale, deep-rooted connections in health ecosystems worldwide, and a knack for pushing boundaries, we're here to revolutionize medicine, one digital solution at a time.\nYour Quest as a Data Analyst:\nEmbark on an adventure where your data wizardry helps unlock new horizons in drug discovery and trial efficiency. Your role is pivotal‚Äîmelding analysis with creativity to illuminate the path forward with insights gleaned from data. Your canvas? A world of complex data sets waiting for your exploratory magic and analytical prowess.\nRequirements\nYour Spellbook Includes:\nData Alchemy: Transform raw data into insights that shape future solutions. You're the master of extracting, cleaning, and interpreting data, finding stories in the numbers that others might miss.\nCollaboration Charms: Work your magic across realms, aligning stakeholders with the stardust of enterprise data models and definitions. Your mission is to weave consensus and drive the adoption of data management standards that resonate across Sanofi.\nVisionary Insight: Recommend KPIs, craft reports, and monitor the adoption of data practices that ensure Sanofi's data remains a beacon of quality, usability, and security.\nYour Arsenal:\nA robust understanding of the mystical arts of databases, data structures, and the tools that keep the data realm in order.\nProficiency in SQL, Python, and a knack for visual storytelling through Tableau, PowerBI, or other visual sorcery.\nA curious mind driven by the quest for knowledge and a passion for solving the puzzles of privacy laws and data compliance.\nThe Reward:\nA chance to play a crucial role in a collaboration that's redefining healthcare through digital transformation.\nA seat at the round table of diversity and inclusion, where different backgrounds and experiences conjure the richness of our culture.\nAn endless horizon of professional growth, learning opportunities, and the chance to contribute to a future where better health is a global reality.\nThe Call to Adventure:\nIf you're ready to join a quest for better ‚Äì better treatments, better outcomes, and better science ‚Äì and believe in the magic of bringing diverse talents together to make miracles happen, we want you. Let's embark on this journey together and transform the future of healthcare.\nBetter is out there. Are you ready to find it with us?\nShow more\nShow less",
        "details": {
            "JobDetail": [
                "Remote"
            ],
            "TypeContract": "",
            "Salary": "",
            "Level": "",
            "Experience": null
        },
        "title": "data analyst",
        "skills": {
            "ProgLanguage": [
                "Python"
            ],
            "DataBase": [
                "SQL"
            ],
            "DataVisualisation": [
                "Tableau"
            ],
            "EnSoftSkils": [
                "Creativity",
                "Communication",
                "Collaboration"
            ]
        }
    },
    {
        "source": "LinkedIn",
        "company": "Mobilize Financial Services",
        "location": "Paris, √éle-de-France, France",
        "link": "https://fr.linkedin.com/jobs/view/business-data-analyst-h-f-at-mobilize-financial-services-3904096866?position=15&pageNum=0&refId=jBvsgtdGm8ta0dsilpa8wg%3D%3D&trackingId=wGmLWi9AJQuurhQ0iaRHwA%3D%3D&trk=public_jobs_jserp-result_search-card",
        "description": "üöó En route vers Mobilize !\nA l‚Äô√©coute de tous nos clients, nous cr√©ons des services financiers innovants pour construire une mobilit√© durable pour tous.\nRejoindre Mobilize Financial Services,\nc‚Äôest d‚Äôabord choisir d‚Äôint√©grer un groupe international\n, filiale de Renault Group, une banque de financement solide, partenaire des constructeurs Renault‚ÄìMitsubishi (Renault, Dacia, Alpine, Renault Samsung Motors, Mobilize, Infiniti, Datsun, et Mitsubishi Motors) dans plusieurs pays. Nos 4 000 collaborateurs pr√©sents dans 36 pays, agissent ensemble au service de nos clients.\nNous proposons √† nos clients - particuliers comme professionnels - les financements et les services les plus adapt√©s pour les v√©hicules neufs et d'occasion.\nNous finan√ßons √©galement l'\nactivit√© des r√©seaux de concessionnaires\ndes marques du groupe Renault et nous veillons √† faciliter leur gestion au quotidien pour leur permettre de d√©velopper leurs ventes et assurer leur p√©rennit√© financi√®re.\nEn 2022, le groupe a financ√© plus de\n1,2 millions de dossiers\n(v√©hicules neufs et v√©hicules d‚Äôoccasion) et vendu\n3,8 millions de services\n. Nous proposons √©galement des\noffres d‚Äô√©pargne\ndans 7 pays.\nNotre entreprise se \"MOBILIZE\" en faveur de la\ndiversit√©\nculturelle, l'√©galit√© hommes-femmes et l'int√©gration de personnes en situation de Handicap, au travers notamment de notre Chartre. Nous favorisons un environnement de travail o√π les diff√©rences individuelles sont reconnues, appr√©ci√©es, respect√©es et valoris√©es, de fa√ßon √† d√©velopper les talents et les forces de chacun.\nEnfin, nous b√©n√©ficions au sein du groupe d‚Äôune forte\npolitique de mobilit√©\n: les possibilit√©s d‚Äô√©volution sont donc multiples et vari√©es.\nüöòPrenez le volant ! Pas de routine, tous nos itin√©raires sont diff√©rents !\nIn the Data Factory Team, reporting to the Data Management Director, the Business Analyst is the proxy Product Owner inside the Data Factory and internal Head of Project. He/She has to :\nSupport MFS internal clients (countries and corporate functions) in their data projects, help them express their needs, advise and guide them on possible solutions:\nCommunicate and promote Data Platform solutions in the different subsidiaries and in Corporate\nFoster the identification of Data Platform use-cases opportunities and added values for business\nEnsure the consistency of Data Platform projects, their alignment with strategy and their compliance (data privacy, data governance, security‚Ä¶)\nIdentify the potentials adherences between the Data platform projects and make propositions accordingly (grouping, carry over , prioritization...)\nTransform clients needs in functional requirements, produce the appropriate documentation for Go/No Go decision, prioritization and development\nSteer and follow Data projects, on QCD axis, from framing to go live, in Agile method\nEnsure compliance and its auditability with Data project methodology and delivery of project documentation\nEnsure, all along the projects, actions coordination between the different stakeholders, in Corporate and in Subsidiaries: Project Owner, Data Governance, Data Privacy, Data Factory (Data Engineering, Data Science, IT & Data Architecture) and the businesses involved such as marketing, digital, regulatory, financials & controlling\nDefine and follow the QCD KPI‚Äôs and report the progress of the projects he/she is in charge of\nEnsure the business validation of the finished products\nEnsure training and operational usage of the finished products\nGuarantee the finished products from delivery in production to serial life management\nDetailed responsibilities\nFrame the Data Platform use cases for the Go/No Go decision and prioritization\nEnsure that the projects prerequisites are met\nEnsure each project KPIs will be measurable and measured\nFormalize through the business requirements documentation, the business need and the different features to set up\nTake the project to Data Factory and Data Office\nChallenge, validate or invalidate the solution and the schedule proposed\nRoll out the different project phases he/she is in charge of, from framing to go live, on QCD axis, following the methodology applied to Data Factory project (agile method) and coordinating stakeholders actions\nSteer project committees and comitology\nPrepare projects reporting for steering committees to present QCD KPIs he has built and followed\nSet up test plans and follow their roll out\nEnsure the proper delivery in production of the finished product\nEnsure training and operational usage of the finished products\nEnsure the maintenance of the finished product\nEnsure that the project documentation has been created in accordance with Data Factory method\nPrepare all necessary presentation of the project\nPropose methodological modifications\nRequired skills / required experience\nFluent English\nBasic SQL Level : ability to perform simple requests\nData analysis skills\nProject management or Project owner support experience required\nExcellent written and verbal communication skills\nBusiness process analysis and data analysis appetence\nAnimation, coordination, and teamwork appetence\nSynthetic spirit, organization and pedagogy required\nKnowledge of the banking, insurance, automobile sectors appreciated\nKnowledge or appetence for Big Data technologies, AI, Data engineering and Data Science appreciated\nKnowledge or appetence for Agile method and related tools\nPack Office mastery\nPourquoi nous rejoindre ? Votre Pack confort est compos√© de nombreux avantages üòÄ :\nUn environnement de travail moderne et convivial\n: locaux agr√©ables, CSE dynamique avec de nombreuses offres (voyages, sport, famille) et, selon les sites, salle de sport, restaurant d‚Äôentreprise ou tickets restaurant, ainsi qu‚Äôun parking\nNous sommes mobilis√©s pour d√©velopper la qualit√© de vie au travail de nos collaborateurs en faisant √©voluer nos fa√ßons de travailler (m√©thodes, outils, organisation du travail‚Ä¶) et nous sommes fiers d‚Äô√™tre\ncertifi√©s ‚≠êGreat Place To Work ‚≠ê\nPossibilit√© de\nt√©l√©travailler 2/3 jours par semaine\nRemboursement √† hauteur de\n75% des frais d‚Äôabonnement aux transports publics\nou forfait de transport mensuel selon le mode de locomotion\nNos locaux sont situ√©s √†\nParis Grands Boulevards\n‚ùó Mobilize Financial Services d√©m√©nage ‚ùó Les postes √† pourvoir en r√©gion parisienne seront tous bas√©s √† Boulogne Billancourt en 2026.\nShow more\nShow less",
        "details": {
            "JobDetail": [],
            "TypeContract": "",
            "Salary": "",
            "Level": "",
            "Experience": null
        },
        "title": "data analyst",
        "skills": {
            "DataBase": [
                "SQL"
            ],
            "Other": [
                "Big Data"
            ],
            "EnSoftSkils": [
                "Teamwork",
                "Communication",
                "Organization"
            ]
        }
    },
    {
        "source": "LinkedIn",
        "company": "Technology & Strategy",
        "location": "Paris, √éle-de-France, France",
        "link": "https://fr.linkedin.com/jobs/view/data-analyst-h-f-at-technology-strategy-3909686864?position=16&pageNum=0&refId=jBvsgtdGm8ta0dsilpa8wg%3D%3D&trackingId=opO%2B6UiSrxYNp3pGtR%2B0Ow%3D%3D&trk=public_jobs_jserp-result_search-card",
        "description": "D√©couvrez Novencia\n:\nExpert en Data et Intelligence Artificielle, nous aidons nos clients √† exploiter et √† valoriser leurs donn√©es sous toutes ses formes en les accompagnant sur des projets de Data Analyse, Data Gourvernance, Data Architecture, Data Science, et Data Engineering‚Ä¶\nVous avez une solide exp√©rience de minimum 4 ans dans l'analyse des donn√©es et vous √™tes √† la recherche de nouveaux d√©fis ? Bouclez votre ceinture, la suite est pour vous !\nType de contrat : CDI\nD√©marrage : D√®s que possible\nLieu : Paris\nDescription du poste :\nNous recherchons un Data Analyst exp√©riment√© pour rejoindre notre √©quipe dynamique en r√©gion parisienne. Le candidat id√©al devrait avoir une solide exp√©rience dans l‚Äôanalyse de donn√©es, ainsi que des comp√©tences techniques en SQL, Python et Power BI (ou tout autre outil de visualisation de donn√©es).\nEn qualit√© de Data Anlayst (H/F)*, vous serez en charge de :\nCollecter, nettoyer et analyser des donn√©es commerciales provenant de diff√©rentes sources.\nCr√©er des rapports et des tableaux de bord pertinents pour les √©quipes op√©rationnelles et de gestion.\nIdentifier les tendances, les opportunit√©s et les domaines d‚Äôam√©lioration √† partir des donn√©es.\nCollaborer avec les √©quipes m√©tier pour comprendre leurs besoins et fournir des analyses approfondies.\nPr√©-requis :\nExp√©rience professionnelle de 4 √† 5 ans en tant que Data Analyst.\nMa√Ætrise des langages SQL et Python pour l‚Äôextraction, la transformation et l‚Äôanalyse des donn√©es.\nConnaissance approfondie de Power BI ou d‚Äôautres outils de visualisation de donn√©es.\nCapacit√© √† travailler de mani√®re autonome et √† communiquer efficacement avec les parties prenantes.\nVous disposez des savoir-√™tre suivants :\nAmbidextre : Agile √† droite, Data √† gauche\nCoordinateur.trice : man≈ìuvre un projet et une √©quipe\nFin.e connaisseur.euse : alimente, reporte et con√ßoit des entrep√¥ts de donn√©es\nDiplomate : r√©sout les in√©vitables complexit√©s de la r√©alisation d‚Äôun projet d‚Äôentreprise\nN√©gociateur.trice : met du tact dans chaque discussion\nTenace : un seul objectif, la satisfaction client\nNotre objectif commun est de co-construire votre carri√®re en fonction de vos aspirations et de vos comp√©tences.\nContactez-moi en message priv√© ou par mail √† s.ziki@technologyandstrategy.com !\nLet's make it possible #together\n*Nos postes sont ouverts aux personnes b√©n√©ficiant d‚Äôune Reconnaissance de la Qualit√© de Travailleur Handicap√© (RQTH). T&S Groupe encourage la diversit√© et l‚Äô√©galit√© sur le lieu de travail. Tous les candidats qualifi√©s H/F/* sont pris en consid√©ration pour un emploi sur un m√™me pied d'√©galit√©.\nShow more\nShow less",
        "details": {
            "JobDetail": [],
            "TypeContract": "CDI",
            "Salary": "",
            "Level": "",
            "Experience": "4 an(s)"
        },
        "title": "data analyst",
        "skills": {
            "ProgLanguage": [
                "Python"
            ],
            "DataBase": [
                "SQL"
            ],
            "DataVisualisation": [
                "Power BI"
            ]
        }
    },
    {
        "source": "LinkedIn",
        "company": "Inetum",
        "location": "Lille, Hauts-de-France, France",
        "link": "https://fr.linkedin.com/jobs/view/data-analyst-h-f-at-inetum-3843955768?position=17&pageNum=0&refId=jBvsgtdGm8ta0dsilpa8wg%3D%3D&trackingId=WgqQmxF94rwdsVuRDQwLFQ%3D%3D&trk=public_jobs_jserp-result_search-card",
        "description": "D√©tail de l'offre\nInformations g√©n√©rales\nEntit√© de rattachement\nInetum est un leader europ√©en des services num√©riques. Pour les entreprises, les acteurs publics et la soci√©t√© dans son ensemble, les 28 000 consultants et sp√©cialistes du groupe visent chaque jour l'impact digital des solutions qui contribuent √† la performance, √† l'innovation et au bien commun.\nPr√©sent dans 19 pays au plus pr√®s des territoires, et avec ses grands partenaires √©diteurs de logiciels, Inetum r√©pond aux enjeux de la transformation digitale avec proximit√© et flexibilit√©.\nPort√© par son ambition de croissance et d'industrialisation, Inetum a g√©n√©r√© en 2023 un chiffre d'affaires de 2,5 milliards d'‚Ç¨.\nPour r√©pondre √† un march√© en croissance continue depuis plus de 30ans, Inetum a fait le choix d√©lib√©r√© de se recentrer sur 4 m√©tiers afin de gagner en puissance et proposer des solutions sur mesure, adapt√©es aux besoins sp√©cifiques de ses clients le conseil (Inetum Consulting), la gestion des infrastructures et applications √† fa√ßon (Inetum Technologies), l'impl√©mentation de progiciels (Inetum Solutions) et sa propre activit√© d'√©diteur de logiciels (Inetum Software). Inetum a conclu des partenariats strat√©giques avec 4 grands √©diteurs mondiaux - Salesforce, ServiceNow, Microsoft et SAP et poursuit une strat√©gie d'acquisitions d√©di√©e afin d'entrer dans le top 5 europ√©en sur ces technologies et proposer la meilleure expertise √† ses clients.\nTous nos postes sont ouverts aux personnes en situation de handicap.\nDescription du poste\nM√©tier\nApplications Delivery - Software Development\nIntitul√© du poste\nData Analyst H/F\nContrat\nCDI\nDescription De La Mission\nDans le cadre de la croissance de notre agence lilloise, nous d√©veloppons notre Practice Data et recrutons des profils Data de divers horizons Data Analyst, Data Engineer, Data Scientist et Data Gouv. Les besoins m√©tiers de nos clients et la multitude des technologies font qu'il nous faut nous appuyer sur une diversit√© de comp√©tences. Vous pourriez √™tre l‚Äôun d‚Äôeux et rejoindre Inetum.\nEn tant que Data Analyst, vos principales missions consistent √†\nAnalyser et retranscrire le besoin client\nIdentifier, extraire et exploiter les sources d'acquisition de donn√©es les plus pertinentes\nValoriser de la donn√©e\nD√©velopper l'outil de data visualisation pour accompagner les √©quipes m√©tiers dans leurs aides √† la d√©cision\n√ätre le lien entre les √©quipes m√©tier pour les accompagner dans la mise en ≈ìuvre des nouveaux outils\nProfil\nPour mener √† bien votre r√¥le, il vous faut\nparler SQL couramment\nun niveau avanc√© sur Excel et/ou Google Spreadsheet\nune ma√Ætrise d'un outil d√©cisionnel comme PowerBI, Qlik, Tableau ou encore Google Data Studio\nVous vous reconnaissez dans ces quelques lignes, alors rencontrons-nous !\nNotre plus\nRejoindre la r√©gion Nord-Est, c‚Äôest b√©n√©ficier des avantages d‚Äôun Grand Groupe tout en gardant la proximit√© r√©gionale.\nNous mettrons tout en ≈ìuvre pour vous apporter un √©quilibre vie perso / vie pro. C‚Äôest pourquoi nous vous proposons un rythme hybride (selon les contraintes clients)\nUne trajectoire de carri√®re personnalis√©e et adapt√©e √† vos souhaits d'√©volution gr√¢ce √† une implantation √† l‚Äôinternational (26 pays, 7 Fablab), des formations cibl√©es et des projets couvrant l‚Äôensemble de la cha√Æne de valeur IT (+25 fili√®res m√©tiers)\nInt√©grer un collectif d‚Äôexperts partageant des valeurs de solidarit√© et d‚Äôexcellence\nInt√©grer une entreprise ayant une strat√©gie affirm√©e de certifications de ses collaborateurs\nLocalisation du poste\nLocalisation du poste\nFrance, Nord, 59 Nord\nVille\nLille\nCrit√®res candidat\nNiveau d'√©tudes min. requis\nBac+5\nNiveau d'exp√©rience min. requis\nPlus de 2 ans\nShow more\nShow less",
        "details": {
            "JobDetail": [
                "Hybride"
            ],
            "TypeContract": "CDI",
            "Salary": "",
            "Level": "Bac+5",
            "Experience": "30 an(s)"
        },
        "title": "data analyst",
        "skills": {
            "DataBase": [
                "SQL"
            ],
            "DataVisualisation": [
                "Tableau"
            ]
        }
    },
    {
        "source": "LinkedIn",
        "company": "CGI",
        "location": "Niort, Nouvelle-Aquitaine, France",
        "link": "https://fr.linkedin.com/jobs/view/data-analyst-f-h-at-cgi-3902408459?position=18&pageNum=0&refId=jBvsgtdGm8ta0dsilpa8wg%3D%3D&trackingId=M3XvIQC%2B%2F604IhMHyZgJxg%3D%3D&trk=public_jobs_jserp-result_search-card",
        "description": "Big Data, Data Science, Data analyse, Data architecture ... √áa n‚Äôa pas de secret pour vous ?\nQue vous commenciez votre carri√®re professionnelle ou que vous soyez sp√©cialiste de l‚Äôune de ces disciplines, int√©grer notre communaut√© Data, c‚Äôest l‚Äôassurance de progresser, innover, partager, vous certifier et rendre service √† nos clients.\nSi vous souhaitez int√©grer nos √©quipes √† Niort et accompagner les plus grands acteurs du secteur des Assurances, cette annonce est susceptible de vous int√©resser.\nEn tant que Data Analyst dans le secteur assurantiel, votre r√¥le principal sera d'analyser et d'interpr√©ter des donn√©es pour fournir des informations strat√©giques et op√©rationnelles permettant d'am√©liorer la prise de d√©cision et la performance de l'entreprise.\nFonctions et responsabilit√©s\nVos responsabilit√©s seront les suivantes:\n-Collecter et Pr√©parer les donn√©es provenant de diverses sources internes et externes.\n-Assurer la qualit√© et la fiabilit√© des donn√©es en nettoyant et en transformant les donn√©es brutes.\n-Analyser les donn√©es\n-Cr√©er des Tableaux de Bord et Rapports\n-Effectuer des mod√©lisation Pr√©dictive\n-Analyser les Performances\n-Travailler en √©troite collaboration avec les √©quipes actuarielles\n-Surveiller des Tendances du March√©\n-Veiller √† ce que toutes les activit√©s d'analyse de donn√©es soient conformes aux normes de s√©curit√© des donn√©es et aux r√©glementations en vigueur, telles que le RGPD.\nEn rejoignant CGI, vous b√©n√©ficiez notamment d‚Äôune offre compl√®te de formations (techniques, m√©tiers, d√©veloppement personnel,‚Ä¶), de flexibilit√© gr√¢ce √† notre accord t√©l√©travail (jusqu‚Äô√† 3 jours de t√©l√©travail par semaine), d‚Äôune politique de cong√©s avantageuse (27 jours de cong√©s pay√©s, RTT, cong√©s anciennet√© et enfant malade,‚Ä¶) et d‚Äôun package d‚Äôavantages int√©ressant (r√©gime d‚Äôachats d‚Äôactions, participation, CSE,...).\nQualit√©s requises pour r√©ussir dans ce r√¥le\nAyant une premi√®re exp√©rience en Data, vous maitrisez les technologies suivantes:\n-Les langages de programmation et de requ√™tage tels que Python, R, SAS et SQL.\n-Solides comp√©tences en analyse statistique et en mod√©lisation de donn√©es, en particulier dans un environnement SAS.\n-Exp√©rience avec des outils de Business Intelligence tels que Tableau, Power BI, QlikView, etc.\nConnaissance approfondie des techniques d'apprentissage automatique et de l'analyse.\nCGI est un employeur inclusif et attentif aux candidatures des personnes en situation de handicap, √† l‚Äô√©volution de carri√®res des hommes et des femmes et au bien-√™tre de nos salari√©s LGBT+. Dans un souci d‚Äôaccessibilit√© et de clart√©, le point m√©dian n‚Äôest pas utilis√© dans cette annonce. Tous les termes employ√©s se r√©f√®rent aussi bien au genre f√©minin que masculin.\nShow more\nShow less",
        "details": {
            "JobDetail": [],
            "TypeContract": "",
            "Salary": "Package",
            "Level": "",
            "Experience": null
        },
        "title": "data analyst",
        "skills": {
            "ProgLanguage": [
                "R",
                "Python"
            ],
            "DataBase": [
                "SQL"
            ],
            "DataAnalytics": [
                "R"
            ],
            "DataVisualisation": [
                "Power BI",
                "Tableau"
            ],
            "Other": [
                "Big Data"
            ],
            "EnSoftSkils": [
                "Collaboration"
            ]
        }
    },
    {
        "source": "LinkedIn",
        "company": "Lagard√®re Travel Retail",
        "location": "Levallois-Perret, √éle-de-France, France",
        "link": "https://fr.linkedin.com/jobs/view/junior-data-analyst-h-f-alternance-septembre-2024-at-lagard%C3%A8re-travel-retail-3909162343?position=19&pageNum=0&refId=jBvsgtdGm8ta0dsilpa8wg%3D%3D&trackingId=WN4Sw3FzYfhTb4FpadsoCw%3D%3D&trk=public_jobs_jserp-result_search-card",
        "description": "Lagard√®re Travel Retail est l‚Äôun des leaders mondiaux du Travel Retail, au service des passager.e.s dans les a√©roports, les gares et autres concessions dans 42 pays. L'une des deux divisions du groupe Lagard√®re, Lagard√®re Travel Retail r√©pond aux besoins des passager.e.s et des conc√©dants de fa√ßon holistique √† travers un r√©seau de plus de 5 000 points de vente Travel Essentials, Duty Free & Fashion et Foodservice. Le groupe s‚Äôest engag√© √† cr√©er des exp√©riences de voyage plus responsables dans le cadre de sa strat√©gie RSE (P.E.P.S) ainsi qu‚Äô√† contribuer √† la neutralit√© carbone globale d'ici fin 2023. En 2022, Lagard√®re Travel Retail a r√©alis√© un chiffre d'affaires de 5.2 milliards d'euros.\nRattach√©.e √† la Direction Commercial Development & Transformation, vous int√®grerez notre √©quipe de Supply-Chain Controller.\nA ce titre, vos principales missions seront les suivantes\n1/ Support sur le projet Datafactory\n- R√©aliser les guides utilisateurs des dashboards;\n- Devenir le support technique aux utilisateurs;\n- Contr√¥ler la qualit√© des donn√©es (versus BW / entre dashboards);\n- G√©rer l‚Äô√©volution de dashbaords suite √† validation en comit√© key users.\n2/ D√©veloppement de nouveaux dashboards en support √† l‚Äô√©quipe supply chain\n- Contribuer √† la r√©daction des cahiers des charges en fonction des besoins r√©colt√©s;\n- √ätre l‚Äôinterface entre l‚ÄôIT et la Supply Chain pour la constitution de nouveaux reportings;\n- Contribuer au d√©veloppement des tableaux de bord avec une IHM adapt√©e aux utilisateurs;\n- Apporter un support √† la conduite du changement pour l'appropriation de l'outil par les op√©rationnels (formation, accompagnement des utilisateurs);\n- Mettre √† jour les modes op√©ratoires et la documentation technique.\n3/ Data analytics/ Data science\n- Participer √† des sujets exploratoires ¬´ big data ¬ª en R ou Python.\nProfil :\nActuellement en Master en √©cole de commerce/d'ing√©nieur ou en universit√© avec une sp√©cialisation en data science, vous recherchez une alternance de deux ans d√®s septembre 2024. Vous justifiez id√©alement d‚Äôune premi√®re exp√©rience dans la data science.\nVous avez un niveau d‚Äôanglais courant √† l'√©crit comme √† l'oral.\nVous maitrisez les outils de bureautiques (Pack office), la maitrise de SAP Hana/BI4/ Power BI est un plus.\nVous √™tes autonome et rigoureux.se, motiv√©.e et organis√©.e, avec un fort esprit d‚Äôanalyse et de synth√®se pour aborder des sujets tr√®s divers.\nNous croyons que l‚Äôinclusion et la diversit√© sont essentielles √† la r√©ussite des entreprises et des personnes. Chez Lagard√®re Travel Retail, nous nous engageons √† cr√©er un environnement de travail dans lequel nos collaborateur.rice.s peuvent r√©aliser leur potentiel et √™tre eux.elles-m√™mes, et √† soutenir chacun.e d'entre eux.elles dans la r√©alisation de ses ambitions. Nous accueillons et prenons en consid√©ration toutes les candidatures, quel que soit leur profil, et garantissons un traitement juste et √©quitable √† tou.te.s les candidat.e.s.\nShow more\nShow less",
        "details": {
            "JobDetail": [],
            "TypeContract": "",
            "Salary": "",
            "Level": "",
            "Experience": null
        },
        "title": "data analyst",
        "skills": {
            "ProgLanguage": [
                "R",
                "Python"
            ],
            "DataAnalytics": [
                "R"
            ],
            "DataVisualisation": [
                "Power BI"
            ],
            "Other": [
                "Big Data"
            ]
        }
    },
    {
        "source": "LinkedIn",
        "company": "Ayming",
        "location": "Lyon, Auvergne-Rh√¥ne-Alpes, France",
        "link": "https://fr.linkedin.com/jobs/view/data-analyst-h-f-at-ayming-3896616843?position=20&pageNum=0&refId=jBvsgtdGm8ta0dsilpa8wg%3D%3D&trackingId=%2FhGBgzTh07dgLybaGD38hA%3D%3D&trk=public_jobs_jserp-result_search-card",
        "description": "Votre job\nVotre job\nQuelles sont vos missions chez Ayming ?\nAu sein de notre activit√© de Conseil en Financement de l‚ÄôInnovation, vous √™tes en support aux √©quipes consulting Innovation France\nVous √™tes membre du ¬´ CSP ¬ª : Centre de Services Partag√©s.\nVos missions seront les suivantes :\nEn tant que r√©f√©rent d‚Äôune √©quipe, vous g√©rez et contribuez √† la fiabilisation des datas Equipe (affectation des ressources missions, pr√©paration de la facturation, co-gestion des stocks (factu et CA)\nAssurer le support aux √©quipes sur les outils\nIntervenir sur le suivi de certains indicateurs\nVos talents et aspirations professionnelles\nVous avez :\nUne formation Bac ou Bac +2 dans la gestion (d√©butant accept√©)\nUne tr√®s bonne ma√Ætrise du VBA, python, SQL\nEnvie d‚Äôint√©grer une entreprise dynamique et leader dans son secteur d‚Äôactivit√©\nLe sens des priorit√©s et le sens du service\nUne approche p√©dagogique\nL‚Äôesprit d‚Äô√©quipe et le go√ªt du challenge\nUn bon relationnel client\nLa capacit√© √† traiter diverses t√¢ches annexes\nVous √™tes :\nOrganis√©, rigoureux, curieux et autonome\nEngag√© et impliqu√©\nForce de proposition\nSi vous devenez un Aymer ?\nVous b√©n√©ficierez :\nBien-√™tre au travail et carri√®re\nD‚Äôune diversit√© de projets et d‚Äôenvironnements m√©tiers et g√©ographiques\nBien-√™tre au travail et carri√®re\nD‚Äôune politique de d√©veloppement de votre potentiel au travers de notre Ayming Academy et Ayming Digital Academy\nUn programme d‚Äô√©volution de carri√®re au travers de nos accompagnements RH ¬´ My Professionnal Journey ¬ª\nDe notre Nouvelle Vie au travail : flexibilit√©, espaces cr√©ativit√© et conviviaux, 108 jours de t√©l√©travail par an\nDes moments de rencontre lors d‚Äô√©v√©nements tout au long de l‚Äòann√©e\nPackage de r√©mun√©ration et avantages sociaux\nR√©mun√©ration fixe et variable selon profil\nStatut employ√©\nSoutien √† la parentalit√©\nVotre recruteur\nRachid BELHOCINE\nPostuler Envoyer √† un(e) ami(e) ‚Ä∫\nPartager cette publication\nPostuler Envoyer √† un(e) ami(e) ‚Ä∫\nNom *\nPr√©nom *\nEmail *\nJe suis int√©ress√© par :\nT√©l√©chargement de votre CV * Types de fichiers accept√©s : pdf, doc, rtf, txt, docx, odt, jpg, Taille max. des fichiers : 24 MB.\n*\nJ'accepte qu'Ayming traite mes donn√©es personnelles pour g√©rer ma candidature dans les conditions d√©taill√©es au sein de la Politique RH .\nNous vous rappelons que vous disposez d'un droit d'acc√®s, de rectification, de suppression, de limitation, de portabilit√© ainsi qu'un droit d'opposition au traitement de vos donn√©es. Pour exercer ces droits, vous pouvez adresser une demande √† : contact@ayming.com.\nShow more\nShow less",
        "details": {
            "JobDetail": [],
            "TypeContract": "",
            "Salary": "24",
            "Level": "",
            "Experience": null
        },
        "title": "data analyst",
        "skills": {
            "ProgLanguage": [
                "Python"
            ],
            "DataBase": [
                "SQL"
            ]
        }
    },
    {
        "source": "LinkedIn",
        "company": "Ayming",
        "location": "Levallois-Perret, √éle-de-France, France",
        "link": "https://fr.linkedin.com/jobs/view/data-analyst-h-f-at-ayming-3896616845?position=21&pageNum=0&refId=jBvsgtdGm8ta0dsilpa8wg%3D%3D&trackingId=pWjSk%2BK7uxcdfSBSld7cmg%3D%3D&trk=public_jobs_jserp-result_search-card",
        "description": "Votre job\nVotre job\nQuelles sont vos missions chez Ayming ?\nAu sein de notre activit√© de Conseil en Financement de l‚ÄôInnovation, vous √™tes en support aux √©quipes consulting Innovation France\nVous √™tes membre du ¬´ CSP ¬ª : Centre de Services Partag√©s.\nVos missions seront les suivantes :\nEn tant que r√©f√©rent d‚Äôune √©quipe, vous g√©rez et contribuez √† la fiabilisation des datas Equipe (affectation des ressources missions, pr√©paration de la facturation, co-gestion des stocks (factu et CA)\nAssurer le support aux √©quipes sur les outils\nIntervenir sur le suivi de certains indicateurs\nVos talents et aspirations professionnelles\nVous avez :\nUne formation Bac ou Bac +2 dans la gestion (d√©butant accept√©)\nUne tr√®s bonne ma√Ætrise du VBA, python, SQL\nEnvie d‚Äôint√©grer une entreprise dynamique et leader dans son secteur d‚Äôactivit√©\nLe sens des priorit√©s et le sens du service\nUne approche p√©dagogique\nL‚Äôesprit d‚Äô√©quipe et le go√ªt du challenge\nUn bon relationnel client\nLa capacit√© √† traiter diverses t√¢ches annexes\nVous √™tes :\nOrganis√©, rigoureux, curieux et autonome\nEngag√© et impliqu√©\nForce de proposition\nSi vous devenez un Aymer ?\nBien-√™tre au travail et carri√®re\nD‚Äôune diversit√© de projets et d‚Äôenvironnements m√©tiers et g√©ographiques\nD‚Äôune politique de d√©veloppement de votre potentiel au travers de notre Ayming Academy et Ayming Digital Academy\nUn programme d‚Äô√©volution de carri√®re au travers de nos accompagnements RH ¬´ My Professionnal Journey ¬ª\nDe notre Nouvelle Vie au travail : flexibilit√©, espaces cr√©ativit√© et conviviaux, 108 jours de t√©l√©travail par an\nDes moments de rencontre lors d‚Äô√©v√©nements tout au long de l‚Äòann√©e\nPackage de r√©mun√©ration et avantages sociaux\nR√©mun√©ration fixe et variable selon profil\nStatut employ√©\nSoutien √† la parentalit√©\nVotre recruteur\nRachid BELHOCINE\nPostuler Envoyer √† un(e) ami(e) ‚Ä∫\nPartager cette publication\nPostuler Envoyer √† un(e) ami(e) ‚Ä∫\nNom *\nPr√©nom *\nEmail *\nJe suis int√©ress√© par :\nT√©l√©chargement de votre CV * Types de fichiers accept√©s : pdf, doc, rtf, txt, docx, odt, jpg, Taille max. des fichiers : 24 MB.\n*\nJ'accepte qu'Ayming traite mes donn√©es personnelles pour g√©rer ma candidature dans les conditions d√©taill√©es au sein de la Politique RH .\nNous vous rappelons que vous disposez d'un droit d'acc√®s, de rectification, de suppression, de limitation, de portabilit√© ainsi qu'un droit d'opposition au traitement de vos donn√©es. Pour exercer ces droits, vous pouvez adresser une demande √† : contact@ayming.com.\nShow more\nShow less",
        "details": {
            "JobDetail": [],
            "TypeContract": "",
            "Salary": "24",
            "Level": "",
            "Experience": null
        },
        "title": "data analyst",
        "skills": {
            "ProgLanguage": [
                "Python"
            ],
            "DataBase": [
                "SQL"
            ]
        }
    },
    {
        "source": "LinkedIn",
        "company": "Akademija Oxford",
        "location": "Boulogne-Billancourt, √éle-de-France, France",
        "link": "https://fr.linkedin.com/jobs/view/apprenti-e-data-analyst-at-akademija-oxford-3917867572?position=22&pageNum=0&refId=jBvsgtdGm8ta0dsilpa8wg%3D%3D&trackingId=lVaSmyHVxk74JYgGCwqu6Q%3D%3D&trk=public_jobs_jserp-result_search-card",
        "description": "Notre partenaire, acteur mondial des m√©tiers des concessions et de la construction, recherche un.e apprenti.e Data Analyst dans le cadre d‚Äôune alternance de 12 √† 24 mois d√©butant √† la rentr√©e de Septembre 2021.\nShow more\nShow less",
        "details": {
            "JobDetail": [],
            "TypeContract": "",
            "Salary": "",
            "Level": "",
            "Experience": null
        },
        "title": "data analyst",
        "skills": {}
    },
    {
        "source": "LinkedIn",
        "company": "Akademija Oxford",
        "location": "Ille-et-Vilaine, Brittany, France",
        "link": "https://fr.linkedin.com/jobs/view/ing%C3%A9nieur-data-at-akademija-oxford-3912800588?position=23&pageNum=0&refId=jBvsgtdGm8ta0dsilpa8wg%3D%3D&trackingId=0TTXCFAk%2FLF32wfFcRuT1w%3D%3D&trk=public_jobs_jserp-result_search-card",
        "description": "Vous souhaitez int√©grer une √©cole √† taille humaine ? Vous √™tes int√©ress√©.es par la donn√©e ? Sup de Vinci propose une formation compl√®te, en Mast√®re Big Data & Intelligence Artificielle (2 ann√©es en alternance).\nL‚Äô√©cole Sup de Vinci, Rennes, accompagne l‚Äôune de ses entreprises partenaires dans son projet de recrutement d‚Äôun profil ing√©nieur data, en alternance pour la rentr√©e 2022.\nShow more\nShow less",
        "details": {
            "JobDetail": [],
            "TypeContract": "",
            "Salary": "",
            "Level": "",
            "Experience": null
        },
        "title": "data engineer",
        "skills": {
            "Other": [
                "Big Data"
            ]
        }
    },
    {
        "source": "LinkedIn",
        "company": "Valeuriad",
        "location": "Nantes, Pays de la Loire, France",
        "link": "https://fr.linkedin.com/jobs/view/data-analyst-h-f-at-valeuriad-3741219622?position=24&pageNum=0&refId=jBvsgtdGm8ta0dsilpa8wg%3D%3D&trackingId=RedIFTSJZaEhGejEZRMlMg%3D%3D&trk=public_jobs_jserp-result_search-card",
        "description": "Rejoins la Team Data\ncr√©√©e par Nicolas Greffard,\nDocteur en Intelligence Artificielle\n, d√©j√† compos√©e de 20 Data Scientists et Data Engineer talentueux üòç\nNous recherchons de nouvelles p√©pites pour rejoindre notre √©quipe de choc et r√©pondre aux multiples probl√©matiques Data science de nos clients nantais mais √©galement contribuer √† nos projets de R&D et travailler sur des conf√©rences incroyables (DevFest, Salon de la Data) ü§©\nTa future mission si tu l'acceptes üòâ\nNous te proposons d'intervenir au sein de nos grandes DSI clientes, sur des sujets de collecte, d'alimentation et de transformation de donn√©es autour de l‚Äôintelligence artificielle.\nLe job en d√©tail ü§©\nToutes Les Missions Ne Sont Pas Identiques, Mais Voici Des Exemples De Choses Sur Lesquelles Nos Data Analyst Sont Intervenus\nMettre en oeuvre des outils informatiques, des techniques et des m√©thodes statistiques pour permettre d'organiser, synth√©tiser et traduire efficacement des donn√©es ;\nFournir un appui analytique √† la conduite d'exploration et √† l'analyse complexe de donn√©es ;\nCr√©er des algorithmes de recherche de donn√©es qui permettent d'explorer les donn√©es utiles ;\nProc√©der √† l'industrialisation du proc√©d√© pour les donn√©es les plus int√©ressantes. Et organiser, synth√©tiser et traduire les informations pour faciliter la prise de d√©cision ;\nG√©rer les op√©rations et l'administration, la mod√©lisation et l'architecture des sources de donn√©es. Et s'assurer que les bases de donn√©es existantes soient op√©rationnelles et int√®gres ;\nDonner un sens aux donn√©es √† l'aide de ses connaissances analytiques (SQL, analytics/BI, statistiques basiques) ;\nD‚Äôint√©grer de nouveaux jeux de donn√©es (Open Data, crowd sourcing, API, fichiers, etc.).\nNous intervenons sur\ndes donn√©es Big Data\n(Hadoop, Hive, Spark, etc...), NoSQL (Neo4j, Redis Graph, Redis, mongo) avec toujours quelques bases de donn√©es Oracle ind√©boulonnables. Mais aussi r√©guli√®rement sur des environnements\nCloud\n(principalement AWS et GCP). C√¥t√© outillage et ETL, les missions r√©centes √©taient principalement sur Informatica, Dataiku et Dig Dash. A retenir : nous faisons de tout !\nPourquoi choisir Valeuriad ? üòä\nEn plus d‚Äô√™tre aujourd‚Äôhui un acteur nantais reconnu de l‚Äôexpertise IT, nous nous inscrivons depuis notre cr√©ation dans une d√©marche d'entreprise\nOpale\net\nHolacratique\n, o√π l'ensemble de nos prises de d√©cisions et projets sont r√©alis√©s par et avec l'ensemble de nos 120 co√©quipiers üí™\nRejoindre Valeuriad, c'est\npouvoir s'investir dans la co-construction\nde l'entreprise :\nPar un r√¥le, avec une fiche de poste et un temps d√©di√© (gestionnaire des Ci‚Äôs, porteur des partenariats √©coles, organisateur d‚Äô√©v√©nements, PO des projets internes, gestion de l'Acad√©mie Valeuriad‚Ä¶).\nPar les projets strat√©giques (200 jours mis √† disposition pour les co√©quipiers chaque ann√©e) pour cr√©er et faire grandir des projets structurants (cr√©ation de nouveaux avantages √† l'anciennet√©, cr√©ation d'indicateurs mensuels pour √™tre toujours plus transparents, m√©c√©nat de comp√©tences pour des associations caritatives...).\nPar les projets cagnottes (150‚Ç¨ par co√©quipiers et par an) pour r√©aliser des projets collaboratifs qui te tiennent √† c≈ìur avec d'autres Valeurieux (d√©couverte du c√©cifoot, challenge √©cologique, challenges sportifs pour des dons √† des associations humanitaires, borne photo...).\nPar les ateliers collaboratifs, chaque mois des brainstorming et ateliers de travail sont propos√©s par les diff√©rents porteurs de projets et sont ouverts √† tous les volontaires.\nMais avant-tout nous sommes une\n√©quipe soud√©e\n, des coll√®gues qui appr√©cient passer du temps ensemble lors de nos soir√©es hebdomadaires et se cr√©er des souvenirs inoubliables ü§© C'est pour √ßa que chez Valeuriad, le plus important pour nous reste le savoir-√™tre : des passionn√©s, du dynamisme, des sourires, de l'√©coute et le sens de la f√™te üòâ\nShow more\nShow less",
        "details": {
            "JobDetail": [],
            "TypeContract": "",
            "Salary": "",
            "Level": "",
            "Experience": null
        },
        "title": "data analyst",
        "skills": {
            "ProgLanguage": [
                "R"
            ],
            "DataBase": [
                "SQL",
                "Neo4j",
                "NoSQL"
            ],
            "DataAnalytics": [
                "R"
            ],
            "BigData": [
                "Hadoop",
                "Spark"
            ],
            "CloudComputing": [
                "GCP",
                "AWS"
            ],
            "Other": [
                "Statistiques",
                "Cloud",
                "Big Data"
            ]
        }
    },
    {
        "source": "LinkedIn",
        "company": "Pluxee",
        "location": "Paris, √éle-de-France, France",
        "link": "https://fr.linkedin.com/jobs/view/data-analyst-at-pluxee-3918821570?position=25&pageNum=0&refId=jBvsgtdGm8ta0dsilpa8wg%3D%3D&trackingId=XAtTme4fJeQAComt5IwV3Q%3D%3D&trk=public_jobs_jserp-result_search-card",
        "description": "Pluxee is a global player in\nemployee benefits and engagement\nthat operates in\n31 countries\n. Pluxee helps companies attract, engage, and retain talent thanks to a broad range of solutions across Meal & Food, Wellbeing, Lifestyle, Reward & Recognition, and Public Benefits.\nPowered by leading technology and more than\n5,000 engaged team members\n, Pluxee acts as a trusted partner within a highly interconnected B2B2C ecosystem made up of more than\n500,000 clients, 36 million consumers and 1.7 million merchants\n.\nConducting its business as a trusted partner for more than 45 years, Pluxee is committed to creating a positive impact on all its stakeholders, from driving business to local communities, to supporting wellbeing at work for employees while protecting the planet.\nüöÄ\nYour next challenge\nPluxee Data organization has chosen a decentralized Data Hub (central) & Data Spoke (local) organization where the Spokes are data factory teams covering multiple countries' Data needs and supporting business teams by delivering operations reporting, the ad-hoc analysis supporting decision making and advanced insights aiming at predicting clients, merchants, or consumers behaviors.\nTo support this objective, your responsibilities will encompass:\nData Analysis and interpretation:\ncollecting and analyzing data from various sources to identify trends and insights relevant for business improvement.\nVisualization and reporting:\ndeveloping clear and informative dashboards and reports using data visualization tools to effectively communicate findings to business teams.\nDecision support:\nproviding ad-hoc analyses and statistical modeling to assist business teams in making informed decisions and defining key performance indicators (KPIs) to measure progress.\nüåü\nYou‚Äôre a match\nTechnical Skills:\nSQL Proficiency:\ndemonstrated expertise in querying and managing data using SQL, with at least 3 years of experience as a Data Analyst.\nKPI Definition and Visualization:\nproficient in designing and developing dashboards using Power BI. Experience in defining and computing key performance indicators (KPIs) in DAX to measure business performance (finance or payment services will be a plus).\nStatistical and Machine Learning:\ngood understanding of\nstatistical analysis and machine learning techniques, enabling advanced data analysis.\nSoft Skills:\nEffective communication:\nstrong verbal and written communication skills in both French and English, adept at interacting with diverse stakeholders with varying cultural backgrounds and technical expertise.\nAnalytical thinking:\nhighly analytical and detail-oriented, with a knack for problem-solving and extracting insights from complex datasets.\nProactive and motivated:\nproactive attitude, hands-on approach, and a high level of motivation to learn quickly and adapt to new challenges in an ever-moving domain.\nüîé\nTo get this challenge\nVideocall with Talent Acquisition Expert.\nTechnical assessment.\nVideocall with Hiring Manager (Data Spoke Manager).\nüèÖ\nYour team\nReporting to Jean Francois Prince (Data Spoke Manager).\nüìç\nYour Location\nCentral Paris, Paris.\nAbility to work in a hybrid mode (3 days at the office and 2 days at home).\n‚òÄÔ∏è Happy at work\nA meaningful job:\nbuild the future of employee benefits and contribute to the quality of life at work for others, you will impact positively local communities too. It counts!\nA great culture:\nwe respect and care authentically about our people, we embrace work-life balance, new ideas and we have a lot of fun!\nEmployee experience is what we do. So, you can expect a comprehensive package including benefits and an annual bonus based on performance.\nAbout Pluxee\nWorking at Pluxee is joining a multicultural team that moves as one. It‚Äôs also a place where your individual ideas, perspectives, and input count. You‚Äôll be given the freedom and autonomy you need to do impactful work, supported by a team that cares about your well-being, growth, and work/life balance.\nIt‚Äôs the agility you‚Äôd expect from a fast-growing small business, with the stability that only a globally renowned company with +45 years in the business can offer. Put a part of yourself into the future of employee benefits and meaningfully contribute to lives and communities worldwide.\nShow more\nShow less",
        "details": {
            "JobDetail": [
                "Full"
            ],
            "TypeContract": "",
            "Salary": "45",
            "Level": "",
            "Experience": null
        },
        "title": "data analyst",
        "skills": {
            "DataBase": [
                "SQL"
            ],
            "DataVisualisation": [
                "Power BI"
            ],
            "Collaboration": [
                "Teams"
            ],
            "Other": [
                "Machine Learning"
            ],
            "EnSoftSkils": [
                "Communication",
                "Organization"
            ]
        }
    },
    {
        "source": "LinkedIn",
        "company": "Aqualung Group",
        "location": "Valbonne, Provence-Alpes-C√¥te d'Azur, France",
        "link": "https://fr.linkedin.com/jobs/view/master-data-analyst-intern-at-aqualung-group-3908876542?position=26&pageNum=0&refId=jBvsgtdGm8ta0dsilpa8wg%3D%3D&trackingId=jzNiCZHh6TTb36amu82WbQ%3D%3D&trk=public_jobs_jserp-result_search-card",
        "description": "Aqualung Group pioneered the creation of modern diving equipment in 1943 when Captain Jacques-Yves Cousteau teamed with √âmile Gagnan to develop the first ‚Äúaqua-lung‚Äù that made underwater exploration possible. Today, Aqualung Group continues to be the leading global designer and manufacturer of dive and water sports gear. With a deep commitment to quality, research and testing, Aqualung Group has revolutionized the scuba diving experience by setting industry standards for scuba equipment in technology, comfort, safety and design.\nThe Aqualung Group consists of premium, innovative and inclusive brands such as Aqualung, Apeks, Aquasphere, Omer;\nSo, are you...\na sport enthusiast\ndo you love oceans and everything beyond\nare you an advocate of making a difference and protect our planet, a world where the ocean and all living creature are healthy and thriving\nor are you simply motivated and inspired to be a part of our passionate team that is always eager for a new challenge\nAqualung believes in the future, thus we invite you to strengthen and broaden your skills, pursue your passion by co-creating the future within an internship open positions.\nScope and Mission\nSupport the Aqualung Group in the daily management of Item master data.\nStart date:\nASAP\nDuration target:\nminimum 6 months\nLocation:\nSophia Antipolis\nKey duties and responsibilities\nSupport the master data team in the Item master data collection processes. (Creation/Update).\nHelp centralizing Master Data information in dedicated MDM tool (Product Hub/Oracle).\nHelp ensuring synchronization of the item master data in consuming systems.\nControl master data availability and quality through the publication of KPIs and implementation of data quality reports.\nEnsure master data collection environments are up to date.\nContribute in implementing data quality reports and corrective processes.\nContribute with the Master Data team in enhancing the existing item Core Model.\nYour qualifications\nLevel of studies:\nBAC + 4/5 minimum / master's degree in data science / data analysis.\nA first level of experience in Master data is preferred.\nSkills\nFluent English\nExcellent communication skills\nWorking effectively in a Team\nGood organizational skills, sense of prioritization\nYou are curious, dynamic, passionate about innovation\nStrong ability in manipulating data. (SQL)\nIf you are excited about this opportunity and joining the Aqua Lung team, please apply!\nWe look forward to receiving your application.\nShow more\nShow less",
        "details": {
            "JobDetail": [],
            "TypeContract": "",
            "Salary": "",
            "Level": "",
            "Experience": null
        },
        "title": "data analyst",
        "skills": {
            "DataBase": [
                "SQL"
            ],
            "EnSoftSkils": [
                "Communication"
            ]
        }
    },
    {
        "source": "LinkedIn",
        "company": "Astek",
        "location": "Paris, √éle-de-France, France",
        "link": "https://fr.linkedin.com/jobs/view/data-analyst-%E2%80%93-paris-france-h-f-at-astek-3839098102?position=27&pageNum=0&refId=jBvsgtdGm8ta0dsilpa8wg%3D%3D&trackingId=BSmRQQfj3MaLcUFEyaTRiQ%3D%3D&trk=public_jobs_jserp-result_search-card",
        "description": "CDI\nParis - France\nPubli√©e il y a 2 mois\nLe Groupe Astek\nCe Que Nous Allons Accomplir Ensemble :\nNous rejoindre en tant que\nData Analyst (H/F),\nafin d‚Äôaccompagner un op√©rateur t√©l√©coms, Leader en Europe dans la gestion de ses solutions robustes, efficientes et s√©curis√©es √† destination d‚Äôenvironnements vari√©s.\nUn challenge portant sur des millions d‚Äôutilisateurs dans un environnement technique innovant, strat√©gique et o√π l‚Äôentraide et la bonne humeur priment !\nVotre Mission, Si Vous L‚Äôacceptez :\nEtude sur les donn√©es pour aide au cadrage du besoin M√©tier.\nForce de proposition sur des solutions analytiques adapt√©es aux besoins utilisateurs (avec nos √©quipes UX).\nAnalyse des besoins m√©tiers, accompagnement √† la formulation et √† la d√©finition de KPI m√©tiers.\nMod√©lisation des donn√©es.\nConception de Datasets Big Query.\nConception et R√©alisation de Datamarts et de Dashboards (PowerBI / Looker)\nAnalyse de la qualit√© de la donn√©e source, pour challenger les √©quipes Digitales / Data Engineers.\nVotre Future √âquipe :\nAu sein d‚Äôun environnement riche et complexe, vous √©voluerez avec des experts passionn√©s √† la fois techniques et fonctionnels (Ing√©nieurs sp√©cialis√©s, chef de projet, scrum master, product owner ‚Ä¶).\nL‚Äô√©quipe est en interaction avec des clients √† la fois internes et externes.\nVotre stack de jeu\nSQL ‚Äì Confirm√©\nMod√©lisation de Donn√©es ‚Äì Confirm√©\nOutils de Data Viz ‚Äì Confirm√©\nGCP ‚Äì Junior\nAnglais ‚Äì Professionnel\nLes Petits Plus Du Projet :\nVous interviendrez de A √† Z sur des projets riches fonctionnellement et ambitieux techniquement. Un challenge portant sur des millions d‚Äôutilisateurs dans un environnement technique innovant et strat√©gique.\nVous ?\nDipl√¥m√©(e) d‚Äôune √©cole d‚Äôing√©nieur ou √©quivalent de niveau Bac+5.\nVous justifiez id√©alement d‚Äôune exp√©rience d‚Äôau moins 3 ans d‚Äôexp√©riences sur un poste similaire ?\nVous faite preuve d‚Äôun bon relationnel et d‚Äôesprit d‚Äô√©quipe, √™tes dot√©(e) d‚Äôun excellent sens de l‚Äôorganisation et vous aimez les challenges et la r√©solution de probl√®me ?\nAlors ce poste est fait pour vous, n‚Äôh√©sitez plus et rejoignez l‚Äôaventure ASTEK !\nAstek\nCr√©√© en France en 1988, Astek est un acteur mondial de l‚Äôing√©nierie et du conseil en technologies. Fort de son expertise dans de nombreux secteurs industriels et tertiaires, Astek accompagne ses clients internationaux dans le d√©ploiement intelligent de leurs produits et de leurs services, et dans la mise en ≈ìuvre de leur transformation digitale.\nDepuis sa cr√©ation, le Groupe a fond√© son d√©veloppement sur une forte culture d‚Äôentrepreneuriat et d‚Äôinnovation, et sur l‚Äôaccompagnement et la mont√©e en comp√©tence de\nses 7800 collaborateurs\nqui s‚Äôengagent chaque jour √† promouvoir la compl√©mentarit√© entre les technologies num√©riques et l‚Äôing√©nierie des syst√®mes complexes.\nRejoignez un Groupe en fort d√©veloppement en France et √† travers le monde ayant r√©alis√© un chiffre d‚Äôaffaires de 600 M‚Ç¨ en 2023.\nTous les d√©tails sur le Groupe sur le site https://astekgroup.fr. Et vous pouvez aussi nous suivre sur notre blog : https://blog.groupeastek.com.\nRencontrons-nous\nNotre projet commun vous plait ?\nPostulez √† cette annonce, et soyez transparent !\nMaud, notre Talent Acquisition Referent, vous contactera pour un premier √©change.\nPuis vous rencontrerez Martin, votre futur manager, avec lequel vous √©changerez autour d‚ÄôAstek, de votre parcours, de vos attentes et de votre future mission .\nEnfin, vous rencontrerez J√©r√©my, notre Directeur d‚Äôagence avec lequel vous pourrez valider votre int√©r√™t et ad√©quation pour le poste et finaliser les √©l√©ments contractuels.\nNos Plus\nAstek est green et fait b√©n√©ficier ses salari√©s d‚Äôune indemnit√© kilom√©trique v√©lo\nUne politique CARE sur-mesure d√©ploy√©e par nos √©quipes RH pour nos collaborateurs (https://astekgroup.fr/engagements)\nNotre charte de la Diversit√©\nMots-cl√©s :\ning√©nieur ‚Äì ing√©nieure ‚Äì consultant ‚Äì consultante ‚Äì data ‚Äì analyst ‚Äì mod√©lisation ‚Äì donn√©es\nCaract√©ristiques de l'emploi\nCat√©gorie Ing√©nieur\nJob Industry T√©l√©com / M√©dia\nPostuler en ligne\nNom *\nPr√©nom *\nEmail *\nUn email valide est requis.\nT√©l√©phone *\nUn num√©ro de t√©l√©phone valide est requis.\nJoindre un CV *\nMots-cl√©s :\ning√©nieur ‚Äì ing√©nieure ‚Äì consultant ‚Äì consultante ‚Äì data ‚Äì analyst ‚Äì mod√©lisation ‚Äì donn√©es\nShow more\nShow less",
        "details": {
            "JobDetail": [
                "Confirm√©",
                "Junior"
            ],
            "TypeContract": "CDI",
            "Salary": "",
            "Level": "Bac+5",
            "Experience": "3 an(s)"
        },
        "title": "data analyst",
        "skills": {
            "DataBase": [
                "SQL"
            ],
            "CloudComputing": [
                "GCP"
            ],
            "DBMS": [
                "Big Query"
            ],
            "Automation": [
                "Chef"
            ]
        }
    },
    {
        "source": "LinkedIn",
        "company": "ACT-ON DATA",
        "location": "Courbevoie, √éle-de-France, France",
        "link": "https://fr.linkedin.com/jobs/view/data-analyst-at-act-on-data-3912559652?position=28&pageNum=0&refId=jBvsgtdGm8ta0dsilpa8wg%3D%3D&trackingId=qqUvkDvbhZMk5pOMux4%2FCQ%3D%3D&trk=public_jobs_jserp-result_search-card",
        "description": "Description de l'entreprise\nSoci√©t√© de conseil & de services, ACT-ON GROUP est l‚Äôacteur leader du #HumanTech.\nIl mobilise ses expertises vari√©es et compl√©mentaires en STRATEGY, HR & HRIS, DATA et TECHNOLOGY, ainsi que la connaissance de son √©cosyst√®me partenaires pour accompagner ses clients dans la r√©ussite de tous leurs projets de transformation qu‚Äôils soient organisationnels, digitaux ou culturels‚Ä¶\nAvec plus de 20 ans d‚Äôexistence, notre groupe compte aujourd‚Äôhui plus de 1 500 missions chez nos clients (ETI, SBF 120, CAC 40, secteur public, associatif et ONG).\nIl r√©unit une communaut√© de plus de 600 collaborateurs, pour un chiffre d‚Äôaffaires de plus de 70 millions d‚Äôeuros.\nHistoriquement pr√©sent sur le march√© fran√ßais, en √éle-de-France, √† Lille, Lyon et Nantes, il se d√©veloppe d√©sormais aussi √† l‚Äôinternational.\nDescription du poste\nAu sein de notre entit√© innovante Act-On Data, vous √™tes int√©gr√©(e) √† une √©quipe d‚Äôexperts m√©tier en tant que Data analyst, potentiellement sur un projet international.\nVous participerez ainsi √† des missions √† forte valeur ajout√©e aupr√®s de nos clients en intervenant sur des probl√©matiques m√©tiers, tout en ayant la charge de probl√©matiques op√©rationnelles :\nMettre √† disposition des outils de pilotage d'activit√© √† destination des √©quipes m√©tier en d√©finissant les principaux KPI √† suivre,\nMener et pr√©senter les analyses demand√©es par les Directions m√©tiers ou la Direction n√©cessaire pour comprendre le business et transformer ces insights en plan d'action,\nVeiller √† am√©liorer et mesurer la qualit√© des donn√©es afin de mettre √† disposition des donn√©es fiables,\nParmi vos missions :\nCollaborer avec les m√©tiers sur la d√©finition des principaux KPI,\nR√©colter des besoins m√©tiers,\nR√©alisation des analyses statistiques simples ou complexes en fonction de la demande,\nConception des monitorings de suivi de la qualit√© des donn√©es des diff√©rents domaines,\nIntervenir techniquement sur la partie aval de la cha√Æne de valeur Data.\nQualifications\nVous justifiez d‚Äôune exp√©rience significative sur un poste similaire.\nVous avez un niveau d‚Äôanglais qui vous permet de piloter un projet √† l‚Äôinternational.\nVous ma√Ætrisez vos domaines de comp√©tences (outils/modules ou fonctionnels) et d√©montrez votre l√©gitimit√© par des exp√©riences significatives sur un poste similaire.\nNous recherchons une personne organis√©e, volontaire, dynamique avec une bonne capacit√© d‚Äôadaptation.\nLe go√ªt des chiffres et la maitrise d‚ÄôExcel sont indispensables.\nVous avez une bonne app√©tence pour la data et sur les outils de reporting (SAP BI, PowerBI, Tableau, ‚Ä¶) et connaissez les plates-formes Cloud (Azure, AWS, GCP)\nD‚Äôun temp√©rament passionn√©, vous aimez les challenges et vous souhaitez vous investir dans cette aventure ?\nAlors ce poste peut vous int√©resser !\nInformations suppl√©mentaires\nCe poste est ouvert au t√©l√©travail.\nCe poste est ouvert aux personnes recherchant un CDI uniquement.\nShow more\nShow less",
        "details": {
            "JobDetail": [],
            "TypeContract": "CDI",
            "Salary": "",
            "Level": "",
            "Experience": "20 an(s)"
        },
        "title": "data analyst",
        "skills": {
            "DataVisualisation": [
                "Tableau"
            ],
            "CloudComputing": [
                "GCP",
                "AWS",
                "Azure"
            ],
            "Other": [
                "Statistiques",
                "Cloud"
            ]
        }
    },
    {
        "source": "LinkedIn",
        "company": "Datatorii",
        "location": "Paris",
        "link": "https://fr.linkedin.com/jobs/view/data-analyst-at-datatorii-3916566708?position=29&pageNum=0&refId=jBvsgtdGm8ta0dsilpa8wg%3D%3D&trackingId=%2B56qG1wm41iP3stNV3mqmQ%3D%3D&trk=public_jobs_jserp-result_search-card",
        "description": "1. Pr√©sentation\nDatatorii est une soci√©t√© de conseil sp√©cialis√©e en data.\nPartenaires des directions m√©tiers et IT, nous accompagnons nos clients dans la mise en place de solutions techniques Microsoft ainsi que dans l‚Äôanalyse de leurs donn√©es.\nLa R&D r√©alis√©e en interne (10% du temps, au Dojo) autour de la formation continue et du suivi des √©volutions technologiques nous positionne comme un partenaire de choix, sp√©cialis√© Data Microsoft.\nOrganisme de formation, nous accompagnons √©galement nos clients de la prise en main jusqu‚Äô√† la ma√Ætrise des outils et des m√©thodes autour de la data.\nNich√©s dans le 1er arrondissement de Paris, nos locaux vous offrent tout le confort pour vous former, √©changer r√©guli√®rement avec vos pairs, participer aux ateliers internes et recevoir nos clients.\nDatatorii vous donne la possibilit√© de r√©aliser vos prochains d√©fis !\n2. Mission\nLa communication en entreprise, interne ou externe, est de plus en plus influenc√©e par la restitution de donn√©es, que ce soit via des dashboards, des rapports interactifs ou des pr√©sentations au Top Management.\nChez Datatorii, vous √©voluerez au sein d‚Äôun dispositif pluridisciplinaire (Ing√©nieur, Data Scientist, Architecte, Chef de projet, Formateur, etc.) qui propose des solutions compl√®tes data :\nLa r√©colte du besoin aupr√®s des utilisateurs, la d√©finition de personas, de maquettes et d‚Äôuser-flow\nLa cr√©ation de Style Guides Data et de th√®mes cl√©-en-main pour les projets de visualisation de donn√©es\nL‚Äôaccompagnement sur les r√©alisations (PowerBI, PowerApps, Microsoft Azure, Python, SQL, Mod√©lisation, ...)\nLa conception d‚Äôoffres innovantes et leur promotion (UX BI, BI Self-service, Low-code application, Data Management ...)\nLa r√©alisation de dashboards et rapports interactifs √† fort enjeux\nLa formation interne ou externe au sein de notre organisme de formation\nGr√¢ce √† nos parcours de carri√®re gamifi√©s, nos training kit et notre dispositif d‚Äôaccompagnement, Datatorii vous int√®gre dans un parcours certifiant et vous offre toutes les chances de r√©ussir avec des perspectives de carri√®re claires et stimulantes.\n3. Profil\nFormation initiale\nBAC +5 Ecole de commerce (Data Analyst, Data Business) ou (Ing√©nieur, math√©matiques, statistiques, informatique)\nConnaissances ou exp√©riences\nVous poss√©dez une premi√®re exp√©rience significative en DataViz\nVous y avez d√©velopp√© des comp√©tences de Business Analyst (DataViz, UX, Mod√©lisation, etc. )\nQualit√©s\nExcellent relationnel\nBon communicant\nProactif\nP√©dagogue\nCapacit√© d‚Äôanalyse et de synth√®se\nShow more\nShow less",
        "details": {
            "JobDetail": [],
            "TypeContract": "",
            "Salary": "",
            "Level": "",
            "Experience": null
        },
        "title": "data analyst",
        "skills": {
            "ProgLanguage": [
                "R",
                "Python"
            ],
            "DataBase": [
                "SQL"
            ],
            "DataAnalytics": [
                "R"
            ],
            "CloudComputing": [
                "Azure"
            ],
            "Automation": [
                "Chef"
            ],
            "Other": [
                "Statistiques"
            ],
            "EnSoftSkils": [
                "Communication"
            ]
        }
    },
    {
        "source": "LinkedIn",
        "company": "Iveco Group",
        "location": "Le Plessis-Belleville, Hauts-de-France, France",
        "link": "https://fr.linkedin.com/jobs/view/data-analysis-assistant-at-iveco-group-3907438232?position=30&pageNum=0&refId=jBvsgtdGm8ta0dsilpa8wg%3D%3D&trackingId=F5EWPCh8u9x3K4ieBNS%2F9A%3D%3D&trk=public_jobs_jserp-result_search-card",
        "description": "FPT Industrial est une marque d'Iveco Group (IVG: MI), d√©di√©e √† la conception, la production et la vente de groupes motopropulseurs et solutions destin√©s aux v√©hicules routiers et tout-terrain, ainsi qu'aux applications marines et de production d'√©nergie. Plus de 8000 salari√©s, r√©partis sur onze sites de production et onze centres de R&D travaillent pour FPT Industrial √† travers le monde. Implant√©s dans pr√®s de 100 pays, le r√©seau mondial de vente et le Customer Service de FTP Industrial soutiennent tous les clients de la Marque.\nNous recherchons : Un(e) assistant(e) Data Analysis en alternance\nMissions :\n‚Ä¢ Fournir les principaux rapports sur les ventes et les produits au niveau de Monde (Europe, Moyen Orient , Asie, Afrique, Am√©rique latine)\n‚Ä¢ Collecter et compiler les donn√©es sur la concurrence et les donn√©es potentielles au niveau des produits\n‚Ä¢ Analyser la performance des ventes par produit\n‚Ä¢ √âlaborer des rapports standards, un tableau de bord des produits et un suivi des indicateurs de performances cl√©s.\n‚Ä¢ Identifier les potentiels produits/ Running parks\nProfil :\nMaster marketing strat√©gique / Data analytics ‚Äì Business analytics\n-Anglais op√©rationnel, l'italien est un plus\n-Comp√©tences d'analyse requises\n-Ouvert d'esprit et curieux : vous ferez partie d'une √©quipe internationale situ√©e entre Le Plessis Belleville et Turin et vous travaillerez dans le d√©partement marketing Reman\n-Dur√©e : √† partir de septembre 2024 pendant 12 √† 24 mois\nOutils :\n-Microsoft Office\n-Excel : tr√®s bonne maitrise\n-Powerpoint : bonne maitrise\n-La maitrise d‚ÄôAccess est un plus\n-Data Warehouse (SAP BW)\n-Qlik sense\n-Power BI est un plus\nShow more\nShow less",
        "details": {
            "JobDetail": [],
            "TypeContract": "",
            "Salary": "",
            "Level": "",
            "Experience": null
        },
        "title": "Other",
        "skills": {
            "ProgLanguage": [
                "R"
            ],
            "DataAnalytics": [
                "R"
            ],
            "DataVisualisation": [
                "Power BI",
                "Tableau"
            ]
        }
    },
    {
        "source": "LinkedIn",
        "company": "Mobiskill | WEFY Group",
        "location": "Paris",
        "link": "https://fr.linkedin.com/jobs/view/data-analyst-at-mobiskill-wefy-group-3900004007?position=31&pageNum=0&refId=jBvsgtdGm8ta0dsilpa8wg%3D%3D&trackingId=FfuHS0i2DjiQ05OHyrPcnQ%3D%3D&trk=public_jobs_jserp-result_search-card",
        "description": "L'entreprise?\nInsurTech r√©cemment cr√©√©e, elle s'impose comme r√©f√©rence sur son march√© en proposant des produits d'assurance disruptif.\nIls travaillent avec des petites entreprises comme des grands noms de l'assurance et cumulent 1 millions de clients.\nTeam?\n40 personnes\nContexte?\nForte traction commerciale, ils ont besoin de structurer leur donn√©e afin de cr√©er de la valeur en interne et de la d√©livrer √† leurs clients aussi.\nLes missions?\n- Participer √† la construction de la roadmap data sur le moyen et le long terme (en accord avec les Business units)\n- Leader la mise en former d'une grosse volum√©trie de Data pour d√©gager de la valeur pour leurs partenaires existants\n- R√©aliser des √©tudes exploratoires pouss√©es pour apporter des recommandations strat√©giques √† l'entreprise\n- Co-construire les KPIs, OKR et dashboards, puis les automatiser\n- A/B testing sur de potentiels features\nTon profil?\n- Dipl√¥m√©(e) Bac+5, vous justifiez d'une exp√©rience de 3 ans minimum dans la Data analyse\n- Id√©alement, vous √™tes familier de l'univers de l'assurance\n- Dot√©(e) d'une forte capacit√© analytique, vous √™tes aussi capable d'exprimer clairement vos √† recommandations √† l'oral\n- Tu ma√Ætrises SQL et un outil de Data vizualisation (Tableau/PowerBI). Id√©alement tu es aussi familier de Python\n- Fiabilit√©, proactivit√© et autonomie sont des comp√©tences cl√©s √† ce poste\nLes++?\n- Soci√©t√© en pleine croissance (suite √† leur lev√©e de fonds, la roadmap 2024 est valid√©e et ils sont pr√™ts √† scaler )\n- Organisation d‚Äôentreprise alliant flexibilit√© et structure (m√©thode de l‚Äôautonomie align√©e)\n- Poste √©volutif avec de fortes perspectives d'√©volutions (dont management)\n- Package attractif\nShow more\nShow less",
        "details": {
            "JobDetail": [],
            "TypeContract": "",
            "Salary": "Package",
            "Level": "Bac+5",
            "Experience": "3 an(s)"
        },
        "title": "data analyst",
        "skills": {
            "ProgLanguage": [
                "Python"
            ],
            "DataBase": [
                "SQL"
            ],
            "DataVisualisation": [
                "Tableau"
            ]
        }
    },
    {
        "source": "LinkedIn",
        "company": "Astek",
        "location": "Lille, Hauts-de-France, France",
        "link": "https://fr.linkedin.com/jobs/view/data-analyst-%E2%80%93-lille-france-h-f-at-astek-3839093481?position=32&pageNum=0&refId=jBvsgtdGm8ta0dsilpa8wg%3D%3D&trackingId=MoPSjLmEdUkC3hffLr7yzg%3D%3D&trk=public_jobs_jserp-result_search-card",
        "description": "CDI\nLille - France\nPubli√©e il y a 2 mois\nLe Groupe Astek\nCe Que Nous Allons Accomplir Ensemble :\nNous rejoindre en tant que\nData Analyst (H/F),\nafin d‚Äôaccompagner un op√©rateur t√©l√©coms, Leader en Europe dans la gestion de ses solutions robustes, efficientes et s√©curis√©es √† destination d‚Äôenvironnements vari√©s.\nUn challenge portant sur des millions d‚Äôutilisateurs dans un environnement technique innovant, strat√©gique et o√π l‚Äôentraide et la bonne humeur priment !\nVotre Mission, Si Vous L‚Äôacceptez :\nEtude sur les donn√©es pour aide au cadrage du besoin M√©tier.\nForce de proposition sur des solutions analytiques adapt√©es aux besoins utilisateurs (avec nos √©quipes UX).\nAnalyse des besoins m√©tiers, accompagnement √† la formulation et √† la d√©finition de KPI m√©tiers.\nMod√©lisation des donn√©es.\nConception de Datasets Big Query.\nConception et R√©alisation de Datamarts et de Dashboards (PowerBI / Looker)\nAnalyse de la qualit√© de la donn√©e source, pour challenger les √©quipes Digitales / Data Engineers.\nVotre Future √âquipe :\nAu sein d‚Äôun environnement riche et complexe, vous √©voluerez avec des experts passionn√©s √† la fois techniques et fonctionnels (Ing√©nieurs sp√©cialis√©s, chef de projet, scrum master, product owner ‚Ä¶).\nL‚Äô√©quipe est en interaction avec des clients √† la fois internes et externes.\nVotre stack de jeu\nSQL ‚Äì Confirm√©\nMod√©lisation de Donn√©es ‚Äì Confirm√©\nOutils de Data Viz ‚Äì Confirm√©\nGCP ‚Äì Junior\nAnglais ‚Äì Professionnel\nLes Petits Plus Du Projet :\nVous interviendrez de A √† Z sur des projets riches fonctionnellement et ambitieux techniquement. Un challenge portant sur des millions d‚Äôutilisateurs dans un environnement technique innovant et strat√©gique.\nVous ?\nDipl√¥m√©(e) d‚Äôune √©cole d‚Äôing√©nieur ou √©quivalent de niveau Bac+5.\nVous justifiez id√©alement d‚Äôune exp√©rience d‚Äôau moins 3 ans d‚Äôexp√©riences sur un poste similaire ?\nVous faite preuve d‚Äôun bon relationnel et d‚Äôesprit d‚Äô√©quipe, √™tes dot√©(e) d‚Äôun excellent sens de l‚Äôorganisation et vous aimez les challenges et la r√©solution de probl√®me ?\nAlors ce poste est fait pour vous, n‚Äôh√©sitez plus et rejoignez l‚Äôaventure ASTEK !\nAstek\nCr√©√© en France en 1988, Astek est un acteur mondial de l‚Äôing√©nierie et du conseil en technologies. Fort de son expertise dans de nombreux secteurs industriels et tertiaires, Astek accompagne ses clients internationaux dans le d√©ploiement intelligent de leurs produits et de leurs services, et dans la mise en ≈ìuvre de leur transformation digitale.\nDepuis sa cr√©ation, le Groupe a fond√© son d√©veloppement sur une forte culture d‚Äôentrepreneuriat et d‚Äôinnovation, et sur l‚Äôaccompagnement et la mont√©e en comp√©tence de\nses 7800 collaborateurs\nqui s‚Äôengagent chaque jour √† promouvoir la compl√©mentarit√© entre les technologies num√©riques et l‚Äôing√©nierie des syst√®mes complexes.\nRejoignez un Groupe en fort d√©veloppement en France et √† travers le monde ayant r√©alis√© un chiffre d‚Äôaffaires de 600 M‚Ç¨ en 2023.\nTous les d√©tails sur le Groupe sur le site https://astekgroup.fr. Et vous pouvez aussi nous suivre sur notre blog : https://blog.groupeastek.com.\nRencontrons-nous\nNotre projet commun vous plait ?\nPostulez √† cette annonce, et soyez transparent !\nMaud, notre Talent Acquisition Referent, vous contactera pour un premier √©change.\nPuis vous rencontrerez Martin, votre futur manager, avec lequel vous √©changerez autour d‚ÄôAstek, de votre parcours, de vos attentes et de votre future mission .\nEnfin, vous rencontrerez J√©r√©my, notre Directeur d‚Äôagence avec lequel vous pourrez valider votre int√©r√™t et ad√©quation pour le poste et finaliser les √©l√©ments contractuels.\nNos Plus\nAstek est green et fait b√©n√©ficier ses salari√©s d‚Äôune indemnit√© kilom√©trique v√©lo\nUne politique CARE sur-mesure d√©ploy√©e par nos √©quipes RH pour nos collaborateurs (https://astekgroup.fr/engagements)\nNotre charte de la Diversit√©\nMots-cl√©s :\ning√©nieur ‚Äì ing√©nieure ‚Äì consultant ‚Äì consultante ‚Äì data ‚Äì analyst ‚Äì mod√©lisation ‚Äì donn√©es\nCaract√©ristiques de l'emploi\nCat√©gorie Ing√©nieur\nJob Industry T√©l√©com / M√©dia\nPostuler en ligne\nNom *\nPr√©nom *\nEmail *\nUn email valide est requis.\nT√©l√©phone *\nUn num√©ro de t√©l√©phone valide est requis.\nJoindre un CV *\nMots-cl√©s :\ning√©nieur ‚Äì ing√©nieure ‚Äì consultant ‚Äì consultante ‚Äì data ‚Äì analyst ‚Äì mod√©lisation ‚Äì donn√©es\nShow more\nShow less",
        "details": {
            "JobDetail": [
                "Confirm√©",
                "Junior"
            ],
            "TypeContract": "CDI",
            "Salary": "",
            "Level": "Bac+5",
            "Experience": "3 an(s)"
        },
        "title": "data analyst",
        "skills": {
            "DataBase": [
                "SQL"
            ],
            "CloudComputing": [
                "GCP"
            ],
            "DBMS": [
                "Big Query"
            ],
            "Automation": [
                "Chef"
            ]
        }
    },
    {
        "source": "LinkedIn",
        "company": "moOngy Digital Lab",
        "location": "Lille",
        "link": "https://fr.linkedin.com/jobs/view/data-analyst-h-f-at-moongy-digital-lab-3890974953?position=33&pageNum=0&refId=jBvsgtdGm8ta0dsilpa8wg%3D%3D&trackingId=L9xZtAwqXVojDTcbN2pv7g%3D%3D&trk=public_jobs_jserp-result_search-card",
        "description": "Web Transition, c‚Äôest qui ?\nFond√©e en 2011,\nWeb transition\nest une entreprise de services num√©riques op√©rant sur le march√© de l‚ÄôIT/Digital !\nConstituant une part essentielle de\nMoOngy Digital Lab\n, Web Transition accompagne ses clients grands comptes sur leurs projets de Webmarketing, de Design, Gestion de projet et √©galement en Data !\nNotre objectif : nous implanter comme un acteur principal sur le march√© de la Transformation Digitale en accompagnant et valorisant les comp√©tences de nos collaborateurs !\nNous sommes convaincus que le succ√®s de MoOngy Digital Lab r√©side dans la somme des potentiels de nos √©quipes ü§ù\nTon √©quipe : La tribu Data\nParce qu‚Äôil est indispensable que tu puisses partager tes connaissances mais aussi en acqu√©rir de nouvelles, tu feras partie de l‚Äôune de nos tribus : celle de la Data. De plus, cela te permettra d‚Äô√™tre acteur dans le d√©veloppement et la strat√©gie de Web Transition. Ce syst√®me de co-r√©flexion et co-construction est un fondement essentiel chez nous !\nDans cette aventure, tu :\nOptimises\nles requ√™tes SQL ;\nConstruis\nles mod√®les de r√©gression ;\nAnalyses\nla rentabilit√© des actions marketing ;\nR√©alises\ndes √©tudes ad hoc sur les comportements clients ;\nProduits\net\nautomatises\nle reporting.\nRejoins-nous si tu as :\nUne exp√©rience de 3 ans minimum,\nUne maitrise technique de GCP / DBT / PowerBI,\nUne exp√©rience similaire dans une startup ou dans l‚Äôindustrie serait un plus !\nTon savoir-√™tre :\nOuvert d‚Äôesprit\nRespectueux des diff√©rences de chacun\nCurieux\nProactif\nPar o√π on commence ?\nUn premier entretien RH d‚Äô1h pour comprendre ton parcours et tes aspirations\nUn second entretien de 45 minutes avec l‚Äôun de nos Business Manager afin de valider tes comp√©tences et qu‚Äôil se projette sur l‚Äôune des missions qu‚Äôil pourrait te proposer\nUn troisi√®me entretien de quelques minutes avec notre responsable d‚Äôagence pour te proposer d‚Äôint√©grer notre superbe Team Web !\n3 entretiens en peu de temps, si ton profil correspond tu int√®greras tr√®s vite nos √©quipes üòâ\nPr√™t pour embarquer dans notre grande aventure humaine ? Deviens notre futur Weber en postulant √† cette offre ! Voici les avantages qui t‚Äôattendent en tant que Weber :\nü§© Des coll√®gues incroyables\nüèÜ Certifi√©e Great Place to Work\nüéÆ Des bureaux sympas (o√π vous serez toujours les bienvenus)\nüéâ Des teambuilding et √©vents tous les mois\nüíª Des tributs m√©tiers pour √©changer entre Weber du m√™me m√©tier\nDes missions chez le client qui sont accompagn√©es et coach√©es par ton manager\nUn accompagnement dans ton plan de carri√®re et tes envies de re skilling\nü§ì Un catalogue de formations certifiantes ouvert √† tous les salari√©s\nüçΩÔ∏è Une carte tickets restaurant MyEdenred\n‚ù§Ô∏è Une mutuelle GrasSavoye\nüöé Une prise en charge des frais de transport √† 100%\nShow more\nShow less",
        "details": {
            "JobDetail": [],
            "TypeContract": "",
            "Salary": "",
            "Level": "",
            "Experience": "3 an(s)"
        },
        "title": "data analyst",
        "skills": {
            "DataBase": [
                "SQL"
            ],
            "CloudComputing": [
                "GCP"
            ]
        }
    },
    {
        "source": "LinkedIn",
        "company": "Novencia Group",
        "location": "Lyon, Auvergne-Rh√¥ne-Alpes, France",
        "link": "https://fr.linkedin.com/jobs/view/data-analyst-lyon-f-h-at-novencia-group-3842056375?position=34&pageNum=0&refId=jBvsgtdGm8ta0dsilpa8wg%3D%3D&trackingId=R7ljJszcODXjSIF%2F3My0tQ%3D%3D&trk=public_jobs_jserp-result_search-card",
        "description": "Carnet de route\nNovencia accompagne ses clients dans leurs projets de transformation digitale, technologique et data.\nExpert en Data et Intelligence Artificielle nous aidons nos clients √† exploiter et valoriser leurs donn√©es sous toutes ses formes en les accompagnant sur des projets de Data Gouvernance, Data Architecture, Data Science, et Data Engineering.\nData Analyst\ndepuis au moins\n3 ans,\ntu es √† la recherche de nouveaux d√©fis. Boucle ta ceinture, la suite est pour toi !\nTon R√¥le\nRattach√©.e aux consultants de l‚Äôagence Lyonnaise, tu seras amen√©.e √† travailler chez les clients finaux et/ou au sein de notre Datalab‚Äô.\nEn tant que Data Analyst, tu auras les missions suivantes :\nT‚Äôimmerger dans le contexte client ;\nMener des ateliers avec les √©quipes m√©tier pour recueillir/ d√©finir leurs besoins ;\nChallenger leurs demandes ;\nParticiper au recueil et √† la mod√©lisation des donn√©es ;\nContr√¥ler la fiabilit√© et la qualit√© des donn√©es ;\nStructurer et exploiter les donn√©es gr√¢ce √† des outils de Data visualisation ;\nAnalyser ces donn√©es et partager les r√©sultats ;\nFaire des recommandations au client.\nTon profil\nDe formation Bac+5 dans le domaine de la Data, tu as au moins 3 ans d‚Äôexp√©rience sur un poste similaire.\nComp√©tences techniques recherch√©es :\nExp√©rience significative sur un outil de Data visualisation pour l‚Äô√©laboration de rapports/tableaux de bord (Power BI/Tableau/QlikSense etc.)\nLangage SQL (Python est un plus)\nMod√©lisation de donn√©es\nConnaissance des bases de donn√©es (e.g. Snowflake, Google BigQuery, SQL Server ou Oracle)\nUtilisation d‚Äôun ETL (e.g. Azure Data Factory, SSIS, Informatica, Talend, Matillion)\nUne exp√©rience dans le fonctionnement d‚Äôune √©quipe agile.\nTu es passionn√©.e par la Data et souhaites √©voluer au sein d‚Äôune communaut√© d‚ÄôExperts de la Data, tu veux t‚Äôinvestir dans des projets data innovants au sein de notre Datalab‚Äô, tu aimes le travail en √©quipe mais sais √™tre autonome sur tes sujets, tu es curieux.euse et force de proposition, tu es capable de chercher et trouver des solutions, tu as un bon niveau d‚Äôanglais.\nEnfin, tu souhaites int√©grer une agence √† taille humaine o√π la bienveillance n‚Äôest pas qu‚Äôun mot marketing.\nS‚Äôengager en faveur du handicap c‚Äôest garantir l‚Äô√©galit√© des chances d√®s le recrutement. √Ä comp√©tences √©gales, nos postes sont ouverts aux personnes en situation de handicap.\nShow more\nShow less",
        "details": {
            "JobDetail": [],
            "TypeContract": "",
            "Salary": "",
            "Level": "Bac+5",
            "Experience": "3 an(s)"
        },
        "title": "data analyst",
        "skills": {
            "ProgLanguage": [
                "Python"
            ],
            "DataBase": [
                "SQL"
            ],
            "DataVisualisation": [
                "Power BI",
                "Tableau"
            ],
            "CloudComputing": [
                "Azure"
            ],
            "DBMS": [
                "SQL Server",
                "BigQuery",
                "Snowflake"
            ]
        }
    },
    {
        "source": "LinkedIn",
        "company": "LEADER S.A.S",
        "location": "Le Havre",
        "link": "https://fr.linkedin.com/jobs/view/data-analyst-h-f-at-leader-s-a-s-3909699484?position=35&pageNum=0&refId=jBvsgtdGm8ta0dsilpa8wg%3D%3D&trackingId=nx78yvS12QieiR91FCSxDQ%3D%3D&trk=public_jobs_jserp-result_search-card",
        "description": "Les soci√©t√©s de LEADER GROUP repr√©sent√©es par pr√®s de 170 salari√©s en France, Allemagne, Autriche, Chine et Etats-Unis, proposent √† leurs clients du monde entier un ensemble de produits ‚Äì √©mulseurs, √©quipements mousse, appareils de recherche de victimes, ventilateurs de d√©senfumage, lances, canons incendies, cam√©ras thermiques, etc. ‚Äì de haute technicit√© et fiables en toutes circonstances pour prot√©ger et secourir les personnes et les biens.\nL'innovation est l'un des moteurs essentiels du Groupe, qui s'appuie √©galement sur un syst√®me d'am√©lioration continue et de responsabilit√© soci√©tale et environnementale.\nRaison d‚Äô√™tre de Leader Group : ¬´ Aider √† sauver des vies ¬ª\nPour r√©pondre √† sa dynamique de croissance, LEADER renforce ses √©quipes et recherche son/sa futur(e)\nData Analyst H/F\nCDI ‚Äì temps plein ‚Äì Le Havre/Octeville sur mer (76)\nVos missions\nRattach√©(e) au site de LEADER et sous la responsabilit√© du Directeur Commercial et Marketing, le/la Data Analyst se charge de l'analyse des donn√©es commerciales et marketing pour aider √† la prise de d√©cisions √©clair√©es au sein des entit√©s du groupe. A ce titre vos principales missions seront de :\nR√©aliser des analyses approfondies des donn√©es de ventes internes, et du march√© des √©quipements concern√©s, incluant les tendances, la demande, et les innovations technologiques.\n√âtudier la concurrence pour comprendre leurs produits, tarifications, et strat√©gies marketing.\nCollaborer √©troitement avec les √©quipes de vente, et chefs produits pour partager les insights du march√© et orienter le d√©veloppement de produits et les strat√©gies commerciales.\n√âlaborer des rapports d√©taill√©s et des pr√©sentations pour la direction, avec des recommandations permettant de guider les d√©cisions strat√©giques, et soutenir l‚Äô√©quipe commerciale.\nEtudier chaque march√© et connaitre le potentiel en chiffres et en volumes dans chaque pays pour les activit√©s de Leader et diff√©rentes familles de produits.\nRechercher, r√©f√©rencer et suivre les appels d‚Äôoffres\nVotre profil\nTitulaire d‚Äôun bac + 4/5 en marketing ou statistiques, vous justifiez d‚Äôune premi√®re exp√©rience du secteur industriel, B2B et des produits techniques.\nOrient√©(e) am√©lioration continue, vous avez une ma√Ætrise parfaite des outils informatiques (Excel), CRM et ERP, de bonnes comp√©tences analytiques et la capacit√© √† communiquer des informations complexes de mani√®re claire et compr√©hensible.\nLa curiosit√©, le souci du d√©tail et une bonne aisance relationnelle sont des qualit√©s qui vous caract√©risent.\nVotre maitrise de l‚Äôanglais vous permet de communiquer ais√©ment √† l‚Äô√©crit comme √† l‚Äôoral.\nDes d√©placements nationaux et internationaux ponctuels sont √† pr√©voir.\nInformations compl√©mentaires\nVotre futur bureau est bas√© √† Octeville sur Mer, commune littorale limitrophe du Havre, au c≈ìur du si√®ge social du Groupe.\nA votre salaire de base (35K‚Ç¨ √† 38K‚Ç¨/an), s‚Äôajoutent une prime annuelle, RTT, mutuelle d‚Äôentreprise, t√©l√©travail partiel possible, conciergerie d‚Äôentreprise, et des titres restaurant.\nSi vous vous reconnaissez dans ce descriptif, et souhaitez relever de nouveaux d√©fis au sein d'une entreprise innovante, en pleine √©volution, rejoignez-nous en envoyant votre candidature\nNous avons h√¢te de vous rencontrer et de d√©couvrir comment vous pouvez contribuer √† notre √©quipe dynamique et √† nos projets passionnants.\nLes √©quipes de LEADER innovent chaque jour pour prot√©ger et secourir.\nPour en savoir plus, n‚Äôh√©sitez pas √† consulter notre site https://www.leader-group.company/fr\nShow more\nShow less",
        "details": {
            "JobDetail": [
                "Temps plein"
            ],
            "TypeContract": "CDI",
            "Salary": "35K",
            "Level": "",
            "Experience": null
        },
        "title": "data analyst",
        "skills": {
            "Other": [
                "Statistiques"
            ]
        }
    },
    {
        "source": "LinkedIn",
        "company": "Volvo Group",
        "location": "V√©nissieux, Auvergne-Rh√¥ne-Alpes, France",
        "link": "https://fr.linkedin.com/jobs/view/data-analyst-at-volvo-group-3860811035?position=36&pageNum=0&refId=jBvsgtdGm8ta0dsilpa8wg%3D%3D&trackingId=Pr5ZjV2XGcCz4zrvvT5ZTQ%3D%3D&trk=public_jobs_jserp-result_search-card",
        "description": "Transport is at the core of modern society. Imagine using your expertise to shape sustainable transport solutions for the future? If you seek to make a difference on a global scale, working with next-gen technologies and the sharpest collaborative teams, then we could be a perfect match.\nWhat You Will Do\nAt DIGITAL&IT DATA you will contribute to the transformation of our company, the transport industry and society at large. You will:\nDrive workshops with the business stakeholders to understand their business context and to collect their needs.\nBecome a Data expert on one or more business domains, to draw conclusions and to provide answers to business stakeholders questions.\nAccess, manipulate, query, and analyze data using different software, tools and techniques.\nBe part of the data modeling process (design and implementation) as well as in the definition of business rules that will ensure data consistency and quality.\nPre-process, clean and structure data to facilitate data exploration and advanced analytics activities.\nDesign and implement dashboards using advanced visualization tools.\nWork in cross functional agile teams to continuously experiment, iterate and deliver on new product objectives.\nBe an active member of the Data Analyst Chapter, sharing knowledge and best practices with your peers.\nBenefit from dedicated trainings to maintain and develop your Data Analyst skills.\nYour Future Team\nAs Data Analyst, you will be part of A&BI (Analytics & Business Intelligence) Trucks Dealer agile team. You will have opportunity to work on heterogenous topics such as (non exhaustive list):\nPaperless NLP: Support Paperless project thanks to NLP (Natural Language Processing) & AI (Artificial Intelligence) processes,\nDealer Quality program: Set of Key Performance Indicators on all Dealer processes to support Sales Area organization,\nSet up Data Product on Azure to support smart business services,\nBe part of the maintenance team to ensure business process continuity, ...\nWho are you?\nDo you dream big? We do too, and we are excited to grow together. Are you the one?\nHaving a master degree or equivalent in IT.\nData & Data Analysis‚ÄØhas been‚ÄØyour‚ÄØworld‚ÄØfor 3-5‚ÄØyears‚ÄØnow.\nYou are an experienced Data Analyst looking for new challenges in the transport industry. You‚ÄØare‚ÄØproactive‚ÄØproblem‚ÄØsolver‚ÄØwith‚ÄØinnovative‚ÄØthinking‚ÄØwith‚ÄØa strong‚ÄØsense of teamwork.\nWriting SQL and doing data modelling are natural activities for you.\nYou are experienced working on data manipulation and data modeling.\nYou are experienced designing and developing dashboard using at least one visualization tool (such as PowerBI for example).\nYou are familiar with Azure Data Analytics Stack (Storage accounts, Databricks, Azure Data Factory, SQL Server, SQL Data base, etc...).\nYou are familiar writing scripts on Python to do data preparation/cleaning.\nYou have excellent communication skills in French and English (C1 level)\nReady for the next move?\nAre you excited to bring your skills and disruptive ideas to the table? We can‚Äôt wait to hear from you. Apply today!\nWe value your data privacy and therefore do not accept applications via mail.\nWho We Are And What We Believe In\nOur focus on Inclusion, Diversity, and Equity allows each of us the opportunity to bring our full authentic self to work and thrive by providing a safe and supportive environment, free of harassment and discrimination. We are committed to removing the barriers to entry, which is why we ask that even if you feel you may not meet every qualification on the job description, please apply and let us decide.\nApplying to this job offers you the opportunity to join\nVolvo Group.\nEvery day, across the globe, our trucks, buses, engines, construction equipment, financial services, and solutions make modern life possible. We are almost 100,000 people empowered to shape the future landscape of efficient, safe and sustainable transport solutions. Fulfilling our mission creates countless career opportunities for talents with sharp minds and passion across the group‚Äôs leading brands and entities.\nGroup Digital & IT\nis the hub for digital development within Volvo Group. Imagine yourself working with cutting-edge technologies in a global team, represented in more than 30 countries. We are dedicated to leading the way of tomorrow‚Äôs transport solutions, guided by a strong customer mindset and high level of curiosity, both as individuals and as a team. Here, you will thrive in your career in an environment where your voice is heard and your ideas matter.\n‚Äò\nData\n‚Äô is a new function within Volvo Digital & IT with the goal to unlock the power of data for the whole Volvo Group to become a fully data-driven company! With data, the core component of our transformation journey, we will, together with our data talents, make the Volvo Group 2030 vision happen. We will take care of all the aspects of Data, how it is quality assured, documented, made available, prepared and consumed through BI, Analytics and Machine Learning. We have an ambitious transformation in front of us, with an implementation of the Data Layer in Azure as well as the reinforcement of Data Governance and Data Management in the full Group.\nThe ‚ÄòData‚Äô function is a large multi-cultural organization with 600+ employees and contractors located mainly in 7 countries - Sweden, Poland, India, Belgium, Brazil, USA, and France. In this role you will be joining the Data Analyst Chapter team in France.\nWe collaborate with other parts of the organization, both in Volvo Digital & IT, with Truck Divisions, Business Areas and Group Functions. We foster an environment where ideas, thoughts and opinions can be shared. We are team players with clear common ambitions, and we win together.\nShow more\nShow less",
        "details": {
            "JobDetail": [
                "Full"
            ],
            "TypeContract": "",
            "Salary": "",
            "Level": "",
            "Experience": null
        },
        "title": "data analyst",
        "skills": {
            "ProgLanguage": [
                "Python"
            ],
            "DataBase": [
                "SQL"
            ],
            "BigData": [
                "Databricks"
            ],
            "CloudComputing": [
                "Azure"
            ],
            "DBMS": [
                "SQL Server"
            ],
            "Collaboration": [
                "Teams"
            ],
            "Other": [
                "Machine Learning"
            ],
            "EnSoftSkils": [
                "Teamwork",
                "Communication",
                "Organization"
            ]
        }
    },
    {
        "source": "LinkedIn",
        "company": "Malt",
        "location": "Paris, √éle-de-France, France",
        "link": "https://fr.linkedin.com/jobs/view/senior-data-analyst-at-malt-3916770897?position=37&pageNum=0&refId=jBvsgtdGm8ta0dsilpa8wg%3D%3D&trackingId=Jzp%2FN8TZv3I1hmLBJnA%2FGw%3D%3D&trk=public_jobs_jserp-result_search-card",
        "description": "Discover our galaxy ü™ê\nSince 2013, when Malt was founded by Vincent Huguet and Hugo Lassi√®ge, we have become Europe‚Äôs fastest-growing freelance marketplace.\nBy acquiring Comatch (the Berlin-based leading marketplace for top freelance management consultants and industry experts) in 2022, we‚Äôre now home to a dynamic community of 550k+ freelancers, 70k+ companies, and 700+ Malters.\nWe‚Äôve built the industry‚Äôs leading freelance management solution ‚Äî all on a powerful, data driven tech platform ‚Äî to match companies with the right freelance talent.\nBut we‚Äôre more than just a connector. Our marketplace streamlines freelancer-client communications, simplifies administrative and legal tasks, expedites invoicing and payments, and so much more.\nToday, our company is growing fast! We need people like you to help us write this next chapter.\nWe Are a Tech Company With a Human Approach üëΩ\nStrong company culture fueled by 700+ Malters from 40 countries\nOffices and teams in France, Germany, Spain, Belgium, United Kingdom, the Netherlands, Switzerland and the Middle East\nCommitted to equality and diversity (50% of people managers are women)\nStrong career path policies allowing all Malters to develop and grow equally\nBacked by renowned investors including ISAI, Eurazeo Growth, Goldman Sachs and BPI France\nRecognized twice by LinkedIn as one of the best start-ups to work at\nExplore your future career üî≠\nYou would be part of Malt‚Äôs data team, an international team of about 30 people, with various profiles, including 7 data analysts, analytics engineers, data engineers, data scientists, and economists... The team is led by\nClaire Lebarz\n, Chief Data & AI Officer @ Malt, and former Head of Data @ Airbnb.\nJoin us and become part of the #FutureOfwork!\nKey Responsibilities ‚ú®\nDevelop a deep understanding of our freelancers and clients and how they interact with each other and with our product\nBe a partner to product and business teams across the marketplace, helping them to better understand their performance through strategic analytics and structured thinking\nSupport our most strategic topics with deep-dive analytics, insights, recommendations\nEmpower the teams across Malt to answer data questions quickly and easily by building high-quality ground truth data sets, metrics and dashboards.\nContribute to the modelization of our databases and semantic layer along with analytics engineers\nBe a key member of the data team, helping spread the data and AI culture within Malt\nAbout You üßë‚ÄçüöÄ\nYou have a Master‚Äôs degree in a quantitative field (e.g., Statistics, Econometrics, Computer Science, Engineering, Mathematics, Data Science, Operations Research) or in Business\nYou have +3 years of experience as a data analyst in a fast-paced and quantitative environment (start-up, scale-up, consulting‚Ä¶)\nYou consider yourself a full-stack data analyst: You write SQL perfectly, you know how to work with ETLs, you‚Äôve been using data modelization tools such as dbt, you can write simple Python scripts‚Ä¶ You are also very comfortable in using data visualization tools (e.g. Looker, Metabase, Tableau‚Ä¶)\nYou have strong communication (written and oral), presentation-building and storytelling skills\nYou are fluent in English\nYou are curious and eager to learn new things and grow\nWhat makes you different from others? ü´µ\nYou have good business acumen, but you also have a ‚Äúhacker‚Äù mindset, you enjoy leveraging technology to find solutions to problems\nYou have a growth mindset: you are comfortable in navigating and excelling in fast-paced environments with no playbook for success\nYou have an ability to influence people, but you are also a strong team player\nHow to join the mission? üöÄ\nScreening with Alex, our Tech Talent Acquisition Manager, to better understand your background, aspirations and answer your questions (45 minutes)\nExperience discussion and technical assessment with the Data Director (Gautier Chenard, your future manager) (45mn)\nTake home assignment and restitution to the Data Director & a Data Analyst (1h)\nInterview with Claire, our Chief Data Officer (30mn)\nMalt is the perfect space to thrive personally and professionally üí´\nOnboarding: Before easing into your new role, you‚Äôll spend your first week learning about our culture, products, and services with other onboardees at our office in Paris\nEquity: Every Malter is entitled to stock options\nLunch vouchers (legal benefit): ‚Ç¨9/day on your Swile card\nTransportation (legal benefit): 50% reimbursement (any type of transport)\nRTT: From 8 to 12 days off\nSports: company participation to a Gymlib membership\nMalt sabbatical: After three years, every Malter is entitled to a one month paid sabbatical leave\nFree books: If you‚Äôre interested in learning more about any topic relevant to Malt‚Äôs business, just tell us the books you‚Äôd like to read, and we‚Äôll order them for you‚Äîwithout any questions asked or approval processes to follow\nRemote work: Hybrid remote policy\nAnnual team building events\nReady? Get your ticket to Malt ü™ê\nShow more\nShow less",
        "details": {
            "JobDetail": [
                "Remote",
                "Full"
            ],
            "TypeContract": "",
            "Salary": "",
            "Level": "",
            "Experience": null
        },
        "title": "data analyst",
        "skills": {
            "ProgLanguage": [
                "Python"
            ],
            "DataBase": [
                "SQL"
            ],
            "DataVisualisation": [
                "Tableau"
            ],
            "Collaboration": [
                "Teams"
            ],
            "EnSoftSkils": [
                "Communication"
            ]
        }
    },
    {
        "source": "LinkedIn",
        "company": "Getaround",
        "location": "Paris, √éle-de-France, France",
        "link": "https://fr.linkedin.com/jobs/view/data-analyst-at-getaround-3913446628?position=38&pageNum=0&refId=jBvsgtdGm8ta0dsilpa8wg%3D%3D&trackingId=1fazPRFKmLVIT6qaPmVL5A%3D%3D&trk=public_jobs_jserp-result_search-card",
        "description": null,
        "details": {
            "JobDetail": [
                "Remote",
                "Full"
            ],
            "TypeContract": "",
            "Salary": "",
            "Level": "",
            "Experience": null
        },
        "title": "data analyst"
    },
    {
        "source": "LinkedIn",
        "company": "Richard Attias & Associates",
        "location": "Paris",
        "link": "https://fr.linkedin.com/jobs/view/junior-data-analyst-at-richard-attias-associates-3916877308?position=39&pageNum=0&refId=jBvsgtdGm8ta0dsilpa8wg%3D%3D&trackingId=eDRP4ZevCdv3sGQIe%2BPRiQ%3D%3D&trk=public_jobs_jserp-result_search-card",
        "description": "Description du poste :\nDans le cadre de son expansion et de son engagement √† consolider ses ressources, Richard Attias & Associ√©s souhaite renforcer ses √©quipes en am√©liorant et en √©toffant sa base de donn√©es.\nNous recherchons 5 collaborateurs talentueux qui auront les principales missions suivantes¬†:\nMise √† jour, maintenance et enrichissement de la base de donn√©es existante, notamment en identifiant et en ajoutant de nouveaux contacts pertinents issus de la presse internationale (les domaines de l'√©conomie et de la finance).\nResponsabilit√©s :\n¬∑¬†¬†¬†¬†¬†¬†¬†T√¢ches administratives quotidiennes :\n¬∑¬†¬†¬†¬†¬†¬†¬†Mise √† jour des contacts, maintien de l'exactitude et de la coh√©rence des informations de la base\n¬∑¬†¬†¬†¬†¬†¬†¬†Identification de nouveaux contacts qualifi√©s en lisant la presse internationale, en mettant des alertes internet de suivi de contacts/ domaines importants prioritaires pour nos √©v√©nements\n¬∑¬†¬†¬†¬†¬†¬†¬†Collaborer avec d'autres d√©partements pour assurer la coh√©rence et la qualit√© des donn√©es.\n¬∑¬†¬†¬†¬†¬†¬†¬†T√¢ches li√©es √† des projets :\n¬∑¬†¬†¬†¬†¬†¬†¬†√âtablir et maintenir des listes de conf√©renciers et de participants pour des √©v√©nements sp√©cifiques\n¬∑¬†¬†¬†¬†¬†¬†¬†Collaborer avec les √©quipes de projet pour d√©velopper des communaut√©s innovantes d‚Äôinfluencers / experts mondiaux\n¬∑¬†¬†¬†¬†¬†¬†¬†Identifier des tendances politiques, sociales, √©conomiques et mondiales pertinentes pour les sujets qui positionnent RA&A en tant que leader en communication strat√©gique\nProfil recherch√© :\n¬∑¬†¬†¬†¬†¬†¬†¬†Formation digitale / data management. 1ere exp√©rience en tant qu'analyste de donn√©es.\n¬∑¬†¬†¬†¬†¬†¬†¬†Excellente ma√Ætrise de MS Office, Excel, Powerpoint et bonne connaissance de Salesforce.\n¬∑¬†¬†¬†¬†¬†¬†¬†Bonne compr√©hension de l'√©conomie et de la politique internationale, conscience des probl√®mes mondiaux, de l'innovation internationale\n¬∑¬†¬†¬†¬†¬†¬†¬†Grande curiosit√© intellectuelle et proactivit√©\n¬∑¬†¬†¬†¬†¬†¬†¬†Comp√©tences organisationnelles exceptionnelles et capacit√© √† effectuer plusieurs t√¢ches √† la fois.\n¬∑¬†¬†¬†¬†¬†¬†¬†Rigueur, sens du d√©tail et esprit d'analyse d√©velopp√©\n¬∑¬†¬†¬†¬†¬†¬†¬†Flexibilit√© pour s'adapter √† un environnement dynamique.\n¬∑¬†¬†¬†¬†¬†¬†¬†Aptitude √† travailler en √©quipe et √† collaborer avec diff√©rents services.\n¬∑¬†¬†¬†¬†¬†¬†¬†Anglais courant + maitrise d‚Äôune autre langue appr√©ci√©e\nPour postuler :\nMerci d'envoyer votre CV et une lettre de motivation √† laurence.ania@richardattiasassociates.com\nLa r√©mun√©ration propos√©e sera discut√©e en fonction de l'exp√©rience et des comp√©tences du candidat retenu.\nShow more\nShow less",
        "details": {
            "JobDetail": [],
            "TypeContract": "",
            "Salary": "",
            "Level": "",
            "Experience": null
        },
        "title": "data analyst",
        "skills": {
            "EnSoftSkils": [
                "Communication"
            ]
        }
    },
    {
        "source": "LinkedIn",
        "company": "Wewyse",
        "location": "Paris, √éle-de-France, France",
        "link": "https://fr.linkedin.com/jobs/view/data-analyst-h-f-at-wewyse-3811756415?position=40&pageNum=0&refId=jBvsgtdGm8ta0dsilpa8wg%3D%3D&trackingId=rMTYnswMxIJJ%2BPlDS7ZOnw%3D%3D&trk=public_jobs_jserp-result_search-card",
        "description": "Wewyse\nest un cabinet de conseil sp√©cialis√© en\nData et en Intelligence Artificielle\n. C'est aussi et surtout une communaut√© de passionn√©s partageant l'ambition de grandir ensemble et d'ouvrir le champ des possibles dans leurs domaines.\nSi vous pensez que la Data et l'Intelligence Artificielle ont beaucoup √† offrir au monde de demain, et si vous souhaitez apporter votre contribution √† ce monde, avec humilit√© et enthousiasme, alors vous √™tes un Wyser en puissance.\n√ätre\nData Analyst\nchez Wewyse c'est :\nInt√©grer une communaut√© d‚Äôexperts Data passionn√©s,\nRecevoir et partager des connaissances, des savoirs-faire lors de nombreux √©v√®nements internes et acqu√©rir constamment de nouvelles comp√©tences,\nIntervenir sur des projets √† la fois techniques et business, souvent dans un contexte international, avec des forts enjeux strat√©giques aupr√®s de nos clients dans tous les secteurs (retail, √©nergie, m√©dias, transports, banque et assurance ‚Ä¶)\nViser l‚Äôexcellence dans la qualit√© et l‚Äôactionnabilit√© des analyses, gr√¢ce √† la ma√Ætrise technique des outils en Data Analytics (d√©veloppement, notebooks, visualisation, techniques de statistiques avanc√©es‚Ä¶) et la bonne compr√©hension des enjeux business de nos clients,\nParticiper √† des projets innovants, impactants et positifs au sein de notre Datalab, en √©quipe, avec des partenaires acad√©miques (CentraleSupelec, ‚Ä¶) et parfois avec des starts up, afin de laisser exprimer vos valeurs et vos id√©es,\nAvoir la possibilit√© de s‚Äôimpliquer dans le d√©veloppement de Wewyse (participer au recrutement, concevoir des formations, donner des masterclass en √©cole d‚Äôing√©nieur, participer √† l‚Äôavant-vente business, piloter des projets au sein du Datalab, d√©velopper de nouveaux partenariats ‚Ä¶)\n√ätre encourag√©, conseill√© et accompagn√© dans un parcours de formation adapt√© √† vos ambitions professionnelles et avec un budget d√©di√©,\nFaire partie de la famille Wemanity, cr√©er rapidement un r√©seau d‚Äôexperts et de personnes reconnues dans leur domaine, participer aux √©v√®nements communs (voyage annuel, talks, afterworks ...) et b√©n√©ficier des multiples opportunit√©s de carri√®re au sein du Groupe,\nAvoir l‚Äôopportunit√© de travailler avec une √©quipe dynamique, dans une ambiance start-up et √† taille humaine dans le centre de Paris (Op√©ra 9√®me arrondissement)\nCe que nous aimons :\nLes personnalit√©s ouvertes, curieuses, ambitieuses\nUn excellent niveau en\nSQL\nUne premi√®re exp√©rience en\nPython\nLa ma√Ætrise d‚Äôun outil de Data Visualisation\n(PBI, Tableau, Qlik, Looker, Data Studio ‚Ä¶)\nUne exp√©rience dans l‚Äôutilisation de\nJupyter Notebook / Databricks Notebook\nest fortement appr√©ci√©e\nL‚Äôaisance en communication\nL‚Äôesprit de synth√®se\nL'anglais\nVous vous reconnaissez ? Alors n'h√©sitez pas √† postuler !\nShow more\nShow less",
        "details": {
            "JobDetail": [],
            "TypeContract": "",
            "Salary": "",
            "Level": "",
            "Experience": null
        },
        "title": "data analyst",
        "skills": {
            "ProgLanguage": [
                "Python"
            ],
            "DataBase": [
                "SQL"
            ],
            "BigData": [
                "Databricks"
            ],
            "DataVisualisation": [
                "Tableau"
            ],
            "Other": [
                "Statistiques"
            ],
            "EnSoftSkils": [
                "Communication"
            ]
        }
    },
    {
        "source": "LinkedIn",
        "company": "Lincoln France",
        "location": "Hauts-de-France, France",
        "link": "https://fr.linkedin.com/jobs/view/data-analyst-h-f-at-lincoln-france-3827765148?position=41&pageNum=0&refId=jBvsgtdGm8ta0dsilpa8wg%3D%3D&trackingId=qxtFap4aZ1CurvlNOOEeEw%3D%3D&trk=public_jobs_jserp-result_search-card",
        "description": "DATA ANALYST H/F\nCDI\n3 ans minimum\nChez Lincoln\n, nous formons une communaut√© d'innovateurs passionn√©s qui red√©finissent l'analyse de donn√©es depuis\nplus de 30 ans\n. En tant que\nPure Player Data\n, notre expertise est reconnue dans les domaines\nde la Modern BI, du Big Data et de la Science des donn√©es\n.\nNotre mission ?\nTransformer les donn√©es en solutions concr√®tes pour nos clients grands comptes dans divers secteurs tels que la banque, le retail, les t√©l√©coms, l'industrie, la sant√©, etc.\nDescription de poste\nNous recherchons un\nData Analyst H/F\npour accompagner nos clients dans leurs projets strat√©giques.\nVos missions\nCollecter, nettoyer et traiter les donn√©es provenant de diff√©rentes sources.\nAnalyser les donn√©es pour identifier des tendances, des corr√©lations et des anomalies.\nConcevoir et d√©velopper des tableaux de bord et des rapports pour pr√©senter les r√©sultats de mani√®re claire et concise.\nCollaborer avec les √©quipes clients pour comprendre leurs besoins et recommander des solutions adapt√©es.\nPr√©requis :\nMa√Ætrise avanc√©e des langages de programmation\n(SQL, Python, R, etc.).\nConnaissance approfondie des bases de donn√©es relationnelles et non relationnelles.\nExp√©rience pratique avec des outils d'analyse de donn√©es\n(Tableau, Power BI, Looker, Qlik etc.).\nFortes comp√©tences analytiques et capacit√© √† transformer les donn√©es brutes en insights exploitables.\nExp√©rience de travail en\nm√©thode Agile\npour la gestion de projet et le d√©veloppement de solutions.\nCapacit√© √† travailler de mani√®re autonome et en √©quipe.\nExcellentes comp√©tences en communication et en pr√©sentation.\nLes plus du poste\nEnvironnement Collaboratif\n: projets innovants favorisant le partage des connaissances.\nAccompagnement individualis√© et de proximit√©\n: formations certifiantes, attribution d‚Äôun Career Manager pour vous orienter dans votre trajectoire professionnelle, opportunit√©s d‚Äô√©volution de carri√®re.\nFlexibilit√© du Travail\n: T√©l√©travail et horaires flexibles pour votre √©quilibre vie professionnelle-personnelle.\nR√©mun√©ration Comp√©titive\n: Salaire comp√©titif avec des avantages sociaux attrayants.\nMobilit√©\n: Possibilit√© de mobilit√© √† Paris, Lyon ou Aix-en-Provence offrant des exp√©riences diversifi√©es au sein de Lincoln.\nNotre processus de recrutement :\nUn entretien RH (1h) et entretien technique (1h)\nCette annonce n‚Äôest pas faite pour vous si :\nVous √™tes freelance et vous comptez le rester !\nToujours l√† ? Postulez et rejoignez nos\n400 experts en Data\nüòâ.\nShow more\nShow less",
        "details": {
            "JobDetail": [],
            "TypeContract": "CDI",
            "Salary": "400",
            "Level": "",
            "Experience": "3 an(s)"
        },
        "title": "data analyst",
        "skills": {
            "ProgLanguage": [
                "R",
                "Python"
            ],
            "DataBase": [
                "SQL"
            ],
            "DataAnalytics": [
                "R"
            ],
            "DataVisualisation": [
                "Power BI",
                "Tableau"
            ],
            "Other": [
                "Big Data"
            ],
            "EnSoftSkils": [
                "Communication"
            ]
        }
    },
    {
        "source": "LinkedIn",
        "company": "Akademija Oxford",
        "location": "Boulogne-Billancourt, √éle-de-France, France",
        "link": "https://fr.linkedin.com/jobs/view/data-analyst-sas-et-qlik-at-akademija-oxford-3917871100?position=42&pageNum=0&refId=jBvsgtdGm8ta0dsilpa8wg%3D%3D&trackingId=NhudTSdpC%2FS%2ByPoPbky7aw%3D%3D&trk=public_jobs_jserp-result_search-card",
        "description": "Un des grands acteurs du secteur des assurances, situ√© dans les Hauts-De-Seine, recherche un.e Data Analyst SAS et QLIK, pr√©parant un Mast√®re sp√©cialisation Big Data, en alternance pour le mois de Septembre 2021.\nShow more\nShow less",
        "details": {
            "JobDetail": [],
            "TypeContract": "",
            "Salary": "",
            "Level": "",
            "Experience": null
        },
        "title": "data analyst",
        "skills": {
            "Other": [
                "Big Data"
            ]
        }
    },
    {
        "source": "LinkedIn",
        "company": "Credit Agricole Consumer Finance",
        "location": "Roubaix, Hauts-de-France, France",
        "link": "https://fr.linkedin.com/jobs/view/data-analyst-senior-at-credit-agricole-consumer-finance-3870530425?position=43&pageNum=0&refId=jBvsgtdGm8ta0dsilpa8wg%3D%3D&trackingId=K%2Bzy5zcPgSd8rR8rgIQ37Q%3D%3D&trk=public_jobs_jserp-result_search-card",
        "description": "Filiale sp√©cialis√©e du Groupe Cr√©dit Agricole en cr√©dit √† la consommation, Cr√©dit Agricole Consumer Finance est l'un des leaders en Europe du cr√©dit √† la consommation et des solutions de financement. Il distribue une gamme compl√®te de produits et services associ√©s, en France et √† l'international.\nEn qualit√© de Lead Data Analyst, vous rejoindrez l‚Äô√©quipe Etudes et Data Science dans leur mission d‚Äô√©clairer l‚Äôentreprise et ses d√©cideurs par des √©l√©ments de d√©finition et de compr√©hension du business model et par des analyses strat√©giques et op√©rationnelles. Plus qu‚Äôune aide √† la d√©cision, les membres de l‚Äô√©quipe ont surtout un objectif de conseil √† l‚Äô√©gard des d√©cideurs de Cr√©dit Agricole Consumer Finance et de ses partenaires.\nVous aurez pour missions principales de :\nCollaborer en transverse avec plusieurs d√©partements internes (Marketing Direct, Digital, Web, Commerces BtoC, BtoB, etc)\nD√©finir des strat√©gies d‚Äôanalyse de donn√©es permettant de r√©pondre de mani√®re pertinente et pragmatique aux probl√©matiques des clients internes\nParticiper √† des projets d‚Äôentreprise et g√©rer des projets analytiques transverses de bout en bout\nCommuniquer efficacement les r√©sultats de vos analyses aux parties prenantes cl√©s pouvant aller des d√©cideurs internes aux √©quipes op√©rationnelles\nGarantir la fiabilit√© et la p√©rennit√© (robustesse et pertinence) des analyses r√©alis√©es en veillant √† la qualit√© de la donn√©e\nR√©aliser des √©tudes approfondies sur nos clients directs et ceux recrut√©s via nos partenaires Retail/grandes distributions afin d‚Äôapporter √† l‚Äôentreprise une vision globale de son portefeuille\nAssurer un management fonctionnel de plusieurs collaborateurs Data et √™tre en capacit√© de prendre en charge des ¬´ Squads ¬ª ou plusieurs collaborateurs se r√©unissent afin de d√©livrer sur un objectif commun\nVotre profil :\nVous avez une exp√©rience d‚Äôau moins trois ans sur un poste √©quivalent\nVous savez combiner une profondeur m√©thodologique avec une approche pragmatique de recherche de la valeur\nVous √™tes en capacit√© √† vous mettre au service du collectif, et √™tes √† l'aise avec la vulgarisation de votre savoir-faire et de vos comp√©tences\nVous avez envie de rejoindre une √©quipe dynamique, bienveillante avec une trajectoire ambitieuse sur les deux prochaines ann√©es\nVous ma√Ætrisez le langage SQL. Des exp√©riences sur Snowflake, PowerBI et/ou SAS seraient des plus\nShow more\nShow less",
        "details": {
            "JobDetail": [],
            "TypeContract": "",
            "Salary": "",
            "Level": "",
            "Experience": null
        },
        "title": "data analyst",
        "skills": {
            "DataBase": [
                "SQL"
            ],
            "DBMS": [
                "Snowflake"
            ]
        }
    },
    {
        "source": "LinkedIn",
        "company": "EXOMIND",
        "location": "√éle-de-France, France",
        "link": "https://fr.linkedin.com/jobs/view/data-analyst-h-f-at-exomind-3912508157?position=44&pageNum=0&refId=jBvsgtdGm8ta0dsilpa8wg%3D%3D&trackingId=j9uQZPtg0HquFycfbCZ46w%3D%3D&trk=public_jobs_jserp-result_search-card",
        "description": "Fusion entre le\ncabinet de conseil IT\net\nagence de d√©veloppement\n, nous accompagnons les grandes entreprises et les pure players dans la conception et le d√©veloppement de leurs solutions digitales.\nNous r√©alisons des applications web et mobiles sur mesure. Nos √©quipes compos√©es de Tech Lead, D√©veloppeurs, Testeur, Product Owner et Designers maitrisent l‚Äôensemble de la chaine de r√©alisation projet : conseil, design, d√©veloppement, qualit√© et post production.\n30 clients\ngrands comptes et pure players pr√©sents sur diff√©rents secteurs (m√©dias, e-commerce, industrie, bancaire, √©nergie et transport).\nCe que nous recherchons, ce que nos clients attendent de nos Data Analyst ?\nAssurer la collecte des donn√©es techniques en provenance du Datawarehouse\nTraiter et consolider les donn√©es techniques via\nDataiku\nD√©finir des indicateurs cl√©s pour orienter les prises de d√©cisions via\nPower BI\nPouvoir collaborer au sein d‚Äôune √©quipe structur√©e et mener les actions n√©cessaires avec les √©quipes techniques et les PO\nMaitrises des outils :\nExcel avanc√©, SQL, Base Oracle, JIRA\n,\nNiveau d'\nanglais\ncourant\nComment avancer ensemble ?\nNous faisons connaissance : Vous nous pr√©sentez votre parcours, votre projet, et vos valeurs et nous vous parlons de nous, de notre culture et de nos attentes\nNous √©valuons votre expertise : L‚Äô√©valuation qui concerne √† la fois les comp√©tences techniques/fonctionnelles, mais aussi les soft skills comme l‚Äôadaptabilit√©, le relationnel, le mindset...\nNous d√©finissons les enjeux de notre collaboration : Nous organisons une rencontre avec le manager de votre future team pour valider le process, int√©grer votre cercle et vous projeter sur votre prochain challenge\nShow more\nShow less",
        "details": {
            "JobDetail": [],
            "TypeContract": "",
            "Salary": "",
            "Level": "",
            "Experience": null
        },
        "title": "data analyst",
        "skills": {
            "DataBase": [
                "SQL"
            ],
            "DataVisualisation": [
                "Power BI"
            ],
            "Collaboration": [
                "JIRA"
            ],
            "EnSoftSkils": [
                "Collaboration"
            ]
        }
    },
    {
        "source": "LinkedIn",
        "company": "Inetum",
        "location": "Niort, Nouvelle-Aquitaine, France",
        "link": "https://fr.linkedin.com/jobs/view/data-analyst-h-f-at-inetum-3892405912?position=45&pageNum=0&refId=jBvsgtdGm8ta0dsilpa8wg%3D%3D&trackingId=CDvZEmy7aGs07kF5ZWkAJg%3D%3D&trk=public_jobs_jserp-result_search-card",
        "description": "D√©tail de l'offre\nInformations g√©n√©rales\nEntit√© de rattachement\nInetum est un leader europ√©en des services num√©riques. Pour les entreprises, les acteurs publics et la soci√©t√© dans son ensemble, les 28 000 consultants et sp√©cialistes du groupe visent chaque jour l'impact digital des solutions qui contribuent √† la performance, √† l'innovation et au bien commun.\nPr√©sent dans 19 pays au plus pr√®s des territoires, et avec ses grands partenaires √©diteurs de logiciels, Inetum r√©pond aux enjeux de la transformation digitale avec proximit√© et flexibilit√©.\nPort√© par son ambition de croissance et d'industrialisation, Inetum a g√©n√©r√© en 2023 un chiffre d'affaires de 2,5 milliards d'‚Ç¨.\nPour r√©pondre √† un march√© en croissance continue depuis plus de 30ans, Inetum a fait le choix d√©lib√©r√© de se recentrer sur 4 m√©tiers afin de gagner en puissance et proposer des solutions sur mesure, adapt√©es aux besoins sp√©cifiques de ses clients le conseil (Inetum Consulting), la gestion des infrastructures et applications √† fa√ßon (Inetum Technologies), l'impl√©mentation de progiciels (Inetum Solutions) et sa propre activit√© d'√©diteur de logiciels (Inetum Software). Inetum a conclu des partenariats strat√©giques avec 4 grands √©diteurs mondiaux - Salesforce, ServiceNow, Microsoft et SAP et poursuit une strat√©gie d'acquisitions d√©di√©e afin d'entrer dans le top 5 europ√©en sur ces technologies et proposer la meilleure expertise √† ses clients.\nTous nos postes sont ouverts aux personnes en situation de handicap.\nDescription du poste\nM√©tier\nData - Data IT\nIntitul√© du poste\nData Analyst H/F\nContrat\nCDI\nDescription De La Mission\nInetum Chauray, recherche un Consultant Data h/f, pour une mission en centre de service ou chez notre client, pour travailler sur des projets d'analyses de donn√©es Assurances.\nEn tant que Data Analyst, vous participerez √† l'√©volution du SI de\nnos clients et vos missions seront vari√©es.\nComp√©tences requises\nMa√Ætrise d'un ETL - Talend OU Informatica.\nUne exp√©rience en Analyse fonctionnelle et une comp√©tence en r√©solution d'incident.\nVous √™tes certifi√©(e) Google avec une connaissance d\nGCP, c'est IDEAL.Base de donn√©es Oracle, SQ\nOutils d√©cisionnels de restitution BI Qliksense, Qlikview\nBITQUERY / GCP\nCe que nous offrons\nUn environnement de travail inclusif et respectueux.\nDes opportunit√©s de formation et de d√©veloppement professionnel.\nUne fourchette de r√©mun√©ration allant de 38K et 42k selon votre niveau d'expertise\nProfil\nDe formation sup√©rieure, vous poss√©dez une exp√©rience de 3 ans minimum dans le domaine de la data.\nLocalisation du poste\nLocalisation du poste\nFrance, Ouest, 79 Deux-S√®vres\nVille\nNiort\nCrit√®res candidat\nNiveau d'√©tudes min. requis\nBac+2\nNiveau d'exp√©rience min. requis\nPlus de 2 ans\nShow more\nShow less",
        "details": {
            "JobDetail": [],
            "TypeContract": "CDI",
            "Salary": "",
            "Level": "",
            "Experience": "30 an(s)"
        },
        "title": "data analyst",
        "skills": {
            "CloudComputing": [
                "GCP"
            ]
        }
    },
    {
        "source": "LinkedIn",
        "company": "Teads",
        "location": "Montpellier, Occitanie, France",
        "link": "https://fr.linkedin.com/jobs/view/product-data-analyst-at-teads-3860869090?position=46&pageNum=0&refId=jBvsgtdGm8ta0dsilpa8wg%3D%3D&trackingId=kUSSzQz%2Fu%2Fh89Vq3sDsh1g%3D%3D&trk=public_jobs_jserp-result_search-card",
        "description": "At Teads, we do quality and responsible advertising, at scale. We invented outstream video advertising and now have a reach of 1,9 billion unique users per month powered by an end-to-end proprietary platform. We foster a sustainable advertising and media ecosystem by funding quality journalism and respectfully connecting brands to consumers.\nTo innovate, we have created a strong company culture that empowers passionate people, gives them the right tools and trusts them to do their jobs as best they can. Teads roadmap is full of ambitious and strategic projects related to the evolution of our offering for both publishers and advertisers.\nOur company offers a\nhybrid work model\n, allowing two days in-office and the flexibility to work from home for the rest of the week. Additionally, we offer relocation packages for those who are interested in moving to one of our engineering offices.\nüëâ Join a team of passionate people who build quality and responsible advertising, at scale!\nOur Business Intelligence Community\nWe want to empower everyone at Teads to take data-driven decisions. To achieve this, we federate a community of Data Analysts, distributed across our product areas. They infuse a data-driven culture within the entire company by driving proactive product analysis and building self-serve Business Intelligence tools. They also make sure everyone else within their product area is empowered to use these tools or run ad-hoc studies of any kind (business analysis, financial reporting, exec summary, growth analysis, etc.).\nWhat will you do?\nAs a\nData Analyst\nin the Product department, your goal is to help infuse a data-driven culture at Teads.\nTo develop BI within your product area, you will proactively:\nDrive the adoption of standard key product metrics, leveraging Teads BI stack (datamarts, data catalog, dashboards, etc.), by making them available in self-service to everyone in the company, with a standardized and accepted definition.\nAssess the success of each product release, by defining and monitoring relevant metrics (success, adoption, etc.), and reporting them regularly to key stakeholders.\nHelp shape the product roadmap, by working closely with Product Managers, and by owning yourself a part of the roadmap, in order to assess business opportunities and challenges.\nDrive ad-hoc studies and self-serve data exploration, by building self-serve BI tools, and providing documented business models developed in close collaboration with Software Engineers.\nSpread BI knowledge and best practices, by animating BI rituals (workshops, trainings, demos, etc.) and keeping a good relationship with data enthusiasts of your product area (business analysts, product managers, leadership, etc.)\nYou will also be part of a community to develop BI transversely. As a member of this community, you will:\nGovern a BI roadmap, around a unified vision and common objectives.\nWork on global BI initiatives, such as standardizing the UI/UX of dashboards, BI learning & knowledge, or consolidating a centralized Data Catalog.\nDefine and share BI best practices, to enforce consistency across the board.\nOwn the complete BI cycle, by developing your technical skills and your knowledge of the ad-tech industry.\nHelp onboarding Data Analysts, with adequate documentation and training.\nWhat will you bring to the team?\nYour Skills And Experience\nAt least 2 years of experience as a Data Analyst.\nBachelor or Master degree in BI, engineering, mathematics, or marketing.\nAdvanced knowledge of SQL and BI tools (warehouse, datamarts, dataviz, etc.).\nAbility to efficiently communicate and collaborate with cross-functional teams.\nData-driven mindset and proactive approach.\nPassionate, innovative, and fast learner.\nStrong problem solving and analytical skills.\nFluent in English.\nBonus Points\nExperience with BI platforms (Looker, Tableau, PowerBI, SiSense, Qlik, Domo, etc.).\nExperience with modern data warehousing solutions (BigQuery, SnowFlake, Redshift, etc.).\nExperience in the digital advertising industry.\nExperience in coding.\nProficient in French.\nWhy work at Teads?\nAt Teads, Product and Engineering work hand in hand and are aligned towards the same goal: to\nscale our business\nwhile continuing to create\nnew and exciting products\n.\nWe value team spirit, pragmatism, listening and we encourage initiatives.\nWe promote end-to-end development: ‚ÄúYou build it, you run it, you monitor it‚Äù.\nWe share knowledge and support with each other beyond any organizational boundary.\nWe fix issues during a blameless postmortem and learn from it so that it doesn‚Äôt happen twice.\nWe are working together to create great engineering, but we are also supportive to promote a great work-life balance.\nWe Care About You\nSecurity & Savings: Attractive package providing financial peace of mind, including competitive compensation, profit-sharing, daily meal vouchers (Swile), family health insurance (Alan), and a personalized relocation package (if needed).\nCareer Development: Continuous investment in our employees' skills: in-house and external training, tech conference opportunities, internal mobility (individual contributor or management career ladder).\nLife Balance: A well-balanced work-life for our employees is one of our top priorities: 35+ days off per year, hybrid work (2-3 days remote work per week, more is open to discussion), fully covered parental leave, and reserved daycare places.\nWellness: Prioritizing employee well-being through premium work equipment, enjoyable work environment (work-life balance, team building events, summits), remote work subsidy, promoting Diversity & Inclusion with internal & external initiatives (women speaking groups, dedicated school partnerships), dedicated charitable time and sustainability actions (Eco Tree, subsidy for eco-mobility).\nDiscover more about our culture and benefits on our Engineering website.\nAbout Teads\nTeads operates a leading, cloud-based, omnichannel platform that enables programmatic digital advertising across a global ecosystem of quality digital media.\nAs an end-to-end solution, Teads‚Äô modular platform allows partners to leverage buy-side, sell-side, creative, data and AI optimization technologies. For advertisers and their agencies, Teads offers a single access point to buy the inventory of many of the world‚Äôs best publishers and content providers.\nThrough exclusive global media partnerships, Teads enables advertisers and agencies to reach billions of unique monthly users in brand safe, responsible advertising environments, while improving the effectiveness and efficiency of digital ad transactions.\nTeads partners with the leading marketers, agencies and publishers through a team of 1,200+ people in 50 offices across more than 30 countries.\nWe're committed to creating a dynamic work environment that values diversity and inclusion, and represents employees across a variety of skill sets. We embrace contributions from all ages, sexes, races, ethnicities, religions, sexual orientations and gender identities.\nShow more\nShow less",
        "details": {
            "JobDetail": [
                "Remote",
                "Full"
            ],
            "TypeContract": "",
            "Salary": "2",
            "Level": "",
            "Experience": null
        },
        "title": "data analyst",
        "skills": {
            "DataBase": [
                "SQL"
            ],
            "DataVisualisation": [
                "Tableau"
            ],
            "DBMS": [
                "BigQuery",
                "Snowflake"
            ],
            "Collaboration": [
                "Teams"
            ],
            "Other": [
                "Cloud"
            ],
            "EnSoftSkils": [
                "Problem Solving",
                "Leadership",
                "Flexibility",
                "Collaboration"
            ]
        }
    },
    {
        "source": "LinkedIn",
        "company": "Wemanity Lille",
        "location": "Lille",
        "link": "https://fr.linkedin.com/jobs/view/data-analyst-h-f-at-wemanity-lille-3890979963?position=47&pageNum=0&refId=jBvsgtdGm8ta0dsilpa8wg%3D%3D&trackingId=PwWHag%2Fa6dUQUflJ8WCYCg%3D%3D&trk=public_jobs_jserp-result_search-card",
        "description": "Fond√©e en 2018, l‚Äôagence\nWemanity Lille\nse d√©veloppe d‚Äôann√©e en ann√©e gr√¢ce aux talents qui font de cette aventure une r√©ussite ! üåà‚Äã\n3 mots pour la d√©crire ? P√©tillante, √† taille humaine et audacieuse !\nPour suivre cette dynamique nous recherchons des talents ayant l'envie de progresser et de se lancer dans une belle aventure professionnelle et humaine √† nos c√¥t√©s. üå≥\nNous recherchons un(e)\nData Analyst (H/F)\navec un minimum d'exp√©rience de 3/4 ans, qui a envie d'apprendre et de d√©voiler tout son potentiel √† nos c√¥t√©s !\nQui sommes-nous\n?\nüí°\nüé¢ Cabinet de conseil sp√©cialis√© en\ntransformations digitales et agiles.\nüåç Pr√©sent √† l‚Äôinternational :\nParis, Lille, Belgique, Pays-bas, Maroc et Luxembourg.\nüë•\n600\ncoop√©rateurs passionn√©s.\nüçÉUn p√¥le RSE d√©bordant d‚Äôid√©es qui propose des projets √†\nimpact\nsociaux\net\nenvironnementaux.\nüíº‚Äã Pr√©sence du Wemanity Learning Center permettant\nformations & certifications.\nü¶∏ Ton profil :\nTu es Data Analyst (H/F)\n, tu as une exp√©rience de plus de 3/4 ans et tu souhaites rejoindre une √©quipe de passionn√©s ambitieux?\nTu aimes mettre en valeur les bonnes pratiques, apprendre et partager ? Cette offre est faite pour toi !\nüöÄ Tes missions* :\nMa√Ætrise des outils d'analyse de donn√©es.\nExp√©rience avec les outils de visualisation de donn√©es (Tableau, Power BI).\nConnaissance des techniques d'analyse statistique et des mod√®les de machine learning.\nUtilisation de m√©thodologies Agile/Scrum.\nCollaboration avec des √©quipes interfonctionnelles.\n*Liste non exhaustive\nüåàPourquoi Wemanity ?\nUn salaire attractif et de nombreux avantages (RTT, formations & certifications, primes vacances, CE, carte Swile ‚Ä¶) ‚òÄÔ∏è\nDes projets vari√©s √† forte valeur ajout√©e üéà\nUne vraie mont√©e en comp√©tences avec notre p√¥le formation (formations, certifications) ü™Ñ\nL‚Äôopportunit√© d‚Äôint√©grer une communaut√© d‚Äôagilistes soud√©e üöÄ\nLa possibilit√© d‚Äôint√©grer des squads agiles qui fonctionnent en mode startup pour intervenir sur des projets from scratch en interne ou chez nos clients ü§π‚Äç\nLa possibilit√© de travailler en r√©elle autonomie (t√©l√©travail) ‚òÄÔ∏è\nUne carri√®re √©volutive au sein d‚Äôune entreprise pleine de projets üí™\nUne entreprise avec un r√©el engagement RSE üå≥\nüìå\nNotre processus de recrutement en 3 √©tapes :\n1√®re √©tape, ton profil nous int√©resse ! Premier √©change avec l‚Äôun de nos recruteurs passionn√©s pour faire connaissance et en savoir plus sur tes souhaits d‚Äô√©volution.\n2√®me √©tape, l‚Äôentretien technique : c‚Äôest le moment d‚Äô√©changes sur la partie technique avec un membre de Wemanity (coop√©rateurs).\nEntretien final : Tu rencontreras un commercial afin de d√©terminer le projet et le client chez qui tu pourras √©voluer et t‚Äô√©panouir ! Suite √† ces 3 √©changes, je te souhaite d‚Äôobtenir ton billet d‚Äôentr√©e pour rejoindre l‚Äôaventure Wemanity !\nShow more\nShow less",
        "details": {
            "JobDetail": [],
            "TypeContract": "",
            "Salary": "3",
            "Level": "",
            "Experience": "4 an(s)"
        },
        "title": "data analyst",
        "skills": {
            "DataVisualisation": [
                "Power BI",
                "Tableau"
            ],
            "Other": [
                "Machine Learning"
            ],
            "EnSoftSkils": [
                "Collaboration"
            ]
        }
    },
    {
        "source": "LinkedIn",
        "company": "Listen too",
        "location": "Nantes, Pays de la Loire, France",
        "link": "https://fr.linkedin.com/jobs/view/data-analyst-at-listen-too-3890444112?position=48&pageNum=0&refId=jBvsgtdGm8ta0dsilpa8wg%3D%3D&trackingId=oJ2u4kAJZaJicFUonn5q2w%3D%3D&trk=public_jobs_jserp-result_search-card",
        "description": "üì¢ Imaginez un lieu o√π votre voix compte autant que vos comp√©tences‚Ä¶\nChez Listen too, nous sommes convaincus que l‚Äô√©coute est indissociable du progr√®s. Cultiv√©e au quotidien, elle devient un catalyseur de croissance et de r√©ussite, tant pour l‚Äôentreprise que pour ses collaborateur¬∑rice¬∑s.\nListen too est une agence conseil sp√©cialis√©e depuis 2013 dans la digitalisation de la Relation Client & Collaborateur. Gr√¢ce √† la justesse de l‚Äôaccompagnement offert √† nos clients comme √† nos consultant¬∑e¬∑s, nous nous sommes construits au fil des ans sur notre march√© une r√©putation de v√©ritables ¬´ horlogers du conseil ¬ª.\nNos domaines d‚Äôexpertise ?\nüéØ Le Product Management : pour porter la vision Produit et maximiser la cr√©ation de valeur.\nüé® Le Product Design : pour une conception Produit centr√©e utilisateur.\nüîß Le Product TechOps : pour d√©ployer les meilleures solutions digitales.\nüì¢ Le Product Marketing : pour maximiser le succ√®s d‚Äôun produit/service sur son march√©.\nüìä Le Product Data : pour mettre la donn√©e au c≈ìur de la strat√©gie de nos clients.\nü§ù La Gouvernance projet : pour optimiser le mode de management et le cadre organisationnel de nos clients.\n√ätre listenien¬∑ne, c‚Äôest √™tre au c≈ìur d‚Äôune entreprise qui valorise votre voix, votre parcours, et votre √©volution. Ici, nous appliquons les principes du design thinking √† votre carri√®re, co-construisant avec vous une trajectoire o√π vos passions, vos aspirations, et vos forces sont au premier plan.\nüí™ Vos futures missions\nVous √™tes passionn√©¬∑e par le domaine de la Data et vous souhaitez rejoindre une √©quipe client avec des projets challengeants ?\nConcr√®tement, vous aurez l'opportunit√© de :\nIdentification des besoins en donn√©es de l'entreprise et leurs objectifs d'analyse.\nCollecte des donn√©es √† partir de diff√©rentes sources telles que des bases de donn√©es, des fichiers Excel, des API, etc.\nNettoyage et pr√©paration des donn√©es.\nAnalyse des data gr√¢ce aux langages de programmation tels que Python, SQL ou Excel.\nCr√©ation de tableaux de bord, de graphiques et de visualisations.\n√âlaboration de rapports et des recommandations.\nCollaboration avec d'autres membres de l'√©quipe, tels que les Data Scientists et les Data Engineers, pour r√©soudre des probl√®mes complexes.\nüòé Votre vie de listenien¬∑ne\nCe qu‚Äôon vous propose ?\nü§ú √ätre membre d‚Äôune communaut√© : partager et enrichir vos comp√©tences au sein d‚Äôune √©quipe soud√©e.\nü§ù √ätre accompagn√©.e : dans votre progression professionnelle et votre quotidien par votre Consultant Manager, votre Business Manager et notre Responsable Exp√©rience collaborateur¬∑rice.\nüéì √ätre form√©¬∑e en continu : gr√¢ce √† un plan de d√©veloppement des comp√©tences co-construit et nourri par nos solutions d‚Äôe-learning (Linkedin Learning & Babbel), nos formations certifiantes et celles de la Listen too Academy, design√©es par nos consultant¬∑e¬∑s pour nos consultant¬∑e¬∑s.\nüöÄ √ätre intrapreneur.e : encourag√© √† innover, √©changer, entreprendre et ainsi contribuer √† l‚Äô√©panouissement du cabinet.\n‚òòÔ∏è √ätre engag√©.e : √† nos c√¥t√©s dans une d√©marche soci√©tale et environnementale responsable et durable.\nü§ó √ätre ¬´ bien ¬ª ! : parce que le bien-√™tre physique et mental de nos collaborateur.rice.s est au c≈ìur de notre r√©ussite.\nConcr√®tement ?\nüéâ De multiples occasions de passer de bons moments avec notamment notre fameux s√©mineige, des afterworks et des teambuildings.\nüèãÔ∏è‚Äç‚ôÇÔ∏è Du sport et de la sant√© avec des √©v√®nements sportifs, nos partenaires Gymlib, Zenride, Moka.care et le programme Vitality.\nüòé Du confort avec du t√©l√©travail ind√©mnis√©.\nü§ó Toujours plus liens avec un onboarding aux petits oignons, notre programme de parrainage, nos newsletters, nos podcasts et nos webinaires.\nü´∂ De l‚Äôengagement solidaire avec notre partenaire Vendredi, plateforme de m√©c√©nat de comp√©tence et b√©n√©volat\nüëç De nombreux avantages avec notre CSE, des tickets restaurant, une prime vacances, des primes de cooptation, de participation, de d√©veloppement‚Ä¶\nProfil recherch√©\nVous avez minimum 5 ans d‚Äôexp√©rience en tant que Data Analyst (ou sur des fonctions associ√©es de Data scientist / Data engineer)\nVous maitrisez les diff√©rents outils indispensable au m√©tier (SQL, Google Sheets, Python (Pandas/Numpy), Microsoft Power Query, outils de Data Visualisation)\nVous avez envie de progresser et d‚Äô√©voluer au sein d‚Äôune soci√©t√© √† taille humaine sur une expertise ou des responsabilit√©s manag√©riales\nVous r√™vez de vous investir au sein d‚Äôune communaut√© soud√©e et passionn√©e\nD√©roulement des entretiens\nüôã‚Äç‚ôÄÔ∏è Un premier entretien t√©l√©phonique ou en visio avec notre charg√©e de recrutement\nJulie\npour voir si √ßa colle entre nous !\nüíÅüèª‚Äç‚ôÄÔ∏è Un deuxi√®me en visio avec\nConstance\n, notre Directrice Grand Ouest, pour valider notre premi√®re impression.\nüôãüèª‚Äç‚ôÇÔ∏è Un dernier √©change sur mesure avec\nFlorent\n, Co-fondateur du cabinet, pour confirmer ce que nous savions d√©j√† ! üòâ\nVous l‚Äôaurez compris, cette phase de recrutement est avant tout l‚Äôoccasion de s‚Äô√©couter et d‚Äô√©changer. Chez Listen too, nous c√©l√©brons la diversit√© et l‚Äôinclusion, convaincus que chaque talent, quelle que soit son origine ou son parcours, est une richesse pour notre √©quipe et contribue √† notre r√©ussite commune.\nShow more\nShow less",
        "details": {
            "JobDetail": [],
            "TypeContract": "",
            "Salary": "",
            "Level": "",
            "Experience": "5 an(s)"
        },
        "title": "data analyst",
        "skills": {
            "ProgLanguage": [
                "Python"
            ],
            "DataBase": [
                "SQL"
            ],
            "DataAnalytics": [
                "NumPy",
                "Pandas"
            ],
            "EnSoftSkils": [
                "Collaboration"
            ]
        }
    },
    {
        "source": "LinkedIn",
        "company": "Lincoln France",
        "location": "√éle-de-France, France",
        "link": "https://fr.linkedin.com/jobs/view/data-analyst-h-f-at-lincoln-france-3892483893?position=49&pageNum=0&refId=jBvsgtdGm8ta0dsilpa8wg%3D%3D&trackingId=BJrA9xzzEoljjqK0jjEP8w%3D%3D&trk=public_jobs_jserp-result_search-card",
        "description": "CDI\nüìä\n3 ans minimum\nChez Lincoln\n, nous formons une communaut√© d'innovateurs passionn√©s qui red√©finissent l'analyse de donn√©es depuis\nplus de 30 ans\n. En tant que\nPure Player Data\n, notre expertise est reconnue dans les domaines\nde la Modern BI, du Big Data et de la Science des donn√©es\n.\nNotre mission ?\nTransformer les donn√©es en solutions concr√®tes pour nos clients grands comptes dans divers secteurs tels que la banque, le retail, les t√©l√©coms, l'industrie, la sant√©, etc.\nDescription du poste\nNous recherchons un\nData Analyst H/F\npour accompagner nos clients dans leurs projets strat√©giques.\nVos missions\nCollecter, nettoyer et traiter les donn√©es provenant de diff√©rentes sources.\nAnalyser les donn√©es pour identifier des tendances, des corr√©lations et des anomalies.\nConcevoir et d√©velopper des tableaux de bord et des rapports pour pr√©senter les r√©sultats de mani√®re claire et concise.\nCollaborer avec les √©quipes clients pour comprendre leurs besoins et recommander des solutions adapt√©es.\nPr√©requis :\nMa√Ætrise avanc√©e des langages de programmation (\nSQL, Python, R\n, etc.).\nConnaissance approfondie des bases de donn√©es relationnelles et non relationnelles.\nExp√©rience pratique avec des outils d'analyse de donn√©es (\nTableau, Power BI\n, etc.).\nFortes comp√©tences analytiques et capacit√© √† transformer les donn√©es brutes en insights exploitables.\nExp√©rience de travail en\nm√©thode Agile\npour la gestion de projet et le d√©veloppement de solutions.\nCapacit√©s √† travailler de mani√®re autonome et en √©quipe.\nExcellentes comp√©tences en communication et en pr√©sentation.\nLes plus du poste\nEnvironnement Collaboratif\n: projets innovants favorisant le partage des connaissances.\nAccompagnement individualis√© et de proximit√©\n: formations certifiantes, attribution d‚Äôun Career Manager pour vous orienter dans votre trajectoire professionnelle, opportunit√©s d‚Äô√©volution de carri√®re.\nFlexibilit√© du Travail\n: T√©l√©travail et horaires flexibles pour votre √©quilibre vie professionnelle-personnelle.\nR√©mun√©ration Comp√©titive\n: Salaire comp√©titif avec des avantages sociaux attrayants.\nMobilit√©\n: Possibilit√© de mobilit√© √† Lille, Lyon ou Aix-en-Provence offrant des exp√©riences diversifi√©es au sein de Lincoln.\nNotre processus de recrutement :\nUn entretien RH (1h) et entretien technique (1h)\nCette annonce n‚Äôest pas faite pour vous si :\nVous √™tes freelance et vous comptez le rester !\nToujours l√† ? Postulez et rejoignez nos\n400 experts en Data\nüòâ.\nShow more\nShow less",
        "details": {
            "JobDetail": [],
            "TypeContract": "CDI",
            "Salary": "400",
            "Level": "",
            "Experience": "3 an(s)"
        },
        "title": "data analyst",
        "skills": {
            "ProgLanguage": [
                "R",
                "Python"
            ],
            "DataBase": [
                "SQL"
            ],
            "DataAnalytics": [
                "R"
            ],
            "DataVisualisation": [
                "Power BI",
                "Tableau"
            ],
            "Other": [
                "Big Data"
            ],
            "EnSoftSkils": [
                "Communication"
            ]
        }
    },
    {
        "source": "LinkedIn",
        "company": "Groupe TF1",
        "location": "Boulogne-Billancourt, √éle-de-France, France",
        "link": "https://fr.linkedin.com/jobs/view/cdi-data-analyst-achats-f-h-at-groupe-tf1-3905896016?position=50&pageNum=0&refId=jBvsgtdGm8ta0dsilpa8wg%3D%3D&trackingId=kz1wOnU7VnpSCT96onAtYQ%3D%3D&trk=public_jobs_jserp-result_search-card",
        "description": "Faisons connaissance\nTF1, c‚Äôest bien s√ªr les grands programmes de divertissement, les s√©ries exclusives, les films et les talk-shows qui nourrissent la culture populaire et r√©unissent le plus grand nombre. C‚Äôest aussi l‚Äôinformation, la plus suivie d‚ÄôEurope, et les √©v√©nements sportifs plan√©taires qui font vibrer tous les Fran√ßais et les Fran√ßaises.\nTF1, c‚Äôest surtout une ambition : celle de d√©velopper la premi√®re plateforme de streaming gratuite en France, pour donner acc√®s √† tous et √† toutes, √† la demande, au meilleur du divertissement et de l‚Äôinfo. Envie d‚Äôinventer la t√©l√©vision de demain ? C‚Äôest ici que √ßa se passe !\nVotre r√¥le au sein de l‚Äô√©quipe\nEn interface avec l‚Äôensemble de la Direction Financi√®re de TF1, le\nData Analyst Achats\naura un r√¥le central dans l‚Äôaccompagnement de la Direction des Achats autour des diff√©rents sujets de reportings et de process.\nDe mani√®re plus globale, il lui sera demand√© de repenser la data comme √©tant au c≈ìur de la strat√©gie de performance de la Direction et d‚Äô√™tre force de proposition quant aux indicateurs, outils, et process mis en place.\nLes principales missions :\nVous serez conduit √† :\nPiloter √™tre force de proposition sur les besoins de reporting de la Direction des Achats\nCr√©er et automatiser les reportings sur Power BI, pour accompagner les acheteurs dans leurs besoins en analyses\nProposer des KPI de suivi\nAdministrer l‚Äôensemble des campagnes d‚Äô√©valuation RSE des fournisseurs\nSuivre l‚Äôavancement du processus RFA et optimiser le process\nFaire de la veille sur les outils d‚ÄôIA au service des directions Achats.\nLe Data Analyst Achats pourra ponctuellement √™tre amen√© √† travailler sur des projets d‚Äôachats en collaboration avec la Directrice Achats.\nVos atouts pour faire la diff√©rence\nVous √™tes issu d'une formation sup√©rieure sp√©cialis√©e dans les Achats et exp√©rience professionnelle souhait√©e dans le domaine de 3/4 ans minimum.\nVous connaissez la m√©thodologie de la conduite de projet et avez une excellente maitrise de Power Bi, ainsi qu'Excel.\nVous avez eu l'occasion de travailler sur de l'analyse financi√®re.\nQUALITES REQUISES :\nSens du relationnel d√©velopp√© ainsi que des capacit√©s reconnues d'√©coute\nAutonomie et force de proposition (capacit√© √† challenger l‚Äôexistant)\nDynamique, rigoureux, organis√© et r√©actif\nForce de conviction, capacit√© √† faire adh√©rer et influencer\nBonnes capacit√©s d'analyse, de r√©daction, de synth√®se et go√ªt pour les chiffres\nGo√ªt pour le travail en √©quipe\nApp√©tence pour la gestion de projet\nShow more\nShow less",
        "details": {
            "JobDetail": [],
            "TypeContract": "",
            "Salary": "",
            "Level": "",
            "Experience": "4 an(s)"
        },
        "title": "data analyst",
        "skills": {
            "DataVisualisation": [
                "Power BI"
            ],
            "EnSoftSkils": [
                "Collaboration"
            ]
        }
    },
    {
        "source": "LinkedIn",
        "company": "Lokad",
        "location": "Paris, √éle-de-France, France",
        "link": "https://fr.linkedin.com/jobs/view/business-data-analyst-h-f-at-lokad-3915779840?position=51&pageNum=0&refId=jBvsgtdGm8ta0dsilpa8wg%3D%3D&trackingId=JMfb1YRIu3BpJuAecVg1%2FQ%3D%3D&trk=public_jobs_jserp-result_search-card",
        "description": "We‚Äôre looking for the right candidate to join our Business Data Analyst team and become part of a fast-growing company that is on always on the look for people that will demonstrate they‚Äôre able to grow with the company. As the role is our entry level, this is a great entry point for a career path at Lokad, either as a future technical expert or as manager.\nWe help companies in different verticals (aerospace, automotive, ecommerce‚Ä¶) to forecast and make decisions about their inventory. The vast majority of our clients are based outside of France, mainly in North America and Europe.\nAs a Business Data Analyst (or Supply Chain Scientist in Lokad's terminology), your role is to make sure our clients get the most from Lokad's technology. The role is a mix between technology, data crunching and supply chain expertise. You will address complex supply chain issues and craft quantitative strategies. Your goal is not only to advise your clients on strategies to adopt, but to craft and execute these strategies on a daily basis while leveraging the data available as much as possible. Your goal is also to keep refining these strategies over time to keep them aligned with the needs of our clients.\nAt Lokad, you will benefit from the extensive training and coaching of our expert team. You will gain skills in supply chain, predictive analysis and overall quantitative optimization for business. You will learn how to achieve measurable business results grounded on scientific analysis of data.\nAbout one quarter of your time is spent interacting with clients in order to better understand their business (mainly over the phone or by mail, with occasional travels). Note that, in order to benefit from your colleagues expertise, you won't be required to work on the customers' premises.\nThe rest of your time is spent on data analysis, including manipulating and cleaning data, setting up forecasts, economic optimization, reporting and data vizualisation. In order to do this, you'll learn to use our Differentiable Programming tools and a DSL (Envision) developped by Lokad.\nWe are looking for candidates with the following skills and qualities:\nA strong engineering background.\nA keen interest in data and quantitative analysis in general.\nGood Excel skills or programming skills (e.g. Python, VBA, SQL, etc.).\nImpeccable command of English\n( French is optional).\nExcellent communication skills and telephone manners.\nA well-made head, rather than a well-filled head.\nWe are not looking for someone who is already an expert in supply chain or programming. We‚Äôre looking for a fast learner, with an ability to quickly grasp technology and concepts, since our technology is by no means a simple and plug-and-play product. Knowledge or understanding of supply chain would be a bonus, but the ability to quickly assess and grasp a new situation or get a clear picture of how an organization works and what are the pain points is what we are really after.\nCandidates must be self-motivated, confident and highly driven to achieve results with a ‚Äúhands on‚Äù attitude.\nThe role is predominantly office based, although some travel will be occasionally required to customers, partners or events. We are located in the very center of Paris, France (station Chevaleret).\nShow more\nShow less",
        "details": {
            "JobDetail": [],
            "TypeContract": "",
            "Salary": "",
            "Level": "",
            "Experience": null
        },
        "title": "data analyst",
        "skills": {
            "ProgLanguage": [
                "Python"
            ],
            "DataBase": [
                "SQL"
            ],
            "EnSoftSkils": [
                "Communication",
                "Organization"
            ]
        }
    },
    {
        "source": "LinkedIn",
        "company": "SOFTEAM",
        "location": "Paris, √éle-de-France, France",
        "link": "https://fr.linkedin.com/jobs/view/data-analyst-f-h-at-softeam-3587086987?position=52&pageNum=0&refId=jBvsgtdGm8ta0dsilpa8wg%3D%3D&trackingId=FFP%2B2Q5b4yUJyWRjMDwkKg%3D%3D&trk=public_jobs_jserp-result_search-card",
        "description": "Vous √©voluez dans le domaine de la Data et souhaitez int√©grer\nun leader de la transformation num√©rique sp√©cialis√© dans les secteurs de la Banque, du Luxe, de l'Assurance, de la Finance, de l'Energie et la possibilit√© d'√©voluer au sein du Groupe Docaposte !\nSofteam est labellis√© \"HappyIndex¬Æ AtWork \" 2022 pour la 5√®me ann√©e cons√©cutive !\nNos collaborateurs\ntravaillent en ¬´ mode projet ¬ª et accompagnent de bout en bout nos clients sur des probl√©matiques de Gouvernance.\nCE QUE NOUS RECHERCHONS\nData Analyst\npour intervenir sur nos projets et contribuer au d√©veloppement de notre Practice ¬´ Augmented analytics ¬ª\nCE QUE NOUS ATTENDONS DE VOUS\nVos missions :\nMa√Ætriser les outils statistiques et les informations n√©cessaires √† la mise en place d'une base de donn√©es,\nG√©rer parfaitement les diff√©rentes technologies sp√©cifiques au big data,\nExtraire les donn√©es du syst√®me source,\nExtraire et traduire des donn√©es business en donn√©es statistiques,\nMod√©liser et assurer les mises √† jour r√©guli√®res de la base de donn√©es,\nContr√¥ler la qualit√© des donn√©es,\nMettre en ≈ìuvre une data warehouse\nSynth√©tiser et vulgariser les informations pour les rendre accessibles aux utilisateurs.\nVOUS ETES\nIng√©nieur(e) de formation avec une sp√©cialit√© Business Analytics, Big Data, Applications des Masses de Donn√©es (IAMD), Syst√®mes D√©cisionnels..\nvous disposez d'une exp√©rience de\n3 ans minimum\nen tant que\nData Analyst/Data Miner\n..\nVous avez une expertise sur un ou plusieurs des outils d'alimentation et de traitement suivants :\nSQL, Alteryx, Dataiku, Python\n..\nVous avez une expertise sur un ou plusieurs des outils de data visualisation suivants :\nPower BI, Looker/GCP, Qlik, Tableau Software,\nBon(ne) communicant(e), curieux(se) et adaptable, v\nous √™tes dot√©(e) d'une grande capacit√© d‚Äôanalyse et de synth√®se et d'un bon esprit d'√©quipe,\nVotre ma√Ætrise de l'\nanglais\nvous permet d'√©voluer dans un contexte international.\nNOUS VOUS OFFRONS\nDes\nmissions engageantes\naupr√®s des grands acteurs du march√©.\nUn management de proximit√© avec\nGilles SALVADOR, Directeur du Centre d'Expertise Data\n, toujours bienveillant et √† √† l'√©coute et avec qui vous pourrez √©changer au quotidien sur les enjeux de votre mission et √©voquer vos futurs projets afin que nous puissions vous aider √† les r√©aliser.\nLa possibilit√© d‚Äô√©voluer et de monter en comp√©tences gr√¢ce √† des\nformations et √† des certifications aupr√®s de nos clients et de nos consultants\n, des\n12@13\n, notre Entit√©\nSofteam Institute, Organisme de formation interne\nde renomm√© qui d√©livre des formations aupr√®s de nos clients...\nQUI SOMMES-NOUS ?\nSOFTEAM DATA\nest une marque de\nDOCAPOSTE\nsp√©cialis√©e dans l'informatique d√©cisionnelle et les nouvelles technologies. Nous apportons notre expertise √† nos clients, principalement des Grands Comptes de la place financi√®re fran√ßaise, dans des projets de transformation digitale et cognitive.\n2000 Softeamien.nes\nsont d√©di√©.es √† la transformation m√©tier et digitale de nos clients et ont g√©n√©r√© 200 M‚Ç¨ de chiffre d‚Äôaffaires en 2020.\nSOFTEAM SPIRIT\nDes\ncommunaut√©s d'expertises sur les sujets de la Data\nDe\nsuper nouveaux locaux qui sont en plus accessibles facilement\nUne\n√©cole de formation int√©gr√©e\nDes\n√©v√®nements : des soir√©es avec les consultants, des 12@13...\nUne entreprise\nlabellis√©e \"Happy at Work\" pour la 5√®me ann√©e cons√©cutive\n.\nN‚Äôattendez plus, rejoignez SOFTEAM et venez nous rencontrer dans nos nouveaux locaux situ√©s √† la D√©fense #DevenezSofteamien !\nShow more\nShow less",
        "details": {
            "JobDetail": [],
            "TypeContract": "",
            "Salary": "",
            "Level": "",
            "Experience": "3 an(s)"
        },
        "title": "data analyst",
        "skills": {
            "ProgLanguage": [
                "Python"
            ],
            "DataBase": [
                "SQL"
            ],
            "DataVisualisation": [
                "Power BI",
                "Tableau"
            ],
            "CloudComputing": [
                "GCP"
            ],
            "Other": [
                "Statistiques",
                "Big Data"
            ]
        }
    },
    {
        "source": "LinkedIn",
        "company": "Talent Disruptors",
        "location": "Paris, √éle-de-France, France",
        "link": "https://fr.linkedin.com/jobs/view/data-analyst-at-talent-disruptors-3860725693?position=53&pageNum=0&refId=jBvsgtdGm8ta0dsilpa8wg%3D%3D&trackingId=0KBJ7Pd6KUtz1%2By4ulonkw%3D%3D&trk=public_jobs_jserp-result_search-card",
        "description": "We are on the lookout for a Data Analyst with a specialization in marketing analytics. In this critical role, you will harness the power of tools like Google Data Studio, BigQuery, and Power BI to derive actionable insights that drive our marketing decisions. Your expertise in analyzing complex datasets and turning them into understandable and strategic information will be essential in shaping our marketing strategies. This position is ideal for someone who thrives on data-driven challenges and has a passion for leveraging technology to inform business decisions.\nWhat You‚Äôll Be Doing\nData Analysis and Interpretation: Utilize tools like Google Data Studio, BigQuery, and Power BI to analyze marketing data and extract meaningful insights.\nDeveloping Reporting Dashboards: Create dynamic dashboards and reports that provide real-time insights into marketing performance.\nCollaborating with Marketing Teams: Work closely with marketing teams to understand their data needs and provide insights that inform strategy and decision-making.\nData Integration and Management: Integrate data from various sources to provide a comprehensive view of marketing performance.\nPerformance Tracking: Monitor key performance indicators (KPIs) to measure the effectiveness of marketing campaigns and strategies.\nPredictive Analysis: Use data to predict trends and market movements, aiding in proactive strategy development.\nTraining and Support: Provide training and support to team members in using data analysis tools and understanding reports.\nWho You Are\nProficient in Data Analysis Tools: You have strong experience with tools such as Google Data Studio, BigQuery, and Power BI.\nAnalytical and Insightful: You possess the ability to analyze complex datasets and turn them into actionable insights.\nCollaborative in Nature: You work well with marketing teams, understanding their needs and communicating data insights effectively.\nSkilled in Data Integration: You are adept at integrating and managing data from various sources.\nDetail-Oriented: You have a keen eye for detail and accuracy in data analysis and reporting.\nProactive and Predictive: You are capable of conducting predictive analyses to inform future marketing strategies.\nExcellent Communicator: You can clearly convey data insights and their implications to non-technical team members.\nWhat Success Looks Like\n30 Days\nEstablish a comprehensive, organized online database in BigQuery to store all client and marketing data and integrate lead data from CRMs, digital advertising data, customer opt-ins, and purchasing data to provide meaningful insights that inform marketing decisions.\nCreate and maintain data dashboards in Looker Studio for easy data visualization, analysis, and automated reporting.\n60 Days\nDevelop statistical models for data analysis, including linear regression modeling and predictive lead scoring, that effectively guide marketing actions.\n90 Days\nAutomated the generation of actionable insights and trends over time from data analysis to inform our marketing strategy.\nShow more\nShow less",
        "details": {
            "JobDetail": [],
            "TypeContract": "",
            "Salary": "",
            "Level": "",
            "Experience": null
        },
        "title": "data analyst",
        "skills": {
            "DataVisualisation": [
                "Power BI"
            ],
            "DBMS": [
                "BigQuery"
            ],
            "Collaboration": [
                "Teams"
            ]
        }
    },
    {
        "source": "LinkedIn",
        "company": "Mazars",
        "location": "Paris, √éle-de-France, France",
        "link": "https://fr.linkedin.com/jobs/view/data-analyst-junior-paris-2024-h-f-at-mazars-3838258695?position=54&pageNum=0&refId=jBvsgtdGm8ta0dsilpa8wg%3D%3D&trackingId=rJqp5EuCxwewlPfzUeQKvA%3D%3D&trk=public_jobs_jserp-result_search-card",
        "description": null,
        "details": {
            "JobDetail": [],
            "TypeContract": "",
            "Salary": "",
            "Level": "",
            "Experience": null
        },
        "title": "data analyst"
    },
    {
        "source": "LinkedIn",
        "company": "Stack Digital",
        "location": "Belfort, Bourgogne-Franche-Comt√©, France",
        "link": "https://fr.linkedin.com/jobs/view/data-analyst-at-stack-digital-3895910936?position=55&pageNum=0&refId=jBvsgtdGm8ta0dsilpa8wg%3D%3D&trackingId=WL17XxGJYCFg2llCVWkoOw%3D%3D&trk=public_jobs_jserp-result_search-card",
        "description": "Job Title:\nData Analyst\nType:\nContract\nLocation:\nBelfort, France\nImmediate Joining Required\nOverview:\nWe are currently seeking a dedicated Analyst with expertise in the Shopfloor/Manufacturing domain to join our team. This role requires a professional who is adept at learning existing application business functions and is capable of working independently on Oracle PL/SQL. The ideal candidate will be based out of our client's office in Belfort and must be willing to collaborate with geographically distributed teams across India and the Americas.\n‚Äã‚Äã‚Äã‚Äã‚Äã‚Äã‚Äã\nKey Responsibilities:\nLearn and understand the business functions of existing applications within the Shopfloor/Manufacturing domain.\nParticipate in the transition process, including documentation and internal transition to other teams.\nIndependently work on Oracle PL/SQL, including solving tickets related to PL/SQL issues.\nCoordinate with third-party application vendors to ensure tickets are resolved within the Service Level Agreement (SLA).\nParticipate in critical outage calls as required.\nPrepare high-quality status reports and present them to stakeholders if needed.\nRequirements:\nProven experience in the Shopfloor/Manufacturing domain.\nStrong capability in working independently on Oracle PL/SQL.\nExperience in coordinating with third-party vendors and managing ticket resolution within SLA.\nExcellent problem-solving skills and ability to participate in critical outage calls.\nNative level French language proficiency and strong business English language skills.\nAbility to work effectively with geographically distributed teams.\nExcellent documentation skills and experience in transition processes.\nWhy Join Us?\nThis is a fantastic opportunity to contribute to a critical role within a dynamic and challenging environment. You will have the chance to work with a diverse team and develop your skills in a global setting. If you are a motivated individual with a passion for the Shopfloor/Manufacturing domain and possess the required skills, we would love to hear from you.\nHow to Apply:\nPlease submit your application, including your CV and a cover letter, highlighting your relevant experience and why you are the best fit for this role. We are looking for immediate joiners, so please indicate your earliest availability.\nShow more\nShow less",
        "details": {
            "JobDetail": [],
            "TypeContract": "",
            "Salary": "",
            "Level": "",
            "Experience": null
        },
        "title": "data analyst",
        "skills": {
            "DataBase": [
                "SQL"
            ],
            "Collaboration": [
                "Teams"
            ]
        }
    },
    {
        "source": "LinkedIn",
        "company": "Allianz France",
        "location": "Paris, √éle-de-France, France",
        "link": "https://fr.linkedin.com/jobs/view/data-analyst-h-f-at-allianz-france-3909795270?position=56&pageNum=0&refId=jBvsgtdGm8ta0dsilpa8wg%3D%3D&trackingId=reZ3nyL33Q3I5e3rpxYHOg%3D%3D&trk=public_jobs_jserp-result_search-card",
        "description": "Allianz\nLeader europ√©en de l'assurance et des services financiers, Allianz propose une offre compl√®te couvrant tous les besoins en assurance, assistance et services financiers des particuliers, professionnels, entreprises et collectivit√©s. Allianz compte plus de 150.000 salari√©s dans le monde. Le groupe r√©alise 75% de ses activit√©s en Europe et il est pr√©sent dans plus de 70 pays. Avec 80 millions de clients dans le monde, Allianz fait partie des 5 plus grands groupes financiers mondiaux et est n¬∞ 1 de l'assurance et des services financiers en Europe.\nL‚ÄôUnit√© Investissements\nAIM Paris (Allianz Investment Management Paris), l‚Äôunit√© Investissement d‚ÄôAllianz France, a la charge de la gestion des investissements des diff√©rentes entit√©s d‚ÄôAllianz France tant sur les portefeuilles d‚Äôactifs g√©n√©raux qu‚Äôen unit√©s de compte (UC), sur toute la cha√Æne de valeur des investissements, qui couvre la gestion actif-passif, la strat√©gie d'investissement, ainsi que la planification des revenus des investissements, le suivi des risques, le reporting et les op√©rations.\nDescriptif / Missions du poste\nPour soutenir ces activit√©s l‚Äô√©quipe AIM Finance & Op√©rations, en charge des donn√©es d‚Äôinvestissements, des reportings et du suivi des risques des investissements, est √† la recherche d‚Äôun ¬´ Data Analyst ¬ª. Ce dernier, rattach√© hi√©rarchiquement √† AIM Finance & Op√©rations, couvrira l‚Äôensemble des besoins des diff√©rentes √©quipes d‚ÄôAIM (AIM Investment Strategy, AIM Asset-Liability Management, AIM Finance) et interviendra de fa√ßon op√©rationnelle sur des projets de transformation locaux et Groupe.\nVotre mission sera d‚Äôintervenir plus particuli√®rement sur :\nL‚Äôautomatisation de sourcing des donn√©es, des contr√¥les et des r√©conciliations entre diff√©rents syst√®mes d‚Äôinformations\nLe d√©veloppement de macros/codes afin d‚Äôautomatiser/optimiser les t√¢ches\nL‚Äôam√©lioration continue des bases de donn√©es Investissements\nLa fiabilisation et l‚Äôam√©lioration continue des bases de donn√©es\nLa mise en place de nouveaux reportings (Power BI)\nLe pilotage de projets en lien avec les initiatives groupes et locales\nVous travaillerez en lien √©troit avec les autres √©quipes d'AIM France ainsi que les √©quipes AIM centrales √† Munich. La maitrise de l‚Äôanglais est alors indispensable.\nProfil\nDipl√¥m√©(e) en informatique/gestion des donn√©es ou d‚Äôune √©cole d‚Äôing√©nieur (BAC +5), vous disposez d‚Äôune exp√©rience significative dans la manipulation de donn√©es (5-10 ans).\nMa√Ætrise de plusieurs langages de d√©veloppement du type Python, VBA, Access, SAS\nBonne ma√Ætrise des outils bureautiques Powerpoint, Excel et VBA, et id√©alement une premi√®re exp√©rience significative dans l‚Äôutilisation d‚Äôoutils de datavisualisation (Power BI)\nCapacit√© d‚Äôanalyse et de synth√®se, ouverture d‚Äôesprit, rigueur, organisation et autonomie,\nFran√ßais et anglais professionnel courants indispensables, √† l‚Äô√©crit comme √† l‚Äôoral.\nD√©but de la mission :\nMars 2024\nLocalisation :\nParis - La D√©fense ‚Äì TAO\nContacts : t ransmettre votre candidature compl√®te (CV + lettre de motivation)\nShow more\nShow less",
        "details": {
            "JobDetail": [],
            "TypeContract": "",
            "Salary": "",
            "Level": "",
            "Experience": "10 an(s)"
        },
        "title": "data analyst",
        "skills": {
            "ProgLanguage": [
                "Python"
            ],
            "DataVisualisation": [
                "Power BI"
            ]
        }
    },
    {
        "source": "LinkedIn",
        "company": "Groupe Q√©rys",
        "location": "Le Haillan, Nouvelle-Aquitaine, France",
        "link": "https://fr.linkedin.com/jobs/view/data-analyst-h-f-at-groupe-q%C3%A9rys-3912192127?position=57&pageNum=0&refId=jBvsgtdGm8ta0dsilpa8wg%3D%3D&trackingId=9TrfwOZb1wDej%2FDQEO3G%2BA%3D%3D&trk=public_jobs_jserp-result_search-card",
        "description": "Le Groupe QERYS, sp√©cialiste de l‚Äôam√©nagement de l‚Äôhabitat, a son si√®ge social QERYS SAS √† Le Haillan en Gironde.\nSes\nfonctions supports\naccompagnent les soci√©t√©s commerciales du Groupe (Bricodeal, Cazabox, Domotelec, Hydro Sud Direct, Midi Piles Services, Sider et Youpalo) dans leur fonctionnement, au travers de services mutualis√©s.\nLe Groupe QERYS propose une offre globale dans le domaine de l‚Äôam√©nagement et de l‚Äôhabitat\n(890 collaborateurs - 299M‚Ç¨ CA en 2022)\nNous rejoindre c‚Äôest :\nL‚Äôassurance d‚Äôun\nGroupe solide\nUn syst√®me de\nmanagement participatif\nUn engagement\nRSE\n(Responsabilit√© soci√©tale des entreprises)\nUne attention particuli√®re √† la\nQVT\n(Qualit√© de vie au Travail)\nUn\nparcours d‚Äôint√©gration\n, des\nformations\net un\naccompagnement\ntout au long de votre carri√®re\nPour en savoir +, consultez notre site institutionnel\nhttps://www.groupe-qerys.com/\nQuel est notre contexte ?\nEn tant que D√©veloppeur Dataviz H/F, vous d√©veloppez des outils d‚Äôaide √† la d√©cision utilisant la donn√©e consolid√©e du Groupe pour faciliter le quotidien des m√©tiers.\nQuel sera votre quotidien ?\nRattach√© au Responsable Informatique BI :\nFACILITER L‚ÄôACCES A L‚ÄôINFORMATION\n‚Ä¢ Cr√©er, d√©velopper et adapter les applications √† destination des diff√©rents services\n‚Ä¢ Homog√©n√©iser les indicateurs pour permettre une lecture analytique simple et optimale\nGARANTIR LA QUALITE DE LA DATA\n‚Ä¢ Contr√¥ler, corriger et fiabiliser toutes les donn√©es du Groupe\n‚Ä¢ Enrichir le d√©cisionnel des donn√©es des nouveaux entrants (Nouveaux outils / Nouvelles Das‚Ä¶)\nEn collaboration avec les Data Ing√©nieurs, trouver des solutions pour optimiser les performances syst√®me et assurer un confort de consultation\n‚Ä¢ Soutenir la d√©marche data de la DSI\nFORMER ET ACCOMPAGNER LES UTILISATEURS SUR L‚ÄôOUTIL DE DATAVIZ\n‚Ä¢ Former les collaborateurs √† l‚Äôoutil de Dataviz\n‚Ä¢ Accompagner le changement aupr√®s des m√©tiers\nMAINTENIR ET DEVELOPPER L‚ÄôOUTIL DE DATAVIZ\n‚Ä¢ Assurer la veille technologique de l‚Äôoutil\n‚Ä¢ Assurer la gestion administrative des acc√®s et des licences\n‚Ä¢ Comprendre les besoins d‚Äôanalyse et y apporter les solutions en ad√©quation avec l‚Äôurgence.\nEnvironnement Technique :\nETL : Talend (OpenStudio) + ETLTools\nRestitution : Qliksense\nBase de donn√©es : SQLServer/Oracle/MySQL/AS400\nM√©thodologie Traditionnel et Agile\nJira/Confluence\nCe que nous vous apportons pour assurer un bon √©quilibre vie pro/vie perso (sous conditions d‚Äô√©ligibilit√©) :\n32 jours\nde cong√©s pay√©s (25 + 7 jours ouvr√©s)\nLundi de pentec√¥te ch√¥m√© et pay√© (Journ√©e de solidarit√© offerte)\nDes\njours suppl√©mentaires\nofferts :\nanciennet√©, d√©m√©nagement, mariage/pacs‚Ä¶\nJusqu‚Äô√†\n2 jours de t√©l√©travail par semaine selon le poste\nPartenariat Klaxit (favoriser le covoiturage)\nUne\nmutuelle gratuite\nUn\nint√©ressement\nPr√©voyance\nR√©duction\nPartenaires -\nD√©jeuner\nUne prime de\ncooptation\npour tout collaborateur recrut√© suite √† votre recommandation\nConditions du contrat :\nCDI - Temps plein\nSalaire et avantages :\n√† partir 34K‚Ç¨brut/an + int√©ressement + mutuelle Groupe + partenariat d√©jeuner\nHoraires :\n38h45 du lundi au vendredi\nLocalisation du poste :\n29 rue Thomas Edison, 33612 Can√©jan\nInformations compl√©mentaires :\nd√©placements occasionnels sur nos diff√©rents sites √† l'√©chelle nationale\nt√©l√©travail possible jusqu‚Äô√† deux jours/semaine\nVotre candidature retiendra notre attention si :\nVous justifiez d‚Äôune premi√®re exp√©rience significative d‚Äôau moins 2 ans sur un poste similaire. Vous disposez d‚Äôun int√©r√™t pour la data. Vous ma√Ætrisez les outils de Dataviz, avez un forte capacit√© d‚Äôanalyse et de synth√®se. Vous √™tes √† l‚Äô√©coute, bon communicant et respectez la confidentialit√© des donn√©es.\nRejoignez l‚Äô√©quipe de Benjamin !\nShow more\nShow less",
        "details": {
            "JobDetail": [
                "Temps plein"
            ],
            "TypeContract": "CDI",
            "Salary": "34K",
            "Level": "",
            "Experience": "2 an(s)"
        },
        "title": "data analyst",
        "skills": {
            "DBMS": [
                "MySQL"
            ],
            "Collaboration": [
                "Confluence",
                "JIRA"
            ],
            "EnSoftSkils": [
                "Collaboration"
            ]
        }
    },
    {
        "source": "LinkedIn",
        "company": "Catalina Marketing France",
        "location": "Boulogne-Billancourt, √éle-de-France, France",
        "link": "https://fr.linkedin.com/jobs/view/data-analyst-python-f-h-cdi-boulogne-billancourt-at-catalina-marketing-france-3907391526?position=58&pageNum=0&refId=jBvsgtdGm8ta0dsilpa8wg%3D%3D&trackingId=zSgtYD1T%2BibeK21Tso9%2BRw%3D%3D&trk=public_jobs_jserp-result_search-card",
        "description": "Catalina est le seul acteur de la GMS √† pouvoir d√©ployer des plans marketing hyper-personnalis√©s avec autant de puissance ! Chez Catalina, on parle en milliards de donn√©es depuis des ann√©es.\nGr√¢ce √† de puissants outils en IA et Machine Learning, nous analysons les comportements d‚Äôachat des clients de la grande distribution pour mettre en place des strat√©gies de recrutement et de fid√©lisation via des plans marketing omnicanaux (couponing cibl√©, couponing digital via Coupon Network, programmes de fid√©lit√©‚Ä¶). Nous √©laborons des milliers de campagnes chaque ann√©e : Leclerc, Carrefour, Monoprix, Nestl√©, Procter & Gamble, Heineken, Coca-Cola, Bjorg‚Ä¶ Ce serait trop long de tous les citer.\nCatalina r√©unit 860 personnes dans le monde, et plus de 240 en France. Travaillant main dans la main, les Cataliniens ont un fort esprit collaboratif et la culture du r√©sultat. Ici on a la gagne !\nDepuis toujours, le succ√®s de Catalina, c'est le talent de nos √©quipes. Chez Catalina, on favorise la confiance, la pro-activit√© et le d√©veloppement en investissant sur la formation continue. Et parce que nous avons tant de p√©pites talentueuses, nous misons sur elles tous les jours en pr√¥nant l‚Äô√©volution. Les meilleurs atouts des grands groupes et des start-ups sont r√©unis en une seule entreprise : puissance et flexibilit√© !\nSoucieux de notre impact, la RSE est au c≈ìur de nos actions depuis toujours. En 2022, nous avons re√ßu la m√©daille d‚Äôargent EcoVadis pour saluer nos engagements sociaux et environnementaux.\nMissions et Responsabilit√©s :\nAu sein du p√¥le Analytics, et int√©gr√©(e) √† une √©quipe de 8 personnes d√©di√©e au support des industriels de la grande distribution √† travers l‚ÄôEurope (France, Italie et UK), tes missions consistent √† :\n-Echanger r√©guli√®rement avec les √©quipes business en France ou en Italie pour prendre connaissance des enjeux et probl√©matiques clients aupr√®s des √©quipes commerciales\n-Proposer, mettre en place des optimisations/Automatisations de nos process statistiques actuels\n-Extraire, analyser et interpr√©ter les r√©sultats des campagnes de marketing direct\n-Participer √† des sessions des brainstorming en interne avec l‚Äô√©quipe DataScience et les autres √©quipes Analytics sur la veille m√©thodologique de nos mesures\n-R√©aliser des projets d‚Äô√©tudes statistiques (segmentations, algo AI/ML, etc.)\nEt si c‚Äô√©tait toi ?\nDe formation sup√©rieure en statistiques, tu b√©n√©ficies d‚Äôun minimum 2 ans d‚Äôexp√©rience id√©alement dans le domaine des √©tudes marketing, et d‚Äôune exp√©rience de travail sur des bases de donn√©es √† forte volum√©trie.\nTu parles Anglais (courant)\nTu as une parfaite ma√Ætrise du SQL.\nTu as une parfaite connaissance de Python, l‚Äôutilisation dans un environnement Cloud est un plus (Azure, Snowflake, Databricks, etc.)\nLa connaissance des outils de Data visualisation comme Power BI est un plus\nTu connais les techniques statistiques appliqu√©es au Marketing Direct : √©chantillonnage, mise en place de t√©moins, analyse des r√©sultats, bonne connaissance des techniques de segmentations et de scoring.\nTu es d√©j√† familier avec les techniques de ML & AI.\nTu es capable de vulgariser votre discours aupr√®s de tes interlocuteurs (√©quipe commerciale, √©quipe marketing, clients‚Ä¶)\nDynamique et curieux(se), ta rigueur, ton aisance relationnelle, ton sens de l‚Äôinitiative ainsi que ton autonomie te permettra de t‚Äôint√©grer rapidement dans notre structure.\nTu es un amoureux de la data, un fin connaisseur de la grande conso, un passionn√© d'innovations digitales ? Tu cherches une entreprise qui te fait confiance et valorise tes talents, une bonne ambiance de travail, un √©quilibre vie priv√©e/ vie pro et une forte coh√©sion d'√©quipe avec un esprit entrepreneurial ?\nEn devenant toi aussi Catalinien, tu seras fier de participer √† cette aventure humaine au c√¥t√© d‚Äôexperts passionn√©s et bons vivants !\nProcess de recrutement :\n1er entretien avec Natacha, Talent Acquisition Manager et test technique de 30 minutes\n2√®me entretien avec Laurence Analytics Director et Murielle Manager Analytics.\nNos infos utiles :\nTon futur lieu de travail : Boulogne-Billancourt (Marcel Sembat)\nContrat: CDI\nT√©l√©travail : 3 jours de t√©l√©travail possible / semaine\nAvantages : 1 RTT / mois, CE, participation, prime vacances, carte restaurant swile, prise en charge de 2/3 de la mutuelle, journ√©e d‚Äôengagement associatif, mais aussi de nombreux team buildings, des ap√©ros, des paniers de fruits, du caf√© √† volont√©‚Ä¶\nCatalina, en tant que responsable de traitement, met en ≈ìuvre un traitement de donn√©es ayant pour finalit√©s principales la gestion et le suivi des candidatures. Tu disposes d‚Äôun droit d‚Äôacc√®s, d‚Äôeffacement, de rectification et de portabilit√© de vos donn√©es, ainsi que d‚Äôun droit d‚Äôopposition et de limitation au traitement de ces donn√©es. L‚Äôexercice des droits s‚Äôeffectue sur la plateforme OneTrust d√©di√©e (choix de la langue en haut √† droite) accessible depuis le site catalinamarketing.fr/politique-confidentialite ¬´ Vos droits, employ√© ¬ª ou par courrier adress√© √† : Catalina Marketing France, Privacy Recrutement, 58 Avenue Edouard Vaillant 92100 Boulogne Billancourt.\nSauf opposition de ta part, les candidatures re√ßues font l‚Äôobjet d‚Äôune conservation pendant 2 ans.\nShow more\nShow less",
        "details": {
            "JobDetail": [],
            "TypeContract": "CDI",
            "Salary": "",
            "Level": "",
            "Experience": "2 an(s)"
        },
        "title": "data analyst",
        "skills": {
            "ProgLanguage": [
                "Python"
            ],
            "DataBase": [
                "SQL"
            ],
            "BigData": [
                "Databricks"
            ],
            "DataVisualisation": [
                "Power BI"
            ],
            "CloudComputing": [
                "Azure"
            ],
            "DBMS": [
                "Snowflake"
            ],
            "Other": [
                "Statistiques",
                "Machine Learning",
                "Cloud",
                "ML"
            ],
            "EnSoftSkils": [
                "Initiative"
            ]
        }
    },
    {
        "source": "LinkedIn",
        "company": "Checkout.com",
        "location": "Paris, √éle-de-France, France",
        "link": "https://fr.linkedin.com/jobs/view/senior-data-analyst-at-checkout-com-3860155203?position=59&pageNum=0&refId=jBvsgtdGm8ta0dsilpa8wg%3D%3D&trackingId=F373RzA%2BYIbaLl1oE%2B3a9w%3D%3D&trk=public_jobs_jserp-result_search-card",
        "description": "Company Description\nWe're Checkout.com\nCheckout.com is one of the most exciting fintechs in the world. Our mission is to enable businesses and their communities to thrive in the digital economy. We‚Äôre the strategic payments partner for some of the best known fast-moving brands globally such as Wise, Hut Group, Sony Electronics, Homebase, Henkel, Binance, Klarna and many others. Purpose-built with performance and scalability in mind, our flexible cloud-based payments platform helps global enterprises launch new products and create experiences customers love. And it's not just what we build that makes us different. It's how.\nWe empower passionate problem-solvers to collaborate, innovate and do their best work. That‚Äôs why we‚Äôre number 9 on the Forbes Cloud 100 list and on Glassdoor‚Äôs list of Top 10 fintechs to work for. And we‚Äôre just getting started. We‚Äôre building diverse and inclusive teams around the world ‚Äî because that‚Äôs how we create even better experiences for our merchants and our partners. And we need your help. So, join us to build tomorrow, today.\nJob Description\nYou will be joining the Identity Verification team, responsible to maintain and continuously improve a world-class online identity verification technology, based on real-time video recognition.\nAs a Senior Product Data Scientist, you'll work as part of a cross-functional team alongside product managers, designers, and software and analytics engineers, using data and your expertise to influence and drive the strategy of our products. You will have end-to-end ownership for all the data aspects for your ‚Äòtribe‚Äô. You'll help define how we measure the success of our products, collaborate with engineers on how we collect data, build data pipelines to track the defined metrics, design and build reports/dashboards, and run analyses to find product improvement opportunities. You'll be a co-owner of a product, driving it to success in partnership with other cross-functional team members.\nYou'll also be part of the broader Analytics function, a team of Analytics Engineers, Data Scientists, and Data Product Managers.\nWe're a new but highly visible function within Checkout.com, so this is an exciting opportunity to drive a positive impact.\nHow you‚Äôll make an impact\nBe responsible for a product domain and its metrics. You'll be accountable for defining, measuring, and presenting metrics.\nContribute product roadmaps through data-based recommendations and continuously define high-impact areas for improvement.\nSupporting product discovery, research, and experimentation\nWorking closely with Data Engineers to make sure we collect and model the right data to produce relevant business insights\nDesign and implement reusable and scalable data models for our data warehouse using dbt and Snowflake\nDesign and implement Looker structures (explores, views, etc) which will enable users across the organization to self-serve analytics\nFoster data culture across products and technology by actively sharing insights and ideas and building positive relationships with colleagues\nBuild experiments and analysis frameworks to quantify the ROI of product development.\nDrive by example your team and broader data community to apply best practices in analytics from data collection to analysis.\nQualifications\nWhat we‚Äôre looking for\nProven delivery experience as a data scientist or data analyst\nStrong communicator, you're able to explain complex technical topics to non-technical team members\nExperience conducting experiments, building measurement frameworks, and validating the results with relevant quantitative methods\nStrong analytical mind, proven experience in converting ambiguous problems into structured and data-informed solutions\nCuriosity and attention to detail: you like to explore and understand the trends and investigate unusual patterns\nProficiency in SQL for data interrogation and data transformation (ideally experience with Looker, Snowflake and dbt)\nKnowledge of applied statistics (e.g., hypothesis testing, regression)\nAdditional Information\nHybrid Working Model:\nAll of our offices globally are\nonsite 3 times per week\n(Tuesday, Wednesday, and Thursday). We‚Äôve worked towards enabling teams to work collaboratively in the same space, while also being able to partner with colleagues globally. During your days at the office, we offer amazing snacks, breakfast, and lunch options in all of our locations.\nApply Without Meeting All Requirements Statement\nIf you don't meet all the requirements but think you might still be right for the role, please apply anyway. We're always keen to speak to people who connect with our mission and values.\nWe believe in equal opportunities\nWe work as one team. Wherever you come from. However you identify. And whichever payment method you use.\nOur clients come from all over the world ‚Äî and so do we. Hiring hard-working people and giving them a community to thrive in is critical to our success.\nWhen you join our team, we‚Äôll empower you to unlock your potential so you can do your best work. We‚Äôd love to hear how you think you could make a difference here with us.\nWe want to set you up for success and make our process as accessible as possible. So let us know in your application, or tell your recruiter directly, if you need anything to make your experience or working environment more comfortable. We‚Äôll be happy to support you.\nTake a peek inside life at Checkout.com via\nOur Culture video https://youtu.be/BEwnpHuadSw\nOur careers page https://www.checkout.com/careers\nOur LinkedIn Life pages bit.ly/3OaoN1U\nOur Instagram https://www.instagram.com/checkout_com/\nShow more\nShow less",
        "details": {
            "JobDetail": [
                "Senior"
            ],
            "TypeContract": "",
            "Salary": "",
            "Level": "",
            "Experience": null
        },
        "title": "data analyst",
        "skills": {
            "DataBase": [
                "SQL"
            ],
            "DBMS": [
                "Snowflake"
            ],
            "Collaboration": [
                "Teams"
            ],
            "Other": [
                "Cloud"
            ],
            "EnSoftSkils": [
                "Organization"
            ]
        }
    },
    {
        "source": "LinkedIn",
        "company": "Mazars",
        "location": "Courbevoie, √éle-de-France, France",
        "link": "https://fr.linkedin.com/jobs/view/data-analyst-junior-paris-2024-h-f-at-mazars-3904531206?position=60&pageNum=0&refId=jBvsgtdGm8ta0dsilpa8wg%3D%3D&trackingId=jM4CkYBw7lqjrrNiqERqpQ%3D%3D&trk=public_jobs_jserp-result_search-card",
        "description": "Description de l'entreprise\nMazars est un groupe international et int√©gr√© sp√©cialis√© dans l‚Äôaudit, la fiscalit√© et le conseil ainsi que dans les services comptables et juridiques*. Pr√©sents dans plus de 95 pays et territoires √† travers le monde, nous nous appuyons sur l‚Äôexpertise de plus de 47 000 professionnels ‚Äì plus de 30 000 au sein de notre partenariat int√©gr√© et plus de 17 000 via ¬´ Mazars North America Alliance ¬ª ‚Äì pour accompagner les clients de toutes tailles √† chaque √©tape de leur d√©veloppement.\nDans les pays o√π les lois en vigueur l‚Äôautorisent\nDescription du poste\nMazars souhaite chaleureusement son √©quipe ¬´ Audit Data Analytics ¬ª au sein de ses √©quipes Data Services.\nAu sein d'une √©quipe √† la fronti√®re entre l'audit et la tech, vous d√©veloppez ainsi une double comp√©tence technique et fonctionnelle ; en v√©ritable Business Analyst, vous concevez et d√©ployez des solutions Analytics pour les clients Mazars.\nVous intervenez sur des missions vari√©es dans plusieurs secteurs d'activit√© (industrie, services, secteur public, services financiers (banque et assurance)) et alimentez les comp√©tences suivantes :\nd√©veloppement de solutions innovantes sur des socles technologiques vari√©s de data analytics, de data visualisation et de programmation : Alteryx, Qlik, SQL, PowerBI, Python, etc. ;\nparticipation √† la conception de solutions fonctionnelles, de la phase de sp√©cifications √† la phase de mise √† disposition ;\ncontribution au d√©veloppement de nouvelles offres Mazars au service des enjeux Data de nos clients ;\nanalyser fonctionnellement les r√©sultats produits par les solutions Analytics ;\nparticipation √† la r√©daction de rapports d'analyse et pr√©sentation des outils et r√©sultats Analytics √† nos clients.\nEn compl√©ment, vous √™tes progressivement form√©s aux technologies de machine learning, √† l'intelligence artificielle et √† la science des donn√©es.\nQualifications\nDe formation Bac+5, vous √™tes jeune dipl√¥m√©(e) d'une √©cole d'ing√©nieurs, √©cole de commerce ou universit√© et avez un go√ªt prononc√© pour les sujets Analytics et les nouvelles technologies de fa√ßon g√©n√©rale, avec une app√©tence pour les probl√©matiques m√©tier et finance :\nVous avez une sp√©cialisation en Syst√®me d'Information et/ou en Data Science ;\nVous √™tes passionn√©(e) par les nouvelles technologies li√©es √† la Data ;\nVous avez id√©alement une exp√©rience de stage au cours de laquelle vous √™tes intervenu(e) sur le domaine de la ¬´ Data ¬ª ;\nVous aimez innover, vous √™tes curieux, dynamique et autonome et vous avez une certaine\naisance √† d√©velopper vos connaissances sur de nouveaux outils ;\nVous avez un excellent sens du travail en √©quipe ;\nVous poss√©dez les connaissances de base parmi les technologies suivantes : SQL, ACL, data studio, PowerBI, Qlik, Alteryx, Tableau softwareetc.)\nInt√©gration pr√©vue √† partir de septembre 2024\nInformations suppl√©mentaires\nLes + du m√©tier :\nDiversit√© des missions\nTravail d'√©quipe\nEquipe dynamique\n√âvolution de carri√®re rapide\nChez Mazars, nous pla√ßons le d√©veloppement personnel au c≈ìur de nos priorit√©s. Vous √™tes force de proposition ? Nous vous donnerons l'opportunit√© de porter et r√©ussir vos id√©es. Vous souhaitez participer √† la croissance du cabinet ? Nous vous int√©grerons dans le d√©veloppement ou le renforcement de nos offres. Enfin, les formations con√ßues par Mazars U Learn vous permettront de r√©inventer et de d√©velopper vos softs skills ainsi que de booster votre talent !\nShow more\nShow less",
        "details": {
            "JobDetail": [],
            "TypeContract": "",
            "Salary": "",
            "Level": "Bac+5",
            "Experience": null
        },
        "title": "data analyst",
        "skills": {
            "ProgLanguage": [
                "Python"
            ],
            "DataBase": [
                "SQL"
            ],
            "DataVisualisation": [
                "Tableau"
            ],
            "Other": [
                "Machine Learning"
            ]
        }
    },
    {
        "source": "LinkedIn",
        "company": "Aqualung Group",
        "location": "Valbonne, Provence-Alpes-C√¥te d'Azur, France",
        "link": "https://fr.linkedin.com/jobs/view/master-data-analyst-intern-at-aqualung-group-3908876542?position=1&pageNum=2&refId=qJ2foyHYFct0ss%2B3yaGaFw%3D%3D&trackingId=tyNyqO4YRk72iJZ1bycEkQ%3D%3D&trk=public_jobs_jserp-result_search-card",
        "description": "Aqualung Group pioneered the creation of modern diving equipment in 1943 when Captain Jacques-Yves Cousteau teamed with √âmile Gagnan to develop the first ‚Äúaqua-lung‚Äù that made underwater exploration possible. Today, Aqualung Group continues to be the leading global designer and manufacturer of dive and water sports gear. With a deep commitment to quality, research and testing, Aqualung Group has revolutionized the scuba diving experience by setting industry standards for scuba equipment in technology, comfort, safety and design.\nThe Aqualung Group consists of premium, innovative and inclusive brands such as Aqualung, Apeks, Aquasphere, Omer;\nSo, are you...\na sport enthusiast\ndo you love oceans and everything beyond\nare you an advocate of making a difference and protect our planet, a world where the ocean and all living creature are healthy and thriving\nor are you simply motivated and inspired to be a part of our passionate team that is always eager for a new challenge\nAqualung believes in the future, thus we invite you to strengthen and broaden your skills, pursue your passion by co-creating the future within an internship open positions.\nScope and Mission\nSupport the Aqualung Group in the daily management of Item master data.\nStart date:\nASAP\nDuration target:\nminimum 6 months\nLocation:\nSophia Antipolis\nKey duties and responsibilities\nSupport the master data team in the Item master data collection processes. (Creation/Update).\nHelp centralizing Master Data information in dedicated MDM tool (Product Hub/Oracle).\nHelp ensuring synchronization of the item master data in consuming systems.\nControl master data availability and quality through the publication of KPIs and implementation of data quality reports.\nEnsure master data collection environments are up to date.\nContribute in implementing data quality reports and corrective processes.\nContribute with the Master Data team in enhancing the existing item Core Model.\nYour qualifications\nLevel of studies:\nBAC + 4/5 minimum / master's degree in data science / data analysis.\nA first level of experience in Master data is preferred.\nSkills\nFluent English\nExcellent communication skills\nWorking effectively in a Team\nGood organizational skills, sense of prioritization\nYou are curious, dynamic, passionate about innovation\nStrong ability in manipulating data. (SQL)\nIf you are excited about this opportunity and joining the Aqua Lung team, please apply!\nWe look forward to receiving your application.\nShow more\nShow less",
        "details": {
            "JobDetail": [],
            "TypeContract": "",
            "Salary": "",
            "Level": "",
            "Experience": null
        },
        "title": "data analyst",
        "skills": {
            "DataBase": [
                "SQL"
            ],
            "EnSoftSkils": [
                "Communication"
            ]
        }
    },
    {
        "source": "LinkedIn",
        "company": "Astek",
        "location": "Paris, √éle-de-France, France",
        "link": "https://fr.linkedin.com/jobs/view/data-analyst-%E2%80%93-paris-france-h-f-at-astek-3839098102?position=2&pageNum=2&refId=qJ2foyHYFct0ss%2B3yaGaFw%3D%3D&trackingId=4d3rgYcDQJw5rvsYeoh9ww%3D%3D&trk=public_jobs_jserp-result_search-card",
        "description": "CDI\nParis - France\nPubli√©e il y a 2 mois\nLe Groupe Astek\nCe Que Nous Allons Accomplir Ensemble :\nNous rejoindre en tant que\nData Analyst (H/F),\nafin d‚Äôaccompagner un op√©rateur t√©l√©coms, Leader en Europe dans la gestion de ses solutions robustes, efficientes et s√©curis√©es √† destination d‚Äôenvironnements vari√©s.\nUn challenge portant sur des millions d‚Äôutilisateurs dans un environnement technique innovant, strat√©gique et o√π l‚Äôentraide et la bonne humeur priment !\nVotre Mission, Si Vous L‚Äôacceptez :\nEtude sur les donn√©es pour aide au cadrage du besoin M√©tier.\nForce de proposition sur des solutions analytiques adapt√©es aux besoins utilisateurs (avec nos √©quipes UX).\nAnalyse des besoins m√©tiers, accompagnement √† la formulation et √† la d√©finition de KPI m√©tiers.\nMod√©lisation des donn√©es.\nConception de Datasets Big Query.\nConception et R√©alisation de Datamarts et de Dashboards (PowerBI / Looker)\nAnalyse de la qualit√© de la donn√©e source, pour challenger les √©quipes Digitales / Data Engineers.\nVotre Future √âquipe :\nAu sein d‚Äôun environnement riche et complexe, vous √©voluerez avec des experts passionn√©s √† la fois techniques et fonctionnels (Ing√©nieurs sp√©cialis√©s, chef de projet, scrum master, product owner ‚Ä¶).\nL‚Äô√©quipe est en interaction avec des clients √† la fois internes et externes.\nVotre stack de jeu\nSQL ‚Äì Confirm√©\nMod√©lisation de Donn√©es ‚Äì Confirm√©\nOutils de Data Viz ‚Äì Confirm√©\nGCP ‚Äì Junior\nAnglais ‚Äì Professionnel\nLes Petits Plus Du Projet :\nVous interviendrez de A √† Z sur des projets riches fonctionnellement et ambitieux techniquement. Un challenge portant sur des millions d‚Äôutilisateurs dans un environnement technique innovant et strat√©gique.\nVous ?\nDipl√¥m√©(e) d‚Äôune √©cole d‚Äôing√©nieur ou √©quivalent de niveau Bac+5.\nVous justifiez id√©alement d‚Äôune exp√©rience d‚Äôau moins 3 ans d‚Äôexp√©riences sur un poste similaire ?\nVous faite preuve d‚Äôun bon relationnel et d‚Äôesprit d‚Äô√©quipe, √™tes dot√©(e) d‚Äôun excellent sens de l‚Äôorganisation et vous aimez les challenges et la r√©solution de probl√®me ?\nAlors ce poste est fait pour vous, n‚Äôh√©sitez plus et rejoignez l‚Äôaventure ASTEK !\nAstek\nCr√©√© en France en 1988, Astek est un acteur mondial de l‚Äôing√©nierie et du conseil en technologies. Fort de son expertise dans de nombreux secteurs industriels et tertiaires, Astek accompagne ses clients internationaux dans le d√©ploiement intelligent de leurs produits et de leurs services, et dans la mise en ≈ìuvre de leur transformation digitale.\nDepuis sa cr√©ation, le Groupe a fond√© son d√©veloppement sur une forte culture d‚Äôentrepreneuriat et d‚Äôinnovation, et sur l‚Äôaccompagnement et la mont√©e en comp√©tence de\nses 7800 collaborateurs\nqui s‚Äôengagent chaque jour √† promouvoir la compl√©mentarit√© entre les technologies num√©riques et l‚Äôing√©nierie des syst√®mes complexes.\nRejoignez un Groupe en fort d√©veloppement en France et √† travers le monde ayant r√©alis√© un chiffre d‚Äôaffaires de 600 M‚Ç¨ en 2023.\nTous les d√©tails sur le Groupe sur le site https://astekgroup.fr. Et vous pouvez aussi nous suivre sur notre blog : https://blog.groupeastek.com.\nRencontrons-nous\nNotre projet commun vous plait ?\nPostulez √† cette annonce, et soyez transparent !\nMaud, notre Talent Acquisition Referent, vous contactera pour un premier √©change.\nPuis vous rencontrerez Martin, votre futur manager, avec lequel vous √©changerez autour d‚ÄôAstek, de votre parcours, de vos attentes et de votre future mission .\nEnfin, vous rencontrerez J√©r√©my, notre Directeur d‚Äôagence avec lequel vous pourrez valider votre int√©r√™t et ad√©quation pour le poste et finaliser les √©l√©ments contractuels.\nNos Plus\nAstek est green et fait b√©n√©ficier ses salari√©s d‚Äôune indemnit√© kilom√©trique v√©lo\nUne politique CARE sur-mesure d√©ploy√©e par nos √©quipes RH pour nos collaborateurs (https://astekgroup.fr/engagements)\nNotre charte de la Diversit√©\nMots-cl√©s :\ning√©nieur ‚Äì ing√©nieure ‚Äì consultant ‚Äì consultante ‚Äì data ‚Äì analyst ‚Äì mod√©lisation ‚Äì donn√©es\nCaract√©ristiques de l'emploi\nCat√©gorie Ing√©nieur\nJob Industry T√©l√©com / M√©dia\nPostuler en ligne\nNom *\nPr√©nom *\nEmail *\nUn email valide est requis.\nT√©l√©phone *\nUn num√©ro de t√©l√©phone valide est requis.\nJoindre un CV *\nMots-cl√©s :\ning√©nieur ‚Äì ing√©nieure ‚Äì consultant ‚Äì consultante ‚Äì data ‚Äì analyst ‚Äì mod√©lisation ‚Äì donn√©es\nShow more\nShow less",
        "details": {
            "JobDetail": [
                "Confirm√©",
                "Junior"
            ],
            "TypeContract": "CDI",
            "Salary": "",
            "Level": "Bac+5",
            "Experience": "3 an(s)"
        },
        "title": "data analyst",
        "skills": {
            "DataBase": [
                "SQL"
            ],
            "CloudComputing": [
                "GCP"
            ],
            "DBMS": [
                "Big Query"
            ],
            "Automation": [
                "Chef"
            ]
        }
    },
    {
        "source": "LinkedIn",
        "company": "ACT-ON DATA",
        "location": "Courbevoie, √éle-de-France, France",
        "link": "https://fr.linkedin.com/jobs/view/data-analyst-at-act-on-data-3912559652?position=3&pageNum=2&refId=qJ2foyHYFct0ss%2B3yaGaFw%3D%3D&trackingId=cGKz7lqM1rjx%2BAvg%2FAK2LQ%3D%3D&trk=public_jobs_jserp-result_search-card",
        "description": "Description de l'entreprise\nSoci√©t√© de conseil & de services, ACT-ON GROUP est l‚Äôacteur leader du #HumanTech.\nIl mobilise ses expertises vari√©es et compl√©mentaires en STRATEGY, HR & HRIS, DATA et TECHNOLOGY, ainsi que la connaissance de son √©cosyst√®me partenaires pour accompagner ses clients dans la r√©ussite de tous leurs projets de transformation qu‚Äôils soient organisationnels, digitaux ou culturels‚Ä¶\nAvec plus de 20 ans d‚Äôexistence, notre groupe compte aujourd‚Äôhui plus de 1 500 missions chez nos clients (ETI, SBF 120, CAC 40, secteur public, associatif et ONG).\nIl r√©unit une communaut√© de plus de 600 collaborateurs, pour un chiffre d‚Äôaffaires de plus de 70 millions d‚Äôeuros.\nHistoriquement pr√©sent sur le march√© fran√ßais, en √éle-de-France, √† Lille, Lyon et Nantes, il se d√©veloppe d√©sormais aussi √† l‚Äôinternational.\nDescription du poste\nAu sein de notre entit√© innovante Act-On Data, vous √™tes int√©gr√©(e) √† une √©quipe d‚Äôexperts m√©tier en tant que Data analyst, potentiellement sur un projet international.\nVous participerez ainsi √† des missions √† forte valeur ajout√©e aupr√®s de nos clients en intervenant sur des probl√©matiques m√©tiers, tout en ayant la charge de probl√©matiques op√©rationnelles :\nMettre √† disposition des outils de pilotage d'activit√© √† destination des √©quipes m√©tier en d√©finissant les principaux KPI √† suivre,\nMener et pr√©senter les analyses demand√©es par les Directions m√©tiers ou la Direction n√©cessaire pour comprendre le business et transformer ces insights en plan d'action,\nVeiller √† am√©liorer et mesurer la qualit√© des donn√©es afin de mettre √† disposition des donn√©es fiables,\nParmi vos missions :\nCollaborer avec les m√©tiers sur la d√©finition des principaux KPI,\nR√©colter des besoins m√©tiers,\nR√©alisation des analyses statistiques simples ou complexes en fonction de la demande,\nConception des monitorings de suivi de la qualit√© des donn√©es des diff√©rents domaines,\nIntervenir techniquement sur la partie aval de la cha√Æne de valeur Data.\nQualifications\nVous justifiez d‚Äôune exp√©rience significative sur un poste similaire.\nVous avez un niveau d‚Äôanglais qui vous permet de piloter un projet √† l‚Äôinternational.\nVous ma√Ætrisez vos domaines de comp√©tences (outils/modules ou fonctionnels) et d√©montrez votre l√©gitimit√© par des exp√©riences significatives sur un poste similaire.\nNous recherchons une personne organis√©e, volontaire, dynamique avec une bonne capacit√© d‚Äôadaptation.\nLe go√ªt des chiffres et la maitrise d‚ÄôExcel sont indispensables.\nVous avez une bonne app√©tence pour la data et sur les outils de reporting (SAP BI, PowerBI, Tableau, ‚Ä¶) et connaissez les plates-formes Cloud (Azure, AWS, GCP)\nD‚Äôun temp√©rament passionn√©, vous aimez les challenges et vous souhaitez vous investir dans cette aventure ?\nAlors ce poste peut vous int√©resser !\nInformations suppl√©mentaires\nCe poste est ouvert au t√©l√©travail.\nCe poste est ouvert aux personnes recherchant un CDI uniquement.\nShow more\nShow less",
        "details": {
            "JobDetail": [],
            "TypeContract": "CDI",
            "Salary": "",
            "Level": "",
            "Experience": "20 an(s)"
        },
        "title": "data analyst",
        "skills": {
            "DataVisualisation": [
                "Tableau"
            ],
            "CloudComputing": [
                "GCP",
                "AWS",
                "Azure"
            ],
            "Other": [
                "Statistiques",
                "Cloud"
            ]
        }
    },
    {
        "source": "LinkedIn",
        "company": "Datatorii",
        "location": "Paris",
        "link": "https://fr.linkedin.com/jobs/view/data-analyst-at-datatorii-3916566708?position=4&pageNum=2&refId=qJ2foyHYFct0ss%2B3yaGaFw%3D%3D&trackingId=5JkTwJE8Av1TCDyTEdU5ZQ%3D%3D&trk=public_jobs_jserp-result_search-card",
        "description": "1. Pr√©sentation\nDatatorii est une soci√©t√© de conseil sp√©cialis√©e en data.\nPartenaires des directions m√©tiers et IT, nous accompagnons nos clients dans la mise en place de solutions techniques Microsoft ainsi que dans l‚Äôanalyse de leurs donn√©es.\nLa R&D r√©alis√©e en interne (10% du temps, au Dojo) autour de la formation continue et du suivi des √©volutions technologiques nous positionne comme un partenaire de choix, sp√©cialis√© Data Microsoft.\nOrganisme de formation, nous accompagnons √©galement nos clients de la prise en main jusqu‚Äô√† la ma√Ætrise des outils et des m√©thodes autour de la data.\nNich√©s dans le 1er arrondissement de Paris, nos locaux vous offrent tout le confort pour vous former, √©changer r√©guli√®rement avec vos pairs, participer aux ateliers internes et recevoir nos clients.\nDatatorii vous donne la possibilit√© de r√©aliser vos prochains d√©fis !\n2. Mission\nLa communication en entreprise, interne ou externe, est de plus en plus influenc√©e par la restitution de donn√©es, que ce soit via des dashboards, des rapports interactifs ou des pr√©sentations au Top Management.\nChez Datatorii, vous √©voluerez au sein d‚Äôun dispositif pluridisciplinaire (Ing√©nieur, Data Scientist, Architecte, Chef de projet, Formateur, etc.) qui propose des solutions compl√®tes data :\nLa r√©colte du besoin aupr√®s des utilisateurs, la d√©finition de personas, de maquettes et d‚Äôuser-flow\nLa cr√©ation de Style Guides Data et de th√®mes cl√©-en-main pour les projets de visualisation de donn√©es\nL‚Äôaccompagnement sur les r√©alisations (PowerBI, PowerApps, Microsoft Azure, Python, SQL, Mod√©lisation, ...)\nLa conception d‚Äôoffres innovantes et leur promotion (UX BI, BI Self-service, Low-code application, Data Management ...)\nLa r√©alisation de dashboards et rapports interactifs √† fort enjeux\nLa formation interne ou externe au sein de notre organisme de formation\nGr√¢ce √† nos parcours de carri√®re gamifi√©s, nos training kit et notre dispositif d‚Äôaccompagnement, Datatorii vous int√®gre dans un parcours certifiant et vous offre toutes les chances de r√©ussir avec des perspectives de carri√®re claires et stimulantes.\n3. Profil\nFormation initiale\nBAC +5 Ecole de commerce (Data Analyst, Data Business) ou (Ing√©nieur, math√©matiques, statistiques, informatique)\nConnaissances ou exp√©riences\nVous poss√©dez une premi√®re exp√©rience significative en DataViz\nVous y avez d√©velopp√© des comp√©tences de Business Analyst (DataViz, UX, Mod√©lisation, etc. )\nQualit√©s\nExcellent relationnel\nBon communicant\nProactif\nP√©dagogue\nCapacit√© d‚Äôanalyse et de synth√®se\nShow more\nShow less",
        "details": {
            "JobDetail": [],
            "TypeContract": "",
            "Salary": "",
            "Level": "",
            "Experience": null
        },
        "title": "data analyst",
        "skills": {
            "ProgLanguage": [
                "R",
                "Python"
            ],
            "DataBase": [
                "SQL"
            ],
            "DataAnalytics": [
                "R"
            ],
            "CloudComputing": [
                "Azure"
            ],
            "Automation": [
                "Chef"
            ],
            "Other": [
                "Statistiques"
            ],
            "EnSoftSkils": [
                "Communication"
            ]
        }
    },
    {
        "source": "LinkedIn",
        "company": "Iveco Group",
        "location": "Le Plessis-Belleville, Hauts-de-France, France",
        "link": "https://fr.linkedin.com/jobs/view/data-analysis-assistant-at-iveco-group-3907438232?position=5&pageNum=2&refId=qJ2foyHYFct0ss%2B3yaGaFw%3D%3D&trackingId=r5z1%2BEhnCgp1DgZHRsC0sA%3D%3D&trk=public_jobs_jserp-result_search-card",
        "description": "FPT Industrial est une marque d'Iveco Group (IVG: MI), d√©di√©e √† la conception, la production et la vente de groupes motopropulseurs et solutions destin√©s aux v√©hicules routiers et tout-terrain, ainsi qu'aux applications marines et de production d'√©nergie. Plus de 8000 salari√©s, r√©partis sur onze sites de production et onze centres de R&D travaillent pour FPT Industrial √† travers le monde. Implant√©s dans pr√®s de 100 pays, le r√©seau mondial de vente et le Customer Service de FTP Industrial soutiennent tous les clients de la Marque.\nNous recherchons : Un(e) assistant(e) Data Analysis en alternance\nMissions :\n‚Ä¢ Fournir les principaux rapports sur les ventes et les produits au niveau de Monde (Europe, Moyen Orient , Asie, Afrique, Am√©rique latine)\n‚Ä¢ Collecter et compiler les donn√©es sur la concurrence et les donn√©es potentielles au niveau des produits\n‚Ä¢ Analyser la performance des ventes par produit\n‚Ä¢ √âlaborer des rapports standards, un tableau de bord des produits et un suivi des indicateurs de performances cl√©s.\n‚Ä¢ Identifier les potentiels produits/ Running parks\nProfil :\nMaster marketing strat√©gique / Data analytics ‚Äì Business analytics\n-Anglais op√©rationnel, l'italien est un plus\n-Comp√©tences d'analyse requises\n-Ouvert d'esprit et curieux : vous ferez partie d'une √©quipe internationale situ√©e entre Le Plessis Belleville et Turin et vous travaillerez dans le d√©partement marketing Reman\n-Dur√©e : √† partir de septembre 2024 pendant 12 √† 24 mois\nOutils :\n-Microsoft Office\n-Excel : tr√®s bonne maitrise\n-Powerpoint : bonne maitrise\n-La maitrise d‚ÄôAccess est un plus\n-Data Warehouse (SAP BW)\n-Qlik sense\n-Power BI est un plus\nShow more\nShow less",
        "details": {
            "JobDetail": [],
            "TypeContract": "",
            "Salary": "",
            "Level": "",
            "Experience": null
        },
        "title": "Other",
        "skills": {
            "ProgLanguage": [
                "R"
            ],
            "DataAnalytics": [
                "R"
            ],
            "DataVisualisation": [
                "Power BI",
                "Tableau"
            ]
        }
    },
    {
        "source": "LinkedIn",
        "company": "Mobiskill | WEFY Group",
        "location": "Paris",
        "link": "https://fr.linkedin.com/jobs/view/data-analyst-at-mobiskill-wefy-group-3900004007?position=6&pageNum=2&refId=qJ2foyHYFct0ss%2B3yaGaFw%3D%3D&trackingId=fm6wVtn%2BXTV741jyiPspHg%3D%3D&trk=public_jobs_jserp-result_search-card",
        "description": "L'entreprise?\nInsurTech r√©cemment cr√©√©e, elle s'impose comme r√©f√©rence sur son march√© en proposant des produits d'assurance disruptif.\nIls travaillent avec des petites entreprises comme des grands noms de l'assurance et cumulent 1 millions de clients.\nTeam?\n40 personnes\nContexte?\nForte traction commerciale, ils ont besoin de structurer leur donn√©e afin de cr√©er de la valeur en interne et de la d√©livrer √† leurs clients aussi.\nLes missions?\n- Participer √† la construction de la roadmap data sur le moyen et le long terme (en accord avec les Business units)\n- Leader la mise en former d'une grosse volum√©trie de Data pour d√©gager de la valeur pour leurs partenaires existants\n- R√©aliser des √©tudes exploratoires pouss√©es pour apporter des recommandations strat√©giques √† l'entreprise\n- Co-construire les KPIs, OKR et dashboards, puis les automatiser\n- A/B testing sur de potentiels features\nTon profil?\n- Dipl√¥m√©(e) Bac+5, vous justifiez d'une exp√©rience de 3 ans minimum dans la Data analyse\n- Id√©alement, vous √™tes familier de l'univers de l'assurance\n- Dot√©(e) d'une forte capacit√© analytique, vous √™tes aussi capable d'exprimer clairement vos √† recommandations √† l'oral\n- Tu ma√Ætrises SQL et un outil de Data vizualisation (Tableau/PowerBI). Id√©alement tu es aussi familier de Python\n- Fiabilit√©, proactivit√© et autonomie sont des comp√©tences cl√©s √† ce poste\nLes++?\n- Soci√©t√© en pleine croissance (suite √† leur lev√©e de fonds, la roadmap 2024 est valid√©e et ils sont pr√™ts √† scaler )\n- Organisation d‚Äôentreprise alliant flexibilit√© et structure (m√©thode de l‚Äôautonomie align√©e)\n- Poste √©volutif avec de fortes perspectives d'√©volutions (dont management)\n- Package attractif\nShow more\nShow less",
        "details": {
            "JobDetail": [],
            "TypeContract": "",
            "Salary": "Package",
            "Level": "Bac+5",
            "Experience": "3 an(s)"
        },
        "title": "data analyst",
        "skills": {
            "ProgLanguage": [
                "Python"
            ],
            "DataBase": [
                "SQL"
            ],
            "DataVisualisation": [
                "Tableau"
            ]
        }
    },
    {
        "source": "LinkedIn",
        "company": "Astek",
        "location": "Lille, Hauts-de-France, France",
        "link": "https://fr.linkedin.com/jobs/view/data-analyst-%E2%80%93-lille-france-h-f-at-astek-3839093481?position=7&pageNum=2&refId=qJ2foyHYFct0ss%2B3yaGaFw%3D%3D&trackingId=CuGoTs8pGBQ2grHeXh6T9w%3D%3D&trk=public_jobs_jserp-result_search-card",
        "description": "CDI\nLille - France\nPubli√©e il y a 2 mois\nLe Groupe Astek\nCe Que Nous Allons Accomplir Ensemble :\nNous rejoindre en tant que\nData Analyst (H/F),\nafin d‚Äôaccompagner un op√©rateur t√©l√©coms, Leader en Europe dans la gestion de ses solutions robustes, efficientes et s√©curis√©es √† destination d‚Äôenvironnements vari√©s.\nUn challenge portant sur des millions d‚Äôutilisateurs dans un environnement technique innovant, strat√©gique et o√π l‚Äôentraide et la bonne humeur priment !\nVotre Mission, Si Vous L‚Äôacceptez :\nEtude sur les donn√©es pour aide au cadrage du besoin M√©tier.\nForce de proposition sur des solutions analytiques adapt√©es aux besoins utilisateurs (avec nos √©quipes UX).\nAnalyse des besoins m√©tiers, accompagnement √† la formulation et √† la d√©finition de KPI m√©tiers.\nMod√©lisation des donn√©es.\nConception de Datasets Big Query.\nConception et R√©alisation de Datamarts et de Dashboards (PowerBI / Looker)\nAnalyse de la qualit√© de la donn√©e source, pour challenger les √©quipes Digitales / Data Engineers.\nVotre Future √âquipe :\nAu sein d‚Äôun environnement riche et complexe, vous √©voluerez avec des experts passionn√©s √† la fois techniques et fonctionnels (Ing√©nieurs sp√©cialis√©s, chef de projet, scrum master, product owner ‚Ä¶).\nL‚Äô√©quipe est en interaction avec des clients √† la fois internes et externes.\nVotre stack de jeu\nSQL ‚Äì Confirm√©\nMod√©lisation de Donn√©es ‚Äì Confirm√©\nOutils de Data Viz ‚Äì Confirm√©\nGCP ‚Äì Junior\nAnglais ‚Äì Professionnel\nLes Petits Plus Du Projet :\nVous interviendrez de A √† Z sur des projets riches fonctionnellement et ambitieux techniquement. Un challenge portant sur des millions d‚Äôutilisateurs dans un environnement technique innovant et strat√©gique.\nVous ?\nDipl√¥m√©(e) d‚Äôune √©cole d‚Äôing√©nieur ou √©quivalent de niveau Bac+5.\nVous justifiez id√©alement d‚Äôune exp√©rience d‚Äôau moins 3 ans d‚Äôexp√©riences sur un poste similaire ?\nVous faite preuve d‚Äôun bon relationnel et d‚Äôesprit d‚Äô√©quipe, √™tes dot√©(e) d‚Äôun excellent sens de l‚Äôorganisation et vous aimez les challenges et la r√©solution de probl√®me ?\nAlors ce poste est fait pour vous, n‚Äôh√©sitez plus et rejoignez l‚Äôaventure ASTEK !\nAstek\nCr√©√© en France en 1988, Astek est un acteur mondial de l‚Äôing√©nierie et du conseil en technologies. Fort de son expertise dans de nombreux secteurs industriels et tertiaires, Astek accompagne ses clients internationaux dans le d√©ploiement intelligent de leurs produits et de leurs services, et dans la mise en ≈ìuvre de leur transformation digitale.\nDepuis sa cr√©ation, le Groupe a fond√© son d√©veloppement sur une forte culture d‚Äôentrepreneuriat et d‚Äôinnovation, et sur l‚Äôaccompagnement et la mont√©e en comp√©tence de\nses 7800 collaborateurs\nqui s‚Äôengagent chaque jour √† promouvoir la compl√©mentarit√© entre les technologies num√©riques et l‚Äôing√©nierie des syst√®mes complexes.\nRejoignez un Groupe en fort d√©veloppement en France et √† travers le monde ayant r√©alis√© un chiffre d‚Äôaffaires de 600 M‚Ç¨ en 2023.\nTous les d√©tails sur le Groupe sur le site https://astekgroup.fr. Et vous pouvez aussi nous suivre sur notre blog : https://blog.groupeastek.com.\nRencontrons-nous\nNotre projet commun vous plait ?\nPostulez √† cette annonce, et soyez transparent !\nMaud, notre Talent Acquisition Referent, vous contactera pour un premier √©change.\nPuis vous rencontrerez Martin, votre futur manager, avec lequel vous √©changerez autour d‚ÄôAstek, de votre parcours, de vos attentes et de votre future mission .\nEnfin, vous rencontrerez J√©r√©my, notre Directeur d‚Äôagence avec lequel vous pourrez valider votre int√©r√™t et ad√©quation pour le poste et finaliser les √©l√©ments contractuels.\nNos Plus\nAstek est green et fait b√©n√©ficier ses salari√©s d‚Äôune indemnit√© kilom√©trique v√©lo\nUne politique CARE sur-mesure d√©ploy√©e par nos √©quipes RH pour nos collaborateurs (https://astekgroup.fr/engagements)\nNotre charte de la Diversit√©\nMots-cl√©s :\ning√©nieur ‚Äì ing√©nieure ‚Äì consultant ‚Äì consultante ‚Äì data ‚Äì analyst ‚Äì mod√©lisation ‚Äì donn√©es\nCaract√©ristiques de l'emploi\nCat√©gorie Ing√©nieur\nJob Industry T√©l√©com / M√©dia\nPostuler en ligne\nNom *\nPr√©nom *\nEmail *\nUn email valide est requis.\nT√©l√©phone *\nUn num√©ro de t√©l√©phone valide est requis.\nJoindre un CV *\nMots-cl√©s :\ning√©nieur ‚Äì ing√©nieure ‚Äì consultant ‚Äì consultante ‚Äì data ‚Äì analyst ‚Äì mod√©lisation ‚Äì donn√©es\nShow more\nShow less",
        "details": {
            "JobDetail": [
                "Confirm√©",
                "Junior"
            ],
            "TypeContract": "CDI",
            "Salary": "",
            "Level": "Bac+5",
            "Experience": "3 an(s)"
        },
        "title": "data analyst",
        "skills": {
            "DataBase": [
                "SQL"
            ],
            "CloudComputing": [
                "GCP"
            ],
            "DBMS": [
                "Big Query"
            ],
            "Automation": [
                "Chef"
            ]
        }
    },
    {
        "source": "LinkedIn",
        "company": "moOngy Digital Lab",
        "location": "Lille",
        "link": "https://fr.linkedin.com/jobs/view/data-analyst-h-f-at-moongy-digital-lab-3890974953?position=8&pageNum=2&refId=qJ2foyHYFct0ss%2B3yaGaFw%3D%3D&trackingId=uf%2FTvTD%2FsimXjgz5Z6hkSQ%3D%3D&trk=public_jobs_jserp-result_search-card",
        "description": "Web Transition, c‚Äôest qui ?\nFond√©e en 2011,\nWeb transition\nest une entreprise de services num√©riques op√©rant sur le march√© de l‚ÄôIT/Digital !\nConstituant une part essentielle de\nMoOngy Digital Lab\n, Web Transition accompagne ses clients grands comptes sur leurs projets de Webmarketing, de Design, Gestion de projet et √©galement en Data !\nNotre objectif : nous implanter comme un acteur principal sur le march√© de la Transformation Digitale en accompagnant et valorisant les comp√©tences de nos collaborateurs !\nNous sommes convaincus que le succ√®s de MoOngy Digital Lab r√©side dans la somme des potentiels de nos √©quipes ü§ù\nTon √©quipe : La tribu Data\nParce qu‚Äôil est indispensable que tu puisses partager tes connaissances mais aussi en acqu√©rir de nouvelles, tu feras partie de l‚Äôune de nos tribus : celle de la Data. De plus, cela te permettra d‚Äô√™tre acteur dans le d√©veloppement et la strat√©gie de Web Transition. Ce syst√®me de co-r√©flexion et co-construction est un fondement essentiel chez nous !\nDans cette aventure, tu :\nOptimises\nles requ√™tes SQL ;\nConstruis\nles mod√®les de r√©gression ;\nAnalyses\nla rentabilit√© des actions marketing ;\nR√©alises\ndes √©tudes ad hoc sur les comportements clients ;\nProduits\net\nautomatises\nle reporting.\nRejoins-nous si tu as :\nUne exp√©rience de 3 ans minimum,\nUne maitrise technique de GCP / DBT / PowerBI,\nUne exp√©rience similaire dans une startup ou dans l‚Äôindustrie serait un plus !\nTon savoir-√™tre :\nOuvert d‚Äôesprit\nRespectueux des diff√©rences de chacun\nCurieux\nProactif\nPar o√π on commence ?\nUn premier entretien RH d‚Äô1h pour comprendre ton parcours et tes aspirations\nUn second entretien de 45 minutes avec l‚Äôun de nos Business Manager afin de valider tes comp√©tences et qu‚Äôil se projette sur l‚Äôune des missions qu‚Äôil pourrait te proposer\nUn troisi√®me entretien de quelques minutes avec notre responsable d‚Äôagence pour te proposer d‚Äôint√©grer notre superbe Team Web !\n3 entretiens en peu de temps, si ton profil correspond tu int√®greras tr√®s vite nos √©quipes üòâ\nPr√™t pour embarquer dans notre grande aventure humaine ? Deviens notre futur Weber en postulant √† cette offre ! Voici les avantages qui t‚Äôattendent en tant que Weber :\nü§© Des coll√®gues incroyables\nüèÜ Certifi√©e Great Place to Work\nüéÆ Des bureaux sympas (o√π vous serez toujours les bienvenus)\nüéâ Des teambuilding et √©vents tous les mois\nüíª Des tributs m√©tiers pour √©changer entre Weber du m√™me m√©tier\nDes missions chez le client qui sont accompagn√©es et coach√©es par ton manager\nUn accompagnement dans ton plan de carri√®re et tes envies de re skilling\nü§ì Un catalogue de formations certifiantes ouvert √† tous les salari√©s\nüçΩÔ∏è Une carte tickets restaurant MyEdenred\n‚ù§Ô∏è Une mutuelle GrasSavoye\nüöé Une prise en charge des frais de transport √† 100%\nShow more\nShow less",
        "details": {
            "JobDetail": [],
            "TypeContract": "",
            "Salary": "",
            "Level": "",
            "Experience": "3 an(s)"
        },
        "title": "data analyst",
        "skills": {
            "DataBase": [
                "SQL"
            ],
            "CloudComputing": [
                "GCP"
            ]
        }
    },
    {
        "source": "LinkedIn",
        "company": "Novencia Group",
        "location": "Lyon, Auvergne-Rh√¥ne-Alpes, France",
        "link": "https://fr.linkedin.com/jobs/view/data-analyst-lyon-f-h-at-novencia-group-3842056375?position=9&pageNum=2&refId=qJ2foyHYFct0ss%2B3yaGaFw%3D%3D&trackingId=bXmYtTRYeAYlcjy0MNiY3g%3D%3D&trk=public_jobs_jserp-result_search-card",
        "description": "Carnet de route\nNovencia accompagne ses clients dans leurs projets de transformation digitale, technologique et data.\nExpert en Data et Intelligence Artificielle nous aidons nos clients √† exploiter et valoriser leurs donn√©es sous toutes ses formes en les accompagnant sur des projets de Data Gouvernance, Data Architecture, Data Science, et Data Engineering.\nData Analyst\ndepuis au moins\n3 ans,\ntu es √† la recherche de nouveaux d√©fis. Boucle ta ceinture, la suite est pour toi !\nTon R√¥le\nRattach√©.e aux consultants de l‚Äôagence Lyonnaise, tu seras amen√©.e √† travailler chez les clients finaux et/ou au sein de notre Datalab‚Äô.\nEn tant que Data Analyst, tu auras les missions suivantes :\nT‚Äôimmerger dans le contexte client ;\nMener des ateliers avec les √©quipes m√©tier pour recueillir/ d√©finir leurs besoins ;\nChallenger leurs demandes ;\nParticiper au recueil et √† la mod√©lisation des donn√©es ;\nContr√¥ler la fiabilit√© et la qualit√© des donn√©es ;\nStructurer et exploiter les donn√©es gr√¢ce √† des outils de Data visualisation ;\nAnalyser ces donn√©es et partager les r√©sultats ;\nFaire des recommandations au client.\nTon profil\nDe formation Bac+5 dans le domaine de la Data, tu as au moins 3 ans d‚Äôexp√©rience sur un poste similaire.\nComp√©tences techniques recherch√©es :\nExp√©rience significative sur un outil de Data visualisation pour l‚Äô√©laboration de rapports/tableaux de bord (Power BI/Tableau/QlikSense etc.)\nLangage SQL (Python est un plus)\nMod√©lisation de donn√©es\nConnaissance des bases de donn√©es (e.g. Snowflake, Google BigQuery, SQL Server ou Oracle)\nUtilisation d‚Äôun ETL (e.g. Azure Data Factory, SSIS, Informatica, Talend, Matillion)\nUne exp√©rience dans le fonctionnement d‚Äôune √©quipe agile.\nTu es passionn√©.e par la Data et souhaites √©voluer au sein d‚Äôune communaut√© d‚ÄôExperts de la Data, tu veux t‚Äôinvestir dans des projets data innovants au sein de notre Datalab‚Äô, tu aimes le travail en √©quipe mais sais √™tre autonome sur tes sujets, tu es curieux.euse et force de proposition, tu es capable de chercher et trouver des solutions, tu as un bon niveau d‚Äôanglais.\nEnfin, tu souhaites int√©grer une agence √† taille humaine o√π la bienveillance n‚Äôest pas qu‚Äôun mot marketing.\nS‚Äôengager en faveur du handicap c‚Äôest garantir l‚Äô√©galit√© des chances d√®s le recrutement. √Ä comp√©tences √©gales, nos postes sont ouverts aux personnes en situation de handicap.\nShow more\nShow less",
        "details": {
            "JobDetail": [],
            "TypeContract": "",
            "Salary": "",
            "Level": "Bac+5",
            "Experience": "3 an(s)"
        },
        "title": "data analyst",
        "skills": {
            "ProgLanguage": [
                "Python"
            ],
            "DataBase": [
                "SQL"
            ],
            "DataVisualisation": [
                "Power BI",
                "Tableau"
            ],
            "CloudComputing": [
                "Azure"
            ],
            "DBMS": [
                "SQL Server",
                "BigQuery",
                "Snowflake"
            ]
        }
    },
    {
        "source": "LinkedIn",
        "company": "LEADER S.A.S",
        "location": "Le Havre",
        "link": "https://fr.linkedin.com/jobs/view/data-analyst-h-f-at-leader-s-a-s-3909699484?position=10&pageNum=2&refId=qJ2foyHYFct0ss%2B3yaGaFw%3D%3D&trackingId=%2B9je3t%2BltPtuFK7aqYiyvA%3D%3D&trk=public_jobs_jserp-result_search-card",
        "description": "Les soci√©t√©s de LEADER GROUP repr√©sent√©es par pr√®s de 170 salari√©s en France, Allemagne, Autriche, Chine et Etats-Unis, proposent √† leurs clients du monde entier un ensemble de produits ‚Äì √©mulseurs, √©quipements mousse, appareils de recherche de victimes, ventilateurs de d√©senfumage, lances, canons incendies, cam√©ras thermiques, etc. ‚Äì de haute technicit√© et fiables en toutes circonstances pour prot√©ger et secourir les personnes et les biens.\nL'innovation est l'un des moteurs essentiels du Groupe, qui s'appuie √©galement sur un syst√®me d'am√©lioration continue et de responsabilit√© soci√©tale et environnementale.\nRaison d‚Äô√™tre de Leader Group : ¬´ Aider √† sauver des vies ¬ª\nPour r√©pondre √† sa dynamique de croissance, LEADER renforce ses √©quipes et recherche son/sa futur(e)\nData Analyst H/F\nCDI ‚Äì temps plein ‚Äì Le Havre/Octeville sur mer (76)\nVos missions\nRattach√©(e) au site de LEADER et sous la responsabilit√© du Directeur Commercial et Marketing, le/la Data Analyst se charge de l'analyse des donn√©es commerciales et marketing pour aider √† la prise de d√©cisions √©clair√©es au sein des entit√©s du groupe. A ce titre vos principales missions seront de :\nR√©aliser des analyses approfondies des donn√©es de ventes internes, et du march√© des √©quipements concern√©s, incluant les tendances, la demande, et les innovations technologiques.\n√âtudier la concurrence pour comprendre leurs produits, tarifications, et strat√©gies marketing.\nCollaborer √©troitement avec les √©quipes de vente, et chefs produits pour partager les insights du march√© et orienter le d√©veloppement de produits et les strat√©gies commerciales.\n√âlaborer des rapports d√©taill√©s et des pr√©sentations pour la direction, avec des recommandations permettant de guider les d√©cisions strat√©giques, et soutenir l‚Äô√©quipe commerciale.\nEtudier chaque march√© et connaitre le potentiel en chiffres et en volumes dans chaque pays pour les activit√©s de Leader et diff√©rentes familles de produits.\nRechercher, r√©f√©rencer et suivre les appels d‚Äôoffres\nVotre profil\nTitulaire d‚Äôun bac + 4/5 en marketing ou statistiques, vous justifiez d‚Äôune premi√®re exp√©rience du secteur industriel, B2B et des produits techniques.\nOrient√©(e) am√©lioration continue, vous avez une ma√Ætrise parfaite des outils informatiques (Excel), CRM et ERP, de bonnes comp√©tences analytiques et la capacit√© √† communiquer des informations complexes de mani√®re claire et compr√©hensible.\nLa curiosit√©, le souci du d√©tail et une bonne aisance relationnelle sont des qualit√©s qui vous caract√©risent.\nVotre maitrise de l‚Äôanglais vous permet de communiquer ais√©ment √† l‚Äô√©crit comme √† l‚Äôoral.\nDes d√©placements nationaux et internationaux ponctuels sont √† pr√©voir.\nInformations compl√©mentaires\nVotre futur bureau est bas√© √† Octeville sur Mer, commune littorale limitrophe du Havre, au c≈ìur du si√®ge social du Groupe.\nA votre salaire de base (35K‚Ç¨ √† 38K‚Ç¨/an), s‚Äôajoutent une prime annuelle, RTT, mutuelle d‚Äôentreprise, t√©l√©travail partiel possible, conciergerie d‚Äôentreprise, et des titres restaurant.\nSi vous vous reconnaissez dans ce descriptif, et souhaitez relever de nouveaux d√©fis au sein d'une entreprise innovante, en pleine √©volution, rejoignez-nous en envoyant votre candidature\nNous avons h√¢te de vous rencontrer et de d√©couvrir comment vous pouvez contribuer √† notre √©quipe dynamique et √† nos projets passionnants.\nLes √©quipes de LEADER innovent chaque jour pour prot√©ger et secourir.\nPour en savoir plus, n‚Äôh√©sitez pas √† consulter notre site https://www.leader-group.company/fr\nShow more\nShow less",
        "details": {
            "JobDetail": [
                "Temps plein"
            ],
            "TypeContract": "CDI",
            "Salary": "35K",
            "Level": "",
            "Experience": null
        },
        "title": "data analyst",
        "skills": {
            "Other": [
                "Statistiques"
            ]
        }
    },
    {
        "source": "LinkedIn",
        "company": "Lokad",
        "location": "Paris, √éle-de-France, France",
        "link": "https://fr.linkedin.com/jobs/view/business-data-analyst-h-f-at-lokad-3915779840?position=1&pageNum=5&refId=9FNYDD6Vrcv1aW7UUJOd7A%3D%3D&trackingId=6nl2OtPTboNbxYMoxBOqGQ%3D%3D&trk=public_jobs_jserp-result_search-card",
        "description": "We‚Äôre looking for the right candidate to join our Business Data Analyst team and become part of a fast-growing company that is on always on the look for people that will demonstrate they‚Äôre able to grow with the company. As the role is our entry level, this is a great entry point for a career path at Lokad, either as a future technical expert or as manager.\nWe help companies in different verticals (aerospace, automotive, ecommerce‚Ä¶) to forecast and make decisions about their inventory. The vast majority of our clients are based outside of France, mainly in North America and Europe.\nAs a Business Data Analyst (or Supply Chain Scientist in Lokad's terminology), your role is to make sure our clients get the most from Lokad's technology. The role is a mix between technology, data crunching and supply chain expertise. You will address complex supply chain issues and craft quantitative strategies. Your goal is not only to advise your clients on strategies to adopt, but to craft and execute these strategies on a daily basis while leveraging the data available as much as possible. Your goal is also to keep refining these strategies over time to keep them aligned with the needs of our clients.\nAt Lokad, you will benefit from the extensive training and coaching of our expert team. You will gain skills in supply chain, predictive analysis and overall quantitative optimization for business. You will learn how to achieve measurable business results grounded on scientific analysis of data.\nAbout one quarter of your time is spent interacting with clients in order to better understand their business (mainly over the phone or by mail, with occasional travels). Note that, in order to benefit from your colleagues expertise, you won't be required to work on the customers' premises.\nThe rest of your time is spent on data analysis, including manipulating and cleaning data, setting up forecasts, economic optimization, reporting and data vizualisation. In order to do this, you'll learn to use our Differentiable Programming tools and a DSL (Envision) developped by Lokad.\nWe are looking for candidates with the following skills and qualities:\nA strong engineering background.\nA keen interest in data and quantitative analysis in general.\nGood Excel skills or programming skills (e.g. Python, VBA, SQL, etc.).\nImpeccable command of English\n( French is optional).\nExcellent communication skills and telephone manners.\nA well-made head, rather than a well-filled head.\nWe are not looking for someone who is already an expert in supply chain or programming. We‚Äôre looking for a fast learner, with an ability to quickly grasp technology and concepts, since our technology is by no means a simple and plug-and-play product. Knowledge or understanding of supply chain would be a bonus, but the ability to quickly assess and grasp a new situation or get a clear picture of how an organization works and what are the pain points is what we are really after.\nCandidates must be self-motivated, confident and highly driven to achieve results with a ‚Äúhands on‚Äù attitude.\nThe role is predominantly office based, although some travel will be occasionally required to customers, partners or events. We are located in the very center of Paris, France (station Chevaleret).\nShow more\nShow less",
        "details": {
            "JobDetail": [],
            "TypeContract": "",
            "Salary": "",
            "Level": "",
            "Experience": null
        },
        "title": "data analyst",
        "skills": {
            "ProgLanguage": [
                "Python"
            ],
            "DataBase": [
                "SQL"
            ],
            "EnSoftSkils": [
                "Communication",
                "Organization"
            ]
        }
    },
    {
        "source": "LinkedIn",
        "company": "SOFTEAM",
        "location": "Paris, √éle-de-France, France",
        "link": "https://fr.linkedin.com/jobs/view/data-analyst-f-h-at-softeam-3587086987?position=2&pageNum=5&refId=9FNYDD6Vrcv1aW7UUJOd7A%3D%3D&trackingId=BgrRUM%2Brzt0%2FFt%2BO31KNyA%3D%3D&trk=public_jobs_jserp-result_search-card",
        "description": "Vous √©voluez dans le domaine de la Data et souhaitez int√©grer\nun leader de la transformation num√©rique sp√©cialis√© dans les secteurs de la Banque, du Luxe, de l'Assurance, de la Finance, de l'Energie et la possibilit√© d'√©voluer au sein du Groupe Docaposte !\nSofteam est labellis√© \"HappyIndex¬Æ AtWork \" 2022 pour la 5√®me ann√©e cons√©cutive !\nNos collaborateurs\ntravaillent en ¬´ mode projet ¬ª et accompagnent de bout en bout nos clients sur des probl√©matiques de Gouvernance.\nCE QUE NOUS RECHERCHONS\nData Analyst\npour intervenir sur nos projets et contribuer au d√©veloppement de notre Practice ¬´ Augmented analytics ¬ª\nCE QUE NOUS ATTENDONS DE VOUS\nVos missions :\nMa√Ætriser les outils statistiques et les informations n√©cessaires √† la mise en place d'une base de donn√©es,\nG√©rer parfaitement les diff√©rentes technologies sp√©cifiques au big data,\nExtraire les donn√©es du syst√®me source,\nExtraire et traduire des donn√©es business en donn√©es statistiques,\nMod√©liser et assurer les mises √† jour r√©guli√®res de la base de donn√©es,\nContr√¥ler la qualit√© des donn√©es,\nMettre en ≈ìuvre une data warehouse\nSynth√©tiser et vulgariser les informations pour les rendre accessibles aux utilisateurs.\nVOUS ETES\nIng√©nieur(e) de formation avec une sp√©cialit√© Business Analytics, Big Data, Applications des Masses de Donn√©es (IAMD), Syst√®mes D√©cisionnels..\nvous disposez d'une exp√©rience de\n3 ans minimum\nen tant que\nData Analyst/Data Miner\n..\nVous avez une expertise sur un ou plusieurs des outils d'alimentation et de traitement suivants :\nSQL, Alteryx, Dataiku, Python\n..\nVous avez une expertise sur un ou plusieurs des outils de data visualisation suivants :\nPower BI, Looker/GCP, Qlik, Tableau Software,\nBon(ne) communicant(e), curieux(se) et adaptable, v\nous √™tes dot√©(e) d'une grande capacit√© d‚Äôanalyse et de synth√®se et d'un bon esprit d'√©quipe,\nVotre ma√Ætrise de l'\nanglais\nvous permet d'√©voluer dans un contexte international.\nNOUS VOUS OFFRONS\nDes\nmissions engageantes\naupr√®s des grands acteurs du march√©.\nUn management de proximit√© avec\nGilles SALVADOR, Directeur du Centre d'Expertise Data\n, toujours bienveillant et √† √† l'√©coute et avec qui vous pourrez √©changer au quotidien sur les enjeux de votre mission et √©voquer vos futurs projets afin que nous puissions vous aider √† les r√©aliser.\nLa possibilit√© d‚Äô√©voluer et de monter en comp√©tences gr√¢ce √† des\nformations et √† des certifications aupr√®s de nos clients et de nos consultants\n, des\n12@13\n, notre Entit√©\nSofteam Institute, Organisme de formation interne\nde renomm√© qui d√©livre des formations aupr√®s de nos clients...\nQUI SOMMES-NOUS ?\nSOFTEAM DATA\nest une marque de\nDOCAPOSTE\nsp√©cialis√©e dans l'informatique d√©cisionnelle et les nouvelles technologies. Nous apportons notre expertise √† nos clients, principalement des Grands Comptes de la place financi√®re fran√ßaise, dans des projets de transformation digitale et cognitive.\n2000 Softeamien.nes\nsont d√©di√©.es √† la transformation m√©tier et digitale de nos clients et ont g√©n√©r√© 200 M‚Ç¨ de chiffre d‚Äôaffaires en 2020.\nSOFTEAM SPIRIT\nDes\ncommunaut√©s d'expertises sur les sujets de la Data\nDe\nsuper nouveaux locaux qui sont en plus accessibles facilement\nUne\n√©cole de formation int√©gr√©e\nDes\n√©v√®nements : des soir√©es avec les consultants, des 12@13...\nUne entreprise\nlabellis√©e \"Happy at Work\" pour la 5√®me ann√©e cons√©cutive\n.\nN‚Äôattendez plus, rejoignez SOFTEAM et venez nous rencontrer dans nos nouveaux locaux situ√©s √† la D√©fense #DevenezSofteamien !\nShow more\nShow less",
        "details": {
            "JobDetail": [],
            "TypeContract": "",
            "Salary": "",
            "Level": "",
            "Experience": "3 an(s)"
        },
        "title": "data analyst",
        "skills": {
            "ProgLanguage": [
                "Python"
            ],
            "DataBase": [
                "SQL"
            ],
            "DataVisualisation": [
                "Power BI",
                "Tableau"
            ],
            "CloudComputing": [
                "GCP"
            ],
            "Other": [
                "Statistiques",
                "Big Data"
            ]
        }
    },
    {
        "source": "LinkedIn",
        "company": "Talent Disruptors",
        "location": "Paris, √éle-de-France, France",
        "link": "https://fr.linkedin.com/jobs/view/data-analyst-at-talent-disruptors-3860725693?position=3&pageNum=5&refId=9FNYDD6Vrcv1aW7UUJOd7A%3D%3D&trackingId=umm8lmNVvTOV8qQw60QtlQ%3D%3D&trk=public_jobs_jserp-result_search-card",
        "description": "We are on the lookout for a Data Analyst with a specialization in marketing analytics. In this critical role, you will harness the power of tools like Google Data Studio, BigQuery, and Power BI to derive actionable insights that drive our marketing decisions. Your expertise in analyzing complex datasets and turning them into understandable and strategic information will be essential in shaping our marketing strategies. This position is ideal for someone who thrives on data-driven challenges and has a passion for leveraging technology to inform business decisions.\nWhat You‚Äôll Be Doing\nData Analysis and Interpretation: Utilize tools like Google Data Studio, BigQuery, and Power BI to analyze marketing data and extract meaningful insights.\nDeveloping Reporting Dashboards: Create dynamic dashboards and reports that provide real-time insights into marketing performance.\nCollaborating with Marketing Teams: Work closely with marketing teams to understand their data needs and provide insights that inform strategy and decision-making.\nData Integration and Management: Integrate data from various sources to provide a comprehensive view of marketing performance.\nPerformance Tracking: Monitor key performance indicators (KPIs) to measure the effectiveness of marketing campaigns and strategies.\nPredictive Analysis: Use data to predict trends and market movements, aiding in proactive strategy development.\nTraining and Support: Provide training and support to team members in using data analysis tools and understanding reports.\nWho You Are\nProficient in Data Analysis Tools: You have strong experience with tools such as Google Data Studio, BigQuery, and Power BI.\nAnalytical and Insightful: You possess the ability to analyze complex datasets and turn them into actionable insights.\nCollaborative in Nature: You work well with marketing teams, understanding their needs and communicating data insights effectively.\nSkilled in Data Integration: You are adept at integrating and managing data from various sources.\nDetail-Oriented: You have a keen eye for detail and accuracy in data analysis and reporting.\nProactive and Predictive: You are capable of conducting predictive analyses to inform future marketing strategies.\nExcellent Communicator: You can clearly convey data insights and their implications to non-technical team members.\nWhat Success Looks Like\n30 Days\nEstablish a comprehensive, organized online database in BigQuery to store all client and marketing data and integrate lead data from CRMs, digital advertising data, customer opt-ins, and purchasing data to provide meaningful insights that inform marketing decisions.\nCreate and maintain data dashboards in Looker Studio for easy data visualization, analysis, and automated reporting.\n60 Days\nDevelop statistical models for data analysis, including linear regression modeling and predictive lead scoring, that effectively guide marketing actions.\n90 Days\nAutomated the generation of actionable insights and trends over time from data analysis to inform our marketing strategy.\nShow more\nShow less",
        "details": {
            "JobDetail": [],
            "TypeContract": "",
            "Salary": "",
            "Level": "",
            "Experience": null
        },
        "title": "data analyst",
        "skills": {
            "DataVisualisation": [
                "Power BI"
            ],
            "DBMS": [
                "BigQuery"
            ],
            "Collaboration": [
                "Teams"
            ]
        }
    },
    {
        "source": "LinkedIn",
        "company": "Mazars",
        "location": "Paris, √éle-de-France, France",
        "link": "https://fr.linkedin.com/jobs/view/data-analyst-junior-paris-2024-h-f-at-mazars-3838258695?position=4&pageNum=5&refId=9FNYDD6Vrcv1aW7UUJOd7A%3D%3D&trackingId=AhU6IATg%2BZgeBQXN2ELG1A%3D%3D&trk=public_jobs_jserp-result_search-card",
        "description": "Votre poste\nMazars est un groupe international et int√©gr√© sp√©cialis√© dans l‚Äôaudit, la fiscalit√© et le conseil ainsi que dans les services comptables et juridiques*. Pr√©sents dans plus de 95 pays et territoires √† travers le monde, nous nous appuyons sur l‚Äôexpertise de plus de 47 000 professionnels ‚Äì plus de 30 000 au sein de notre partenariat int√©gr√© et plus de 17 000 via ¬´ Mazars North America Alliance ¬ª ‚Äì pour accompagner les clients de toutes tailles √† chaque √©tape de leur d√©veloppement.\n*Dans les pays o√π les lois en vigueur l‚Äôautorisent\nVos principales missions\nMazars souhaite chaleureusement son √©quipe ¬´ Audit Data Analytics ¬ª au sein de ses √©quipes Data Services.\nAu sein d'une √©quipe √† la fronti√®re entre l'audit et la tech, vous d√©veloppez ainsi une double comp√©tence technique et fonctionnelle ; en v√©ritable Business Analyst, vous concevez et d√©ployez des solutions Analytics pour les clients Mazars.\nVous Intervenez Sur Des Missions Vari√©es Dans Plusieurs Secteurs D'activit√© (industrie, Services, Secteur Public, Services Financiers (banque Et Assurance)) Et Alimentez Les Comp√©tences Suivantes\nd√©veloppement de solutions innovantes sur des socles technologiques vari√©s de data analytics, de data visualisation et de programmation : Alteryx, Qlik, SQL, PowerBI, Python, etc. ;\nparticipation √† la conception de solutions fonctionnelles, de la phase de sp√©cifications √† la phase de mise √† disposition ;\ncontribution au d√©veloppement de nouvelles offres Mazars au service des enjeux Data de nos clients ;\nanalyser fonctionnellement les r√©sultats produits par les solutions Analytics ;\nparticipation √† la r√©daction de rapports d'analyse et pr√©sentation des outils et r√©sultats Analytics √† nos clients.\nEn compl√©ment, vous √™tes progressivement form√©s aux technologies de machine learning, √† l'intelligence artificielle et √† la science des donn√©es.\nVotre profil\nDe Formation Bac+5, Vous √ätes Jeune Dipl√¥m√©(e) D'une √âcole D'ing√©nieurs, √âcole De Commerce Ou Universit√© Et Avez Un Go√ªt Prononc√© Pour Les Sujets Analytics Et Les Nouvelles Technologies De Fa√ßon G√©n√©rale, Avec Une App√©tence Pour Les Probl√©matiques M√©tier Et Finance\nVous avez une sp√©cialisation en Syst√®me d'Information et/ou en Data Science ;\nVous √™tes passionn√©(e) par les nouvelles technologies li√©es √† la Data ;\nVous avez id√©alement une exp√©rience de stage au cours de laquelle vous √™tes intervenu(e) sur le domaine de la ¬´ Data ¬ª ;\nVous aimez innover, vous √™tes curieux, dynamique et autonome et vous avez une certaine\naisance √† d√©velopper vos connaissances sur de nouveaux outils ;\nVous avez un excellent sens du travail en √©quipe ;\nVous poss√©dez les connaissances de base parmi les technologies suivantes : SQL, ACL, data studio, PowerBI, Qlik, Alteryx, Tableau softwareetc.)\nInt√©gration pr√©vue √† partir de septembre 2024\nShow more\nShow less",
        "details": {
            "JobDetail": [],
            "TypeContract": "",
            "Salary": "",
            "Level": "Bac+5",
            "Experience": null
        },
        "title": "data analyst",
        "skills": {
            "ProgLanguage": [
                "Python"
            ],
            "DataBase": [
                "SQL"
            ],
            "DataVisualisation": [
                "Tableau"
            ],
            "Other": [
                "Machine Learning"
            ]
        }
    },
    {
        "source": "LinkedIn",
        "company": "Stack Digital",
        "location": "Belfort, Bourgogne-Franche-Comt√©, France",
        "link": "https://fr.linkedin.com/jobs/view/data-analyst-at-stack-digital-3895910936?position=5&pageNum=5&refId=9FNYDD6Vrcv1aW7UUJOd7A%3D%3D&trackingId=vUmOApUSAzjlXJCoQmU7ww%3D%3D&trk=public_jobs_jserp-result_search-card",
        "description": "Job Title:\nData Analyst\nType:\nContract\nLocation:\nBelfort, France\nImmediate Joining Required\nOverview:\nWe are currently seeking a dedicated Analyst with expertise in the Shopfloor/Manufacturing domain to join our team. This role requires a professional who is adept at learning existing application business functions and is capable of working independently on Oracle PL/SQL. The ideal candidate will be based out of our client's office in Belfort and must be willing to collaborate with geographically distributed teams across India and the Americas.\n‚Äã‚Äã‚Äã‚Äã‚Äã‚Äã‚Äã\nKey Responsibilities:\nLearn and understand the business functions of existing applications within the Shopfloor/Manufacturing domain.\nParticipate in the transition process, including documentation and internal transition to other teams.\nIndependently work on Oracle PL/SQL, including solving tickets related to PL/SQL issues.\nCoordinate with third-party application vendors to ensure tickets are resolved within the Service Level Agreement (SLA).\nParticipate in critical outage calls as required.\nPrepare high-quality status reports and present them to stakeholders if needed.\nRequirements:\nProven experience in the Shopfloor/Manufacturing domain.\nStrong capability in working independently on Oracle PL/SQL.\nExperience in coordinating with third-party vendors and managing ticket resolution within SLA.\nExcellent problem-solving skills and ability to participate in critical outage calls.\nNative level French language proficiency and strong business English language skills.\nAbility to work effectively with geographically distributed teams.\nExcellent documentation skills and experience in transition processes.\nWhy Join Us?\nThis is a fantastic opportunity to contribute to a critical role within a dynamic and challenging environment. You will have the chance to work with a diverse team and develop your skills in a global setting. If you are a motivated individual with a passion for the Shopfloor/Manufacturing domain and possess the required skills, we would love to hear from you.\nHow to Apply:\nPlease submit your application, including your CV and a cover letter, highlighting your relevant experience and why you are the best fit for this role. We are looking for immediate joiners, so please indicate your earliest availability.\nShow more\nShow less",
        "details": {
            "JobDetail": [],
            "TypeContract": "",
            "Salary": "",
            "Level": "",
            "Experience": null
        },
        "title": "data analyst",
        "skills": {
            "DataBase": [
                "SQL"
            ],
            "Collaboration": [
                "Teams"
            ]
        }
    },
    {
        "source": "LinkedIn",
        "company": "Allianz France",
        "location": "Paris, √éle-de-France, France",
        "link": "https://fr.linkedin.com/jobs/view/data-analyst-h-f-at-allianz-france-3909795270?position=6&pageNum=5&refId=9FNYDD6Vrcv1aW7UUJOd7A%3D%3D&trackingId=ojlNCfNepK96X%2BENBfD4Cg%3D%3D&trk=public_jobs_jserp-result_search-card",
        "description": "Allianz\nLeader europ√©en de l'assurance et des services financiers, Allianz propose une offre compl√®te couvrant tous les besoins en assurance, assistance et services financiers des particuliers, professionnels, entreprises et collectivit√©s. Allianz compte plus de 150.000 salari√©s dans le monde. Le groupe r√©alise 75% de ses activit√©s en Europe et il est pr√©sent dans plus de 70 pays. Avec 80 millions de clients dans le monde, Allianz fait partie des 5 plus grands groupes financiers mondiaux et est n¬∞ 1 de l'assurance et des services financiers en Europe.\nL‚ÄôUnit√© Investissements\nAIM Paris (Allianz Investment Management Paris), l‚Äôunit√© Investissement d‚ÄôAllianz France, a la charge de la gestion des investissements des diff√©rentes entit√©s d‚ÄôAllianz France tant sur les portefeuilles d‚Äôactifs g√©n√©raux qu‚Äôen unit√©s de compte (UC), sur toute la cha√Æne de valeur des investissements, qui couvre la gestion actif-passif, la strat√©gie d'investissement, ainsi que la planification des revenus des investissements, le suivi des risques, le reporting et les op√©rations.\nDescriptif / Missions du poste\nPour soutenir ces activit√©s l‚Äô√©quipe AIM Finance & Op√©rations, en charge des donn√©es d‚Äôinvestissements, des reportings et du suivi des risques des investissements, est √† la recherche d‚Äôun ¬´ Data Analyst ¬ª. Ce dernier, rattach√© hi√©rarchiquement √† AIM Finance & Op√©rations, couvrira l‚Äôensemble des besoins des diff√©rentes √©quipes d‚ÄôAIM (AIM Investment Strategy, AIM Asset-Liability Management, AIM Finance) et interviendra de fa√ßon op√©rationnelle sur des projets de transformation locaux et Groupe.\nVotre mission sera d‚Äôintervenir plus particuli√®rement sur :\nL‚Äôautomatisation de sourcing des donn√©es, des contr√¥les et des r√©conciliations entre diff√©rents syst√®mes d‚Äôinformations\nLe d√©veloppement de macros/codes afin d‚Äôautomatiser/optimiser les t√¢ches\nL‚Äôam√©lioration continue des bases de donn√©es Investissements\nLa fiabilisation et l‚Äôam√©lioration continue des bases de donn√©es\nLa mise en place de nouveaux reportings (Power BI)\nLe pilotage de projets en lien avec les initiatives groupes et locales\nVous travaillerez en lien √©troit avec les autres √©quipes d'AIM France ainsi que les √©quipes AIM centrales √† Munich. La maitrise de l‚Äôanglais est alors indispensable.\nProfil\nDipl√¥m√©(e) en informatique/gestion des donn√©es ou d‚Äôune √©cole d‚Äôing√©nieur (BAC +5), vous disposez d‚Äôune exp√©rience significative dans la manipulation de donn√©es (5-10 ans).\nMa√Ætrise de plusieurs langages de d√©veloppement du type Python, VBA, Access, SAS\nBonne ma√Ætrise des outils bureautiques Powerpoint, Excel et VBA, et id√©alement une premi√®re exp√©rience significative dans l‚Äôutilisation d‚Äôoutils de datavisualisation (Power BI)\nCapacit√© d‚Äôanalyse et de synth√®se, ouverture d‚Äôesprit, rigueur, organisation et autonomie,\nFran√ßais et anglais professionnel courants indispensables, √† l‚Äô√©crit comme √† l‚Äôoral.\nD√©but de la mission :\nMars 2024\nLocalisation :\nParis - La D√©fense ‚Äì TAO\nContacts : t ransmettre votre candidature compl√®te (CV + lettre de motivation)\nShow more\nShow less",
        "details": {
            "JobDetail": [],
            "TypeContract": "",
            "Salary": "",
            "Level": "",
            "Experience": "10 an(s)"
        },
        "title": "data analyst",
        "skills": {
            "ProgLanguage": [
                "Python"
            ],
            "DataVisualisation": [
                "Power BI"
            ]
        }
    },
    {
        "source": "LinkedIn",
        "company": "Groupe Q√©rys",
        "location": "Le Haillan, Nouvelle-Aquitaine, France",
        "link": "https://fr.linkedin.com/jobs/view/data-analyst-h-f-at-groupe-q%C3%A9rys-3912192127?position=7&pageNum=5&refId=9FNYDD6Vrcv1aW7UUJOd7A%3D%3D&trackingId=AL6badOm1oi06lyjb5xCFQ%3D%3D&trk=public_jobs_jserp-result_search-card",
        "description": "Le Groupe QERYS, sp√©cialiste de l‚Äôam√©nagement de l‚Äôhabitat, a son si√®ge social QERYS SAS √† Le Haillan en Gironde.\nSes\nfonctions supports\naccompagnent les soci√©t√©s commerciales du Groupe (Bricodeal, Cazabox, Domotelec, Hydro Sud Direct, Midi Piles Services, Sider et Youpalo) dans leur fonctionnement, au travers de services mutualis√©s.\nLe Groupe QERYS propose une offre globale dans le domaine de l‚Äôam√©nagement et de l‚Äôhabitat\n(890 collaborateurs - 299M‚Ç¨ CA en 2022)\nNous rejoindre c‚Äôest :\nL‚Äôassurance d‚Äôun\nGroupe solide\nUn syst√®me de\nmanagement participatif\nUn engagement\nRSE\n(Responsabilit√© soci√©tale des entreprises)\nUne attention particuli√®re √† la\nQVT\n(Qualit√© de vie au Travail)\nUn\nparcours d‚Äôint√©gration\n, des\nformations\net un\naccompagnement\ntout au long de votre carri√®re\nPour en savoir +, consultez notre site institutionnel\nhttps://www.groupe-qerys.com/\nQuel est notre contexte ?\nEn tant que D√©veloppeur Dataviz H/F, vous d√©veloppez des outils d‚Äôaide √† la d√©cision utilisant la donn√©e consolid√©e du Groupe pour faciliter le quotidien des m√©tiers.\nQuel sera votre quotidien ?\nRattach√© au Responsable Informatique BI :\nFACILITER L‚ÄôACCES A L‚ÄôINFORMATION\n‚Ä¢ Cr√©er, d√©velopper et adapter les applications √† destination des diff√©rents services\n‚Ä¢ Homog√©n√©iser les indicateurs pour permettre une lecture analytique simple et optimale\nGARANTIR LA QUALITE DE LA DATA\n‚Ä¢ Contr√¥ler, corriger et fiabiliser toutes les donn√©es du Groupe\n‚Ä¢ Enrichir le d√©cisionnel des donn√©es des nouveaux entrants (Nouveaux outils / Nouvelles Das‚Ä¶)\nEn collaboration avec les Data Ing√©nieurs, trouver des solutions pour optimiser les performances syst√®me et assurer un confort de consultation\n‚Ä¢ Soutenir la d√©marche data de la DSI\nFORMER ET ACCOMPAGNER LES UTILISATEURS SUR L‚ÄôOUTIL DE DATAVIZ\n‚Ä¢ Former les collaborateurs √† l‚Äôoutil de Dataviz\n‚Ä¢ Accompagner le changement aupr√®s des m√©tiers\nMAINTENIR ET DEVELOPPER L‚ÄôOUTIL DE DATAVIZ\n‚Ä¢ Assurer la veille technologique de l‚Äôoutil\n‚Ä¢ Assurer la gestion administrative des acc√®s et des licences\n‚Ä¢ Comprendre les besoins d‚Äôanalyse et y apporter les solutions en ad√©quation avec l‚Äôurgence.\nEnvironnement Technique :\nETL : Talend (OpenStudio) + ETLTools\nRestitution : Qliksense\nBase de donn√©es : SQLServer/Oracle/MySQL/AS400\nM√©thodologie Traditionnel et Agile\nJira/Confluence\nCe que nous vous apportons pour assurer un bon √©quilibre vie pro/vie perso (sous conditions d‚Äô√©ligibilit√©) :\n32 jours\nde cong√©s pay√©s (25 + 7 jours ouvr√©s)\nLundi de pentec√¥te ch√¥m√© et pay√© (Journ√©e de solidarit√© offerte)\nDes\njours suppl√©mentaires\nofferts :\nanciennet√©, d√©m√©nagement, mariage/pacs‚Ä¶\nJusqu‚Äô√†\n2 jours de t√©l√©travail par semaine selon le poste\nPartenariat Klaxit (favoriser le covoiturage)\nUne\nmutuelle gratuite\nUn\nint√©ressement\nPr√©voyance\nR√©duction\nPartenaires -\nD√©jeuner\nUne prime de\ncooptation\npour tout collaborateur recrut√© suite √† votre recommandation\nConditions du contrat :\nCDI - Temps plein\nSalaire et avantages :\n√† partir 34K‚Ç¨brut/an + int√©ressement + mutuelle Groupe + partenariat d√©jeuner\nHoraires :\n38h45 du lundi au vendredi\nLocalisation du poste :\n29 rue Thomas Edison, 33612 Can√©jan\nInformations compl√©mentaires :\nd√©placements occasionnels sur nos diff√©rents sites √† l'√©chelle nationale\nt√©l√©travail possible jusqu‚Äô√† deux jours/semaine\nVotre candidature retiendra notre attention si :\nVous justifiez d‚Äôune premi√®re exp√©rience significative d‚Äôau moins 2 ans sur un poste similaire. Vous disposez d‚Äôun int√©r√™t pour la data. Vous ma√Ætrisez les outils de Dataviz, avez un forte capacit√© d‚Äôanalyse et de synth√®se. Vous √™tes √† l‚Äô√©coute, bon communicant et respectez la confidentialit√© des donn√©es.\nRejoignez l‚Äô√©quipe de Benjamin !\nShow more\nShow less",
        "details": {
            "JobDetail": [
                "Temps plein"
            ],
            "TypeContract": "CDI",
            "Salary": "34K",
            "Level": "",
            "Experience": "2 an(s)"
        },
        "title": "data analyst",
        "skills": {
            "DBMS": [
                "MySQL"
            ],
            "Collaboration": [
                "Confluence",
                "JIRA"
            ],
            "EnSoftSkils": [
                "Collaboration"
            ]
        }
    },
    {
        "source": "LinkedIn",
        "company": "Catalina Marketing France",
        "location": "Boulogne-Billancourt, √éle-de-France, France",
        "link": "https://fr.linkedin.com/jobs/view/data-analyst-python-f-h-cdi-boulogne-billancourt-at-catalina-marketing-france-3907391526?position=8&pageNum=5&refId=9FNYDD6Vrcv1aW7UUJOd7A%3D%3D&trackingId=4W0j8BPf8es2VkbZTqz6qg%3D%3D&trk=public_jobs_jserp-result_search-card",
        "description": "Catalina est le seul acteur de la GMS √† pouvoir d√©ployer des plans marketing hyper-personnalis√©s avec autant de puissance ! Chez Catalina, on parle en milliards de donn√©es depuis des ann√©es.\nGr√¢ce √† de puissants outils en IA et Machine Learning, nous analysons les comportements d‚Äôachat des clients de la grande distribution pour mettre en place des strat√©gies de recrutement et de fid√©lisation via des plans marketing omnicanaux (couponing cibl√©, couponing digital via Coupon Network, programmes de fid√©lit√©‚Ä¶). Nous √©laborons des milliers de campagnes chaque ann√©e : Leclerc, Carrefour, Monoprix, Nestl√©, Procter & Gamble, Heineken, Coca-Cola, Bjorg‚Ä¶ Ce serait trop long de tous les citer.\nCatalina r√©unit 860 personnes dans le monde, et plus de 240 en France. Travaillant main dans la main, les Cataliniens ont un fort esprit collaboratif et la culture du r√©sultat. Ici on a la gagne !\nDepuis toujours, le succ√®s de Catalina, c'est le talent de nos √©quipes. Chez Catalina, on favorise la confiance, la pro-activit√© et le d√©veloppement en investissant sur la formation continue. Et parce que nous avons tant de p√©pites talentueuses, nous misons sur elles tous les jours en pr√¥nant l‚Äô√©volution. Les meilleurs atouts des grands groupes et des start-ups sont r√©unis en une seule entreprise : puissance et flexibilit√© !\nSoucieux de notre impact, la RSE est au c≈ìur de nos actions depuis toujours. En 2022, nous avons re√ßu la m√©daille d‚Äôargent EcoVadis pour saluer nos engagements sociaux et environnementaux.\nMissions et Responsabilit√©s :\nAu sein du p√¥le Analytics, et int√©gr√©(e) √† une √©quipe de 8 personnes d√©di√©e au support des industriels de la grande distribution √† travers l‚ÄôEurope (France, Italie et UK), tes missions consistent √† :\n-Echanger r√©guli√®rement avec les √©quipes business en France ou en Italie pour prendre connaissance des enjeux et probl√©matiques clients aupr√®s des √©quipes commerciales\n-Proposer, mettre en place des optimisations/Automatisations de nos process statistiques actuels\n-Extraire, analyser et interpr√©ter les r√©sultats des campagnes de marketing direct\n-Participer √† des sessions des brainstorming en interne avec l‚Äô√©quipe DataScience et les autres √©quipes Analytics sur la veille m√©thodologique de nos mesures\n-R√©aliser des projets d‚Äô√©tudes statistiques (segmentations, algo AI/ML, etc.)\nEt si c‚Äô√©tait toi ?\nDe formation sup√©rieure en statistiques, tu b√©n√©ficies d‚Äôun minimum 2 ans d‚Äôexp√©rience id√©alement dans le domaine des √©tudes marketing, et d‚Äôune exp√©rience de travail sur des bases de donn√©es √† forte volum√©trie.\nTu parles Anglais (courant)\nTu as une parfaite ma√Ætrise du SQL.\nTu as une parfaite connaissance de Python, l‚Äôutilisation dans un environnement Cloud est un plus (Azure, Snowflake, Databricks, etc.)\nLa connaissance des outils de Data visualisation comme Power BI est un plus\nTu connais les techniques statistiques appliqu√©es au Marketing Direct : √©chantillonnage, mise en place de t√©moins, analyse des r√©sultats, bonne connaissance des techniques de segmentations et de scoring.\nTu es d√©j√† familier avec les techniques de ML & AI.\nTu es capable de vulgariser votre discours aupr√®s de tes interlocuteurs (√©quipe commerciale, √©quipe marketing, clients‚Ä¶)\nDynamique et curieux(se), ta rigueur, ton aisance relationnelle, ton sens de l‚Äôinitiative ainsi que ton autonomie te permettra de t‚Äôint√©grer rapidement dans notre structure.\nTu es un amoureux de la data, un fin connaisseur de la grande conso, un passionn√© d'innovations digitales ? Tu cherches une entreprise qui te fait confiance et valorise tes talents, une bonne ambiance de travail, un √©quilibre vie priv√©e/ vie pro et une forte coh√©sion d'√©quipe avec un esprit entrepreneurial ?\nEn devenant toi aussi Catalinien, tu seras fier de participer √† cette aventure humaine au c√¥t√© d‚Äôexperts passionn√©s et bons vivants !\nProcess de recrutement :\n1er entretien avec Natacha, Talent Acquisition Manager et test technique de 30 minutes\n2√®me entretien avec Laurence Analytics Director et Murielle Manager Analytics.\nNos infos utiles :\nTon futur lieu de travail : Boulogne-Billancourt (Marcel Sembat)\nContrat: CDI\nT√©l√©travail : 3 jours de t√©l√©travail possible / semaine\nAvantages : 1 RTT / mois, CE, participation, prime vacances, carte restaurant swile, prise en charge de 2/3 de la mutuelle, journ√©e d‚Äôengagement associatif, mais aussi de nombreux team buildings, des ap√©ros, des paniers de fruits, du caf√© √† volont√©‚Ä¶\nCatalina, en tant que responsable de traitement, met en ≈ìuvre un traitement de donn√©es ayant pour finalit√©s principales la gestion et le suivi des candidatures. Tu disposes d‚Äôun droit d‚Äôacc√®s, d‚Äôeffacement, de rectification et de portabilit√© de vos donn√©es, ainsi que d‚Äôun droit d‚Äôopposition et de limitation au traitement de ces donn√©es. L‚Äôexercice des droits s‚Äôeffectue sur la plateforme OneTrust d√©di√©e (choix de la langue en haut √† droite) accessible depuis le site catalinamarketing.fr/politique-confidentialite ¬´ Vos droits, employ√© ¬ª ou par courrier adress√© √† : Catalina Marketing France, Privacy Recrutement, 58 Avenue Edouard Vaillant 92100 Boulogne Billancourt.\nSauf opposition de ta part, les candidatures re√ßues font l‚Äôobjet d‚Äôune conservation pendant 2 ans.\nShow more\nShow less",
        "details": {
            "JobDetail": [],
            "TypeContract": "CDI",
            "Salary": "",
            "Level": "",
            "Experience": "2 an(s)"
        },
        "title": "data analyst",
        "skills": {
            "ProgLanguage": [
                "Python"
            ],
            "DataBase": [
                "SQL"
            ],
            "BigData": [
                "Databricks"
            ],
            "DataVisualisation": [
                "Power BI"
            ],
            "CloudComputing": [
                "Azure"
            ],
            "DBMS": [
                "Snowflake"
            ],
            "Other": [
                "Statistiques",
                "Machine Learning",
                "Cloud",
                "ML"
            ],
            "EnSoftSkils": [
                "Initiative"
            ]
        }
    },
    {
        "source": "LinkedIn",
        "company": "Checkout.com",
        "location": "Paris, √éle-de-France, France",
        "link": "https://fr.linkedin.com/jobs/view/senior-data-analyst-at-checkout-com-3860155203?position=9&pageNum=5&refId=9FNYDD6Vrcv1aW7UUJOd7A%3D%3D&trackingId=c%2FTawuU0%2Frn24Zsqr0ew8A%3D%3D&trk=public_jobs_jserp-result_search-card",
        "description": "Company Description\nWe're Checkout.com\nCheckout.com is one of the most exciting fintechs in the world. Our mission is to enable businesses and their communities to thrive in the digital economy. We‚Äôre the strategic payments partner for some of the best known fast-moving brands globally such as Wise, Hut Group, Sony Electronics, Homebase, Henkel, Binance, Klarna and many others. Purpose-built with performance and scalability in mind, our flexible cloud-based payments platform helps global enterprises launch new products and create experiences customers love. And it's not just what we build that makes us different. It's how.\nWe empower passionate problem-solvers to collaborate, innovate and do their best work. That‚Äôs why we‚Äôre number 9 on the Forbes Cloud 100 list and on Glassdoor‚Äôs list of Top 10 fintechs to work for. And we‚Äôre just getting started. We‚Äôre building diverse and inclusive teams around the world ‚Äî because that‚Äôs how we create even better experiences for our merchants and our partners. And we need your help. So, join us to build tomorrow, today.\nJob Description\nYou will be joining the Identity Verification team, responsible to maintain and continuously improve a world-class online identity verification technology, based on real-time video recognition.\nAs a Senior Product Data Scientist, you'll work as part of a cross-functional team alongside product managers, designers, and software and analytics engineers, using data and your expertise to influence and drive the strategy of our products. You will have end-to-end ownership for all the data aspects for your ‚Äòtribe‚Äô. You'll help define how we measure the success of our products, collaborate with engineers on how we collect data, build data pipelines to track the defined metrics, design and build reports/dashboards, and run analyses to find product improvement opportunities. You'll be a co-owner of a product, driving it to success in partnership with other cross-functional team members.\nYou'll also be part of the broader Analytics function, a team of Analytics Engineers, Data Scientists, and Data Product Managers.\nWe're a new but highly visible function within Checkout.com, so this is an exciting opportunity to drive a positive impact.\nHow you‚Äôll make an impact\nBe responsible for a product domain and its metrics. You'll be accountable for defining, measuring, and presenting metrics.\nContribute product roadmaps through data-based recommendations and continuously define high-impact areas for improvement.\nSupporting product discovery, research, and experimentation\nWorking closely with Data Engineers to make sure we collect and model the right data to produce relevant business insights\nDesign and implement reusable and scalable data models for our data warehouse using dbt and Snowflake\nDesign and implement Looker structures (explores, views, etc) which will enable users across the organization to self-serve analytics\nFoster data culture across products and technology by actively sharing insights and ideas and building positive relationships with colleagues\nBuild experiments and analysis frameworks to quantify the ROI of product development.\nDrive by example your team and broader data community to apply best practices in analytics from data collection to analysis.\nQualifications\nWhat we‚Äôre looking for\nProven delivery experience as a data scientist or data analyst\nStrong communicator, you're able to explain complex technical topics to non-technical team members\nExperience conducting experiments, building measurement frameworks, and validating the results with relevant quantitative methods\nStrong analytical mind, proven experience in converting ambiguous problems into structured and data-informed solutions\nCuriosity and attention to detail: you like to explore and understand the trends and investigate unusual patterns\nProficiency in SQL for data interrogation and data transformation (ideally experience with Looker, Snowflake and dbt)\nKnowledge of applied statistics (e.g., hypothesis testing, regression)\nAdditional Information\nHybrid Working Model:\nAll of our offices globally are\nonsite 3 times per week\n(Tuesday, Wednesday, and Thursday). We‚Äôve worked towards enabling teams to work collaboratively in the same space, while also being able to partner with colleagues globally. During your days at the office, we offer amazing snacks, breakfast, and lunch options in all of our locations.\nApply Without Meeting All Requirements Statement\nIf you don't meet all the requirements but think you might still be right for the role, please apply anyway. We're always keen to speak to people who connect with our mission and values.\nWe believe in equal opportunities\nWe work as one team. Wherever you come from. However you identify. And whichever payment method you use.\nOur clients come from all over the world ‚Äî and so do we. Hiring hard-working people and giving them a community to thrive in is critical to our success.\nWhen you join our team, we‚Äôll empower you to unlock your potential so you can do your best work. We‚Äôd love to hear how you think you could make a difference here with us.\nWe want to set you up for success and make our process as accessible as possible. So let us know in your application, or tell your recruiter directly, if you need anything to make your experience or working environment more comfortable. We‚Äôll be happy to support you.\nTake a peek inside life at Checkout.com via\nOur Culture video https://youtu.be/BEwnpHuadSw\nOur careers page https://www.checkout.com/careers\nOur LinkedIn Life pages bit.ly/3OaoN1U\nOur Instagram https://www.instagram.com/checkout_com/\nShow more\nShow less",
        "details": {
            "JobDetail": [
                "Senior"
            ],
            "TypeContract": "",
            "Salary": "",
            "Level": "",
            "Experience": null
        },
        "title": "data analyst",
        "skills": {
            "DataBase": [
                "SQL"
            ],
            "DBMS": [
                "Snowflake"
            ],
            "Collaboration": [
                "Teams"
            ],
            "Other": [
                "Cloud"
            ],
            "EnSoftSkils": [
                "Organization"
            ]
        }
    },
    {
        "source": "LinkedIn",
        "company": "Mazars",
        "location": "Courbevoie, √éle-de-France, France",
        "link": "https://fr.linkedin.com/jobs/view/data-analyst-junior-paris-2024-h-f-at-mazars-3904531206?position=10&pageNum=5&refId=9FNYDD6Vrcv1aW7UUJOd7A%3D%3D&trackingId=Jamm1MtpZy%2BS5vmsVMyqOA%3D%3D&trk=public_jobs_jserp-result_search-card",
        "description": "Description de l'entreprise\nMazars est un groupe international et int√©gr√© sp√©cialis√© dans l‚Äôaudit, la fiscalit√© et le conseil ainsi que dans les services comptables et juridiques*. Pr√©sents dans plus de 95 pays et territoires √† travers le monde, nous nous appuyons sur l‚Äôexpertise de plus de 47 000 professionnels ‚Äì plus de 30 000 au sein de notre partenariat int√©gr√© et plus de 17 000 via ¬´ Mazars North America Alliance ¬ª ‚Äì pour accompagner les clients de toutes tailles √† chaque √©tape de leur d√©veloppement.\nDans les pays o√π les lois en vigueur l‚Äôautorisent\nDescription du poste\nMazars souhaite chaleureusement son √©quipe ¬´ Audit Data Analytics ¬ª au sein de ses √©quipes Data Services.\nAu sein d'une √©quipe √† la fronti√®re entre l'audit et la tech, vous d√©veloppez ainsi une double comp√©tence technique et fonctionnelle ; en v√©ritable Business Analyst, vous concevez et d√©ployez des solutions Analytics pour les clients Mazars.\nVous intervenez sur des missions vari√©es dans plusieurs secteurs d'activit√© (industrie, services, secteur public, services financiers (banque et assurance)) et alimentez les comp√©tences suivantes :\nd√©veloppement de solutions innovantes sur des socles technologiques vari√©s de data analytics, de data visualisation et de programmation : Alteryx, Qlik, SQL, PowerBI, Python, etc. ;\nparticipation √† la conception de solutions fonctionnelles, de la phase de sp√©cifications √† la phase de mise √† disposition ;\ncontribution au d√©veloppement de nouvelles offres Mazars au service des enjeux Data de nos clients ;\nanalyser fonctionnellement les r√©sultats produits par les solutions Analytics ;\nparticipation √† la r√©daction de rapports d'analyse et pr√©sentation des outils et r√©sultats Analytics √† nos clients.\nEn compl√©ment, vous √™tes progressivement form√©s aux technologies de machine learning, √† l'intelligence artificielle et √† la science des donn√©es.\nQualifications\nDe formation Bac+5, vous √™tes jeune dipl√¥m√©(e) d'une √©cole d'ing√©nieurs, √©cole de commerce ou universit√© et avez un go√ªt prononc√© pour les sujets Analytics et les nouvelles technologies de fa√ßon g√©n√©rale, avec une app√©tence pour les probl√©matiques m√©tier et finance :\nVous avez une sp√©cialisation en Syst√®me d'Information et/ou en Data Science ;\nVous √™tes passionn√©(e) par les nouvelles technologies li√©es √† la Data ;\nVous avez id√©alement une exp√©rience de stage au cours de laquelle vous √™tes intervenu(e) sur le domaine de la ¬´ Data ¬ª ;\nVous aimez innover, vous √™tes curieux, dynamique et autonome et vous avez une certaine\naisance √† d√©velopper vos connaissances sur de nouveaux outils ;\nVous avez un excellent sens du travail en √©quipe ;\nVous poss√©dez les connaissances de base parmi les technologies suivantes : SQL, ACL, data studio, PowerBI, Qlik, Alteryx, Tableau softwareetc.)\nInt√©gration pr√©vue √† partir de septembre 2024\nInformations suppl√©mentaires\nLes + du m√©tier :\nDiversit√© des missions\nTravail d'√©quipe\nEquipe dynamique\n√âvolution de carri√®re rapide\nChez Mazars, nous pla√ßons le d√©veloppement personnel au c≈ìur de nos priorit√©s. Vous √™tes force de proposition ? Nous vous donnerons l'opportunit√© de porter et r√©ussir vos id√©es. Vous souhaitez participer √† la croissance du cabinet ? Nous vous int√©grerons dans le d√©veloppement ou le renforcement de nos offres. Enfin, les formations con√ßues par Mazars U Learn vous permettront de r√©inventer et de d√©velopper vos softs skills ainsi que de booster votre talent !\nShow more\nShow less",
        "details": {
            "JobDetail": [],
            "TypeContract": "",
            "Salary": "",
            "Level": "Bac+5",
            "Experience": null
        },
        "title": "data analyst",
        "skills": {
            "ProgLanguage": [
                "Python"
            ],
            "DataBase": [
                "SQL"
            ],
            "DataVisualisation": [
                "Tableau"
            ],
            "Other": [
                "Machine Learning"
            ]
        }
    },
    {
        "source": "LinkedIn",
        "company": "Disneyland Paris",
        "location": "Marne-la-Vall√©e, √éle-de-France, France",
        "link": "https://fr.linkedin.com/jobs/view/alternance-%E2%80%93-data-analyst-junior-reporting-f-h-nb-at-disneyland-paris-3901105673?position=1&pageNum=7&refId=QYO6QFCk1HyZpy1IxSLXjw%3D%3D&trackingId=wJnmePfCYzhHCYd4vWttEw%3D%3D&trk=public_jobs_jserp-result_search-card",
        "description": "Le Sourcing √† Disneyland¬Æ Paris :\nLe d√©partement division Sourcing et Environnement Produits Merchandise Food & Beverage est compos√©e de 4 p√¥les : la coordination Environnementale produits, l‚ÄôAdministration des achats, le p√¥le Outils et Analyses et enfin le p√¥le Achat sourcing.\nLa mission principale de l‚Äô√©quipe est de n√©gocier des co√ªts d'acquisition des produits merchandise ou food & beverage, dans le respect du cahier des charges produits, en veillant √† la conformit√© r√©glementaire, environnementale et en pleine ad√©quation avec les objectifs commerciaux.\nVos missions :\nRattach√©(e) au p√¥le Outils et Analyses, vos missions seront les suivantes :\nVous √™tes garant(e) de la mise √† jour des reportings existants et n√©cessaires au fonctionnement de l'activit√© ;\nVous assistez les analystes au quotidien (√©criture des process, support sur les analyses‚Ä¶) ;\nVous participez au d√©veloppement d'outils de reportings vari√©s (Excel, Query, Power BI‚Ä¶) ;\nEnfin, vous collaborez en mode projet selon l‚Äôactualit√© du service.\nVos atouts pour ce poste :\nIl s'agit d'une alternance de 1 an ou 2 ans.\nVous pr√©parez un dipl√¥me d‚Äôun niveau Bac+3 au minimum sp√©cialis√© en analyse de donn√©es, informatique ou √©quivalent.\nVous avez id√©alement une premi√®re exp√©rience dans le domaine (stage/alternance).\nVous avez une bonne ma√Ætrise du Pack Office (niveau avanc√©). La connaissance de Power BI, Tableau ou Business solution est un plus.\nVous justifiez d‚Äôun niveau d‚Äôanglais interm√©diaire (B2).\nAu quotidien, vous faites preuve d‚Äôorganisation et de rigueur. Vous appr√©ciez √©voluer dans un environnement collaboratif, √©changer avec de multiples interlocuteurs et t√©moignez d‚Äôun bel esprit d‚Äô√©quipe.\nEnfin, vous √™tes reconnu(e) pour votre esprit d‚Äôanalyse.\nLa diff√©rence Disney\n‚ú®\nLa diversit√© des interactions et donc les opportunit√©s pour rencontrer une multitude de m√©tiers autour des achats, de la supply chain ou du d√©veloppement produit comme de la relation commerciale.\nQuelques avantages de notre entreprise :\nUn cadre de travail unique dans un contexte international aux nombreuses opportunit√©s,\nUn logement √† proximit√© de nos parcs (sous conditions),\nLe remboursement de 80% des abonnements pour les transports quotidiens domicile‚Äìtravail,\nOffre diversifi√©e de restauration d‚Äôentreprise et subvention allou√©e,\nDes acc√®s aux parcs pour vous et vos proches, et √† la plateforme Disney+,\nDes r√©ductions tarifaires dans les boutiques, restaurants et h√¥tels Disney toute l‚Äôann√©e,\nDe nombreux avantages suppl√©mentaires : temps de formation, programmes de reconnaissance, √©v√®nements exclusifs, aide √† la parentalit√©, conciergerie d‚Äôentreprise, compl√©mentaire sant√©‚Ä¶\nT√©l√©travail possible lorsque la fonction ne n√©cessite pas une pr√©sence sur site.\nVous √™tes pr√™t(e) √† participer √† une formidable aventure humaine‚ÄØet √† rejoindre nos 18 000 collaborateurs (Cast Members) qui partagent tous la m√™me ambition professionnelle‚ÄØ: faire vivre la magie Disney et faire r√™ver des millions de visiteurs‚ÄØ? Nous sommes pr√™ts √† vous donner les moyens de faire rayonner vos talents‚ÄØ! #DLPCAMPUSGA24\nüè∞\nShow more\nShow less",
        "details": {
            "JobDetail": [],
            "TypeContract": "",
            "Salary": "",
            "Level": "Bac+3",
            "Experience": "2 an(s)"
        },
        "title": "data analyst",
        "skills": {
            "DataVisualisation": [
                "Power BI",
                "Tableau"
            ]
        }
    },
    {
        "source": "LinkedIn",
        "company": "VINCI Airports",
        "location": "Lyon, Auvergne-Rh√¥ne-Alpes, France",
        "link": "https://fr.linkedin.com/jobs/view/data-analyst-f-h-at-vinci-airports-3918622032?position=3&pageNum=7&refId=QYO6QFCk1HyZpy1IxSLXjw%3D%3D&trackingId=Pn%2B%2BQas%2Bc6Wf6MzEIV%2Fr0w%3D%3D&trk=public_jobs_jserp-result_search-card",
        "description": "Lyon A√©roport, 1er a√©roport du r√©seau VINCI Airports en France pilote l‚Äôexploitation des a√©roports Lyon‚ÄìSaint Exup√©ry et Lyon‚ÄìBron.\nRattach√©(e) au responsable √©tudes et projets, le/la data analyst se positionne comme r√©f√©rent technique et fonctionnel sur le p√©rim√®tre data de la DCM. Il organise et valorise les donn√©es pour d√©livrer des reportings et des analyses √† valeur ajout√©e.\nExpert technique, il/elle collabore avec les √©quipes informatiques pour construire les environnements et assurer le traitement de donn√©es. Expert analytique, il/elle capte les enjeux et besoins m√©tiers et se positionne comme v√©ritable ¬´ business partner ¬ª.\nMISSIONS\nCe poste n√©cessite une r√©elle double comp√©tence technique et analytique, et la capacit√© √† travailler en autonomie et transversalit√© :\nTechnique : data cleaning, data modeling et business intelligence\nSourcer, structurer, croiser, redresser, valider les donn√©es\nConstruire des univers de donn√©es orient√©s d√©cisionnels\nProduire les KPIs et tableaux de bords sous Power BI (et Business Object)\nPr√©parer / collaborer √† l‚Äôindustrialisation des travaux\nFavoriser la self-BI dans les √©quipes m√©tiers\nAnalytique : exploration, √©tudes et data mining\nConsolider les besoins m√©tiers d‚Äôanalyses et de reporting\nSch√©matiser les flux et mod√®les de donn√©es, et consigner les r√®gles de gestion\nFaire √©merger par vos propres recherches de nouveaux axes d‚Äôanalyses / leviers de performance\nR√©aliser les analyses : du tableau √† plat au mod√®le statistique avanc√© (ex : pr√©dictif)\nPr√©senter les r√©sultats : structuration de fichiers, tableaux, pr√©sentation power point\nTransverse : projets et gouvernance\nDocumenter les travaux : supports techniques et fonctionnels\nPromouvoir une d√©marche de gouvernance\nGarantir la qualit√© des donn√©es et am√©liorer les r√©f√©rentiels\nPiloter / contribuer √† des projets orient√©s data et technologiques\nEnqu√™tes\nCollaborer avec les instituts d‚Äô√©tudes prestataires en charge de mener des enqu√™tes\nCadrer le besoin et valider les choix m√©thodologiques et l‚Äô√©chantillon\nProduire des rapports trimestriels et r√©aliser des analyses ad hoc\nIndustrialiser le recueil des donn√©es pour une exploitation automatis√©e\nBac +4/5, double comp√©tence, exp√©rience 3 √† 5 ans\nVous disposez de comp√©tences techniques vous permettant d‚Äô√©voluer en compl√®te autonomie, et vous √™tes en capacit√© de mener des analyses percutantes. Vous faites donc preuve d‚Äôagilit√© pour collaborer avec des interlocuteurs aux profils vari√©s. Et de r√©silience pour consacrer l‚Äô√©nergie suffisante √† la pr√©paration des donn√©es dans un environnement en mutation. Votre curiosit√© et votre sensibilit√© vous permettent d‚Äôappr√©hender les enjeux m√©tiers, et vous savez y r√©pondre par des livrables de qualit√©, orient√©s usages et r√©sultats.\nVous serez amen√© √† travailler en autonomie avec les environnements, outils et langages suivants : Google Cloud Plateform (GCP / Big - Power Query), Oracle (SQL), Power BI (PBI / DAX), Business Object (BO), Python.\nVous r√©aliserez des dashboards / analyses portant sur les parkings, le pricing, l‚Äôa√©ronautique, le retail, CRM‚Ä¶\nGestion de projet, autonomie, initiative, pers√©v√©rance, rigueur, curiosit√©, enthousiasme, esprit d‚Äô√©quipe, anglais\nShow more\nShow less",
        "details": {
            "JobDetail": [],
            "TypeContract": "",
            "Salary": "",
            "Level": "",
            "Experience": "5 an(s)"
        },
        "title": "data analyst",
        "skills": {
            "ProgLanguage": [
                "Python"
            ],
            "DataBase": [
                "SQL"
            ],
            "DataVisualisation": [
                "Power BI",
                "Tableau"
            ],
            "CloudComputing": [
                "GCP"
            ],
            "Other": [
                "Cloud"
            ],
            "EnSoftSkils": [
                "Initiative"
            ]
        }
    },
    {
        "source": "LinkedIn",
        "company": "Accor",
        "location": "Issy-les-Moulineaux, √éle-de-France, France",
        "link": "https://fr.linkedin.com/jobs/view/business-data-analyst-at-accor-3849451754?position=4&pageNum=7&refId=QYO6QFCk1HyZpy1IxSLXjw%3D%3D&trackingId=6WzHkxk%2FOyXxqQg8i7yv3g%3D%3D&trk=public_jobs_jserp-result_search-card",
        "description": "Company Description\nLeading the hospitality revolution, Accor is more than a hotel group. With luxury to economy, homestays to resorts, we are a holistic ecosystem of 40 brands in 110 countries, Talent and Solutions, ready to engage with the future‚Äôs endless possibilities. Accor has an offer to bring new life to the way you live, work, play and do business with a personalized guest experience.\nAstore is Accor‚Äôs Procurement Organization, that is revolutionizing the hospitality sector by offering all the products and services necessary to ensure the proper functioning of all hospitality businesses. With a team of 200 experts serving 5000 customers in 20 countries, Astore is able to negotiate some of the best prices and conditions on the market. With more than 7500 clients worldwide and about 2000 external partners, our ambition is to become the first choice for procurement solution for the hospitality sector.\nAstore Digital Factory leads all our Digital activities within the Procurement function. Its main responsibility is to develop the business thanks to best-in-class digital tools maximizing the impact (Revenue, EBITDA) of our Procurement business teams in the Paris HQ and in the different worldwide regions. The digital platforms are covering all Procurement business processes: (i) Hospitality supply chain at site (e-ordering through marketplace, Supplier directory, Pre-opening project management, Inventory & recipe management, Invoice to pay, Data, Customer Analytics & Procurement news) and (ii) Internal Procurement operations (Source to contract, CRM, Marketing & Sales automation, Ticketing, Customer Website, Full order to pay Revenue / Back end rebate Management, CSR, Finance process & Business performance analytics).\nThe Hotel Tools Product team is in charge of all tools at hotel level (e-ordering, inventory & recipe management, invoice to pay), out of which some are ‚Äúcustom‚Äù and others ‚ÄúSaaS‚Äù (Mirakl, Tradeshift, FutureLog).\nJob Description\nThe Business Data Analyst (BDA) is the interface between the Data and business teams. The BDA is in charge of understanding the demands of Procurement department and carefully providing and planning a solution. The BDA is a data-driven professional, uses the data analysis process to understand, interpret, and predict patterns in business, and then use those data-driven insights to enhance their business process and making decisions. The BDA aims to identify opportunities to grow, optimize, and improve an organization‚Äôs business processes. His function is on of vision and strategy implementation. The BDA also helps in making judgments that are aligned with corporate objectives.\nMain Activities\nHas experience in Data-driven Business Analysis on simple and complex problems\nIn charge of prioritization of business requirements according to the objectifs requested\nCollaborates with the users or business experts to define what it is expected\nAnalyses requirements and participates in the design of the solution with the technical team\nLies at the intersection of Data Analysis and Business Analysis\nCreates and modifies computer programs to extract information from company databases\nInteracts with data engineer and data scientists to understand how data needs to be converted, loaded and presented\nDevelops and deploys dashboards, reports, to collect data-backed insights\nInterprets key business data sets\nProvides insights on potential areas of growth, optimization, and improvements\nWorks cross-department on data-driven strategies that improve business processes and decision-making\nIs responsible of writing or providing US stories or/and Business Rules.\nQualifications\nSkills & profile\n:\nBS/BA Degree (MS preferred) preferably in Computer Science, Statistics, Math or equivalent combination of education and experience.)\n1-5 years of experience with data analysis and preparation, including experience with very large data sets\nExperience working with unstructured data sets is a plus\nMathematical skills to help collect, measure, organize and analyze data\nKnowledge of programming languages like SQL, R, Python\nTechnical proficiency regarding database design development, data models\nKnowledge of data visualization\nKnowledge of how to create and apply the most accurate algorithms to datasets in order to find solutions\nKnowledge of the project management process.\n3+ years in management/executive role\nExperience in Agile Development\nAdditional Information\nWhat benefits can Accor offer its employees?\nA real Work life balance\nRemote work / autnomous framework\nAttractive Finance Benefits\nProfit sharing bonus \"interessement participation\" compulsory and voluntary plans / 700 ‚Ç¨ per year Allowance Green transportation such as electrical bike, scooter / Pass Navigo subsidised max 75% / Referral bonus / meal ticket / free coffee\nLearning & development\nManagement talent at the earth our of HR Accor strategy.\nWe want you to feel free to dare and free to grow, by opening new doors to continuous learning and skills development. Challenge yourself and switch between jobs, brands, and career paths\nShow more\nShow less",
        "details": {
            "JobDetail": [
                "Remote",
                "Full"
            ],
            "TypeContract": "",
            "Salary": "",
            "Level": "",
            "Experience": null
        },
        "title": "data analyst",
        "skills": {
            "ProgLanguage": [
                "R",
                "Python"
            ],
            "DataBase": [
                "SQL"
            ],
            "DataAnalytics": [
                "R"
            ],
            "Collaboration": [
                "Teams"
            ],
            "EnSoftSkils": [
                "Organization"
            ]
        }
    },
    {
        "source": "LinkedIn",
        "company": "FBD Group",
        "location": "Tremblay-en-France, √éle-de-France, France",
        "link": "https://fr.linkedin.com/jobs/view/data-analyst-f-h-at-fbd-group-3886652484?position=5&pageNum=7&refId=QYO6QFCk1HyZpy1IxSLXjw%3D%3D&trackingId=wzAHo5vhmHxpEaABJc8jHA%3D%3D&trk=public_jobs_jserp-result_search-card",
        "description": "Vous aimez :\nConduire le changement dans le secteur de la distribution\nPartager les challenges d‚Äôune entreprise agile en forte croissance\nL‚Äôesprit d‚Äô√©quipe et l‚Äôambiance qui r√®gnent dans un groupe √† taille humaine (250 collaborateurs)\nL‚Äôinnovation, le num√©rique et les nouvelles technologies au service de l‚Äôexp√©rience client\nLa gestion de projet\nVous aimerez accompagner l‚Äôentreprise dans son √©volution en √©tant un agitateur d'id√©es.\nRattach√©(e) au Responsable Performance, vous aurez pour objectif principal le recueil, l‚Äôanalyse et l‚Äôinterpr√©tation de la donn√©e de l‚Äôentreprise. Ces donn√©es peuvent √™tre li√©es aux clients (CRM), aux produits et √† leurs performances, ou m√™me aux concurrents.\nEn collaboration √©troite avec les autres p√¥les de la Direction Digitale, les √©quipes Commerce, les √©quipes Marketing, et les √©quipes IT, ainsi que les autres Directions support du Groupe, vous construirez, exploiterez et interpr√©terez les donn√©es pour en d√©gager des observations business utiles.\nMissions Principales :\nEchanger avec les diff√©rentes √©quipes internes concern√©es pour comprendre leurs besoins et leurs enjeux\nD√©finir les indicateurs cl√©s de performance (KPI) avec les parties prenantes pour mesurer la tenue des objectifs\nMettre en place ou optimiser les outils de suivi et de pr√©vision avec la DSI\nAnalyser les bases de donn√©es\nSynth√©tiser les r√©sultats de ces analyses pour les communiquer aux bons interlocuteurs\nProposer des plans d‚Äôaction (mise en place d‚Äôoutils, d√©finition des processus‚Ä¶)\nIdentifier les probl√®mes et proposer des solutions appropri√©es\nAssurer la qualit√© et la fiabilit√© des donn√©es\nEtablir une cartographie des donn√©es utilis√©es au sein des analyses pour une meilleure compr√©hension des interlocuteurs\nMissions D√©taill√©es :\nRecueil des besoins\nEchanger avec les diff√©rentes √©quipes internes concern√©es pour comprendre leurs besoins et leurs enjeux\nD√©finir les indicateurs cl√©s de performance (KPI) avec les parties prenantes pour mesurer la tenue des objectifs\nMod√©liser les donn√©es n√©cessaires √† l‚Äôanalyse\nCollecte des donn√©es\nRecueillir et extraire les sources de donn√©es pertinentes (savoir o√π les trouver) et de qualit√©, √† traduire ensuite en donn√©es statistiques\nAssurer la qualit√© et la fiabilit√© des donn√©es\nIdentifier les probl√®mes (donn√©es manquantes, qualit√© insuffisante, stockage, centralisation, etc.) et proposer des solutions appropri√©es en exprimant le besoin associ√© aux √©quipes IT\nTraitement\nProposer des plans d‚Äôaction :\nMettre en place des process/requ√™tes et des automatisations\nMettre en place ou optimiser les outils de suivi et de pr√©vision avec la DSI\nTrouver de nouvelles fa√ßons de traiter la donn√©e avec l‚Äôappui de nouveaux outils, au vu de l‚Äôaccroissement consid√©rable du nombre de donn√©es\nAnalyse\nD√©finir et g√©rer des outils d‚Äôanalyse et d‚Äôaide √† la d√©cision : pr√©visions et objectifs de vente, tableaux de bord, indicateurs de performance, analyse de la conjoncture et des march√©s, suivi de la performance et appui aux √©quipes commerciales\nAnalyser les bases de donn√©es, produire des analyses m√©tiers et proposer des recommandations aux managers\nS‚Äôassurer de la coh√©rence des r√©sultats par rapport au commerce et √† l‚Äôactivit√© r√©elle en point de vente\nCommunication\nCr√©er des Dashboard, mettre en place des KPIs et des reportings de performance\nConstruire et faire √©voluer les rapports issus de la Business Intelligence (BI) & Web Analytics\nSynth√©tiser les r√©sultats de ces analyses pour les communiquer aux bons interlocuteurs\nEtablir une cartographie des donn√©es utilis√©es au sein des analyses pour une meilleure compr√©hension des interlocuteurs\nDiffuser et assurer la bonne interpr√©tation et la bonne compr√©hension des rapports d‚Äôanalyse\nTransverse\nFaire preuve de proactivit√© pour explorer les donn√©es disponibles et proposer des analyses non sollicit√©es\nR√©aliser une veille marketing et commerciale sur la concurrence et proposer des analyses associ√©es\nContribuer √† l‚Äôanalyse des parcours omnicanaux et √† la recherche de leviers de croissance\nExplorer les opportunit√©s d‚Äôapplication de l‚ÄôIA dans la Data Analyse\nR√©aliser des √©tudes qualitatives sur diff√©rentes probl√©matiques business\nParticiper √† la mesure √©conom√©trique des campagnes d‚Äôacquisition ainsi qu‚Äô√† la mesure de l‚Äôattribution/contribution des diff√©rents leviers marketing actionn√©s\nExp√©rience : 5 ans minimum en Data analyse, avec des connaissances en data engineering id√©alement dans le secteur du retail\nFormation : Bac+5, cursus en math√©matiques, statistiques, √©conomie, marketing ou en informatique (id√©alement Master en statistiques / √©conom√©trie ou Master sp√©cialis√© en Big Data)\nLa maitrise de l‚Äôanglais courant est n√©cessaire\nSavoir-faire & comp√©tences :\nMa√Ætrise des bases de donn√©es business (BigQuery, Snowflake, Redshift‚Ä¶) et du langage SQL\nMaitrise de la construction d‚Äôun Datawarehouse\nMa√Ætrise d‚Äôun outil d‚Äôorchestration (DBT, Airflow‚Ä¶) et du langage Python\nMa√Ætrise d‚Äôau moins un outil de dashboarding (Looker, Power BI, Tableau‚Ä¶)\nMa√Ætrise des librairies de manipulation de donn√©es en Python (NumPy, Pandas, Matplotlib, SciPy, Scikit-learn)\nUne connaissance des outils tels que Hadoop ou Spark serait un plus\nCompr√©hension des enjeux li√©s √† la tra√ßabilit√© des donn√©es (data lineage)\nUne connaissance m√©tier, notamment en marketing et relation client est n√©cessaire\nSavoir √™tre :\nGrande aisance √©crite et orale pour optimiser la compr√©hension et la communication avec les √©quipes\nPassion pour les chiffres et les statistiques\nOrientation business pour faire des recommandations pertinentes et actionnables\nAisance relationnelle pour emporter l‚Äôadh√©sion des interlocuteurs\nEsprit de synth√®se et analytique\nEsprit ouvert et comp√©tences transverses pour appr√©hender les probl√©matiques techniques et les restituer de fa√ßon compr√©hensible aux diff√©rents publics\nRigoureux, organis√© et r√©actif\nForce de proposition\nPrise de recul\nPourquoi nous rejoindre ?\nLa brigade\nUne Direction qui accorde une attention particuli√®re au bien √™tre des collaborateurs : Nous sommes Great Place to Work !\nLes ingr√©dients\nVous aurez tous les ustensiles n√©cessaires pour votre recette (ordinateur, t√©l√©phone portable professionnel etc.)\nUne r√©mun√©ration fixe + Prime annuelle li√©e √† vos objectifs + Prime de participation\nLes assaisonnements\nUne mutuelle familiale prise en charge √† 100% par le Groupe FBD\nL‚Äôacc√®s √† un Restaurant Interentreprises\n2 jours de t√©l√©travail par semaine sans condition d‚Äôanciennet√©\nDes locaux √† Roissy √† 200m du RER B et une annexe √† Paris 9√®me\nUn r√©seau social Entreprise pour vous mettre au courant et participer √† la vie d‚Äôentreprise\nLa carte\nNotre menu est compos√©e d‚Äôingr√©dients divers et vari√©s, ce qui en fait la richesse de ses plats.\nNous accordons une attention particuli√®re √† lutter contre toute formes de discriminations, raison pour laquelle nous avons adh√©r√© √† l'association A Comp√©tences Egales qui ≈ìuvre dans ce domaine.\nLa cerise sur le g√¢teau\nBoissons chaudes et fruits Bio √† disposition pour bien commencer la journ√©e !\nDes activit√©s tous les mois pour les collaborateurs, pr√©par√©s par notre service Com Interne + 2 √©v√®nements groupe par an.\nEn cuisine, le meilleur reste √† inventer ! Nous vous attendons !\nShow more\nShow less",
        "details": {
            "JobDetail": [],
            "TypeContract": "",
            "Salary": "",
            "Level": "Bac+5",
            "Experience": "5 an(s)"
        },
        "title": "data analyst",
        "skills": {
            "ProgLanguage": [
                "Python"
            ],
            "DataBase": [
                "SQL"
            ],
            "DataAnalytics": [
                "NumPy",
                "Pandas"
            ],
            "BigData": [
                "Hadoop",
                "Spark"
            ],
            "MachineLearning": [
                "Scikit-Learn"
            ],
            "DataVisualisation": [
                "Power BI",
                "Matplotlib",
                "Tableau"
            ],
            "DBMS": [
                "BigQuery",
                "Snowflake"
            ],
            "Automation": [
                "Airflow"
            ],
            "Other": [
                "Statistiques",
                "Big Data"
            ],
            "EnSoftSkils": [
                "Communication",
                "Collaboration"
            ]
        }
    },
    {
        "source": "LinkedIn",
        "company": "eXalt",
        "location": "Paris, √éle-de-France, France",
        "link": "https://fr.linkedin.com/jobs/view/data-analyst-at-exalt-3856622458?position=6&pageNum=7&refId=QYO6QFCk1HyZpy1IxSLXjw%3D%3D&trackingId=Iy5BukBI5QpMOdTFJaCkbw%3D%3D&trk=public_jobs_jserp-result_search-card",
        "description": "Descriptif du poste\nNous recherchons un.e\nData Analyst Confirm√© H/F\npour rejoindre notre communaut√© sur le\npilier Data Performance & Analytics.\nVos missions:\nCollecter, nettoyer et traiter les donn√©es provenant des diff√©rentes sources de donn√©es de l‚Äôentreprise\nAnalyser les donn√©es pour identifier des tendances, des corr√©lations et des anomalies.\nConcevoir et d√©velopper des tableaux de bord et des rapports pour pr√©senter les r√©sultats de mani√®re claire et concise.\nCollaborer avec les √©quipes clients pour comprendre leurs besoins et recommander des solutions adapt√©es.\nExplorer les r√©sultats des analyses en utilisant la Data Visualisation\nProfil recherch√©\nMa√Ætrise avanc√©e des langages de programmation (SQL, Python, R, etc.).\nBonnes connaissances en mod√©lisation de donn√©es\nExp√©rience pratique en dashboarding (Tableau, Power BI, Dataiku, Qlikview,etc.).\nFortes comp√©tences analytiques et capacit√© √† transformer les donn√©es brutes en insights exploitables.\nExp√©rience de travail en m√©thode Agile\nCapacit√© √† travailler de mani√®re autonome et en √©quipe.\nExcellentes comp√©tences en communication et en r√©solution de probl√®mes.\nMa√Ætrise de l‚Äôanglais (oral & √©crit dans un contexte international professionnel).\nD√©roulement des entretiens\nUn entretien RH avec Estelle, √† la suite duquel vous saurez tout (ou presque) d‚ÄôeXalt Value,\nUn entretien technique avec un Manager assorti d‚Äôun test technique sur un outil de Dataviz/Analyse de Donn√©es lors duquel vous aurez l‚Äôoccasion de d√©montrer vos talents mais aussi d‚Äôapprendre avant m√™me de dire oui,\nUn entretien final avec la Directrice Associ√©e ou le Directeur Op√©rationnel, pour finir de vous convaincre de nous rejoindre üòä\nVotre environnement eXalt√©:\nRejoindre\neXalt Value\n, c‚Äôest √©galement :\nUn environnement de travail Collaboratif favorisant les initiatives et projets transverses √† la Practice Data & IA (Lab IA, Data Hub, etc)\nUn collectif de consultants passionn√©s, s‚Äôint√©ressant aux tendances innovantes du secteur\nUne Practice de proximit√©, privil√©giant la mont√©e en comp√©tence de ses collaborateurs (formations, coachings, mentorats,etc)\nUn suivi individualis√© et de proximit√© par un.e Data Sales Manager r√©f√©rent du compte client, un.e Charg√©.e RH et un.e Practice Manager\nUne √©quipe sympa et dynamique, qui privil√©gie des moments de partage (s√©minaires, eXaltemps, meet-ups, d√©jeuners d‚Äô√©quipe,etc.)\nQui sont-ils ?\neXalt\nest un cabinet de conseil IT\nPure player Data\n& IA bas√© √† Paris (1er arrondissement).\nNotre offre s‚Äôarticule autour de 4 piliers r√©unis au sein d‚Äôune m√™me communaut√© pour un accompagnement √† 360¬∞ alliant une expertise technique et m√©thodologique √† une approche conseil m√©tier:\nData Gouvernance & Project\nData Engineering & Big Data\nData Performance‚ÄØ& Analytics\nData Science & IA\nFiliale du groupe eXalt cr√©√© en 2018,\nregroupant plus de\n950 collaborateurs en France\n(Paris, Lyon, Bordeaux, Lille, Nantes, Marseille)\net √† l‚Äôinternational\n(Colombie, Etats-Unis, Espagne, Belgique),\neXalt Value\nd√©montre une\nexpertise approfondie\ndans le domaine de la Data & IA et conseille les entreprises dans le d√©ploiement de leurs strat√©gies data-driven.\nB√©n√©ficiant de la renomm√©e et des relations client du groupe eXalt\n(1er dans la cat√©gorie Conseil & Audit au classement des Champions de la Croissance 2024), eXalt Value\nest en pleine croissance et regroupe aujourd‚Äôhui une communaut√© d‚Äôexpertise de plus de 60 collaborateurs en r√©gion parisienne.\nNos consultants interviennent sur d\nes projets d‚Äôenvergure stimulants\ndans divers secteurs d‚Äôactivit√©, Banque & Assurance, M√©dias, Transports, Retail, Tourisme, etc.\nShow more\nShow less",
        "details": {
            "JobDetail": [
                "Confirm√©"
            ],
            "TypeContract": "",
            "Salary": "",
            "Level": "",
            "Experience": null
        },
        "title": "data analyst",
        "skills": {
            "ProgLanguage": [
                "R",
                "Python"
            ],
            "DataBase": [
                "SQL"
            ],
            "DataAnalytics": [
                "R"
            ],
            "DataVisualisation": [
                "Power BI",
                "Tableau"
            ],
            "Other": [
                "Big Data"
            ],
            "EnSoftSkils": [
                "Communication"
            ]
        }
    },
    {
        "source": "LinkedIn",
        "company": "Allianz France",
        "location": "Paris, √éle-de-France, France",
        "link": "https://fr.linkedin.com/jobs/view/alternance-data-analyst-h-f-at-allianz-france-3888470171?position=7&pageNum=7&refId=QYO6QFCk1HyZpy1IxSLXjw%3D%3D&trackingId=XOY6FwwxT2NZ2yuOdnAuFA%3D%3D&trk=public_jobs_jserp-result_search-card",
        "description": "Nous vous proposons une mission de Data Analyst au sein de l‚ÄôUnit√© Data, Engagement Marketing, et Strat√©gie de la Direction Leads & Data.\nVos principales missions seront :\nContribution aux op√©rations r√©currentes de collecte, analyse et exploration des donn√©es clients\nParticipation aux validation des donn√©es du datamart connaissance client\nExtraction et mise √† disposition de donn√©es pour d‚Äôautres directions d‚ÄôAllianz France\nPrise en charge d‚Äô√©tudes statistiques et notamment sur la qualit√© des donn√©es √† partir du datamart\nCadre de la mission :\nVous serez int√©gr√© √† l‚Äô√©quipe Data Client situ√©e √† la D√©fense.\nVous serez accompagn√© par un encadrant, votre futur tuteur.\nVous disposerez de tous les outils de travail √† distance et aurez la possibilit√© de faire un jour de t√©l√©travail par semaine, une fois que vous serez autonome.\nProfil / Comp√©tences :\nIssu(e) d‚Äôune formation sup√©rieure dans un domaine li√© : Data/Math√©matiques/Statistiques, vous √™tes √† la recherche d‚Äôune alternance pour un BAC+4 ou BAC+5\nVous avez de solides bases en d√©veloppement SAS (SAS GUIDE) et en Python\nVous √™tes de nature curieuse et aimez prendre d√©couvrir / apprendre de nouvelles technologies\nVous avez une tr√®s bonne autonomie/rigueur/curiosit√© intellectuelle\nInformations pratiques :\nType de contrat : apprentissage ou contrat de professionnalisation.\nDate de d√©marrage : septembre 2024\nDur√©e : 12 mois\nLieu : La D√©fense (m√©tro Esplanade de la D√©fense)\n√ätre stagiaire chez Allianz France, c'est aussi b√©n√©ficier de...\nUne journ√©e de travail √† distance par semaine\nUn remboursement des frais de transport √† 50%\nUne r√©mun√©ration attractive\nAllianz est la 1√®re marque mondiale d‚Äôassurance pr√©sente dans 70 pays. Les #Allianzers, ce sont 9.000 salari√©s en France qui accompagnent leurs clients tout au long de leur vie, des collaborateurs qui associent innovation, performance et agilit√© pour relever des d√©fis permanents au quotidien.\nSe soucier de nos employ√©s, de leurs ambitions, de leurs r√™ves et de leurs d√©fis, voil√† ce qui fait de nous un employeur unique. Ensemble, nous pouvons construire un environnement o√π chacun se sent responsabilis√© et a la confiance n√©cessaire pour explorer, se d√©velopper et fa√ßonner un meilleur avenir pour nos clients et le monde qui nous entoure.\nEn qualit√© d‚Äôemployeur engag√©, Allianz reconna√Æt que sa force se trouve dans la diversit√© de ses collaborateurs. Nous sommes fiers de promouvoir l‚Äôint√©gration et l‚Äô√©galit√© des chances quel que soit le sexe, l‚Äô√¢ge, l‚Äôorigine, la nationalit√©, la religion, le handicap, ou l‚Äôorientation sexuelle de nos collaborateurs.\nAllianz, Let‚Äôs care for tomorrow !\nShow more\nShow less",
        "details": {
            "JobDetail": [],
            "TypeContract": "",
            "Salary": "",
            "Level": "Bac+5",
            "Experience": null
        },
        "title": "data analyst",
        "skills": {
            "ProgLanguage": [
                "Python"
            ],
            "Other": [
                "Statistiques"
            ]
        }
    },
    {
        "source": "LinkedIn",
        "company": "STATION F",
        "location": "Paris, √éle-de-France, France",
        "link": "https://fr.linkedin.com/jobs/view/data-analyst-at-station-f-3818685290?position=8&pageNum=7&refId=QYO6QFCk1HyZpy1IxSLXjw%3D%3D&trackingId=iayrIDeQMFcxT%2BAQ7DTLrg%3D%3D&trk=public_jobs_jserp-result_search-card",
        "description": "Job Description\nThis position is remote-friendly.\nüßöüèª\nOur Data team\nThe Data team at Joko is turning mountains of data into actionable insights for all the teams! The Data team is part of our Operations department led by Quentin, our COO, and our mission is to empower the company to make informed decisions.\nMore Specifically, The Team's Responsibilities Are\nData for Business: We create top-notch reports and tools, making it easy for teams to dive into data and excel in their decision-making.\nHelp our stakeholders with the best data stack: We load and transform data, automate reports, and continuously improve our data stack. This allows teams to use valuable insights built on robust and scalable foundations.\nSpread the data culture: At Joko, we have a strong engineering and tech culture across all teams, making it an ideal environment for our Data team to have a significant impact. We provide support and training on data tools to our stakeholders, and by closely collaborating with them, we ensure that our solutions align perfectly with their operational needs.\nüéØ What You Will Do\nAs a Data Analyst, you will have a cross-functional role and collaborate closely with teams to understand our data and develop insights.\nDeep-dive analyses: You will explore and analyse data to uncover trends, patterns, and potential issues that will help in the decision-making processes across all teams.\nReporting and Data Visualization: You will participate in creating content, such as dashboards and charts, using our data visualization tool. You will be involved in defining the report's content and constructing dashboards and charts to effectively communicate data-driven findings to stakeholders.\nData loading and transformation: You will be involved in loading and transforming the data as we have a ‚Äúfull stack‚Äù approach in Data at Joko. Of course, you will get some help on Data Engineering parts but you will be involved in the entire lifecycle of our data.\nInteractions with stakeholders: You will work hand-in-hand with them to understand their needs, collect their feedback, and also evangelize data usage to help them make smarter choices.\nContinuous Learning and Improvement: As \"never stop learning\" is one of our values, you will grow along the way and learn how to use analytical methods and the different tools that we use (and will use) in our data stack.\nPreferred Experience\nExperience: You have 1-3y of professional experience in data analysis (relevant internships can count).\nEducation: You graduated from an engineering or business school (or equivalent).\nMindset: You have an entrepreneurial mindset, you like challenges, you welcome feedback and you are willing to get better everyday to reach excellence.\nProblem-solving & Analytical skills: You love solving complex problems and analyzing data.\nCoding knowledge: Mastering SQL and Python is not mandatory, as you can still learn when joining, but it's a plus.\nBusiness acumen: You can understand the needs of your business stakeholders and get the big picture of how the business is running.\nCommunication: You know how to present your conclusions clearly and synthetically (written and oral).\nLanguages: You are fluent in English, both written and spoken.\nRecruitment Process\n15-min call with the Hiring Manager\n45-min personality interview with two team members\nA case study followed by a 45-min debrief\n45-min Founders interview\nReference calls\nYou might also be invited to meet other team members at the office for a coffee or a drink!\nAdditional Information\nContract Type: Full-Time\nLocation: Paris\nPossible full remote\nShow more\nShow less",
        "details": {
            "JobDetail": [
                "Remote",
                "Full"
            ],
            "TypeContract": "",
            "Salary": "",
            "Level": "",
            "Experience": null
        },
        "title": "data analyst",
        "skills": {
            "ProgLanguage": [
                "Python"
            ],
            "DataBase": [
                "SQL"
            ],
            "Collaboration": [
                "Teams"
            ],
            "EnSoftSkils": [
                "Communication"
            ]
        }
    },
    {
        "source": "LinkedIn",
        "company": "Voodoo",
        "location": "Paris, √éle-de-France, France",
        "link": "https://fr.linkedin.com/jobs/view/data-analyst-at-voodoo-3902465580?position=9&pageNum=7&refId=QYO6QFCk1HyZpy1IxSLXjw%3D%3D&trackingId=WW6m%2FNzPWPqSaavHT3oVxg%3D%3D&trk=public_jobs_jserp-result_search-card",
        "description": "Team\nThe Engineering & Data team builds innovative tech products and platforms to support the impressive growth of their gaming and consumer apps which allow Voodoo to stay at the forefront of the mobile industry. The Engineering & Data team plays a key role in Voodoo‚Äôs long-term strategy. It enables Voodoo to both accelerate product diversification and provide a state of the art growth-engine to distribute and scale our games. They create innovative solutions that drive growth with a pragmatic approach, ranging from simple searching to complex machine learning systems.\nWe are looking for a Data Analyst who is deeply passionate about data-driven decisions, transforming raw data into clear actionable business insights, and who is constantly driving themselves and the team towards completing the next challenge.\nBy joining this team, you will have a strong impact on the business and a unique opportunity to reach hundreds of millions of users with your insights and recommendations.\nThe Analytics Team works closely with Voodoo‚Äôs game studios. We specialize in crafting analytical tools that dissect gaming behavior, offering crucial insights to our studio game analysts. Our proficiency in analyzing gaming behavior equips us to devise and implement innovative solutions. These solutions fuel growth and fortify the success of Voodoo‚Äôs diverse gaming portfolio.\nRole\nWork on end-to-end data projects in collaboration with internal departments, aiming to enhance our games and boost both monetization and player retention.\nBuild and manage robust data pipelines to align with ever-evolving business needs, ensuring optimal architecture support.\nDevelop dashboards and reports to foster company-wide comprehension of key business metrics and player experiences.\nAnalyze large, complex datasets representing the behavior of millions of online and mobile game players, delivering actionable recommendations that shape game features, economies, and future product roadmaps.\nProfile\nYou possess substantial experience in analytical roles, ideally within a web or mobile company or the online gaming industry.\nYou are highly skilled in SQL and have a proven track record of building production-ready pipelines that handle large and complex data sets.\nYou have practical experience with Tableau, and can create dashboards that are shared company-wide, facilitating data-driven decision-making across departments.\nYou enjoy working in a fast-paced environment and are able to balance the tradeoff between time-consuming development and rapid results.\nA BA/B.Sc degree in Statistics, Math, Engineering, Economy, or other quantitative fields is mandatory for this role.\nAdvanced knowledge of statistical tools and models will be considered a significant advantage.\nBenefits\nCompetitive salary upon experience\nSwile Lunch voucher\nGymlib (100% borne by Voodoo)\nPremium healthcare coverage SideCare, for your family is 100% borne by Voodoo\nChild day care facilities (Les Petits Chaperons rouges)\nWellness activities in our Paris office\nUnlimited vacation policy\nRemote days\nVoodoo just won the award for Best Office Space in France\nShow more\nShow less",
        "details": {
            "JobDetail": [
                "Remote"
            ],
            "TypeContract": "",
            "Salary": "100",
            "Level": "",
            "Experience": null
        },
        "title": "data analyst",
        "skills": {
            "DataBase": [
                "SQL"
            ],
            "DataVisualisation": [
                "Tableau"
            ],
            "Other": [
                "Machine Learning"
            ],
            "EnSoftSkils": [
                "Collaboration"
            ]
        }
    },
    {
        "source": "LinkedIn",
        "company": "AccorInvest",
        "location": "√âvry, √éle-de-France, France",
        "link": "https://fr.linkedin.com/jobs/view/hr-data-analyst-h-f-cdd-at-accorinvest-3883853598?position=10&pageNum=7&refId=QYO6QFCk1HyZpy1IxSLXjw%3D%3D&trackingId=RcogLii3ygNT3HfutMbu9g%3D%3D&trk=public_jobs_jserp-result_search-card",
        "description": "Dans le cadre d'un remplacement partiel de cong√© maternit√©, d√®s juin 2024, vous ferez partie de\nl‚Äô√©quipe HR Data / Contr√¥le de Gestion Sociale. Vous aurez pour principales missions de collecter, analyser et synth√©tiser les donn√©es sociales. Pour r√©aliser un travail de qualit√©, vous devrez aussi contr√¥ler la coh√©rence et la fiabilit√© de ces donn√©es.\nVos principales missions seront:\nAssurer la production et l‚Äôanalyse du HR Dashboard Europe du Sud\nAssurer la production et l‚Äôanalyse des rapports l√©gaux France (BDES : Bilan Social, Index, SSCT, Rapport de Situation Compar√©e)\nR√©pondre aux demandes mensuelles, trimestrielles et ponctuelles des CSE et de tous les clients internes\nProduction et contr√¥le de l‚Äôensemble des documents li√©es aux expertises CSE\nR√©aliser des simulations de co√ªts li√©s √† la politique sociale\n√ätre garant de la qualit√© des donn√©es et des process et alerter de toutes d√©rives sur les process data et r√©sultats de KPIs\n√ätre capable de vulgariser les analyses et transmettre des informations compr√©hensibles pour aider √† la prise de d√©cision.\nG√©rer l‚Äôadministration des acc√®s et publication des donn√©es BDES\nVeiller √† ce que les donn√©es num√©riques des collaborateurs soient prot√©g√©es et utilis√©es en parfaite conformit√© avec les r√®glementations en vigueur\nPiloter une partie de l‚Äôautomatisation des productions pour s√©curiser et fiabiliser les rapports.\nProfil et Comp√©tences:\nFormation :\nMaster 2 RH ou Contr√¥le de Gestion.\nExp√©rience professionnelle requise :\n3ans min. d‚Äôexp√©rience en Contr√¥le de Gestion Sociale, HR data analyst, Data scientist.\nSavoir faire:\nExcel\nApp√©tence pour les chiffres\nAisance avec les syst√®mes d‚Äôinformations\nRigueur dans la manipulation des donn√©es\nEsprit d‚Äôanalyse et de synth√®se\nGestion des priorit√©s et des d√©lais\nAnglais\nConnaissance GXP, HRI, Power BI et Oracle serait un plus\nSavoir √™tre:\nAutonomie\nEsprit d‚Äô√©quipe\nR√©actif\nInt√©r√™t/Curiosit√© sur les sujets RH\nRespect de la confidentialit√© des donn√©es\nLe poste est √† pourvoir d√®s juin 2024 en Contrat √† Dur√©e D√©termin√©e.\nInformation sur le traitement des donn√©es personnelles\nLorsqu‚Äôune personne soumet sa candidature √† SGHI, cette soci√©t√© SGHI traite certaines de ses donn√©es pour √©valuer et g√©rer la candidature. En notre qualit√© de responsable de traitement de vos donn√©es personnelles, nous veillons √† nous conformer √† la l√©gislation relative √† la protection des donn√©es personnelles (notamment √† la loi du 6 janvier 1978 modifi√©e relative √† l'informatique, aux fichiers et aux libert√©s ainsi qu‚Äôau r√®glement europ√©en n¬∞2016-679 du 27/04/2016 sur la protection des donn√©es (R√®glement G√©n√©ral sur la Protection des Donn√©es ou ¬´ RGPD ¬ª)). Par ailleurs, nous pouvons √™tre amen√©s √† contacter un ou plusieurs des anciens employeurs du candidat. Nous pouvons √©galement proposer au candidat de proc√©der √† un questionnaire de personnalit√© ; il est pr√©cis√© que les r√©ponses √† ce questionnaire n‚Äôentraineront pas de d√©cision automatis√©e concernant le recrutement.L‚Äôensemble des informations relatives au traitement des donn√©es personnelles des candidats et notamment √† l‚Äôexercice de leurs droits d‚Äôacc√®s, d‚Äôopposition, de rectification, de suppression, est disponible dans notre\nPolitique deprotection des donn√©es personnelles des collaborateurs\n.\nShow more\nShow less",
        "details": {
            "JobDetail": [],
            "TypeContract": "",
            "Salary": "",
            "Level": "",
            "Experience": "3 an(s)"
        },
        "title": "data analyst",
        "skills": {
            "DataVisualisation": [
                "Power BI"
            ]
        }
    },
    {
        "source": "LinkedIn",
        "company": "Aubay",
        "location": "Paris, √éle-de-France, France",
        "link": "https://fr.linkedin.com/jobs/view/consultant-data-power-bi-f-h-at-aubay-3621584441?position=1&pageNum=10&refId=tn2QJQESk9ttg00nH%2FdA7g%3D%3D&trackingId=wnFdgAH1t6J9nGP4Lb8VpQ%3D%3D&trk=public_jobs_jserp-result_search-card",
        "description": "Rejoins une Team Data du tonnerre ‚ö° et une communaut√© Data driven d‚Äôexp√©rience avec des experts qui analysent, cr√©ent des outils de pilotage, valorisent les visuels et accompagnent des clients de tous secteurs d‚Äôactivit√© pour booster leurs performances en Modern Business Intelligence (BI) et en Data Viz.\nAubay renforce ses √©quipes Data et recherche des consultants Power BI pour intervenir sur des projets de d√©veloppement ou de refonte de rapports et de tableaux de bords bas√©s sur des solutions BI legacy.\nTon quotidien en tant que Consultant Data Power BI :\nParticipation aux ateliers de cadrage et d‚Äôexpression de besoins avec les m√©tiers\nPr√©paration des donn√©es avec Power Query et Power BI Dataflow\nMod√©lisation de donn√©es performants\nProduction et mise √† disposition de rapports avec Power BI Desktop et Service\nAccompagnement des m√©tiers au cours de la phase de recette des rapports et dans l'adoption des principes de Data Viz et de la solution Power BI\nTes qualifications :\nSoft skills :\nTu disposes d‚Äôune formation niveau BAC+5 (Master 2 ou √©cole d‚Äôing√©nieur) sp√©cialis√©e en informatique (id√©alement d‚Äôune fili√®re orient√©e BI / Data Analytics) et tu as d√©j√† une premi√®re exp√©rience significative (2 ans ou plus) dans la mise en ≈ìuvre de la solution Power BI\nTu sais ce qu‚Äôimplique l‚Äôexpression ¬´ garbage in ‚Äì garbage out ¬ª dans un contexte Data. Tu es donc vigilant √† la qualit√© des donn√©es que tu manipules et force de proposition pour identifier et mettre en ≈ìuvre des actions curatives / correctives p√©rennes\nTes qualit√©s de communication orale et √©crite te permettent d‚Äô√©changer et collaborer de mani√®re efficace aussi bien avec des profils m√©tiers / fonctionnels qu‚Äôavec des profils techniques\nTu es soucieux de la qualit√© visuelle de tes livrables (documents, tableaux de bords, etc.) afin de garantir une exp√©rience utilisateur r√©ussie\nHard skills :\nTu connais les langages SQL, DAX, M et Python\nTu ma√Ætrises les concepts de mod√©lisation de donn√©es\nLes plus qui te feront sortir du lot :\nTu as obtenu la certification ¬´ Microsoft Power BI Data Analyst Associate ¬ª (DA-100 / PL-300)\nConnaissance des autres solutions de la Power Platform de Microsoft et notamment Power Automate\nTu as d√©j√† eu une exp√©rience un service cloud type Azure, AWS ou GCP\nTu sais g√©rer un projet en mode agile\nTu es √† l‚Äôaise en anglais √† l‚Äôoral comme √† l‚Äô√©crit\nTu crois aux valeurs d‚Äôexcellence, d‚Äôefficacit√©, de bienveillance, d‚Äôintraprenariat et de responsabilit√©.\nPourquoi nous rejoindre ?\nDes missions et projets dans le domaine Modern BI & Analytics en nombre et dans des secteurs vari√©s (Banque, Assurance, Telecom, Industrie, ‚Ä¶) qui permettent √† nos collaborateurs de monter en comp√©tences et de devenir des experts Data reconnus\nDe l‚Äôapprentissage en continu avec des formations et des certifications sur les technologies Data de pointe\nDes experts Data mobilisables pour accompagner et soutenir techniquement les collaborateurs sur leurs projets\nDes communaut√©s de savoir-faire Data proposant de mani√®re r√©guli√®re aux collaborateurs d‚ÄôAubay du contenu et des √©v√®nements de partage (webinar, meetup/afterwork, BBL, ‚Ä¶) sur les th√©matiques suivantes : Data Engineering, Modern BI & Analytics, Data Science/IA, Data Platform & Architecture, ‚Ä¶\nTa carri√®re chez Aubay\nTu auras la possibilit√© de certifier tes comp√©tences et de d√©velopper tes connaissances sur diff√©rentes solutions Modern BI & Data Viz comme Power BI, Tableau, QlikSense ou Preset.io\nTu rejoindras la BU d‚Äôexcellence Data et √©volueras au sein d‚Äôun environnement humain et professionnel de haut niveau. Tu profiteras d‚Äôun management sur-mesure pour t‚Äôaccompagner dans ta trajectoire de carri√®re\nAu sein de la BU d‚Äôexcellence, de multiples perspectives s‚Äôoffriront √† toi, de devenir :\nLead en √©tant un r√©f√©rent aupr√®s de nos clients et des collaborateurs de la communaut√© Modern BI & Analytics\nChampion en repr√©sentant Aubay aupr√®s de nos partenaires\nHead en prenant la t√™te d‚Äôune practice (d√©veloppement business, recrutement, management de collaborateurs, d√©finition de la strat√©gie et animation de la communaut√© au sein du groupe Aubay, etc.)\nBesoin d‚Äôen savoir plus sur le processus de recrutement ?\nUn √©change macro\nau niveau RH\navec\nDoriane\nUn entretien\ntechnique\navec\nClaudio\n, un de nos r√©f√©rents techniques\nUn √©change\nmanag√©rial\navec\nle Directeur de la BU Modern BI & Data\nA savoir que l‚Äôordre des √©tapes peut varier selon tes envies (ex : √©change manag√©rial avec l‚Äô√©change technique)\nAubay encourage la diversit√© sous toutes ses formes et garantit l'√©galit√© des chances √† tous les candidats. Tous nos postes sont ouverts aux personnes en situation de handicap et nous proposons tous les am√©nagements n√©cessaires.\nShow more\nShow less",
        "details": {
            "JobDetail": [],
            "TypeContract": "",
            "Salary": "",
            "Level": "Bac+5",
            "Experience": "2 an(s)"
        },
        "title": "consultant data",
        "skills": {
            "ProgLanguage": [
                "Python"
            ],
            "DataBase": [
                "SQL"
            ],
            "DataVisualisation": [
                "Power BI",
                "Tableau"
            ],
            "CloudComputing": [
                "GCP",
                "AWS",
                "Azure"
            ],
            "Other": [
                "Cloud"
            ],
            "EnSoftSkils": [
                "Communication"
            ]
        }
    },
    {
        "source": "LinkedIn",
        "company": "Artefact",
        "location": "Paris, √éle-de-France, France",
        "link": "https://fr.linkedin.com/jobs/view/senior-data-analyst-paris-at-artefact-3435228972?position=2&pageNum=10&refId=tn2QJQESk9ttg00nH%2FdA7g%3D%3D&trackingId=Gb3m8CHu%2BrgF70zxy%2FCNYQ%3D%3D&trk=public_jobs_jserp-result_search-card",
        "description": "Who We Are\nArtefact is a new generation of data service provider, specialised in data consulting and data-driven digital marketing.\nOur purpose?\nEvery day we boost our clients‚Äô data transformation into business impact across the entire value chain of organisations.\nOur strength?\nOur data services stand on double expertise: the combination of Artificial Intelligence and the business prowess acquired from our customers around the world, such as AccorHotels, Orange, Carrefour, Engie, Samsung, L'Or√©al, Nissan...\nArtefact‚Äôs success comes from a unique mix of company assets: cutting-edge data technologies, agile methodologies for fast delivery, cohesive teams assembling the finest business consultants, data analysts, data scientists, data engineers, and digital marketing experts.\nArtefact Is\n13 offices in Paris, London, Shanghai, Dubai...\n900 employees\n4 practices: Data Consulting, Data Marketing, Activation and Creation\nWhat you will be doing: Key responsibilities\nAs a Senior Data Analyst, Your Role Will Encompass\nConducting projects to accompany the transformation of your clients‚Äô businesses through the effective collection, processing, and visualisation of data\nExtracting valuable insights from our clients‚Äô marketing-related data sources.\nDesigning dashboards for marketing decision-making while taking into account the business needs\nAccompanying our clients in the conception and implementation of data architectures and data pipelines, from collection to monitoring.\nActively contributing to the expertise level and competencies of the Data & Analytics team\nClosely collaborate with the other divisions (Media & Activation, Creation, Consulting, Data Science and Data Engineer) to provide comprehensive services to your clients\nBeing a great tech role model\nDemonstrating the skill and credibility required to ensure the success of our clients‚Äô initiatives\nResearching and developing new technical approaches to address problems efficiently\nStaying up-to-date on developments within the industry, sharing best practices and actively contributing to Artefact‚Äôs institutional knowledge\nEmbodying Artefact‚Äôs values and inspiring others to do the same\nQualifications: Education & experience required\nHaving an academic level of education (Bachelor or Master), in a data-driven working environment, you have experience or have knowledge in :\nA minimum of 3 year of work experience in a data-driven working environment\n1 or more data collection (Google Analytics, Adobe Analytics, SQL database, CRM database, transactional data)\n1 or 2 programming languages among SQL, Python and/or R.\n1 or more Data visualisation tool (Tableau, Data Studio, Dataviz, R / Python dataviz libraries, ...)\nIn addition, you have the knowledge in one or more of the following technologies:\nGoogle Cloud Platform resources (Big Query, Google Cloud Storage) or its equivalent in Azure or AWS\nYou know how to connect to an API through the knowledge of the different authentication method (OAuth, HTTP Basic, API key)\nAdvertising tool, linked to tracking and/or analytics in a marketing context (Google Analytics, Adobe Analytics, DMP, DSP, Adservers, DV 360...)\nETL tool (Airflow, Dataiku, Dataflow, Dataprep...)\nWeb application (R-Shiny, Python Flask) that you have industrialized\nIdeally You Have\nKnowledge of statistics\nKnowledge of machine learning and data engineering\nWhat We Are Looking For\nA Doer: you get things done and inspire your team to do the same\nAn Analyst: you LOVE data and think every company should take their decisions based on facts\nA Pragmatist: you have a no-nonsense mindset that seeks for practical and realistic solutions\nA Mentor: your clients and colleagues naturally seek you out for advice\nAn Adventurer: you‚Äôre an entrepreneur constantly looking for business opportunities\nWhy you should join us\nArtefact is the place to be: come and build the future of marketing\nProgress: every day offers new challenges and new opportunities to learn\nCulture: join the best team you could ever imagine\nEntrepreneurship: you will be joining a team of driven entrepreneurs. We won‚Äôt give up until we make a huge dent in this industry!\nCome join us!\nShow more\nShow less",
        "details": {
            "JobDetail": [
                "Senior"
            ],
            "TypeContract": "",
            "Salary": "",
            "Level": "",
            "Experience": null
        },
        "title": "data analyst",
        "skills": {
            "ProgLanguage": [
                "R",
                "Python"
            ],
            "DataBase": [
                "SQL"
            ],
            "DataAnalytics": [
                "R"
            ],
            "MachineLearning": [
                "Orange"
            ],
            "DataVisualisation": [
                "Tableau"
            ],
            "CloudComputing": [
                "AWS",
                "Google Cloud Platform",
                "Azure"
            ],
            "DBMS": [
                "Big Query"
            ],
            "Automation": [
                "Airflow"
            ],
            "Collaboration": [
                "Teams"
            ],
            "Other": [
                "Machine Learning",
                "Cloud"
            ]
        }
    },
    {
        "source": "LinkedIn",
        "company": "Artefact",
        "location": "Paris, √éle-de-France, France",
        "link": "https://fr.linkedin.com/jobs/view/data-analyst-specialist-entry-level-at-artefact-3072340205?position=3&pageNum=10&refId=tn2QJQESk9ttg00nH%2FdA7g%3D%3D&trackingId=%2F%2BAExzq8YRDeWurxr8thNg%3D%3D&trk=public_jobs_jserp-result_search-card",
        "description": "Who We Are\nArtefact is a new generation of a data service provider, specialised in data consulting and data-driven digital marketing.\nOur purpose?\nEvery day we boost our clients‚Äô data transformation into business impact across the entire value chain of organisations.\nOur strength?\nOur data services stand on a double expertise: the combination of Artificial Intelligence and the business prowess acquired from our customers around the world, such as AccorHotels, Orange, Carrefour, Engie, Samsung, L'Or√©al, Nissan...\nArtefact‚Äôs success comes from a unique mix of company assets: cutting-edge data technologies, agile methodologies for fast delivery, cohesive teams assembling the finest business consultants, data analysts, data scientists, data engineers, and digital marketing experts.\nArtefact is looking for a Data Analyst Specialist for our clients, in order to reinforce our multiple data marketing offers.\nArtefact Is\n13 offices in Paris, London, Shanghai, Dubai...\n900 employees\n4 practices: Data Consulting, Data Marketing, Activation and Creation\nWhat you will be doing: Key responsibilities\nAs a Data Analyst Specialist, Your Role Will Encompass\nCreating and implementing a tagging plan, using analytics tools according to the template and basic configuration\nPerforming audit reports and creating web analysis studies (client journey, landing page, channels ROI) by defining and monitoring different KPIs and PIs\nMonitoring different activities that can be impacted by web analytics (Activation, UX/CRO, tracking, trafficking).\nActively contributing to the expertise level and competencies of the Data & Analytics team\nClosely collaborate with the other divisions (Media & Activation, Creation, Consulting, Data Science and Data Infrastructure) to provide data-driven marketing services to your clients\nQualifications: Education & experience required\nWith 1-2 years of experience in the digital marketing environment, preferably with big client accounts, you have:\nAcademic level of education (Bachelor or Master)\nKnowledge in working with a tagging plan, either by optimising an existing setup by solving problems and challenging existing tagging plan, or draft and set-up a tagging plan according to the template.\nKnowledge of web analytics platforms like Google Analytics, Adobe Analytics, etc.\nFamiliarity with tag management systems like Google Tag Manager, Tag Commander, Tealium IQ Tag Management, Launch/DTM etc.\nPreferably, You Also Have\nGood knowledge of web-related technologies (JavaScript, CSS and HTML)\nOptionally, familiarity with the Data Management Platforms like BlueKai, Krux, Ysance, Weborama, Adobe Audience Manager, Tealium Audience Streams, etc.\nKnowledge in a website optimization tools like hotjar, Google Optimize360, Content Square, AB Tasty etc. is appreciated.\nKnowledge in customer journey optimization / CRO is appreciated.\nWhat We Are Looking For\nA Doer: you get things done and inspire your colleagues to do the same\nAn Analyst: you LOVE data and think every company should take their decisions based on facts\nA Pragmatist: you have a no-nonsense mindset that seeks for practical and realistic solutions\nA Mentor: your clients and teams naturally seek you out for advice\nAn Adventurer: you‚Äôre an entrepreneur constantly looking for business opportunities\nWhy you should join us\nArtefact is the place to be: come and build the future of marketing\nProgress: every day offers new challenges and new opportunities to learn\nCulture: join the best team you could ever imagine\nEntrepreneurship: you will be joining a team of driven entrepreneurs. We won‚Äôt give up until we make a huge dent in this industry!\nCome join us!\n#fr\nShow more\nShow less",
        "details": {
            "JobDetail": [],
            "TypeContract": "",
            "Salary": "",
            "Level": "",
            "Experience": null
        },
        "title": "data analyst",
        "skills": {
            "MachineLearning": [
                "Orange"
            ],
            "Collaboration": [
                "Teams"
            ]
        }
    },
    {
        "source": "LinkedIn",
        "company": "GROUPE ADF",
        "location": "Vitrolles, Provence-Alpes-C√¥te d'Azur, France",
        "link": "https://fr.linkedin.com/jobs/view/data-analyst-f-h-at-groupe-adf-3906894523?position=4&pageNum=10&refId=tn2QJQESk9ttg00nH%2FdA7g%3D%3D&trackingId=nvEl2SXyoFq0DHIN7d1rIw%3D%3D&trk=public_jobs_jserp-result_search-card",
        "description": "Description\nActeur majeur en prestations de maintenance et services connexes aux industries et fortement implant√© √† l‚Äôinternational, le Groupe ADF (3900 collaborateurs / 540 millions de CA) propose √† ses clients des solutions de maintenance ax√©es sur l'am√©lioration continue et l'optimisation de ses √©quipements, ainsi que des installations industrielles cl√©s en main.\nDans le cadre de son d√©veloppement la Direction des Achats du Groupe ADF, recrute son/sa futur(e) Analyste Achat (F/H).\nMission\nAnalyse, reporting et suivi des KPI\n√âlaborer et suivre les indicateurs cl√©s de performance (KPI) pour √©valuer la performance de la Direction des Achats\nAnalyser et communiquer par des tableaux de bord visuels pour pr√©senter les r√©sultats aux diff√©rents responsables achats\nApprofondir certaines d√©rives constat√©es avec des reportings p√©riodiques sur des sujets cibl√©s\nSuivre, animer et co piloter les plans d‚Äôactions initi√©s dans le cadre de la strat√©gie Achat du Groupe\nOptimisation des processus & applications\nCollaborer avec les √©quipes internes pour identifier des possibilit√©s d'efficacit√© et de r√©duction des co√ªts\nProposer des recommandations bas√©es sur les donn√©es pour am√©liorer les processus existants\nAssurer un r√¥le de r√©f√©rent pour certains projets transverses impliquant l‚Äôenvironnement applicatif achat.\nProfil\nDipl√¥m√©(e) d‚Äôune √©cole de Commerce, vous disposez d‚Äôune premi√®re exp√©rience dans l‚Äôanalyse des processus achats d‚Äôun Groupe ainsi que dans la gestion d‚Äôapplications.\nLa maitrise d‚ÄôExcel est requise.\nLa connaissance d‚Äôoutils de gestion de base de donn√©es (Access) et de reporting (Power BI) sera un plus √† votre candidature.\nLe d√©veloppement du Groupe √† l‚Äôinternational impliquera certains √©changes en Anglais.\nVotre polyvalence et votre autonomie ainsi que votre app√©tence √† la prise d‚Äôinitiative seront des qualit√©s indispensables pour la r√©ussite de votre mission !\nAvantages\nAccord int√©ressement / participation\nConvention collective M√©tallurgie / Syntec\nAvantages CSE (ch√®ques cadeaux, tarifs pr√©f√©rentiels, ch√®ques vacances, etc)\nAccord QVT\nMutuelle\nPossibilit√© de t√©l√©travail en fonction du poste\nPasserelle m√©tiers (mobilit√© interne et internationale, cooptation, etc)\nPrime de cooptation\nApplication de covoiturage, Klaxit\nCentre de formation interne, OTI\nTitre Restaurant\nInt√©ress√©(e) par notre proposition ?\nTransmettez-nous votre candidature !\nNotre service recrutement et nos experts techniques l'√©tudieront avec attention.\nSi elle est retenue, nous vous contacterons pour un premier √©change t√©l√©phonique puis pour un entretien avec un expert technique.\nDans le cadre de sa politique diversit√©, Groupe ADF √©tudie, √† comp√©tences √©gales, toutes candidatures dont celles de personnes en situation de handicap.\nShow more\nShow less",
        "details": {
            "JobDetail": [],
            "TypeContract": "",
            "Salary": "",
            "Level": "",
            "Experience": null
        },
        "title": "data analyst",
        "skills": {
            "DataVisualisation": [
                "Power BI"
            ],
            "EnSoftSkils": [
                "Initiative"
            ]
        }
    },
    {
        "source": "LinkedIn",
        "company": "CubeRH",
        "location": "Tourcoing, Hauts-de-France, France",
        "link": "https://fr.linkedin.com/jobs/view/data-analyst-h-f-cdi-at-cuberh-3840635774?position=5&pageNum=10&refId=tn2QJQESk9ttg00nH%2FdA7g%3D%3D&trackingId=wVZSg%2FbQFHyd%2BXSVzxZMLQ%3D%3D&trk=public_jobs_jserp-result_search-card",
        "description": "La soci√©t√© :\nNotre client est une entreprise de services sp√©cialis√©e dans le domaine de la Data, √† √©chelle humaine, qui se distingue par son expertise d√©velopp√©e autour de trois axes principaux : la Data g√©n√©raliste, l'outil de reporting Power BI et la solution cloud Microsoft Azure.\nAu c≈ìur de sa mission, l'√©co-responsabilit√© constitue un pilier essentiel. En adoptant cette approche, elle offre une vision compl√®te et int√©gr√©e de la gestion des donn√©es. Gr√¢ce √† une √©quipe de consultants experts, elle simplifie les op√©rations, optimise les donn√©es et les valorise, offrant ainsi √† ses clients une opportunit√© de progression.\nEn pleine croissance, l'entreprise recherche √† agrandir son √©quipe avec un Data Analyst H/F.\nSi vous recherchez une √©quipe qui met en avant votre d√©veloppement professionnel et votre √©panouissement, vous √™tes au bon endroit !\nL'objectif de la mission :\nAnalyser les probl√©matiques m√©tier et les synth√©tiser\nManipuler la donn√©e, l'exploiter et l'interpr√©ter pour en d√©gager des observations business utiles\nCr√©er des dashboards et rapports afin d'obtenir des √©l√©ments de d√©cision\nMettre en place des kpis de performances permettant de donner une vision coh√©rente des r√©sultats aux diff√©rentes √©quipes m√©tiers\nDevenir un r√©f√©rent technique sur l'outil de reporting Power BI\nPrendre part au d√©veloppement de la startup avec tes id√©es innovantes\nLes conditions de travail :\nUne mutuelle avantageuse et des tickets restaurants\nRemboursement int√©gral de vos frais de transports en commun\nDes trottinettes √©lectrique et des v√©los √† disposition\nPrimes (notamment de cooptation)\nT√©l√©travail\nVotre profil :\nMaitrise du SQL\nConnaissance analytiques et statistiques\nBonne maitrise de Power BI\nConnaissance du cloud\nConnaissance d'outils d'analyse de donn√©es (SAS, R, etc.) ainsi que de python qui serait un plus.\nProcess entretien :\nDeux premiers √©changes avec le cabinet Cube RH;\nEntretiens avec le client (RH et avec le manager).\nShow more\nShow less",
        "details": {
            "JobDetail": [],
            "TypeContract": "",
            "Salary": "",
            "Level": "",
            "Experience": null
        },
        "title": "data analyst",
        "skills": {
            "ProgLanguage": [
                "R",
                "Python"
            ],
            "DataBase": [
                "SQL"
            ],
            "DataAnalytics": [
                "R"
            ],
            "DataVisualisation": [
                "Power BI"
            ],
            "CloudComputing": [
                "Azure"
            ],
            "Other": [
                "Statistiques",
                "Cloud"
            ]
        }
    },
    {
        "source": "LinkedIn",
        "company": "Boursorama",
        "location": "Boulogne-Billancourt, √éle-de-France, France",
        "link": "https://fr.linkedin.com/jobs/view/data-analyst-marketing-boursorama-h-f-at-boursorama-3854191406?position=6&pageNum=10&refId=tn2QJQESk9ttg00nH%2FdA7g%3D%3D&trackingId=%2FMChFsGgtUuLBs7azXCy5w%3D%3D&trk=public_jobs_jserp-result_search-card",
        "description": "23000UHD\nVos missions au quotidien\nAu sein de la Direction Marketing Epargne, et en bin√¥me avec un autre Data Analyst, votre mission sera de suivre l‚Äôactivit√© Marketing et Commerciale en exploitant les diff√©rentes sources de donn√©es.\nPour mener votre mission √† bien, vous pourrez vous appuyer sur l‚Äôexpertise des autres Data Analysts de la communaut√© Data Marketing.\nExpertise en Dashboarding :\nConcevoir, produire et faire √©voluer les tableaux de bord de l‚Äôactivit√© commerciale et marketing en Datavisualisation (Tableau)\nProduire des insights pertinents pour tirer des enseignements, lever des alertes dans le cadre de certains reportings d‚Äôactivit√©s √† forte valeur ajout√©e\nInterpr√©ter les r√©sultats en regard des actualit√©s Business\nSuivre des actions commerciales :\nR√©aliser le ciblage dans le cadre d‚Äôactions commerciales/ campagnes marketing en lien avec les autres √©quipes marketing : appropriation du contexte et des enjeux, challenge des demandeurs m√©tier\nEffectuer des bilans des campagnes marketing / d‚Äôop√©rations et produire des enseignements sur la performance des campagnes et des recommandations pour des futures actions marketing\nConnaissance clients :\nR√©aliser des √©tudes statistiques adhoc sur des probl√©matiques marketing (acquisition, fid√©lisation, lancement de produits/services ‚Ä¶)\nComprendre les enjeux business et l‚Äôimpact de son travail sur la prise de d√©cision\nContribuer √† la construction et l‚Äô√©volution des outils de fid√©lisation : segmentation client, relances automatis√©es, gestion des moments de vie ‚Ä¶\nEtudier la performance de notre recrutement pour optimisation (analyse des tunnels de transformation, analyse des canaux d‚Äôacquisition ‚Ä¶)\nR√©aliser des analyses li√©es √† des probl√©matiques d‚Äôautres Directions\nEt si c‚Äô√©tait vous ?\nDe formation Bac +4/5 en statistiques, vous justifiez d‚Äôune premi√®re exp√©rience r√©ussie dans ce domaine ‚Äì alternance y compris.\nVous avez une bonne compr√©hension des probl√©matiques marketing et de l‚Äò√©cosyst√®me data dans le digital (DMP, web analytics, ...)\nVous ma√Ætrisez SAS (langage macro), Excel, Powerpoint et un outil de DataVisualisation (id√©alement Tableau). La connaissance du langage Python est un plus.\nVotre capacit√© d‚Äôanalyse, votre bon relationnel et votre capacit√© √† g√©rer des projets Data en travaillant de fa√ßon transverse avec d‚Äôautres Directions seront de r√©els atouts\nPourquoi nous choisir ?\nBoursorama est un acteur pionner et leader sur ses trois activit√©s principales : la banque en ligne, le courtage en ligne et l‚Äôinformation financi√®re sur Internet.\nPr√©curseur d‚Äôune nouvelle g√©n√©ration de banque depuis 2005, Boursorama, filiale de la Soci√©t√© G√©n√©rale est aujourd‚Äôhui pl√©biscit√©e et recommand√©e par 85% de ses clients.\nAccessible √† tous et class√©e banque la moins ch√®re depuis 15 ans, Boursorama a doubl√© le nombre de ses clients ces trois derni√®res ann√©es.\nL‚Äôentreprise conforte chaque ann√©e sa position d‚Äôacteur majeur du secteur et compte aujourd‚Äôhui plus de 5 millions de clients.\nEnvie de prendre part √† cette aventure professionnelle enrichissante et construire un projet professionnel solide, venez rejoindre vos 930 futurs coll√®gues dans nos locaux de Boulogne Billancourt (92) et Nancy (54).\nBoursorama est certifi√©e B CorpTM et rejoint le mouvement mondial des soci√©t√©s engag√©es en mati√®re d‚Äôimpact social et environnemental, de transparence et de responsabilit√©.En tant qu‚Äôacteur engag√©, Boursorama au c≈ìur de ses valeurs les th√©matiques RSE. Nous avons notamment mis en place des actions visant √† r√©duire notre impact √©cologique : accord in√©dit sur le t√©l√©travail, proposition de moyen de locomotion √©lectrique, z√©ro d√©chet‚Ä¶.\nNous avons aussi √† c≈ìur d‚Äôassurer le bien-√™tre de nos √©quipes en proposant des avantages notamment 2 jours de t√©l√©travail hebdomadaires et un accord d‚Äôint√©ressement motivant.\nEn int√©grant la Direction Marketing et Communication\nvous conforterez chaque jour la position de leader de Boursorama.\nNous sommes un\nemployeur garantissant l'√©galit√© des chances\net nous sommes fiers de faire de la diversit√© une force pour notre entreprise. Le groupe s‚Äôengage √† reconna√Ætre et √†\npromouvoir tous les talents\n, quels que soient leurs croyances, √¢ge, handicap, parentalit√©, origine ethnique, nationalit√©, identit√© de genre, orientation sexuelle, appartenance √† une organisation politique, religieuse, syndicale ou √† une minorit√©, ou toute autre caract√©ristique qui pourrait faire l‚Äôobjet d‚Äôune discrimination.\nShow more\nShow less",
        "details": {
            "JobDetail": [],
            "TypeContract": "",
            "Salary": "",
            "Level": "",
            "Experience": "15 an(s)"
        },
        "title": "data analyst",
        "skills": {
            "ProgLanguage": [
                "Python"
            ],
            "DataVisualisation": [
                "Tableau"
            ],
            "Other": [
                "Statistiques"
            ],
            "EnSoftSkils": [
                "Communication"
            ]
        }
    },
    {
        "source": "LinkedIn",
        "company": "Bpifrance",
        "location": "Maisons-Alfort, √éle-de-France, France",
        "link": "https://fr.linkedin.com/jobs/view/data-analyst-f-h-at-bpifrance-3911935389?position=7&pageNum=10&refId=tn2QJQESk9ttg00nH%2FdA7g%3D%3D&trackingId=IEzuL7VfCUjSl0J%2FRyb%2BBQ%3D%3D&trk=public_jobs_jserp-result_search-card",
        "description": "Vos missions au service de l‚Äô√©conomie fran√ßaise\nNous recherchons un.e Data Analyste.\nVous travaillez au sein des √©quipes en charge du socle Data Gouvernance, en √©troite collaboration avec les √©quipes de la Gouvernance des donn√©es.\nVous jouerez un r√¥le cl√© dans la transformation Data Centric de notre syst√®me d‚Äôinformation Bpifrance au service de toutes les directions m√©tiers.\nVous contribuez activement aux enjeux du socle data gouvernance pour positionner le dictionnaire de donn√©es au c≈ìur des process du SI et am√©liorerez les services pour assurer la data quality tout au long de son cycle de vie.\nVos activit√©s principales au sein de l‚Äô√©quipe socle Data Gouvernance :\nAccompagner au quotidien les √©quipes agiles et les m√©tiers dans la prise en main des outils du socle.\nAnimer la communaut√© du socle au travers de communications\nAnimer le club utilisateurs du socle\nMettre en ≈ìuvre des e-learning\nMettre en place des indicateurs de mesure et de pilotage du socle,\nSuperviser, mesurer, suivre l‚Äô√©volution des indicateurs de mesure et de pilotage du socle au travers de tableaux de bord que vous produirez pour des comit√©s de supervision,\nD√©velopper des tableaux de bords √† destination de diff√©rentes instances et m√©tiers,\nSuivre les √©diteurs (demandes d‚Äô√©volutions, releases, incidents,..)\nVotre environnement technique sera le suivant :\nNotre dictionnaire de donn√©es est la solution DataGalaxy.\nNos outils de mesure de la qualit√© de donn√©es sont Informatica Data Quality (Informatica) et Cloud Data Quality (Informatica).\nNotre outil de Dataviz est Qlik Sense.\nNous interagissons avec l‚Äôensemble des m√©tiers de la banque !\nProfil recherch√©\nPr√™ts √† rejoindre notre √©quipe ?\nVotre profil :\nVous disposez d‚Äôune premi√®re exp√©rience autour des outils de la gouvernance des donn√©es et en comprenez les enjeux.\nVous √™tes dot√© d‚Äôun excellent relationnel, vous permettant de sensibiliser vos diff√©rents interlocuteurs M√©tiers, Data & IT\nVous √™tes √† la fois rigoureux et analytique\nVous aimez travailler en √©quipe, vous √™tes curieux, proactif et responsable\nVous √™tes dipl√¥m√©.e Bac+5 et parlez couramment anglais\nLes + du poste :\nDes challenges tech √† relever et des √©v√©nements tech futuristes auxquels vous serez acteur.trice et convi√©.e\nVivre au rythme d‚Äôune culture Tech affirm√©e au c≈ìur d‚Äôune √©quipe soud√©e\nVibrer au son d‚Äôun podcast hebdo\nAssister √† des Town Hall (√©v√©nements virtuels & soir√©es) trimestriels\nLe poste est localiseÃÅ soit au si√®ge de Maisons-Alfort, soit l√† o√π vous √™tes en France.\nLes bonnes raisons de rejoindre l‚Äôaventure Bpifrance !\nUn travail avec du sens : Vous contribuerez √† une mission unique d‚Äôutilit√© publique au service de l‚Äô√©conomie fran√ßaise et au sein d‚Äôune banque engag√©e sur des sujets de soci√©t√© (climat, jeunesse, √©galit√© des chances‚Ä¶).\nUn environnement dans lequel il fait bon vivre : Vous int√©grerez des √©quipes dynamiques et bienveillantes, au sein d‚Äôune entreprise attentive √† la Qualit√© de Vie au Travail de ses collaborateurs. Nos certifications Happy Trainees et Meilleurs Employeurs France par Glassdoor en t√©moignent !\nDes conditions avantageuses : Vous b√©n√©ficierez des nombreux avantages qu‚Äôoffre le groupe pour ses collaborateurs : t√©l√©travail, cong√©s pay√©s sup√©rieurs au minimum l√©gal, √©pargne salariale attractive, CSE, dispositifs de Qualit√© de Vie au Travail‚Ä¶\nUn tremplin pour votre carri√®re : Vous profiterez des meilleures conditions mises en place chez Bpifrance pour d√©velopper vos comp√©tences et construire votre parcours de carri√®re, gr√¢ce √† un accompagnement sur-mesure et des parcours de formation complets et personnalis√©s.\nTravailler chez Bpifrance, c‚Äôest int√©grer une banque pas comme les autres, un projet d‚Äôentreprise ambitieux et tourn√© vers l‚Äôavenir. C‚Äôest plus qu‚Äôun m√©tier : c‚Äôest une mission, une √©quipe, un r√©seau et un √©cosyst√®me.\nPour d√©couvrir nos autres opportunit√©s et tout savoir de la vie au sein du groupe, rendez-vous sur notre site carri√®re !\nBpifrance est une banque citoyenne dot√©e d‚Äôun code de d√©ontologie et d‚Äôune politique anti-corruption.\nAvant de postuler, nous vous invitons √† consulter notre politique relative √† la gestion des donn√©es √† caract√®re personnel disponible sur notre site.\nShow more\nShow less",
        "details": {
            "JobDetail": [],
            "TypeContract": "",
            "Salary": "",
            "Level": "Bac+5",
            "Experience": null
        },
        "title": "data analyst",
        "skills": {
            "Other": [
                "Cloud"
            ],
            "EnSoftSkils": [
                "Collaboration"
            ]
        }
    },
    {
        "source": "LinkedIn",
        "company": "Scalian",
        "location": "Toulouse, Occitanie, France",
        "link": "https://fr.linkedin.com/jobs/view/hr-data-analyst-f-h-at-scalian-3841931151?position=8&pageNum=10&refId=tn2QJQESk9ttg00nH%2FdA7g%3D%3D&trackingId=Ah2hjwDXMTkyq32AW8A0Jw%3D%3D&trk=public_jobs_jserp-result_search-card",
        "description": "TOULOUSE\nVous √™tes HR Data Analyst (F/H) ou vous souhaitez le devenir !\nCDI √† Toulouse /T√©l√©travail partiel possible\nAu moins 5 ans d'exp√©rience dans l'analyse de donn√©es.\nR√©mun√©ration selon votre exp√©rience et vos comp√©tences.\nVous √™tes int√©ress√©¬∑e par l‚Äôanalyse de donn√©es RH ?\nVous savez prendre du recul et analyser votre production ?\nVous avez une app√©tence pour les chiffres et l‚Äôam√©lioration continue ?\nRejoignez notre √©quipe !\nQuel sera votre r√¥le ?\nAu sein de la Direction des Affaires sociales et sous la responsabilit√© du Directeur des Affaires Sociales Groupe, vous aurez pour mission\nl‚Äô√©laboration et l‚Äôanalyse des datas sociales\nr√©currentes sur des process industrialis√©s et ponctuelles :\nProposer des process d‚Äô√©laboration des outils reporting permettant une productivit√©, fiabilit√©, et agilit√© pour des r√©sultats attendus pr√©cis, rigoureux et adaptables selon l‚Äô√©volution du nombre de soci√©t√©s du groupe,\nEtablir des zones de v√©rifications et de contr√¥les de coh√©rences pour assurer la v√©racit√© des donn√©es transmises,\nD√©terminer et formaliser les r√®gles et processus devant √™tre mis en ≈ìuvre avec rigueur par vos clients internes,\nAssurer un back up op√©rationnel pouvant √™tre pris en charge en cas d‚Äôabsence par la personne en charge des rapports sociaux,\nEnrichir les KPI actuels d‚Äô√©l√©ments plus qualitatifs RH permettant une lecture plus pr√©cise de l‚Äô√©tat des Ressources Humaines du Groupe.\nD'autres missions concerneront les r√©mun√©rations internationales :\nMener ponctuellement des comparaisons inter soci√©t√©s sur leurs √©l√©ments de r√©mun√©rations prenant en compte le salaire fixe, le variable individuel et/ou collectif, les r√©gimes de sant√©, et tous autres p√©riph√©riques de r√©mun√©ration,\nAdapter des automatismes de reportings mensuels (Effectifs et niveaux de salaires) suffisamment fiables et flexibles permettant d‚Äô√©clairer le management,\nR√©pondre √† toute analyse souhait√©e par le traitement des donn√©es sociales internationales et fran√ßaises.\nCe que cette exp√©rience va vous apporter\nVous int√®grerez notre √©quipe Social Affairs, au sein de la\nHolding Scalian\nafin d‚Äôoccuper un poste alliant la technique de votre m√©tier, ainsi que l‚Äôanalyse et la mise en perspective de votre travail quotidien, le tout sur un p√©rim√®tre France et international.\nNotre contexte local :\nUne partie de la Direction des Ressources Humaines bas√©e √† Toulouse, dont la Direction des Affaires Sociales, compos√©e de 5 personnes,\nDes interlocuteurs internes et externes.\nCe que nous recherchons chez vous\nMaster 2 ou Ing√©nieur¬∑e de formation,\nExp√©rience certaine en analyse de donn√©es dans un contexte d'entreprise complexe et multi-filiales,\nAvoir travaill√© sur des donn√©es RH et savoir faire des analyses pertinentes,\nRechercher une performance sur la production des rapports et leur fiabilit√©,\nAnglais courant : √©crit et oral,\n√ätre autonome sur l‚Äô√©volution des syst√®mes,\nAvoir le souci du d√©tail, √™tre rigoureux¬∑se.\n√ätre dynamique, curieux¬∑se, avoir le sens de l'adaptabilit√©.\nPourquoi feriez-vous le grand saut ?\nParce que Scalian vous accompagne dans le d√©veloppement de votre carri√®re :\nProgramme d'onboarding complet sur 1 an avec votre manager et votre RH\nProgramme de formation (Scalian Academy, e-learning, webinaires et formations externes)\nCommunaut√©s techniques (Squads, Practices) afin de valoriser et d√©velopper votre expertise\n√âv√©nements internes (Afterworks, Awards Dinner, Kick Off, Live Event du COMEX, Stand Up) et externes (participation √† des salons et forums sp√©cialis√©s dans nos domaines d‚Äôactivit√©s‚Ä¶)\nDispositif d‚Äôacc√©l√©ration d‚Äôacc√®s √† la mobilit√© interne et √† des √©changes internationaux type Erasmus\nParce que Scalian favorise la Qualit√© de Vie au Travail :\nCertifications Great Place to Work¬Æ et Best Workplaces for Women¬Æ\nPrime de cooptation, prime vacances, prise en charge par l‚Äôemployeur de 60% des titres-restaurant, Accord t√©l√©travail (jusqu‚Äô√† 2,5 jours par semaine indemnis√©s), RTT (dont une partie mon√©tisable), CSE (activit√©s ludiques, ch√®ques-cadeaux, ch√®ques vacances)\nBerceaux en cr√®ches inter-entreprises\nDon ou r√©ception de jours de cong√©s en cas de difficult√©s personnelles\nParce que Scalian d√©veloppe une politique RSE concr√®te et ambitieuse :\nMobilit√© durable (indemnit√© kilom√©trique v√©lo, leasing de v√©los √† assistance √©lectrique)\nActions environnementales (Fresque du Climat, Reforest'Action, Clean Up Day, m√©c√©nat ONF)\nPostes ouverts aux personnes en situation de Handicap\nDiverses politiques de diversit√©, d‚Äôinclusion et d‚Äôint√©gration mises en place\nScalian c‚Äôest aussi :\nUne entreprise en tr√®s forte croissance qui, cr√©√©e en 1989, compte aujourd‚Äôhui plus de 5500 personnes\nDes r√©f√©rences clients √† forte valeur ajout√©e aupr√®s de grands industriels fran√ßais (du CAC40) et internationaux\nUn terrain de jeu o√π l‚Äôexpertise se conjugue avec audace, libert√© d‚Äôentreprendre et convivialit√©\nSi vous aspirez √† un environnement de travail qui valorise autant votre bien-√™tre que votre d√©veloppement professionnel,\nrejoignez-nous et exprimez pleinement votre talent !\nQuelles seront les prochaines √©tapes ?\nEchange en visio avec Janice, Talent Acquisition Officer,\n1er entretien avec √âric, Social Affairs Director,\n2nd entretien avec Caroline, Head of Human Ressources.\nShow more\nShow less",
        "details": {
            "JobDetail": [],
            "TypeContract": "CDI",
            "Salary": "5",
            "Level": "",
            "Experience": "5 an(s)"
        },
        "title": "data analyst",
        "skills": {}
    },
    {
        "source": "LinkedIn",
        "company": "METEOJOB by CleverConnect",
        "location": "Marseille, Provence-Alpes-C√¥te d'Azur, France",
        "link": "https://fr.linkedin.com/jobs/view/data-analyst-power-bi-h-f-at-meteojob-by-cleverconnect-3915208737?position=9&pageNum=10&refId=tn2QJQESk9ttg00nH%2FdA7g%3D%3D&trackingId=8PDR2hc7py4NvsCCa%2FGa%2Fg%3D%3D&trk=public_jobs_jserp-result_search-card",
        "description": "Entreprise\nJob Link est un groupe de recrutement CDD/CDI et int√©rim existant depuis 2005 et en pleine croissance.\nNous sommes implant√©s sur 14 bureaux (Lille, Paris et Ile-de-France, Lyon, Marseille, Aix-en-Provence, Aubagne, Nantes, Bordeaux, Toulon et Toulouse).\nNos 80 collaborateurs passionn√©s par leur m√©tier sont anim√©s par la m√™me ambition : accompagner les candidats et les clients au plus pr√®s de leurs besoins. Pour cela, nous proposons un service de recrutement tr√®s s√©lectif et performant, optimis√© par un sourcing multicanal, un processus d'√©valuation m√©tier par mise en situation et des tests de s√©lections sp√©cifiques.\nEn 2022, nos √©quipes ont propos√© un entretien √† plus de 8000 candidats et 4500 d'entre eux ont pu d√©crocher l'emploi souhait√©.\nDescription Du Poste\nJob Link, sp√©cialis√© en recrutement CDD/CDI recherche pour un de ses clients cabinet d'expertise et de conseils un DATA ANALYST expert POWER BI H/F pour un CDI sur Marseille.\nPour Poursuivre Son D√©veloppement Et Accompagner Au Mieux Ses Clients Dans L'analyse De Leurs Donn√©es, Le Cabinet Recherche Un Consultant.e Data Analyst Sp√©cialis√©.e Sur Power BI\nd√©ploiement de Power BI en interne et aupr√®s des clients du cabinet\nd√©veloppement de tableaux de bord en fonction des attentes clients\nam√©lioration des solutions de BI\nFormation aupr√®s de utilisateurs\ncontrat CDI\nsalaire en fonction de l'exp√©rience\nDescription Du Profil\nFormation informatique ou data analyst\nExpertise Power BI\nBon communiquant\nUne premi√®re exp√©rience r√©ussie sur ce type de poste d'au moins 2 ans souhait√©e\nShow more\nShow less",
        "details": {
            "JobDetail": [],
            "TypeContract": "CDI, CDD",
            "Salary": "2",
            "Level": "",
            "Experience": "2 an(s)"
        },
        "title": "data analyst",
        "skills": {
            "DataVisualisation": [
                "Power BI"
            ]
        }
    },
    {
        "source": "LinkedIn",
        "company": "Relais Colis",
        "location": "Cr√©teil, √éle-de-France, France",
        "link": "https://fr.linkedin.com/jobs/view/data-analyst-h-f-at-relais-colis-3901520746?position=10&pageNum=10&refId=tn2QJQESk9ttg00nH%2FdA7g%3D%3D&trackingId=3v0tpbE58kFJ%2FqiriMliuw%3D%3D&trk=public_jobs_jserp-result_search-card",
        "description": "Inventeur du concept de la livraison en Relais, riche de plus de\n54 ans d'exp√©rience\n,\nRelais Colis\nlivre aujourd'hui plus de\n40 millions de colis par an\nen Relais et √† Domicile, pour les grands noms du e-commerce, de plus en plus nombreux √† lui faire confiance.\nPartenaire n¬∞1 du Top 10 e-commerce avec des grandes enseignes comme\nLA REDOUTE, CDISCOUNT, VEEPEE, AMAZON, SHOWROOMPRIVE, BOUYGUES TELECOM, CONFORAMA, VINTED...\nRelais Colis compte plus de 450 collaborateurs. Entreprise citoyenne, Relais Colis m√®ne une politique volontariste en faveur de l‚Äôinsertion des personnes en situation de handicap.\nRejoignez Relais Colis en tant que :\nData Analyst (F/H)\nLa Direction data accompagne les diff√©rentes directions de Walden Express International (Relais Colis et Ciblex) et ses parties prenantes dans la mise en place du pilotage de leurs activit√©s par la data.\nElle participe activement √† l‚Äô√©laboration, √† la valorisation et la restitution de la data pour √©clairer les d√©cisions.\nEn collaboration avec les √©quipes commerciales, relation client et op√©rationnelles, le(la) data analyst contribue √† la mise en ≈ìuvre d‚Äôun pilotage orient√© data chez Relais Colis et Ciblex.\nRattach√©(e) au Directeur data, vous assumez les missions suivantes :\nRecueillir les besoins Data et contribuer √† l‚Äô√©laboration des indicateurs et dashboards sur le p√©rim√®tre.\nIdentifier les axes d‚Äôam√©lioration.\nApporter votre support et votre expertise dans les √©changes avec nos clients et les autres directions.\nContribuer au suivi qualitatif de notre performance\nMettre en place les routines de Data Quality afin d‚Äôatteindre l‚Äôobjectif d‚Äôune entreprise Data Driven\nIssu(e) d'une formation sup√©rieure, vous √™tes \"dataphile\", orient√©(e) business et m√©tiers, et surtout dot√©(e) d'un fort esprit d'entreprise et plein d'enthousiasme\nVous savez coder en SQL et Python\nVous √™tes autonome, orient√©(e) client et connaissez les m√©tiers du transport et de la logistique.\nVous disposez d'une premi√®re exp√©rience r√©ussie et √™tes curieux(se), appr√©ciez de travailler en √©quipe transverse et disposez d'excellente qualit√©s relationnelles et d'organisation, vous avez un r√©el sens client\nLa base de vos missions se fera par le biais de SAS Visual Analytics et Power BI : une connaissance de ces outils serait un plus.\nUn niveau d‚Äôanglais professionnel est n√©cessaire.\nShow more\nShow less",
        "details": {
            "JobDetail": [],
            "TypeContract": "CDI",
            "Salary": "",
            "Level": "",
            "Experience": "54 an(s)"
        },
        "title": "data analyst",
        "skills": {
            "ProgLanguage": [
                "Python"
            ],
            "DataBase": [
                "SQL"
            ],
            "DataVisualisation": [
                "Power BI"
            ],
            "EnSoftSkils": [
                "Collaboration"
            ]
        }
    },
    {
        "source": "LinkedIn",
        "company": "Foxintelligence",
        "location": "Paris, √éle-de-France, France",
        "link": "https://fr.linkedin.com/jobs/view/business-data-analyst-stage-at-foxintelligence-3828937325?position=1&pageNum=12&refId=3UAduJ9EGa9s5reXg%2Ffruw%3D%3D&trackingId=S21H3lOORpE6U7m7zStesQ%3D%3D&trk=public_jobs_jserp-result_search-card",
        "description": "Chez Foxintelligence, nous sommes des amoureux de la data. ü§ì\nNotre mission est de rendre les consommateurs et les marques plus intelligents, gr√¢ce √† une donn√©e de march√© r√©volutionnaire issue de l'intelligence collective. Pour les consommateurs, Foxintelligence rend accessibles et utiles leurs donn√©es transactionnelles issues de leurs bo√Ætes mail ou comptes bancaires. En les anonymisant, nous cr√©ons des statistiques uniques qui permettent aux marques de rester en phase avec les produits qui se vendent le mieux et les attentes des consommateurs.\nNous publions une application grand public aim√©e par des millions de personnes (Cleanfox, 5m+ de t√©l√©chargements, 4.8/5 üíñ sur l'app store et le play store) et pr√©parons le lancement d'une app de bilan carbone √† l'exp√©rience radicalement nouvelle. Gr√¢ce √† notre plateforme data, elle va rendre possible une prise de conscience massive des enjeux du changement climatique üåç et des actions individuelles possibles pour le combattre. Nous pensons que l'information est une force de changement puissante, lorsqu'elle s'appuie sur la data.\nUtilisant ces donn√©es personnelles totalement anonymis√©es, notre plateforme SaaS foxintelligence.io est devenue la r√©f√©rence de la market intelligence digitale en Europe avec des dizaines de grands groupes clients. Le point commun entre Deliveroo, Just Eat, Mano Mano, BackMarket ou The Boston Consulting Group ? Ils vont tr√®s vite (on ne s'ennuie pas avec eux !) et ils nous font tous confiance !\nSoutenus par des investisseurs de premier plan (17m lev√©s aupr√®s de Daphni, Partech, GFC et eFounders) et r√©cemment int√©gr√© au groupe NielsenIQ nous sommes maintenant √† la conqu√™te de l'Europe et en phase d'hyper-croissance.\nSi notre FoxHQ reste √† Paris, notre √©quipe de plus de 140 talents pluridisciplinaires (tech, data et business) travaille depuis partout en France et m√™me en dehors (ex. Turquie). Nous pensons que notre politique remote-first, notre culture forte (bienveillance, exigence, r√©silience et data-first) et notre innovation permanente en termes de modes de travail (ex. grille de salaire transparente, formation au changement climatique, transparence sur la strat√©gie) sont les cl√©s de notre r√©ussite collective.... et de ta r√©ussite avec nous !\nJob Description\nFoxintelligence recherche un\nstagiaire analyst full-stack data & business.\nTu seras rattach√©(e) √† l'√©quipe\nDigital & New Verticals\n, responsable de l'int√©gralit√© du dataflow sur nos verticales digitales (food delivery et ride hailing) et du lancement de nouvelles industries innovantes telles que le gaming, le Buy-Now-Pay-Later ou les hedge funds.\nTes responsabilit√©s au quotidien:\nParticiper activement au lancement de nouveaux produits (via Tableau, ou la construction d'applications SaaS natives) et contribuer au d√©veloppement de nouveaux enrichissements de donn√©es (par exemple pour notre dataset mobile apps, l'identification de l'application li√©e √† chaque transaction, via du matching de logos)\nContribuer √† notre expansion internationale via le d√©veloppement de nouveaux pays sur les 5 continents, des Etats-Unis au Canada, en passant par l'Inde et le Japon\nParticiper √† la gestion de partenariats strat√©giques avec des clients globaux et cl√©s pour Foxintelligence, en comprenant leurs besoins et en d√©veloppant des nouvelles analyses (sous Tableau, ou Google Big Query) qui y r√©pondent\nExplorer et mettre en oeuvre des projets data √† fort potentiel strat√©gique et commercial, tels que le redressement et l'extrapolation de notre panel, ou l'automatisation de nos process de qualit√©\nRequirements\nComp√©tences n√©cessaires (ce qu'il te faut pour r√©ussir sur ce poste):\nSoft Skills\nEsprit analytique et structur√©\nPassionn√©(e) par les d√©fis et √† l'aise face √† des probl√®mes nouveaux et complexes\nEnvie d'apprendre, de contribuer spontan√©ment √† son environnement et d'aider l'√©quipe √† s'am√©liorer\nHard Skills\nCapacit√© √† comprendre rapidement le fonctionnement de produits techniques complexes: soit par une exp√©rience pertinente (auto formation, projet perso, etc), soit par une formation adapt√©e (grande √©cole d'ing√©nieur ou √©quivalent √† l'√©tranger, √©cole de commerce avec parcours avanc√©e en data)\nComp√©tences en code suffisantes pour manipuler de la data (R ou Python)\nExp√©rience\nTu as une premi√®re exp√©rience d'au moins 6 mois en data, op√©ration ou produit dans des startups tech, ou en cabinets de conseil\nComp√©tences bonus\nHard skills\nMaitrise de Tableau, SQL (id√©alement BigQuery), Github, Airflow, Google Cloud Platform\nExp√©rience\nR√¥le pr√©c√©dent dans un environnement tech o√π on passe √† l'√©chelle\nTu as d√©j√† mont√© un projet entrepreneurial ou personnel\nLadies\nLes √©tudes montrent que les femmes ont moins tendance √† postuler √† une offre d'emploi quand elles n'ont pas toutes les qualifications. Ladies, ne vous mettez pas de barri√®re et donnez nous la chance de nous faire notre propre avis, nous serons toujours ravis d'√©changer avec vous ! Si notre raison d'√™tre vous parle, postulez !\nSelf made data lovers\nLes dipl√¥mes c'est bien, les skills c'est mieux et l'exp√©rience t'en donne. Aucun dipl√¥me n'est requis chez nous, ce sont les comp√©tences et l'√©nergie qui comptent !\nBenefits\nAvantages/ce que nous offrons:\nR√©mun√©ration comp√©titive\nRemote friendly mais notre bureau dans le 10e arrondissement √† Paris est ouvert si tu veux venir !\nTitres restaurants (swile) : pris en charge √† 60% par Fox\nCulture forte et pratiques de management √† la pointe (strat√©gie et r√©sultats financiers transparents, feedback360, grille de salaire innovante et transparente etc.)\nD√©roulement des entretiens\nRound 0 : entretien (fit) avec un membre de l'√©quipe HR\nRound 1 : entretiens (exp√©rience et fit) avec deux leads data analystes de l'√©quipe\nEtude de cas\nDecision Round : Entretien (fit et vision) avec la manager de l'√©quipe\nShow more\nShow less",
        "details": {
            "JobDetail": [
                "Remote",
                "Full"
            ],
            "TypeContract": "",
            "Salary": "5",
            "Level": "",
            "Experience": null
        },
        "title": "data analyst",
        "skills": {
            "ProgLanguage": [
                "R",
                "Python"
            ],
            "DataBase": [
                "SQL"
            ],
            "DataAnalytics": [
                "R"
            ],
            "DataVisualisation": [
                "Tableau"
            ],
            "CloudComputing": [
                "Google Cloud Platform"
            ],
            "DBMS": [
                "Big Query",
                "BigQuery"
            ],
            "Automation": [
                "Airflow"
            ],
            "Other": [
                "Statistiques",
                "Cloud"
            ]
        }
    },
    {
        "source": "LinkedIn",
        "company": "Zoomalia",
        "location": "Castets, Nouvelle-Aquitaine, France",
        "link": "https://fr.linkedin.com/jobs/view/data-analyst-h-f-at-zoomalia-3898519325?position=2&pageNum=12&refId=3UAduJ9EGa9s5reXg%2Ffruw%3D%3D&trackingId=oave2oZ4XEuLqQRvWdHkyQ%3D%3D&trk=public_jobs_jserp-result_search-card",
        "description": "Cette offre d‚Äôemploi est fournie par P√¥le emploi\nDescription\nAnalyse des donn√©es (√©conomiques, statistiques, ...) et les restitue en une information op√©rationnelle et strat√©gique d'aide √† la d√©cision pour la structure, l'entreprise. Peut r√©aliser et mettre en oeuvre le recueil de donn√©es. Peut coordonner une √©quipe ou diriger un service.\nPROFIL SOUHAIT√â\nExp√©rience\nD√©butant accept√©\nSource: Pole emploi (https://www.pole-emploi.fr)\nShow more\nShow less",
        "details": {
            "JobDetail": [],
            "TypeContract": "",
            "Salary": "",
            "Level": "",
            "Experience": null
        },
        "title": "data analyst",
        "skills": {
            "Other": [
                "Statistiques"
            ]
        }
    },
    {
        "source": "LinkedIn",
        "company": "LVMH",
        "location": "Paris, √éle-de-France, France",
        "link": "https://fr.linkedin.com/jobs/view/data-analyst-global-travel-retail-assistant-internship-at-lvmh-3904852662?position=3&pageNum=12&refId=3UAduJ9EGa9s5reXg%2Ffruw%3D%3D&trackingId=laxu6ugtThE2OKruQl5j2A%3D%3D&trk=public_jobs_jserp-result_search-card",
        "description": "Mo√´t Hennessy, No. 1 worldwide in Luxury Wines & Spirits, owns prestigious brands such as Mo√´t & Chandon, Dom P√©rignon, Hennessy, Glenmorangie, Ruinart and Veuve Clicquot... As a part of LVMH, luxury sector leader, Mo√´t Hennessy is recognized for the quality of its products, its constant search for excellence and innovation. Mo√´t Hennessy realizes more than 90% of its turnover in the export and embodies the French Art de vivre.\nThe Travel Retail works in close relationship with its main customers to deliver unique brand experiences in the biggest Airports and Cruises Lines across the world. In the highly dynamic environment of Travel Retail, our team is dedicated to sharing and promote with passion the excellence of our Wines & Spirits portfolio.\nAs part of the Travel Retail division team based in Paris, you will work closely along the business controllers, with a key focus on business intelligence. You will oversee the existing BI tools we are using, maintaining and developing them. You will directly impact the top-level decisions by providing key analysis. You will be the data expert for all the departments (Finance, Marketing, Sales).\nThis internship is the perfect opportunity to understand and experience the role of the finance function within a highly dynamic Business environment.\nHOW YOU WILL CONTRIBUTE TO MH TR‚ÄôS SUCCESS\nData management\nEnsure a good maintenance of our data systems (Power BI, Anaplan)\nProvide data reports, analytic insights and clear data visualizations for different stakeholders (Finance, Marketing, Sales)\nTransform the data to deliver insights to the top management\nOrganize trainings for your key users\nMake recommendations on best practices / technological watch\nKey point of contact with our internal business users and external Power BI consultant\nSupport GTR consolidation\nAssist GTR controller on all analysis (Monthly Sell-in, Sell-out, P&L, MMF etc)\nParticipate to all reporting phases of Global Travel Retail (budget, LE1, LE2 and Actuals)\nAd-hoc analysis for top management (Business reviews, customers / product analysis etc)\nWE THINK YOU WILL FIT IN GREAT WITH US IF\nYou are doing business or engineering studies (master level or bac +5)\nExcel has no secret for you, a first experience with Power BI is a must\nYou are problem solving oriented\nYou are a team player\nYou know how to deal with complexity and thrive in a dynamic working environment\nYou speak French and English\nYou show strong analytical skills, with an ability to use multiple data sources to extract the best insights from it\nYou are autonomous, proactive\nWHAT WE OFFER IN RETURN\nWorking with the world-leading luxury company\nEmbrace diversity, equity, and inclusion as core values, fostering an inclusive culture\nWill join a vibrant and creative global community at MH/LVMH\nOffer a hybrid working arrangement and a collaborative environment\nCareer growth opportunities with mobility options within LVMH Group\nStaff enjoy exclusive discounts on Mo√´t Hennessy and other LVMH brands\nInternship of 6 months starting July 2024\nShow more\nShow less",
        "details": {
            "JobDetail": [],
            "TypeContract": "",
            "Salary": "",
            "Level": "",
            "Experience": null
        },
        "title": "data analyst",
        "skills": {
            "DataVisualisation": [
                "Power BI"
            ],
            "EnSoftSkils": [
                "Problem Solving"
            ]
        }
    },
    {
        "source": "LinkedIn",
        "company": "eXalt",
        "location": "Lille, Hauts-de-France, France",
        "link": "https://fr.linkedin.com/jobs/view/data-analyst-h-f-%40exalt-lille-at-exalt-3842174165?position=4&pageNum=12&refId=3UAduJ9EGa9s5reXg%2Ffruw%3D%3D&trackingId=vXxmvLhqT6a0f%2Bpeq4Ma%2Fg%3D%3D&trk=public_jobs_jserp-result_search-card",
        "description": "Descriptif du poste\neXalt Lille recherche son/sa nouveau/elle\nData Analyst\npour aller √† la conqu√™te de nouveaux projets ! Vous √©voluerez dans un contexte multi soci√©t√©s et challengeant.\nVous serez rattach√©(e) √† notre bureau Lillois.\nVos principales missions seront de :\nComprendre les probl√©matiques m√©tiers et les traduire de mani√®res analytiques\nExtraire les donn√©es n√©cessaires √† l‚Äôanalyse\nD√©finir et r√©aliser le nettoyage de la base de donn√©es\nS‚Äôassurer la qualit√© des donn√©es tout au long de leur traitement\nAnalyser et exploiter les donn√©es\nCr√©er des dashboards via des outils de visualisations\nEffectuer une veille sur les nouvelles technologies et solutions logicielles d‚Äôanalyse des donn√©es\nPourquoi nous rejoindre ?\nLa force d‚ÄôeXalt consiste √† s‚Äôorganiser en interne comme une organisation produit et √† cultiver. Nous avons √† c≈ìur de vous accompagner tout au long de votre carri√®re gr√¢ce √† nos formations et √† notre accompagnement au passage de certifications. Anim√©s par nos valeurs que sont la cocr√©ation, la do-ocratie et le permanent b√™ta, nous vous permettrons de vous √©panouir dans un environnement dynamique et favorisons votre proactivit√© et esprit d‚Äôinitiative !\nProfil recherch√©\nNous recherchons avant tout une personne anim√©e par l‚Äôesprit et l‚ÄôADN d‚ÄôeXalt ‚òÄÔ∏è ayant l‚Äôenvie de prendre part √† un superbe challenge et √† notre aventure !\nVous √™tes dipl√¥m√©(e) d‚Äôun Bac+5\nVous b√©n√©ficiez d‚Äôune exp√©rience d‚Äôau moins 3 ans en tant que Data Analyst\nVous avez une expertise en base de donn√©es et gestion de base de donn√©es (SQL/ NoSQL)\nVous maitrisez des outils de data visualisation (Tableau, Qlikview, PowerBI) et/ou des outils de fouille et analyse de donn√©es (Dataiku)\nVous avez une aisance r√©dactionnelle & relationnelle\nVous avez une passion pour les chiffres et le go√ªt pour l‚Äôinnovation\nVous √™tes reconnu(e) pour votre rigueur, votre organisation et votre adaptabilit√©\nD√©roulement des entretiens\nUn premier entretien avec un/e Digital Sales Manager pour se d√©couvrir mutuellement\nUn second entretien avec un/e associ√©/e co-fondateur/rice pour aller plus loin dans les probl√©matiques abord√©es en mission et les enjeux ma√Ætris√©s\nUn dernier entretien avec un Consultant Senior, pour faire le point sur votre positionnement et vos comp√©tences\nNous sommes agiles !\nCes entretiens peuvent se faire en visio et/ou en pr√©sentiel !\nVenez nous rencontrer autour d‚Äôun caf√© dans nos locaux, situ√©s: 57 rue Nationale, 59 800 Lille ‚òï\nQui sont-ils ?\nCabinet de conseil en Transformation Digitale, eXalt est avant tout une formidable aventure humaine, et une communaut√© de plus de 950 collaborateurs, bas√©s √† Paris, Lyon, Lille, Nantes, Rennes, Bordeaux, Aix-en-Provence, Bogota, New-York et Madrid.\nFond√©e en juillet 2018 autour des valeurs d‚Äôintrapreneuriat, de co-apprentissage et de co-construction, eXalt inscrit son d√©veloppement dans un engagement fort aupr√®s de ses clients et de ses √©quipes. Multi-sp√©cialiste, le groupe d√©cline son mod√®le dans diff√©rents domaines √† travers ses filiales d√©di√©es :\nLe Product Management & la Gestion de Projet au sein d‚ÄôeXalt Flow\nLa Finance de March√© au sein d‚ÄôeXalt Fi,\nLa Tech au sein d‚ÄôeXalt IT,\nLa Cybers√©curit√© au sein d‚ÄôeXalt Shield\nLa Data au sein d‚ÄôeXalt Value\neXalt Lille, filiale du groupe sp√©cialis√©e sur les m√©tiers du Product & Project Management, recherche son/sa nouveau/elle\nData Analyst\npour aller √† la conqu√™te de nouveaux projets ! Vous √©voluerez dans un contexte multi soci√©t√©s et challengeant.\nVous serez rattach√©(e) √† notre bureau lillois.\nShow more\nShow less",
        "details": {
            "JobDetail": [
                "Senior"
            ],
            "TypeContract": "",
            "Salary": "",
            "Level": "Bac+5",
            "Experience": "3 an(s)"
        },
        "title": "data analyst",
        "skills": {
            "DataBase": [
                "SQL",
                "NoSQL"
            ],
            "DataVisualisation": [
                "Tableau"
            ],
            "EnSoftSkils": [
                "Initiative"
            ]
        }
    },
    {
        "source": "LinkedIn",
        "company": "Notariat Services",
        "location": "Arnac-Pompadour, Nouvelle-Aquitaine, France",
        "link": "https://fr.linkedin.com/jobs/view/data-analyst-h-f-at-notariat-services-3910209780?position=5&pageNum=12&refId=3UAduJ9EGa9s5reXg%2Ffruw%3D%3D&trackingId=JVHqa3jl4WfnUViVon5Ecw%3D%3D&trk=public_jobs_jserp-result_search-card",
        "description": "Cette offre d‚Äôemploi est fournie par P√¥le emploi\nDescription\nLe Groupe Notariat Services, fort de 55 ans d'exp√©rience en communication immobili√®re notariale, recrute une.e Data Analyst. Ce poste est bas√© √† POMPADOUR, √† 45 min de Limoges et de Brive. Vous aurez pour mission d'analyser et interpr√©ter des donn√©es complexes, de formuler des insights pertinents, et de contribuer √† la prise de d√©cision strat√©gique au sein de l'entreprise. Vous participerez activement √† l'extraction, au traitement, √† l'analyse et √† la visualisation des donn√©es. Responsabilit√©s Principales : 1. Collecte de Donn√©es : - Identifier et collecter les donn√©es n√©cessaires √† l'analyse. - Collaborer avec les √©quipes concern√©es pour assurer une collecte de donn√©es efficace. 2. Traitement des Donn√©es : - Transformer les donn√©es brutes en formats exploitables pour l'analyse. 3. Analyse Statistique : - Utiliser des techniques statistiques pour analyser les tendances, les corr√©lations et les mod√®les dans les donn√©es. - Effectuer des analyses descriptives et pr√©dictives. 4. Visualisation des Donn√©es : - Cr√©er des visualisations claires et informatives pour faciliter la compr√©hension des r√©sultats. - Utiliser des outils de visualisation tels que Tableau, Power BI, etc. 5. Rapports et Pr√©sentations : - Pr√©parer des rapports r√©guliers sur les analyses effectu√©es. - Pr√©senter les r√©sultats de mani√®re compr√©hensible aux parties prenantes. 6. Collaboration Interfonctionnelle : - Collaborer avec les √©quipes m√©tier pour comprendre leurs besoins et fournir des solutions adapt√©es. - Travailler en √©troite collaboration avec les √©quipes informatiques pour assurer l'int√©gration des donn√©es. 7. (En plus : Mod√©lisation et Machine Learning ) - D√©velopper des mod√®les pr√©dictifs en utilisant des algorithmes de machine learning. - √âvaluer et am√©liorer la performance des mod√®les existants. Comp√©tences Requises : - Comp√©tences en programmation (Python, R, etc.). - Ma√Ætrise des outils et langages li√©s √† la manipulation de donn√©es (SQL, etc.). - Connaissance des techniques d'analyse statistique (et de machine learning). - Exp√©rience dans la cr√©ation de visualisations de donn√©es. - Excellentes comp√©tences en communication et capacit√© √† pr√©senter des r√©sultats de mani√®re compr√©hensible. - Capacit√© √† travailler de mani√®re autonome et en √©quipe. VOTRE CV DOIT √äTRE ACCOMPAGN√â D'UNE LETTRE DE MOTIVATION\nPROFIL SOUHAIT√â\nExp√©rience\n2 An(s)\nSavoirs et savoir-faire\nAdapter les outils de traitement statistique de donn√©es\nR√©diger l'information produite\nPr√©senter et diffuser les r√©sultats des √©tudes r√©alis√©es\nR√©aliser une √©tude\nD√©finir et faire √©voluer des proc√©d√©s de traitement de l'information\nSavoir-√™tre professionnels\nFaire preuve de rigueur et de pr√©cision\nPrendre des initiatives et √™tre force de proposition\nTravailler en √©quipe\nSource: Pole emploi (https://www.pole-emploi.fr)\nShow more\nShow less",
        "details": {
            "JobDetail": [],
            "TypeContract": "",
            "Salary": "",
            "Level": "",
            "Experience": "55 an(s)"
        },
        "title": "data analyst",
        "skills": {
            "ProgLanguage": [
                "R",
                "Python"
            ],
            "DataBase": [
                "SQL"
            ],
            "DataAnalytics": [
                "R"
            ],
            "DataVisualisation": [
                "Power BI",
                "Tableau"
            ],
            "Other": [
                "Statistiques",
                "Machine Learning"
            ],
            "EnSoftSkils": [
                "Communication",
                "Collaboration"
            ]
        }
    },
    {
        "source": "LinkedIn",
        "company": "Envu",
        "location": "Lyon, Auvergne-Rh√¥ne-Alpes, France",
        "link": "https://fr.linkedin.com/jobs/view/senior-data-analyst-at-envu-3913350840?position=6&pageNum=12&refId=3UAduJ9EGa9s5reXg%2Ffruw%3D%3D&trackingId=c2M3Q0VRNkAz32ebgDZ86g%3D%3D&trk=public_jobs_jserp-result_search-card",
        "description": "We‚Äôre Hiring!\nSenior Data Analyst (all genders)\nAt Envu, we partner with our customers to design world-class, forward-thinking innovations that protect and enhance the health of environments around the world. We offer dedicated services in: Professional Pest Management, Forestry, Ornamentals, Golf, Industrial Vegetation Management, Lawn & Landscape, Mosquito Management, and Range & Pasture.\nEnvu brings together diverse points of view to look beyond chemistry and dare to explore new paths forward. Guided by our inclusive culture, we embrace change and flexibility, tackling our customers‚Äô toughest challenges proactively, passionately and with an entrepreneurial spirit.\nWe pursue our ambitions collaboratively because we know that a unified and empowered team is an unstoppable force, allowing us to achieve our vision of healthy environments for everyone, everywhere. Join Us.\nFUNCTION\n: Senior Data Analyst\nLOCATION\n: Lyon, France\nJOB\nTYPE\n: Permanent\nROLE\nSENIORITY\n: Manager\nGET TO KNOW YOUR AREA:\nJoin the Finance Data Analytics team to enhance data analysis and visualization tools to drive financial strategy, enhance forecasting accuracy, and provide critical insights that support key business decisions.\nFocus on leveraging the capabilities of our Azure Data lake and the Microsoft Power Platform (Power BI, PowerApps, and Power Automate) to enhance our reports, process automation, and custom business applications.\nYOUR MISSION WILL BE TO:\nDesign, develop and maintain complex Power BI dashboards for decision-making while taking into account the needs from the different stakeholders (Finance, Business, Marketing)\nPerform data modeling, transformation, and analytics using SQL and DAX\nContinuously evaluate and improve existing processes and systems using insights derived from data analysis and automation projects\nDevelop custom business applications using Power Platform, integrating with various data sources and APIs to fulfill unique business requirements\nActively contributing to the expertise level and competencies of the Finance Data & Analytics team\nCollaborate with other departments to identify opportunities for process improvement and automation in reporting workflows\nARE YOU READY FOR THE ROLE?\nMain requirements:\nMaster's degree in a relevant field such as Computer Science, Statistics, or Data Analytics. Experience in Finance is required\nMinimum of 5 years of experience in a data analyst role, with a proven experience in data visualization using Power BI\nExperience in writing scripts, and queries using SQL\nExpertise in Power Platform is a strong plus\nSolid understanding of data governance, data management, and data visualization best practices\nExcellent analytical and problem-solving skills, with the ability to translate complex data into actionable insights\nEnvu is committed to diversity in all aspects for all employees and candidates, regardless of ethnicity, color, race, religion, origin, age, gender, gender identity or expression, sexual orientation, or other conditions. And all opportunities are open to people with disabilities.\nBy applying for this position, you agree that your personal data are going to be processed and recorded by Envu for recruitment purposes only. For candidates who are not selected for this position, personal data will be kept for a period of two years and then permanently deleted.\nWe will soon be in touch to let you know the next steps to be taken!\nShow more\nShow less",
        "details": {
            "JobDetail": [
                "Senior"
            ],
            "TypeContract": "",
            "Salary": "",
            "Level": "",
            "Experience": null
        },
        "title": "data analyst",
        "skills": {
            "DataBase": [
                "SQL"
            ],
            "DataVisualisation": [
                "Power BI"
            ],
            "CloudComputing": [
                "Azure"
            ],
            "EnSoftSkils": [
                "Flexibility"
            ]
        }
    },
    {
        "source": "LinkedIn",
        "company": "Capgemini",
        "location": "Nantes, Pays de la Loire, France",
        "link": "https://fr.linkedin.com/jobs/view/business-analyst-data-nantes-at-capgemini-3803937789?position=7&pageNum=12&refId=3UAduJ9EGa9s5reXg%2Ffruw%3D%3D&trackingId=hhi3cfaxZ94Cn0pSipWkhw%3D%3D&trk=public_jobs_jserp-result_search-card",
        "description": "Capgemini\nChoisir Capgemini, c'est choisir une entreprise o√π vous serez en mesure de fa√ßonner votre carri√®re selon vos aspirations, o√π vous serez soutenu et inspir√© par une communaut√© d‚Äôexperts dans le monde entier, o√π vous pourrez r√©√©crire votre futur. Rejoignez-nous pour red√©finir les limites de ce qui est possible, contribuer √† lib√©rer la valeur de la technologie pour les plus grandes organisations et participez √† la construction d‚Äôun monde plus durable et inclusif.\nVos missions :\nInt√©gr√©(e) au sein d‚Äôune √©quipe projet BI, Big Data ou Data Gouvernance pour des clients intervenant dans des secteurs d'activit√©s divers, vous serez notamment en charge des missions suivantes :\nD√©finir les besoins r√©els de nos clients, et d√©terminer la meilleure mani√®re d‚Äôy r√©pondre en utilisant la Data\nConduire des ateliers avec le client sur les aspects fonctionnels et techniques\nR√©daction des User Stories et/ou les sp√©cifications fonctionnelles , R√©daction de sp√©cifications d√©taill√©es\nSupport √† la recette m√©tier\nCoordination d‚Äô√©quipes pluri disciplinaire\nPilotage et gestion de projets.\nVotre profil :\nDipl√¥me d‚Äôing√©nieur ou √©quivalent universitaire\nMinimum 3 ans d‚Äôexp√©rience\nEncadrement d'√©quipe\nAnglais courant\nExcellentes qualit√©s d‚Äô√©coute et d‚Äôanalyse,\nMa√Ætrise de la r√©daction de documentation fonctionnelle, de la m√©thodologie projet (Scrum),\nConnaissances de la mod√©lisation de donn√©es, du langage SQL et d'un ou de plusieurs outils de reporting tels que Power BI, Tableau ou Qlik Sense.\n3 raisons de nous rejoindre :\nQualit√© de vie au travail : accord de t√©l√©travail en France et √† l‚Äôinternational, accord sur l‚Äô√©galit√©\nprofessionnelle, la parentalit√©, l‚Äô√©quilibre des temps et la mobilit√© durable.\nApprentissage en continu : certifications et formations en libre acc√®s, accompagnement sur mesure avec votre carreer manager, parcours d‚Äôint√©gration sur 9 mois.\nAvantages groupe & CSE : plan actionnariat, activit√©s √† tarifs pr√©f√©rentiels, remboursement partiel\nvacances, remboursement de votre abonnement sportif ou culturel.\nNos engagements et priorit√©s :\nLe groupe Capgemini encourage une culture inclusive dans un cadre multiculturel et handi-accueillant. En nous rejoignant, vous int√©grez un collectif qui valorise la diversit√©, d√©veloppe le potentiel de ses talents, s‚Äôengage dans des initiatives solidaires avec ses partenaires, et se mobilise pour r√©duire son impact environnemental sur tous ses sites et aupr√®s de ses clients.\nCapgemini\nCapgemini est un leader mondial, responsable et multiculturel, regroupant pr√®s de 350 000 personnes dans plus de 50 pays. Fort de 55 ans d‚Äôexp√©rience, nous sommes un partenaire strat√©gique des entreprises pour la transformation de leurs activit√©s en tirant profit de toute la puissance de la technologie et des innovations dans les domaines en perp√©tuelle √©volution tels que le cloud, la data, l‚ÄôIntelligence Artificielle, la connectivit√©, les logiciels, l‚Äôing√©nierie digitale ou les plateformes.\nGet The Future You Want* | www.capgemini.com/fr-fr\n*Capgemini, le futur que vous voulez\nShow more\nShow less",
        "details": {
            "JobDetail": [],
            "TypeContract": "",
            "Salary": "",
            "Level": "",
            "Experience": "3 an(s)"
        },
        "title": "data analyst",
        "skills": {
            "DataBase": [
                "SQL"
            ],
            "DataVisualisation": [
                "Power BI",
                "Tableau"
            ],
            "Other": [
                "Cloud",
                "Big Data"
            ]
        }
    },
    {
        "source": "LinkedIn",
        "company": "Prisma Media",
        "location": "√éle-de-France, France",
        "link": "https://fr.linkedin.com/jobs/view/data-analyst-yield-f-h-cdi-at-prisma-media-3918307053?position=9&pageNum=12&refId=3UAduJ9EGa9s5reXg%2Ffruw%3D%3D&trackingId=zyBZt5P2r%2BuaJ8TiMuZTWw%3D%3D&trk=public_jobs_jserp-result_search-card",
        "description": "Vos Missions ?\nAu sein de la cellule digitale de Prisma Media Solutions, votre objectif est de traiter et d‚Äôanalyser l'ensemble des donn√©es d'inventaire et de revenus, sur les formats publicitaires et sur les partenaires.\nPouss√© par la volont√© d'√™tre toujours √† la pointe, nous testons √©norm√©ment d‚Äôinnovations march√© afin d‚Äôavoir l‚Äôenvironnement le plus performant.\nVos missions seront les suivantes :\nAnalyse des KPI cl√© de la performance (Visibilit√©, CPM, ‚Ä¶)\nConstruction et d√©veloppement d‚Äôoutils d‚Äôaide √† la d√©cision et suivi des performances\nMaintien et d√©veloppement des diff√©rents dashboard m√©tier\nEchange avec les √©quipes Adops, IT et Traffic acquisition pour l‚Äôorientation de la strat√©gie mon√©tisation et acquisition\nSuivi et analyse des A/B Test\nAide √† l'optimisation des remplissages, des revenus et des mesures de performances\nD'autres missions pourront √™tre confi√©es en fonction de l'activit√© du service.\nVotre Profil ?\nCe poste est fait pout vous si :\nDipl√¥m√©.e d‚Äôuniversit√© ou d‚Äô√©cole sup√©rieure (BAC+5), vous avez une forte app√©tence pour l'analyse de donn√©es.\nDynamique, vous appr√©cierez √©voluer dans un environnement passionnant en pleine transformation\nVous √™tes autonome et savez √™tre force de proposition\nExcel n'a aucun secret pour vous\nLa connaissance du langage SQL ou de l‚Äôunivers de la publicit√© seraient un plus.\nVotre future entreprise ?\nLe groupe Prisma Media accompagne le quotidien des Fran√ßais depuis plus de 40 ans pour les divertir et les informer. Il est aujourd‚Äôhui le leader de la presse magazine et des m√©dias en ligne. Chaque mois, 2 Fran√ßais sur 3 consultent une marque de Prisma Media. Avec un portefeuille de 35 marques de r√©f√©rence, le groupe est pr√©sent sur les principaux segments grand public et luxe. Prisma Media a pour ambition de devenir le leader europ√©en des marques m√©dias d√©sirables.\nPrisma Media est aussi un groupe qui s‚Äôengage :\nDes marques engag√©es aupr√®s d‚Äôassociations pour faire la diff√©rence :\nLe Rire M√©decin, La Maison des Femmes ou encore la collecte de nos magazines pour l‚ÄôAPHP\nDes r√©f√©rents handicap et LGBTQIA+ pour que tous se sentent accompagn√©\n100% des papiers de nos magazines sont issus de for√™ts √©co-g√©r√©es\nEt tellement d‚Äôautres actions √† d√©couvrir !\nLes petits plus chez nous ?\nNos chiffres et nos marques ne sont pas des arguments suffisants pour attirer votre attention ? Ne vous en faites pas, nous en avons d‚Äôautres !\nR√©mun√©ration selon profil\n6 semaines de cong√©s + 3 semaines de RTT\nDu t√©l√©travail\nUne conciergerie : pressing, coiffeur, boutique‚Ä¶\nCaf√© et th√© gratuits, cantine de qualit√© avec des produits de saisons cuisin√©s sur place\nDes formations & conf√©rences mensuelles sur des th√©matiques diverses : r√©seaux sociaux, d√©veloppement personnel, intelligence artificielle‚Ä¶\nDes events annuels : Garden party, journ√©e, Vis ma vie, afterworks‚Ä¶\nShow more\nShow less",
        "details": {
            "JobDetail": [],
            "TypeContract": "",
            "Salary": "",
            "Level": "Bac+5",
            "Experience": "40 an(s)"
        },
        "title": "data analyst",
        "skills": {
            "DataBase": [
                "SQL"
            ]
        }
    },
    {
        "source": "LinkedIn",
        "company": "GN Group",
        "location": "Villeneuve-d‚ÄôAscq, Hauts-de-France, France",
        "link": "https://fr.linkedin.com/jobs/view/data-analyst-at-gn-group-3887257536?position=10&pageNum=12&refId=3UAduJ9EGa9s5reXg%2Ffruw%3D%3D&trackingId=HH6kspxd23vDpZ4edAKA4g%3D%3D&trk=public_jobs_jserp-result_search-card",
        "description": "Lille\nSteelSeries\nest un groupe danois, leader mondial sp√©cialis√© dans les √©quipements de jeu vid√©o haute performance utilis√©s par les joueurs professionnels.\nPionniers des comp√©titions de jeux vid√©o et eSports, nous am√©liorons les performances gr√¢ce √† des innovations et des technologies de premier ordre.\nSteelSeries France\n, anciennement\nNahimic\n, fait partie depuis 3 ans de la division Software de\nSteelSeries\n. Notre √©quipe de sp√©cialistes en traitement audio et g√©nie logiciel est bas√©e en France, √† Singapour et √† Taiwan. Nous d√©veloppons la prochaine g√©n√©ration de logiciels audio, combinant technologies de pointe et innovations pour booster l‚Äôexp√©rience de jeu des gamers. Nous √©quipons les PC et p√©riph√©riques des plus grandes marques telles que MSI, Dell, Asus, Huawei et Lenovo.\nNotre site fran√ßais, bas√© √† Villeneuve d‚ÄôAscq, compte 40 collaborateurs dont 15 D√©veloppeurs.\nNous avons des bureaux mondiaux en Am√©rique du Nord, en Europe et en Asie, offrant une gamme compl√®te de produits con√ßus pour les jeux.\nSteelSeries\nconna√Æt une croissance rapide et, en janvier 2022, nous avons int√©gr√© le Groupe\nGN Store Nord.\nLa forte croissance du march√© du jeu vid√©o et le d√©veloppement du t√©l√©travail sont autant de boosters pour notre activit√© : Aujourd‚Äôhui il nous faut renforcer nos √©quipes pour pouvoir continuer √† satisfaire les demandes de nos clients !\nNotre Poste:\nNous recrutons notre futur Data Analyst. En tant que partenaire du business et expert en analyse de donn√©es, vous avez un r√¥le cl√©, dans la transformation digitale de notre offre de Software & Products (Business Unit). Software & Products de SteelSeries se concentre sur la construction d‚Äôun √©cosyst√®me de produits et services logiciels pour la communaut√© des gamers du monde entier.\nNotre logiciel GG incluant Engine, Sonar, Moments & 3D Aim Trainer, est aujourd‚Äôhui utilis√© par des millions de gamers. Nous souhaitons continuer d‚Äôam√©liorer nos produits et nos logiciels afin de fid√©liser et acqu√©rir de nouveaux utilisateurs.\nPersuad√©s que la Data est un √©l√©ment cl√© dans cette am√©lioration, nous sommes √† la recherche d‚Äôun Data Analyst, afin de nous accompagner sur la compr√©hension de nos produits et sur l‚Äôacquisition, l‚Äôactivation et la conversion de nouveaux utilisateurs.\nAu sein de l‚Äô√©quipe Data, et en √©troite collaboration avec notre Lead Data Engineer, vous aurez comme principales responsabilit√©s :\nRencontrer les parties prenantes de la gestion et de la conception de produits, de l‚Äôing√©nierie et de SteelSeries afin de comprendre les besoins inter fonctionnels des √©quipes et de prioriser les analyses et metrics des produits ;\nAccompagner les √©quipes Produits & Marketing afin de les aider √† am√©liorer l‚Äôexp√©rience Produit pour d√©velopper notre base clients ;\nTraduire et transformer les questions business en cas d'√©tude analytiques en questionnant, challengeant, et accompagnant les m√©tiers dans la compr√©hension et l‚Äôexploitation des donn√©es ;\nTravailler de mani√®re proactive et collaborative avec les √©quipes Produits et Marketing pour s‚Äôassurer, valider que les mesures, les KPIs et les analyses r√©pondent aux exigences du produit, du marketing et de SteelSeries ;\nUtiliser votre expertise Data afin de valoriser nos Data internes vers un objectif de croissance produit dans une dimension client.\nLa dimension interculturelle est important dans cette √©quipe (√©changes quotidiens avec nos √©quipes bas√©es aux USA, en Europe et en Asie), nous sommes des collaborateurs impliqu√©s et proactifs et tr√®s passionn√©s par les jeux vid√©o et la technologie grand public.\nVous √™tes exp√©riment√©, adaptable, √©nergique et avait l‚Äôenvie de participer activement √† l‚Äôanalyse et la consolidation de notre portefeuille produits pour proposer les meilleurs produits aux joueurs avec un impact commercial direct √©norme et f√©d√©rer de plus en plus de joueurs autour de SteelSeries.\nNos Data Stack:\nSnowflake/ Data warehouse & Amazon S3 / Data Lake\nDbt pour notre ETL\nSegment pour notre Customer Data Platform\nSQL & Python pour notre data stack applicatif\nRedash et Power BI pour la dataviz\nLe profil que nous recherchons :\nVous √™tes un v√©ritable passionn√© de la Data et au-del√† de votre niveau de formation :\nVous √™tes issu(e) d‚Äôune formation sup√©rieure de niveau BAC +5 en √©cole d‚Äôing√©nieur ou de commerce et b√©n√©ficiez d'une exp√©rience de 5 ans minimum dans la Data Analyse\nVous avez en partie construit votre exp√©rience dans des probl√©matiques d‚Äôacquisition et de croissance client dans des domaines digitaux (id√©alement produits Logiciels),\nCapacit√© d‚Äôanalyse crois√©e sur diff√©rents domaines : Logiciels, e-Commerce et produits,\nExp√©rience en SQL & Python (ou similaire) ,\nExp√©rience avec les outils de Dataviz ,\nBonne compr√©hension des structures, des principes, des th√©ories et des meilleures pratiques des bases de donn√©es,\nExp√©rience avec des m√©thodes marketing digitales (A/B testing, groupe t√©moin, clustering, ‚Ä¶)\nAnglais n√©cessaire pour √©changer avec nos coll√®gues aux USA, Asie & Europe : La collaboration est le ma√Ætre mot de notre fa√ßon de travailler !\nVous √™tes curieux et agile dans votre fonctionnement,\nBon communicant, vous savez adapter votre discours en fonction de vos interlocuteurs et avez un sens aigu du service client (interne / externe),\nVous avez le sens de l‚Äôexcellence, du partage,\nVous avez envie de travailler dans l‚Äôunivers du Gaming,\nVous √™tes ambitieux et avez envie de faire partie d‚Äôune aventure qui repousse les limites du gaming et du d√©veloppement produits.\nC‚Äôest un +: Si vous avez d√©j√† travaill√© dans des √©quipes de Software grand public, Web ou e-commerce,de pr√©f√©rence avec des √©quipes produit et / ou marketing et si vous avez connaissance des packages d'analyse et de mod√©lisation de la science des donn√©es en Python et / ou R !\n¬´ Steelseries s'engage en faveur de la diversit√© culturelle, l'√©galit√© hommes-femmes et l'emploi des travailleurs handicap√©s. ¬ª\nNous vous proposons de rejoindre une √©quipe de talents √† taille humaine qui vous attend d√©j√† ! O√π les choses bougent rapidement Et qui b√©n√©ficie de l‚Äôappui d‚Äôun groupe solide et reconnu et nous ouvre de nombreuses perspectives.\nCe que nous proposons :\nUn cadre de travail moderne et innovant avec des locaux √† c√¥t√© de Lille et des conditions de travail plus qu‚Äôagr√©ables (horaires am√©nag√©s, t√©l√©travail, salle de jeux video, salle de sport..) :\nsalaire attractif\nRTT\nmutuelle (familiale) prise en charge √† 100%\ndes tickets restos\ndes primes sur objectifs (jusqu‚Äô√† 2 mois de salaire)\nPossibilit√© de travailler en remote (3 j/hebdo)\nEn v√©lo, en m√©tro ou en voiture : Venez nous rejoindre √† la\nPilaterie de Villeneuve d‚ÄôAscq\n(√† 6 minutes du centre ville de Lille et tout √† c√¥t√© des embranchements routiers)\nShow more\nShow less",
        "details": {
            "JobDetail": [
                "Remote"
            ],
            "TypeContract": "",
            "Salary": "100, 100",
            "Level": "",
            "Experience": "3 an(s)"
        },
        "title": "data analyst",
        "skills": {
            "ProgLanguage": [
                "R",
                "Python"
            ],
            "DataBase": [
                "SQL"
            ],
            "DataAnalytics": [
                "R"
            ],
            "DataVisualisation": [
                "Power BI"
            ],
            "DBMS": [
                "Snowflake"
            ],
            "EnSoftSkils": [
                "Collaboration"
            ]
        }
    },
    {
        "source": "LinkedIn",
        "company": "euRHasi",
        "location": "Paris, √éle-de-France, France",
        "link": "https://fr.linkedin.com/jobs/view/data-analyst-h-f-at-eurhasi-3919187688?position=1&pageNum=15&refId=nmjl8wtZkD%2F%2FLwpmcHztLg%3D%3D&trackingId=tf2e1FWGJSer%2B7hChtmpaQ%3D%3D&trk=public_jobs_jserp-result_search-card",
        "description": "EURHASI recrute pour son client un\nData Analyst (H/F)\nNotre client est un groupe de production d‚Äôartistes\nLe client n‚Äôaccepte pas de candidatures n√©cessitant des d√©marches administratives pour une autorisation de travail (permis de s√©jour, permis de travail, autorisations diverses ...)\nMission\nSous la responsabilit√© de la Directrice du Service Billetterie, le Data Analyst (H/F) aura les missions suivantes, sans que celles-ci ne soient exhaustives :\nOptimisation et analyses business\nAnalyses r√©guli√®res de la performance billetterie et site web de nos artistes et salles durant la vie commerciale des manifestations\nOptimisation des canaux de ventes selon les performances de chacun\nRecommandations d‚Äôaction billetterie en fonction des r√©sultats obtenus\nAnalyses Adhoc selon les demandes du d√©partement ou Groupe.\nGestion de l‚Äôoutil d√©di√© au reporting et √† l‚Äôanalyse des ventes\nFinalisation, √©volution et optimisation de l‚Äôoutil d√©di√© mis en ≈ìuvre au sein du service\nInt√©gration progressive de sources de donn√©es externes √† la billetterie\nInt√©gration progressive de l‚Äôoutil aupr√®s des divers interlocuteurs et accompagnement dans l‚Äôadoption de cet outil\nCollaboration avec les divers services pour cr√©ation et optimisation des dashboards et suivi des Kpi de chaque activit√©\nMise en place de grilles tarifaires et optimisation des revenus durant la vie commerciale des manifestations selon plusieurs crit√®res :\nAnalyse du potentiel de l‚Äôartiste, du spectacle ou de la salle.\nAnalyse de l‚Äôhistorique billetterie d‚Äôune pr√©c√©dente tourn√©e ou spectacle similaire\nBenchmark d‚Äôartistes ou spectacles similaires, de notori√©t√© √©quivalente ou de spectacles similaires\nMise en place de grilles tarifaires √©volutives durant la vie commerciale des manifestations afin de mieux coller √† la demande et au remplissage par cat√©gorie.\nFaire d√©couler de ces grilles tarifaires des budgets billetteries et points d‚Äôatterrissage potentiels.\nProfil\nProfil recherch√©\nIssu(e) d‚Äôune formation BAC+4 minimum,\nVous maitrisez la suite Office (Word / Excel / Outlook)\nVous maitrisez Tableau ou un outil similaire d‚Äôanalyse de donn√©es\nVous avez un bon esprit de synth√®se et d‚Äôanalyse\nVous √™tes rigoureux(se), r√©actif(ve), organis√©(e), pr√©cis(e)\nVous avez un bon relationnel et vous savez faire preuve d‚Äôinitiatives\nVous aimez le travail en √©quipe\nComp√©tences minimum attendues :\nExp√©rience de 3 ans en tant que Data Analyst et non pas \"d√©veloppeur\" ( en dehors de stage et alternance )\nExcellent esprit synth√©tique/d'analyse et tr√®s √† l'aise avec les chiffres\nTr√®s bon relationnel\nArrive √† vulgariser facilement des donn√©es complexes\nProfil qui connait le secteur du divertissement ou du moins qui d√©montre un vrai int√©r√™t\nProfil qui a d√©j√† travaill√© dans un secteur complexe, rythme soutenu (divertissement, grande distribution, etc)\nA noter : poste en lien direct avec la Directrice Billetterie (donn√©es complexes √† traiter) + lien en direct avec le DG\nInformations contractuelles\nLes avantages\nCong√©s additionnels\nT√©l√©travail 1 jour de TT ( lundi - avant la validation de la p√©riode d‚Äôessai ) / 2 jours de TT apr√®s la validation de p√©riode d‚Äôessai de TT\nMutuelle d'entreprise\nTickets restaurant\nRemboursement de transport √† 70%\nShow more\nShow less",
        "details": {
            "JobDetail": [],
            "TypeContract": "",
            "Salary": "",
            "Level": "",
            "Experience": "3 an(s)"
        },
        "title": "data analyst",
        "skills": {
            "DataVisualisation": [
                "Tableau"
            ],
            "EnSoftSkils": [
                "Collaboration"
            ]
        }
    },
    {
        "source": "LinkedIn",
        "company": "Plus que PRO ‚≠ê‚≠ê‚≠ê‚≠ê‚≠ê",
        "location": "Schiltigheim, Grand Est, France",
        "link": "https://fr.linkedin.com/jobs/view/data-analyst-h-f-at-plus-que-pro-%E2%AD%90%E2%AD%90%E2%AD%90%E2%AD%90%E2%AD%90-3910218289?position=2&pageNum=15&refId=nmjl8wtZkD%2F%2FLwpmcHztLg%3D%3D&trackingId=IxHmf727HJhWsO%2B09HCsxQ%3D%3D&trk=public_jobs_jserp-result_search-card",
        "description": "√Ä propos de nous\nDevenez acteur du changement et rejoignez un Leader sur son march√© :\nProt√©gez les consommateurs,\nValorisez le savoir-faire des TPME Fran√ßaises !\nConstruisons ensemble un monde plus s√ªr pour les Consommateurs et plus valorisant pour les Entrepreneurs.\nD√©couvrez un secteur en pleine expansion et vivez avec nous une histoire pleine de succ√®s !\nMission\nTu as la passion de la data et des chiffres en g√©n√©ral ?\nTu aimes observer, d√©crire, analyser et d√©cortiquer de l‚Äôinfo, des tableaux et des flux de donn√©es ?\nTu aimerais participer √† la cr√©ation et l‚Äôoptimisation d‚Äôun syst√®me d‚Äôinformation au service de la performance de Plus que PRO ?\nBienvenue chez Plus que PRO !\n¬´ Un environnement de travail qu‚Äôil est chouette ¬ª\nInt√©grer Plus que PRO, c‚Äôest avoir l‚Äôopportunit√© d‚Äô√©voluer au sein d‚Äôune entreprise ¬´ fun & serious ¬ª. Concr√®tement, cela signifie que pas une journ√©e ne se passe sans que nous puissions √©changer dans la bonne humeur et le second degr√©.\nMais cela veut aussi dire qu‚Äôil y a des choses que nous prenons tr√®s √† c≈ìur, parmi lesquelles : l‚Äôatteinte de nos objectifs, le go√ªt du challenge, la qualit√© de la collaboration et la confiance que nous portent nos diff√©rents interlocuteurs.\nTu participeras √† l‚Äôanalyse de l‚Äôactivit√© des diff√©rents p√¥les d‚Äôactivit√© de Plus que PRO.\nTu participeras √† la cr√©ation d‚Äôoutil de mesure de la performance et d‚Äôaide √† la d√©cision au b√©n√©fice de chaque responsable de p√¥le.\nTu soutiendras les responsables de p√¥le √† la mise √† jour des tableaux de bord et √† la construction des remont√©es d‚Äôinformation aux dirigeants.\nTu auras l‚Äôopportunit√© de mener diverses analyses ad-hoc en fonction des besoin des √©quipes et formuler des recommandations & des alertes √† destination des BU & de la direction.\nProfil\nDe formation initiale : √âcole d‚Äôing√©nieur / √âcole de commerce dominante Finance / Gestion et/ ou en pr√©paration d‚Äôun dipl√¥me master en data management.\nTu recherches une exp√©rience dans les m√©tiers de la Gestion, des Analytics & de l‚ÄôInnovation.\nTu fais preuve de curiosit√©, d‚Äôune bonne culture technologique et d‚Äôun int√©r√™t pour le d√©veloppement de solutions de traitement de donn√©es.\nTu as une forte app√©tence pour l‚Äôanalyse et la manipulation de donn√©es.\nId√©alement, tu b√©n√©ficies d‚Äôune exp√©rience professionnelle pr√©alable dans un environnement demandant une forte capacit√© d‚Äôadaptation et d‚Äôanalyse.\nTu as une bonne capacit√© √† traduire les analyses dans des outils de mesure et de communication afin de les diffuser pour aider le pilotage et la prise de d√©cision.\nR√©f√©rence de l'offre : g5fwk6y375\nShow more\nShow less",
        "details": {
            "JobDetail": [],
            "TypeContract": "",
            "Salary": "",
            "Level": "",
            "Experience": null
        },
        "title": "data analyst",
        "skills": {
            "EnSoftSkils": [
                "Communication",
                "Collaboration"
            ]
        }
    },
    {
        "source": "LinkedIn",
        "company": "Equativ",
        "location": "Paris, √éle-de-France, France",
        "link": "https://fr.linkedin.com/jobs/view/data-analyst-at-equativ-3910669096?position=3&pageNum=15&refId=nmjl8wtZkD%2F%2FLwpmcHztLg%3D%3D&trackingId=R7JjLGn7MOEFymtoEts6nA%3D%3D&trk=public_jobs_jserp-result_search-card",
        "description": "üë´ About the team\nHelping the company be fully data-driven is not just a buzzword, it is our mission at Equativ. We, the Data Analytics team at Equativ, maximize Equativ‚Äôs efficiency by enabling easy and permanent access to quality data, valuable insights & rigorous thinking. Our responsibility is to ensure our local and central teams, clients and partners, make informed business decisions. To do so, we leverage huge volumes of data (Equativ handles 150Bn Auctions per day) in a state-of-the-art tech stack (AirFlow, Snowflake, Tableau‚Ä¶) in order to provide actionable insights to all teams at Equativ!\n‚úèÔ∏è What you'll do\nCollaborate with the Product Analytics Manager and a dynamic team of 15 analysts within the Analytics team\nSupport the product team in solving challenges through advanced analyses, providing actionable insights and sanity checks on new features, and prioritizing roadmap topics based on estimated business value\nCreate and maintain performance dashboards used by product and service teams, enabling them to better understand their customers‚Äô performance and achieve their objectives\nDevelop your technical knowledge of our product, growing to proactively identify areas of concern, and propose corrective actions to optimize client setups and buying strategies and ultimately drive Equativ‚Äôs revenue growth\nDepending on your interests and skills, you may also:\nDevelop and maintain data tools tailored to specific use cases\nParticipate in sourcing, continuously enriching our databases with new internal data\nü§ù Collaboration\nEngage with Product, Product Marketing, and R&D leaders and teams to align on recent deliverables, understand upcoming needs, and prioritize effectively\nWork closely with cross-functional teams serving our B2B Marketplace, driving actions based on data-driven insights\nEnsure widespread adoption of metrics and reports through effective internal go-to-market strategies (beta-testing, communication, training, and continuous optimization)\nü§© Why You Should Join Us:\nOpportunity to work with modern data tools (Snowflake, Tableau, Airflow, Python, Google BigQuery) and technologies in an intellectually stimulating environment\nCollaborative culture that encourages professional growth and development\nImpactful role with opportunities to drive tangible results and contribute to company growth\nüí™ About you\nYou are curious, love solving problems, and want to develop your autonomy and expertise\nExcellent communication skills and ability to form recommendations and present insights to both technical and non-technical audiences\nMaster‚Äôs degree or higher in a quantitative or business field (Statistics, Mathematics, Econometrics, Economics, Finance, etc.)\nYou are fluent in English\nTechnical knowledge of SQL is a must\nBasic knowledge of reporting software (Tableau)\nPython and other programming languages are a plus\nüëã About us\nEquativ is the new single name for Smart Adserver, DynAdmic, LiquidM and Nowtilus ‚Äî four proven innovators in advertising technology. The vertically integrated company provides brand and privacy-safe solutions that empower its clients to achieve maximum impact while respecting the rights of consumers. The union combines client expertise and engineering excellence to serve the interests of both the supply- side and demand-side with equal professionalism and technical sophistication.\nHeadquartered in Paris and New York, Equativ operates globally with a team of more than 550 people in 20 offices. Equativ offers the market its own independent ad server, SSP, buyer tools, and media services to fulfill the promise of advertising technology. Learn more at Equativ.com.\nThe company is ranked on the Deloitte Technology Fast 500 EMEA and in the Financial Times‚Äô FT 1000: Europe‚Äôs Fastest-Growing Companies.\nEquativ (formerly Smart AdServer) has been awarded the HappyIndex@Work label and is proud to be among the best companies in the ChooseMyCompany ranking, recognized for its flexible working environment.\nCome and lead the charge with us in building a transparent ecosystem based on quality!\nEquativ is an equal opportunity employer. Equal access to employment, services, and programs are available to everyone, regardless of race, color, ancestry, religion, sex, national origin, sexual orientation, age, citizenship, marital status, disability, gender identity, or Veteran status. If you require reasonable accommodation throughout the application and/or interview process, please contact the recruitment team at ta-team@equativ.com\nShow more\nShow less",
        "details": {
            "JobDetail": [
                "Full"
            ],
            "TypeContract": "",
            "Salary": "",
            "Level": "",
            "Experience": null
        },
        "title": "data analyst",
        "skills": {
            "ProgLanguage": [
                "R",
                "Python"
            ],
            "DataBase": [
                "SQL"
            ],
            "DataAnalytics": [
                "R"
            ],
            "DataVisualisation": [
                "Tableau"
            ],
            "DBMS": [
                "BigQuery",
                "Snowflake"
            ],
            "Automation": [
                "Airflow"
            ],
            "Collaboration": [
                "Teams"
            ],
            "EnSoftSkils": [
                "Communication",
                "Collaboration"
            ]
        }
    },
    {
        "source": "LinkedIn",
        "company": "Treezor",
        "location": "Paris, √éle-de-France, France",
        "link": "https://fr.linkedin.com/jobs/view/data-analyst-h-f-at-treezor-3882828889?position=4&pageNum=15&refId=nmjl8wtZkD%2F%2FLwpmcHztLg%3D%3D&trackingId=7DektiSvMTNL96mO8i%2FmFQ%3D%3D&trk=public_jobs_jserp-result_search-card",
        "description": "Fond√©e en 2015 et acquise en 2019 par le groupe Soci√©t√© G√©n√©rale, Treezor est un √âtablissement de Monnaie √âlectronique, agr√©√© par l‚ÄôACPR, autoris√© √† op√©rer dans 25 pays et membre principal du r√©seau Mastercard.\nTreezor est le pr√©curseur du ‚ÄúBanking as a Service‚Äù et int√®gre dans son offre les dimensions technologiques, r√©glementaire et s√©curitaire pour proposer en API l‚Äôacc√®s √† l‚Äôensemble des services de la cha√Æne de paiements, en acquisition et √©mission. Treezor consacre une partie importante de ses ressources au d√©veloppement de nouvelles technologies afin de soutenir l‚Äôinnovation et la strat√©gie de croissance de ses clients.\nüí∂ 80 milliards+ d'euros de flux g√©r√©s depuis notre lancement\nüí≥ 5 millions+ cartes de paiement √©mises\nü§ù 150+ clients (n√©obanques, n√©obanques professionnelles, marketplaces...)\nüåç 25 pays couverts\nüë• 250+ collaborateurs\nüí¨ 20+ nationalit√©s\nPour accompagner sa croissance, Treezor recherche un(e) Data Analyst (H/F).\nL‚Äô√©quipe Data a pour mission de d√©mocratiser l‚Äôusage de la Data √† tous les niveaux de l'entreprise.\nLe Data Analyst joue un r√¥le cl√© pour permettre une large adoption de la Data sous ses diff√©rents aspects au sein de Treezor. Il accompagne les √©quipes m√©tiers pour affiner leurs besoins et d√©finir la meilleure fa√ßon de repr√©senter la donn√©e.\nVous aurez pour principales missions :\nExtraire divers indicateurs de notre Data Lake\nConstruire des Dashboards pour les √©quipes m√©tiers et les conseiller sur le meilleure mani√®re d‚Äôexploiter la donn√©e\nExploiter des sources de donn√©es vari√©es (fichiers CSV, Google Docs, etc.) pour enrichir les donn√©es du Data Lake\nComprendre pr√©cis√©ment les probl√©matiques m√©tiers et les traduire de mani√®re analytique\nVoici les pr√©requis pour ce poste :\nBac+3/5 dans les domaines suivants : Technicien/Ing√©nieur informatique avec une sp√©cialisation ou bien une forte app√©tence Data\nMa√Ætrise du langage SQL, id√©alement sur plusieurs types de bases de donn√©es\nConnaissance d'un outil de visualisation de donn√©es (Quicksight est un plus)\nCompr√©hension de la mod√©lisation de donn√©es dans des bases de donn√©es relationnelles\nApp√©tence pour les interactions avec les √©quipes m√©tiers\nConnaissance de l‚Äôenvironnement AWS\nCapacit√© √† comprendre rapidement les environnements techniques complexes\nQualit√© de pr√©sentation et de r√©daction en fran√ßais et en anglais\nAutonomie\nMa√Ætrise du langage Python dans un contexte Data serait un plus\nRejoindre l‚Äôaventure TREEZOR c‚Äôest aussi :\nüí• Un environnement agile, dynamique et en pleine croissance et des bureaux en plein c≈ìur de Paris (pr√®s de l‚ÄôArc de Triomphe) et de Rennes (pr√®s de la gare)\nüìñ Des opportunit√©s d'apprentissage constantes\nü§ù Une culture collaborative o√π la cr√©ativit√© est encourag√©e\nüí∞ Une r√©mun√©ration comp√©titive\nüè† Organisation de travail hybride avec une participation financi√®re pour vous √©quiper √† la maison\nüöÄ Des avantages pour les salari√©s (des subventions, des cartes cadeaux etc.) et des √©v√©nements cr√©√©s par le CSE (loterie, sorties de groupe dans des parcs d'attractions, grands √©v√©nements mondiaux comme Roland Garros et Rolex Paris Master, etc.)\nAu travers de ses recrutements, Treezor cultive une politique en faveur de la diversit√©, de l‚Äô√©galit√© professionnelle et de l‚Äôemploi des travailleurs handicap√©s.\nShow more\nShow less",
        "details": {
            "JobDetail": [
                "Hybride"
            ],
            "TypeContract": "",
            "Salary": "",
            "Level": "Bac+3",
            "Experience": null
        },
        "title": "data analyst",
        "skills": {
            "ProgLanguage": [
                "Python"
            ],
            "DataBase": [
                "SQL"
            ],
            "CloudComputing": [
                "AWS"
            ]
        }
    },
    {
        "source": "LinkedIn",
        "company": "RAJA",
        "location": "Roissy-en-France, √éle-de-France, France",
        "link": "https://fr.linkedin.com/jobs/view/business-data-analyst-at-raja-3916636230?position=5&pageNum=15&refId=nmjl8wtZkD%2F%2FLwpmcHztLg%3D%3D&trackingId=sLuBYUBqtui9ZBHFtOsmcQ%3D%3D&trk=public_jobs_jserp-result_search-card",
        "description": "Description Du Poste\nAu sein du pole achat, vos missions seront:\nRecueillir et analyser l‚Äôensemble des donn√©es autour des produits sur la base des extractions MDM, ERP ou autres applicatifs pour contribuer √† la construction et la mise en ≈ìuvre du mod√®le de donn√©es cible\nEtudier, recouper, retraiter et nettoyer des donn√©es pour les transformer en informations exploitables\nProposer et cr√©er des KPI et des Dashboard pertinents\nParticiper aux r√©unions d‚Äô√©quipe MDM et toute autre instance projet n√©cessaire\nContribuer au chantier de refonte de la BI produit : expression des besoins propres √† la BDDP\nContribuer √† la d√©finition fonctionnelle du monitoring de la donn√©e produit\nMonter en comp√©tence sur la gouvernance et la maintenance de la donn√©e produit Groupe Pilotage des analyses en Run\nExtraire les donn√©es √† partir des sources de donn√©es pertinentes\nContr√¥ler la qualit√© de donn√©es\nAnalyser et exploiter les donn√©es du MDM post mise en ≈ìuvre du nouveau data model\nAssurer une mise √† jour r√©guli√®re\nProposer et cr√©er des KPI et des Dashboard pertinents\nVulgariser et synth√©tiser visuellement des donn√©es pour les rendre accessibles aux d√©cideurs et √† sa hi√©rarchie\nMettre en place des process de requ√™tes automatiques afin de faciliter l‚Äôextraction de donn√©es\nProduire des analyses en fonction des attentes de sa Direction\nAssurer la cr√©ation/modification des articles pour les soci√©t√©s Office (JPG / Mondoffice et Kalamazoo)\nAssurer le r√¥le de r√©f√©rent data MDM pour les soci√©t√©s Office\nProfil recherch√©\nDe formation sup√©rieure (Bac +4/5) en ing√©nierie informatique / statistique, ou mast√®re sp√©cialis√© Big Data, avec une exp√©rience de 2 ans sur un emploi similaire.\nVous Avez\nDe la rigueur\nUn esprit analytique et de synth√®se\nUne forte app√©tence pour les statistiques\nLe sens du service\nShow more\nShow less",
        "details": {
            "JobDetail": [],
            "TypeContract": "",
            "Salary": "",
            "Level": "",
            "Experience": "2 an(s)"
        },
        "title": "data analyst",
        "skills": {
            "Other": [
                "Statistiques",
                "Big Data"
            ]
        }
    },
    {
        "source": "LinkedIn",
        "company": "TotalEnergies",
        "location": "Courbevoie, √éle-de-France, France",
        "link": "https://fr.linkedin.com/jobs/view/data-analyst-rh-d%C3%A9butant-e-h-f-at-totalenergies-3920520940?position=6&pageNum=15&refId=nmjl8wtZkD%2F%2FLwpmcHztLg%3D%3D&trackingId=qUkbsze2oibJsQwPoMp5WQ%3D%3D&trk=public_jobs_jserp-result_search-card",
        "description": "Profil du candidat\nVous √™tes r√©cemment dipl√¥m√©.e d'un Bac+5/Master 2 et recherchez une exp√©rience stimulante dans le domaine des RH et Data RH, au c≈ìur d‚Äô√©quipes internationales, engag√©es dans la transition √©nerg√©tique !\nNous vous proposons un contrat de professionnalisation temps plein qualifiant de 12 mois incluant 15% de formation interne (m√©tier, linguistique, outils‚Ä¶). Ces formations sont dispens√©es en interne par des organismes s√©lectionn√©s par TotalEnergies. Ce contrat vous permettra d‚Äôacqu√©rir une ann√©e d‚Äôexp√©rience professionnelle tout en √©tant form√© aux sp√©cificit√©s de votre m√©tier en lien avec les activit√©s de la Compagnie. Un r√©el atout pour booster votre employabilit√© !\nPour postuler √† cette offre, vous devez imp√©rativement poss√©der, √† la date d‚Äôembauche, un titre de s√©jour valide pour la p√©riode couverte par cette offre (attention, la conclusion de ce contrat de professionnalisation ne permet pas la d√©livrance d‚Äôun titre de s√©jour (article R.52221-6 du Code du travail).\nATTENTION CE POSTE NE S'ADRESSE PAS AUX PERSONNES RECHERCHANT UNE ALTERNANCE AVEC UNE ECOLE OU UNE FORMATION DIPLOMANTE MAIS AUX PERSONNES RECEMMENT DIPLOMEES A LA RECHERCHE D‚ÄôUNE PREMIERE EXPERIENCE\nConnaissances techniques et informatiques :\nAnalyse et gestion de bases de donn√©es\nMode gestion de projet\nExcel (Excellent niveau)\nPower BI (Navigation assur√©e dans l'outil pour mont√©e en comp√©tence des √©quipes en place)\nBO Business Object (utile)\nAnglais\nSavoir-√™tre :\nRigueur\nOrganisation\nGo√ªt du travail en √©quipe\nTotalEnergies recherche avant tout des comp√©tences et des personnalit√©s et s‚Äôouvre √† tous les talents repr√©sentant la diversit√© et la richesse des profils. Depuis de nombreuses ann√©es, nous menons une politique volontariste favorisant l‚Äôinsertion professionnelle et l‚Äôaccompagnement dans l‚Äôemploi de nos salari√©s en situation de handicap tout au long de leur carri√®re.\nSi cette offre vous int√©resse alors n'attendez plus... Postulez chez TotalEnergies !\nActivit√©s\nNous recherchons un sp√©cialiste Power Bi pour accompagner nos recherches, envisager des automatisations et simplifications, lancer des d√©veloppements, am√©liorer nos reportings, les faire √©voluer tout en gagnant du temps √† r√©pondre aux demandes ponctuelles qui interviennent au fil de l‚Äôeau (listes de diffusion, √©tudes, populations).\nLe temps de travail sera r√©parti entre un v√©ritable back-office de l'√©quipe Data et le travail direct avec la fonction RH et les √©quipes qui utilisent les donn√©es RH de la branche.Le candidat retenu devra suivre l'√©quipe dans ce qu'elle produit quotidiennement ou p√©riodiquement, maitriser les sujets dans la pratique et devenir aussi un potentiel back up ou relais possible selon les p√©riodes et les demandes. Faire, comprendre et connaitre est la meilleure passerelle pour construire, orienter et am√©liorer les process.\nSur l'aspect Technique de l'outil, un cahier des charges sera constitu√© au fur et √† mesure pour tenter de simplifier certaines √©tudes, de diminuer le d√©lai de r√©alisation des livrables (aujourd'hui sous excel), d'assurer la maintenance des dashboards d√©j√† r√©alis√©s sur PowerBI et utilisant le codage sous Power Query et et de trouver les astuces pour monitorer au mieux les donn√©es et rendre les visuels les plus attractifs possibles.\nContexte et environnement\nAccompagn√© de son tuteur et de ses futurs coll√®gues data analystes, le candidat retenu int√®grera un open space bienveillant, agr√©able et dynamique de +/- 15 personnes, qui travaille en mode \"projet\". Entre les syst√®mes d‚Äôinformation RH et la partie d√©veloppement, la passerelle est quasi invisible et l‚Äôentraide un point fort .\nShow more\nShow less",
        "details": {
            "JobDetail": [
                "Temps plein"
            ],
            "TypeContract": "",
            "Salary": "",
            "Level": "Bac+5",
            "Experience": null
        },
        "title": "data analyst",
        "skills": {
            "ProgLanguage": [
                "R"
            ],
            "DataAnalytics": [
                "R"
            ],
            "DataVisualisation": [
                "Power BI"
            ]
        }
    },
    {
        "source": "LinkedIn",
        "company": "Balzac Paris",
        "location": "Paris, √éle-de-France, France",
        "link": "https://fr.linkedin.com/jobs/view/data-analyst-h-f-alternance-at-balzac-paris-3920291908?position=7&pageNum=15&refId=nmjl8wtZkD%2F%2FLwpmcHztLg%3D%3D&trackingId=3NSSzEYWCpKlpLJFbU7ZWA%3D%3D&trk=public_jobs_jserp-result_search-card",
        "description": "Balzac Paris est √† la recherche d'un.e\nData Analyst H/F\nen alternance !\nRattach√©.e au RAF, vous serez garant.e de la mod√©lisation et de l'exploitation de la base de donn√©es pour accroitre les performances de l'entreprise.\nA Ce Titre, Vous Aurez Les Missions Suivantes\nMod√©lisation de la base de donn√©es\nIdentifier les besoins en travaillant avec les √©quipes m√©tiers pour construire les diff√©rents mod√®les et analyses\nCollecter, organiser, et mod√©liser les donn√©es (donn√©es business)\nExploitation de la donn√©e\nProduire des analyses m√©tiers et faire des recommandations aux √©quipes\nFluidifier les √©changes avec nos partenaires (filtrer les demandes, co-construire les solutions)\nAccompagnement des √©quipes\nParticiper √† r√©pandre la culture data chez Balzac Paris en mettant la donn√©e au centre de chaque prise de d√©cision\nAccompagner les √©quipes pour les rendre le plus ind√©pendantes possibles dans leur consommation de donn√©e (document de formation, tuto)\n‚ú®Profil Recherch√©\nFormation : bac +4/5\nAptitude : Ma√Ætriser le stockage de donn√©es\nTr√®s forte capacit√© en Excel (VBA a minima)\nConna√Ætre les outils de Web Analytics : Google Analytics, Power BI, Biron‚Ä¶\nComp√©tences en math√©matiques/statistiques\nEsprit d‚Äôanalyse et de synth√®se\nCapacit√© d‚Äô√©coute\nRigueur\nOrganisation\nSens de la p√©dagogie\n‚ù§Ô∏èCe Que Nous Vous Offrons\nDes bureaux en plein c≈ìur de Paris avec des espaces de travail agr√©ables\nDes coll√®gues enthousiastes et de bonne humeur au quotidien\nLe remboursement √† hauteur de 50% de votre titre de transports\nUne mutuelle 100% prise en charge\nUne carte restaurant Swile\nDes r√©ductions sur notre site Balzac Paris et un acc√®s √† nos ventes priv√©es du personnel ! üéÅ\nVous souhaitez nous rejoindre et √™tre un acteur incontournable dans une entreprise en pleine croissance? N‚Äôh√©sitez plus et postulez d√®s maintenant !\n¬´ Le g√©nie a cela de beau qu‚Äôil ressemble √† tout le monde et que personne ne lui ressemble. ¬ª\nSur les traces d‚ÄôHonor√© de Balzac et parce que chacun d‚Äôentre vous est unique, nous nous engageons en faveur de la diversit√© au sein de nos √©quipes.\nShow more\nShow less",
        "details": {
            "JobDetail": [],
            "TypeContract": "",
            "Salary": "",
            "Level": "",
            "Experience": null
        },
        "title": "data analyst",
        "skills": {
            "DataVisualisation": [
                "Power BI"
            ],
            "Other": [
                "Statistiques"
            ]
        }
    },
    {
        "source": "LinkedIn",
        "company": "Onatera",
        "location": "Aix-en-Provence, Provence-Alpes-C√¥te d'Azur, France",
        "link": "https://fr.linkedin.com/jobs/view/alternance-data-analyst-h-f-at-onatera-3872986165?position=8&pageNum=15&refId=nmjl8wtZkD%2F%2FLwpmcHztLg%3D%3D&trackingId=2%2FdoWWFGXCwnyAxCyhWebQ%3D%3D&trk=public_jobs_jserp-result_search-card",
        "description": "Chez Onatera, depuis plus de 12 ans, la nature nous inspire, nous guide, nous comble.\nNotre mission est simple : proposer un choix le plus large de produits et d‚Äôingr√©dients naturels, efficaces et sensoriels √† nos clients pour qu‚Äôils prennent soin d‚Äôeux, de leur corps et de leur esprit.\nCette approche holistique, nous pousse √† sans cesse d√©velopper nos univers afin que nos clients puissent trouver en un seul et m√™me endroit tout ce dont ils ont besoin pour prendre soin d'eux plus naturellement et plus durablement. Forts de notre exp√©rience, et convaincus que nous pouvons offrir √† nos clients des produits encore meilleurs et au meilleur prix, nous sommes devenus fabricant, et avons ouvert notre usine √† Salon de Provence.\nUn grand pas qui permet aujourd'hui de proposer plus de 1500 produits, 300 plantes, 200 actifs naturels et 120 huiles essentielles pour que chaque client s‚Äôoccupe de son corps, de son esprit et de son c≈ìur.\nInt√©grer Onatera c'est rejoindre un projet collectif, avec des √©quipes passionn√©es et unies par l‚Äôenvie de rendre le bien-√™tre au naturel accessible √† tous.\nVous √™tes √† la recherche d‚Äôune alternance responsabilisante et vous avez envie de rejoindre une aventure dans laquelle chaque effort contribue au d√©veloppement d‚ÄôOnatera ?\nRejoignez nos √©quipes pour une alternance en tant que Data Analyst (h/f) √† Aix en Provence. Au sein de la direction e-commerce, vous contribuez √† l‚Äôanalyse de la data pour optimiser le pilotage de l‚Äôensemble des leviers d‚Äôacquisition online dans une logique d‚Äôacquisition √† la fois performante et qualitative.\nVos missions :\nParticiper au d√©ploiement du plan d‚Äôacquisition Web (plan d‚Äôacquisition et de fid√©lisation des clients pertinent) avec notre agence et la direction e-commerce pour accompagner la croissance, dans le respect d‚Äôun cadre budg√©taire pr√©alablement d√©fini.\nCollecter, mesurer, optimiser, tester, mesurer encore la data‚Ä¶pour contribuer √† l‚Äôaugmentation du volume de conversion et pour suivre les performances des actions mises en place en acquisition.\nVeille active sur les tendances et compilation des best practices.\nPour ce projet, nous recherchons un √©tudiant qui a une bonne compr√©hension globale du fonctionnement du digital, des leviers pour acqu√©rir du trafic, et, avec une sensibilit√© aux environnements BtoC. Les must have :\nVous poss√©dez d‚Äôexcellentes capacit√©s analytiques pour √©valuer et restituer les performances des actions.\nVous √™tes curieux et faites preuve de pro-activit√© et de rigueur pour piloter vos projets efficacement.\nVotre esprit d‚Äô√©quipe sera un atout pour collaborer avec les √©quipes Marketing/ CRM/ Communication ou encore Tech.\nVous ma√Ætrisez Excel √† un niveau avanc√©.\nCe poste est ouvert aux personnes en situation de handicap.\nD√©couvrez nos derni√®res actualit√©s sur notre page LinkedIn & abonnez vous -> Onatera\nShow more\nShow less",
        "details": {
            "JobDetail": [],
            "TypeContract": "",
            "Salary": "",
            "Level": "",
            "Experience": "12 an(s)"
        },
        "title": "data analyst",
        "skills": {
            "EnSoftSkils": [
                "Communication"
            ]
        }
    },
    {
        "source": "LinkedIn",
        "company": "Foxintelligence",
        "location": "Paris, √éle-de-France, France",
        "link": "https://fr.linkedin.com/jobs/view/lead-data-analyst-at-foxintelligence-3835174526?position=9&pageNum=15&refId=nmjl8wtZkD%2F%2FLwpmcHztLg%3D%3D&trackingId=J43OIwMa5fITBnT1J74P6w%3D%3D&trk=public_jobs_jserp-result_search-card",
        "description": "Chez Foxintelligence, nous sommes des amoureux de la data. ü§ì\nNotre mission est de rendre les consommateurs et les marques plus intelligents, gr√¢ce √† une donn√©e de march√© r√©volutionnaire issue de l'intelligence collective. Pour les consommateurs, Foxintelligence rend accessibles et utiles leurs donn√©es transactionnelles issues de leurs bo√Ætes mail. En les anonymisant, nous cr√©ons des statistiques uniques qui permettent aux marques de rester en phase avec les produits qui se vendent le mieux et les attentes des consommateurs.\nNous publions une application grand public aim√©e par des millions de personnes (Cleanfox, 15m+ de t√©l√©chargements, 4.8/5 üíñ sur l'app store et le play store) et pr√©parons le lancement d'une app de bilan carbone √† l'exp√©rience radicalement nouvelle. Gr√¢ce √† notre plateforme data, elle va rendre possible une prise de conscience massive des enjeux du changement climatique üåç et des actions individuelles possibles pour le combattre. Nous pensons que l'information est une force de changement puissante, lorsqu'elle s'appuie sur la data.\nUtilisant ces donn√©es personnelles totalement anonymis√©es, notre plateforme SaaS foxintelligence.io est devenue la r√©f√©rence de la market intelligence digitale en Europe avec des dizaines de grands groupes clients. Le point commun entre Deliveroo, Just Eat, BackMarket ou The Boston Consulting Group ? Ils vont tr√®s vite (on ne s'ennuie pas avec eux !) et ils nous font tous confiance !\nSoutenus par des investisseurs de premier plan et r√©cemment int√©gr√©s au groupe NielsenIQ (17m lev√©s aupr√®s de Daphni, Partech, GFC et eFounders), nous sommes maintenant √† la conqu√™te de l'Europe et en phase d'hyper-croissance\nSi notre FoxHQ reste √† Paris, notre √©quipe de plus de 120 talents pluridisciplinaires (tech, data et business) travaille depuis partout en France. Nous pensons que notre politique de remote, notre culture forte (bienveillance, exigence, r√©silience et data-first) et notre innovation permanente en termes de modes de travail (ex. grille de salaire transparente, formation au changement climatique, transparence sur la strat√©gie) sont les cl√©s de notre r√©ussite collective.... et de ta r√©ussite avec nous !\nJob Description\nFoxintelligence recherche un(e)\nLead Data Analyst.\nTes responsabilit√©s au quotidien :\nData Analysis/Engineering\nAutomatisation & scale : Construire des outils de productivit√© √† destination des √©quipes M√©tiers pour leur permettre de gagner en efficacit√© (d√©finition de process transverses, automatisation de t√¢ches avec Python, mise √† disposition de dashboards Tableau d'investigations etc...)\nExpertise technique : Avoir une parfaite ma√Ætrise de notre pipeline Data et √™tre le/la r√©f√©rent(e) technique aupr√®s des √©quipes M√©tiers. Les accompagner au quotidien, les former et les rendre autonomes\nAnalyses : Faire des analyses approfondies sur une vari√©t√© d'enrichissements comme l'√¢ge des consommateurs ou la g√©olocalisation des commandes. Remettre en question ces enrichissements, identifier les am√©liorations n√©cessaires et construire la roadmap qui nous permettra de scaler √† l'international\nManagement : Superviser et faire grandir les data analysts de l'√©quipe\nProduct Management Data\nProjets strat√©giques : Orchestrer les initiatives majeures et √† fort potentiel pour Fox sur le plan Data. Etre l'interlocuteur/trice des √©quipes internes et externes (NielsenIQ, partenaires strat√©giques) et piloter les projets de A √† Z : d√©finition de la roadmap, structuration et ex√©cution. A titre d'exemple, l'un de nos challenges actuels est l'int√©gration avec NielsenIQ pour rendre possibles des analyses omnicanales (online/offline)\nProduct Owner de nos applications internes :\nD√©finir les besoins avec les √©quipes M√©tiers\nConcevoir de nouveaux outils et fonctionnalit√©s, et accompagner les √©quipes dans leur prise en main\nConstruire la roadmap, la d√©composer en tickets, tester et communiquer aupr√®s de l'ensemble des √©quipes\nRequirements\nComp√©tences n√©cessaires (ce qu'il te faut pour r√©ussir sur ce poste) :\nSoft Skills\nEsprit analytique et structur√©\nMotiv√©(e) par les d√©fis et √† l'aise face √† des probl√®mes nouveaux et complexes\nCapacit√© √† collaborer avec des clients de s√©niorit√© diverses et diff√©rents interlocuteurs internes (Marketing & Sales, Produits & Tech, R&D data)\nEnvie d'apprendre, de contribuer spontan√©ment √† son environnement et d'aider l'√©quipe √† s'am√©liorer\nHard Skills\nCapacit√© √† comprendre et challenger rapidement le fonctionnement de produits techniques complexes : soit par une exp√©rience pertinente (auto-formation, projet perso), soit par une formation adapt√©e (grande √©cole d'ing√©nieur ou √©quivalent √† l'√©tranger, √©cole de commerce avec parcours avanc√© en data)\nCapacit√© √† g√©rer simultan√©ment de multiples projets et √† prendre des d√©cisions rapidement au regard des enjeux techniques mais aussi business, y compris √† divers niveaux de risque ou d'incertitude\nMa√Ætrise de Tableau, SQL (id√©alement BigQuery), Github, Airflow, Google Cloud Platform\nAvanc√© en R ou en Python\nExp√©rience\n3-5 ans d'exp√©rience en data, op√©ration ou produit dans des startups/environnements tech, ou en cabinet de conseil\nComp√©tences bonus\nExp√©rience pass√©e dans un environnement tech o√π on passe √† l'√©chelle, ou au lancement d'un produit data/tech de z√©ro\nConnaissances en IA/LLM\nLadies\nLes √©tudes montrent que les femmes ont moins tendance √† postuler √† une offre d'emploi quand elles n'ont pas toutes les qualifications requises. Ladies, ne vous mettez pas de barri√®re et donnez-nous la chance de nous faire notre propre avis, nous serons toujours ravis d'√©changer avec vous ! Si notre raison d'√™tre vous parle, postulez !\nSelf-made data lovers\nLes dipl√¥mes c'est bien, les skills c'est mieux et l'exp√©rience t'en donne. Aucun dipl√¥me n'est requis chez nous, c'est les comp√©tences et l'√©nergie qui comptent !\nRecruitment process\nRound 0 : entretien (fit) avec notre Head of People\nRound 1 : entretien (exp√©rience et fit) avec notre Head of Data Management\nTest technique\nRound 2: entretiens avec le/la manager de l'√©quipe\nDecision round: entretien avec deux membres de l'√©quipe\nBenefits\nAvantages/ce que nous offrons :\nSalaire et variable comp√©titifs\nRemote friendly (+ budget am√©nagement de l'espace de travail @Home)\nBonus Cooptation\nBonne assurance sant√© (Alan)\nTitres restaurants (swile) : pris en charge √† 60% par Fox\nSyst√®me de cr√®che subventionn√© par Fox\nCulture forte et pratiques de management √† la pointe (strat√©gie et r√©sultats financiers transparents, feedback 360, grille de salaire innovante et transparente etc.)\n4 jours par an offert pour faire du b√©n√©volat (partenariat avec la plateforme vendredi)\nShow more\nShow less",
        "details": {
            "JobDetail": [
                "Remote"
            ],
            "TypeContract": "",
            "Salary": "3",
            "Level": "",
            "Experience": "5 an(s)"
        },
        "title": "data analyst",
        "skills": {
            "ProgLanguage": [
                "R",
                "Python"
            ],
            "DataBase": [
                "SQL"
            ],
            "DataAnalytics": [
                "R"
            ],
            "DataVisualisation": [
                "Tableau"
            ],
            "CloudComputing": [
                "Google Cloud Platform"
            ],
            "DBMS": [
                "BigQuery"
            ],
            "Automation": [
                "Airflow"
            ],
            "Other": [
                "Statistiques",
                "Cloud"
            ]
        }
    },
    {
        "source": "LinkedIn",
        "company": "Terres d'Aventure",
        "location": "Paris, √éle-de-France, France",
        "link": "https://fr.linkedin.com/jobs/view/data-analyst-at-terres-d-aventure-3866774439?position=10&pageNum=15&refId=nmjl8wtZkD%2F%2FLwpmcHztLg%3D%3D&trackingId=V1LeoVp4H%2Bl1pmy2ppkJfQ%3D%3D&trk=public_jobs_jserp-result_search-card",
        "description": "√Ä propos de nous\nOsez l'aventure et transformez votre passion en carri√®re !\nDepuis plus de 45 ans, nous explorons le monde avec une curiosit√© insatiable et une passion intacte pour organiser des voyages inoubliables ! Sp√©cialiste de la randonn√©e, du trekking et du voyage √† v√©lo,\nTerres d‚Äôaventure est le num√©ro 1 du voyage d‚Äôaventure\nfaisant ainsi voyager chaque ann√©e des milliers d‚Äôaventuriers dans le monde entier. Engag√©s dans le tourisme durable nous proposons des voyages respectueux des pays dans lesquels nous allons et 100% carbone absorb√©s.\nVous √™tes passionn√©¬∑e par les voyages et la randonn√©e ? Vous souhaitez int√©grer une entreprise\ndynamique et innovante\navec des\nvaleurs fortes\net investie dans le\ntourisme durable\n? Rejoignez l‚Äô√©quipe Terdav ! www.terdav.com\nMission\nLe service Business Analyst est un service strat√©gique pour l‚Äôensemble de l‚Äôentreprise.\nVos Missions Sont Les Suivantes\nLa r√©alisation d‚Äô√©tudes marketing, commerciales et d‚Äôanalyses de donn√©es\nD√©finition, √©laboration et d√©ploiement de reportings marketing et commerciaux p√©riodiques sur l‚Äôactivit√© de la soci√©t√©, √† la demande de la direction ou des diff√©rents services de l‚Äôentreprise\nAnalyses ad hoc sur des sujets sp√©cifiques √† la demande de la direction ou des diff√©rents services de l‚Äôentreprise\nLa Gestion Des Process\nAnalyse des process internes et externes en fonction des projets et √† la demande des directions de la soci√©t√©\nD√©finition, √©laboration et proposition de plans d‚Äôaction pour am√©liorer les process\nProposition d‚Äô√©volution des outils pour suivre les modifications de process\nD√©ploiement des nouveaux process et accompagnements des √©quipes dans leur mise en ≈ìuvre\nLe Bilan Carbone\nR√©alisation du bilan carbone de Terres d‚ÄôAventure\nCalcul des √©missions carbone des trajets a√©riens des clients du groupe Voyageurs du Monde\nProfil\nIssu¬∑e d‚Äôune grande √©cole de commerce vous b√©n√©ficiez d‚Äôune exp√©rience d‚Äôau moins 3 ans dans un poste similaire.\nDot√©¬∑e de tr√®s bonnes capacit√©s d‚Äôanalyse et de synth√®se vous poss√©dez un vif int√©r√™t pour le marketing et l‚Äôanalyse de donn√©es. Vous avez une tr√®s bonne connaissance des outils d‚Äôanalyse‚ÄØdont Excel (notamment Power Query), Power BI ou autre outil similaire et √™tes tr√®s √† l‚Äôaise avec la manipulation de base de donn√©es m√©tier‚ÄØ(compr√©hension, mod√©lisation, traitement et analyse). Enfin, vous avez de grandes capacit√©s r√©dactionnelles.\nOrganis√©¬∑e, rigoureux¬∑se et m√©thodique, vous aimez travailler en √©quipe.\nDe nature dynamique, curieux¬∑se et proactive, vous savez vous adapter et poss√©dez une bonne √©coute et un tr√®s bon sens relationnel.\nVous avez le go√ªt du challenge ? Vous vous reconnaissez dans ce poste ? Rejoignez-nous et aidez nos client¬∑e¬∑s √† vivre des aventures uniques et inoubliables √† travers le monde.\nRejoindre Terres D'Aventure C'est\nB√©n√©ficier de supers avantages et en plus ils sont nombreux ! :\n6 semaines de cong√©s pay√©s\nJusqu‚Äô√† 2 jours de t√©l√©travail par semaine,\nUn syst√®me d‚Äôint√©ressement et de participation pouvant aller jusqu‚Äô√† 3 mois de salaire,\nUne mutuelle prise en charge √† 85% par l'entreprise,\nDes tickets restaurant d‚Äôune valeur de 10‚Ç¨ pris en charge √† 60%,\nUne prise en charge des indemnit√©s kilom√©triques v√©lo et de 50% des abonnements aux transports en commun\nDes prix r√©duits sur nos voyages\nDes avantages divers avec notre CSE comme des cours de sport ou des massages √† l‚Äôheure du d√©jeuner, des weekends, des tarifs pr√©f√©rentiels pour divers √©v√®nements et le cin√©ma...\nTravailler dans des locaux accueillants situ√©s en centre-ville sur un poste int√©grant de nombreuses formations, polyvalent et √©volutif √† destination d'une client√®le de voyageur¬∑se¬∑s passionn√©¬∑e¬∑s.\nInt√©grer une √©quipe passionn√©e, soud√©e, bienveillante, conviviale et sportive. Chez Terres d'Aventure, nous croyons en la force de l'√©quipe. On aime relever des d√©fis dans le travail ou en dehors comme le Marathon des Sables, un semi-marathon ou des projets caritatifs. Et comme nous sommes convaincus qu‚Äôon travaille mieux dans une ambiance conviviale on aime √©galement se retrouver autour d‚Äôun caf√©, d‚Äôun d√©jeuner ou au cours d‚Äô√©v√®nements d‚Äôentreprise.\nRejoindre une entreprise avec des valeurs fortes qui ne cesse d'innover, de se d√©velopper et qui s'engage dans le tourisme responsable avec des engagements environnementaux et le soutien d‚ÄôONG et d‚Äôassociations au travers de sa fondation.\nFaire partie d‚Äôun groupe international et profiter de possibilit√©s d‚Äô√©volution.\nConditions\nLe poste est √† pourvoir d√®s que possible en CDI.\nLocalisation\n: Dans nos locaux de Paris.\nR√©mun√©ration\nUn salaire fixe sur 12 mois selon profil,\nUn syst√®me d‚Äôint√©ressement et de participation pouvant aller jusqu‚Äô√† 3 mois de salaire.\nR√©f√©rence de l'offre : 39b71s4u4n\nShow more\nShow less",
        "details": {
            "JobDetail": [],
            "TypeContract": "CDI",
            "Salary": "85",
            "Level": "",
            "Experience": "45 an(s)"
        },
        "title": "data analyst",
        "skills": {
            "DataVisualisation": [
                "Power BI"
            ]
        }
    }
]