[
    {
        "source": "LinkedIn",
        "company": "Akademija Oxford",
        "location": "Boulogne-Billancourt, √éle-de-France, France",
        "link": "https://fr.linkedin.com/jobs/view/data-analyst-junior-h-f-at-akademija-oxford-3917871112?position=2&pageNum=0&refId=3%2BsKCnzKBomYeuJjjsOexw%3D%3D&trackingId=4%2Fa7pNvAsIgWJtMpHVaPXA%3D%3D&trk=public_jobs_jserp-result_search-card",
        "description": "Notre entreprise partenaire, sp√©cialiste de la vente de m√©dicaments et produits de sant√©, recherche un apprenti Data Analyst (H/F) pr√©parant un bac +4/+5 en fili√®re Big Data pour la rentr√©e de Septembre 2021.\nShow more\nShow less",
        "details": {
            "JobDetail": [],
            "TypeContract": "",
            "Salary": "",
            "Level": "",
            "Experience": null
        },
        "title": "data analyst",
        "skills": {
            "Other": [
                "Big Data"
            ]
        }
    },
    {
        "source": "LinkedIn",
        "company": "Akademija Oxford",
        "location": "Ille-et-Vilaine, Brittany, France",
        "link": "https://fr.linkedin.com/jobs/view/ing%C3%A9nieur-data-at-akademija-oxford-3912800588?position=3&pageNum=0&refId=3%2BsKCnzKBomYeuJjjsOexw%3D%3D&trackingId=oQd1rnnUf9GBIkM2KvjqXw%3D%3D&trk=public_jobs_jserp-result_search-card",
        "description": "Vous souhaitez int√©grer une √©cole √† taille humaine ? Vous √™tes int√©ress√©.es par la donn√©e ? Sup de Vinci propose une formation compl√®te, en Mast√®re Big Data & Intelligence Artificielle (2 ann√©es en alternance).\nL‚Äô√©cole Sup de Vinci, Rennes, accompagne l‚Äôune de ses entreprises partenaires dans son projet de recrutement d‚Äôun profil ing√©nieur data, en alternance pour la rentr√©e 2022.\nShow more\nShow less",
        "details": {
            "JobDetail": [],
            "TypeContract": "",
            "Salary": "",
            "Level": "",
            "Experience": null
        },
        "title": "data engineer",
        "skills": {
            "Other": [
                "Big Data"
            ]
        }
    },
    {
        "source": "LinkedIn",
        "company": "Akademija Oxford",
        "location": "Boulogne-Billancourt, √éle-de-France, France",
        "link": "https://fr.linkedin.com/jobs/view/data-engineer-s%C3%A9curit%C3%A9-h-f-at-akademija-oxford-3917866657?position=4&pageNum=0&refId=3%2BsKCnzKBomYeuJjjsOexw%3D%3D&trackingId=LZWNDjODSr2WKASECOYsmw%3D%3D&trk=public_jobs_jserp-result_search-card",
        "description": "Une entreprise du secteur de la protection de l‚Äôenvironnement et bas√©e dans les Hauts-De-Seine recherche un.e Data Engineer S√©curit√© dans le cadre d‚Äôun contrat d‚Äôapprentissage.\nAu sein de son Data Service, votre r√¥le sera d‚Äô√©tablir la strat√©gie des architectures data sur les aspects s√©curit√© en lien avec la strat√©gie globale m√©tier et contribuer √† la d√©clinaison des principes du mod√®le de s√©curit√© globale.\nVous devrez √©galement √©laborer des mod√®les de r√©f√©rence pour les architectures data, mais aussi contribuer √† la d√©clinaison des politiques de s√©curit√© en standards de s√©curit√© op√©rationnels.\nShow more\nShow less",
        "details": {
            "JobDetail": [],
            "TypeContract": "",
            "Salary": "",
            "Level": "",
            "Experience": null
        },
        "title": "data engineer",
        "skills": {}
    },
    {
        "source": "LinkedIn",
        "company": "Akademija Oxford",
        "location": "Boulogne-Billancourt, √éle-de-France, France",
        "link": "https://fr.linkedin.com/jobs/view/data-analyst-at-akademija-oxford-3917868480?position=5&pageNum=0&refId=3%2BsKCnzKBomYeuJjjsOexw%3D%3D&trackingId=vHT%2FnfuS2czWJA7syxxhGQ%3D%3D&trk=public_jobs_jserp-result_search-card",
        "description": "Nos collaborateurs travaillent au quotidien avec tous les m√©tiers et avec notre r√©seau international. Et pour √™tre au top de l‚Äôinnovation, on a ce qui se fait de mieux en mati√®re d‚Äôenvironnement de travail et d‚Äôoutils technos : datalab, delta room, intelligence artificielle, machine learning‚Ä¶\nR√©sultats ? Une activit√© multipli√©e par 2 en 3 ans (et ce n‚Äôest pas fini), une expertise reconnue et une position de leader en France.\nBienvenue au c≈ìur du big bang !\nShow more\nShow less",
        "details": {
            "JobDetail": [],
            "TypeContract": "",
            "Salary": "",
            "Level": "",
            "Experience": "3 an(s)"
        },
        "title": "data analyst",
        "skills": {
            "Other": [
                "Machine Learning"
            ]
        }
    },
    {
        "source": "LinkedIn",
        "company": "Akademija Oxford",
        "location": "Ille-et-Vilaine, Brittany, France",
        "link": "https://fr.linkedin.com/jobs/view/data-analyst-at-akademija-oxford-3917868488?position=6&pageNum=0&refId=3%2BsKCnzKBomYeuJjjsOexw%3D%3D&trackingId=Hn7b1Ugq%2FuoI3OMUVld89Q%3D%3D&trk=public_jobs_jserp-result_search-card",
        "description": "Dipl√¥m√©(e) d‚Äôun bac+2 dans le secteur informatique et plus pr√©cis√©ment dans le domaine du d√©veloppement.\nDans le cadre d‚Äôun contrat d‚Äôapprentissage de 12 mois, nous recherchons pour l‚Äôun de nos partenaires, un Data Analyst qui souhaite apporter ses comp√©tences techniques tout en faisant preuve d‚Äôun excellent savoir-√™tre.\nShow more\nShow less",
        "details": {
            "JobDetail": [],
            "TypeContract": "",
            "Salary": "",
            "Level": "",
            "Experience": null
        },
        "title": "data analyst",
        "skills": {}
    },
    {
        "source": "LinkedIn",
        "company": "Akademija Oxford",
        "location": "Ille-et-Vilaine, Brittany, France",
        "link": "https://fr.linkedin.com/jobs/view/data-analyst-at-akademija-oxford-3917872056?position=7&pageNum=0&refId=3%2BsKCnzKBomYeuJjjsOexw%3D%3D&trackingId=p0A9v%2BlDKjsXyUwA1W0smA%3D%3D&trk=public_jobs_jserp-result_search-card",
        "description": "L‚Äô√©cole Sup de Vinci, Rennes, accompagne l‚Äôune de ses entreprises partenaires dans son projet de recrutement d‚Äôun profil Big Data en alternance pour la rentr√©e de Septembre 2021.\nA noter : Sup de Vinci pr√©sentera √† cette entreprise partenaire uniquement des candidats ayant pass√© les tests d‚Äôadmission et qui seront admissibles dans son √©tablissement.\nShow more\nShow less",
        "details": {
            "JobDetail": [],
            "TypeContract": "",
            "Salary": "",
            "Level": "",
            "Experience": null
        },
        "title": "data analyst",
        "skills": {
            "Other": [
                "Big Data"
            ]
        }
    },
    {
        "source": "LinkedIn",
        "company": "Capgemini",
        "location": "Bordeaux, Nouvelle-Aquitaine, France",
        "link": "https://fr.linkedin.com/jobs/view/data-engineer-bordeaux-at-capgemini-3889788624?position=8&pageNum=0&refId=3%2BsKCnzKBomYeuJjjsOexw%3D%3D&trackingId=4fssEcWN4xK2SLQ4KEHn8w%3D%3D&trk=public_jobs_jserp-result_search-card",
        "description": "Choisir Capgemini, c'est choisir une entreprise o√π vous serez en mesure de fa√ßonner votre carri√®re selon vos aspirations. Avec le soutien et l'inspiration d'une\ncommunaut√© d‚Äôexperts dans le monde entier, vous pourrez r√©√©crire votre futur. Rejoignez-nous pour red√©finir les limites de ce qui est possible, contribuer √† lib√©rer la\nvaleur de la technologie pour les plus grandes organisations et participer √† la construction d‚Äôun monde plus durable et inclusif.\nVos missions :\nVous √™tes passionn√© par le domaine de la Data, vous souhaitez prendre part √† des projets d'envergure, concevoir des solutions, les impl√©menter et les faire √©voluer?\nAlors rejoignez notre √©quipe Data Engineering Services au sein de Capgemini Cloud Infrastructure Services en tant que Data Engineer.\nVous avez acquis une exp√©rience solide dans le d√©veloppement, la mise en ≈ìuvre et l‚Äôoptimisation de solutions pour le traitement d'un grand volume de donn√©es, vous √™tes capable de cr√©er des solutions qui r√©pondent aux besoins m√©tiers et IT, alors rejoignez notre √©quipe d‚Äôexperts.\nEn qualit√© de Data engineer, vos missions sont les suivantes :\n‚ñ™ Concevoir et d√©velopper des solutions Data/IA.\n‚ñ™ Accompagner les M√©tier dans la compr√©hension et la mise en ≈ìuvre de solution orient√©es donn√©es.\n‚ñ™ Collaborer avec les Dev, les Ops, les experts infrastructures dans la construction de solutions et d‚Äôinfrastructures ax√©es sur les donn√©es.\n‚ñ™ G√©rer un √©cosyst√®me de partenaires data et assurer un haut niveau d'expertise\n‚ñ™ Assurer un r√¥le de veille technologique sur tous les outils autours de la data, de l‚ÄôIA et de la BI.\nVotre profil :\nVous √™tes issu d‚Äôune formation ing√©nieur ou √©quivalent bac+5 informatique sp√©cialis√©e en DATA et vous justifiez d‚Äôune exp√©rience de 3 √† 5 ans dans un r√¥le similaire. Expert dans une technologie de base de donn√©es relationnelle (PostgreSQL, Oracle...)\nExpert dans une technologie de base NoSQL (MongoDB, Cassandra...)\nVous maitrisez un framework de manipulation de donn√©es (Hadoop, Spark, Kafka...)\nVous maitrisez les concepts DevOps et avez de bonnes notions en scripting et d√©veloppement\nVous avez une exp√©rience des outils BI et de data visualisation (Kibana, PowerBI...)\nLa maitrise de l'anglais est n√©cessaire.\n3 raisons de nous rejoindre :\nQualit√© de vie au travail :\naccord de t√©l√©travail en France et √† l‚Äôinternational, accord sur l‚Äô√©galit√© professionnelle, la parentalit√©, l‚Äô√©quilibre des temps et la mobilit√© durable.\nApprentissage en continu :\ncertifications et formations en libre acc√®s, accompagnement sur mesure avec votre career manager, parcours d‚Äôint√©gration sur 9 mois.\nAvantages groupe & CSE :\nplan actionnariat, tarif pr√©f√©rentiels, remboursement partiel vacances, remboursement de votre abonnement sportif ou culture\nNos engagements et priorit√©s :\nLe groupe Capgemini encourage une culture inclusive dans un cadre multiculturel et handi-accueillant. En nous rejoignant, vous int√©grez un collectif qui valorise la diversit√©, d√©veloppe le potentiel de ses talents, s‚Äôengage dans des initiatives solidaires avec ses partenaires, et se mobilise pour r√©duire son impact environnemental sur tous ses sites et aupr√®s de ses clients.\n√Ä propos de Capgemini :\nCapgemini est un leader mondial, responsable et multiculturel, regroupant pr√®s de 350 000 personnes dans plus de 50 pays. Fort de 55 ans d‚Äôexp√©rience, nous sommes un partenaire strat√©gique des entreprises pour la transformation de leurs activit√©s en tirant profit de toute la puissance de la technologie et des innovations dans les domaines en perp√©tuelle √©volution tels que le cloud, la data, l‚ÄôIntelligence Artificielle, la connectivit√©, les logiciels, l‚Äôing√©nierie digitale ou les plateformes.\nGet The Future You Want* | www.capgemini.com/fr-fr\n*Capgemini, le futur que vous voulez\nShow more\nShow less",
        "details": {
            "JobDetail": [],
            "TypeContract": "",
            "Salary": "",
            "Level": "Bac+5",
            "Experience": "5 an(s)"
        },
        "title": "data engineer",
        "skills": {
            "DataBase": [
                "MongoDB",
                "Cassandra",
                "NoSQL"
            ],
            "BigData": [
                "Hadoop",
                "Spark"
            ],
            "DBMS": [
                "PostgreSQL"
            ],
            "SoftBigDataProcessing": [
                "Cassandra"
            ],
            "Other": [
                "Cloud",
                "DevOps"
            ]
        }
    },
    {
        "source": "LinkedIn",
        "company": "SFR",
        "location": "Paris, √éle-de-France, France",
        "link": "https://fr.linkedin.com/jobs/view/data-engineer-h-f-at-sfr-3879318123?position=9&pageNum=0&refId=3%2BsKCnzKBomYeuJjjsOexw%3D%3D&trackingId=9OjeHMY3jduvNS6nVrWxVg%3D%3D&trk=public_jobs_jserp-result_search-card",
        "description": "En tant que Data Ing√©nieur exp√©riment√©, vous occuperez un r√¥le essentiel dans notre √©quipe Data Science.\nVous serez responsable de la conception, du d√©veloppement et de la maintenance des pipelines de donn√©es ainsi que de l'int√©gration de sources de donn√©es multiples.\nVotre expertise sera cruciale pour garantir une gestion efficace des flux de donn√©es, ainsi que pour faciliter l'analyse et la visualisation des donn√©es en plus du support aux data scientists vos missions seront les suivantes :\nArchitecture projet des donn√©es\n: Concevoir et d√©velopper des architectures projet de donn√©es robustes, √©volutives et performantes pour int√©grer et g√©rer de grandes quantit√©s de donn√©es provenant de sources multiples. Assurer la fiabilit√©, l'√©volutivit√© et la s√©curit√© des flux de donn√©es entrant d‚Äôun projet Data Science.\nInt√©gration des donn√©es\n: √âlaborer des pipelines de donn√©es efficaces pour l'extraction, la transformation et le chargement des donn√©es (via notre Framework ELT/ETL interne) provenant de diff√©rentes sources. Mettre en place des processus d'int√©gration automatis√©s et veiller √† la qualit√© des donn√©es.\nGestion des bases de donn√©es\n: Concevoir et optimiser des bases de donn√©es pour r√©pondre aux besoins analytiques et de reporting. Assurer la performance, la disponibilit√© et la s√©curit√© des bases de donn√©es, ainsi que la gestion efficace des requ√™tes.\nCollaboration interfonctionnelle\n: Support des Data Scientists, vous travaillerez avec les √©quipes business pour comprendre leurs besoins et fournir des conseils et des recommandations bas√©s sur les donn√©es.\nOptimisation des performances\n: Surveiller et optimiser les performances des pipelines de donn√©es, des bases de donn√©es et des requ√™tes. Identifier les goulots d'√©tranglement et les points d'optimisation, et proposer des am√©liorations pour garantir des performances optimales.\nS√©curit√© et conformit√©\n: Veiller √† ce que les donn√©es soient trait√©es et stock√©es conform√©ment aux normes de s√©curit√© et de confidentialit√©. Mettre en place des m√©canismes de s√©curit√© pour prot√©ger les donn√©es sensibles et garantir la conformit√© aux r√©glementations en vigueur.\nVotre profil :\nVous avez un\nDipl√¥me universitaire en informatique, en g√©nie logiciel, en science des donn√©es ou dans un domaine connexe et vous avez √† minima 5 ans d'exp√©rience en tant que Data Ing√©nieur.\nVous poss√©dez √©galement une solide ma√Ætrise des technologies et des outils suivants :\nHadoop, Spark, SQL, Kafka, GCP BigQuery,\nDe plus vous avez une bonne compr√©hension des architectures, des mod√®les et des concepts de base de donn√©s avec une exp√©rience avanc√©e dans la mise en ≈ìuvre de pipelines ETL et dans la gestion de bases de donn√©es.\nVos connaissances en mati√®re de s√©curit√© des donn√©es, de conformit√© aux r√©glementations ainsi que vos comp√©tences en programmation scripting et en d√©veloppement logiciel seront un plus.\nVos excellentes comp√©tences en communication seront des qualit√©s appr√©ci√©es et\nun niveau d'anglais (appliqu√©e au domaine technique) est un plus.\nShow more\nShow less",
        "details": {
            "JobDetail": [],
            "TypeContract": "",
            "Salary": "",
            "Level": "",
            "Experience": "5 an(s)"
        },
        "title": "data engineer",
        "skills": {
            "DataBase": [
                "SQL"
            ],
            "BigData": [
                "Hadoop",
                "Spark"
            ],
            "CloudComputing": [
                "GCP"
            ],
            "DBMS": [
                "BigQuery"
            ],
            "EnSoftSkils": [
                "Communication",
                "Collaboration"
            ]
        }
    },
    {
        "source": "LinkedIn",
        "company": "Capgemini",
        "location": "Lille",
        "link": "https://fr.linkedin.com/jobs/view/data-engineer-lille-at-capgemini-3914228495?position=10&pageNum=0&refId=3%2BsKCnzKBomYeuJjjsOexw%3D%3D&trackingId=PkwyrVao7fUjVVda5pf%2BSg%3D%3D&trk=public_jobs_jserp-result_search-card",
        "description": "Capgemini en quelques mots\nChoisir Capgemini, c'est choisir une entreprise o√π vous serez en mesure de fa√ßonner votre carri√®re selon vos aspirations, o√π vous serez soutenu et inspir√© par une communaut√© d‚Äôexperts dans le monde entier, o√π vous pourrez r√©√©crire votre futur. Rejoignez-nous pour red√©finir les limites de ce qui est possible, contribuer √† lib√©rer la valeur de la technologie pour les plus grandes organisations et participez √† la construction d‚Äôun monde plus durable et inclusif.\nVos missions\nVous maitrisez au minimum un langage de programmation appliqu√© √† l‚Äôanalyse de donn√©es\n(Java, Python, Scala et les environnements Spark et / ou Hadoop).\nVous √™tes passionn√© par le Big Data et le Machine Learning et l‚Äôanalyse de donn√©es\nVous concevez et mettez en ≈ìuvre des strat√©gies s√©curis√©es d'acquisition et d'int√©gration de donn√©es\nVous configurez des r√©f√©rentiels de donn√©es √† la pointe de la technologie dans des environnements distribu√©s\nVous construisez des pipelines de donn√©es pour collecter, transformer et traiter des donn√©es en collaboration avec des scientifiques de donn√©es afin de r√©pondre aux exigences de la mod√©lisation de donn√©es d'analyse avanc√©e\nVotre profil\nDipl√¥m√©(e) de Bac+5 en informatique\n4 ans d‚Äôexp√©rience\n(au sein d‚Äôune ESN ou chez un int√©grateur) en conseil client√®le\nUne solide culture technologique\nUn bon niveau d‚Äôanglais\n3 raisons de nous rejoindre\nQualit√© de vie au travail :\naccord de t√©l√©travail en France et √† l‚Äôinternational, accord sur l‚Äô√©galit√©\nprofessionnelle, la parentalit√©, l‚Äô√©quilibre des temps et la mobilit√© durable.\nApprentissage en continu :\ncertifications et formations en libre acc√®s, accompagnement sur mesure avec\nvotre carreer manager, parcours d‚Äôint√©gration sur 9 mois.\nAvantages groupe & CSE :\nplan actionnariat, activit√©s √† tarifs pr√©f√©rentiels, remboursement partiel\nvacances, remboursement de votre abonnement sportif ou culturel\nNos engagements et priorit√©s\nLe groupe Capgemini encourage une\nculture inclusive dans un cadre multiculturel et handi-accueillant.\nEn nous rejoignant, vous int√©grez un collectif qui valorise la diversit√©, d√©veloppe le potentiel de ses talents, s‚Äôengage dans des\ninitiatives solidaires avec ses partenaires, et se mobilise pour r√©duire son impact environnemental sur tous ses sites et aupr√®s de ses clients.\nCapgemini\nest un\nleader mondial\n, responsable et multiculturel, regroupant pr√®s de 350 000 personnes dans plus de 50 pays. Fort de\n55 ans d‚Äôexp√©rience,\nnous sommes un partenaire strat√©gique des entreprises pour la transformation de leurs activit√©s en tirant profit de toute la puissance de la technologie et des innovations dans les domaines en perp√©tuelle √©volution tels que le\ncloud, la data, l‚ÄôIntelligence Artificielle, la connectivit√©, les logiciels, l‚Äôing√©nierie digitale ou les plateformes.\nGet The Future You Want* | www.capgemini.com/fr-fr\n*Capgemini, le futur que vous voulez\nShow more\nShow less",
        "details": {
            "JobDetail": [],
            "TypeContract": "",
            "Salary": "",
            "Level": "Bac+5",
            "Experience": "4 an(s)"
        },
        "title": "data engineer",
        "skills": {
            "ProgLanguage": [
                "Java",
                "Scala",
                "Python"
            ],
            "BigData": [
                "Hadoop",
                "Spark"
            ],
            "Other": [
                "Machine Learning",
                "Cloud",
                "Big Data"
            ],
            "EnSoftSkils": [
                "Collaboration"
            ]
        }
    },
    {
        "source": "LinkedIn",
        "company": "Akademija Oxford",
        "location": "Paris, √éle-de-France, France",
        "link": "https://fr.linkedin.com/jobs/view/d%C3%A9veloppeur-euse-data-at-akademija-oxford-3917871099?position=11&pageNum=0&refId=3%2BsKCnzKBomYeuJjjsOexw%3D%3D&trackingId=H45gptKDFqpuRTlD%2BOGEbA%3D%3D&trk=public_jobs_jserp-result_search-card",
        "description": "Une entreprise du secteur de la pr√©voyance situ√©e √† Paris recherche un.e D√©veloppeur.euse Data, rattach√© au Responsable Data ‚Äì BI dans le cadre d‚Äôun contrat d‚Äôapprentissage d√©butant en Septembre 2021.\nShow more\nShow less",
        "details": {
            "JobDetail": [],
            "TypeContract": "",
            "Salary": "",
            "Level": "",
            "Experience": null
        },
        "title": "Other",
        "skills": {}
    },
    {
        "source": "LinkedIn",
        "company": "Thales",
        "location": "V√©lizy-Villacoublay, √éle-de-France, France",
        "link": "https://fr.linkedin.com/jobs/view/data-engineer-f-h-at-thales-3908228180?position=12&pageNum=0&refId=3%2BsKCnzKBomYeuJjjsOexw%3D%3D&trackingId=QoUqtZ4lBaasx8PwNxxUag%3D%3D&trk=public_jobs_jserp-result_search-card",
        "description": "QUI SOMMES-NOUS ?\nThales est un leader mondial des hautes technologies comptant plus de 81 000 collaborateurs pr√©sents sur tous les continents. Le Groupe investit dans les innovations du num√©rique et de la ¬´ deep tech ¬ª ‚Äì big data, intelligence artificielle, connectivit√©, cybers√©curit√© et quantique ‚Äì pour construire un avenir de confiance, essentiel au d√©veloppement de nos soci√©t√©s, en pla√ßant l‚Äôhumain au c≈ìur des d√©cisions.\nThales propose des solutions, services et produits qui aident ses clients ‚Äì entreprises, organisations, Etats ‚Äì dans cinq grands march√©s vitaux pour le fonctionnement de nos soci√©t√©s : identit√© et s√©curit√© num√©riques, d√©fense, a√©ronautique, espace, et transport.\nQUI ETES-VOUS ?\nDipl√¥m√© d‚Äôun Bac+5 en √©cole d‚Äôing√©nieur ou √©quivalent universitaire avec une sp√©cialisation en informatique, vous avez au moins 3 ans d'exp√©rience dans les technologies Big Data.\nCE QUE NOUS POUVONS ACCOMPLIR ENSEMBLE :\nEn tant que Data Engineer, vous jouerez un r√¥le cl√© dans la conception, le d√©veloppement et la maintenance de notre infrastructure de donn√©es, ainsi que dans la transformation et la gestion des flux de donn√©es.\nVOS MISSIONS :\n‚Ä¢ Concevoir, d√©velopper et d√©ployer des solutions Big Data en utilisant les technologies Hadoop.\n‚Ä¢ Mettre en place des pipelines de donn√©es performants pour l'ingestion, le traitement et le stockage des donn√©es massives.\n‚Ä¢ Collaborer √©troitement avec les √©quipes m√©tier pour comprendre leurs besoins en mati√®re d'analyse de donn√©es et proposer des solutions adapt√©es.\n‚Ä¢ Optimiser les performances des clusters Hadoop pour garantir une exploitation efficace des donn√©es.\n‚Ä¢ Assurer la qualit√© et la fiabilit√© des donn√©es trait√©es, en mettant en place des processus de validation et de nettoyage.\n‚Ä¢ Identifier et r√©soudre les probl√®mes li√©s √† l'infrastructure Big Data et proposer des am√©liorations.\n‚Ä¢ Travailler en √©troite collaboration avec les Data Scientists et les Data Analysts pour fournir des insights pertinents √† partir des donn√©es.\nInnovation, passion, ambition : rejoignez Thales et cr√©ez le monde de demain, d√®s aujourd‚Äôhui.\nShow more\nShow less",
        "details": {
            "JobDetail": [],
            "TypeContract": "",
            "Salary": "",
            "Level": "Bac+5",
            "Experience": "3 an(s)"
        },
        "title": "data engineer",
        "skills": {
            "BigData": [
                "Hadoop"
            ],
            "Other": [
                "Big Data"
            ],
            "EnSoftSkils": [
                "Collaboration"
            ]
        }
    },
    {
        "source": "LinkedIn",
        "company": "LVMH",
        "location": "Paris, √éle-de-France, France",
        "link": "https://fr.linkedin.com/jobs/view/data-solutions-engineer-data-ai-at-lvmh-3900392289?position=13&pageNum=0&refId=3%2BsKCnzKBomYeuJjjsOexw%3D%3D&trackingId=88V2zvA7VgiUnRocByb4DA%3D%3D&trk=public_jobs_jserp-result_search-card",
        "description": "LVMH is the #1 Luxury group and is currently accelerating rapidly on digitalisation. It is bringing technology and innovation in the core of the established 75+ Maisons by inventing unique and powerful products and services.\nWe are looking for talented solution engineers (Software, Cloud, Data and AI) to join our team and be part of this tech revolution of bringing the Group and its Maisons to the next level.\nIf you believe Data and AI can enhance the retail industry, from the day-to-day operational tasks to the long term customer experience,\nIf you think that the Cloud technologies (we love Google Cloud) is a revolution for Data and AI products,\nIf you like building tech solutions having direct impacts on billion-dollar-valued businesses,\nIf you have good communication skills and like sharing your knowledge,\nApply now, and join us!\nThe mission\nThe Solution Engineer is providing advices and technical assets to the Maisons having Data & AI projects.\nOur team (Group Data team) is building a technical framework for all the Maisons to implement easily and quickly Data and AI use cases. Your mission will be to support the Maisons to convert their use case needs to concrete and production ready technical solutions using our framework and tools.\nYou will cover a portfolio of Maisons, in direct contact with their business analysts, data scientists and IT teams. You will be their dedicated referent on the Data & AI technical topics (Data platform, AI/ML softwares, data transport and transformations, data quality).\nMain responsibilities\nYou will be responsible of providing support and advices to a portfolio of Maisons on Data & AI tech topics (Cloud, Data stacks, Data transformations, Data transfers, ML ops).\nYou will keep a recurrent discussion with the Maisons to accelerate their projects and immediately provide our support when it's needed.\nYou will follow-up the engaged productions in the Maisons and report them to the global group data strategy committees.\nApplying the quality and security standards. Making them evolve if necessary.\nProducing realistic, understandable and documented solutions following the group guidelines.\nSharing and learning from the team by communicating difficulties and successes, taking and bringing honest feedbacks and improving the identified pain points.\nTaking responsibility as member of the team on the product performances (delivery and long term usage)\nRequired expertise and knowledge\nAbility to build technical solutions answering concrete usage (User Stories) and communicate them to the team.\nDimension and evaluate complexity for technical solution productions.\nExtensive knowledge and experience with good learning and sharing abilities.\nEvaluate quickly risks and opportunities about technical choices.\nSolid oral, written, presentation and interpersonal communication and relationship skills.\nProblem-solving skills on Data and AI, coding and software development\nTech lover\nFeedback taker and giver\nTeam player\nKey benefits to join our team\nAttractive packages\nOffices in the 8th arrondissement near the Champs Elys√©es\nFlexibility on the working hours\nRemote work possible (~40%)\n7 weeks of holidays (cong√©s pay√©s + RTT)\nLVMH brands exclusive private sales\nGreat employee committee and health insurance (CE, mutuelle)\nLast generation MacBooks\nPart of a young, motivated and tech savvy team. Get prepared for the Thursday drinks and the tech meet-ups!\nYou‚Äôre eligible if\nYou have a strong experience (3+ years) in cloud data architecting or consultancy.\nYou graduated from an engineering (or equivalent) with a master‚Äôs degree. Computer Science knowledge is mandatory.\nExperience on data stacks and/or Google Cloud (built in components) is a huge plus.\nFrench and English both written and oral (Maisons are all over the world)\nYou‚Äôre thrilled to support the #1 luxury group to get even better.\nHiring Process\nCall with our HR partner dedicated to the Tech Team\nTechnical interview with the Solution Engineering Manager\nTechnical test\nInterview with the Head of Engineering\nStill here? Apply now!!\nShow more\nShow less",
        "details": {
            "JobDetail": [
                "Remote"
            ],
            "TypeContract": "",
            "Salary": "40",
            "Level": "",
            "Experience": null
        },
        "title": "data engineer",
        "skills": {
            "Collaboration": [
                "Teams"
            ],
            "Other": [
                "Cloud",
                "ML"
            ],
            "EnSoftSkils": [
                "Flexibility",
                "Communication"
            ]
        }
    },
    {
        "source": "LinkedIn",
        "company": "Capgemini",
        "location": "Grenoble, Auvergne-Rh√¥ne-Alpes, France",
        "link": "https://fr.linkedin.com/jobs/view/data-engineer-%E2%80%93-grenoble-at-capgemini-3905836212?position=14&pageNum=0&refId=3%2BsKCnzKBomYeuJjjsOexw%3D%3D&trackingId=kCCidaEslhnyuykxU40ubg%3D%3D&trk=public_jobs_jserp-result_search-card",
        "description": "Choisir Capgemini, c'est choisir une entreprise o√π vous serez en mesure de fa√ßonner votre carri√®re selon vos aspirations. Avec le soutien et l'inspiration d'une communaut√© d‚Äôexperts dans le monde entier, vous pourrez r√©√©crire votre futur. Rejoignez-nous pour red√©finir les limites de ce qui est possible, contribuer √† lib√©rer la valeur de la technologie pour les plus grandes organisations et participer √† la construction d‚Äôun monde plus durable et inclusif.\nVos missions :\nEn tant que Data Engineer au sein d'une √©quipe multidisciplinaire, vos responsabilit√©s principales seront les suivantes :\nIntervenir sur les diff√©rentes phases d'un projet dans un environnement Cloud et Agile.\nContribuer √† la gestion de la qualit√© des donn√©es et extraction et analyse de celle-ci, ainsi qu‚Äô√† la pr√©sentation des donn√©es dans leur forme raffin√©e.\nProposer des nouvelles lectures de donn√©es via un travail de fouille sur les gisements d‚Äôinformation, notamment client.\nAdopter une posture de consultant : proposer de nouvelles solutions et accompagner le client dans ses choix.\nVotre profil :\nTitulaire d'un Bac+5 en √©cole d‚Äôing√©nieur ou en universit√©.\nConnaissances approfondies des ETL (Talend, Informatica ou SSIS), du traitement de donn√©es (Spark, Python, Scala) ainsi que des bases de donn√©es (Oracle, SQL Server, Postgres).\nFacult√© pour se montrer curieux, autonome et proactif dans la r√©alisation de ses t√¢ches.\nCapacit√© √† faire preuve de rigueur et √† travailler en √©quipe.\nBon niveau d‚Äôanglais (B2 minimum).\n3 raisons de nous rejoindre :\nQualit√© de vie au travail\n: accord de t√©l√©travail en France et √† l‚Äôinternational, accord sur l‚Äô√©galit√© professionnelle, la parentalit√©, l‚Äô√©quilibre des temps et la mobilit√© durable.\nApprentissage en continu\n: certifications et formations en libre acc√®s, accompagnement sur mesure avec votre career manager, parcours d‚Äôint√©gration sur 9 mois.\nAvantages groupe & CSE\n: plan actionnariat, tarif pr√©f√©rentiels, remboursement partiel vacances, remboursement de votre abonnement sportif ou culturel.\nNos engagements et priorit√©s\n:\nLe groupe Capgemini encourage une culture inclusive dans un cadre multiculturel et handi-accueillant. En nous rejoignant, vous int√©grez un collectif qui valorise la diversit√©, d√©veloppe le potentiel de ses talents, s‚Äôengage dans des initiatives solidaires avec ses partenaires, et se mobilise pour r√©duire son impact environnemental sur tous ses sites et aupr√®s de ses clients.\n√Ä propos de Capgemini :\nCapgemini est un leader mondial, responsable et multiculturel, regroupant pr√®s de 350 000 personnes dans plus de 50 pays. Fort de 55 ans d‚Äôexp√©rience, nous sommes un partenaire strat√©gique des entreprises pour la transformation de leurs activit√©s en tirant profit de toute la puissance de la technologie et des innovations dans les domaines en perp√©tuelle √©volution tels que le cloud, la data, l‚ÄôIntelligence Artificielle, la connectivit√©, les logiciels, l‚Äôing√©nierie digitale ou les plateformes.\nGet The Future You Want* | www.capgemini.com/fr-fr\n*Capgemini, le futur que vous voulez\nShow more\nShow less",
        "details": {
            "JobDetail": [],
            "TypeContract": "",
            "Salary": "",
            "Level": "Bac+5",
            "Experience": "55 an(s)"
        },
        "title": "data engineer",
        "skills": {
            "ProgLanguage": [
                "Scala",
                "Python"
            ],
            "DataBase": [
                "SQL"
            ],
            "BigData": [
                "Spark"
            ],
            "DBMS": [
                "SQL Server"
            ],
            "Other": [
                "Cloud"
            ]
        }
    },
    {
        "source": "LinkedIn",
        "company": "Thales",
        "location": "Lyon, Auvergne-Rh√¥ne-Alpes, France",
        "link": "https://fr.linkedin.com/jobs/view/data-engineer-h-f-at-thales-3903089036?position=15&pageNum=0&refId=3%2BsKCnzKBomYeuJjjsOexw%3D%3D&trackingId=QCrBY3k8aK8YeRYaEeexyg%3D%3D&trk=public_jobs_jserp-result_search-card",
        "description": "üì¢ Nous recherchons un(e) Data Engineer, bas√©(e) √† Lyon\nüëâQuelques mots sur les activit√©s num√©riques de Thales Lyon :\nLes activit√©s num√©riques repr√©sentent une entit√© rattach√©e au groupe Thales, sp√©cialis√©e dans l‚ÄôIT et pr√©sente au national.\nL‚Äôagence de Lyon adresse divers sujets d‚Äôexpertise : ing√©nierie logiciels, cybers√©curit√©, infog√©rance des infrastructures et transformation digitale.\nüéØ\nVotre r√¥le et missions\nEn nous rejoignant, vous int√©grerez le centre de comp√©tences\nAugmented data\n,\nsp√©cialis√© dans la conception, le d√©veloppement et l‚Äô√©volution d‚Äôapplications data centr√©es. Vous y boosterez votre carri√®re en travaillant sur des technologies telles que\nSpark, Elasticsearch, Kube ...\nle plus souvent dans un environnement\nAgile\n.\nDans le cadre des projets que nous op√©rons aujourd‚Äôhui :\n- Vous contribuerez √† la conception, au maintien, √† la scalabilit√© des plateformes d‚Äôanalyse de donn√©es au travers de votre expertise sur les sujets data (base de donn√©es, gestion de flux, ETL ‚Ä¶)\n- Vous contribuerez √† la conception et √† la mise en production des pipelines d‚Äôanalyses et de transformations de donn√©es en veillant √† leur bonne adaptation aux besoins m√©tiers et aux contraintes techniques du client\n- Vous pourrez intervenir sur des sujets de visualisations, dans le but de notamment accompagn√©es nos clients sur la conception de Dashboard m√©tier intelligent ‚Ä¶\n- Vous serez √©galement amen√©es √† √©changer directement avec des DevOps/Datascientist pour la mise en place, l‚Äôint√©gration des pipelines et l‚Äô√©laboration des algorithmes de traitements de donn√©es.\n- A l‚Äô√©chelle du d√©partement, Vous serez un acteur majeur du d√©veloppement de notre activit√© et du lancement de nouveaux projets de valorisation de donn√©es.\nüôã‚Äç‚ôÄÔ∏è üôã‚Äç‚ôÇÔ∏è\nVotre profil\nDe formation Bac +5 en informatique (√©cole d‚Äôing√©nieur, Master ou √©quivalent), vous justifiez d‚Äôune premi√®re exp√©rience r√©ussie sur un projet data ? Vous souhaitez participer √† la conception et intervenir sur des solutions de r√©cup√©ration et d‚Äôexploitation de donn√©es m√©tiers dans des contextes critiques et hautement s√©curis√©s ?\nAutonome, dynamique, organis√©(e) et proactif(ve), vous souhaitez √©voluer au sein d‚Äô√©quipes passionn√©es par l‚Äôexploration et l‚Äôint√©gration des technologies nouvelles au service des m√©tiers de nos clients ?\nVous avez des comp√©tences qui couvrent les domaines suivants :\nMise en place et gestion de base de donn√©es (SQL, Elasticsearch, Clickhouse ...)\nLangages de programmations (Java, Python)\nGestion de flux (Kafka, flink, logstash ‚Ä¶)\nEnvironnements big Data (Spark/hadoop )\nPrincipes et outils de type ETL\nVous √™tes de plus int√©ress√©(e):\nPar les environnements containeris√©s (docker, kubernetes, helm ...)\nLes concepts DevOps (Ansible, CI/CD...)\nLes sujets de Datavisualisation (Vega, Kibana, python librairies...)\nVous aimez travailler en √©quipe ? Vous √™tes reconnu(e) pour vos qualit√©s relationnelles et vos capacit√©s de vulgarisation ?\nAlors notre poste d‚ÄôIng√©nieur(e) Data(H/F) est fait pour vous !\nüôå\nVotre carri√®re chez Thales\nDiff√©rentes opportunit√©s vous permettront de d√©couvrir d'autres domaines ou sites. Vous pourrez √©voluer et d√©velopper vos comp√©tences dans diff√©rents domaines.\nExplorez un espace attentif au d√©veloppement personnel.\nD√©veloppez vos talents dans un autre domaine du groupe Thales, en d√©couvrant de nouveaux produits, de nouveaux clients, un nouveau pays ou en vous orientant vers une solution plus complexe.\nChoisissez entre une expertise technique ou un parcours de leadership.\nVous travaillerez dans une entreprise r√©solument humaine avec des valeurs fortes comme la s√©curit√© au travail, l‚Äô√©galit√© Homme/Femme et l‚Äô√©quilibre vie personnelle/professionnelle (Accord T√©l√©travail).\nRattach√©(e) √† la Convention m√©tallurgie, vous b√©n√©ficierez aussi de ses multiples avantages (‚Ä¶)\nVous souhaitez en savoir plus ?\nN‚Äôh√©sitez pas √† contacter notre √©quipe de recrutement ou nos √©quipes directement.\nShow more\nShow less",
        "details": {
            "JobDetail": [],
            "TypeContract": "",
            "Salary": "",
            "Level": "",
            "Experience": null
        },
        "title": "data engineer",
        "skills": {
            "ProgLanguage": [
                "Java",
                "Python"
            ],
            "DataBase": [
                "Elasticsearch",
                "SQL"
            ],
            "BigData": [
                "Hadoop",
                "Flink",
                "Spark"
            ],
            "DevTools": [
                "Docker"
            ],
            "Automation": [
                "Kubernetes",
                "Ansible"
            ],
            "Containers": [
                "Docker",
                "Kubernetes"
            ],
            "Other": [
                "Big Data",
                "DevOps",
                "CI/CD"
            ],
            "EnSoftSkils": [
                "Leadership"
            ]
        }
    },
    {
        "source": "LinkedIn",
        "company": "Capgemini",
        "location": "Nantes, Pays de la Loire, France",
        "link": "https://fr.linkedin.com/jobs/view/data-engineer-nantes-at-capgemini-3803998213?position=16&pageNum=0&refId=3%2BsKCnzKBomYeuJjjsOexw%3D%3D&trackingId=wZbQb5KuBsOLycS5Aft7kg%3D%3D&trk=public_jobs_jserp-result_search-card",
        "description": "Capgemini\nChoisir Capgemini, c'est choisir une entreprise o√π vous serez en mesure de fa√ßonner votre carri√®re selon vos aspirations, o√π vous serez soutenu et inspir√© par une communaut√© d‚Äôexperts dans le monde entier, o√π vous pourrez r√©√©crire votre futur. Rejoignez-nous pour red√©finir les limites de ce qui est possible, contribuer √† lib√©rer la valeur de la technologie pour les plus grandes organisations et participez √† la construction d‚Äôun monde plus durable et inclusif.\nVos missions :\nInt√©gr√©(e) au sein d'une √©quipe projets intervenant pour des clients dans des secteurs d'activit√©s vari√©es, vous serez notamment en charge des missions suivantes :\nConcevoir et mettre en oeuvre des strat√©gies s√©curis√©es d'acquisition et d'int√©gration de donn√©es,\nConfigurer des r√©f√©rentiels de donn√©es √† la pointe de la technologie dans des environnements distribu√©s, majoritairement dans le cloud (Google Cloud Platform, Azure Databricks, AWS) et/ou en environnement Hadoop (distribution MapR, Cloudera, Hortonworks),\nConstruire des pipelines de donn√©es pour collecter, transformer et traiter des donn√©es en collaboration avec des scientifiques de donn√©es afin de r√©pondre aux exigences de la mod√©lisation de donn√©es d'analyse avanc√©e.\nVotre profil :\nDipl√¥me d‚Äôing√©nieur ou √©quivalent universitaire\nMinimum 3 ans d'exp√©rience\nAnglais courant\nMa√Ætrise des langages Java, Scala ou Python et expertise sur les framework Spark et/ou Hadoop.\nExpertise sur les services Cloud Data Platform suivants : Azure Data Lake, Azure synapse, Azure Data Factory, Azure Data Explorer, GCP, AWS, Snowflake, Databricks‚Ä¶\n3 raisons de nous rejoindre :\nQualit√© de vie au travail : accord de t√©l√©travail en France et √† l‚Äôinternational, accord sur l‚Äô√©galit√©\nprofessionnelle, la parentalit√©, l‚Äô√©quilibre des temps et la mobilit√© durable.\nApprentissage en continu : certifications et formations en libre acc√®s, accompagnement sur mesure avec votre carreer manager, parcours d‚Äôint√©gration sur 9 mois.\nAvantages groupe & CSE : plan actionnariat, activit√©s √† tarifs pr√©f√©rentiels, remboursement partiel\nvacances, remboursement de votre abonnement sportif ou culturel.\nNos engagements et priorit√©s :\nLe groupe Capgemini encourage une culture inclusive dans un cadre multiculturel et handi-accueillant. En nous rejoignant, vous int√©grez un collectif qui valorise la diversit√©, d√©veloppe le potentiel de ses talents, s‚Äôengage dans des initiatives solidaires avec ses partenaires, et se mobilise pour r√©duire son impact environnemental sur tous ses sites et aupr√®s de ses clients.\nCapgemini\nCapgemini est un leader mondial, responsable et multiculturel, regroupant pr√®s de 350 000 personnes dans plus de 50 pays. Fort de 55 ans d‚Äôexp√©rience, nous sommes un partenaire strat√©gique des entreprises pour la transformation de leurs activit√©s en tirant profit de toute la puissance de la technologie et des innovations dans les domaines en perp√©tuelle √©volution tels que le cloud, la data, l‚ÄôIntelligence Artificielle, la connectivit√©, les logiciels, l‚Äôing√©nierie digitale ou les plateformes.\nGet The Future You Want* | www.capgemini.com/fr-fr\n*Capgemini, le futur que vous voulez\nShow more\nShow less",
        "details": {
            "JobDetail": [],
            "TypeContract": "",
            "Salary": "",
            "Level": "",
            "Experience": "3 an(s)"
        },
        "title": "data engineer",
        "skills": {
            "ProgLanguage": [
                "Java",
                "Scala",
                "Python"
            ],
            "BigData": [
                "Databricks",
                "Hadoop",
                "Spark"
            ],
            "CloudComputing": [
                "GCP",
                "AWS",
                "Google Cloud Platform",
                "Azure"
            ],
            "DBMS": [
                "Snowflake"
            ],
            "Other": [
                "Cloud"
            ],
            "EnSoftSkils": [
                "Collaboration"
            ]
        }
    },
    {
        "source": "LinkedIn",
        "company": "Akademija Oxford",
        "location": "Bordeaux, Nouvelle-Aquitaine, France",
        "link": "https://fr.linkedin.com/jobs/view/apprenti-e-ing%C3%A9nieur-data-at-akademija-oxford-3912806043?position=17&pageNum=0&refId=3%2BsKCnzKBomYeuJjjsOexw%3D%3D&trackingId=4jIJa%2B5MYicKzQ2041q3Og%3D%3D&trk=public_jobs_jserp-result_search-card",
        "description": "Vous souhaitez int√©grer une √©cole √† taille humaine ? Vous √™tes int√©ress√© par le secteur du d√©veloppement informatique ? Sup de Vinci propose une formation compl√®te en Mast√®re Big Data.\nL‚Äô√©cole Sup de Vinci √† Bordeaux, accompagne l‚Äôune de ses entreprises partenaires dans son projet de recrutement d‚Äôun profil Ing√©nieur Data, en alternance pour la rentr√©e 2022.\nShow more\nShow less",
        "details": {
            "JobDetail": [],
            "TypeContract": "",
            "Salary": "",
            "Level": "",
            "Experience": null
        },
        "title": "data engineer",
        "skills": {
            "Other": [
                "Big Data"
            ]
        }
    },
    {
        "source": "LinkedIn",
        "company": "Orange Business",
        "location": "Lille, Hauts-de-France, France",
        "link": "https://fr.linkedin.com/jobs/view/big-data-engineer-spark-python-f-h-at-orange-business-3916552415?position=18&pageNum=0&refId=3%2BsKCnzKBomYeuJjjsOexw%3D%3D&trackingId=gVbBfCnKp17Fh%2FK7yMriLQ%3D%3D&trk=public_jobs_jserp-result_search-card",
        "description": "Et si Business & Decision et Orange Business conjuguaient leurs forces pour devenir l‚Äôun des leaders europ√©ens de la Data transformation ?\nNous l‚Äôavons fait ! Notre alchimie nous positionne comme un\nacteur unique\nintervenant sur toutes les √©tapes du\nvoyage de la donn√©e.\nDepuis 30 ans, Business & Decision, entit√© de Digital Services s'est impos√©e comme un partenaire strat√©gique pour la transformation Data de nombreux clients, dans des secteurs tr√®s vari√©s. Digital Services est aujourd‚Äôhui l‚Äô\nESN d‚ÄôOrange Business\nalliant les expertises historiques Cloud et Digital d‚ÄôOrange ainsi que le c≈ìur de m√©tier Data/IA de Business & Decision. Son but est d‚Äôaccompagner les entreprises et les acteurs publics dans leur transformation gr√¢ce aux 4000 experts pr√©sents dans plusieurs grandes villes fran√ßaises comme Montpellier, Niort, Lyon, Bordeaux, Lille et Toulouse ‚Ä¶\nDescription du poste\nOrange Business, recherche pour son site de Lille, son futur Ing√©nieur Big Data pour rejoindre sa team Data.\nVotre quotidien ?\nEn int√©grant Orange Business, vous pouvez participer √† une grande diversit√© d‚Äôactivit√©s dans la Data. En voici un aper√ßu :\nAu d√©marrage du projet :\nRecueillir et analyser les besoins du client\nR√©diger les sp√©cifications fonctionnelles et techniques\nEstimer les charges\nPendant la phase de r√©alisation :\nMod√©liser des datawarehouses et datamart\nD√©velopper les proc√©dures d‚Äôalimentation (ETL)\nD√©veloppement SPARK\nen batch et streaming\nD√©velopper les visualisations de donn√©es (DataViz)\nR√©aliser la recette et les tests\nSuivre et mettre en production\nEn fonction de votre √©volution et de nos enjeux, vous pouvez aussi √©voluer sur des missions transverses (conseil, coaching, avant-vente, formation, audit, etc.). La prise d‚Äôinitiative est toujours la bienvenue !\nQualifications\nVous poss√©dez 5 ans d'exp√©rience ou plus dans la mise en ≈ìuvre de projets d√©cisionnels.\nVous avez de solides comp√©tences\nSpark\n(job, scripting, d√©ploiement) ainsi que sur\nPython.\nAvoir des connaissances Kafka sera un plus √©galement.\nEnvie d‚Äôapprendre de nouvelles technos ? Vous souhaitez partager vos comp√©tences et b√©n√©ficier des expertises de la Team Orange Business ?\nOutre l‚Äôaspect technique, c‚Äôest une personnalit√© qui est recherch√©e !\nShow more\nShow less",
        "details": {
            "JobDetail": [],
            "TypeContract": "",
            "Salary": "",
            "Level": "",
            "Experience": "30 an(s)"
        },
        "title": "data engineer",
        "skills": {
            "ProgLanguage": [
                "Python"
            ],
            "BigData": [
                "Spark"
            ],
            "MachineLearning": [
                "Orange"
            ],
            "Other": [
                "Cloud",
                "Big Data"
            ],
            "EnSoftSkils": [
                "Initiative"
            ]
        }
    },
    {
        "source": "LinkedIn",
        "company": "Technology & Strategy",
        "location": "Lyon, Auvergne-Rh√¥ne-Alpes, France",
        "link": "https://fr.linkedin.com/jobs/view/data-engineer-h-f-at-technology-strategy-3881556102?position=19&pageNum=0&refId=3%2BsKCnzKBomYeuJjjsOexw%3D%3D&trackingId=rfE5EC9w%2FL0oU8z85LCfuA%3D%3D&trk=public_jobs_jserp-result_search-card",
        "description": "D√©couvrez Novencia\n:\nExpert en Data et Intelligence Artificielle, nous aidons nos clients √† exploiter et √† valoriser leurs donn√©es sous toutes ses formes en les accompagnant sur des projets de Data Analyse, Data Gourvernance, Data Architecture, Data Science, et Data Engineering‚Ä¶\nVous avez une solide exp√©rience de minimum 2 ans dans l'ing√©nierie des donn√©es et vous √™tes √† la recherche de nouveaux d√©fis ? Bouclez votre ceinture, la suite est pour vous !\nType de contrat : CDI\nLieu : Lyon\nEn qualit√© de Data Engineer (H/F), votre r√¥le sera :\nConcevoir et proposer les solutions de d√©veloppement r√©pondant aux besoins fonctionnels et techniques des projets big data.\nTu participes √† la conception de solutions permettant le traitement de volumes importants de pipelines donn√©es.\nR√©aliser ces solutions par l‚Äô√©criture de code, en respectant les m√©thodes et proc√©dures qualit√©s d√©finies au sein du d√©partement Technique.\nMise √† disposition s√©curis√© et lisible de la data.\nS‚Äôassurer de la conformit√© fonctionnelle et technique de ces r√©alisations en effectuant les tests automatis√©s n√©cessaire et la mise en place de monitoring (syst√®me et qualit√©).\nAssurer la maintenance des applicatifs / plateforme data science\nAssurer une veille technologique\nVous disposez des comp√©tences suivantes :\nMaitrise des plateformes Cloud (AWS, GCP ou Azure), de Scala et de SQL.\nUn.e touche √† tout : poss√©dant des comp√©tences en langage Python/Spark, de bonnes capacit√©s de mod√©lisation, une forte app√©tence pour le Big Data\nFin.e connaisseur.euse : Data Engineer convaincu, tr√®s peu de secrets pour les clusters et pour les calculs parall√®les\nExplorateur.trice : d√©couvre de nouvelles technos gr√¢ce √† une veille r√©guli√®re\nD√©brouillard.e : rel√®ve de nouveaux d√©fis\nNotre objectif commun est de co-construire votre carri√®re en fonction de vos aspirations et de vos comp√©tences.\nContactez-moi en message priv√© ou par mail √† s.ziki@technologyandstrategy.com !\nLet's make it possible #together\n*Nos postes sont ouverts aux personnes b√©n√©ficiant d‚Äôune Reconnaissance de la Qualit√© de Travailleur Handicap√© (RQTH). T&S Groupe encourage la diversit√© et l‚Äô√©galit√© sur le lieu de travail. Tous les candidats qualifi√©s H/F/* sont pris en consid√©ration pour un emploi sur un m√™me pied d'√©galit√©.\nShow more\nShow less",
        "details": {
            "JobDetail": [],
            "TypeContract": "CDI",
            "Salary": "",
            "Level": "",
            "Experience": "2 an(s)"
        },
        "title": "data engineer",
        "skills": {
            "ProgLanguage": [
                "Scala",
                "Python"
            ],
            "DataBase": [
                "SQL"
            ],
            "BigData": [
                "Spark"
            ],
            "CloudComputing": [
                "GCP",
                "AWS",
                "Azure"
            ],
            "Other": [
                "Cloud",
                "Big Data"
            ]
        }
    },
    {
        "source": "LinkedIn",
        "company": "digiRocks recrute ‚úÖ",
        "location": "Paris, √éle-de-France, France",
        "link": "https://fr.linkedin.com/jobs/view/data-engineer-at-digirocks-recrute-%E2%9C%85-3903481080?position=20&pageNum=0&refId=3%2BsKCnzKBomYeuJjjsOexw%3D%3D&trackingId=TlAWC5PhE0jt5w68KPQDTg%3D%3D&trk=public_jobs_jserp-result_search-card",
        "description": "üòé Envie d'accompagner des organisations dans leurs strat√©gies, Fan de data?\nRejoins un jeune cabinet de conseil en strat√©gie sp√©cialis√© en data. Le cabinet a √©t√© cr√©√© il y a 4 ans pas des anciens de grands cabinets de conseil en strat√©gie qui ne se reconnaissaient plus dans ce qu'est devenu le \"consulting\". Cependant ils n'ont pas perdu espoir de pouvoir apporter du conseil √† haute valeur ajout√©e dans une ambiance friendly, fa√ßon start-up, sans sacrifier l'excellence.\nJean-Patrick recrute un(e) Consultant Data Engineer √† Paris en CDI\n‚úÖ MISSION :\nVous serez responsable de la mise en ≈ìuvre de bout en bout de la pile de donn√©es, de la collecte au reporting, avec un accent sur l'infrastructure et les processus techniques. Vous travaillerez avec des Consultants en Strat√©gie & Data et les soutiendrez dans la r√©solution des d√©fis li√©s aux donn√©es de leurs clients. Vous contribuerez √† la d√©finition des strat√©gies de donn√©es, √† la mise en ≈ìuvre des syst√®mes de donn√©es et vous soutiendrez l'exploitation des donn√©es dans des projets transformationnels. En g√©n√©ral, vous serez responsable de comprendre intimement les probl√®mes, de concevoir une strat√©gie technique pour les adresser et de faciliter une ex√©cution technique de haute qualit√©.\n‚úÖ R√âSULTATS ATTENDUS :\nüöÄ R√©sultat 1: Unificateur de Donn√©es : Architecturer, assembler, assimiler, nettoyer et conformer de grands ensembles de donn√©es complexes pour livrer des insights commerciaux et alimenter les exp√©riences de produits de donn√©es.\nüöÄ R√©sultat 2: Agent de S√©curit√© des Donn√©es : Concevoir et construire une infrastructure de donn√©es fiable et √©volutive avec les techniques de confidentialit√© et de s√©curit√© de pointe pour prot√©ger les donn√©es.\nüöÄ R√©sultat 3: DataOps : Poss√©der la pile de donn√©es de bout en bout, y compris la collecte d'√©v√©nements, la gouvernance des donn√©es, les int√©grations de donn√©es et la mod√©lisation.\nüöÄ R√©sultat 4: Gardien des Donn√©es : Assurer la coh√©rence et la qualit√© de l'environnement technique et de la structure des donn√©es √† travers des m√©triques, de la documentation, des processus, des tests de donn√©es et de la formation.\nRequirements\n‚úÖ PROFIL RECHERCH√â :\nDipl√¥m√© d'une Grande Ecole de Commerce ou d'ing√©nieur, avec une premi√®re exp√©rience r√©ussie comme Data Engineer, id√©alement dans un contexte similaire au Conseil,\nConnaissance des services de Data Warehouses Cloud. Exp√©rience avec Google BigQuery, Snowflake, AWS Redshift/Athena, Looker, Azure SQL DWH, ou Azure Databricks est tr√®s souhaitable.\nConnaissance des architectures de donn√©es relationnelles et de grandes donn√©es, de l'entreposage de donn√©es, de l'int√©gration de donn√©es, de la mod√©lisation de donn√©es, de l'optimisation de donn√©es et des techniques d'analyse de donn√©es.\nExp√©rience dans la construction de pipelines de donn√©es de bout en bout en utilisant des plateformes de donn√©es sur site ou bas√©es sur le cloud.\nExp√©rience pratique dans la livraison de solutions comprenant des bases de donn√©es, SQL avanc√© et d√©veloppement logiciel dans des langues telles que Python.\nInt√©ress√© et connaissant les technologies Big Data et les technologies de l'√©cosyst√®me Apache telles que Beam, Spark, Kafka, Airflow, bases de donn√©es, int√©gration, gestion des donn√©es de r√©f√©rence, assurance qualit√©, manipulation de donn√©es et technologies de gouvernance des donn√©es.\nExp√©rience avec les plateformes cloud publiques et l'infrastructure cloud qui est essentielle.\nExpos√© aux outils ETL/ELT et de gouvernance.\nInt√©ress√© par les technologies et principes IA et ML.\nShow more\nShow less",
        "details": {
            "JobDetail": [],
            "TypeContract": "CDI",
            "Salary": "",
            "Level": "",
            "Experience": "4 an(s)"
        },
        "title": "data engineer",
        "skills": {
            "ProgLanguage": [
                "Python"
            ],
            "DataBase": [
                "SQL"
            ],
            "BigData": [
                "Databricks",
                "Spark"
            ],
            "CloudComputing": [
                "AWS",
                "Azure"
            ],
            "DBMS": [
                "BigQuery",
                "Snowflake"
            ],
            "Automation": [
                "Airflow"
            ],
            "Other": [
                "ML",
                "Cloud",
                "Big Data"
            ]
        }
    },
    {
        "source": "LinkedIn",
        "company": "Orange Business",
        "location": "Lille",
        "link": "https://fr.linkedin.com/jobs/view/data-engineer-%E2%80%93-sql-gcp-f-h-at-orange-business-3916557264?position=21&pageNum=0&refId=3%2BsKCnzKBomYeuJjjsOexw%3D%3D&trackingId=KZtYfL29GoYlm476j4MI9A%3D%3D&trk=public_jobs_jserp-result_search-card",
        "description": "Et si Business & Decision et Orange Business conjuguaient leurs forces pour devenir l‚Äôun des leaders europ√©ens de la Data transformation ?\nNous l‚Äôavons fait ! Notre alchimie nous positionne comme un acteur unique intervenant sur toutes les √©tapes du voyage de la donn√©e.\nDepuis 30 ans, Business & Decision, entit√© de Digital Services s'est impos√©e comme un partenaire strat√©gique pour la transformation Data de nombreux clients, dans des secteurs tr√®s vari√©s. Digital Services est aujourd‚Äôhui l‚ÄôESN d‚ÄôOrange Business alliant les expertises historiques Cloud et Digital d‚ÄôOrange ainsi que le c≈ìur de m√©tier Data/IA de Business & Decision. Son but est d‚Äôaccompagner les entreprises et les acteurs publics dans leur transformation gr√¢ce aux 4000 experts pr√©sents dans plusieurs grandes villes fran√ßaises comme Montpellier, Niort, Lyon, Bordeaux, Lille et Toulouse ‚Ä¶\nDescription du poste\nOrange Business, recherche pour son site de Lille, son futur Data Engineer pour rejoindre sa team Data.\nVotre quotidien ?\nEn int√©grant Orange Business, vous pouvez participer √† une grande diversit√© d‚Äôactivit√©s dans la Data. En voici un aper√ßu :\nAu d√©marrage du projet :\nRecueillir et analyser les besoins du client\nR√©diger les sp√©cifications fonctionnelles et techniques\nEstimre les charges\nPendant la phase de r√©alisation :\nMod√©liser des datawarehouses et datamart (int√©gration de flux et consolidation des donn√©es)\nD√©velopper les proc√©dures d‚Äôalimentation (ETL)\nD√©velopper en SQL\n/ PLSQL / Shell\nGarantir la qualit√© des donn√©es et leur disponibilit√©\nConcevoir et d√©velopper des solutions frontend BI √† des fins analytics & dashboarding\nR√©aliser la recette et les tests\nSuivre et mettre en production\nEn fonction de votre √©volution et de nos enjeux, vous pouvez aussi √©voluer sur des missions transverses (conseil, coaching, avant-vente, formation, audit, etc.). La prise d‚Äôinitiative est toujours la bienvenue !\nQualifications\nVous poss√©dez 3 ans d'exp√©rience ou plus dans la mise en ≈ìuvre de projets d√©cisionnels et ing√©nierie ou analyse data.\nVous avez de\nsolides comp√©tences en d√©veloppement SQL\n(job, scripting, d√©ploiement), vous avez l‚Äôhabitude de travailler dans un\nenvironnement Google Cloud Plateform\nainsi qu‚Äôavec\nPower BI\n.\nEnvie d‚Äôapprendre de nouvelles technos ? Vous souhaitez partager vos comp√©tences et b√©n√©ficier des expertises de la Team Orange Business ?\nOutre l‚Äôaspect technique, c‚Äôest une personnalit√© qui est recherch√©e !\nShow more\nShow less",
        "details": {
            "JobDetail": [],
            "TypeContract": "",
            "Salary": "",
            "Level": "",
            "Experience": "30 an(s)"
        },
        "title": "data engineer",
        "skills": {
            "DataBase": [
                "SQL"
            ],
            "MachineLearning": [
                "Orange"
            ],
            "DataVisualisation": [
                "Power BI"
            ],
            "Other": [
                "Cloud"
            ],
            "EnSoftSkils": [
                "Initiative"
            ]
        }
    },
    {
        "source": "LinkedIn",
        "company": "Chantelle",
        "location": "Cachan, √éle-de-France, France",
        "link": "https://fr.linkedin.com/jobs/view/data-engineer-h-f-at-chantelle-3909775663?position=22&pageNum=0&refId=3%2BsKCnzKBomYeuJjjsOexw%3D%3D&trackingId=WesNidpJXmnR0vuCvjZZUA%3D%3D&trk=public_jobs_jserp-result_search-card",
        "description": "La Direction des Syst√®mes d'Information et du Digital du groupe Chantelle recherche son/sa futur.e Data Engineer H/F, pour le lancement du grand chantier de r√©novation de l'architecture Data : la bascule de l'int√©gralit√© de son Data Warehouse vers Google Big Query.\nNous souhaitons recruter un Data Engineer H/F confirm√©.e, charg√©.e de contribuer √† la d√©finition de la feuille de route de la Chantelle Data Plaform. En tant que Data Engineer vous travaillerez au sein de l'√©quipe Data Int√©gration en charge de la Chantelle Data Platform.\nVos Missions :\n- Mettre en ≈ìuvre une infrastructure autour de Google Cloud Platform permettant de collecter (airbyte, API, ...) , transformer (dataform, Bigquery ...), exposer (dataviz, API, applications, ...) et historiser les donn√©es g√©n√©r√©es par l'entreprise.\n- Travailler en √©troite proximit√© avec les responsables des diff√©rents domaines fonctionnels (R√©f√©rentiels, Supply Chain, Manufacturing, B2B, Retail & e-commerce, Finance, ...), avec notre √©quipe de Data Analysts ainsi qu'avec l'√©quipe technique en charge des infrastructures transverses\n- √ätre force de proposition sur tous les sujets d'architecture et de mod√©lisation (choix de mise en place de pipeline temps r√©els ou au contraire de flux de donn√©es en mode batch, ou bien encore stockage sur Big Query / Big Table en fonction des cas d'usage).\n- D√©finir les √©l√©ments structurants, en justifiant vos choix, et les mettre en ≈ìuvre.\n- Rationaliser et moderniser notre architecture d'int√©gration inter-applicative; se projeter sur la cr√©ation d'un mod√®le de donn√©es de type Datamesh.\n- Faire la refonte de la BI de nombreux use cases tels que le pilotage de nos stocks, personnalisation de nos sites e-commerce en temps r√©el en fonction de nos profils client, etc‚Ä¶\nStack technique : Google Cloud Platform, BigQuery, DataForm, DataFlow, PubSub, Airbyte, Github ...\nBonne ma√Ætrise des langages Python et SQL\nPourquoi travailler chez Chantelle ?\nUne flexibilit√© dans votre lieu de travail, selon la politique de t√©l√©travail de l'entreprise.\n11 jours de RTT/an ainsi qu'un 13√®me mois.\nUne culture d'entreprise familiale bas√©e sur des valeurs de respect, de cr√©ativit√©, de durabilit√© et de transparence\nUne aventure dans laquelle vous pourrez vous √©panouir, apprendre et entreprendre, avec une grande vari√©t√© de missions et beaucoup d'autonomie\nDes √©quipes ressources humaines et des managers √† votre √©coute pour vous accompagner dans votre parcours professionnel\nDes r√©ductions sur nos produits et des ventes au personnel\nDes avantages dans votre qualit√© de vie au travail : une conciergerie compl√®te proposant un large panel de services, des activit√©s en interne, un CSE.\nVous souhaitez rejoindre un Groupe familial, innovant, engag√© et leader dans son secteur en France comme √† l'international et vous souhaitez apporter votre expertise et authenticit√© pour guider votre √©quipe vers le succ√®s : postulez et rejoignez le Groupe Chantelle !\nShow more\nShow less",
        "details": {
            "JobDetail": [
                "Confirm√©"
            ],
            "TypeContract": "",
            "Salary": "",
            "Level": "",
            "Experience": null
        },
        "title": "data engineer",
        "skills": {
            "ProgLanguage": [
                "Python"
            ],
            "DataBase": [
                "SQL"
            ],
            "CloudComputing": [
                "Google Cloud Platform"
            ],
            "DBMS": [
                "Big Query",
                "BigQuery"
            ],
            "Other": [
                "Cloud"
            ]
        }
    },
    {
        "source": "LinkedIn",
        "company": "Orange Business",
        "location": "Lille",
        "link": "https://fr.linkedin.com/jobs/view/data-engineer-mod%C3%A9lisation-sql-f-h-at-orange-business-3916551577?position=23&pageNum=0&refId=3%2BsKCnzKBomYeuJjjsOexw%3D%3D&trackingId=8Y5dwKvhVb6ZluKzoHL6Ag%3D%3D&trk=public_jobs_jserp-result_search-card",
        "description": "Et si Business & Decision et Orange Business conjuguaient leurs forces pour devenir l‚Äôun des leaders europ√©ens de la Data transformation ?\nNous l‚Äôavons fait ! Notre alchimie nous positionne comme un acteur unique intervenant sur toutes les √©tapes du voyage de la donn√©e.\nDepuis 30 ans, Business & Decision, entit√© de Digital Services s'est impos√©e comme un partenaire strat√©gique pour la transformation Data de nombreux clients, dans des secteurs tr√®s vari√©s. Digital Services est aujourd‚Äôhui l‚ÄôESN d‚ÄôOrange Business alliant les expertises historiques Cloud et Digital d‚ÄôOrange ainsi que le c≈ìur de m√©tier Data/IA de Business & Decision. Son but est d‚Äôaccompagner les entreprises et les acteurs publics dans leur transformation gr√¢ce aux 4000 experts pr√©sents dans plusieurs grandes villes fran√ßaises comme Montpellier, Niort, Lyon, Bordeaux, Lille et Toulouse ‚Ä¶\nDescription du poste\nOrange Business, recherche pour son site de Lille, son futur Data Engineer pour rejoindre sa team Data.\nVotre quotidien ?\nEn int√©grant Orange Business, vous pouvez participer √† une grande diversit√© d‚Äôactivit√©s dans la Data. En voici un aper√ßu :\nAu d√©marrage du projet :\nRecueillir et analyser les besoins du client\nR√©diger les sp√©cifications fonctionnelles et techniques\nEstimer les charges\nPendant la phase de r√©alisation :\nMod√©liser des datawarehouses et datamart (int√©gration de flux et consolidation des donn√©es)\nD√©velopper les proc√©dures d‚Äôalimentation (ETL)\nD√©velopper en SQL / PLSQL / Shell\nGarantir la qualit√© des donn√©es et leur disponibilit√©\nR√©aliser la recette et les tests\nSuivre et mettre en production\nEn fonction de votre √©volution et de nos enjeux, vous pouvez aussi √©voluer sur des missions transverses (conseil, coaching, avant-vente, formation, audit, etc.). La prise d‚Äôinitiative est toujours la bienvenue !\nQualifications\nVous poss√©dez 5 ans d'exp√©rience ou plus dans la mise en ≈ìuvre de projets d√©cisionnels et en mod√©lisation.\nVous avez de s\nolides comp√©tences en d√©veloppement SQL\n(job, scripting, d√©ploiement) ainsi que sur Python.\nEnvie d‚Äôapprendre de nouvelles technos ? Vous souhaitez partager vos comp√©tences et b√©n√©ficier des expertises de la Team Orange Business ?\nOutre l‚Äôaspect technique, c‚Äôest une personnalit√© qui est recherch√©e !\nShow more\nShow less",
        "details": {
            "JobDetail": [],
            "TypeContract": "",
            "Salary": "",
            "Level": "",
            "Experience": "30 an(s)"
        },
        "title": "data engineer",
        "skills": {
            "ProgLanguage": [
                "Python"
            ],
            "DataBase": [
                "SQL"
            ],
            "MachineLearning": [
                "Orange"
            ],
            "Other": [
                "Cloud"
            ],
            "EnSoftSkils": [
                "Initiative"
            ]
        }
    },
    {
        "source": "LinkedIn",
        "company": "eXalt Value",
        "location": "√éle-de-France, France",
        "link": "https://fr.linkedin.com/jobs/view/data-engineer-at-exalt-value-3897767649?position=24&pageNum=0&refId=3%2BsKCnzKBomYeuJjjsOexw%3D%3D&trackingId=%2BCqn5%2Bror35%2Fyn7g5I0gCQ%3D%3D&trk=public_jobs_jserp-result_search-card",
        "description": "eXalt\nest un cabinet de conseil IT\nPure player Data\n& IA bas√© √† Paris.\nNotre offre s‚Äôarticule autour de 4 piliers r√©unis au sein d‚Äôune m√™me communaut√© pour un accompagnement √† 360¬∞ alliant une expertise technique et m√©thodologique √† une approche conseil m√©tier:\nData Gouvernance & Project\nData Engineering & Big Data\nData Performance & Analytics\nData Science & IA\nFiliale du groupe eXalt, cr√©√© en 2018,\nregroupant plus de\n950 collaborateurs en France\n(Paris, Lyon, Bordeaux, Lille, Nantes, Marseille)\net √† l‚Äôinternational\n(Colombie, Etats-Unis, Espagne, Belgique),\neXalt Value\napporte une\nexpertise approfondie\ndans le domaine de la Data & IA et conseille les entreprises dans le d√©ploiement de leurs strat√©gies data-driven.\nB√©n√©ficiant du support du groupe eXalt\n(1er dans la cat√©gorie Conseil & Audit au classement des Champions de la Croissance 2024), eXalt Value\nest en pleine croissance et regroupe aujourd‚Äôhui une communaut√© d‚Äôexpertise de plus de 60 collaborateurs en r√©gion parisienne.\nNos consultants interviennent sur d\nes projets d‚Äôenvergure\ndans divers secteurs d‚Äôactivit√©,\nBanque & Assurance, M√©dias, Transports, Retail, Tourisme, etc.\nNous recherchons un\nData Engineer Confirm√© H/F (minimum 4 ans d'exp√©rience dans la fonction)\npour rejoindre notre communaut√© sur le\npilier Data Engineering & Big Data.\nVos missions:\nConcevoir et d√©velopper des pipelines et des flux de donn√©es.\nInt√©grer et transformer des donn√©es provenant de diff√©rentes sources.\nD√©velopper et mettre en ≈ìuvre des algorithmes de traitement de donn√©es avanc√©s.\nCollaborer √©troitement avec les √©quipes clients pour comprendre leurs besoins et fournir des solutions adapt√©es.\nAssurer la qualit√© et la fiabilit√© des solutions d√©velopp√©es.\nConseiller les √©quipes clients sur les solutions √† mettre en place.\nLes Pr√©requis :\nTitulaire d'un Bac+5, Ecole d'Ing√©nieur\nMa√Ætrise d'un ou plusieurs langages de programmation (\nPython, Scala, Spark, etc\n.).\nExp√©rience approfondie des technologies\nBig Data (Hadoop, Spark, Kafka, Talend, etc.)\nExp√©rience av√©r√©e\nen\nenvironnement Cloud (AWS, GCP, ou Azure)\n.\nSolides comp√©tences en conception et en optimisation de pipelines de donn√©es.\nExp√©rience de travail en\nm√©thode Agile\nCapacit√© √† travailler de mani√®re autonome et en √©quipe.\nExcellentes comp√©tences en communication et en r√©solution de probl√®mes.\nMa√Ætrise de l‚Äôanglais (oral & √©crit dans un contexte international professionnel).\nVotre environnement eXalt√©:\nUn environnement de travail Collaboratif\nfavorisant les initiatives et projets transverses √† la Practice Data & IA (Lab IA, Data Hub, etc.).\nUn collectif de consultants passionn√©s,\ns‚Äôint√©ressant aux tendances innovantes du secteur.\nUne Practice de proximit√©,\nprivil√©giant la mont√©e en comp√©tence de ses collaborateurs (formations, coachings, mentorats, etc.)\nUn suivi individualis√© et de proximit√©\npar un.e Data Sales Manager r√©f√©rent du compte client, un.e Charg√©.e RH et un.e Practice Manager\nUne √©quipe ouverte et dynamique,\nqui privil√©gie les moments de partage et de convivialit√© (s√©minaires, eXaltemps, meet-up, d√©jeuners d‚Äô√©quipe, etc.)\nNotre processus de recrutement :\nUn entretien RH avec Estelle,\n√† la suite duquel vous saurez tout (ou presque) d‚ÄôeXalt Value,\nUn entretien technique avec un Manager assorti d‚Äôun test technique,\nlors duquel vous aurez l‚Äôoccasion de d√©montrer vos talents mais aussi d‚Äôapprendre avant m√™me de dire oui,\nUn entretien final avec la Directrice Associ√©e ou le Directeur Op√©rationnel,\npour finir de vous convaincre de nous rejoindre üòä\nNous avons h√¢te de recevoir vos CV, et de faire votre connaissance!\nShow more\nShow less",
        "details": {
            "JobDetail": [
                "Confirm√©"
            ],
            "TypeContract": "",
            "Salary": "",
            "Level": "Bac+5",
            "Experience": "4 an(s)"
        },
        "title": "data engineer",
        "skills": {
            "ProgLanguage": [
                "Scala",
                "Python"
            ],
            "BigData": [
                "Hadoop",
                "Spark"
            ],
            "CloudComputing": [
                "GCP",
                "AWS",
                "Azure"
            ],
            "Other": [
                "Cloud",
                "Big Data"
            ],
            "EnSoftSkils": [
                "Communication"
            ]
        }
    },
    {
        "source": "LinkedIn",
        "company": "MindPal",
        "location": "Paris, √éle-de-France, France",
        "link": "https://fr.linkedin.com/jobs/view/data-engineer-at-mindpal-3919800161?position=25&pageNum=0&refId=3%2BsKCnzKBomYeuJjjsOexw%3D%3D&trackingId=qCmZh4kBZiW%2FKGAELVKS7Q%3D%3D&trk=public_jobs_jserp-result_search-card",
        "description": "We are looking for\nData Engineer!\nResponsibilities\nDesigning, creating, and maintaining data processing systems\nAnalyzing and optimizing data processing workflows\nCollaborating with the team to ensure data quality and efficiency\nTesting and implementing new solutions\nRequirements\nAt least 2 years of experience in designing and creating data processing systems\nProficiency in tools and programming languages related to data engineering (e.g. Hadoop, Spark, Scala, Python)\nExcellent knowledge of databases and SQL language\nAbility to work in a team and communicate effectively with other departments\nCommunicative English skills\nExperience with AWS/AWS Glue is a plus\nWe Offer\nB2B contract\nFull-time job\nRemote work and flexible hours\nShow more\nShow less",
        "details": {
            "JobDetail": [
                "Remote",
                "Full"
            ],
            "TypeContract": "",
            "Salary": "",
            "Level": "",
            "Experience": null
        },
        "title": "data engineer",
        "skills": {
            "ProgLanguage": [
                "Scala",
                "Python"
            ],
            "DataBase": [
                "SQL"
            ],
            "BigData": [
                "Hadoop",
                "Spark"
            ],
            "CloudComputing": [
                "AWS"
            ]
        }
    },
    {
        "source": "LinkedIn",
        "company": "EarthDaily Agro",
        "location": "Balma, Occitanie, France",
        "link": "https://fr.linkedin.com/jobs/view/data-engineer-at-earthdaily-agro-3883708013?position=26&pageNum=0&refId=3%2BsKCnzKBomYeuJjjsOexw%3D%3D&trackingId=JIXRz5%2F3ejQTYD%2BCJbgc1w%3D%3D&trk=public_jobs_jserp-result_search-card",
        "description": "About Us\nEarthDaily Agro provides space age data and analytics to the organizations and people who feed the planet!\nWith 35 years of industry experience, EarthDaily Agro provides customers with the data, analysis and knowledge they need to make more efficient and effective decisions. B2B services range from global risk management and monitoring of agricultural commodities to the marketing of inputs and precision agriculture consulting, using the latest research in agronomy, information technologies and remote sensing.\nEarthDaily Agro also develops highly customized business solutions for agricultural lenders, insurers, input suppliers and food companies, with easy-to-use analytics, that help reduce the daily risks of agriculture.\nEarthDaily Agro is headquartered in Minneapolis, MN, USA, with offices in France, Brazil, Australia and Switzerland and is a division of EarthDaily Analytics Corp.\nEarthDaily Analytics Corp., a vertically-integrated data processing and analytics company, is launching a new constellation of earth observation satellites. The EarthDaily satellite constellation will significantly enhance geospatial analytics capabilities in agriculture, forestry, environment, financial services, and intelligence, among many other verticals.\nMain Job Tasks And Responsibilities\nAs a EarthDailyAgro Data Engineer, your primary responsibility will be to design, develop, and manage data pipelines and infrastructure specialized for geospatial and remote sensing applications. You will work closely with data scientists, geospatial analysts, remote sensing experts, software engineers, and DevOps teams to ensure the successful deployment and scaling of data pipeline to feed geospatial data machine learning models. Your role will be crucial in optimizing the geospatial machine learning ecosystem and ensuring the seamless integration of AI-driven geospatial solutions into real-world applications.\nYour Responsibilities Include\nCloud-based data pipeline Conceptualization, Development and Scaling: Build up pipeline to ingest large volumes of geospatial data, pre-process them and meet data scientists‚Äô requirements, in terms of accessibility, speed, format, quality.\nAutomation and CI/CD: Industrialization of pipeline deployment, orchestration, workflows, and versioning.\nCost & Speed Optimization: Collaborate with infrastructure team to develop, optimize, and fine-tune pipeline.\nCloud and Containerization: Experience with cloud platforms (e.g., AWS, Azure, GCP) and containerization tools.\nInfrastructure Management: Utilize containerization technologies and cloud-based services to set up and manage infrastructure, enabling seamless deployment and scalability.\nMonitoring and Anomaly Detection: Implement monitoring systems to track pipeline performance and identify anomalies.\nVersion Control and Data Version Control: Proficient with version control systems like Git and DVC.\nSecurity and Compliance: Ensure the security and privacy of geospatial data, adhering to relevant data protection regulations and industry best practices.\nCollaboration and Communication: Collaborate with interdisciplinary teams to integrate data pipeline into existing applications or develop new geospatial products.\nIssue Resolution and Troubleshooting: Identify and resolve promptly technical issues related to geospatial data processing, performance, or infrastructure.\nEducation, Knowledge And Abilities\nRequirements\nEducation: Master's degree in Computer Science, specialisation in Geomatics and/or Remote sensing would be a plus.\nExperience: 3+ years experiences with data pipeline processes and deployment is a must-have. Proven hands-on experience in setting up pipelines and data processes with opensource tools (e.g., MLFlow, Argo, Kubeflow) is desirable.\nProgramming Skills: Proficiency in Python and with data manipulation frameworks (e.g., dataframe, numpy, pandas, xarray, rasterio) and librairies (e.g., Dask).\nProblem-Solving Skills: Autonomous, and strong analytical and problem-solving abilities to address complex geospatial data and analysis challenges.\nCommunication Skills: Excellent communication and interpersonal skills to collaborate effectively with cross-functional teams and stakeholders.\nFrench mandatory (job based in France). Fluent in English (oral and written):‚ÄØmeetings with internal are mostly in‚ÄØEnglish.\nPreferred Additional Skills\nExperience with Earth Observation (EO) data analysis and processing.\nExperience with geospatial data formats (e.g., GeoTIFF, Shapefile, NetCDF).\nSpatial Analysis Techniques: Understanding of spatial analysis techniques and algorithms commonly used in geospatial data manipulation.\nRemote Sensing Integration: Knowledge of remote sensing data sources (e.g., STAC catalog, satellite imagery, LiDAR, SAR) integration into data pipelines for accurate and up-to-date geospatial analysis.\nCONDITIONS\nFull time job based in Balma, near Toulouse, France.\nFixed + Bonuses\nTR / \"Family\" insurance / CSE\nPowered by JazzHR\nWrfSXQ5YJg\nShow more\nShow less",
        "details": {
            "JobDetail": [
                "Remote",
                "Full"
            ],
            "TypeContract": "",
            "Salary": "",
            "Level": "",
            "Experience": null
        },
        "title": "data engineer",
        "skills": {
            "ProgLanguage": [
                "Python"
            ],
            "DataAnalytics": [
                "NumPy",
                "Pandas"
            ],
            "CloudComputing": [
                "GCP",
                "AWS",
                "Azure"
            ],
            "DevTools": [
                "Git"
            ],
            "Collaboration": [
                "Teams"
            ],
            "Other": [
                "Machine Learning",
                "Cloud",
                "DevOps",
                "CI/CD"
            ],
            "EnSoftSkils": [
                "Interpersonal Skills",
                "Communication",
                "Collaboration"
            ]
        }
    },
    {
        "source": "LinkedIn",
        "company": "Aubay",
        "location": "√éle-de-France, France",
        "link": "https://fr.linkedin.com/jobs/view/data-engineer-f-h-at-aubay-3573871076?position=27&pageNum=0&refId=3%2BsKCnzKBomYeuJjjsOexw%3D%3D&trackingId=%2BDhsy3rEKRHdvXmK%2BbFIcQ%3D%3D&trk=public_jobs_jserp-result_search-card",
        "description": "Passionn√© par la Data, tu souhaites rejoindre une communaut√© d‚Äôexperts dans le domaine afin de d√©velopper tes comp√©tences en Data Engineering. Aubay renforce ses √©quipes Data et recherche des Data Engineers pour int√©grer des dispositifs de projets pointus et vari√©s.\nTon quotidien en tant que Data Engineer chez Aubay, :\nD√©finition de la strat√©gie de stockage et mise en ≈ìuvre des technologie appropri√©es (base de donn√©es SQL, NoSQL, stockage distribu√©,‚Ä¶)\nIngestion des donn√©es (structur√©es, semi-structur√©es ou non-structur√©es) selon diff√©rentes fr√©quences : batch, micro-batch ou temps r√©el\nConception et mise en ≈ìuvre de pipelines de donn√©es afin de fournir des donn√©es pr√™tes √† l‚Äôemploi aux consommateurs : uniformisation, mise en qualit√©, enrichissement, calcul d‚Äôindicateurs,‚Ä¶\nConception et d√©veloppement d‚ÄôAPI pour exposer les donn√©es aupr√®s d‚Äôapplications tierces\nAppui aux Data Scientists pour industrialiser et optimiser les algorithmes de Machine Learning\nPr√©paration et animation d‚Äôateliers de travail avec des interlocuteurs vari√©s : recueil/approfondissement des besoins m√©tiers, avancement/restitution des travaux, transfert de comp√©tences,‚Ä¶\nTon profil :\nTu dispose d‚Äôune formation niveau BAC+5 (Master 2 ou √©cole d‚Äôing√©nieur) sp√©cialis√©e en informatique\nTu as d√©j√† une premi√®re exp√©rience significative (a minima 2 ans) en Data Engineering sur des technologies Big Data\nLes technologies telles que Hadoop, Spark ou Kafka sont tes technologies de pr√©dilection\nLa programmation n‚Äôa plus de secret pour toi et tu maitrise parfaitement un ou plusieurs langages de programmation suivants : Java, Scala et Python\nTu ma√Ætrises les tenants et aboutissants de la philosophie DevOps et des outils orient√©s CI/CD\nTu es soucieux de la qualit√© et de la performance de tes d√©veloppements et tu t'int√©resse √† l‚Äôinnovation frugale\nTu es un expert technique dans ton domaine sans pour autant oublier l‚Äôimportance d‚Äôune communication orale et √©crite de qualit√© et adapt√©e √† chacun de tes interlocuteurs\nTu travaille au quotidien en mode agile et tu en maitrise les fondements\nCe qui nous caract√©rise :\nDes missions et projets dans le domaine du Data Engineering en nombre et dans des secteurs vari√©s (Banque, Assurance, Telecom, Industrie,‚Ä¶) qui permettent √† nos collaborateurs de monter en comp√©tences et de devenir des experts Data reconnus\nDe l‚Äôapprentissage en continu avec des formations et des certifications sur les technologies Data d‚Äôaujourd‚Äôhui et de demain\nDes experts Data mobilisables pour accompagner et soutenir techniquement les collaborateurs sur leurs projets\nDes communaut√©s de savoir-faire Data proposant de mani√®re r√©guli√®re aux collaborateurs d‚ÄôAubay du contenu et des √©v√®nements de partage (webinar, meetup/afterwork, BBL,‚Ä¶) sur les th√©matiques suivantes : Data Engineering, Data Viz, Data Science/IA, Data Platform & Architecture,‚Ä¶\nAubay encourage la diversit√© sous toutes ses formes et garantit l'√©galit√© des chances √† tous les candidats. Tous nos postes sont ouverts aux personnes en situation de handicap et nous proposons tous les am√©nagements n√©cessaires.\nTa carri√®re chez Aubay :\nTu auras la possibilit√© de d√©velopper et certifier tes comp√©tences sur les derni√®res technologies Data avec un focus fort sur les plateformes Data Cloud telles qu‚ÄôAzure Synapse Analytics, Google Cloud Platform, Snowflake et Databricks\nTu pourras rejoindre la BU d‚Äôexcellence Data et √©voluer au sein d‚Äôun environnement humain et professionnel de haut niveau. Tu profiteras d‚Äôun management sur-mesure pour t'accompagner dans ta trajectoire de carri√®re\nAu sein de la BU d‚Äôexcellence, de multiples perspectives s‚Äôoffriront √† toi :\nR√¥le de ¬´ Lead ¬ª : Vous pourrez gagner en responsabilit√© sur le plan technologique et devenir un r√©f√©rent aupr√®s de nos clients et des collaborateurs de la communaut√© Data Engineering\nR√¥le de ¬´ Champion ¬ª : Vous repr√©senterez Aubay aupr√®s d‚Äôun ou plusieurs de nos partenaires √©diteurs strat√©giques et vous participerez activement √† l‚Äôanimation de la relation sur le plan technologique\nR√¥le de ¬´ Head ¬ª : Vous pourrez prendre la responsabilit√© du savoir-faire Data Engineering et de ses offres et en assurer le d√©veloppement au sens large (d√©veloppement business, recrutement, management de collaborateurs, d√©finition de la strat√©gie et animation de la communaut√© au sein du groupe Aubay,‚Ä¶)\nBesoin d‚Äôen savoir plus sur le processus de recrutement ?\nUn √©change macro au niveau RH avec Doriane\nUn entretien technique avec Marius ou Peter, deux de nos r√©f√©rents techniques\nUn √©change manag√©rial avec le Directeur de la BU Modern BI & Data\nA savoir que l‚Äôordre des √©tapes peut varier selon tes envies (ex : √©change manag√©rial avec l‚Äô√©change technique)\nAubay encourage la diversit√© sous toutes ses formes et garantit l'√©galit√© des chances √† tous les candidats. Tous nos postes sont ouverts aux personnes en situation de handicap et nous proposons tous les am√©nagements n√©cessaires.\nShow more\nShow less",
        "details": {
            "JobDetail": [],
            "TypeContract": "",
            "Salary": "",
            "Level": "Bac+5",
            "Experience": "2 an(s)"
        },
        "title": "data engineer",
        "skills": {
            "ProgLanguage": [
                "Java",
                "Scala",
                "Python"
            ],
            "DataBase": [
                "SQL",
                "NoSQL"
            ],
            "BigData": [
                "Databricks",
                "Hadoop",
                "Spark"
            ],
            "CloudComputing": [
                "Google Cloud Platform",
                "Azure"
            ],
            "DBMS": [
                "Snowflake"
            ],
            "Other": [
                "CI/CD",
                "Big Data",
                "Machine Learning",
                "Cloud",
                "DevOps"
            ],
            "EnSoftSkils": [
                "Communication"
            ]
        }
    },
    {
        "source": "LinkedIn",
        "company": "Air France",
        "location": "Provence-Alpes-C√¥te d'Azur, France",
        "link": "https://fr.linkedin.com/jobs/view/data-engineer-d%C3%A9veloppeur-big-data-%23-h-f-at-air-france-3900080172?position=28&pageNum=0&refId=3%2BsKCnzKBomYeuJjjsOexw%3D%3D&trackingId=dmp2wF79Mu2ZqoKLf6rgVA%3D%3D&trk=public_jobs_jserp-result_search-card",
        "description": "Description du poste\nIntitul√© du poste\nData Engineer / D√©veloppeur Big Data # H/F\nM√©tier\nSyst√®mes d'informations - D√©veloppement\nCat√©gorie socio-professionnelle\nCadre\nPr√©sentation du contexte\nVous avez peut-√™tre d√©j√† voyag√© avec nous, mais que connaissez-vous de nos m√©tiers et de la richesse des donn√©es qu‚Äôils g√©n√®rent au quotidien ? Comment le traitement et l‚Äôexploitation de ces donn√©es peut contribuer √† notre strat√©gie de Revenue Management, ou encore aux multiples op√©rations √† r√©aliser pour permettre √† un vol de partir √† l‚Äôheure ?\nAir France-KLM fait r√™ver 104 millions de passagers par an, en les emmenant vers plus de 250 destinations, gr√¢ce √† une flotte de plus de 500 appareils. Le Groupe emploie 80 000 collaborateurs partout dans le monde :les opportunit√©s sont vastes pour mettre √† profit ses comp√©tences, apprendre et se d√©velopper !\nLe d√©partement de d√©veloppement DATA, OR & AI d‚ÄôAir France, au sein de la direction des Syst√®mes d‚ÄôInformation, intervient dans toute la cha√Æne de captation et de traitement des donn√©es du groupe pour d√©livrer √† nos m√©tiers des solutions applicatives cl√©s en main.\nLe d√©partement est √©galement en charge de l‚Äôensemble des outils techniques (ETL, DataLakes, DataWarehouses, Data visualisation) et du d√©veloppement des talents et comp√©tences de Data Engineering.\nNotre mission ? Transformer la donn√©e brute en d√©cision intelligente, pour mieux optimiser les m√©tiers d‚ÄôAir France ‚Äì KLM !\nPour cela, nous avons chacun un r√¥le essentiel √† jouer, pourquoi le v√¥tre ne serait pas celui de Data Engineer et de d√©veloppeur Big Data ?\nDescription de la mission\nAu sein de notre d√©partement, vous travaillerez main dans la main avec d‚Äôautres Data Engineers et d√©veloppeurs Big Data ainsi qu‚Äôavec des sp√©cialistes des m√©tiers.\nInt√©gr√© au sein d‚Äôune product team agile passionn√©e et dynamique :\nVous participez √† l‚Äôanalyse des besoins m√©tiers du commercial, des op√©rations a√©riennes, de l‚Äôexploitation sol en a√©roport, de la maintenance a√©ronautique ou encore du Cargo.\nVous contribuez √† la d√©finition, au d√©veloppement, √† l‚Äôindustrialisation et √† la maintenance d‚Äôapplications Big Data ou en Business Intelligence\nVous pr√©sentez la restitution de vos travaux et accompagnez les utilisateurs d‚Äôun point de vue fonctionnel ou m√©thodologique\nVous serez en contact avec les directions m√©tier du groupe Air France KLM.\nNous attachons beaucoup d'importance au d√©veloppement des comp√©tences de nos collaborateurs ainsi qu‚Äô√† leur offrir des conditions de travail favorables √† l‚Äôautonomie et aux missions √† forte valeur ajout√©e. L'ouverture, le respect, la bienveillance et le partage sont des valeurs humaines port√©es par l'entreprise.\nProfil recherch√©\nVous √™tes dipl√¥m√© de niveau Master ou Ing√©nieur dans les domaines informatiques, vous avez acquis une exp√©rience professionnelle dans le d√©veloppement d‚Äôapplications.\nVous disposez d‚Äôune exp√©rience du d√©veloppement indispensable en Backend / Java\nVous ma√Ætrisez les bases de donn√©es relationnelles et le langage SQL\nEn Compl√©ment, Vous Avez Une Connaissance Ou Une Exp√©rience Dans Tout Ou Partie Des Concepts Ou Outils Suivants\nEnvironnement Big Data (Spark, Hadoop, Elasticsearch, Kafka, ...)\nBase de donn√©es noSQL (MongoDB, HBase, REDIS) ou Data Warehouse Teradata\nOutil de Datavisualisation (Spotfire, PowerBI, Qlik ou Kibana)\nSolutions de Cloud (GCP) et hybride (GCP / AZURE)\n(Ces comp√©tences compl√©mentaires ou manquantes pouvant aussi s'acqu√©rir √† travers un parcours de reskilling et de formations aux outils du data engineering dispens√© en interne).\nVous avez particip√© √† des projets organis√©s en Scrum ou Kanban, et avez peut-√™tre m√™me ≈ìuvr√© comme Scrum-Master, ce qui vous permettra de vous int√©grer ais√©ment au sein d‚Äôune Product Team. Votre esprit de synth√®se, votre force de conviction et votre ma√Ætrise de la communication facilitent les d√©cisions avec l‚Äôensemble des collaborateurs de l‚Äô√©quipe, √©ventuellement en langue anglaise, √† l‚Äô√©crit comme √† l‚Äôoral.\nVous √™tes autonome, rigoureux(se), responsable et curieux(se), vous aimez travailler en √©quipe. Vous poss√©dez de bonnes capacit√©s d'√©coute, d'analyse, de synth√®se et de communication.\nEt bien s√ªr, vous √™tes passionn√©(e), enthousiaste et ing√©nieux(se)\nCe que nous vous offrons\nDe la cr√©ation de valeur pour l‚Äôensemble des m√©tiers d‚ÄôAir France KLM\nDes challenges et probl√©matiques complexes √† r√©soudre\nL‚Äôopportunit√© de d√©ployer des solutions Data industrielles √† l‚Äô√©chelle !\nUne grande part de responsabilit√© dans une structure hi√©rarchique horizontale\nUn important degr√© de libert√© pour apprendre et d√©velopper son expertise au sein de l‚Äô√©quipe\nOn vous attend le plus rapidement possible ! Et pour une dur√©e ind√©termin√©e ;)\nType de contrat\nCDI\nTemps partiel possible\nNon\nType d'horaires\nAdministratif\nProfil candidat\nNiveau d'√©tudes min. requis\nBac + 5 et plus\nLangue\nAnglais (4 - Confirm√© / C1)\nLocalisation du poste\nLocalisation du poste\nFrance, Provence-Alpes-C√¥te d'Azur, Alpes Maritimes (06)\nSite\nValbonne\nShow more\nShow less",
        "details": {
            "JobDetail": [
                "Hybride",
                "Confirm√©"
            ],
            "TypeContract": "CDI",
            "Salary": "",
            "Level": "",
            "Experience": null
        },
        "title": "data engineer",
        "skills": {
            "ProgLanguage": [
                "Java"
            ],
            "DataBase": [
                "MongoDB",
                "HBase",
                "Elasticsearch",
                "SQL",
                "NoSQL"
            ],
            "BigData": [
                "Hadoop",
                "Spark"
            ],
            "CloudComputing": [
                "GCP",
                "Azure"
            ],
            "SoftBigDataProcessing": [
                "HBase"
            ],
            "Other": [
                "Cloud",
                "Big Data"
            ],
            "EnSoftSkils": [
                "Communication"
            ]
        }
    },
    {
        "source": "LinkedIn",
        "company": "WA.Technology",
        "location": "Crouseilles, Nouvelle-Aquitaine, France",
        "link": "https://fr.linkedin.com/jobs/view/junior-data-engineer-at-wa-technology-3908458326?position=29&pageNum=0&refId=3%2BsKCnzKBomYeuJjjsOexw%3D%3D&trackingId=pTTf1RlEgSzwnv0Px26QCw%3D%3D&trk=public_jobs_jserp-result_search-card",
        "description": "WA.Technology\nis a B2B supplier of iGaming solutions with rapidly growing clients and partnerships in emerging markets. We offer a state-of-the-art iGaming platform, turnkey solutions, and standalone products that empower operators to enter or expand into emerging markets quickly and easily.\nThe WA.Platform is a fully scalable and customisable solution, featuring over 75 game providers, 6,400+ games, and support for multiple currencies, along with access to over 80 payment methods. WA. Technology enables operators to build their own casino, sportsbook, lottery, fantasy, or poker business precisely as they envision it.\nAbout The Role,\nWe are seeking a highly skilled and motivated\nData Engineer\nto design, implement, and maintain efficient and scalable data pipelines on the Google Cloud Platform (GCP). In this role, you will be responsible for managing data from MariaDB and Kafka sources, ensuring seamless integration into BigQuery, our primary data destination. Collaboration with cross-functional teams is crucial to understanding and meeting diverse data needs.\nIn this role, you will need to:\nDesign, implement, and maintain robust data pipelines on Google Cloud Platform.\nIntegrate MariaDB and Kafka as primary data sources for seamless data flow into BigQuery.\nCollaborate across departments to address unique data requirements aligned with organizational goals.\nUtilize Dataflow and Dataform for efficient data processing and transformation.\nEnsure data integrity through rigorous validation and cleansing processes.\nOptimize cloud-based infrastructure for speed and scalability.\nImplement monitoring tools for proactive system performance tracking and issue resolution.\nProvide ongoing support for data integrity and availability.\nMaintain comprehensive documentation of data architecture, updating regularly.\nStay informed about the latest data technology trends.\nEvaluate and recommend new technologies/methodologies to enhance processing and analysis capabilities.\nWhat are the key experience and personal attribute requirements?\nBachelor's degree in Computer Science, Information Technology, or a related field.\n2+ Hands-on experience relational database\nProven experience in developing data pipelines and ETL processes.\nStrong SQL skills.\nKnowledge of data modeling and database design.\nExcellent collaboration and communication skills.\nStrong problem-solving and troubleshooting abilities.\nAbility to work independently and as part of a team.\nContinuous learner, keeping up with emerging trends in data engineering.\nWhat are some of the benefits of working at WA Technology?\n100% remote opportunity\nFlexible work environment\nAttractive remuneration package\nOpportunity to work with well-connected industry leaders.\nA leadership approach that fosters innovation, creativity, and trust.\nOpportunity to experience the buzz of highly driven and motivated work colleagues.\nExperience a start-up feel in a fast-paced growth-driven environment.\nShow more\nShow less",
        "details": {
            "JobDetail": [
                "Remote",
                "Full"
            ],
            "TypeContract": "",
            "Salary": "Package",
            "Level": "",
            "Experience": null
        },
        "title": "data engineer",
        "skills": {
            "DataBase": [
                "SQL"
            ],
            "CloudComputing": [
                "GCP",
                "Google Cloud Platform"
            ],
            "DBMS": [
                "BigQuery"
            ],
            "Collaboration": [
                "Teams"
            ],
            "Other": [
                "Cloud"
            ],
            "EnSoftSkils": [
                "Creativity",
                "Leadership",
                "Communication",
                "Collaboration"
            ]
        }
    },
    {
        "source": "LinkedIn",
        "company": "iPepperGroup",
        "location": "Valbonne, Provence-Alpes-C√¥te d'Azur, France",
        "link": "https://fr.linkedin.com/jobs/view/data-engineer-h-f-at-ipeppergroup-3894091360?position=30&pageNum=0&refId=3%2BsKCnzKBomYeuJjjsOexw%3D%3D&trackingId=ha0JPYWhIadsVqbabNBPCg%3D%3D&trk=public_jobs_jserp-result_search-card",
        "description": "iPepper recrute pour l'un de ses clients une PME √©diteur de logiciel dans le domaine du voyage, un\nData Engineer (H/F)\npassionn√©(e) et exp√©riment√©(e) pour rejoindre une √©quipe dynamique.\nEn tant qu'Ing√©nieur(e) Data, vous serez en charge d'extraire et de transformer des donn√©es, de construire et d'optimiser des pipelines de donn√©es, ainsi que de concevoir des visualisations de donn√©es intuitives et informatives.\nResponsabilit√©s :\nConcevoir, construire et maintenir des pipelines de donn√©es √©volutifs et efficaces pour transf√©rer des donn√©es entre des bases de donn√©es SQL et NoSQL.\nD√©velopper et mettre en ≈ìuvre des processus ETL pour extraire, transformer et charger des donn√©es √† partir de diff√©rentes sources dans notre entrep√¥t de donn√©es.\nCollaborer avec des √©quipes pluridisciplinaires pour comprendre les besoins en donn√©es et garantir la fourniture r√©ussie de solutions de donn√©es.\nOptimiser et ajuster les pipelines de donn√©es existants pour la performance et la fiabilit√©.\nConcevoir et d√©velopper des visualisations de donn√©es et des tableaux de bord pour fournir des insights exploitables aux parties prenantes.\nSurveiller et r√©soudre les probl√®mes de pipelines de donn√©es, en veillant √† la qualit√© et √† l'int√©grit√© des donn√©es.\nProfil recherch√© :\nDipl√¥me universitaire en informatique, en ing√©nierie ou dans un domaine connexe.\nExp√©rience av√©r√©e en tant que Data Engineer ou dans un r√¥le similaire, avec un accent particulier sur la construction de pipelines de donn√©es et de processus ETL.\nCompr√©hension solide des bases de donn√©es\nSQL\net\nNoSQL\n, y compris la mod√©lisation des donn√©es et la conception de sch√©mas.\nMa√Ætrise des langages de programmation tels que\nPython, Java ou Scala.\nExp√©rience avec des outils de visualisation de donn√©es tels que\nTableau, Power BI.\nSolides comp√©tences en analyse et en r√©solution de probl√®mes, avec la capacit√© de traduire des donn√©es complexes en insights exploitables.\nExcellentes comp√©tences en communication et en collaboration, avec la capacit√© de travailler efficacement dans un environnement d'√©quipe pluridisciplinaire.\nShow more\nShow less",
        "details": {
            "JobDetail": [],
            "TypeContract": "",
            "Salary": "",
            "Level": "",
            "Experience": null
        },
        "title": "data engineer",
        "skills": {
            "ProgLanguage": [
                "Java",
                "Scala",
                "Python"
            ],
            "DataBase": [
                "SQL",
                "NoSQL"
            ],
            "DataVisualisation": [
                "Power BI",
                "Tableau"
            ],
            "EnSoftSkils": [
                "Communication",
                "Collaboration"
            ]
        }
    },
    {
        "source": "LinkedIn",
        "company": "LCL",
        "location": "Villejuif, √éle-de-France, France",
        "link": "https://fr.linkedin.com/jobs/view/data-engineer-profils-exp%C3%A9riment%C3%A9s-h-f-at-lcl-3888403052?position=31&pageNum=0&refId=3%2BsKCnzKBomYeuJjjsOexw%3D%3D&trackingId=1669O%2BXVTXi8nbyJkeSoXA%3D%3D&trk=public_jobs_jserp-result_search-card",
        "description": "üè¶ LCL, c‚Äôest LA banque urbaine du Groupe Cr√©dit Agricole - avec nous, accompagnez la transformation, le d√©veloppement et le maintien technologiques de nos outils avec une vision business et de satisfaction de nos 6 millions de clients.\nEn tant qu‚Äôacteur majeur de la banque de d√©tail, nous nous adaptons chaque jour aux nouveaux modes de consommation et les projets de nos de clients internes et externes tout en garantissant le besoin de s√©curit√© et de d√©veloppement technologique qu‚Äôimpliquent nos activit√©s.\nüí°Organis√©es en mode Agile, les 8 squads de la tribu DATA (6 squads M√©tier et 2 squads transverses) ≈ìuvrent au quotidien pour r√©pondre √† un enjeu majeur pour la banque : la collecte, le stockage, la gestion et l‚Äôusage de la donn√©e. En interaction permanente avec les autres tribus IT et les m√©tiers, elles √©tudient et proposent les solutions et architectures √† d√©ployer pour r√©pondre au mieux aux strat√©gies de d√©veloppement et de pilotage de l‚Äôensemble des m√©tiers de la banque.\nRejoignez-nous si vous souhaitez participer aux r√©flexions et au d√©veloppement de la trajectoire technique et DataCentric du SI LCL et plus largement du Groupe CA. Vous c√¥toierez et serez au c≈ìur de l‚Äôimpl√©mentation de technologies vari√©es telles que les plateformes Teradata, les solutions d‚Äôarchitecture applicative des technologies BigData ou IA, des environnements analytiques ou encore des solutions de datavisualisation. Vous assurerez le traitement de donn√©es en temps r√©el ou en batch et exposerez les donn√©es sous diff√©rentes formes.\nQue vous souhaitiez devenir expert sur les socles technologiques ou relever le challenge de la gestion de projets M√©tier, nous vous aiderons √† atteindre vos propres objectifs.\nVous rejoindrez une √©quipe pluridisciplinaire, clairement orient√©e vers le d√©veloppement de ses collaborateurs √† de nouvelles technologies !\nüéØ En tant que Data Engineer :\n¬∑ Vous aimez analyser les besoins avec les m√©tiers, challenger, identifier les sources de donn√©es dans les diff√©rents univers technologiques, industrialiser des algorithmes, concevoir et d√©velopper des Datalab ou des Datamart sur les plateformes ? Vous saurez relever les challenges propos√©s par les squads m√©tier !\n¬∑ Vous pr√©f√©rez travailler √† l‚Äôarchitecture et au d√©ploiement de nouvelles plateformes, √† la lev√©e de la dette technologique ou encore r√©aliser de la veille au service de notre trajectoire ? La squad Socles Data est faite pour vous !\n¬∑ Au-del√† des projets que vous g√©rerez, garant du bon fonctionnement de votre parc applicatif, vous attacherez une grande attention √† la mise en ≈ìuvre de solutions optimis√©es.\n¬∑ La rigueur, la communication, l‚Äôesprit d‚Äô√©quipe mais aussi la curiosit√© et la cr√©ativit√© font partie de vos soft skills ! ils vous permettront de r√©pondre aux enjeux de s√©curit√©, de qualit√©, de transmission de la connaissance et contribueront √† l‚Äôatteinte des objectifs de l‚ÄôIT et plus largement de LCL, au service de ses clients.\nüíª Voici les principales technologies utilis√©es au sein de la tribu, si certaines vous sont famili√®res, nous vous aiderons √† monter en comp√©tence sur d‚Äôautres !\nLangages utilis√©s : SQL, Python, Scala\nSGBD : Teradata et utilitaires (TPT, BTEQ, ‚Ä¶)\nStreaming : Kafka\nSearch : ElasticSearch, SolR\nEnvironnement : Unix\nSolutions Big Data : Hadoop Cloudera, DataIku, HDFS, Hive, Impala,\nDevops : GitLab, Jenkins, Nexus\nOutils de visualisation : MS BI (SSIS, SSAS, SSRS) Qlik Sens, BO\nMod√©lisation : MEGA\nOutils collaboratifs : GIT, Jira, Confluence, Teams\n‚ö°Si les nouveaux enjeux bancaires vous int√©ressent, que vous souhaitez int√©grer une √©quipe Agile au service des m√©tiers dans laquelle vous serez force de proposition et que vous aimez travailler dans un environnement motivant et dynamique, rejoignez-nous, cette offre est faite pour vous !\nüî• Les + de notre entreprise :\nAcc√®s au Plan d‚Äô√©pargne Groupe, int√©ressement et participation aux b√©n√©fices de l‚Äôentreprise + abondement\nPrix pr√©f√©rentiels bancaires et avantages CSE\nParcours √©volutif dans l‚Äôentreprise et/ou dans le Groupe CA.S.A\nT√©l√©travail (jusqu'√† 2 jours de t√©l√©travail par semaine)\nDe multiples commodit√©s sur le campus (restaurants d'entreprise, salle de sport, cr√®che, centre m√©dical, m√©diath√®que...)\nForfait et avantages pratiques ¬´ mobilit√© durable ¬ª pour les velotafeurs\nDes √©quipes aussi diversifi√©es que structur√©es dans une dynamique de transformation\nLCL s‚Äôengage en faveur de la diversit√© et nous encourageons tout(e) candidat(e) ayant l‚Äôexp√©rience requise √† postuler √† nos offres. Tous nos postes sont ouverts aux personnes en situation de handicap.\nNous avons encore de nombreuses raisons √† vous pr√©senter pour vous convaincre de nous rejoindre mais pour cela, il faudra postuler ici !\nShow more\nShow less",
        "details": {
            "JobDetail": [],
            "TypeContract": "",
            "Salary": "",
            "Level": "",
            "Experience": null
        },
        "title": "data engineer",
        "skills": {
            "ProgLanguage": [
                "Scala",
                "Python"
            ],
            "DataBase": [
                "Elasticsearch",
                "SQL"
            ],
            "BigData": [
                "Hadoop"
            ],
            "DevTools": [
                "Git",
                "Jenkins"
            ],
            "Collaboration": [
                "Confluence",
                "Teams",
                "JIRA"
            ],
            "Other": [
                "Big Data",
                "DevOps"
            ],
            "EnSoftSkils": [
                "Communication"
            ]
        }
    },
    {
        "source": "LinkedIn",
        "company": "Ramify",
        "location": "Paris",
        "link": "https://fr.linkedin.com/jobs/view/data-engineer-at-ramify-3896146641?position=32&pageNum=0&refId=3%2BsKCnzKBomYeuJjjsOexw%3D%3D&trackingId=e4XI0cdZ19g8lYZB0g9RxQ%3D%3D&trk=public_jobs_jserp-result_search-card",
        "description": "ABOUT\nRamify‚Äôs mission is to help people achieve financial freedom, no matter who they are and how much they have. We are revolutionizing the private wealth management industry by making smart and affordable financial products for everyone.\nNo more standardized solutions, hidden fees and complicated words, Ramify enables everyone to become a smart investor. The team combines elements of its research with technology to design customized investment portfolios composed of world-class financial products.\nThe team comprises around 15 talented individuals. Ramify is looking for talented people in all sectors, who want to have a huge impact, move fast and deliver.\nJOB DESCRIPTION\nThe Quantitative Investment Solutions (QIS) Team is dedicated to designing innovative investment portfolio models and developing cutting-edge investment features within our product suite. Moreover, the QIS Team is at the forefront of driving AI-based solutions for Ramify. This involves conceptualizing and implementing transformative AI solutions tailored to meet the diverse needs of various teams within Ramify.\nAs a Data Engineer on our QIS Team, you will play a pivotal role in shaping the future of investment strategies through data-driven insights and AI-based solutions. Collaborating closely with our talented team of quantitative researchers, and investment experts, your responsibilities will encompass architecting and implementing robust data pipelines. These pipelines will facilitate the seamless integration of diverse data sources, empowering Ramify teams to make informed decision-making.\nKey Responsibilities:\nDesign, build and launch data pipelines at scale to move data across Ramify platform with SQL technologies.\nDesign and implement processes and tools for data onboarding and quality, helping to deliver an industry best-practice solution for managing the data lifecycle.\nProduce stand-alone tools that can be used by other teams to automate data quality and discover faults.\nBuild analytical tools that provide insight into business metrics across Ramify.\nArchitect and lead the implementation of AI based solutions within Ramify\nPREFERRED EXPERIENCE\nWe're looking for people who:\nWant to make a difference. We are a small team effectively reshaping how people look at the industry. We need people who 'get it' and want to play an integral part in helping us accomplish this mission and are persistent in getting the job done.\nSkills we're looking for:\nMaster‚Äôs or upper-year undergraduate-level coursework in either Computer Science, Management Information Systems, Business Information Systems, Mathematics or Finance related field.\n2+ years of professional experience in data engineering.\n2+ years of experience with one or more coding languages such as Python (is a must), Java.\nExperience with data modeling and ETL design, implementation and maintenance.\nDemonstrable mastery of industry best practices in the data lifecycle, including data quality automation and tooling.\nExcellent written and verbal communication skills with ability to communicate complex designs and solutions to non-technical and highly technical audiences alike.\nGood attention to detail.\nStrong analytics and strategic thinking skills\nNice-to-haves :\nUnderstanding of ML/ Generative AI technologies and their applications.\nPossess a passion, curiosity, and energy for finance + investing. You understand the ins and outs of the wealth management, trading, and more importantly - know how to explain these concepts simply\nShow more\nShow less",
        "details": {
            "JobDetail": [],
            "TypeContract": "",
            "Salary": "",
            "Level": "",
            "Experience": null
        },
        "title": "data engineer",
        "skills": {
            "ProgLanguage": [
                "Java",
                "Python"
            ],
            "DataBase": [
                "SQL"
            ],
            "Collaboration": [
                "Teams"
            ],
            "Other": [
                "ML"
            ],
            "EnSoftSkils": [
                "Communication"
            ]
        }
    },
    {
        "source": "LinkedIn",
        "company": "Renault Digital",
        "location": "Boulogne-Billancourt, √éle-de-France, France",
        "link": "https://fr.linkedin.com/jobs/view/data-engineer-f-h-at-renault-digital-3911202728?position=33&pageNum=0&refId=3%2BsKCnzKBomYeuJjjsOexw%3D%3D&trackingId=0bxX79baJOSj%2BbQi4KG%2BzA%3D%3D&trk=public_jobs_jserp-result_search-card",
        "description": "Contexte :\nDans le cadre de son programme Industrie 4.0, Renault d√©veloppe depuis 2017 sa propre plateforme pour connecter et agr√©ger les donn√©es industrielles des 22 sites du Groupe et de plus de 2500 machines.\nFort de partenariats strat√©giques sign√©s avec Google Cloud (stack data full GCP), Renault Digital est √† la recherche d‚Äôun(e) Data Engineer au sein du P√¥le Architecture et Data pour mettre en place des cha√Ænes de traitement de donn√©es r√©pondant √† de nouveaux besoins m√©tiers.\nVous collaborerez au jour le jour avec les √©quipes m√©tiers ainsi qu‚Äôavec les autres fonctions du P√¥le Architecture & Data (Data Analysts et Scientists, architectes, ‚Ä¶), exploitant des t√©raoctets de donn√©es (√©v√©nements en mode streaming, traitements en batch et temps r√©els et les appels aux APIs) afin entre autres d‚Äôalimenter des mod√®les de machine learning (segmentation clients, d√©tection automatiquement des pannes des v√©hicules, ‚Ä¶).\nResponsabilit√©s principales :\nVous participez aux phases de framing, MVP et release des produits, services et APIs orient√©s data ;\nVous argumentez les choix d‚Äôarchitecture des projets et de la plateforme datalake sur GCP ;\nVous contribuez √† la valeur m√©tier des produits orient√©s Data s‚Äôappuyant sur le Datalake, en mettant en place des cha√Ænes bout en bout de traitement de la data, de l‚Äôingestion √† l‚Äôexposition d‚ÄôAPIs et √† la visualisation des donn√©es et des solutions ML/DS ;\nVous √™tes garant de la qualit√© des donn√©es transform√©es dans le Datalake, du bon fonctionnement des cha√Ænes de traitement et de l‚Äôoptimisation de l‚Äôutilisation des ressources des ressources cloud ;\nVous proposez des standards d‚Äôarchitecture et de d√©veloppement ;\nVous √™tes force de proposition, innovant(e) et bienveillant(e).\nEnvironement technique :\nSpark, Scala, Python, Java, Airflow, SQL, Google Cloud Platform (BigQuery, Cloud Storage, PubSub, Beam, Dataflow, Cloud ML, TensorFlow, Kubernetes), Git, Docker, JSON, Bash, Spotfire\nProfil recherch√© :\nVous avez minimum 5 ans d‚Äôexp√©rience en tant que Data Engineer ;\nVous disposez d‚Äôune exp√©rience en d√©veloppement Spark, Scala, Python et requ√™tage SQL sur des gros volumes de donn√©es ;\nVous avez une app√©tence pour la data : validation, transformation, analyse, valorisation ;\nVous poss√©dez une exp√©rience de d√©veloppement et orchestration de chaines ETL complexes via Airflow ou √©quivalent ;\nVous pratiquez la m√©thodologie agile (Agile Scrum et/ou Kanban) ;\nVous utilisez les services cloud (pr√©f√©rablement GCP) ;\nVous √™tes capable d‚Äô√©changer en anglais technique √©crit et oral.\nInformations compl√©mentaires :\nVotre poste sera bas√© √† Boulogne-Billancourt (France) en CDI (temps plein)\nVous b√©n√©ficiez de 2 √† 3 jours de t√©l√©travail par semaine\nShow more\nShow less",
        "details": {
            "JobDetail": [
                "Temps plein",
                "Full"
            ],
            "TypeContract": "CDI",
            "Salary": "",
            "Level": "",
            "Experience": "5 an(s)"
        },
        "title": "data engineer",
        "skills": {
            "ProgLanguage": [
                "Java",
                "Bash",
                "Scala",
                "Python"
            ],
            "DataBase": [
                "SQL"
            ],
            "BigData": [
                "Spark"
            ],
            "MachineLearning": [
                "TensorFlow"
            ],
            "DataSerialization": [
                "Json"
            ],
            "CloudComputing": [
                "GCP",
                "Google Cloud Platform"
            ],
            "DevTools": [
                "Git",
                "Docker"
            ],
            "DBMS": [
                "BigQuery"
            ],
            "Automation": [
                "Airflow",
                "Kubernetes"
            ],
            "Containers": [
                "Docker",
                "Kubernetes"
            ],
            "Other": [
                "Machine Learning",
                "Cloud",
                "ML"
            ]
        }
    },
    {
        "source": "LinkedIn",
        "company": "Inetum",
        "location": "St.-Ouen, √éle-de-France, France",
        "link": "https://fr.linkedin.com/jobs/view/data-engineer-h-f-at-inetum-3843966639?position=34&pageNum=0&refId=3%2BsKCnzKBomYeuJjjsOexw%3D%3D&trackingId=TdwMuSB3Y6fg6jshb%2BTZRg%3D%3D&trk=public_jobs_jserp-result_search-card",
        "description": "D√©tail de l'offre\nInformations g√©n√©rales\nEntit√© de rattachement\nInetum est un leader europ√©en des services num√©riques. Pour les entreprises, les acteurs publics et la soci√©t√© dans son ensemble, les 28 000 consultants et sp√©cialistes du groupe visent chaque jour l'impact digital des solutions qui contribuent √† la performance, √† l'innovation et au bien commun.\nPr√©sent dans 19 pays au plus pr√®s des territoires, et avec ses grands partenaires √©diteurs de logiciels, Inetum r√©pond aux enjeux de la transformation digitale avec proximit√© et flexibilit√©.\nPort√© par son ambition de croissance et d'industrialisation, Inetum a g√©n√©r√© en 2023 un chiffre d'affaires de 2,5 milliards d'‚Ç¨.\nPour r√©pondre √† un march√© en croissance continue depuis plus de 30ans, Inetum a fait le choix d√©lib√©r√© de se recentrer sur 4 m√©tiers afin de gagner en puissance et proposer des solutions sur mesure, adapt√©es aux besoins sp√©cifiques de ses clients le conseil (Inetum Consulting), la gestion des infrastructures et applications √† fa√ßon (Inetum Technologies), l'impl√©mentation de progiciels (Inetum Solutions) et sa propre activit√© d'√©diteur de logiciels (Inetum Software). Inetum a conclu des partenariats strat√©giques avec 4 grands √©diteurs mondiaux - Salesforce, ServiceNow, Microsoft et SAP et poursuit une strat√©gie d'acquisitions d√©di√©e afin d'entrer dans le top 5 europ√©en sur ces technologies et proposer la meilleure expertise √† ses clients.\nTous nos postes sont ouverts aux personnes en situation de handicap.\nDescription du poste\nM√©tier\nApplications Delivery - Software Development\nIntitul√© du poste\nData Engineer H/F\nContrat\nCDI\nDescription De La Mission\nLe p√¥le BFA de la branche Application Services du groupe INETUM, recherche plusieurs Data Engineers afin d'intervenir aupr√®s de clients grands comptes au sein des march√©s bancaires et de l'assurance.\nAu sein de l'√©quipe Data, en tant que Data Engineer, vous participez √† la r√©alisation de divers projets et vos missions sont\nApporter votre connaissance en Big Data permettant la manipulation des donn√©es\nConcevoir les plateformes permettant de traiter des volumes de donn√©es importants\nMettre en place des bases de donn√©es\nPr√©parer le pipeline de donn√©es pour que les donn√©es d√©ploy√©es soient s√©curis√©es et claires afin d'√™tre analys√©es et transform√©es.\nProfil\nDe formation ing√©nieure en informatique Bac + 5 informatique ou scientifique\nBonne communication orale et √©crite en fran√ßais et niveau d‚Äôanglais professionnel\nSavoir- √™tre Bon esprit d'analyse et de synth√®se, sens de l'organisation et de la qualit√©, force de proposition, rigueur, travail en √©quipe, adaptabilit√©.\nSi vous vous reconnaissez, n'h√©sitez pas √† postuler !\nLocalisation du poste\nLocalisation du poste\nFrance\nVille\nSaint-Ouen\nCrit√®res candidat\nNiveau d'√©tudes min. requis\nBac+5\nNiveau d'exp√©rience min. requis\nPlus de 2 ans\nComp√©tences\nSQL\nShow more\nShow less",
        "details": {
            "JobDetail": [],
            "TypeContract": "CDI",
            "Salary": "",
            "Level": "Bac+5",
            "Experience": "30 an(s)"
        },
        "title": "data engineer",
        "skills": {
            "DataBase": [
                "SQL"
            ],
            "Other": [
                "Big Data"
            ],
            "EnSoftSkils": [
                "Communication"
            ]
        }
    },
    {
        "source": "LinkedIn",
        "company": "Capgemini",
        "location": "Nantes, Pays de la Loire, France",
        "link": "https://fr.linkedin.com/jobs/view/data-engineer-bi-nantes-at-capgemini-3803963477?position=35&pageNum=0&refId=3%2BsKCnzKBomYeuJjjsOexw%3D%3D&trackingId=0Pfx7yf7BS4uAZp8IATuug%3D%3D&trk=public_jobs_jserp-result_search-card",
        "description": "Capgemini\nChoisir Capgemini, c'est choisir une entreprise o√π vous serez en mesure de fa√ßonner votre carri√®re selon vos aspirations, o√π vous serez soutenu et inspir√© par une communaut√© d‚Äôexperts dans le monde entier, o√π vous pourrez r√©√©crire votre futur. Rejoignez-nous pour red√©finir les limites de ce qui est possible, contribuer √† lib√©rer la valeur de la technologie pour les plus grandes organisations et participez √† la construction d‚Äôun monde plus durable et inclusif.\nVos missions :\nInt√©gr√©(e) au sein d‚Äôune √©quipe projet BI, Big Data ou Data Gouvernance pour des clients intervenant dans des secteurs d'activit√©s divers, vous serez notamment en charge des missions suivantes :\nMener les analyses fonctionnelles destin√©es √† traduire les besoins du client,\nMener les travaux de conception et de mod√©lisation,\nDiriger le d√©veloppement de la solution / des traitements d'alimentation du DataWareHouse,\nOrganiser et pr√©parer les travaux de recette utilisateurs,\nMettre en place les processus d'industrialisation et mener cette derni√®re.\nVotre profil :\nDipl√¥me d‚Äôing√©nieur ou √©quivalent universitaire\nMinimum 3 ans d'exp√©rience\nAnglais courant\nComp√©tences en BI sur SAP BI (Hana, BW, BODS, BI 4), Microsoft BI (SQL Server, SSIS, SSAS, SSRS), Oracle (ODI, OBIEE), Teradata, Informatica (Powercenter), IBM (Datastage, Cognos, TM1), Talend, AB Initio\nMa√Ætrise d'un ou de plusieurs outils de Dataviz : Microsoft Power BI, Tableau, Qlikview\nConnaissances en Big Data (Ecosyst√®me Hadoop (HIVE, PIG, Mahout‚Ä¶), Cloudera, Pivotal, Spark, HNX) ou en analytics (R, SAS, IBM SPSS)\n3 raisons de nous rejoindre :\nQualit√© de vie au travail : accord de t√©l√©travail en France et √† l‚Äôinternational, accord sur l‚Äô√©galit√©\nprofessionnelle, la parentalit√©, l‚Äô√©quilibre des temps et la mobilit√© durable.\nApprentissage en continu : certifications et formations en libre acc√®s, accompagnement sur mesure avec votre carreer manager, parcours d‚Äôint√©gration sur 9 mois.\nAvantages groupe & CSE : plan actionnariat, activit√©s √† tarifs pr√©f√©rentiels, remboursement partiel\nvacances, remboursement de votre abonnement sportif ou culturel.\nNos engagements et priorit√©s :\nLe groupe Capgemini encourage une culture inclusive dans un cadre multiculturel et handi-accueillant. En nous rejoignant, vous int√©grez un collectif qui valorise la diversit√©, d√©veloppe le potentiel de ses talents, s‚Äôengage dans des initiatives solidaires avec ses partenaires, et se mobilise pour r√©duire son impact environnemental sur tous ses sites et aupr√®s de ses clients.\nCapgemini\nCapgemini est un leader mondial, responsable et multiculturel, regroupant pr√®s de 350 000 personnes dans plus de 50 pays. Fort de 55 ans d‚Äôexp√©rience, nous sommes un partenaire strat√©gique des entreprises pour la transformation de leurs activit√©s en tirant profit de toute la puissance de la technologie et des innovations dans les domaines en perp√©tuelle √©volution tels que le cloud, la data, l‚ÄôIntelligence Artificielle, la connectivit√©, les logiciels, l‚Äôing√©nierie digitale ou les\nplateformes.\nGet The Future You Want* | www.capgemini.com/fr-fr\n*Capgemini, le futur que vous voulez\nShow more\nShow less",
        "details": {
            "JobDetail": [],
            "TypeContract": "",
            "Salary": "",
            "Level": "",
            "Experience": "3 an(s)"
        },
        "title": "data engineer",
        "skills": {
            "ProgLanguage": [
                "R"
            ],
            "DataBase": [
                "SQL"
            ],
            "DataAnalytics": [
                "R"
            ],
            "BigData": [
                "Hadoop",
                "Spark"
            ],
            "DataVisualisation": [
                "Power BI",
                "Tableau"
            ],
            "DBMS": [
                "SQL Server"
            ],
            "Other": [
                "Cloud",
                "Big Data"
            ]
        }
    },
    {
        "source": "LinkedIn",
        "company": "Thales",
        "location": "Ollioules, Provence-Alpes-C√¥te d'Azur, France",
        "link": "https://fr.linkedin.com/jobs/view/data-engineer-at-thales-3902424527?position=36&pageNum=0&refId=3%2BsKCnzKBomYeuJjjsOexw%3D%3D&trackingId=Tln2wh6ZyG6g2nuwAtwA0A%3D%3D&trk=public_jobs_jserp-result_search-card",
        "description": "QUI SOMMES-NOUS ?\nThales est un leader mondial des hautes technologies comptant plus de 81 000 collaborateurs pr√©sents sur tous les continents. Le Groupe investit dans les innovations du num√©rique et de la ¬´ deep tech ¬ª ‚Äì big data, intelligence artificielle, connectivit√©, cybers√©curit√© et quantique ‚Äì pour construire un avenir de confiance, essentiel au d√©veloppement de nos soci√©t√©s, en pla√ßant l‚Äôhumain au c≈ìur des d√©cisions.\nThales propose des solutions, services et produits qui aident ses clients ‚Äì entreprises, organisations, Etats ‚Äì dans cinq grands march√©s vitaux pour le fonctionnement de nos soci√©t√©s : identit√© et s√©curit√© num√©riques, d√©fense, a√©ronautique, espace, et transport.\nQUI ETES-VOUS ?\nDipl√¥m√© d‚Äôun Bac+5 en √©cole d‚Äôing√©nieur ou √©quivalent universitaire avec une sp√©cialisation en informatique, vous avez a\nu moins 3 ans d'exp√©rience\ndans les technologies Big Data.\nPassionn√© par le\nsecteur de la D√©fense et du Naval.\nCE QUE NOUS POUVONS ACCOMPLIR ENSEMBLE :\nEn tant que\nData Engineer,\nvous jouerez un r√¥le cl√© dans la conception, le d√©veloppement et la maintenance de notre infrastructure de donn√©es, ainsi que dans la transformation et la gestion des flux de donn√©es.\nVOS MISSIONS :\n‚Ä¢ Concevoir, d√©velopper et d√©ployer des solutions Big Data en utilisant les technologies\nHadoop, Spark, Scala\n.\n‚Ä¢ Mettre en place des pipelines de donn√©es performants pour l'ingestion, le traitement et le stockage des donn√©es massives.\n‚Ä¢ Collaborer √©troitement avec les √©quipes m√©tier pour comprendre leurs besoins en mati√®re d'analyse de donn√©es et proposer des solutions adapt√©es.\n‚Ä¢ Optimiser les performances des clusters Hadoop pour garantir une exploitation efficace des donn√©es.\n‚Ä¢ Assurer la qualit√© et la fiabilit√© des donn√©es trait√©es, en mettant en place des processus de validation et de nettoyage.\n‚Ä¢ Identifier et r√©soudre les probl√®mes li√©s √† l'infrastructure Big Data et proposer des am√©liorations.\nInnovation, passion, ambition : rejoignez Thales et cr√©ez le monde de demain, d√®s aujourd‚Äôhui.\nShow more\nShow less",
        "details": {
            "JobDetail": [],
            "TypeContract": "",
            "Salary": "",
            "Level": "Bac+5",
            "Experience": "3 an(s)"
        },
        "title": "data engineer",
        "skills": {
            "ProgLanguage": [
                "Scala"
            ],
            "BigData": [
                "Hadoop",
                "Spark"
            ],
            "Other": [
                "Big Data"
            ]
        }
    },
    {
        "source": "LinkedIn",
        "company": "Beelix",
        "location": "Antibes, Provence-Alpes-C√¥te d'Azur, France",
        "link": "https://fr.linkedin.com/jobs/view/data-engineer-h-f-at-beelix-3838611420?position=37&pageNum=0&refId=3%2BsKCnzKBomYeuJjjsOexw%3D%3D&trackingId=broPHyuEihx3QbpwB5jySg%3D%3D&trk=public_jobs_jserp-result_search-card",
        "description": "Qui sommes-nous ?\nDepuis 2016, nous accompagnons nos clients sur des probl√©matiques de Product Management, Data et Design Thinking. Beelix contribue √† fa√ßonner le monde de demain en participant aux grandes avanc√©es des secteurs suivants :\nüöóAutomobile\n‚ö°Energie\nüì°M√©dias & T√©l√©coms\nüëóLuxe & Retail\nüí∂ Banque, Finance & Assurance\n‚úàÔ∏èD√©fense\nAujourd‚Äôhui, Beelix compte plus de 200 collaborateurs motiv√©s et dynamiques. Lab√©lis√©e Great Place To work en 2023, Beelix est aussi une entreprise engag√©e o√π il fait bon vivre.\nDans le cadre de notre d√©veloppement, nous recherchons un Data Engineer (H/F) pour l'un de nos clients.\nQuelles missions au quotidien ?\n√ätre le leader de la brique Datalakehouse\nD√©velopper les scripts de transformations de donn√©es et les pipelines d‚Äôalimentation\nProposer des √©volutions architecturales ou de fonctionnalit√©s pour am√©liorer le socle technique\n√ätre le back-up du leader technique sur la partie reporting (Power BI)\nOrientation satisfaction client et r√©sultat final forte mais √©galement sensibilit√© au ¬´ comment ¬ª\nInnovation et proposition de nouvelles pratiques pour am√©liorer l‚Äôenvironnement et les conditions de travail des √©quipes\nA propos de vous ?\n5 + ann√©es d'exp√©rience en tant que Data Engineer\nMa√Ætrise des technologies suivantes : Microsoft Azure, Microsoft Azure Synapse Analytics (Spark / Python / Pipeline / Serverless), fichiers parquet / delta, Microsoft Power BI, Microsoft SQL Server, langage SQL, Datawarehousing / Mod√©lisation de donn√©es\nAnalyses et export de donn√©es\nConnaissance de l‚Äôensemble du processus depuis la collecte jusqu‚Äô√† la mise √† disposition des donn√©es en ayant comme point fort la maitrise de sa transformation et mise en forme\nVous avez un bon niveau d‚Äôanglais\nLocalisation : Biot et/ou Carros\nShow more\nShow less",
        "details": {
            "JobDetail": [],
            "TypeContract": "",
            "Salary": "",
            "Level": "",
            "Experience": null
        },
        "title": "data engineer",
        "skills": {
            "ProgLanguage": [
                "Python"
            ],
            "DataBase": [
                "SQL"
            ],
            "BigData": [
                "Spark"
            ],
            "DataVisualisation": [
                "Power BI"
            ],
            "CloudComputing": [
                "Azure"
            ],
            "DBMS": [
                "SQL Server"
            ]
        }
    },
    {
        "source": "LinkedIn",
        "company": "Digital Waffle",
        "location": "Paris, √éle-de-France, France",
        "link": "https://fr.linkedin.com/jobs/view/data-engineer-at-digital-waffle-3913824888?position=38&pageNum=0&refId=3%2BsKCnzKBomYeuJjjsOexw%3D%3D&trackingId=0AvzzJrWcc2DQ043UYCc1A%3D%3D&trk=public_jobs_jserp-result_search-card",
        "description": "Digital Waffle is proud to have partnered with an innovative tech startup in Paris, who are looking for a talented Data Engineer to join their growing team!\nThey are made up of a powerhouse of experts, combining\ndata engineers, business process gurus, and Project managers\nwho leverage the most advanced solutions available; utilising process mining, automation tools, and smart execution systems.\nLooking for an experienced Data Engineer (3-5 years)\nWhat You'll Do:\nThis is a full-time,\nhybrid role (Paris-based)\nwhere you'll wear many hats: data exploration, system integration, data prep, data modeling, and implementing data solutions.\nExperience:\nExpertise in data engineering, data modeling, and ETL (Extract, Transform, Load) processes\nData warehousing and data analytics skills\nExperience handling large, complex datasets\nProficiency in SQL and programming languages like Python or Java\nStellar problem-solving and analytical skills\nTop-notch communication and collaboration abilities\nBachelor's or Master's in Computer Science, Information Systems, or a similar field (a plus for process mining or intelligent process automation experience)\nIf you are an experienced and driven Data Engineer, please apply here!\nShow more\nShow less",
        "details": {
            "JobDetail": [
                "Full"
            ],
            "TypeContract": "",
            "Salary": "",
            "Level": "",
            "Experience": null
        },
        "title": "data engineer",
        "skills": {
            "ProgLanguage": [
                "Java",
                "Python"
            ],
            "DataBase": [
                "SQL"
            ],
            "EnSoftSkils": [
                "Communication",
                "Collaboration"
            ]
        }
    },
    {
        "source": "LinkedIn",
        "company": "Ippon Technologies",
        "location": "Nantes",
        "link": "https://fr.linkedin.com/jobs/view/data-engineer-h-f-at-ippon-technologies-3902436649?position=39&pageNum=0&refId=3%2BsKCnzKBomYeuJjjsOexw%3D%3D&trackingId=%2BfCnAFVBGALLgH%2BE4pEmKQ%3D%3D&trk=public_jobs_jserp-result_search-card",
        "description": "Envie de rejoindre la communaut√© DATA la plus dynamique de France ?\nNotre sp√©cialit√© est de construire des data platform dans le Cloud public avec les meilleurs technos du moment : Snowflake, Databricks, Matillion, DBT.\nMembre de la Practice Data, le/la futur(e) Data Engineer sera int√©gr√©(e) √† nos √©quipes de conseil et sera suivi(e) par un(e) mentor qui l‚Äôaidera √† monter en comp√©tences.\nVotre champs d‚Äôexpertise :\nIntervenir sur les data platforms de nos clients pour d√©velopper de nouveaux pipelines de donn√©es (ingestion, traitement, exposition).\nTravailler en collaboration avec les m√©tiers et les data scientists pour leur fournir un support √† l‚Äôindustrialisation de leurs travaux (tests, int√©gration continue, scalabilit√© des mod√®les, craftsmanship etc‚Ä¶)\nD√©ployer des infrastructures cloud full\ninfra-as-code\n(Terraform, CloudFormation).\nParticiper aux √©v√®nements internes √† la communaut√© data (BBL, webinar, datap√©ro interne, meetup, blog, dojos) et externes (Salon du Big Data, GCP Summit, Spark Summit, AWS Summit, Devoxx, workshop partenaire, meetups).\nCapitaliser sur les missions et les diff√©rents √©v√®nements de la communaut√© au travers d‚Äôarticles de blogs, REX, BBL interne.\nVos connaissances :\nUn framework de calcul distribu√© tel que Spark, Storm, Flink.\nUn ou plusieurs langages de programmation (Python, Scala, Java...)\nDiff√©rents syst√®mes de stockage de donn√©es (SQL ou NoSQL) et bien s√ªr le langage SQL.\nLa connaissance de Snowflake est bienvenue ;-)\nUn framework de streaming de donn√©es tel que Kafka ou Amazon Kinesis.\nUne exp√©rience sur les technologies Cloud : AWS, GCP, Azure\nLe delivery et les projets en production faisant partie de notre ADN, vous √™tes capable de livrer du code de qualit√© dans des environnements agiles.\nDe plus en plus de nos projets se font en remote avec des clients du monde entier, il devient n√©cessaire d‚Äô√™tre √† l‚Äôaise en Anglais.\nIppon technologies c‚Äôest aussi :\nüëç B√©n√©ficier d'un suivi de proximit√© r√©alis√© par votre manager technique : points r√©guliers pour votre suivi en mission, votre formation et votre √©volution de carri√®re\n‚úåÔ∏è Rejoindre une entreprise o√π les valeurs du sport sont nos leitmotiv : d√©passement de soi, travail en √©quipe, bienveillance.\nüóíÔ∏è Apprendre via notre programme de formation BlackBelt : https://bit.ly/3ByqcIL\nüòÅ Travailler en pair programming ou avec un.e mentor pour gravir les √©chelons !\nüí™ Pouvoir participer √† une aventure humaine au sein de notre Fondation Ippon pour r√©duire la fracture num√©rique dans le monde !\nü§ù Participer √† nos ap√©ros et divers √©v√®nements internes pour consolider la coh√©sion d‚Äô√©quipe\nEt apr√®s ?\nEt oui alors ? Que se passe-t-il une fois que vous √™tes convaincu d‚Äôavoir lu l‚Äôoffre d‚Äôemploi qui vous correspond bien ?\nNous vous proposons de prendre contact et de nous rencontrer !\nLes Next Steps :\n1 call RH\n1 √©change RH\n1 √©change Technique\nSi le match est bon des deux c√¥t√©s : Hadjim√© ! Vous vous lancerez sur le tatami Ippon !\nShow more\nShow less",
        "details": {
            "JobDetail": [
                "Remote",
                "Full"
            ],
            "TypeContract": "",
            "Salary": "",
            "Level": "",
            "Experience": null
        },
        "title": "data engineer",
        "skills": {
            "ProgLanguage": [
                "Java",
                "Scala",
                "Python"
            ],
            "DataBase": [
                "SQL",
                "NoSQL"
            ],
            "BigData": [
                "Databricks",
                "Flink",
                "Spark"
            ],
            "CloudComputing": [
                "GCP",
                "AWS",
                "Azure"
            ],
            "DBMS": [
                "Snowflake"
            ],
            "InfrastructureAsCode": [
                "CloudFormation",
                "Terraform"
            ],
            "Other": [
                "Cloud",
                "Big Data"
            ],
            "EnSoftSkils": [
                "Collaboration"
            ]
        }
    },
    {
        "source": "LinkedIn",
        "company": "Shippeo",
        "location": "Paris",
        "link": "https://fr.linkedin.com/jobs/view/data-engineer-at-shippeo-3908268236?position=40&pageNum=0&refId=3%2BsKCnzKBomYeuJjjsOexw%3D%3D&trackingId=JjADy0kCP97kvy2bKYZWgw%3D%3D&trk=public_jobs_jserp-result_search-card",
        "description": "Founded in 2014, Shippeo is a French based SaaS company providing supply chain visibility. Shippeo has grown from 70 to 220 employees during the last two years and is continuing to rapidly scale after an additional $40M fundraising round in October 2022.\nShippeo is an exceptionally diverse company with colleagues from 27 different nationalities and speaking 29 languages. With offices throughout Europe, North America and recently Asia, Shippeo provides global coverage to all of our clients.\nOur product is composed of a mission critical SaaS web platform (API everywhere), with high traffic inbound/outbound integrations.\nOur mission is to anticipate problems and proactively alert end-customers so they can efficiently manage exceptions. We achieve this by collecting and matching millions of theoretical and real data from different stakeholders.\nThe Data Intelligence Tribe is responsible for leveraging Shippeo‚Äôs data from our large shipper and carrier base, to build data products that help our users (shippers and carriers alike) and ML models to provide predictive insights. This tribe‚Äôs typical responsibilities are to:\nget accurately alerted in advance of any potential delays on their multimodal flows or anomalies so that they can proactively anticipate any resulting disruptions\nextract the data they need, get direct access to it or analyze it directly on the platform to gain actionable insights that can help them increase their operational performance and the quality and compliance of their tracking\nprovide best-in-class data quality by implementing advanced cleansing & enhancement rules\nAs a Data Engineer at Shippeo, your objective is to ensure that data is available and exploitable by our Data Scientists and Analysts on our different data platforms. You will contribute to the construction and maintenance of Shippeo‚Äôs modern data stack that‚Äôs composed of different technology blocks:\nData Acquisition (Kafka, KafkaConnect, RabbitMQ),\nBatch data transformation (Airflow, DBT),\nCloud Data Warehousing (Snowflake, BigQuery),\nStream/event data processing (Python, docker, Kubernetes) and all the underlying infrastructure that support these use cases.\nQualifications\nRequired:\nYou have a degree (MSc or equivalent) in Computer Science.\n3+ years of experience as a Data Engineer.\nExperience building, maintaining, testing and optimizing data pipelines and architectures\nProgramming skills in Python and experience with asynchronous event processing (asyncio).\nAdvanced working knowledge of SQL, experience working with relational databases and familiarity with a variety of databases.\nWorking knowledge of message queuing and stream processing.\nKnowledge of Docker and Kubernetes.\nKnowledge of a cloud platform (preferably GCP).\nExperience working with workflow management systems such as Airflow.\nDesired:\nExperience with cloud based data warehouse solutions (BigQuery, Snowflake).\nExperience with Kafka and KafkaConnect (Debezium).\nExperience with Infrastructure as code (Terraform/Terragrunt).\nExperience building and evolving CI/CD pipelines with Github Actions.\nMonitoring and alerting on Grafana / Prometheus.\nExperience working on Apache Nifi.\nInformations suppl√©mentaires\nWe are looking for talents who share our values:\nüöÄ Ambition\nüíô Care\nüéØ Deliver\nü§ù Collaboration\nFind out more about our values in\nOur Culture Book\nIf you identify with our values and enjoy working in a fast-paced and international environment, Shippeo is just the place for you!\nWe are committed to fostering diversity and inclusion within our workplace as we value the unique perspectives and experiences that individuals from all backgrounds bring to our team. We are dedicated to providing equal employment opportunities to all candidates, regardless of their background or abilities, and our commitment to inclusion is reflected in our policies, practices, and workplace culture.\nWe understand that candidates may have unique needs or questions related to disability inclusion. To facilitate this, you can reach our dedicated Disability Advisor at\ninclusion@shippeo.com\nwith any inquiries or requests for accommodations during the application process.\nShow more\nShow less",
        "details": {
            "JobDetail": [],
            "TypeContract": "",
            "Salary": "",
            "Level": "",
            "Experience": null
        },
        "title": "data engineer",
        "skills": {
            "ProgLanguage": [
                "Python"
            ],
            "DataBase": [
                "SQL"
            ],
            "CloudComputing": [
                "GCP"
            ],
            "DevTools": [
                "Docker"
            ],
            "DBMS": [
                "BigQuery",
                "Snowflake"
            ],
            "Automation": [
                "Airflow",
                "Kubernetes"
            ],
            "InfrastructureAsCode": [
                "Terraform"
            ],
            "Containers": [
                "Docker",
                "Kubernetes"
            ],
            "Other": [
                "Cloud",
                "ML",
                "CI/CD"
            ],
            "EnSoftSkils": [
                "Collaboration"
            ]
        }
    },
    {
        "source": "LinkedIn",
        "company": "United Robotics Group",
        "location": "Paris, √éle-de-France, France",
        "link": "https://fr.linkedin.com/jobs/view/data-engineer-f-h-at-united-robotics-group-3891680780?position=41&pageNum=0&refId=3%2BsKCnzKBomYeuJjjsOexw%3D%3D&trackingId=FazbdV6EK0j0iUsCsme7kQ%3D%3D&trk=public_jobs_jserp-result_search-card",
        "description": "Bienvenue chez\nAldebaran\n, leader europ√©en de la robotique\nau sein du groupe\nUnited Robotics Group\n.\nNous concevons et industrialisons des robots innovants avec une vision soci√©tale ambitieuse pour fa√ßonner un monde plus humain. Depuis 2005, nous sommes √† l'avant-garde de l'interaction homme-robot avec des produits embl√©matiques tels que NAO et Pepper.\nNotre dernier-n√©,\nPlato\n,\nincarne notre engagement envers la technologie de pointe et la s√©curit√©,\nfabriqu√© en France avec des composants europ√©ens.\nRejoignez nos √©quipes multiculturelles et dynamiques pour √™tre au c≈ìur de la r√©volution de la robotique.\nSi vous √™tes passionn√©.e par la robotique et l'intelligence artificielle, et que vous souhaitez contribuer √† fa√ßonner l'avenir, nous vous offrons une exp√©rience enrichissante et stimulante.\nEn tant que membre de notre √©quipe, vous b√©n√©ficierez d'une culture d'entreprise ax√©e sur le sens de ce que nous faisons et valorisant la responsabilit√© sociale et environnementale.\nChez Aldebaran, nous valorisons l'innovation, la diversit√© et l'√©galit√© et encourageons chacun.e √† √™tre ouvert.e, authentique, courageux.se, responsable et engag√©.e.\nFinalit√© du poste\nAu sein de l'√©quipe Cloud-Online Services, le Data engineer int√©grera l'√©quipe Data, responsable du d√©veloppement des produits destin√©s √† la collecte, aux process et √† l'exploitation des donn√©es de nos robots.\nIl aura pour r√¥le de d√©finir et d'impl√©menter des services data, sur une infrastructure Cloud AWS, supportant des services en ligne qui g√®rent les robots du groupe.\nMissions principales\nLe Data engineer aura pour responsabilit√©s de :\n√©valuer les choix d'architecture et de solutions techniques lors de la mise en place de PoC,\nconcevoir et d√©velopper des services Data en respectant la sp√©cification fonctionnelle et la m√©thodologie agile,\nagr√©ger et stocker de grandes quantit√©s de donn√©es,\nmettre en place des solutions de data processing,\nint√©grer/d√©velopper des outils de visualisation de donn√©es et analyser les KPI,\nd√©velopper, tester, s√©lectionner et mettre en production des algorithmes qui permettent de r√©pondre aux besoins,\nr√©aliser des analyses de donn√©es,\nmettre en place des tests de charge et fonctionnels pour les solutions Data,\ninvestiguer et corriger les bugs remont√©s par les utilisateurs,\ncontribuer √† la mise en place de l'infrastructure et outil de d√©ploiement (CI/CD)\nRejoignez-nous pour faire partie d'une aventure passionnante o√π Pepper, NAO, Plato et leurs futurs successeurs attendent votre contribution pour repousser les limites de la technologie robotique !\nRequirements\nPour la bonne ex√©cution des missions confi√©es, vous t√©moignez d'au moins 6 ans d'exp√©rience en tant que d√©veloppeur sur des projets data en Cloud en Python et Spark et avec comme Cloud provider AWS.\nComp√©tences demand√©es :\nBonne compr√©hension des technologies d'infrastructure et de d√©ploiement,\nComp√©tences techniques sur les services AWS : IOT core , Glue, lambda, Kinesis, S3, RDS,\nBonne compr√©hension technique dans la mise en place et l'automatisation de tests de charge et fonctionnels,\nBonne maitrise d'outils BI ou de dashboarding (POWER BI, TABLEAU, QUICKSIGHT)\nBonne connaissance et une exp√©rience pratique de Scrum\\Scrumban et des m√©thodes agiles,\nUne certification AWS sera appr√©ci√©e,\nUn niveau de fran√ßais et d'anglais courant est indispensable,\nDes exp√©riences dans des environnements fortement internationaux sont un plus\nBenefits\nNos principaux avantages :\nUne culture du bien-√™tre en entreprise qui a fait ses preuves (budget c√©l√©bration et moments de convivialit√© par √©quipes et directions, restauration collective de qualit√©, environnement de travail agr√©able)\nUn engagement fort en mati√®re de responsabilit√© sociale et environnementale (promotion de l'√©galit√© professionnelle, performance de notre plan diversit√© et inclusion, r√©f√©rent handicap, fresque du num√©rique)\nUne culture du t√©l√©travail encadr√©e de mani√®re appropri√©e !\nTous nos postes sont ouverts aux personnes en situation de handicap.\nShow more\nShow less",
        "details": {
            "JobDetail": [],
            "TypeContract": "",
            "Salary": "",
            "Level": "",
            "Experience": "6 an(s)"
        },
        "title": "data engineer",
        "skills": {
            "ProgLanguage": [
                "Python"
            ],
            "BigData": [
                "Spark"
            ],
            "DataVisualisation": [
                "Power BI",
                "Tableau"
            ],
            "CloudComputing": [
                "AWS"
            ],
            "Other": [
                "Cloud",
                "CI/CD"
            ]
        }
    },
    {
        "source": "LinkedIn",
        "company": "Neosoft",
        "location": "Lille, Hauts-de-France, France",
        "link": "https://fr.linkedin.com/jobs/view/data-engineer-h-f-at-neosoft-3877878521?position=42&pageNum=0&refId=3%2BsKCnzKBomYeuJjjsOexw%3D%3D&trackingId=EeSkZArOsu8330eBfIJXDw%3D%3D&trk=public_jobs_jserp-result_search-card",
        "description": "Tous nos postes sont ouverts au t√©l√©travail\nGroupe ind√©pendant de conseil en transformation digitale de pr√®s de 1800 collaborateurs, N√©osoft s‚Äôest construit, depuis 2005, sur un mod√®le qui place l‚Äôexcellence, le d√©passement de soi et la RSE au c≈ìur de sa strat√©gie.\nEn nous rejoignant, vous int√©grez des communaut√©s d‚Äôexperts et de talents qui vous permettent de d√©velopper vos comp√©tences et d‚Äôoffrir √† nos clients le meilleur accompagnement possible.\nNotre savoir-faire s‚Äôarticule autour de nos 6 domaines d‚Äôexpertise :\nConseil & Agilit√©\nCybers√©curit√©\nData\nDevOps\nInfrastructures & Cloud\nSoftware Engineering\nNous recherchons pour int√©grer notre\nagence lilloise\nun(e)\nData Engineer confirm√©(e)\n.\nNous aimerions vous voir rayonner au sein de notre communaut√© DATA (+100 collaborateurs) anim√©e par Nicolas Huche, son practice leader et Thibaud Blanchard son Technical Officer. Vous aiderez les clients √† consolider un patrimoine Data responsable.\nüéØ\nVos missions :\nApr√®s une p√©riode d‚Äôint√©gration, en tant que\nData Engineer\n, voici √† quoi ressembleront vos activit√©s dans des contextes clients Retail ou Banque / Assurance / Finance :\nAnalyser et s'approprier les cas d'usages\nAnalyser et valoriser les donn√©es du patrimoine\nMettre en place des flux de transformation de donn√©es\nR√©aliser les tests permettant de s'assurer la qualit√© du delivery\nContinuer la mise au point de frameworks data\nCr√©er et d√©velopper des modules de d√©ploiement des solutions\nAssurer l'industrialisation de moteurs bas√©s sur l'IA\nAssurer le niveau de performance des pipelines\nImpl√©menter les outils de monitoring du socles de donn√©es\nüìù\nVotre profil :\nNous vous imaginons avec au moins 4 ans d‚Äôexp√©riences sur des projets autour de la\nData\n, une ma√Ætrise des\nbases de donn√©es (SQL)\n, des outils de transformation de la donn√©e\n(Talend, BigQuery, Airflow)\n, et un socle de comp√©tences solides autours des langages\nPython, Spark, Scala, Hadoop, Java.\nüëâ\nVotre carri√®re chez N√©osoft\nDepuis sa cr√©ation, N√©osoft place ses collaborateurs au c≈ìur de sa strat√©gie. Notre culture pourrait se r√©sumer en un mot : le collectif.\nNos communaut√©s d‚Äôexperts vous donnent la possibilit√© d‚Äôapprendre, mais aussi de transmettre et de partager vos savoirs pour faire progresser les autres.\nNous veillons √† ce que chacun b√©n√©ficie d‚Äôun accompagnement de proximit√© et d‚Äôun suivi de carri√®re personnalis√© aupr√®s de votre manager d√©di√© :\n1 bilan d‚Äôactivit√© trimestriel pour suivre le d√©veloppement de vos comp√©tences\n1 entretien d‚Äô√©valuation qui a lieu chaque ann√©e pour √©valuer votre performance et d√©terminer vos nouveaux objectifs\n1 entretien annuel aupr√®s de votre RH dans le but de cartographier vos nouvelles comp√©tences pour √©changer sur vos projets professionnels et souhaits de formations\nüëâ\nVos avantages\nFormations et d√©veloppement de l‚Äôexpertise :\nVous disposez de temps allou√© et r√©mun√©r√© en contribuant au d√©veloppement de votre expertise technique et de celle du groupe (Participations √† des Tech days, animation d‚Äôune conf√©rence √† l‚Äôinterne ou √† l‚Äôexterne, r√©daction d‚Äôarticles, rencontres avec nos candidats en processus de recrutement‚Ä¶)\nUn abonnement illimit√© LinkedIn Learning offert\nBien-√™tre au travail :\nUn accord de t√©l√©travail flexible jusqu‚Äô√† 100% de t√©l√©travail et personnalisable\nUn partenariat avec Gymlib qui favorise le sport en entreprise\nDes initiatives locales (afterworks, d√©fis sportifs, team buildings, ‚Ä¶)\nEt bien plus encore :\nParce que les meilleurs cooptent les meilleurs, une politique de cooptation attractive r√©mun√©r√©e d√®s l‚Äôarriv√©e du collaborateur\nEn plus de votre salaire : participation, compte √©pargne temps, actionnariat...\nüëâ\nVotre parcours candidat\nNotre processus de recrutement se compose de deux √©tapes cl√©s :\nUn entretien de recrutement RH avec un Talent Acquisition Sp√©cialiste pour dresser un bilan de votre parcours professionnel et identifier les trajectoires de carri√®re possibles au sein de notre groupe\nUn entretien d‚Äô√©valuation technique pour r√©aliser un diagnostic de vos comp√©tences techniques et identifier les comp√©tences sur lesquels poursuivre votre √©volution\nVous aurez √©galement la possibilit√© de rencontrer pour compl√©ter votre processus un acteur de notre p√¥le Business ou un pair de votre m√©tier pour √©changer sur son exp√©rience collaborateur.\nNous avons h√¢te de vous rencontrer !\nA bient√¥t,\nL‚Äô√©quipe N√©osoft üñê\nShow more\nShow less",
        "details": {
            "JobDetail": [
                "Confirm√©"
            ],
            "TypeContract": "",
            "Salary": "Salaire",
            "Level": "",
            "Experience": "4 an(s)"
        },
        "title": "data engineer",
        "skills": {
            "ProgLanguage": [
                "Java",
                "Scala",
                "Python"
            ],
            "DataBase": [
                "SQL"
            ],
            "BigData": [
                "Hadoop",
                "Spark"
            ],
            "DBMS": [
                "BigQuery"
            ],
            "Automation": [
                "Airflow"
            ],
            "Other": [
                "Cloud",
                "DevOps"
            ]
        }
    },
    {
        "source": "LinkedIn",
        "company": "fifty-five",
        "location": "Paris, √éle-de-France, France",
        "link": "https://fr.linkedin.com/jobs/view/data-cloud-engineer-h-f-at-fifty-five-3910028674?position=43&pageNum=0&refId=3%2BsKCnzKBomYeuJjjsOexw%3D%3D&trackingId=%2BsCqFzOn7VuceeF9BVnI4w%3D%3D&trk=public_jobs_jserp-result_search-card",
        "description": "Data & Cloud Engineer\nfifty-five est une data-company d'un genre nouveau qui aide les marques √† exploiter les donn√©es pour am√©liorer le marketing, les m√©dias et l'exp√©rience client gr√¢ce √† une combinaison de services de conseil et de technologie sp√©cialis√©s.\nEn tant que pilier data et marketing du Brandtech Group, nous offrons des services qui combinent le conseil en strat√©gie, les services de cloud, le conseil en m√©dia et l'exp√©rience client.\nfifty-five, c'est plus de 400 experts du num√©rique. Des digital consultants, des sp√©cialistes du tracking et du m√©dia, des ing√©nieurs et des data scientists, travaillent tous en √©troite collaboration pour fournir des conseils marketing de haut niveau et une assistance technique aux marques, dans tout type d'industrie, partout dans le monde.\nPartenaire des annonceurs de la collecte √† l'activation et l'exploitation des donn√©es, nous aidons les organisations √† devenir de v√©ritables entit√©s omnicanales ma√Ætrisant l'efficacit√© de leur √©cosyst√®me digital et ses synergies avec le monde physique.\nBas√© √† Paris, nous op√©rons sur 3 fuseaux horaires depuis nos 10 bureaux, situ√©s √† Paris, Londres, Gen√®ve, Milan, Shanghai, Hong Kong, Shenzhen, Taipei, Singapour et New York. fifty-five attache une importance particuli√®re au bien-√™tre de ses collaborateurs, ce qui lui a permis de figurer dans le classement Best Workplaces France en 2018.\nContexte :\nL'√©quipe d'ing√©nierie d√©veloppe et met en ≈ìuvre les solutions techniques permettant la r√©alisation de pipelines de donn√©es et l'impl√©mentation de data platform pour nos clients : r√©cup√©ration de datas sur de multiples sources de donn√©es (APIs, files, etc.), data cleaning, data processing, automation et monitoring de l'ensemble. L'√©quipe s'appuie sur des technologies r√©centes (docker, kubernetes, terraform, notebooks, etc.) et met en place ses projets dans les diff√©rents clouds du march√© (GCP, Azure, AWS...).\nMission :\nNous sommes √† la recherche d'une personne capable de r√©aliser des projets techniques pour r√©pondre aux besoins de nos clients (par exemple: syst√®me de recommandations de produits, d√©tection d'anomalies, ranking). Les activit√©s vont du chiffrage et du sizing technique √† la mise en ≈ìuvre des architectures, en passant par la revue des sp√©cifications fonctionnelles et la production de code. Le Data & Cloud Engineer sera √©paul√© par un Lead dans ses missions. Il sera √©galement amen√© √† participer √† la R&D et √† accompagner les √©quipes transverses dans la mise en place d'outils de travail internes (librairies pour les data scientists, environnement Notebooks pour les data analysts et data scientists, d√©veloppement de frameworks sur diff√©rents cloud providers, etc.).\nNous souhaitons trouver la bonne personne pour faire √©voluer ou cr√©er de nouvelles solutions dans ce cadre. Les missions comprennent aussi bien du prototypage rapide pour des d√©monstrateurs, que de la production de code robuste qui tourne en production tous les jours.\nComp√©tences et exp√©riences :\n2 ans d'exp√©rience en tant que Data Engineer\nMa√Ætrise de Python, SQL\nMa√Ætrise des environnements Cloud. Id√©alement certifi√© GCP, Azure ou AWS\nBonne connaissance de Docker/Kubernetes\nBonne connaissance d'au moins un data warehouse (BigQuery, Snowflake, etc)\nConnaissance autour des Notebooks (Jupyter)\nA l'aise avec des concepts li√©s aux APIs (OAuth, REST, etc.)\nA l'aise avec les notions d'Infrastructure as Code (Terraform)\nAu courant des pratiques GitOps et connaissances des concepts autour du CI/CD\nLa ma√Ætrise d'un orchestrateur, comme Apache Airflow, est un plus\nEsprit d'√©quipe (collaborer aux tests unitaires, revue de code, partage de code, sprints)\nBon niveau en fran√ßais et en anglais\nA d√©j√† travaill√© en mode projet avec des interlocuteurs vari√©s (consultant, data analyst, data scientist)\nUne exp√©rience en marketing digital est un plus\nNous proposons :\nun bureau au centre de Paris avec terrasse et jardin\nun environnement multiculturel avec des collaborateurs aux nationalit√©s multiples (France, Royaume-Uni, Etats-Unis, Chine, Tunisie, Italie et plus)\ndes projets avec nos bureaux √† Londres, Hong Kong, New York, Shanghai, Gen√®ve, Shenzhen et Taipei\ndes TGIF et supers soir√©es\nShow more\nShow less",
        "details": {
            "JobDetail": [],
            "TypeContract": "",
            "Salary": "",
            "Level": "",
            "Experience": "2 an(s)"
        },
        "title": "data engineer",
        "skills": {
            "ProgLanguage": [
                "R",
                "Python"
            ],
            "DataBase": [
                "SQL"
            ],
            "DataAnalytics": [
                "R"
            ],
            "BigData": [
                "Apache Airflow"
            ],
            "CloudComputing": [
                "GCP",
                "AWS",
                "Azure"
            ],
            "DevTools": [
                "Docker"
            ],
            "DBMS": [
                "BigQuery",
                "Snowflake"
            ],
            "Automation": [
                "Airflow",
                "Kubernetes"
            ],
            "InfrastructureAsCode": [
                "Terraform"
            ],
            "Containers": [
                "Docker",
                "Kubernetes"
            ],
            "Other": [
                "Cloud",
                "CI/CD"
            ],
            "EnSoftSkils": [
                "Collaboration"
            ]
        }
    },
    {
        "source": "LinkedIn",
        "company": "AFD Technologies",
        "location": "Lille, Hauts-de-France, France",
        "link": "https://fr.linkedin.com/jobs/view/data-engineer-at-afd-technologies-3899625641?position=44&pageNum=0&refId=3%2BsKCnzKBomYeuJjjsOexw%3D%3D&trackingId=orGpiUT6ZkfNr5fLDMxvXw%3D%3D&trk=public_jobs_jserp-result_search-card",
        "description": "AFD.TECH part of Accenture\nest le sp√©cialiste du conseil en transformation digitale des grandes entreprises üöÄ.\nA ce jour, le Groupe est compos√© de 2.000 talents r√©partis dans 3 pays (France, Belgique & Maroc) üåé pour un chiffre d‚Äôaffaires annuel de 125M‚Ç¨ !\nNos Talents d‚Äôabord üòé:\nLes Talents d‚ÄôAFD.TECH part of Accenture sont au c≈ìur de la strat√©gie du Groupe et il est primordial pour nous que chaque collaborateur trouve du sens dans son travail.\nAu-del√† de proposer une carri√®re ambitieuse et personnalis√©e √† nos Talents, nous avons √† c≈ìur de leur offrir un environnement de travail flexible (remote), inclusif et √©panouissant dans tous nos bureaux (Paris, Bruxelles, Rabat, Lyon, Strasbourg, Lille, Nantes, Toulouse, Marseille, Bordeaux et Rennes)üåç.\nAvec 20% de croissance par an et plus de 20 ans d‚Äôexistence, AFD.TECH part of Accenture est devenu l‚Äôacteur incontournable du march√© des infrastructures informatiques, r√©seaux et t√©l√©coms.\nNotre proposition de valeur ? Intervenir sur l‚Äôensemble du cycle de vie de projets complexes, pour des clients grands comptes, venant de secteurs tels que la banque, le ferroviaire, les m√©dias, t√©l√©coms, etc (comme la Soci√©t√© G√©n√©rale, Bouygues Telecom, Orange, Thales et bien d‚Äôautres encore !)üë©üèª‚Äçüíª.\nNous rejoindre est une formidable aventure humaine : nous vous proposons un poste un poste de\nData Engineer en CDI\n, au sein de notre agence Lilloise.\nVos missions ‚úÖ:\nEn tant que Data Engineer pour l'un de nos clients grands comptes, votre r√¥le s‚Äôarticulera autour de diff√©rents axes :\nAppr√©hender le contexte et les enjeux m√©tier du client.\nCollaborer avec les √©quipes m√©tier pour comprendre les exigences en mati√®re de donn√©es.\nD√©finir des architectures data.\nConcevoir et mettre en place des pipelines de donn√©es.\nConstruire des flux de donn√©es complexes.\nVous travaillerez dans une mission √† forte valeur ajout√©e et de longue dur√©e (minimum 1 an et demi).\nVotre profil‚úÖ:\nVous ma√Ætrisez le langage SQL, les ETL et les ELT.\nVous aimez automatiser, mettre en place vos data pipelines et ma√Ætriser les technologies: CI/CD, Terraform, Github, Python, Kafka.\nVous poss√©dez des comp√©tences en data visualisation : Business Objects, Qlikview, Qlik Sense, PowerBI ou Data Studio.\nVous connaissez Google Cloud Platform (GCS, BigQuery).\nVous √™tes dipl√¥m√©(e) d‚Äôune formation BAC + 5.\nVous avez une premi√®re exp√©rience significative dans la data engineering (\nminimum 3 ans\n).\nVous projetez votre carri√®re dans un cabinet de conseil exigent et successful, qui vous permettra de d√©velopper votre esprit entrepreneurial et de r√©pondre √† vos ambitions.\nCe que nous offrons chez AFD.TECH part of Accenture ü§ó:\nUne politique de flexibilit√© dans votre organisation et un bon √©quilibre de vie üèÉ‚Äç‚ôÇÔ∏è.\nDes avantages plus que comp√©titifs üí∞.\nUn accompagnement et un suivi r√©gulier durant tout votre parcours chez AFD.TECH (Launchpad, Linkers, rookies, etc‚Ä¶).\nUn √©tat d‚Äôesprit familial et de la proximit√© entre tous üë®‚Äçüë©‚Äçüëß‚Äçüë¶.\nDes moments de convivialit√© toute l‚Äôann√©e üçæ (√©vent en √©quipe, s√©minaire annuel, sports collectifs etc.).\nUn parcours d‚Äô√©volution sur mesure üîº.\nA tr√®s bient√¥t chez AFD.TECH part of Accenture!\nShow more\nShow less",
        "details": {
            "JobDetail": [
                "Remote"
            ],
            "TypeContract": "CDI",
            "Salary": "",
            "Level": "",
            "Experience": "20 an(s)"
        },
        "title": "data engineer",
        "skills": {
            "ProgLanguage": [
                "Python"
            ],
            "DataBase": [
                "SQL"
            ],
            "MachineLearning": [
                "Orange"
            ],
            "CloudComputing": [
                "Google Cloud Platform"
            ],
            "DBMS": [
                "BigQuery"
            ],
            "InfrastructureAsCode": [
                "Terraform"
            ],
            "Other": [
                "Cloud",
                "CI/CD"
            ]
        }
    },
    {
        "source": "LinkedIn",
        "company": "Extia",
        "location": "Paris, √éle-de-France, France",
        "link": "https://fr.linkedin.com/jobs/view/data-engineer-h-f-at-extia-3599188121?position=45&pageNum=0&refId=3%2BsKCnzKBomYeuJjjsOexw%3D%3D&trackingId=idnvST7Wgm%2FYg5eqGhW2tQ%3D%3D&trk=public_jobs_jserp-result_search-card",
        "description": "Vous souhaitez rejoindre une entreprise qui place l‚Äôhumain au c≈ìur de ses pr√©occupations ? On vous attend chez\nExtia\n!\nSoci√©t√© de conseil sp√©cialis√©e dans les m√©tiers de l‚ÄôIT, de l‚Äôing√©nierie et du digital, Extia privil√©gie depuis sa cr√©ation en 2007 une approche qui allie performance et bien-√™tre au travail. Une vision de l‚Äôentreprise partag√©e aujourd‚Äôhui par plus de 2 500 Extiens en France et √† l'international et r√©compens√©e par le label Great Place to Work¬Æ depuis 13 ans, notamment en\n2024 o√π les Extiens se hissent √† la premi√®re place du palmar√®s Best Workplaces France\n!\nChez Extia, c‚Äôest ¬´ D‚Äôabord qui, ensuite quoi ¬ª alors, allons-y !\nD'abord qui\nVous √™tes habitu√© √† travailler aussi bien avec des m√©ta-donn√©es qu‚Äôavec des donn√©es non-structur√©es. A cet effet vous maitrisez un ou plusieurs des concepts comme l‚ÄôETL, le Data mining le Machine learning, les Big data ou encore la Th√©orie des graphes par exemple,\nVous maitrisez les bases de l‚Äôanalyse statistique,\nVous √™tes apte √† r√©diger des scripts en Python et/ou R, et une connaissance d'autres langages de programmation comme Java, Scala ou SAS est un plus,\nVous maitrisez Spark et Hadoop\nVous √™tes familiaris√© avec l‚Äôenvironnement Linux,\nUne exp√©rience avec les outils de Stockage de fichiers volumineux (HDFS, Data Lake, S3, stockage Blob), la connaissance des infrastructures cloud AWS ou GCP et des bases en streaming temps r√©el seront aussi de r√©els atouts.\nEnsuite quoi\nVous aurez le r√¥le de support technique aux √©quipes d‚Äôanalyse : structurer les donn√©es, r√©aliser des analyses ¬´ statistiques ¬ª ou ¬´ techniques ¬ª sur les donn√©es, d√©velopper des outils d‚Äôanalyse‚Ä¶\nVous m√®nerez des √©tudes afin d‚Äô√©valuer les nouvelles technologies dans le domaine du Big Data, Data Mining ou Machine Learning afin d‚Äôidentifier les solutions les plus pertinentes.\nVous serez en charge de :\nParticiper √† la d√©finition des besoins et √† la r√©daction des User Stories,\nCollaborer avec les Data Scientists au d√©veloppement des modules d‚Äôanalyse de donn√©e,\nConcevoir et construire des architectures de donn√©es,\nInt√©grer des sources de donn√©es,\nVous assurez que les donn√©es sont facilement accessibles et que leur exploitation fonctionne comme demand√©, m√™me dans des circonstances hautement √©volutives,\nEx√©cuter des processus ETL (extraire / transformer / charger) √† partir d'ensembles de donn√©es complexes et / ou volumineux\nShow more\nShow less",
        "details": {
            "JobDetail": [],
            "TypeContract": "",
            "Salary": "",
            "Level": "",
            "Experience": "13 an(s)"
        },
        "title": "data engineer",
        "skills": {
            "ProgLanguage": [
                "R",
                "Java",
                "Scala",
                "Python"
            ],
            "DataAnalytics": [
                "R"
            ],
            "BigData": [
                "Hadoop",
                "Spark"
            ],
            "CloudComputing": [
                "GCP",
                "AWS"
            ],
            "OS": [
                "Linux"
            ],
            "Other": [
                "Statistiques",
                "Machine Learning",
                "Cloud",
                "Big Data"
            ]
        }
    },
    {
        "source": "LinkedIn",
        "company": "ternair",
        "location": "Lille",
        "link": "https://fr.linkedin.com/jobs/view/data-engineer-h-f-at-ternair-3915757963?position=46&pageNum=0&refId=3%2BsKCnzKBomYeuJjjsOexw%3D%3D&trackingId=k70htbH6tNUd3%2BJHjI90jA%3D%3D&trk=public_jobs_jserp-result_search-card",
        "description": "üë®‚ÄçüöÄ MISSION : üë©‚ÄçüöÄ\nEn coh√©rence avec la strat√©gie d‚Äôentreprise et la roadmap data, vous aurez pour principales missions de :\nEn lien avec l‚Äô√©quipe DevOps, construire, maintenir et faire √©voluer la plateforme de donn√©es;\nD√©finir et piloter la coh√©rence de la collecte, la gestion et l‚Äôalimentation des donn√©es internes et externes, en diff√©rents modes : batch, streaming, API (architecture micro-services);\nPr√©parer et mettre en qualit√© les donn√©es pour les rendre disponibles dans les diff√©rents environnements de travail (datalake, datawarehouse, datamart);\nV√©rifier la qualit√© des donn√©es, de leur bonne et r√©guli√®re ex√©cution ainsi que de leur utilisation ad√©quate (gestion des co√ªts);\nTravailler en √©troite collaboration avec les data analysts, scientists et data stewards et business de l‚Äôentreprise ;\nEn lien avec l‚ÄôIT et la s√©curit√©, veiller aux r√®gles d'int√©grit√© et de s√©curit√© des donn√©es;\nVeille technologique.\nüßÆ Les outils :\nPlateforme data : Google Cloud Platform (Big Query, Airflow)\nD√©veloppement : Github/GitLab, Docker, Terraform, Python\nAnalytiques : Qlik\nGestion de projet s: Jira, Confluence, Miro, Drive, Docs, Sheets, Slides\nü§© Profil recherch√© : ü§©\nExp√©rience d'au moins 4-5 ans (apr√®s √©tudes) en data ing√©nierie (flux, mod√©lisation, run)\nA l‚Äôaise avec l‚Äôenvironnement Cloud et les infrastructures digitales\nCommuniquant, p√©dagogue et fortes capacit√©s relationnelles\nAnglais (√† l‚Äô√©crit)\nR√©mun√©ration : 42-60 k‚Ç¨ en package selon exp√©rience\nShow more\nShow less",
        "details": {
            "JobDetail": [],
            "TypeContract": "",
            "Salary": "Package",
            "Level": "",
            "Experience": "5 an(s)"
        },
        "title": "data engineer",
        "skills": {
            "ProgLanguage": [
                "Python"
            ],
            "CloudComputing": [
                "Google Cloud Platform"
            ],
            "DevTools": [
                "Docker"
            ],
            "DBMS": [
                "Big Query"
            ],
            "Automation": [
                "Airflow"
            ],
            "InfrastructureAsCode": [
                "Terraform"
            ],
            "Containers": [
                "Docker"
            ],
            "Collaboration": [
                "Confluence",
                "JIRA"
            ],
            "Other": [
                "Cloud",
                "DevOps"
            ],
            "EnSoftSkils": [
                "Collaboration"
            ]
        }
    },
    {
        "source": "LinkedIn",
        "company": "Herm√®s",
        "location": "Paris, √éle-de-France, France",
        "link": "https://fr.linkedin.com/jobs/view/alternance-data-engineer-h-f-at-herm%C3%A8s-3889716412?position=47&pageNum=0&refId=3%2BsKCnzKBomYeuJjjsOexw%3D%3D&trackingId=ugM4PYXtnIt7owFtQtvTFQ%3D%3D&trk=public_jobs_jserp-result_search-card",
        "description": "El√©ments de contexte\nHerm√®s Digital Ventes et Services recherche pour sa direction Data & Performance :\nUn Alternant Data Engineer (H/F)\nContrat d'alternance de 12 mois\nA partir de Septembre 2024\nBas√© √† Paris\nPrincipales activit√©s\nVous √™tes rattach√© au Data manager.\nVous avez pour principale mission d‚Äôaccompagner l‚Äô√©quipe Data dans les t√¢ches quotidiennes :\nReporting et statistiques de ventes et trafic (notamment via l‚Äôoutil Google Analytics et Google BigQuery)\nAnalyse des leviers d‚Äôacquisition de traffic SEA/SEO/Referral\nCr√©ation de Dashboard via l‚Äôoutil Google Data Studio\nParticipation aux travaux de CRO (Conversion Rate Optimization) et d‚ÄôAB testing\nMise en place d‚Äô√©tude pr√©dictive sur les donn√©es des sites Ecommerce\nProfil\nEtudiant en √©cole d‚Äôing√©nieur poss√©dant une forte culture Internet et une sensibilit√© aux probl√©matiques digitales e-commerce, vous avez une premi√®re exp√©rience en entreprise\nProfil technique ou ais√© avec la technique, une sp√©cialisation en digital est en plus\nOrganis√©, rigoureux, curieux, autonome, bonne expression √©crite et aisance relationnelle\nMa√Ætrise du Pack Office indispensable, ayant d√©j√† utilis√© Google Analytics\nLa connaissance d‚Äôoutils de BI / Datavisualisation serait appr√©ci√©e (Google Data Studio, Tableau Software, Bime ou QlikView/QlikSense, PowerBI), de Base de Donn√©es (SQL, MySQL, BigQuery)\nUne app√©tence pour la Data, ses languages (Python, R) et ses technologies (Notebooks, mod√©lisation statistique, Machine learning) est fortement appr√©ci√©e.\nAnglais courant souhait√©\nSensible aux produits hauts de gamme, vous souhaitez vous investir dans un stage riche et formateur\nShow more\nShow less",
        "details": {
            "JobDetail": [],
            "TypeContract": "",
            "Salary": "",
            "Level": "",
            "Experience": null
        },
        "title": "data engineer",
        "skills": {
            "ProgLanguage": [
                "R",
                "Python"
            ],
            "DataBase": [
                "SQL"
            ],
            "DataAnalytics": [
                "R"
            ],
            "DataVisualisation": [
                "Tableau"
            ],
            "DBMS": [
                "BigQuery",
                "MySQL"
            ],
            "Other": [
                "Statistiques",
                "Machine Learning"
            ]
        }
    },
    {
        "source": "LinkedIn",
        "company": "Thales",
        "location": "V√©lizy-Villacoublay, √éle-de-France, France",
        "link": "https://fr.linkedin.com/jobs/view/ing%C3%A9nieur-data-spark-f-h-at-thales-3890949531?position=48&pageNum=0&refId=3%2BsKCnzKBomYeuJjjsOexw%3D%3D&trackingId=dcxA0hGPUFkhVxFUbO46aw%3D%3D&trk=public_jobs_jserp-result_search-card",
        "description": "QUI SOMMES-NOUS ?\nThales est un leader mondial des hautes technologies comptant plus de 81 000 collaborateurs pr√©sents sur tous les continents. Le Groupe investit dans les innovations du num√©rique et de la ¬´ deep tech ¬ª ‚Äì big data, intelligence artificielle, connectivit√©, cybers√©curit√© et quantique ‚Äì pour construire un avenir de confiance, essentiel au d√©veloppement de nos soci√©t√©s, en pla√ßant l‚Äôhumain au c≈ìur des d√©cisions.\nThales propose des solutions, services et produits qui aident ses clients ‚Äì entreprises, organisations, Etats ‚Äì dans cinq grands march√©s vitaux pour le fonctionnement de nos soci√©t√©s : identit√© et s√©curit√© num√©riques, d√©fense, a√©ronautique, espace, et transport.\nQUI ETES-VOUS ?\nDipl√¥m√© d‚Äôun Bac+5 en √©cole d‚Äôing√©nieur ou √©quivalent universitaire avec une sp√©cialisation en informatique, vous avez au moins 3 ans d'exp√©rience dans les technologies Big Data.\nCE QUE NOUS POUVONS ACCOMPLIR ENSEMBLE :\nEn tant que Data Engineer, vous jouerez un r√¥le cl√© dans la conception, le d√©veloppement et la maintenance de notre infrastructure de donn√©es, ainsi que dans la transformation et la gestion des flux de donn√©es.\nVOS MISSIONS :\n‚Ä¢ Concevoir, d√©velopper et d√©ployer des solutions Big Data en utilisant les technologies Spark.\n‚Ä¢ Mettre en place des pipelines de donn√©es performants pour l'ingestion, le traitement et le stockage des donn√©es massives.\n‚Ä¢ Collaborer √©troitement avec les √©quipes m√©tier pour comprendre leurs besoins en mati√®re d'analyse de donn√©es et proposer des solutions adapt√©es.\n‚Ä¢ Optimiser les performances des clusters Hadoop pour garantir une exploitation efficace des donn√©es.\n‚Ä¢ Assurer la qualit√© et la fiabilit√© des donn√©es trait√©es, en mettant en place des processus de validation et de nettoyage.\n‚Ä¢ Identifier et r√©soudre les probl√®mes li√©s √† l'infrastructure Big Data et proposer des am√©liorations.\n‚Ä¢ Travailler en √©troite collaboration avec les Data Scientists et les Data Analysts pour fournir des insights pertinents √† partir des donn√©es.\nInnovation, passion, ambition : rejoignez Thales et cr√©ez le monde de demain, d√®s aujourd‚Äôhui.\nShow more\nShow less",
        "details": {
            "JobDetail": [],
            "TypeContract": "",
            "Salary": "",
            "Level": "Bac+5",
            "Experience": "3 an(s)"
        },
        "title": "data engineer",
        "skills": {
            "BigData": [
                "Hadoop",
                "Spark"
            ],
            "Other": [
                "Big Data"
            ],
            "EnSoftSkils": [
                "Collaboration"
            ]
        }
    },
    {
        "source": "LinkedIn",
        "company": "Coders Connect",
        "location": "Paris, √éle-de-France, France",
        "link": "https://fr.linkedin.com/jobs/view/data-engineer-at-coders-connect-3870419202?position=49&pageNum=0&refId=3%2BsKCnzKBomYeuJjjsOexw%3D%3D&trackingId=9QJTVineCdvNmTlkNlCzGg%3D%3D&trk=public_jobs_jserp-result_search-card",
        "description": "Coders Connect and Sanofi are joining forces to bring an electrifying twist to the biopharmaceutical world!\nWork with a rhythm that suits your style (2 days remote and 3 days onsite magic).\nLanguage\n: Proficiency in English is required for this role to ensure effective communication within our diverse, global team.\nAbout Sanofi:\nWe're not just a company; we're a global movement, focused on human health and making a real difference. Our mission? To battle pain, ease suffering, and sprinkle a little bit of magic in the process by developing life-changing medicines and vaccines through breakthrough science and wizard-level technology.\nDigital & Data: The Pulse of Our Mission\nAt the heart of our quest lies our digital and data powerhouse. Think of us as the digital healthcare platform of your dreams, where innovation meets speed, and technology shakes hands with medicine. With our scale, deep-rooted connections in health ecosystems worldwide, and a knack for pushing boundaries, we're here to revolutionise medicine, one digital solution at a time.\nThe Role: Data Engineering Virtuoso\nAs our Data Engineering Virtuoso, you're tasked with designing and orchestrating the data pipelines that power our ambitious data analytics initiatives. You'll ensure our data's integrity and accessibility, laying the groundwork for groundbreaking insights and innovations.\nRequirements\nCloud Platforms: Proficient in AWS services, with Azure & GCP knowledge a plus. Your work involves leveraging cloud solutions for scalable data processing and storage.\nData Modeling & Query Performance: Expertise in crafting data models and optimizing SQL queries to enhance performance. Experience with Snowflake or similar data warehousing solutions is highly valued.\nIntegration Services: Skilled in utilizing Integration Services like IICS and Tibco, you facilitate seamless data flow and integration across various platforms.\nScripting & Development: Proficient in scripting languages such as Python and R, enabling you to automate tasks and manipulate data efficiently. Familiarity with GitHub for source code management underscores your commitment to collaborative development and version control.\nVisualization & Reporting: Knowledgeable in creating insightful data visualizations using tools like PowerBI, Tableau, or similar, turning complex data into actionable insights.\nData Governance & Compliance: A keen understanding of data quality, security, and governance standards, especially in healthcare environments subject to regulations like GxP, SOX, and data privacy laws.\nReal World Data & Standard Models: Experience with Real World Data (e.g., EHR, Claims) and familiarity with standard data models (e.g., OMOP, FHIR) enhance your ability to contribute to our healthcare objectives.\nPipeline Frameworks: Proficiency in using frameworks like Apache Airflow or Kedro for crafting efficient, reliable data pipelines that support our AI and ML initiatives.\nThe Reward:\nA chance to play a crucial role in a collaboration that's redefining healthcare through digital transformation.\nA seat at the round table of diversity and inclusion, where different backgrounds and experiences conjure the richness of our culture.\nAn endless horizon of professional growth, learning opportunities, and the chance to contribute to a future where better health is a global reality.\nThe Call to Adventure:\nIf you're ready to join a quest for better ‚Äì better treatments, better outcomes, and better science ‚Äì and believe in the magic of bringing diverse talents together to make miracles happen, we want you. Let's embark on this journey together and transform the future of healthcare.\nBetter is out there. Are you ready to find it with us?\nShow more\nShow less",
        "details": {
            "JobDetail": [
                "Remote"
            ],
            "TypeContract": "",
            "Salary": "",
            "Level": "",
            "Experience": null
        },
        "title": "data engineer",
        "skills": {
            "ProgLanguage": [
                "R",
                "Python"
            ],
            "DataBase": [
                "SQL"
            ],
            "DataAnalytics": [
                "R"
            ],
            "BigData": [
                "Apache Airflow"
            ],
            "DataVisualisation": [
                "Tableau"
            ],
            "CloudComputing": [
                "GCP",
                "AWS",
                "Azure"
            ],
            "DBMS": [
                "Snowflake"
            ],
            "Automation": [
                "Airflow"
            ],
            "Other": [
                "Cloud",
                "ML"
            ],
            "EnSoftSkils": [
                "Communication",
                "Collaboration"
            ]
        }
    },
    {
        "source": "LinkedIn",
        "company": "Airswift",
        "location": "Paris, √éle-de-France, France",
        "link": "https://fr.linkedin.com/jobs/view/data-engineer-at-airswift-3909165766?position=50&pageNum=0&refId=3%2BsKCnzKBomYeuJjjsOexw%3D%3D&trackingId=q7y9K5yzxgMnbFX9%2Fd5j6g%3D%3D&trk=public_jobs_jserp-result_search-card",
        "description": "Data Engineer\nLocation\n: Paris (Hybrid)\nContract type\n: 12 months +\nYears of Experience\n: 4+\nRecruitment Partner:\nAirswift\nKey Words:\nProject Management | Jira | Digiboard | Banking | Stakeholder Management | Architecture | Cloud | Payments/Credit |ServiceNow | PPM |\nResponsibilities\nDesign, develop, and implement data pipelines to collect, process, and store structured and unstructured data from various sources.\nCollaborate with data scientists, analysts, and other stakeholders to understand data requirements and translate them into technical solutions.\nOptimize and tune data pipelines for performance, scalability, and reliability.\nEnsure data quality and integrity throughout the data lifecycle, implementing data validation and monitoring processes.\nEvaluate and implement new tools and technologies to enhance our data infrastructure and capabilities.\nRequirements\n:\nExtensive experience in Python.\nStrong experience with data processing frameworks and tools such as Apache Spark.\nExperience with cloud platforms such as AWS, Azure, or Google Cloud Platform.\nSolid understanding of data modelling, database design, and SQL\nFrench and English speaking\nFreelancing opportunity\nThe next step\nWe have an exceptional team in place, and we are pleased to be able to appoint a further person to our growing business. We are aware that you may not ‚Äòtick all the boxes‚Äô, but if you believe you can genuinely offer some valuable skills and experience to our business, please in the first instance contact our recruitment partner Airswift.\nShow more\nShow less",
        "details": {
            "JobDetail": [],
            "TypeContract": "",
            "Salary": "",
            "Level": "",
            "Experience": null
        },
        "title": "data engineer",
        "skills": {
            "ProgLanguage": [
                "Python"
            ],
            "DataBase": [
                "SQL"
            ],
            "BigData": [
                "Spark"
            ],
            "CloudComputing": [
                "AWS",
                "Google Cloud Platform",
                "Azure"
            ],
            "Collaboration": [
                "JIRA"
            ],
            "Other": [
                "Cloud"
            ]
        }
    },
    {
        "source": "LinkedIn",
        "company": "Astek",
        "location": "Antibes, Provence-Alpes-C√¥te d'Azur, France",
        "link": "https://fr.linkedin.com/jobs/view/data-engineer-%E2%80%93-antibes-france-h-f-at-astek-3909192086?position=51&pageNum=0&refId=3%2BsKCnzKBomYeuJjjsOexw%3D%3D&trackingId=%2Fx2IpOfjS03kulxGTh%2FqRg%3D%3D&trk=public_jobs_jserp-result_search-card",
        "description": "CDI\nAntibes - France\nPubli√©e il y a 2 semaines\nLe Groupe Astek\nCe Que Nous Allons Accomplir Ensemble :\nIntervenir dans la conception, le d√©veloppement, les tests unitaires, la qualification, l‚Äôint√©gration continue et la mise en production d‚Äô√©volutions sur les projets du p√¥le produits scoring (un p√¥le visant √† d√©velopper des solutions permettant de g√©n√©rer des scores ou des segments d‚Äôinformation pertinents dans divers domaines, notamment : profiling TV, PUB, SAB, MMDM, Voscastview) chez l‚Äôun de nos partenaires sp√©cialis√© dans le secteur des t√©l√©coms.\nVotre Mission, Si Vous L‚Äôacceptez :\nEn collaboration avec les autres membres de l‚Äô√©quipe, vous devrez prendre en charge le RUN des applications du p√¥le produit scoring.\nConception d‚Äôune solution se basant sur les d√©veloppements existants et les besoins m√©tiers remont√©s par le Product Owner.\nR√©alisation et d√©veloppement de nouvelles fonctionnalit√©s sur les composants des applications du p√¥le produits scoring et environnement CGP.\nVotre Future √âquipe :\nAu sein d‚Äôun environnement riche et complexe, vous √©voluerez avec des experts passionn√©s √† la fois techniques et fonctionnels (Ing√©nieurs sp√©cialis√©s, chef de projet, scrum master, product owner, analystes ‚Ä¶).\nVotre stack de jeu\nD ans un environnement SAFE sous cloud GCP, Big Query, OnPrime, Grafana, Python et Ansible.\nVous ?\nDe formation Ing√©nieur, vous justifiez d‚Äôune premi√®re exp√©rience sur un poste de Data engineer. Vous poss√©dez des comp√©tences d‚Äôautonomie et d‚Äôadaptabilit√© et vous avez une capacit√© √† communiquer efficacement au sein d‚Äôune √©quipe.\nLe Groupe Astek\nCr√©√© en France en 1988, Astek est un acteur mondial de l‚Äôing√©nierie et du conseil en technologies. Fort de son expertise dans de nombreux secteurs industriels et tertiaires, Astek accompagne ses clients internationaux dans le d√©ploiement intelligent de leurs produits et de leurs services, et dans la mise en ≈ìuvre de leur transformation digitale.\nDepuis sa cr√©ation, le Groupe a fond√© son d√©veloppement sur une forte culture d‚Äôentrepreneuriat et d‚Äôinnovation, et sur l‚Äôaccompagnement et la mont√©e en comp√©tence de\nses 7800 collaborateurs\nqui s‚Äôengagent chaque jour √† promouvoir la compl√©mentarit√© entre les technologies num√©riques et l‚Äôing√©nierie des syst√®mes complexes.\nRejoignez un Groupe en fort d√©veloppement en France et √† travers le monde ayant r√©alis√© un chiffre d‚Äôaffaires de 600 M‚Ç¨ en 2023.\nTous les d√©tails sur le Groupe sur le site https://astekgroup.fr. Et vous pouvez aussi nous suivre sur notre blog : https://blog.groupeastek.com.\nRencontrons-nous\nCr√©√© en France en 1988, Astek est un acteur mondial de l‚Äôing√©nierie et du conseil en technologies, pr√©sent sur les 5 continents. Fort de son expertise dans de nombreux secteurs industriels et tertiaires, Astek accompagne ses clients internationaux dans le d√©ploiement intelligent de leurs produits et de leurs services, et dans la mise en ≈ìuvre de leur transformation digitale.\nDepuis sa cr√©ation, le Groupe a fond√© son d√©veloppement sur une forte culture d‚Äôentrepreneuriat et d‚Äôinnovation, et sur l‚Äôaccompagnement et la mont√©e en comp√©tence de ses 7800 collaborateurs qui s‚Äôengagent chaque jour √† promouvoir la compl√©mentarit√© entre les technologies num√©riques et l‚Äôing√©nierie des syst√®mes complexes.\nRejoignez un Groupe en fort d√©veloppement en France et √† travers le monde et ayant r√©alis√© un chiffre d‚Äôaffaires hors\nacquisitions de 600M‚Ç¨ en 2023.\nTous les d√©tails sur le Groupe sur le site\nNos Plus\nAstek est green et fait b√©n√©ficier ses salari√©s d‚Äôune indemnit√© kilom√©trique v√©lo\nUne politique CARE sur-mesure d√©ploy√©e par nos √©quipes RH pour nos collaborateurs (https://astekgroup.fr/engagements)\nNotre charte de la Diversit√©\nMots-cl√©s :\ning√©nieur ‚Äì ing√©nieure ‚Äì consultant ‚Äì consultante ‚Äì Data engineer ‚Äì Big Data\nCaract√©ristiques de l'emploi\nCat√©gorie Ing√©nieur\nJob Industry T√©l√©com / M√©dia\nPostuler en ligne\nNom *\nPr√©nom *\nEmail *\nUn email valide est requis.\nT√©l√©phone *\nUn num√©ro de t√©l√©phone valide est requis.\nJoindre un CV *\nMots-cl√©s :\ning√©nieur ‚Äì ing√©nieure ‚Äì consultant ‚Äì consultante ‚Äì Data engineer ‚Äì Big Data\nShow more\nShow less",
        "details": {
            "JobDetail": [],
            "TypeContract": "CDI",
            "Salary": "",
            "Level": "",
            "Experience": null
        },
        "title": "data engineer",
        "skills": {
            "ProgLanguage": [
                "Python"
            ],
            "CloudComputing": [
                "GCP"
            ],
            "DBMS": [
                "Big Query"
            ],
            "Automation": [
                "Chef",
                "Ansible"
            ],
            "Other": [
                "Cloud",
                "Big Data"
            ],
            "EnSoftSkils": [
                "Collaboration"
            ]
        }
    },
    {
        "source": "LinkedIn",
        "company": "Web Transition",
        "location": "Lille, Hauts-de-France, France",
        "link": "https://fr.linkedin.com/jobs/view/data-engineer-h-f-at-web-transition-3909147172?position=52&pageNum=0&refId=3%2BsKCnzKBomYeuJjjsOexw%3D%3D&trackingId=BIIB%2Bl%2B%2Fq%2BoLTD44AOhf6A%3D%3D&trk=public_jobs_jserp-result_search-card",
        "description": "Web Transition, c‚Äôest qui ?\nFond√©e en 2011,\nWeb transition\nest une entreprise de services num√©riques op√©rant sur le march√© de l‚ÄôIT/Digital !\nConstituant une part essentielle de\nMoOngy Digital Lab\n, Web Transition accompagne ses clients grands comptes sur leurs projets de Webmarketing, de Design, Gestion de projet et √©galement en Data !\nNotre objectif : nous implanter comme un acteur principal sur le march√© de la Transformation Digitale en accompagnant et valorisant les comp√©tences de nos collaborateurs !\nNous sommes convaincus que le succ√®s de MoOngy Digital Lab r√©side dans la somme des potentiels de nos √©quipes ü§ù\nTon √©quipe : La tribu Data\nParce qu‚Äôil est indispensable que tu puisses partager tes connaissances mais aussi en acqu√©rir de nouvelles, tu feras partie de l‚Äôune de nos tribus : celle de la Data. De plus, cela te permettra d‚Äô√™tre acteur dans le d√©veloppement et la strat√©gie de Web Transition. Ce syst√®me de co-r√©flexion et co-construction est un fondement essentiel chez nous !\nDans cette aventure, tu :\nT‚Äôassures\nde la ma√Ætrise de la donn√©e et est garant de la qualit√© de son utilisation (r√©f√©rencement, normalisation, et qualification)\nTravailles\n√† la compr√©hension et l'int√©gration des donn√©es en provenance des diff√©rents formats\ndes interfaces de flux\n√©galement √† la d√©finition de la politique de la donn√©e et √† la structuration de son cycle de vie dans le respect des r√©glementations en vigueur\nla supervision et l'int√©gration des donn√©es de diverse nature qui proviennent de ces sources multiples et v√©rifie la qualit√© des donn√©es qui entrent dans le Data Lake\nGarantis\nl'acc√®s qualitatif aux sources de donn√©es\nFacilites\nl‚Äôacc√®s aux donn√©es pour tes coll√®gues (data scientists, data analysts‚Ä¶)\nAssistes\nles autres √©quipes dans l'acc√®s et la compr√©hension des donn√©es des socles.\nRejoins-nous si tu as :\nExp√©rience d‚Äôau-moins 4 ans dans la Data\nApp√©tence √† la qualit√© des donn√©es.\nConnaissance famili√®re des Datawarehouses.\nMaitrise de Python, Oracle SQL, GCP/Power BI\nAisance avec les indicateurs, tu as une bonne capacit√© d'analyse et de r√©daction.\nTon savoir-√™tre :\nOuvert d‚Äôesprit\nRigoureux\nAutonome\nRespectueux des diff√©rences de chacun\nCurieux\nProactif\nAgile\nPar o√π on commence ?\nUn premier entretien RH d‚Äô1h pour comprendre ton parcours et tes aspirations\nUn second entretien de 45 minutes avec l‚Äôun de nos Business Manager afin de valider tes comp√©tences et qu‚Äôil se projette sur l‚Äôune des missions qu‚Äôil pourrait te proposer\nUn troisi√®me entretien de quelques minutes avec notre responsable d‚Äôagence pour te proposer d‚Äôint√©grer notre superbe Team Web !\n3 entretiens en peu de temps, si ton profil correspond tu int√®greras tr√®s vite nos √©quipes üòâ\nPr√™t pour embarquer dans notre grande aventure humaine ? Deviens notre futur Weber en postulant √† cette offre ! Voici les avantages qui t‚Äôattendent en tant que Weber :\nü§© Des coll√®gues incroyables\nüèÜ Certifi√©e Great Place to Work\nüéÆ Des bureaux sympas (o√π vous serez toujours les bienvenus)\nüéâ Des teambuilding et √©vents tous les mois\nüíª Des tributs m√©tiers pour √©changer entre Weber du m√™me m√©tier\nDes missions chez le client qui sont accompagn√©es et coach√©es par ton manager\nUn accompagnement dans ton plan de carri√®re et tes envies de re skilling\nü§ì Un catalogue de formations certifiantes ouvert √† tous les salari√©s\nüçΩÔ∏è Une carte tickets restaurant MyEdenred\n‚ù§Ô∏è Une mutuelle GrasSavoye\nüöé Une prise en charge des frais de transport √† 100%\nShow more\nShow less",
        "details": {
            "JobDetail": [],
            "TypeContract": "",
            "Salary": "",
            "Level": "",
            "Experience": "4 an(s)"
        },
        "title": "data engineer",
        "skills": {
            "ProgLanguage": [
                "Python"
            ],
            "DataBase": [
                "SQL"
            ],
            "DataVisualisation": [
                "Power BI"
            ],
            "CloudComputing": [
                "GCP"
            ],
            "DBMS": [
                "Oracle SQL"
            ]
        }
    },
    {
        "source": "LinkedIn",
        "company": "Mobilize Financial Services ‚Äì France",
        "location": "Noisy-le-Grand, √éle-de-France, France",
        "link": "https://fr.linkedin.com/jobs/view/data-engineer-f-h-at-mobilize-financial-services-%E2%80%93-france-3869637982?position=53&pageNum=0&refId=3%2BsKCnzKBomYeuJjjsOexw%3D%3D&trackingId=CKz25Qo0Q47Y0UW4EgySmA%3D%3D&trk=public_jobs_jserp-result_search-card",
        "description": "üöó En route vers Mobilize !\nA l‚Äô√©coute de tous nos clients, nous cr√©ons des services financiers innovants pour construire une mobilit√© durable pour tous.\nRejoindre Mobilize Financial Services,\nc‚Äôest d‚Äôabord choisir d‚Äôint√©grer un groupe international\n, filiale de Renault Group, une banque de financement solide, partenaire des constructeurs Renault‚ÄìNissan‚ÄìMitsubishi. Nos 4 000 collaborateurs pr√©sents dans 35 pays, agissent ensemble au service de nos clients.\nNous proposons √† nos clients - particuliers comme professionnels - les financements et les services les plus adapt√©s pour les v√©hicules neufs et d'occasion.\nNous finan√ßons √©galement l'activit√© des r√©seaux de concessionnaires des marques de l'Alliance Renault-Nissan-Mitsubishi et nous veillons √† faciliter leur gestion au quotidien pour leur permettre de d√©velopper leurs ventes et assurer leur p√©rennit√© financi√®re.\nNotre entreprise se \"MOBILIZE\" en faveur de la diversit√© culturelle, l'√©galit√© hommes-femmes et l'int√©gration de personnes en situation de Handicap. Nous favorisons un environnement de travail o√π les diff√©rences individuelles sont reconnues, appr√©ci√©es, respect√©es et valoris√©es, de fa√ßon √† mettre √† profit les talents et les forces de chacun.\nüöòPrenez le volant ! Pas de routine, tous nos itin√©raires sont diff√©rents !\nAu sein de la DSI\n,\nvotre\nfutur m√©tier consistera √† :\nAccompagner l‚Äô√©quipe dans la transformation du domaine d√©cisionnel construit sur une architecture type DWH et le porter sur la solution GCP (Google Cloud Platform) de Mobilize FS\nParticiper √† la construction du projet de transformation vers GCP\nParticiper aux projets d‚Äô√©volution de notre plateforme Suite Elastic (ELK - Kibana)\nPiloter des projets en √©troite collaboration avec les directions m√©tier et en accord avec le TBA (Tableau de Bord des Actions).\nAssurer la gestion du budget, du planning, de la tenue des jalons et du respect des engagements sur les projets en responsabilit√©\nAssurer la qualit√© et le bon fonctionnement du chargement des donn√©es.\nAssurer la mise √† disposition des donn√©es et des outils de reportings √† toutes les directions clientes dans le respect des contrats de service\nV√©ritable tout-terrain, vous nous int√©ressez !\nL‚Äôesprit d‚Äô√©quipe et le sens du service client pour atteindre ensemble les diff√©rents objectifs ambitieux et satisfaire les diff√©rentes parties avec un haut niveau de qualit√©.\nVous avez un bon relationnel, de l‚Äô√©coute et une excellente communication afin d‚Äôinteragir avec des interlocuteurs de diff√©rents niveaux (direction technique et m√©tier) et de travailler en transverse.\nLe sens de l‚Äôanalyse et de bonnes capacit√©s d‚Äôanticipation pour d√©celer les probl√®mes avant la naissance de ces derniers.\nForce de proposition : avec vous il n'y a pas de probl√®mes, que des solutions\nVous avez un niveau d‚Äôanglais vous permettant de lire et de comprendre de la documentation technique\nüíªüñ± Environnement technique :\nMaitrise des langages Python - SQL / NoSQL\nExp√©rience significative sur Python\nExp√©rience avec Git\nUne exp√©rience avec les outils Nifi, Airflow et GCP (BigQuery / Cloud Function / Cloud Storage ‚Ä¶) serait un plus\nGestion de projet, maintenance, √©volution, support\nApp√©tence pour les sujets techniques et fonctionnels : outils de mod√©lisation, exploration de donn√©es, IA, machine learning\nPourquoi nous rejoindre ?\nVotre Pack confort\nest compos√© de nombreux avantages üòÄ :\nRejoindre Mobilize Financial Services c‚Äôest int√©grer un grand groupe international qui offre des opportunit√©s de carri√®re\n.\nUn environnement de travail moderne et convivial\n: locaux agr√©ables, salle de sport, terrasse, restaurant d‚Äôentreprise, parking avec un CSE dynamique avec de nombreuses offres voyages, sport, famille,\nNous sommes mobilis√©s pour d√©velopper la qualit√© de vie au travail de nos collaborateurs en faisant √©voluer nos fa√ßons de travailler (m√©thodes, outils, organisation du travail‚Ä¶) et nous sommes fiers d‚Äô√™tre certifi√©s ‚≠ê\nGreat Place To Work ‚≠ê\nPossibilit√© de t√©l√©travailler 2 jours par semaine\nNous proposons une\nr√©mun√©ration selon profil + Participation + Int√©ressement\nLocaux situ√©s au pied du RER A ‚Äì Noisy le Grand Mont d‚ÄôEst\n‚ùó Mobilize Financial Services d√©m√©nage ‚ùó Les postes √† pourvoir en r√©gion parisienne seront bas√©s √† Boulogne Billancourt √† horizon 2026\nPour en savoir plus sur notre entreprise,\nsuivez-nous sur LinkedIn !\nLa route du recrutement ?\nüìû Un rapide entretien t√©l√©phonique,\nüõë\nun premier √©change\navec Marie DE CARLI, Responsable du d√©partement DATA\n‚Ü™ et un dernier virage avec Agathe GROSBOIS, Responsale des Ressources Humaines\nL‚Äô√©quipe Mobilize FS a h√¢te de vous recevoir !\nShow more\nShow less",
        "details": {
            "JobDetail": [],
            "TypeContract": "",
            "Salary": "",
            "Level": "",
            "Experience": null
        },
        "title": "data engineer",
        "skills": {
            "ProgLanguage": [
                "Python"
            ],
            "DataBase": [
                "SQL",
                "NoSQL"
            ],
            "DataVisualisation": [
                "Tableau"
            ],
            "CloudComputing": [
                "GCP",
                "Google Cloud Platform"
            ],
            "DevTools": [
                "Git"
            ],
            "DBMS": [
                "BigQuery"
            ],
            "Automation": [
                "Airflow"
            ],
            "Other": [
                "Machine Learning",
                "Cloud"
            ],
            "EnSoftSkils": [
                "Communication",
                "Collaboration"
            ]
        }
    },
    {
        "source": "LinkedIn",
        "company": "MP DATA",
        "location": "Toulouse, Occitanie, France",
        "link": "https://fr.linkedin.com/jobs/view/data-engineer-h-f-at-mp-data-3908719610?position=54&pageNum=0&refId=3%2BsKCnzKBomYeuJjjsOexw%3D%3D&trackingId=6BLg7dCoO3iP33cOMKL%2B9g%3D%3D&trk=public_jobs_jserp-result_search-card",
        "description": "MP DATA est une soci√©t√© sp√©cialis√©e dans l‚Äôacquisition, le traitement, et la valorisation des donn√©es.\nDepuis sa cr√©ation en 2015, MP DATA accompagne ses clients, majoritairement industriels, dans le management de leur performance et l‚Äôexploitation de leurs donn√©es.\nLes collaborateurs, tous issus de grandes √©coles, incarnent au quotidien les valeurs d‚ÄôExcellence, de Partage et d‚ÄôEngagement.\nIls associent savoir-faire technique, m√©thodologie et passion et mettent leurs comp√©tences au service de missions et projets au sein de grands groupes fran√ßais.\nMP DATA accompagne ses clients sur toute la chaine au travers de 3 p√¥les d‚Äôexpertise : Conseil et Strat√©gie, Infrastructure & CloudOPS, Data Science.\nChez MP DATA, les √©quipes commerciales cherchent des missions en fonction des envies des collaborateurs et non pas l‚Äôinverse. Les consultants sont accompagn√©s dans tous leurs projets, de la mobilit√© g√©ographique, au changement de secteur d‚Äôactivit√© en passant par le d√©veloppement de nouvelles comp√©tences.\nRejoindre MP DATA, c‚Äôest la garantie de travailler sur des sujets passionnants avec un cadre technique fort.\nDescriptif du poste :\nNous recherchons un Data Engineer exp√©riment√© pour rejoindre notre √©quipe.\nEn tant que Data Engineer, vous serez responsable de la conception, du d√©veloppement et de la mise en ≈ìuvre de pipelines de traitement de donn√©es en temps r√©el √† grande √©chelle.\nVous travaillerez avec des technologies telles que Kafka, Flink, Kinesis et vous utiliserez les services du cloud AWS pour stocker et traiter les donn√©es.\nVos responsabilit√©s :\nUtiliser Kafka pour le traitement de flux de donn√©es en temps r√©el √† grande √©chelle, en travaillant avec les producteurs, les consommateurs et les topics.\nMettre en ≈ìuvre des pipelines de traitement de donn√©es en streaming avec Flink, en appliquant des transformations complexes et en g√©rant les √©tats.\n√âcrire du code efficace et maintenable en Java / Python pour manipuler et analyser les donn√©es en temps r√©el.\nUtiliser Kubernetes pour d√©ployer et g√©rer des applications conteneuris√©es √† grande √©chelle, en assurant la r√©silience et l‚Äô√©volutivit√© des services.\nUtiliser les services AWS tels que Amazon S3, AWS Lambda, Elastic Kubernetes Service (EKS), Elastic Container Service (ECS) et Elastic Compute Cloud (EC2) pour le stockage, le traitement et le calcul des donn√©es en temps r√©el.\nSuivre les meilleures pratiques pour une utilisation efficace du cloud, en assurant la gestion des co√ªts, la s√©curit√© des donn√©es et la disponibilit√© des services.\nCollaborer avec l‚Äô√©quipe de d√©veloppement logiciel et la gestion de projets pour assurer un flux de d√©veloppement fluide et une livraison efficace des fonctionnalit√©s.\nBon √† savoir :\nCDI / ASAP / Toulouse\nProfil recherch√©:\nNous recherchons un candidat dipl√¥m√© d'une grande √©cole d'Ing√©nieur avec une premi√®re exp√©rience.\nComp√©tences n√©cessaires :\nExp√©rience significative dans un environnement industriel en mode DevOps, avec des outils tels que CICD, gitlab, Jenkins, Sonar, Nexus, XLdeploy, Camunda, etc.\nMa√Ætrise des langages de programmation tels que Python, Java et expertise dans l‚Äô√©criture et l‚Äôoptimisation du code SQL\nMa√Ætrise du fran√ßais et bonne maitrise de l‚Äôanglais.\nCapacit√© √† travailler en √©quipe et esprit d‚Äô√©quipe.\nLe processus de recrutement se d√©roule en 3 entretiens :\nPrise de contact\n1er entretien : Pr√©sentation et projet du candidat + pr√©sentation MP DATA\n2√®me entretien : Entretien de qualification technique\n3√®me entretien : Rencontre avec les √©quipes dans les locaux MP DATA + Proposition de collaboration\nShow more\nShow less",
        "details": {
            "JobDetail": [],
            "TypeContract": "CDI",
            "Salary": "",
            "Level": "",
            "Experience": null
        },
        "title": "data engineer",
        "skills": {
            "ProgLanguage": [
                "Java",
                "Python"
            ],
            "DataBase": [
                "SQL"
            ],
            "BigData": [
                "Flink"
            ],
            "CloudComputing": [
                "AWS"
            ],
            "DevTools": [
                "Jenkins"
            ],
            "Automation": [
                "Kubernetes"
            ],
            "Containers": [
                "Kubernetes"
            ],
            "Other": [
                "Cloud",
                "DevOps"
            ],
            "EnSoftSkils": [
                "Collaboration"
            ]
        }
    },
    {
        "source": "LinkedIn",
        "company": "SEVETYS",
        "location": "Paris, √éle-de-France, France",
        "link": "https://fr.linkedin.com/jobs/view/data-engineer-at-sevetys-3905649273?position=55&pageNum=0&refId=3%2BsKCnzKBomYeuJjjsOexw%3D%3D&trackingId=Lf0jM8Rc3OE5oWaxmOH4DQ%3D%3D&trk=public_jobs_jserp-result_search-card",
        "description": "Sevetys, premier groupe fran√ßais de cliniques v√©t√©rinaires, est pr√©sent dans toute la France avec plus de 150 √©tablissements. Cr√©√© en 2016, le groupe souhaite moderniser le m√©tier et mettre la qualit√© des soins et la satisfaction client au c≈ìur de son projet.\nLe projet d‚Äôentreprise se caract√©rise par son hyper croissance et une culture de type start-up ax√©e sur le collectif, la coh√©sion, et l‚Äôengagement.\nFort de son succ√®s, Sevetys poursuit sa structuration et recrute un / une :\nData Engineer\n‚ÄãLe\nData Engineer\ntravaille en √©troite collaboration avec une √©quipe Agile pluridisciplinaire pour construire des pipelines de donn√©es de haute qualit√© permettant de mettre en ≈ìuvre des solutions analytiques. Ces solutions g√©n√®reront des informations √† partir de nos donn√©es collect√©es, permettant de faire progresser les capacit√©s de prise de d√©cision du management de l‚Äôentreprise. Ce r√¥le n√©cessite une compr√©hension approfondie de l'architecture des donn√©es, de l'ing√©nierie des donn√©es, de l'analyse des donn√©es, du reporting. Le candidat id√©al est un ing√©nieur en donn√©es/logiciel ayant au moins une premi√®re exp√©rience dans la cr√©ation de produits de donn√©es soutenant des solutions analytiques.\nMissions :\nCon√ßoit, d√©veloppe, optimise et maintient une architecture de donn√©es et des pipelines qui respectent les objectifs de l'entreprise ;\nR√©sout des probl√®mes de donn√©es afin de fournir des informations qui aident notre entreprise √† atteindre ses objectifs ;\nCr√©e des jeux de donn√©es pour les membres de l'√©quipe d'analyse afin d'am√©liorer leur productivit√© ;\nFavorise une culture du partage, de la r√©utilisation, de la stabilit√© de la conception √† l'√©chelle et de l'efficacit√© op√©rationnelle des donn√©es et des solutions analytiques ;\nContribue √† l'√©valuation, la mise en ≈ìuvre et le d√©ploiement d'outils et de processus √©mergents pour l'ing√©nierie des donn√©es analytiques afin d'am√©liorer notre productivit√© en tant qu'√©quipe ;\n√âlabore et met en ≈ìuvre des plans de communication/√©ducation sur les capacit√©s, les normes et les processus d'ing√©nierie des donn√©es analytiques ;\nTravaille en partenariat avec des analystes business et des architectes de solutions pour d√©velopper des architectures techniques pour les projets et initiatives strat√©giques de l'entreprise.\nExpertises techniques :\nExp√©rience du d√©veloppement de bases de donn√©es et d'une vari√©t√© de technologies de bases de donn√©es relationnelles ;\nExp√©rience des entrep√¥ts de donn√©es ;\nExpertise en SQL et en analyse de donn√©es ; ma√Ætrise Python ;\nId√©alement certifi√© des technologies BI du Cloud Azure (Synapse, Azure Data Factory, PurView) ;\nConnaissance de l'intelligence artificielle, des statistiques et/ou des math√©matiques appliqu√©es ;\nExp√©rience dans le d√©veloppement de solutions sur des services et infrastructures de cloud computing dans le domaine des donn√©es et de l'analyse ;\nExp√©rience du d√©ploiement de Power BI ;\nExp√©rience conceptuelle des donn√©es et de l'analyse, par exemple ETL, mod√©lisation dimensionnelle, outils de reporting, gouvernance des donn√©es, entreposage des donn√©es, donn√©es structur√©es et non structur√©es, qualit√© de donn√©es ;\nConnaissance CI/CD et GitLab fortement appr√©ci√©.\nExp√©rience agile / Digitale / gouvernance :\nPassionn√©(e) le d√©veloppement bas√© sur les donn√©es, la fiabilit√© et l'exp√©rimentation ;\nExp√©rience souhait√©e de travail au sein d'une √©quipe produit Agile collaborative ;\nConnaissance de la gouvernance de la donn√©e.\nSkills Individuels :\nMotiv√©(e) et dot√©(e) de solides comp√©tences en mati√®re de r√©solution de probl√®mes et d'apprentissage ;\nFlexibilit√© face aux changements d'orientation du travail au fur et √† mesure de l'√©volution du projet ;\nExcellentes capacit√©s de communication, d'√©coute et de persuasion.\nAttitude attendue :\nSens aigu des chiffres, curiosit√© intellectuelle et volont√© d'adapter sa position sur la base d'informations compl√©mentaires ;\nForte √©thique de travail ; capacit√© √† travailler √† un niveau abstrait et √† obtenir un consensus.\nInformations suppl√©mentaires :\nPoste √† pourvoir d√®s que possible ;\nRemboursement des frais de transports + Mutuelle ;\nPossibilit√© de t√©l√©travail jusqu'√† un jour par semaine.\nShow more\nShow less",
        "details": {
            "JobDetail": [],
            "TypeContract": "",
            "Salary": "",
            "Level": "",
            "Experience": null
        },
        "title": "data engineer",
        "skills": {
            "ProgLanguage": [
                "Python"
            ],
            "DataBase": [
                "SQL"
            ],
            "DataVisualisation": [
                "Power BI"
            ],
            "CloudComputing": [
                "Azure"
            ],
            "Other": [
                "Statistiques",
                "Cloud",
                "CI/CD"
            ],
            "EnSoftSkils": [
                "Communication",
                "Collaboration"
            ]
        }
    },
    {
        "source": "LinkedIn",
        "company": "Akkodis",
        "location": "Lille",
        "link": "https://fr.linkedin.com/jobs/view/data-engineer-h-f-at-akkodis-3890779946?position=56&pageNum=0&refId=3%2BsKCnzKBomYeuJjjsOexw%3D%3D&trackingId=utcB03oN0vsGUS9G8IIHTw%3D%3D&trk=public_jobs_jserp-result_search-card",
        "description": "La ligne de service Consulting & Solutions d‚ÄôAkkodis France renforce ses √©quipes en r√©gion Hauts-de-France et recrute un\nData engineer H/F\nen\nCDI\nsur la\nm√©tropole lilloise\n:\nDescription de la mission :\nConcevoir, mettre en oeuvre et maintenir des pipelines de donn√©es efficaces et √©volutifs dans un environnement cloud (comme AWS, Azure, Google Cloud Platform‚Ä¶)\nAssurer la qualit√© des donn√©es et des mod√®les\nD√©finir les bonnes pratiques de d√©veloppement en impl√©mentant des outils de CI/CD\nAssurer une veille technologique sur les technologies Cloud\nCapacit√© √† interagir avec des parties prenantes diverses : business analyst, architecte, m√©tier‚Ä¶\nVeiller au bon fonctionnement des pipelines en production\nProfil :\nDe formation\nBac +4/5 en informatique\nou issu d'une\n√©cole d'ing√©nieur\n, vous poss√©dez une exp√©rience de\n3 ans\nminimum en tant que data engineer ainsi que les comp√©tences suivantes :\nUne bonne connaissance des √©cosyst√®mes li√©s √† la data (Kafka, ETL, base de donn√©es‚Ä¶)\nUne premi√®re exp√©rience sur un cloud provider (AWS, Azure, GCP)\nUne bonne maitrise de langages de programmation tels que SQL, Python, Scala\nAkkodis accompagne ses clients dans la mondialisation de leurs projets, aussi un anglais courant est requis pour l‚Äôensemble de nos collaborateurs.\nProcessus de recrutement :\nUne charg√©e de recrutement vous contacte pour √©changer sur votre projet professionnel\nVous √©changez ensuite avec un.e manager sur les aspects techniques, les projets\nChez Akkodis nous sommes convaincus que de l‚Äôintelligence collective na√Æt le succ√®s. Il n‚Äôexiste pas qu‚Äôun mod√®le, nous valorisons l‚Äôagilit√© et l‚Äôexcellence, l‚Äôaudace et la cr√©ativit√©.\nEt si nous parlions ensemble de vos ambitions pour les prochaines ann√©es ?\nAkkodis est une entreprise handi-engag√©e et inclusive. Tous nos postes sont ouverts aux handicaps et √† la diversit√©. Tous diff√©rents, tous comp√©tents !\nAkkodis, est un acteur mondial de l‚Äôing√©nierie et de l‚ÄôIT et un leader dans la smart industrie. Nous accompagnons nos clients dans leurs projets de transformation digitale via 4 lignes de service : Consulting, Solutions, Talent et Academy. Akkodis est un partenaire technologique de confiance pour ses clients √† l‚Äô√©chelle internationale. Nous co-cr√©ons et nous imaginons des solutions de pointe pour r√©pondre aux d√©fis majeurs de notre soci√©t√©, qu'il s'agisse d'acc√©l√©rer la transition √©nerg√©tique et de d√©velopper la mobilit√© verte, ou encore de construire des approches centr√©es sur les utilisateurs.\nDot√©s d‚Äôune forte culture de l‚Äôinclusion et de la diversit√©, nos 50 000 experts en IT et en ing√©nierie, pr√©sents dans 30 pays, allient les meilleures comp√©tences technologiques √† une connaissance transverse de toutes les industries pour fa√ßonner un futur plus durable. Nous sommes passionn√©s par l‚Äôid√©e d‚Äôinventer ensemble un avenir meilleur.\nAkkodis en France, ce sont pr√®s de 9.000 experts en IT et en ing√©nierie r√©partis sur l'ensemble du territoire, des collaborateurs partageant des valeurs fortes d'honn√™tet√©, de respect, d'√©quit√© et d'inclusion. Notre engagement : leur permettre au quotidien d'√™tre eux-m√™mes au travail, et acteurs de leur vie et de leur d√©veloppement au sein d'Akkodis.\n*Akkodis est une marque commerciale sous laquelle les entit√©s AKKA et Modis op√®rent\nShow more\nShow less",
        "details": {
            "JobDetail": [],
            "TypeContract": "CDI",
            "Salary": "",
            "Level": "",
            "Experience": "3 an(s)"
        },
        "title": "data engineer",
        "skills": {
            "ProgLanguage": [
                "Scala",
                "Python"
            ],
            "DataBase": [
                "SQL"
            ],
            "CloudComputing": [
                "GCP",
                "AWS",
                "Google Cloud Platform",
                "Azure"
            ],
            "Other": [
                "Cloud",
                "CI/CD"
            ]
        }
    },
    {
        "source": "LinkedIn",
        "company": "FINAXYS",
        "location": "Paris, √éle-de-France, France",
        "link": "https://fr.linkedin.com/jobs/view/data-engineer-python-at-finaxys-3887107285?position=57&pageNum=0&refId=3%2BsKCnzKBomYeuJjjsOexw%3D%3D&trackingId=8PYxM2n53IXQxAe8yjEkSw%3D%3D&trk=public_jobs_jserp-result_search-card",
        "description": "LE CONTEXTE\nLeader en\nIT\n, dans les domaines Banque\n,\nFinance\net\nAssurance\n,\nFinaxys\nest un cabinet de\nconseil\ncr√©√© en 2008. Nous accompagnons au quotidien les plus grandes banques du pays sur leur\ntransformation digitale\n(BNP Paribas, Soci√©t√© G√©n√©rale, Cr√©dit Agricole, Natixis, etc.)\nNos clients bancaires travaillent √©galement dans des contextes Big Data sur des applications centrales rattach√©es aux Datalakes.\nLES MISSIONS\nD√©veloppement et traitements sur des applications Big Data (Python)\n√ätre force de proposition sur les choix techniques les plus pertinents\nMaintenir la qualit√© des solutions, mesure de cette qualit√©, alerte sur les non-conformit√©s et validation des solutions d√©finitives.\nAnalyser des risques li√©s aux solutions envisag√©es et proposition des actions de rem√©diation.\nApporter des solutions IT r√©pondant au mieux aux besoins du business port√© par la/le Product Owner (M√©tiers/Fonctions) en cherchant toujours la maximisation de la valeur g√©n√©r√©e\nAccompagner les √©quipes dans les migrations Cloud\nENVIRONNEMENT TECHNIQUE\nPython\nPandas\nScirpting Big Data\nCulture DevOps (Jenkins, Maven, Ansible)\nPROFIL\nComp√©tences Techniques et Fonctionnelles requises\nMaitrise obligatoire de l‚Äôanglais\nShow more\nShow less",
        "details": {
            "JobDetail": [],
            "TypeContract": "",
            "Salary": "",
            "Level": "",
            "Experience": null
        },
        "title": "data engineer",
        "skills": {
            "ProgLanguage": [
                "Python"
            ],
            "DataAnalytics": [
                "Pandas"
            ],
            "DevTools": [
                "Jenkins"
            ],
            "Automation": [
                "Ansible"
            ],
            "Other": [
                "Cloud",
                "Big Data",
                "DevOps"
            ]
        }
    },
    {
        "source": "LinkedIn",
        "company": "Apside",
        "location": "Nantes, Pays de la Loire, France",
        "link": "https://fr.linkedin.com/jobs/view/data-engineer-at-apside-3909772916?position=58&pageNum=0&refId=3%2BsKCnzKBomYeuJjjsOexw%3D%3D&trackingId=njzYBPoccfJwy9kiqugRwg%3D%3D&trk=public_jobs_jserp-result_search-card",
        "description": "Offre d'Emploi : DATA ENGINEER H/F chez Apside\nDescription du poste :\nNous sommes √† la recherche d'un Data Engineer passionn√© pour rejoindre notre √©quipe dynamique. Si vous avez une expertise dans le Big Data, la Data Science, l'analyse de donn√©es et l'architecture de donn√©es, cette opportunit√© est faite pour vous. Int√©grer notre communaut√© Data, c‚Äôest l‚Äôassurance de progresser, innover, partager, vous certifier et rendre service √† nos clients.\nVos missions :\nD√©veloppement des jobs Spark pour la collecte et la transformation des donn√©es comptables disponibles dans les bucket S3.\nOptimisation des jobs Spark.\nD√©veloppement des batchs Java et √©criture des donn√©es au formats comptables.\n√âcriture et ordonnancement des DAGs Airflow.\nSupport du d√©veloppement Spark Scala.\nMaintenance applicative.\nProduction des √©v√©nements d√©di√©s √† la plateforme de donn√©es.\n.\nVotre r√¥le, vos comp√©tences :\nVous ma√Ætrisez au minimum un langage de programmation appliqu√© √† l‚Äôanalyse de donn√©es (SQL, Scala, Python, Java).\nVous √™tes passionn√© par le Big Data et le Machine Learning.\nVous concevez et mettez en ≈ìuvre des strat√©gies s√©curis√©es d'acquisition et d'int√©gration de donn√©es.\nVous configurez des r√©f√©rentiels de donn√©es √† la pointe de la technologie dans des environnements distribu√©s, majoritairement dans le cloud (Google Cloud Platform, Azure, AWS) et/ou en environnement Hadoop (distribution MapR, Cloudera, Hortonworks).\nEnvironnement technique :\nSQL\nPython/Spark\nCloud AWS: AWS Glue, AWS Lambda (possibilit√© de vous former sur AWS)\nStockage objet (AWS S3)\nOrchestration et scheduling de t√¢ches (Apache Airflow)\nBases analytiques et bases NoSQL (ElasticSearch, AWS Athena)\nVotre profil :\nFort de 4 ann√©es d‚Äôexp√©rience en Data Engineer/ DATA ANALYST\nTitulaire d‚Äôune formation sup√©rieure IT.\nCapacit√© √† s‚Äôint√©grer dans un cadre technique client tout en √©tant √† m√™me de proposer des pistes d‚Äôam√©liorations pertinentes.\nAutonome dans la gestion des projets.\nCurieux et impliqu√©, vous √™tes bon communicant avec les clients et les acteurs de culture technique diff√©rente.\nDe bonnes raisons de rejoindre Apside ?\nUn esprit start-up avec la stabilit√© d‚Äôun grand groupe, qui favorise l‚Äôagilit√©, le travail d‚Äô√©quipe et la proximit√©. Alors qu‚ÄôApside ne cesse d‚Äôagrandir sa famille d√©j√† forte de plus de 3000 consultants, nous sommes √† la recherche de nos nouveaux talents !\nCDI + package salarial avantageux (Mutuelle offerte, RTT, Tickets Restaurant, Int√©ressement ...)\nParticipez et animez nos soir√©es techniques (Project Lab, Test Lab‚Ä¶),\nDevenez speaker (Devoxx, DevFest, NCraft‚Ä¶),\nFormez vous avec l‚ÄôAcademy By Apside (e-learning, formation, certification).\nD√©veloppez votre r√©seau (Soir√©es trimestrielles, Afterwork, Soir√©es d‚Äôint√©gration‚Ä¶),\nInt√©grez notre Communaut√©s d‚ÄôExperts et testez les derni√®res innovations techniques sur notre Bac √† Sable !\nApside s‚Äôengage en faveur de l‚Äôemploi des personnes en situation de handicap avec sa filiale Apsid‚ÄôEA : 1√®re entreprise adapt√©e totalement int√©gr√©e √† une ESN !\nPour aller plus loin avec APSIDE !\nhttps://www.apside.com/fr/nos-offres-emploi/?_joboffer-agency=17833&_paged=2\nCe poste de DATA ENGINEER est fait pour vous !\nShow more\nShow less",
        "details": {
            "JobDetail": [],
            "TypeContract": "CDI",
            "Salary": "17833",
            "Level": "",
            "Experience": null
        },
        "title": "data engineer",
        "skills": {
            "ProgLanguage": [
                "Java",
                "Scala",
                "Python"
            ],
            "DataBase": [
                "Elasticsearch",
                "SQL",
                "NoSQL"
            ],
            "BigData": [
                "Hadoop",
                "Apache Airflow",
                "Spark"
            ],
            "CloudComputing": [
                "AWS",
                "Google Cloud Platform",
                "Azure"
            ],
            "Automation": [
                "Airflow"
            ],
            "Other": [
                "Machine Learning",
                "Cloud",
                "Big Data"
            ]
        }
    },
    {
        "source": "LinkedIn",
        "company": "AXA en France",
        "location": "Hauts-de-Seine, √éle-de-France, France",
        "link": "https://fr.linkedin.com/jobs/view/data-engineer-senior-at-axa-en-france-3884386043?position=59&pageNum=0&refId=3%2BsKCnzKBomYeuJjjsOexw%3D%3D&trackingId=jYXbX2rDlEmATeFHwBpbng%3D%3D&trk=public_jobs_jserp-result_search-card",
        "description": "Environnement\nEn tant que\nSenior Data Engineer F/H\n, vous allez contribuer directement aux projets des directions m√©tier (ex : fraude sant√©, multi√©quipements, pricing IARD, optimisation du lead management, fragilit√© auto, ‚Ä¶) d‚ÄôAXA France et √† la construction du socle technique Big Data.\nVous allez int√©grer une √©quipe d'une dizaine de personne compos√©e de Data Engineer et des Tech Lead travaillant en mode Feature Team au sein des tribus m√©tier de la Direction Transformation Digital Tech et DATA (DT2).\nLa Direction Transformation Digital Tech et DATA d'AXA France en quelques mots :\n- Une organisation agile en feature teams : tribus, guildes, squads\n- Des projets sur des applications innovantes √† fort trafic (web, mobile‚Ä¶)\n- Des m√©thodologies craft (TDD, BDD, clean code, code review‚Ä¶) et DevOps\n- Une communaut√© de partage de bonnes pratiques (BBL, dojo, meetup, conf‚Ä¶)\nVotre r√¥le et vos missions\nVous aurez pour missions principales de d√©velopper les projets Big Data demand√©s par le m√©tier, et notamment :\nPasser de la donn√©e brute √† de la donn√©e exploitable, expos√©e sous forme de tables requ√™tables dans le datalake\nConsolider ces donn√©es au fur et √† mesure de leur alimentation r√©currente dans le data lake\nLes exploiter pour atteindre la finalit√© business (exposition de business view, r√©int√©gration des r√©sultats dans le SI, service de scoring, ‚Ä¶)\nDe travailler √† la cr√©ation du socle technique Big Data et industrialiser le cycle de d√©veloppement de l'√©quipe\nDe mettre en place et de garantir le respect dans la dur√©e d'un processus qualit√© sur l'ensemble du cycle de DEV (documents, tests unitaires / int√©gration / fonctionnels, commentaires, versionning, etc.)\nVotre profil\nVous justifiez de plusieurs exp√©riences significatives (+ de 5 ans) sur du\nd√©veloppement big data, en particulier sur du PySpark.\nComp√©tences techniques :\nConnaissances avanc√©es en d√©veloppement en\nPySpark\n(Spark avec le langage Python)\nMaitrise de l'environnement\nMicrosoft Azure\nConnaissances avanc√©es d'outils de BI comme\nPowerBI\nComp√©tences transverses :\nCapacit√© √† interagir avec des parties prenantes diverses : Business analyst, Architectes, M√©tier\nExp√©rience en mode de delivery Agile (Scrum, Kanban, etc...)\nDriver et accompagner des Data Engineer junior sur les aspects technique\nEt Id√©alement :\nDes Connaissances sur Azure DevOps, Azure Pipeline, GIT, JIRA\nMaitrise des Traitements Big Data en mode Streaming\nMaitrise des Bases de donn√©es relationnelles et NoSQL\nUne exp√©rience professionnelle avec des outils comme Azure Databricks, Azure Data Lake Storage ou encore Azure Data Factory\nQui sommes nous ?\nAXA est un des leaders de l‚Äôassurance et de la gestion d‚Äôactifs dans le monde.\nNous aidons nos 108 millions de clients √† traverser les petites et grandes difficult√©s de la vie.\nChaque jour, nous agissons ensemble pour inventer la meilleure mani√®re de les prot√©ger et voulons donner √† chacun les moyens de vivre une vie meilleure.\nUn challenge qui donne le sourire et envie de se lever le matin !\nChez AXA, nous sommes persuad√©s que pour bien prendre soin de nos clients, nous devons commencer par bien prendre soin de nos collaborateurs. C‚Äôest pour cette raison que nous menons une politique RH engag√©e qui favorise la diversit√©, qui pr√©serve l‚Äô√©quilibre vie priv√©e-vie professionnelle et acc√©l√®re le d√©veloppement des comp√©tences et des carri√®res.\nAinsi, en rejoignant AXA France vous travaillerez dans une entreprise responsable, offrant une v√©ritable culture d‚Äôexpertise, acc√©l√©rant le d√©veloppement des comp√©tences de chacun et proposant une r√©mun√©ration attractive.\nPourquoi nous rejoindre ?\nVous √™tes porteur d‚Äôid√©es et d‚Äôinitiatives innovantes ? Vous proposez des solutions et √™tes au service du client ? Faites partie de notre grande famille en rejoignant\nUn leader mondial offrant des opportunit√©s de carri√®res int√©ressantes\nUne entreprise qui donne une place de choix √† l‚Äôinnovation, √† l‚Äôinitiative et aux actions solidaires (notamment via l‚Äôassociation AXA Atout C≈ìur)\nUn environnement inclusif √† tous les niveaux (mixit√©, handicap, initiatives pour favoriser l‚Äôinsertion des jeunes, orientation sexuelle, etc.)\nUn acc√®s √† de multiples avantages (cong√©s, temps partiel, t√©l√©travail, etc.)\nUn cadre stimulant, qui permet de rencontrer des collaborateurs performants et d‚Äôenrichir ses comp√©tences\nVictime ou t√©moin, en cas de discrimination, vous pouvez adresser vos signalements et/ou alertes discrimination √† alerte.discrimination.harcelement@axa.fr\nShow more\nShow less",
        "details": {
            "JobDetail": [
                "Junior",
                "Senior"
            ],
            "TypeContract": "",
            "Salary": "",
            "Level": "",
            "Experience": "5 an(s)"
        },
        "title": "data engineer",
        "skills": {
            "ProgLanguage": [
                "Python"
            ],
            "DataBase": [
                "NoSQL"
            ],
            "BigData": [
                "Databricks",
                "Spark"
            ],
            "CloudComputing": [
                "Azure"
            ],
            "DevTools": [
                "Git"
            ],
            "Collaboration": [
                "Teams",
                "JIRA"
            ],
            "Other": [
                "Big Data",
                "DevOps"
            ],
            "EnSoftSkils": [
                "Initiative"
            ]
        }
    },
    {
        "source": "LinkedIn",
        "company": "Beelix",
        "location": "Paris, √éle-de-France, France",
        "link": "https://fr.linkedin.com/jobs/view/data-engineer-at-beelix-3865239426?position=60&pageNum=0&refId=3%2BsKCnzKBomYeuJjjsOexw%3D%3D&trackingId=fIAQGZ8QGGFUOJnyjmSu2g%3D%3D&trk=public_jobs_jserp-result_search-card",
        "description": "Qui sommes-nous ?\nDepuis 2016, nous accompagnons nos clients sur des probl√©matiques de Product Management, Data et Design Thinking. Beelix contribue √† fa√ßonner le monde de demain en participant aux grandes avanc√©es des secteurs suivants:\nüöóAutomobile\n‚ö°Energie\nüì°M√©dias & T√©l√©coms\nüëóLuxe & Retail\nüí∂ Banque, Finance & Assurance\n‚úàÔ∏èD√©fense\nAujourd‚Äôhui, Beelix compte plus de 200 collaborateurs motiv√©s et dynamiques. Lab√©lis√©e Great Place To work en 2023, Beelix est aussi une entreprise engag√©e o√π il fait bon vivre.\nDans le cadre de notre d√©veloppement, nous recherchons un Data Engineer en √éle-de-France.\nQuelles missions au quotidien ?\nVous aurez pour missions principales de d√©velopper les projets Big Data demand√©s par le m√©tier, et notamment :\nPasser de la donn√©e brute √† de la donn√©e exploitable, expos√©e sous forme de tables requ√™tables dans le Datalake\nConsolider ces donn√©es au fur et √† mesure de leur alimentation r√©currente dans le Datalake\nLes exploiter pour atteindre la finalit√© business (exposition de Business View, r√©int√©gration des r√©sultats dans le SI, service de scoring, ‚Ä¶)\nDe mettre en place et de garantir le respect dans la dur√©e d'un processus qualit√© sur l'ensemble du cycle de DEV (documents, tests unitaires / int√©gration / fonctionnels, commentaires, versionning, etc.)\nAccompagner les Data Engineers sur son p√©rim√®tre pour garantir la qualit√© des livrables\nExpertise souhait√©e\nExpertise en SPARK et PySpark\nExpertise sur Databricks\nUne exp√©rience sur un cloud provider public comme Azure (id√©alement), AWS, ou GCP\nConnaissances avanc√©es d'outils de BI comme PowerBI (id√©alement) ou Spotfire\nCapacit√© √† interagir avec des parties prenantes diverses : Business analyst, Architectes, M√©tier\nEtre expert dans les pratiques du Software Craftsmanship (Test Driven Development, Behavior Driven Development, Clean Code, Code Reviews, etc.)\nDes Connaissances sur Azure DevOps, Azure Pipeline, GIT\nMaitrise des Traitements Big Data en mode Streaming\nMaitrise des Bases de donn√©es relationnelles et NoSQL\nUne exp√©rience professionnelle avec des outils comme Azure Databricks, Azure Data Lake Storage ou encore Azure Data Factory\nA propos de vous ?\nDipl√¥m√© d'une √©cole d'ing√©nieurs ou √©quivalent\nAu moins 3 ans d'exp√©rience en tant que Data Engineer\nExp√©rience en mode de Delivery Agile (Scrum, Kanban, etc.‚Ä¶)\nVous avez un bon niveau d‚Äôanglais tant √† l‚Äô√©crit qu‚Äô√† l‚Äôoral\nPourquoi nous rejoindre ?\nUn suivi et un accompagnement au quotidien\nUn organisme de formation certifi√© Qualiopi, un abonnement linkedin learning pour chaque salari√© et des partenariats avec des sp√©cialistes pour d‚Äôautres expertises\nDe nombreux √©v√©nements : Afterworks, Communaut√©s m√©tiers, Happy talks‚Ä¶\nune Exp√©rience personnalis√©e bas√©e sur vos besoins gr√¢ce au Pr√©dictive Index\nNotre package ¬´ unBeelievable ¬ª : 100% du titre de transport, Tickets restaurants, CSE, Prime de participation ...\nNombreux √©v√®nements (afterworks, sport, etc) et des communaut√©s m√©tiers dynamiques\nLe processus de recrutement ?\n√âchange t√©l√©phonique (15 min)\nEntretien 1 RH pour apprendre √† vous conna√Ætre\nEntretien 2 avec votre futur N+1 pour appr√©hender la relation manag√©riale\nEntretien 3 avec un Responsable commercial pour avoir la vision strat√©gique\nShow more\nShow less",
        "details": {
            "JobDetail": [],
            "TypeContract": "",
            "Salary": "100",
            "Level": "",
            "Experience": "3 an(s)"
        },
        "title": "data engineer",
        "skills": {
            "DataBase": [
                "NoSQL"
            ],
            "BigData": [
                "Databricks",
                "Spark"
            ],
            "CloudComputing": [
                "GCP",
                "AWS",
                "Azure"
            ],
            "DevTools": [
                "Git"
            ],
            "Other": [
                "Cloud",
                "Big Data",
                "DevOps"
            ]
        }
    },
    {
        "source": "LinkedIn",
        "company": "EarthDaily Agro",
        "location": "Balma, Occitanie, France",
        "link": "https://fr.linkedin.com/jobs/view/data-engineer-at-earthdaily-agro-3883708013?position=1&pageNum=2&refId=ScAHuRnPnFA7sPESHrUwtg%3D%3D&trackingId=Ytwd%2FdNgDJIktwGUm2oPgA%3D%3D&trk=public_jobs_jserp-result_search-card",
        "description": "About Us\nEarthDaily Agro provides space age data and analytics to the organizations and people who feed the planet!\nWith 35 years of industry experience, EarthDaily Agro provides customers with the data, analysis and knowledge they need to make more efficient and effective decisions. B2B services range from global risk management and monitoring of agricultural commodities to the marketing of inputs and precision agriculture consulting, using the latest research in agronomy, information technologies and remote sensing.\nEarthDaily Agro also develops highly customized business solutions for agricultural lenders, insurers, input suppliers and food companies, with easy-to-use analytics, that help reduce the daily risks of agriculture.\nEarthDaily Agro is headquartered in Minneapolis, MN, USA, with offices in France, Brazil, Australia and Switzerland and is a division of EarthDaily Analytics Corp.\nEarthDaily Analytics Corp., a vertically-integrated data processing and analytics company, is launching a new constellation of earth observation satellites. The EarthDaily satellite constellation will significantly enhance geospatial analytics capabilities in agriculture, forestry, environment, financial services, and intelligence, among many other verticals.\nMain Job Tasks And Responsibilities\nAs a EarthDailyAgro Data Engineer, your primary responsibility will be to design, develop, and manage data pipelines and infrastructure specialized for geospatial and remote sensing applications. You will work closely with data scientists, geospatial analysts, remote sensing experts, software engineers, and DevOps teams to ensure the successful deployment and scaling of data pipeline to feed geospatial data machine learning models. Your role will be crucial in optimizing the geospatial machine learning ecosystem and ensuring the seamless integration of AI-driven geospatial solutions into real-world applications.\nYour Responsibilities Include\nCloud-based data pipeline Conceptualization, Development and Scaling: Build up pipeline to ingest large volumes of geospatial data, pre-process them and meet data scientists‚Äô requirements, in terms of accessibility, speed, format, quality.\nAutomation and CI/CD: Industrialization of pipeline deployment, orchestration, workflows, and versioning.\nCost & Speed Optimization: Collaborate with infrastructure team to develop, optimize, and fine-tune pipeline.\nCloud and Containerization: Experience with cloud platforms (e.g., AWS, Azure, GCP) and containerization tools.\nInfrastructure Management: Utilize containerization technologies and cloud-based services to set up and manage infrastructure, enabling seamless deployment and scalability.\nMonitoring and Anomaly Detection: Implement monitoring systems to track pipeline performance and identify anomalies.\nVersion Control and Data Version Control: Proficient with version control systems like Git and DVC.\nSecurity and Compliance: Ensure the security and privacy of geospatial data, adhering to relevant data protection regulations and industry best practices.\nCollaboration and Communication: Collaborate with interdisciplinary teams to integrate data pipeline into existing applications or develop new geospatial products.\nIssue Resolution and Troubleshooting: Identify and resolve promptly technical issues related to geospatial data processing, performance, or infrastructure.\nEducation, Knowledge And Abilities\nRequirements\nEducation: Master's degree in Computer Science, specialisation in Geomatics and/or Remote sensing would be a plus.\nExperience: 3+ years experiences with data pipeline processes and deployment is a must-have. Proven hands-on experience in setting up pipelines and data processes with opensource tools (e.g., MLFlow, Argo, Kubeflow) is desirable.\nProgramming Skills: Proficiency in Python and with data manipulation frameworks (e.g., dataframe, numpy, pandas, xarray, rasterio) and librairies (e.g., Dask).\nProblem-Solving Skills: Autonomous, and strong analytical and problem-solving abilities to address complex geospatial data and analysis challenges.\nCommunication Skills: Excellent communication and interpersonal skills to collaborate effectively with cross-functional teams and stakeholders.\nFrench mandatory (job based in France). Fluent in English (oral and written):‚ÄØmeetings with internal are mostly in‚ÄØEnglish.\nPreferred Additional Skills\nExperience with Earth Observation (EO) data analysis and processing.\nExperience with geospatial data formats (e.g., GeoTIFF, Shapefile, NetCDF).\nSpatial Analysis Techniques: Understanding of spatial analysis techniques and algorithms commonly used in geospatial data manipulation.\nRemote Sensing Integration: Knowledge of remote sensing data sources (e.g., STAC catalog, satellite imagery, LiDAR, SAR) integration into data pipelines for accurate and up-to-date geospatial analysis.\nCONDITIONS\nFull time job based in Balma, near Toulouse, France.\nFixed + Bonuses\nTR / \"Family\" insurance / CSE\nPowered by JazzHR\nWrfSXQ5YJg\nShow more\nShow less",
        "details": {
            "JobDetail": [
                "Remote",
                "Full"
            ],
            "TypeContract": "",
            "Salary": "",
            "Level": "",
            "Experience": null
        },
        "title": "data engineer",
        "skills": {
            "ProgLanguage": [
                "Python"
            ],
            "DataAnalytics": [
                "NumPy",
                "Pandas"
            ],
            "CloudComputing": [
                "GCP",
                "AWS",
                "Azure"
            ],
            "DevTools": [
                "Git"
            ],
            "Collaboration": [
                "Teams"
            ],
            "Other": [
                "Machine Learning",
                "Cloud",
                "DevOps",
                "CI/CD"
            ],
            "EnSoftSkils": [
                "Interpersonal Skills",
                "Communication",
                "Collaboration"
            ]
        }
    },
    {
        "source": "LinkedIn",
        "company": "Aubay",
        "location": "√éle-de-France, France",
        "link": "https://fr.linkedin.com/jobs/view/data-engineer-f-h-at-aubay-3573871076?position=2&pageNum=2&refId=ScAHuRnPnFA7sPESHrUwtg%3D%3D&trackingId=Z5Mewzr%2FSGPKfaqPEhLUvw%3D%3D&trk=public_jobs_jserp-result_search-card",
        "description": "Passionn√© par la Data, tu souhaites rejoindre une communaut√© d‚Äôexperts dans le domaine afin de d√©velopper tes comp√©tences en Data Engineering. Aubay renforce ses √©quipes Data et recherche des Data Engineers pour int√©grer des dispositifs de projets pointus et vari√©s.\nTon quotidien en tant que Data Engineer chez Aubay, :\nD√©finition de la strat√©gie de stockage et mise en ≈ìuvre des technologie appropri√©es (base de donn√©es SQL, NoSQL, stockage distribu√©,‚Ä¶)\nIngestion des donn√©es (structur√©es, semi-structur√©es ou non-structur√©es) selon diff√©rentes fr√©quences : batch, micro-batch ou temps r√©el\nConception et mise en ≈ìuvre de pipelines de donn√©es afin de fournir des donn√©es pr√™tes √† l‚Äôemploi aux consommateurs : uniformisation, mise en qualit√©, enrichissement, calcul d‚Äôindicateurs,‚Ä¶\nConception et d√©veloppement d‚ÄôAPI pour exposer les donn√©es aupr√®s d‚Äôapplications tierces\nAppui aux Data Scientists pour industrialiser et optimiser les algorithmes de Machine Learning\nPr√©paration et animation d‚Äôateliers de travail avec des interlocuteurs vari√©s : recueil/approfondissement des besoins m√©tiers, avancement/restitution des travaux, transfert de comp√©tences,‚Ä¶\nTon profil :\nTu dispose d‚Äôune formation niveau BAC+5 (Master 2 ou √©cole d‚Äôing√©nieur) sp√©cialis√©e en informatique\nTu as d√©j√† une premi√®re exp√©rience significative (a minima 2 ans) en Data Engineering sur des technologies Big Data\nLes technologies telles que Hadoop, Spark ou Kafka sont tes technologies de pr√©dilection\nLa programmation n‚Äôa plus de secret pour toi et tu maitrise parfaitement un ou plusieurs langages de programmation suivants : Java, Scala et Python\nTu ma√Ætrises les tenants et aboutissants de la philosophie DevOps et des outils orient√©s CI/CD\nTu es soucieux de la qualit√© et de la performance de tes d√©veloppements et tu t'int√©resse √† l‚Äôinnovation frugale\nTu es un expert technique dans ton domaine sans pour autant oublier l‚Äôimportance d‚Äôune communication orale et √©crite de qualit√© et adapt√©e √† chacun de tes interlocuteurs\nTu travaille au quotidien en mode agile et tu en maitrise les fondements\nCe qui nous caract√©rise :\nDes missions et projets dans le domaine du Data Engineering en nombre et dans des secteurs vari√©s (Banque, Assurance, Telecom, Industrie,‚Ä¶) qui permettent √† nos collaborateurs de monter en comp√©tences et de devenir des experts Data reconnus\nDe l‚Äôapprentissage en continu avec des formations et des certifications sur les technologies Data d‚Äôaujourd‚Äôhui et de demain\nDes experts Data mobilisables pour accompagner et soutenir techniquement les collaborateurs sur leurs projets\nDes communaut√©s de savoir-faire Data proposant de mani√®re r√©guli√®re aux collaborateurs d‚ÄôAubay du contenu et des √©v√®nements de partage (webinar, meetup/afterwork, BBL,‚Ä¶) sur les th√©matiques suivantes : Data Engineering, Data Viz, Data Science/IA, Data Platform & Architecture,‚Ä¶\nAubay encourage la diversit√© sous toutes ses formes et garantit l'√©galit√© des chances √† tous les candidats. Tous nos postes sont ouverts aux personnes en situation de handicap et nous proposons tous les am√©nagements n√©cessaires.\nTa carri√®re chez Aubay :\nTu auras la possibilit√© de d√©velopper et certifier tes comp√©tences sur les derni√®res technologies Data avec un focus fort sur les plateformes Data Cloud telles qu‚ÄôAzure Synapse Analytics, Google Cloud Platform, Snowflake et Databricks\nTu pourras rejoindre la BU d‚Äôexcellence Data et √©voluer au sein d‚Äôun environnement humain et professionnel de haut niveau. Tu profiteras d‚Äôun management sur-mesure pour t'accompagner dans ta trajectoire de carri√®re\nAu sein de la BU d‚Äôexcellence, de multiples perspectives s‚Äôoffriront √† toi :\nR√¥le de ¬´ Lead ¬ª : Vous pourrez gagner en responsabilit√© sur le plan technologique et devenir un r√©f√©rent aupr√®s de nos clients et des collaborateurs de la communaut√© Data Engineering\nR√¥le de ¬´ Champion ¬ª : Vous repr√©senterez Aubay aupr√®s d‚Äôun ou plusieurs de nos partenaires √©diteurs strat√©giques et vous participerez activement √† l‚Äôanimation de la relation sur le plan technologique\nR√¥le de ¬´ Head ¬ª : Vous pourrez prendre la responsabilit√© du savoir-faire Data Engineering et de ses offres et en assurer le d√©veloppement au sens large (d√©veloppement business, recrutement, management de collaborateurs, d√©finition de la strat√©gie et animation de la communaut√© au sein du groupe Aubay,‚Ä¶)\nBesoin d‚Äôen savoir plus sur le processus de recrutement ?\nUn √©change macro au niveau RH avec Doriane\nUn entretien technique avec Marius ou Peter, deux de nos r√©f√©rents techniques\nUn √©change manag√©rial avec le Directeur de la BU Modern BI & Data\nA savoir que l‚Äôordre des √©tapes peut varier selon tes envies (ex : √©change manag√©rial avec l‚Äô√©change technique)\nAubay encourage la diversit√© sous toutes ses formes et garantit l'√©galit√© des chances √† tous les candidats. Tous nos postes sont ouverts aux personnes en situation de handicap et nous proposons tous les am√©nagements n√©cessaires.\nShow more\nShow less",
        "details": {
            "JobDetail": [],
            "TypeContract": "",
            "Salary": "",
            "Level": "Bac+5",
            "Experience": "2 an(s)"
        },
        "title": "data engineer",
        "skills": {
            "ProgLanguage": [
                "Java",
                "Scala",
                "Python"
            ],
            "DataBase": [
                "SQL",
                "NoSQL"
            ],
            "BigData": [
                "Databricks",
                "Hadoop",
                "Spark"
            ],
            "CloudComputing": [
                "Google Cloud Platform",
                "Azure"
            ],
            "DBMS": [
                "Snowflake"
            ],
            "Other": [
                "CI/CD",
                "Big Data",
                "Machine Learning",
                "Cloud",
                "DevOps"
            ],
            "EnSoftSkils": [
                "Communication"
            ]
        }
    },
    {
        "source": "LinkedIn",
        "company": "Air France",
        "location": "Provence-Alpes-C√¥te d'Azur, France",
        "link": "https://fr.linkedin.com/jobs/view/data-engineer-d%C3%A9veloppeur-big-data-%23-h-f-at-air-france-3900080172?position=3&pageNum=2&refId=ScAHuRnPnFA7sPESHrUwtg%3D%3D&trackingId=U19TyprNBrvh%2BroLfsfJ7g%3D%3D&trk=public_jobs_jserp-result_search-card",
        "description": "Description du poste\nIntitul√© du poste\nData Engineer / D√©veloppeur Big Data # H/F\nM√©tier\nSyst√®mes d'informations - D√©veloppement\nCat√©gorie socio-professionnelle\nCadre\nPr√©sentation du contexte\nVous avez peut-√™tre d√©j√† voyag√© avec nous, mais que connaissez-vous de nos m√©tiers et de la richesse des donn√©es qu‚Äôils g√©n√®rent au quotidien ? Comment le traitement et l‚Äôexploitation de ces donn√©es peut contribuer √† notre strat√©gie de Revenue Management, ou encore aux multiples op√©rations √† r√©aliser pour permettre √† un vol de partir √† l‚Äôheure ?\nAir France-KLM fait r√™ver 104 millions de passagers par an, en les emmenant vers plus de 250 destinations, gr√¢ce √† une flotte de plus de 500 appareils. Le Groupe emploie 80 000 collaborateurs partout dans le monde :les opportunit√©s sont vastes pour mettre √† profit ses comp√©tences, apprendre et se d√©velopper !\nLe d√©partement de d√©veloppement DATA, OR & AI d‚ÄôAir France, au sein de la direction des Syst√®mes d‚ÄôInformation, intervient dans toute la cha√Æne de captation et de traitement des donn√©es du groupe pour d√©livrer √† nos m√©tiers des solutions applicatives cl√©s en main.\nLe d√©partement est √©galement en charge de l‚Äôensemble des outils techniques (ETL, DataLakes, DataWarehouses, Data visualisation) et du d√©veloppement des talents et comp√©tences de Data Engineering.\nNotre mission ? Transformer la donn√©e brute en d√©cision intelligente, pour mieux optimiser les m√©tiers d‚ÄôAir France ‚Äì KLM !\nPour cela, nous avons chacun un r√¥le essentiel √† jouer, pourquoi le v√¥tre ne serait pas celui de Data Engineer et de d√©veloppeur Big Data ?\nDescription de la mission\nAu sein de notre d√©partement, vous travaillerez main dans la main avec d‚Äôautres Data Engineers et d√©veloppeurs Big Data ainsi qu‚Äôavec des sp√©cialistes des m√©tiers.\nInt√©gr√© au sein d‚Äôune product team agile passionn√©e et dynamique :\nVous participez √† l‚Äôanalyse des besoins m√©tiers du commercial, des op√©rations a√©riennes, de l‚Äôexploitation sol en a√©roport, de la maintenance a√©ronautique ou encore du Cargo.\nVous contribuez √† la d√©finition, au d√©veloppement, √† l‚Äôindustrialisation et √† la maintenance d‚Äôapplications Big Data ou en Business Intelligence\nVous pr√©sentez la restitution de vos travaux et accompagnez les utilisateurs d‚Äôun point de vue fonctionnel ou m√©thodologique\nVous serez en contact avec les directions m√©tier du groupe Air France KLM.\nNous attachons beaucoup d'importance au d√©veloppement des comp√©tences de nos collaborateurs ainsi qu‚Äô√† leur offrir des conditions de travail favorables √† l‚Äôautonomie et aux missions √† forte valeur ajout√©e. L'ouverture, le respect, la bienveillance et le partage sont des valeurs humaines port√©es par l'entreprise.\nProfil recherch√©\nVous √™tes dipl√¥m√© de niveau Master ou Ing√©nieur dans les domaines informatiques, vous avez acquis une exp√©rience professionnelle dans le d√©veloppement d‚Äôapplications.\nVous disposez d‚Äôune exp√©rience du d√©veloppement indispensable en Backend / Java\nVous ma√Ætrisez les bases de donn√©es relationnelles et le langage SQL\nEn Compl√©ment, Vous Avez Une Connaissance Ou Une Exp√©rience Dans Tout Ou Partie Des Concepts Ou Outils Suivants\nEnvironnement Big Data (Spark, Hadoop, Elasticsearch, Kafka, ...)\nBase de donn√©es noSQL (MongoDB, HBase, REDIS) ou Data Warehouse Teradata\nOutil de Datavisualisation (Spotfire, PowerBI, Qlik ou Kibana)\nSolutions de Cloud (GCP) et hybride (GCP / AZURE)\n(Ces comp√©tences compl√©mentaires ou manquantes pouvant aussi s'acqu√©rir √† travers un parcours de reskilling et de formations aux outils du data engineering dispens√© en interne).\nVous avez particip√© √† des projets organis√©s en Scrum ou Kanban, et avez peut-√™tre m√™me ≈ìuvr√© comme Scrum-Master, ce qui vous permettra de vous int√©grer ais√©ment au sein d‚Äôune Product Team. Votre esprit de synth√®se, votre force de conviction et votre ma√Ætrise de la communication facilitent les d√©cisions avec l‚Äôensemble des collaborateurs de l‚Äô√©quipe, √©ventuellement en langue anglaise, √† l‚Äô√©crit comme √† l‚Äôoral.\nVous √™tes autonome, rigoureux(se), responsable et curieux(se), vous aimez travailler en √©quipe. Vous poss√©dez de bonnes capacit√©s d'√©coute, d'analyse, de synth√®se et de communication.\nEt bien s√ªr, vous √™tes passionn√©(e), enthousiaste et ing√©nieux(se)\nCe que nous vous offrons\nDe la cr√©ation de valeur pour l‚Äôensemble des m√©tiers d‚ÄôAir France KLM\nDes challenges et probl√©matiques complexes √† r√©soudre\nL‚Äôopportunit√© de d√©ployer des solutions Data industrielles √† l‚Äô√©chelle !\nUne grande part de responsabilit√© dans une structure hi√©rarchique horizontale\nUn important degr√© de libert√© pour apprendre et d√©velopper son expertise au sein de l‚Äô√©quipe\nOn vous attend le plus rapidement possible ! Et pour une dur√©e ind√©termin√©e ;)\nType de contrat\nCDI\nTemps partiel possible\nNon\nType d'horaires\nAdministratif\nProfil candidat\nNiveau d'√©tudes min. requis\nBac + 5 et plus\nLangue\nAnglais (4 - Confirm√© / C1)\nLocalisation du poste\nLocalisation du poste\nFrance, Provence-Alpes-C√¥te d'Azur, Alpes Maritimes (06)\nSite\nValbonne\nShow more\nShow less",
        "details": {
            "JobDetail": [
                "Hybride",
                "Confirm√©"
            ],
            "TypeContract": "CDI",
            "Salary": "",
            "Level": "",
            "Experience": null
        },
        "title": "data engineer",
        "skills": {
            "ProgLanguage": [
                "Java"
            ],
            "DataBase": [
                "MongoDB",
                "HBase",
                "Elasticsearch",
                "SQL",
                "NoSQL"
            ],
            "BigData": [
                "Hadoop",
                "Spark"
            ],
            "CloudComputing": [
                "GCP",
                "Azure"
            ],
            "SoftBigDataProcessing": [
                "HBase"
            ],
            "Other": [
                "Cloud",
                "Big Data"
            ],
            "EnSoftSkils": [
                "Communication"
            ]
        }
    },
    {
        "source": "LinkedIn",
        "company": "WA.Technology",
        "location": "Crouseilles, Nouvelle-Aquitaine, France",
        "link": "https://fr.linkedin.com/jobs/view/junior-data-engineer-at-wa-technology-3908458326?position=4&pageNum=2&refId=ScAHuRnPnFA7sPESHrUwtg%3D%3D&trackingId=i6ZV0xp3%2B13c2YxX5xinEQ%3D%3D&trk=public_jobs_jserp-result_search-card",
        "description": "WA.Technology\nis a B2B supplier of iGaming solutions with rapidly growing clients and partnerships in emerging markets. We offer a state-of-the-art iGaming platform, turnkey solutions, and standalone products that empower operators to enter or expand into emerging markets quickly and easily.\nThe WA.Platform is a fully scalable and customisable solution, featuring over 75 game providers, 6,400+ games, and support for multiple currencies, along with access to over 80 payment methods. WA. Technology enables operators to build their own casino, sportsbook, lottery, fantasy, or poker business precisely as they envision it.\nAbout The Role,\nWe are seeking a highly skilled and motivated\nData Engineer\nto design, implement, and maintain efficient and scalable data pipelines on the Google Cloud Platform (GCP). In this role, you will be responsible for managing data from MariaDB and Kafka sources, ensuring seamless integration into BigQuery, our primary data destination. Collaboration with cross-functional teams is crucial to understanding and meeting diverse data needs.\nIn this role, you will need to:\nDesign, implement, and maintain robust data pipelines on Google Cloud Platform.\nIntegrate MariaDB and Kafka as primary data sources for seamless data flow into BigQuery.\nCollaborate across departments to address unique data requirements aligned with organizational goals.\nUtilize Dataflow and Dataform for efficient data processing and transformation.\nEnsure data integrity through rigorous validation and cleansing processes.\nOptimize cloud-based infrastructure for speed and scalability.\nImplement monitoring tools for proactive system performance tracking and issue resolution.\nProvide ongoing support for data integrity and availability.\nMaintain comprehensive documentation of data architecture, updating regularly.\nStay informed about the latest data technology trends.\nEvaluate and recommend new technologies/methodologies to enhance processing and analysis capabilities.\nWhat are the key experience and personal attribute requirements?\nBachelor's degree in Computer Science, Information Technology, or a related field.\n2+ Hands-on experience relational database\nProven experience in developing data pipelines and ETL processes.\nStrong SQL skills.\nKnowledge of data modeling and database design.\nExcellent collaboration and communication skills.\nStrong problem-solving and troubleshooting abilities.\nAbility to work independently and as part of a team.\nContinuous learner, keeping up with emerging trends in data engineering.\nWhat are some of the benefits of working at WA Technology?\n100% remote opportunity\nFlexible work environment\nAttractive remuneration package\nOpportunity to work with well-connected industry leaders.\nA leadership approach that fosters innovation, creativity, and trust.\nOpportunity to experience the buzz of highly driven and motivated work colleagues.\nExperience a start-up feel in a fast-paced growth-driven environment.\nShow more\nShow less",
        "details": {
            "JobDetail": [
                "Remote",
                "Full"
            ],
            "TypeContract": "",
            "Salary": "Package",
            "Level": "",
            "Experience": null
        },
        "title": "data engineer",
        "skills": {
            "DataBase": [
                "SQL"
            ],
            "CloudComputing": [
                "GCP",
                "Google Cloud Platform"
            ],
            "DBMS": [
                "BigQuery"
            ],
            "Collaboration": [
                "Teams"
            ],
            "Other": [
                "Cloud"
            ],
            "EnSoftSkils": [
                "Creativity",
                "Leadership",
                "Communication",
                "Collaboration"
            ]
        }
    },
    {
        "source": "LinkedIn",
        "company": "iPepperGroup",
        "location": "Valbonne, Provence-Alpes-C√¥te d'Azur, France",
        "link": "https://fr.linkedin.com/jobs/view/data-engineer-h-f-at-ipeppergroup-3894091360?position=5&pageNum=2&refId=ScAHuRnPnFA7sPESHrUwtg%3D%3D&trackingId=dD9us48XNutKivZNI9mbOQ%3D%3D&trk=public_jobs_jserp-result_search-card",
        "description": "iPepper recrute pour l'un de ses clients une PME √©diteur de logiciel dans le domaine du voyage, un\nData Engineer (H/F)\npassionn√©(e) et exp√©riment√©(e) pour rejoindre une √©quipe dynamique.\nEn tant qu'Ing√©nieur(e) Data, vous serez en charge d'extraire et de transformer des donn√©es, de construire et d'optimiser des pipelines de donn√©es, ainsi que de concevoir des visualisations de donn√©es intuitives et informatives.\nResponsabilit√©s :\nConcevoir, construire et maintenir des pipelines de donn√©es √©volutifs et efficaces pour transf√©rer des donn√©es entre des bases de donn√©es SQL et NoSQL.\nD√©velopper et mettre en ≈ìuvre des processus ETL pour extraire, transformer et charger des donn√©es √† partir de diff√©rentes sources dans notre entrep√¥t de donn√©es.\nCollaborer avec des √©quipes pluridisciplinaires pour comprendre les besoins en donn√©es et garantir la fourniture r√©ussie de solutions de donn√©es.\nOptimiser et ajuster les pipelines de donn√©es existants pour la performance et la fiabilit√©.\nConcevoir et d√©velopper des visualisations de donn√©es et des tableaux de bord pour fournir des insights exploitables aux parties prenantes.\nSurveiller et r√©soudre les probl√®mes de pipelines de donn√©es, en veillant √† la qualit√© et √† l'int√©grit√© des donn√©es.\nProfil recherch√© :\nDipl√¥me universitaire en informatique, en ing√©nierie ou dans un domaine connexe.\nExp√©rience av√©r√©e en tant que Data Engineer ou dans un r√¥le similaire, avec un accent particulier sur la construction de pipelines de donn√©es et de processus ETL.\nCompr√©hension solide des bases de donn√©es\nSQL\net\nNoSQL\n, y compris la mod√©lisation des donn√©es et la conception de sch√©mas.\nMa√Ætrise des langages de programmation tels que\nPython, Java ou Scala.\nExp√©rience avec des outils de visualisation de donn√©es tels que\nTableau, Power BI.\nSolides comp√©tences en analyse et en r√©solution de probl√®mes, avec la capacit√© de traduire des donn√©es complexes en insights exploitables.\nExcellentes comp√©tences en communication et en collaboration, avec la capacit√© de travailler efficacement dans un environnement d'√©quipe pluridisciplinaire.\nShow more\nShow less",
        "details": {
            "JobDetail": [],
            "TypeContract": "",
            "Salary": "",
            "Level": "",
            "Experience": null
        },
        "title": "data engineer",
        "skills": {
            "ProgLanguage": [
                "Java",
                "Scala",
                "Python"
            ],
            "DataBase": [
                "SQL",
                "NoSQL"
            ],
            "DataVisualisation": [
                "Power BI",
                "Tableau"
            ],
            "EnSoftSkils": [
                "Communication",
                "Collaboration"
            ]
        }
    },
    {
        "source": "LinkedIn",
        "company": "LCL",
        "location": "Villejuif, √éle-de-France, France",
        "link": "https://fr.linkedin.com/jobs/view/data-engineer-profils-exp%C3%A9riment%C3%A9s-h-f-at-lcl-3888403052?position=6&pageNum=2&refId=ScAHuRnPnFA7sPESHrUwtg%3D%3D&trackingId=IJXsroGkVIWK02iuomr4Xg%3D%3D&trk=public_jobs_jserp-result_search-card",
        "description": "üè¶ LCL, c‚Äôest LA banque urbaine du Groupe Cr√©dit Agricole - avec nous, accompagnez la transformation, le d√©veloppement et le maintien technologiques de nos outils avec une vision business et de satisfaction de nos 6 millions de clients.\nEn tant qu‚Äôacteur majeur de la banque de d√©tail, nous nous adaptons chaque jour aux nouveaux modes de consommation et les projets de nos de clients internes et externes tout en garantissant le besoin de s√©curit√© et de d√©veloppement technologique qu‚Äôimpliquent nos activit√©s.\nüí°Organis√©es en mode Agile, les 8 squads de la tribu DATA (6 squads M√©tier et 2 squads transverses) ≈ìuvrent au quotidien pour r√©pondre √† un enjeu majeur pour la banque : la collecte, le stockage, la gestion et l‚Äôusage de la donn√©e. En interaction permanente avec les autres tribus IT et les m√©tiers, elles √©tudient et proposent les solutions et architectures √† d√©ployer pour r√©pondre au mieux aux strat√©gies de d√©veloppement et de pilotage de l‚Äôensemble des m√©tiers de la banque.\nRejoignez-nous si vous souhaitez participer aux r√©flexions et au d√©veloppement de la trajectoire technique et DataCentric du SI LCL et plus largement du Groupe CA. Vous c√¥toierez et serez au c≈ìur de l‚Äôimpl√©mentation de technologies vari√©es telles que les plateformes Teradata, les solutions d‚Äôarchitecture applicative des technologies BigData ou IA, des environnements analytiques ou encore des solutions de datavisualisation. Vous assurerez le traitement de donn√©es en temps r√©el ou en batch et exposerez les donn√©es sous diff√©rentes formes.\nQue vous souhaitiez devenir expert sur les socles technologiques ou relever le challenge de la gestion de projets M√©tier, nous vous aiderons √† atteindre vos propres objectifs.\nVous rejoindrez une √©quipe pluridisciplinaire, clairement orient√©e vers le d√©veloppement de ses collaborateurs √† de nouvelles technologies !\nüéØ En tant que Data Engineer :\n¬∑ Vous aimez analyser les besoins avec les m√©tiers, challenger, identifier les sources de donn√©es dans les diff√©rents univers technologiques, industrialiser des algorithmes, concevoir et d√©velopper des Datalab ou des Datamart sur les plateformes ? Vous saurez relever les challenges propos√©s par les squads m√©tier !\n¬∑ Vous pr√©f√©rez travailler √† l‚Äôarchitecture et au d√©ploiement de nouvelles plateformes, √† la lev√©e de la dette technologique ou encore r√©aliser de la veille au service de notre trajectoire ? La squad Socles Data est faite pour vous !\n¬∑ Au-del√† des projets que vous g√©rerez, garant du bon fonctionnement de votre parc applicatif, vous attacherez une grande attention √† la mise en ≈ìuvre de solutions optimis√©es.\n¬∑ La rigueur, la communication, l‚Äôesprit d‚Äô√©quipe mais aussi la curiosit√© et la cr√©ativit√© font partie de vos soft skills ! ils vous permettront de r√©pondre aux enjeux de s√©curit√©, de qualit√©, de transmission de la connaissance et contribueront √† l‚Äôatteinte des objectifs de l‚ÄôIT et plus largement de LCL, au service de ses clients.\nüíª Voici les principales technologies utilis√©es au sein de la tribu, si certaines vous sont famili√®res, nous vous aiderons √† monter en comp√©tence sur d‚Äôautres !\nLangages utilis√©s : SQL, Python, Scala\nSGBD : Teradata et utilitaires (TPT, BTEQ, ‚Ä¶)\nStreaming : Kafka\nSearch : ElasticSearch, SolR\nEnvironnement : Unix\nSolutions Big Data : Hadoop Cloudera, DataIku, HDFS, Hive, Impala,\nDevops : GitLab, Jenkins, Nexus\nOutils de visualisation : MS BI (SSIS, SSAS, SSRS) Qlik Sens, BO\nMod√©lisation : MEGA\nOutils collaboratifs : GIT, Jira, Confluence, Teams\n‚ö°Si les nouveaux enjeux bancaires vous int√©ressent, que vous souhaitez int√©grer une √©quipe Agile au service des m√©tiers dans laquelle vous serez force de proposition et que vous aimez travailler dans un environnement motivant et dynamique, rejoignez-nous, cette offre est faite pour vous !\nüî• Les + de notre entreprise :\nAcc√®s au Plan d‚Äô√©pargne Groupe, int√©ressement et participation aux b√©n√©fices de l‚Äôentreprise + abondement\nPrix pr√©f√©rentiels bancaires et avantages CSE\nParcours √©volutif dans l‚Äôentreprise et/ou dans le Groupe CA.S.A\nT√©l√©travail (jusqu'√† 2 jours de t√©l√©travail par semaine)\nDe multiples commodit√©s sur le campus (restaurants d'entreprise, salle de sport, cr√®che, centre m√©dical, m√©diath√®que...)\nForfait et avantages pratiques ¬´ mobilit√© durable ¬ª pour les velotafeurs\nDes √©quipes aussi diversifi√©es que structur√©es dans une dynamique de transformation\nLCL s‚Äôengage en faveur de la diversit√© et nous encourageons tout(e) candidat(e) ayant l‚Äôexp√©rience requise √† postuler √† nos offres. Tous nos postes sont ouverts aux personnes en situation de handicap.\nNous avons encore de nombreuses raisons √† vous pr√©senter pour vous convaincre de nous rejoindre mais pour cela, il faudra postuler ici !\nShow more\nShow less",
        "details": {
            "JobDetail": [],
            "TypeContract": "",
            "Salary": "",
            "Level": "",
            "Experience": null
        },
        "title": "data engineer",
        "skills": {
            "ProgLanguage": [
                "Scala",
                "Python"
            ],
            "DataBase": [
                "Elasticsearch",
                "SQL"
            ],
            "BigData": [
                "Hadoop"
            ],
            "DevTools": [
                "Git",
                "Jenkins"
            ],
            "Collaboration": [
                "Confluence",
                "Teams",
                "JIRA"
            ],
            "Other": [
                "Big Data",
                "DevOps"
            ],
            "EnSoftSkils": [
                "Communication"
            ]
        }
    },
    {
        "source": "LinkedIn",
        "company": "Ramify",
        "location": "Paris",
        "link": "https://fr.linkedin.com/jobs/view/data-engineer-at-ramify-3896146641?position=7&pageNum=2&refId=ScAHuRnPnFA7sPESHrUwtg%3D%3D&trackingId=sd79m7aEJdZqm5M%2BxmhIsA%3D%3D&trk=public_jobs_jserp-result_search-card",
        "description": "ABOUT\nRamify‚Äôs mission is to help people achieve financial freedom, no matter who they are and how much they have. We are revolutionizing the private wealth management industry by making smart and affordable financial products for everyone.\nNo more standardized solutions, hidden fees and complicated words, Ramify enables everyone to become a smart investor. The team combines elements of its research with technology to design customized investment portfolios composed of world-class financial products.\nThe team comprises around 15 talented individuals. Ramify is looking for talented people in all sectors, who want to have a huge impact, move fast and deliver.\nJOB DESCRIPTION\nThe Quantitative Investment Solutions (QIS) Team is dedicated to designing innovative investment portfolio models and developing cutting-edge investment features within our product suite. Moreover, the QIS Team is at the forefront of driving AI-based solutions for Ramify. This involves conceptualizing and implementing transformative AI solutions tailored to meet the diverse needs of various teams within Ramify.\nAs a Data Engineer on our QIS Team, you will play a pivotal role in shaping the future of investment strategies through data-driven insights and AI-based solutions. Collaborating closely with our talented team of quantitative researchers, and investment experts, your responsibilities will encompass architecting and implementing robust data pipelines. These pipelines will facilitate the seamless integration of diverse data sources, empowering Ramify teams to make informed decision-making.\nKey Responsibilities:\nDesign, build and launch data pipelines at scale to move data across Ramify platform with SQL technologies.\nDesign and implement processes and tools for data onboarding and quality, helping to deliver an industry best-practice solution for managing the data lifecycle.\nProduce stand-alone tools that can be used by other teams to automate data quality and discover faults.\nBuild analytical tools that provide insight into business metrics across Ramify.\nArchitect and lead the implementation of AI based solutions within Ramify\nPREFERRED EXPERIENCE\nWe're looking for people who:\nWant to make a difference. We are a small team effectively reshaping how people look at the industry. We need people who 'get it' and want to play an integral part in helping us accomplish this mission and are persistent in getting the job done.\nSkills we're looking for:\nMaster‚Äôs or upper-year undergraduate-level coursework in either Computer Science, Management Information Systems, Business Information Systems, Mathematics or Finance related field.\n2+ years of professional experience in data engineering.\n2+ years of experience with one or more coding languages such as Python (is a must), Java.\nExperience with data modeling and ETL design, implementation and maintenance.\nDemonstrable mastery of industry best practices in the data lifecycle, including data quality automation and tooling.\nExcellent written and verbal communication skills with ability to communicate complex designs and solutions to non-technical and highly technical audiences alike.\nGood attention to detail.\nStrong analytics and strategic thinking skills\nNice-to-haves :\nUnderstanding of ML/ Generative AI technologies and their applications.\nPossess a passion, curiosity, and energy for finance + investing. You understand the ins and outs of the wealth management, trading, and more importantly - know how to explain these concepts simply\nShow more\nShow less",
        "details": {
            "JobDetail": [],
            "TypeContract": "",
            "Salary": "",
            "Level": "",
            "Experience": null
        },
        "title": "data engineer",
        "skills": {
            "ProgLanguage": [
                "Java",
                "Python"
            ],
            "DataBase": [
                "SQL"
            ],
            "Collaboration": [
                "Teams"
            ],
            "Other": [
                "ML"
            ],
            "EnSoftSkils": [
                "Communication"
            ]
        }
    },
    {
        "source": "LinkedIn",
        "company": "Renault Digital",
        "location": "Boulogne-Billancourt, √éle-de-France, France",
        "link": "https://fr.linkedin.com/jobs/view/data-engineer-f-h-at-renault-digital-3911202728?position=8&pageNum=2&refId=ScAHuRnPnFA7sPESHrUwtg%3D%3D&trackingId=u6M0icZBx1jNW9jmHGT6PQ%3D%3D&trk=public_jobs_jserp-result_search-card",
        "description": "Contexte :\nDans le cadre de son programme Industrie 4.0, Renault d√©veloppe depuis 2017 sa propre plateforme pour connecter et agr√©ger les donn√©es industrielles des 22 sites du Groupe et de plus de 2500 machines.\nFort de partenariats strat√©giques sign√©s avec Google Cloud (stack data full GCP), Renault Digital est √† la recherche d‚Äôun(e) Data Engineer au sein du P√¥le Architecture et Data pour mettre en place des cha√Ænes de traitement de donn√©es r√©pondant √† de nouveaux besoins m√©tiers.\nVous collaborerez au jour le jour avec les √©quipes m√©tiers ainsi qu‚Äôavec les autres fonctions du P√¥le Architecture & Data (Data Analysts et Scientists, architectes, ‚Ä¶), exploitant des t√©raoctets de donn√©es (√©v√©nements en mode streaming, traitements en batch et temps r√©els et les appels aux APIs) afin entre autres d‚Äôalimenter des mod√®les de machine learning (segmentation clients, d√©tection automatiquement des pannes des v√©hicules, ‚Ä¶).\nResponsabilit√©s principales :\nVous participez aux phases de framing, MVP et release des produits, services et APIs orient√©s data ;\nVous argumentez les choix d‚Äôarchitecture des projets et de la plateforme datalake sur GCP ;\nVous contribuez √† la valeur m√©tier des produits orient√©s Data s‚Äôappuyant sur le Datalake, en mettant en place des cha√Ænes bout en bout de traitement de la data, de l‚Äôingestion √† l‚Äôexposition d‚ÄôAPIs et √† la visualisation des donn√©es et des solutions ML/DS ;\nVous √™tes garant de la qualit√© des donn√©es transform√©es dans le Datalake, du bon fonctionnement des cha√Ænes de traitement et de l‚Äôoptimisation de l‚Äôutilisation des ressources des ressources cloud ;\nVous proposez des standards d‚Äôarchitecture et de d√©veloppement ;\nVous √™tes force de proposition, innovant(e) et bienveillant(e).\nEnvironement technique :\nSpark, Scala, Python, Java, Airflow, SQL, Google Cloud Platform (BigQuery, Cloud Storage, PubSub, Beam, Dataflow, Cloud ML, TensorFlow, Kubernetes), Git, Docker, JSON, Bash, Spotfire\nProfil recherch√© :\nVous avez minimum 5 ans d‚Äôexp√©rience en tant que Data Engineer ;\nVous disposez d‚Äôune exp√©rience en d√©veloppement Spark, Scala, Python et requ√™tage SQL sur des gros volumes de donn√©es ;\nVous avez une app√©tence pour la data : validation, transformation, analyse, valorisation ;\nVous poss√©dez une exp√©rience de d√©veloppement et orchestration de chaines ETL complexes via Airflow ou √©quivalent ;\nVous pratiquez la m√©thodologie agile (Agile Scrum et/ou Kanban) ;\nVous utilisez les services cloud (pr√©f√©rablement GCP) ;\nVous √™tes capable d‚Äô√©changer en anglais technique √©crit et oral.\nInformations compl√©mentaires :\nVotre poste sera bas√© √† Boulogne-Billancourt (France) en CDI (temps plein)\nVous b√©n√©ficiez de 2 √† 3 jours de t√©l√©travail par semaine\nShow more\nShow less",
        "details": {
            "JobDetail": [
                "Temps plein",
                "Full"
            ],
            "TypeContract": "CDI",
            "Salary": "",
            "Level": "",
            "Experience": "5 an(s)"
        },
        "title": "data engineer",
        "skills": {
            "ProgLanguage": [
                "Java",
                "Bash",
                "Scala",
                "Python"
            ],
            "DataBase": [
                "SQL"
            ],
            "BigData": [
                "Spark"
            ],
            "MachineLearning": [
                "TensorFlow"
            ],
            "DataSerialization": [
                "Json"
            ],
            "CloudComputing": [
                "GCP",
                "Google Cloud Platform"
            ],
            "DevTools": [
                "Git",
                "Docker"
            ],
            "DBMS": [
                "BigQuery"
            ],
            "Automation": [
                "Airflow",
                "Kubernetes"
            ],
            "Containers": [
                "Docker",
                "Kubernetes"
            ],
            "Other": [
                "Machine Learning",
                "Cloud",
                "ML"
            ]
        }
    },
    {
        "source": "LinkedIn",
        "company": "Inetum",
        "location": "St.-Ouen, √éle-de-France, France",
        "link": "https://fr.linkedin.com/jobs/view/data-engineer-h-f-at-inetum-3843966639?position=9&pageNum=2&refId=ScAHuRnPnFA7sPESHrUwtg%3D%3D&trackingId=Gwv1jWjhHHw8djXLLXWCHA%3D%3D&trk=public_jobs_jserp-result_search-card",
        "description": "D√©tail de l'offre\nInformations g√©n√©rales\nEntit√© de rattachement\nInetum est un leader europ√©en des services num√©riques. Pour les entreprises, les acteurs publics et la soci√©t√© dans son ensemble, les 28 000 consultants et sp√©cialistes du groupe visent chaque jour l'impact digital des solutions qui contribuent √† la performance, √† l'innovation et au bien commun.\nPr√©sent dans 19 pays au plus pr√®s des territoires, et avec ses grands partenaires √©diteurs de logiciels, Inetum r√©pond aux enjeux de la transformation digitale avec proximit√© et flexibilit√©.\nPort√© par son ambition de croissance et d'industrialisation, Inetum a g√©n√©r√© en 2023 un chiffre d'affaires de 2,5 milliards d'‚Ç¨.\nPour r√©pondre √† un march√© en croissance continue depuis plus de 30ans, Inetum a fait le choix d√©lib√©r√© de se recentrer sur 4 m√©tiers afin de gagner en puissance et proposer des solutions sur mesure, adapt√©es aux besoins sp√©cifiques de ses clients le conseil (Inetum Consulting), la gestion des infrastructures et applications √† fa√ßon (Inetum Technologies), l'impl√©mentation de progiciels (Inetum Solutions) et sa propre activit√© d'√©diteur de logiciels (Inetum Software). Inetum a conclu des partenariats strat√©giques avec 4 grands √©diteurs mondiaux - Salesforce, ServiceNow, Microsoft et SAP et poursuit une strat√©gie d'acquisitions d√©di√©e afin d'entrer dans le top 5 europ√©en sur ces technologies et proposer la meilleure expertise √† ses clients.\nTous nos postes sont ouverts aux personnes en situation de handicap.\nDescription du poste\nM√©tier\nApplications Delivery - Software Development\nIntitul√© du poste\nData Engineer H/F\nContrat\nCDI\nDescription De La Mission\nLe p√¥le BFA de la branche Application Services du groupe INETUM, recherche plusieurs Data Engineers afin d'intervenir aupr√®s de clients grands comptes au sein des march√©s bancaires et de l'assurance.\nAu sein de l'√©quipe Data, en tant que Data Engineer, vous participez √† la r√©alisation de divers projets et vos missions sont\nApporter votre connaissance en Big Data permettant la manipulation des donn√©es\nConcevoir les plateformes permettant de traiter des volumes de donn√©es importants\nMettre en place des bases de donn√©es\nPr√©parer le pipeline de donn√©es pour que les donn√©es d√©ploy√©es soient s√©curis√©es et claires afin d'√™tre analys√©es et transform√©es.\nProfil\nDe formation ing√©nieure en informatique Bac + 5 informatique ou scientifique\nBonne communication orale et √©crite en fran√ßais et niveau d‚Äôanglais professionnel\nSavoir- √™tre Bon esprit d'analyse et de synth√®se, sens de l'organisation et de la qualit√©, force de proposition, rigueur, travail en √©quipe, adaptabilit√©.\nSi vous vous reconnaissez, n'h√©sitez pas √† postuler !\nLocalisation du poste\nLocalisation du poste\nFrance\nVille\nSaint-Ouen\nCrit√®res candidat\nNiveau d'√©tudes min. requis\nBac+5\nNiveau d'exp√©rience min. requis\nPlus de 2 ans\nComp√©tences\nSQL\nShow more\nShow less",
        "details": {
            "JobDetail": [],
            "TypeContract": "CDI",
            "Salary": "",
            "Level": "Bac+5",
            "Experience": "30 an(s)"
        },
        "title": "data engineer",
        "skills": {
            "DataBase": [
                "SQL"
            ],
            "Other": [
                "Big Data"
            ],
            "EnSoftSkils": [
                "Communication"
            ]
        }
    },
    {
        "source": "LinkedIn",
        "company": "Capgemini",
        "location": "Nantes, Pays de la Loire, France",
        "link": "https://fr.linkedin.com/jobs/view/data-engineer-bi-nantes-at-capgemini-3803963477?position=10&pageNum=2&refId=ScAHuRnPnFA7sPESHrUwtg%3D%3D&trackingId=NR3ocFz4q9uIIduh74kWZg%3D%3D&trk=public_jobs_jserp-result_search-card",
        "description": "Capgemini\nChoisir Capgemini, c'est choisir une entreprise o√π vous serez en mesure de fa√ßonner votre carri√®re selon vos aspirations, o√π vous serez soutenu et inspir√© par une communaut√© d‚Äôexperts dans le monde entier, o√π vous pourrez r√©√©crire votre futur. Rejoignez-nous pour red√©finir les limites de ce qui est possible, contribuer √† lib√©rer la valeur de la technologie pour les plus grandes organisations et participez √† la construction d‚Äôun monde plus durable et inclusif.\nVos missions :\nInt√©gr√©(e) au sein d‚Äôune √©quipe projet BI, Big Data ou Data Gouvernance pour des clients intervenant dans des secteurs d'activit√©s divers, vous serez notamment en charge des missions suivantes :\nMener les analyses fonctionnelles destin√©es √† traduire les besoins du client,\nMener les travaux de conception et de mod√©lisation,\nDiriger le d√©veloppement de la solution / des traitements d'alimentation du DataWareHouse,\nOrganiser et pr√©parer les travaux de recette utilisateurs,\nMettre en place les processus d'industrialisation et mener cette derni√®re.\nVotre profil :\nDipl√¥me d‚Äôing√©nieur ou √©quivalent universitaire\nMinimum 3 ans d'exp√©rience\nAnglais courant\nComp√©tences en BI sur SAP BI (Hana, BW, BODS, BI 4), Microsoft BI (SQL Server, SSIS, SSAS, SSRS), Oracle (ODI, OBIEE), Teradata, Informatica (Powercenter), IBM (Datastage, Cognos, TM1), Talend, AB Initio\nMa√Ætrise d'un ou de plusieurs outils de Dataviz : Microsoft Power BI, Tableau, Qlikview\nConnaissances en Big Data (Ecosyst√®me Hadoop (HIVE, PIG, Mahout‚Ä¶), Cloudera, Pivotal, Spark, HNX) ou en analytics (R, SAS, IBM SPSS)\n3 raisons de nous rejoindre :\nQualit√© de vie au travail : accord de t√©l√©travail en France et √† l‚Äôinternational, accord sur l‚Äô√©galit√©\nprofessionnelle, la parentalit√©, l‚Äô√©quilibre des temps et la mobilit√© durable.\nApprentissage en continu : certifications et formations en libre acc√®s, accompagnement sur mesure avec votre carreer manager, parcours d‚Äôint√©gration sur 9 mois.\nAvantages groupe & CSE : plan actionnariat, activit√©s √† tarifs pr√©f√©rentiels, remboursement partiel\nvacances, remboursement de votre abonnement sportif ou culturel.\nNos engagements et priorit√©s :\nLe groupe Capgemini encourage une culture inclusive dans un cadre multiculturel et handi-accueillant. En nous rejoignant, vous int√©grez un collectif qui valorise la diversit√©, d√©veloppe le potentiel de ses talents, s‚Äôengage dans des initiatives solidaires avec ses partenaires, et se mobilise pour r√©duire son impact environnemental sur tous ses sites et aupr√®s de ses clients.\nCapgemini\nCapgemini est un leader mondial, responsable et multiculturel, regroupant pr√®s de 350 000 personnes dans plus de 50 pays. Fort de 55 ans d‚Äôexp√©rience, nous sommes un partenaire strat√©gique des entreprises pour la transformation de leurs activit√©s en tirant profit de toute la puissance de la technologie et des innovations dans les domaines en perp√©tuelle √©volution tels que le cloud, la data, l‚ÄôIntelligence Artificielle, la connectivit√©, les logiciels, l‚Äôing√©nierie digitale ou les\nplateformes.\nGet The Future You Want* | www.capgemini.com/fr-fr\n*Capgemini, le futur que vous voulez\nShow more\nShow less",
        "details": {
            "JobDetail": [],
            "TypeContract": "",
            "Salary": "",
            "Level": "",
            "Experience": "3 an(s)"
        },
        "title": "data engineer",
        "skills": {
            "ProgLanguage": [
                "R"
            ],
            "DataBase": [
                "SQL"
            ],
            "DataAnalytics": [
                "R"
            ],
            "BigData": [
                "Hadoop",
                "Spark"
            ],
            "DataVisualisation": [
                "Power BI",
                "Tableau"
            ],
            "DBMS": [
                "SQL Server"
            ],
            "Other": [
                "Cloud",
                "Big Data"
            ]
        }
    },
    {
        "source": "LinkedIn",
        "company": "Astek",
        "location": "Antibes, Provence-Alpes-C√¥te d'Azur, France",
        "link": "https://fr.linkedin.com/jobs/view/data-engineer-%E2%80%93-antibes-france-h-f-at-astek-3909192086?position=1&pageNum=5&refId=ta7dp2AfGVWmvLdIA1X0jA%3D%3D&trackingId=zTGOsE%2F7O3zniEvcuaWrOw%3D%3D&trk=public_jobs_jserp-result_search-card",
        "description": "CDI\nAntibes - France\nPubli√©e il y a 2 semaines\nLe Groupe Astek\nCe Que Nous Allons Accomplir Ensemble :\nIntervenir dans la conception, le d√©veloppement, les tests unitaires, la qualification, l‚Äôint√©gration continue et la mise en production d‚Äô√©volutions sur les projets du p√¥le produits scoring (un p√¥le visant √† d√©velopper des solutions permettant de g√©n√©rer des scores ou des segments d‚Äôinformation pertinents dans divers domaines, notamment : profiling TV, PUB, SAB, MMDM, Voscastview) chez l‚Äôun de nos partenaires sp√©cialis√© dans le secteur des t√©l√©coms.\nVotre Mission, Si Vous L‚Äôacceptez :\nEn collaboration avec les autres membres de l‚Äô√©quipe, vous devrez prendre en charge le RUN des applications du p√¥le produit scoring.\nConception d‚Äôune solution se basant sur les d√©veloppements existants et les besoins m√©tiers remont√©s par le Product Owner.\nR√©alisation et d√©veloppement de nouvelles fonctionnalit√©s sur les composants des applications du p√¥le produits scoring et environnement CGP.\nVotre Future √âquipe :\nAu sein d‚Äôun environnement riche et complexe, vous √©voluerez avec des experts passionn√©s √† la fois techniques et fonctionnels (Ing√©nieurs sp√©cialis√©s, chef de projet, scrum master, product owner, analystes ‚Ä¶).\nVotre stack de jeu\nD ans un environnement SAFE sous cloud GCP, Big Query, OnPrime, Grafana, Python et Ansible.\nVous ?\nDe formation Ing√©nieur, vous justifiez d‚Äôune premi√®re exp√©rience sur un poste de Data engineer. Vous poss√©dez des comp√©tences d‚Äôautonomie et d‚Äôadaptabilit√© et vous avez une capacit√© √† communiquer efficacement au sein d‚Äôune √©quipe.\nLe Groupe Astek\nCr√©√© en France en 1988, Astek est un acteur mondial de l‚Äôing√©nierie et du conseil en technologies. Fort de son expertise dans de nombreux secteurs industriels et tertiaires, Astek accompagne ses clients internationaux dans le d√©ploiement intelligent de leurs produits et de leurs services, et dans la mise en ≈ìuvre de leur transformation digitale.\nDepuis sa cr√©ation, le Groupe a fond√© son d√©veloppement sur une forte culture d‚Äôentrepreneuriat et d‚Äôinnovation, et sur l‚Äôaccompagnement et la mont√©e en comp√©tence de\nses 7800 collaborateurs\nqui s‚Äôengagent chaque jour √† promouvoir la compl√©mentarit√© entre les technologies num√©riques et l‚Äôing√©nierie des syst√®mes complexes.\nRejoignez un Groupe en fort d√©veloppement en France et √† travers le monde ayant r√©alis√© un chiffre d‚Äôaffaires de 600 M‚Ç¨ en 2023.\nTous les d√©tails sur le Groupe sur le site https://astekgroup.fr. Et vous pouvez aussi nous suivre sur notre blog : https://blog.groupeastek.com.\nRencontrons-nous\nCr√©√© en France en 1988, Astek est un acteur mondial de l‚Äôing√©nierie et du conseil en technologies, pr√©sent sur les 5 continents. Fort de son expertise dans de nombreux secteurs industriels et tertiaires, Astek accompagne ses clients internationaux dans le d√©ploiement intelligent de leurs produits et de leurs services, et dans la mise en ≈ìuvre de leur transformation digitale.\nDepuis sa cr√©ation, le Groupe a fond√© son d√©veloppement sur une forte culture d‚Äôentrepreneuriat et d‚Äôinnovation, et sur l‚Äôaccompagnement et la mont√©e en comp√©tence de ses 7800 collaborateurs qui s‚Äôengagent chaque jour √† promouvoir la compl√©mentarit√© entre les technologies num√©riques et l‚Äôing√©nierie des syst√®mes complexes.\nRejoignez un Groupe en fort d√©veloppement en France et √† travers le monde et ayant r√©alis√© un chiffre d‚Äôaffaires hors\nacquisitions de 600M‚Ç¨ en 2023.\nTous les d√©tails sur le Groupe sur le site\nNos Plus\nAstek est green et fait b√©n√©ficier ses salari√©s d‚Äôune indemnit√© kilom√©trique v√©lo\nUne politique CARE sur-mesure d√©ploy√©e par nos √©quipes RH pour nos collaborateurs (https://astekgroup.fr/engagements)\nNotre charte de la Diversit√©\nMots-cl√©s :\ning√©nieur ‚Äì ing√©nieure ‚Äì consultant ‚Äì consultante ‚Äì Data engineer ‚Äì Big Data\nCaract√©ristiques de l'emploi\nCat√©gorie Ing√©nieur\nJob Industry T√©l√©com / M√©dia\nPostuler en ligne\nNom *\nPr√©nom *\nEmail *\nUn email valide est requis.\nT√©l√©phone *\nUn num√©ro de t√©l√©phone valide est requis.\nJoindre un CV *\nMots-cl√©s :\ning√©nieur ‚Äì ing√©nieure ‚Äì consultant ‚Äì consultante ‚Äì Data engineer ‚Äì Big Data\nShow more\nShow less",
        "details": {
            "JobDetail": [],
            "TypeContract": "CDI",
            "Salary": "",
            "Level": "",
            "Experience": null
        },
        "title": "data engineer",
        "skills": {
            "ProgLanguage": [
                "Python"
            ],
            "CloudComputing": [
                "GCP"
            ],
            "DBMS": [
                "Big Query"
            ],
            "Automation": [
                "Chef",
                "Ansible"
            ],
            "Other": [
                "Cloud",
                "Big Data"
            ],
            "EnSoftSkils": [
                "Collaboration"
            ]
        }
    },
    {
        "source": "LinkedIn",
        "company": "Web Transition",
        "location": "Lille, Hauts-de-France, France",
        "link": "https://fr.linkedin.com/jobs/view/data-engineer-h-f-at-web-transition-3909147172?position=2&pageNum=5&refId=ta7dp2AfGVWmvLdIA1X0jA%3D%3D&trackingId=J8wiaPcFaiEqxgjJ7EJDjw%3D%3D&trk=public_jobs_jserp-result_search-card",
        "description": "Web Transition, c‚Äôest qui ?\nFond√©e en 2011,\nWeb transition\nest une entreprise de services num√©riques op√©rant sur le march√© de l‚ÄôIT/Digital !\nConstituant une part essentielle de\nMoOngy Digital Lab\n, Web Transition accompagne ses clients grands comptes sur leurs projets de Webmarketing, de Design, Gestion de projet et √©galement en Data !\nNotre objectif : nous implanter comme un acteur principal sur le march√© de la Transformation Digitale en accompagnant et valorisant les comp√©tences de nos collaborateurs !\nNous sommes convaincus que le succ√®s de MoOngy Digital Lab r√©side dans la somme des potentiels de nos √©quipes ü§ù\nTon √©quipe : La tribu Data\nParce qu‚Äôil est indispensable que tu puisses partager tes connaissances mais aussi en acqu√©rir de nouvelles, tu feras partie de l‚Äôune de nos tribus : celle de la Data. De plus, cela te permettra d‚Äô√™tre acteur dans le d√©veloppement et la strat√©gie de Web Transition. Ce syst√®me de co-r√©flexion et co-construction est un fondement essentiel chez nous !\nDans cette aventure, tu :\nT‚Äôassures\nde la ma√Ætrise de la donn√©e et est garant de la qualit√© de son utilisation (r√©f√©rencement, normalisation, et qualification)\nTravailles\n√† la compr√©hension et l'int√©gration des donn√©es en provenance des diff√©rents formats\ndes interfaces de flux\n√©galement √† la d√©finition de la politique de la donn√©e et √† la structuration de son cycle de vie dans le respect des r√©glementations en vigueur\nla supervision et l'int√©gration des donn√©es de diverse nature qui proviennent de ces sources multiples et v√©rifie la qualit√© des donn√©es qui entrent dans le Data Lake\nGarantis\nl'acc√®s qualitatif aux sources de donn√©es\nFacilites\nl‚Äôacc√®s aux donn√©es pour tes coll√®gues (data scientists, data analysts‚Ä¶)\nAssistes\nles autres √©quipes dans l'acc√®s et la compr√©hension des donn√©es des socles.\nRejoins-nous si tu as :\nExp√©rience d‚Äôau-moins 4 ans dans la Data\nApp√©tence √† la qualit√© des donn√©es.\nConnaissance famili√®re des Datawarehouses.\nMaitrise de Python, Oracle SQL, GCP/Power BI\nAisance avec les indicateurs, tu as une bonne capacit√© d'analyse et de r√©daction.\nTon savoir-√™tre :\nOuvert d‚Äôesprit\nRigoureux\nAutonome\nRespectueux des diff√©rences de chacun\nCurieux\nProactif\nAgile\nPar o√π on commence ?\nUn premier entretien RH d‚Äô1h pour comprendre ton parcours et tes aspirations\nUn second entretien de 45 minutes avec l‚Äôun de nos Business Manager afin de valider tes comp√©tences et qu‚Äôil se projette sur l‚Äôune des missions qu‚Äôil pourrait te proposer\nUn troisi√®me entretien de quelques minutes avec notre responsable d‚Äôagence pour te proposer d‚Äôint√©grer notre superbe Team Web !\n3 entretiens en peu de temps, si ton profil correspond tu int√®greras tr√®s vite nos √©quipes üòâ\nPr√™t pour embarquer dans notre grande aventure humaine ? Deviens notre futur Weber en postulant √† cette offre ! Voici les avantages qui t‚Äôattendent en tant que Weber :\nü§© Des coll√®gues incroyables\nüèÜ Certifi√©e Great Place to Work\nüéÆ Des bureaux sympas (o√π vous serez toujours les bienvenus)\nüéâ Des teambuilding et √©vents tous les mois\nüíª Des tributs m√©tiers pour √©changer entre Weber du m√™me m√©tier\nDes missions chez le client qui sont accompagn√©es et coach√©es par ton manager\nUn accompagnement dans ton plan de carri√®re et tes envies de re skilling\nü§ì Un catalogue de formations certifiantes ouvert √† tous les salari√©s\nüçΩÔ∏è Une carte tickets restaurant MyEdenred\n‚ù§Ô∏è Une mutuelle GrasSavoye\nüöé Une prise en charge des frais de transport √† 100%\nShow more\nShow less",
        "details": {
            "JobDetail": [],
            "TypeContract": "",
            "Salary": "",
            "Level": "",
            "Experience": "4 an(s)"
        },
        "title": "data engineer",
        "skills": {
            "ProgLanguage": [
                "Python"
            ],
            "DataBase": [
                "SQL"
            ],
            "DataVisualisation": [
                "Power BI"
            ],
            "CloudComputing": [
                "GCP"
            ],
            "DBMS": [
                "Oracle SQL"
            ]
        }
    },
    {
        "source": "LinkedIn",
        "company": "Mobilize Financial Services ‚Äì France",
        "location": "Noisy-le-Grand, √éle-de-France, France",
        "link": "https://fr.linkedin.com/jobs/view/data-engineer-f-h-at-mobilize-financial-services-%E2%80%93-france-3869637982?position=3&pageNum=5&refId=ta7dp2AfGVWmvLdIA1X0jA%3D%3D&trackingId=nMUVu2xWNyaFQacbVrv%2B9Q%3D%3D&trk=public_jobs_jserp-result_search-card",
        "description": "üöó En route vers Mobilize !\nA l‚Äô√©coute de tous nos clients, nous cr√©ons des services financiers innovants pour construire une mobilit√© durable pour tous.\nRejoindre Mobilize Financial Services,\nc‚Äôest d‚Äôabord choisir d‚Äôint√©grer un groupe international\n, filiale de Renault Group, une banque de financement solide, partenaire des constructeurs Renault‚ÄìNissan‚ÄìMitsubishi. Nos 4 000 collaborateurs pr√©sents dans 35 pays, agissent ensemble au service de nos clients.\nNous proposons √† nos clients - particuliers comme professionnels - les financements et les services les plus adapt√©s pour les v√©hicules neufs et d'occasion.\nNous finan√ßons √©galement l'activit√© des r√©seaux de concessionnaires des marques de l'Alliance Renault-Nissan-Mitsubishi et nous veillons √† faciliter leur gestion au quotidien pour leur permettre de d√©velopper leurs ventes et assurer leur p√©rennit√© financi√®re.\nNotre entreprise se \"MOBILIZE\" en faveur de la diversit√© culturelle, l'√©galit√© hommes-femmes et l'int√©gration de personnes en situation de Handicap. Nous favorisons un environnement de travail o√π les diff√©rences individuelles sont reconnues, appr√©ci√©es, respect√©es et valoris√©es, de fa√ßon √† mettre √† profit les talents et les forces de chacun.\nüöòPrenez le volant ! Pas de routine, tous nos itin√©raires sont diff√©rents !\nAu sein de la DSI\n,\nvotre\nfutur m√©tier consistera √† :\nAccompagner l‚Äô√©quipe dans la transformation du domaine d√©cisionnel construit sur une architecture type DWH et le porter sur la solution GCP (Google Cloud Platform) de Mobilize FS\nParticiper √† la construction du projet de transformation vers GCP\nParticiper aux projets d‚Äô√©volution de notre plateforme Suite Elastic (ELK - Kibana)\nPiloter des projets en √©troite collaboration avec les directions m√©tier et en accord avec le TBA (Tableau de Bord des Actions).\nAssurer la gestion du budget, du planning, de la tenue des jalons et du respect des engagements sur les projets en responsabilit√©\nAssurer la qualit√© et le bon fonctionnement du chargement des donn√©es.\nAssurer la mise √† disposition des donn√©es et des outils de reportings √† toutes les directions clientes dans le respect des contrats de service\nV√©ritable tout-terrain, vous nous int√©ressez !\nL‚Äôesprit d‚Äô√©quipe et le sens du service client pour atteindre ensemble les diff√©rents objectifs ambitieux et satisfaire les diff√©rentes parties avec un haut niveau de qualit√©.\nVous avez un bon relationnel, de l‚Äô√©coute et une excellente communication afin d‚Äôinteragir avec des interlocuteurs de diff√©rents niveaux (direction technique et m√©tier) et de travailler en transverse.\nLe sens de l‚Äôanalyse et de bonnes capacit√©s d‚Äôanticipation pour d√©celer les probl√®mes avant la naissance de ces derniers.\nForce de proposition : avec vous il n'y a pas de probl√®mes, que des solutions\nVous avez un niveau d‚Äôanglais vous permettant de lire et de comprendre de la documentation technique\nüíªüñ± Environnement technique :\nMaitrise des langages Python - SQL / NoSQL\nExp√©rience significative sur Python\nExp√©rience avec Git\nUne exp√©rience avec les outils Nifi, Airflow et GCP (BigQuery / Cloud Function / Cloud Storage ‚Ä¶) serait un plus\nGestion de projet, maintenance, √©volution, support\nApp√©tence pour les sujets techniques et fonctionnels : outils de mod√©lisation, exploration de donn√©es, IA, machine learning\nPourquoi nous rejoindre ?\nVotre Pack confort\nest compos√© de nombreux avantages üòÄ :\nRejoindre Mobilize Financial Services c‚Äôest int√©grer un grand groupe international qui offre des opportunit√©s de carri√®re\n.\nUn environnement de travail moderne et convivial\n: locaux agr√©ables, salle de sport, terrasse, restaurant d‚Äôentreprise, parking avec un CSE dynamique avec de nombreuses offres voyages, sport, famille,\nNous sommes mobilis√©s pour d√©velopper la qualit√© de vie au travail de nos collaborateurs en faisant √©voluer nos fa√ßons de travailler (m√©thodes, outils, organisation du travail‚Ä¶) et nous sommes fiers d‚Äô√™tre certifi√©s ‚≠ê\nGreat Place To Work ‚≠ê\nPossibilit√© de t√©l√©travailler 2 jours par semaine\nNous proposons une\nr√©mun√©ration selon profil + Participation + Int√©ressement\nLocaux situ√©s au pied du RER A ‚Äì Noisy le Grand Mont d‚ÄôEst\n‚ùó Mobilize Financial Services d√©m√©nage ‚ùó Les postes √† pourvoir en r√©gion parisienne seront bas√©s √† Boulogne Billancourt √† horizon 2026\nPour en savoir plus sur notre entreprise,\nsuivez-nous sur LinkedIn !\nLa route du recrutement ?\nüìû Un rapide entretien t√©l√©phonique,\nüõë\nun premier √©change\navec Marie DE CARLI, Responsable du d√©partement DATA\n‚Ü™ et un dernier virage avec Agathe GROSBOIS, Responsale des Ressources Humaines\nL‚Äô√©quipe Mobilize FS a h√¢te de vous recevoir !\nShow more\nShow less",
        "details": {
            "JobDetail": [],
            "TypeContract": "",
            "Salary": "",
            "Level": "",
            "Experience": null
        },
        "title": "data engineer",
        "skills": {
            "ProgLanguage": [
                "Python"
            ],
            "DataBase": [
                "SQL",
                "NoSQL"
            ],
            "DataVisualisation": [
                "Tableau"
            ],
            "CloudComputing": [
                "GCP",
                "Google Cloud Platform"
            ],
            "DevTools": [
                "Git"
            ],
            "DBMS": [
                "BigQuery"
            ],
            "Automation": [
                "Airflow"
            ],
            "Other": [
                "Machine Learning",
                "Cloud"
            ],
            "EnSoftSkils": [
                "Communication",
                "Collaboration"
            ]
        }
    },
    {
        "source": "LinkedIn",
        "company": "MP DATA",
        "location": "Toulouse, Occitanie, France",
        "link": "https://fr.linkedin.com/jobs/view/data-engineer-h-f-at-mp-data-3908719610?position=4&pageNum=5&refId=ta7dp2AfGVWmvLdIA1X0jA%3D%3D&trackingId=QC7vcJ028LquS7NZmeHEFA%3D%3D&trk=public_jobs_jserp-result_search-card",
        "description": "MP DATA est une soci√©t√© sp√©cialis√©e dans l‚Äôacquisition, le traitement, et la valorisation des donn√©es.\nDepuis sa cr√©ation en 2015, MP DATA accompagne ses clients, majoritairement industriels, dans le management de leur performance et l‚Äôexploitation de leurs donn√©es.\nLes collaborateurs, tous issus de grandes √©coles, incarnent au quotidien les valeurs d‚ÄôExcellence, de Partage et d‚ÄôEngagement.\nIls associent savoir-faire technique, m√©thodologie et passion et mettent leurs comp√©tences au service de missions et projets au sein de grands groupes fran√ßais.\nMP DATA accompagne ses clients sur toute la chaine au travers de 3 p√¥les d‚Äôexpertise : Conseil et Strat√©gie, Infrastructure & CloudOPS, Data Science.\nChez MP DATA, les √©quipes commerciales cherchent des missions en fonction des envies des collaborateurs et non pas l‚Äôinverse. Les consultants sont accompagn√©s dans tous leurs projets, de la mobilit√© g√©ographique, au changement de secteur d‚Äôactivit√© en passant par le d√©veloppement de nouvelles comp√©tences.\nRejoindre MP DATA, c‚Äôest la garantie de travailler sur des sujets passionnants avec un cadre technique fort.\nDescriptif du poste :\nNous recherchons un Data Engineer exp√©riment√© pour rejoindre notre √©quipe.\nEn tant que Data Engineer, vous serez responsable de la conception, du d√©veloppement et de la mise en ≈ìuvre de pipelines de traitement de donn√©es en temps r√©el √† grande √©chelle.\nVous travaillerez avec des technologies telles que Kafka, Flink, Kinesis et vous utiliserez les services du cloud AWS pour stocker et traiter les donn√©es.\nVos responsabilit√©s :\nUtiliser Kafka pour le traitement de flux de donn√©es en temps r√©el √† grande √©chelle, en travaillant avec les producteurs, les consommateurs et les topics.\nMettre en ≈ìuvre des pipelines de traitement de donn√©es en streaming avec Flink, en appliquant des transformations complexes et en g√©rant les √©tats.\n√âcrire du code efficace et maintenable en Java / Python pour manipuler et analyser les donn√©es en temps r√©el.\nUtiliser Kubernetes pour d√©ployer et g√©rer des applications conteneuris√©es √† grande √©chelle, en assurant la r√©silience et l‚Äô√©volutivit√© des services.\nUtiliser les services AWS tels que Amazon S3, AWS Lambda, Elastic Kubernetes Service (EKS), Elastic Container Service (ECS) et Elastic Compute Cloud (EC2) pour le stockage, le traitement et le calcul des donn√©es en temps r√©el.\nSuivre les meilleures pratiques pour une utilisation efficace du cloud, en assurant la gestion des co√ªts, la s√©curit√© des donn√©es et la disponibilit√© des services.\nCollaborer avec l‚Äô√©quipe de d√©veloppement logiciel et la gestion de projets pour assurer un flux de d√©veloppement fluide et une livraison efficace des fonctionnalit√©s.\nBon √† savoir :\nCDI / ASAP / Toulouse\nProfil recherch√©:\nNous recherchons un candidat dipl√¥m√© d'une grande √©cole d'Ing√©nieur avec une premi√®re exp√©rience.\nComp√©tences n√©cessaires :\nExp√©rience significative dans un environnement industriel en mode DevOps, avec des outils tels que CICD, gitlab, Jenkins, Sonar, Nexus, XLdeploy, Camunda, etc.\nMa√Ætrise des langages de programmation tels que Python, Java et expertise dans l‚Äô√©criture et l‚Äôoptimisation du code SQL\nMa√Ætrise du fran√ßais et bonne maitrise de l‚Äôanglais.\nCapacit√© √† travailler en √©quipe et esprit d‚Äô√©quipe.\nLe processus de recrutement se d√©roule en 3 entretiens :\nPrise de contact\n1er entretien : Pr√©sentation et projet du candidat + pr√©sentation MP DATA\n2√®me entretien : Entretien de qualification technique\n3√®me entretien : Rencontre avec les √©quipes dans les locaux MP DATA + Proposition de collaboration\nShow more\nShow less",
        "details": {
            "JobDetail": [],
            "TypeContract": "CDI",
            "Salary": "",
            "Level": "",
            "Experience": null
        },
        "title": "data engineer",
        "skills": {
            "ProgLanguage": [
                "Java",
                "Python"
            ],
            "DataBase": [
                "SQL"
            ],
            "BigData": [
                "Flink"
            ],
            "CloudComputing": [
                "AWS"
            ],
            "DevTools": [
                "Jenkins"
            ],
            "Automation": [
                "Kubernetes"
            ],
            "Containers": [
                "Kubernetes"
            ],
            "Other": [
                "Cloud",
                "DevOps"
            ],
            "EnSoftSkils": [
                "Collaboration"
            ]
        }
    },
    {
        "source": "LinkedIn",
        "company": "SEVETYS",
        "location": "Paris, √éle-de-France, France",
        "link": "https://fr.linkedin.com/jobs/view/data-engineer-at-sevetys-3905649273?position=5&pageNum=5&refId=ta7dp2AfGVWmvLdIA1X0jA%3D%3D&trackingId=Pr6uHm3LOJ7s%2BqiuHJTBTA%3D%3D&trk=public_jobs_jserp-result_search-card",
        "description": "Sevetys, premier groupe fran√ßais de cliniques v√©t√©rinaires, est pr√©sent dans toute la France avec plus de 150 √©tablissements. Cr√©√© en 2016, le groupe souhaite moderniser le m√©tier et mettre la qualit√© des soins et la satisfaction client au c≈ìur de son projet.\nLe projet d‚Äôentreprise se caract√©rise par son hyper croissance et une culture de type start-up ax√©e sur le collectif, la coh√©sion, et l‚Äôengagement.\nFort de son succ√®s, Sevetys poursuit sa structuration et recrute un / une :\nData Engineer\n‚ÄãLe\nData Engineer\ntravaille en √©troite collaboration avec une √©quipe Agile pluridisciplinaire pour construire des pipelines de donn√©es de haute qualit√© permettant de mettre en ≈ìuvre des solutions analytiques. Ces solutions g√©n√®reront des informations √† partir de nos donn√©es collect√©es, permettant de faire progresser les capacit√©s de prise de d√©cision du management de l‚Äôentreprise. Ce r√¥le n√©cessite une compr√©hension approfondie de l'architecture des donn√©es, de l'ing√©nierie des donn√©es, de l'analyse des donn√©es, du reporting. Le candidat id√©al est un ing√©nieur en donn√©es/logiciel ayant au moins une premi√®re exp√©rience dans la cr√©ation de produits de donn√©es soutenant des solutions analytiques.\nMissions :\nCon√ßoit, d√©veloppe, optimise et maintient une architecture de donn√©es et des pipelines qui respectent les objectifs de l'entreprise ;\nR√©sout des probl√®mes de donn√©es afin de fournir des informations qui aident notre entreprise √† atteindre ses objectifs ;\nCr√©e des jeux de donn√©es pour les membres de l'√©quipe d'analyse afin d'am√©liorer leur productivit√© ;\nFavorise une culture du partage, de la r√©utilisation, de la stabilit√© de la conception √† l'√©chelle et de l'efficacit√© op√©rationnelle des donn√©es et des solutions analytiques ;\nContribue √† l'√©valuation, la mise en ≈ìuvre et le d√©ploiement d'outils et de processus √©mergents pour l'ing√©nierie des donn√©es analytiques afin d'am√©liorer notre productivit√© en tant qu'√©quipe ;\n√âlabore et met en ≈ìuvre des plans de communication/√©ducation sur les capacit√©s, les normes et les processus d'ing√©nierie des donn√©es analytiques ;\nTravaille en partenariat avec des analystes business et des architectes de solutions pour d√©velopper des architectures techniques pour les projets et initiatives strat√©giques de l'entreprise.\nExpertises techniques :\nExp√©rience du d√©veloppement de bases de donn√©es et d'une vari√©t√© de technologies de bases de donn√©es relationnelles ;\nExp√©rience des entrep√¥ts de donn√©es ;\nExpertise en SQL et en analyse de donn√©es ; ma√Ætrise Python ;\nId√©alement certifi√© des technologies BI du Cloud Azure (Synapse, Azure Data Factory, PurView) ;\nConnaissance de l'intelligence artificielle, des statistiques et/ou des math√©matiques appliqu√©es ;\nExp√©rience dans le d√©veloppement de solutions sur des services et infrastructures de cloud computing dans le domaine des donn√©es et de l'analyse ;\nExp√©rience du d√©ploiement de Power BI ;\nExp√©rience conceptuelle des donn√©es et de l'analyse, par exemple ETL, mod√©lisation dimensionnelle, outils de reporting, gouvernance des donn√©es, entreposage des donn√©es, donn√©es structur√©es et non structur√©es, qualit√© de donn√©es ;\nConnaissance CI/CD et GitLab fortement appr√©ci√©.\nExp√©rience agile / Digitale / gouvernance :\nPassionn√©(e) le d√©veloppement bas√© sur les donn√©es, la fiabilit√© et l'exp√©rimentation ;\nExp√©rience souhait√©e de travail au sein d'une √©quipe produit Agile collaborative ;\nConnaissance de la gouvernance de la donn√©e.\nSkills Individuels :\nMotiv√©(e) et dot√©(e) de solides comp√©tences en mati√®re de r√©solution de probl√®mes et d'apprentissage ;\nFlexibilit√© face aux changements d'orientation du travail au fur et √† mesure de l'√©volution du projet ;\nExcellentes capacit√©s de communication, d'√©coute et de persuasion.\nAttitude attendue :\nSens aigu des chiffres, curiosit√© intellectuelle et volont√© d'adapter sa position sur la base d'informations compl√©mentaires ;\nForte √©thique de travail ; capacit√© √† travailler √† un niveau abstrait et √† obtenir un consensus.\nInformations suppl√©mentaires :\nPoste √† pourvoir d√®s que possible ;\nRemboursement des frais de transports + Mutuelle ;\nPossibilit√© de t√©l√©travail jusqu'√† un jour par semaine.\nShow more\nShow less",
        "details": {
            "JobDetail": [],
            "TypeContract": "",
            "Salary": "",
            "Level": "",
            "Experience": null
        },
        "title": "data engineer",
        "skills": {
            "ProgLanguage": [
                "Python"
            ],
            "DataBase": [
                "SQL"
            ],
            "DataVisualisation": [
                "Power BI"
            ],
            "CloudComputing": [
                "Azure"
            ],
            "Other": [
                "Statistiques",
                "Cloud",
                "CI/CD"
            ],
            "EnSoftSkils": [
                "Communication",
                "Collaboration"
            ]
        }
    },
    {
        "source": "LinkedIn",
        "company": "Akkodis",
        "location": "Lille",
        "link": "https://fr.linkedin.com/jobs/view/data-engineer-h-f-at-akkodis-3890779946?position=6&pageNum=5&refId=ta7dp2AfGVWmvLdIA1X0jA%3D%3D&trackingId=51eLIaLagCCvbVYrGyhL0A%3D%3D&trk=public_jobs_jserp-result_search-card",
        "description": "La ligne de service Consulting & Solutions d‚ÄôAkkodis France renforce ses √©quipes en r√©gion Hauts-de-France et recrute un\nData engineer H/F\nen\nCDI\nsur la\nm√©tropole lilloise\n:\nDescription de la mission :\nConcevoir, mettre en oeuvre et maintenir des pipelines de donn√©es efficaces et √©volutifs dans un environnement cloud (comme AWS, Azure, Google Cloud Platform‚Ä¶)\nAssurer la qualit√© des donn√©es et des mod√®les\nD√©finir les bonnes pratiques de d√©veloppement en impl√©mentant des outils de CI/CD\nAssurer une veille technologique sur les technologies Cloud\nCapacit√© √† interagir avec des parties prenantes diverses : business analyst, architecte, m√©tier‚Ä¶\nVeiller au bon fonctionnement des pipelines en production\nProfil :\nDe formation\nBac +4/5 en informatique\nou issu d'une\n√©cole d'ing√©nieur\n, vous poss√©dez une exp√©rience de\n3 ans\nminimum en tant que data engineer ainsi que les comp√©tences suivantes :\nUne bonne connaissance des √©cosyst√®mes li√©s √† la data (Kafka, ETL, base de donn√©es‚Ä¶)\nUne premi√®re exp√©rience sur un cloud provider (AWS, Azure, GCP)\nUne bonne maitrise de langages de programmation tels que SQL, Python, Scala\nAkkodis accompagne ses clients dans la mondialisation de leurs projets, aussi un anglais courant est requis pour l‚Äôensemble de nos collaborateurs.\nProcessus de recrutement :\nUne charg√©e de recrutement vous contacte pour √©changer sur votre projet professionnel\nVous √©changez ensuite avec un.e manager sur les aspects techniques, les projets\nChez Akkodis nous sommes convaincus que de l‚Äôintelligence collective na√Æt le succ√®s. Il n‚Äôexiste pas qu‚Äôun mod√®le, nous valorisons l‚Äôagilit√© et l‚Äôexcellence, l‚Äôaudace et la cr√©ativit√©.\nEt si nous parlions ensemble de vos ambitions pour les prochaines ann√©es ?\nAkkodis est une entreprise handi-engag√©e et inclusive. Tous nos postes sont ouverts aux handicaps et √† la diversit√©. Tous diff√©rents, tous comp√©tents !\nAkkodis, est un acteur mondial de l‚Äôing√©nierie et de l‚ÄôIT et un leader dans la smart industrie. Nous accompagnons nos clients dans leurs projets de transformation digitale via 4 lignes de service : Consulting, Solutions, Talent et Academy. Akkodis est un partenaire technologique de confiance pour ses clients √† l‚Äô√©chelle internationale. Nous co-cr√©ons et nous imaginons des solutions de pointe pour r√©pondre aux d√©fis majeurs de notre soci√©t√©, qu'il s'agisse d'acc√©l√©rer la transition √©nerg√©tique et de d√©velopper la mobilit√© verte, ou encore de construire des approches centr√©es sur les utilisateurs.\nDot√©s d‚Äôune forte culture de l‚Äôinclusion et de la diversit√©, nos 50 000 experts en IT et en ing√©nierie, pr√©sents dans 30 pays, allient les meilleures comp√©tences technologiques √† une connaissance transverse de toutes les industries pour fa√ßonner un futur plus durable. Nous sommes passionn√©s par l‚Äôid√©e d‚Äôinventer ensemble un avenir meilleur.\nAkkodis en France, ce sont pr√®s de 9.000 experts en IT et en ing√©nierie r√©partis sur l'ensemble du territoire, des collaborateurs partageant des valeurs fortes d'honn√™tet√©, de respect, d'√©quit√© et d'inclusion. Notre engagement : leur permettre au quotidien d'√™tre eux-m√™mes au travail, et acteurs de leur vie et de leur d√©veloppement au sein d'Akkodis.\n*Akkodis est une marque commerciale sous laquelle les entit√©s AKKA et Modis op√®rent\nShow more\nShow less",
        "details": {
            "JobDetail": [],
            "TypeContract": "CDI",
            "Salary": "",
            "Level": "",
            "Experience": "3 an(s)"
        },
        "title": "data engineer",
        "skills": {
            "ProgLanguage": [
                "Scala",
                "Python"
            ],
            "DataBase": [
                "SQL"
            ],
            "CloudComputing": [
                "GCP",
                "AWS",
                "Google Cloud Platform",
                "Azure"
            ],
            "Other": [
                "Cloud",
                "CI/CD"
            ]
        }
    },
    {
        "source": "LinkedIn",
        "company": "FINAXYS",
        "location": "Paris, √éle-de-France, France",
        "link": "https://fr.linkedin.com/jobs/view/data-engineer-python-at-finaxys-3887107285?position=7&pageNum=5&refId=ta7dp2AfGVWmvLdIA1X0jA%3D%3D&trackingId=LAW%2BLRyFCy23JG8FyMIylQ%3D%3D&trk=public_jobs_jserp-result_search-card",
        "description": "LE CONTEXTE\nLeader en\nIT\n, dans les domaines Banque\n,\nFinance\net\nAssurance\n,\nFinaxys\nest un cabinet de\nconseil\ncr√©√© en 2008. Nous accompagnons au quotidien les plus grandes banques du pays sur leur\ntransformation digitale\n(BNP Paribas, Soci√©t√© G√©n√©rale, Cr√©dit Agricole, Natixis, etc.)\nNos clients bancaires travaillent √©galement dans des contextes Big Data sur des applications centrales rattach√©es aux Datalakes.\nLES MISSIONS\nD√©veloppement et traitements sur des applications Big Data (Python)\n√ätre force de proposition sur les choix techniques les plus pertinents\nMaintenir la qualit√© des solutions, mesure de cette qualit√©, alerte sur les non-conformit√©s et validation des solutions d√©finitives.\nAnalyser des risques li√©s aux solutions envisag√©es et proposition des actions de rem√©diation.\nApporter des solutions IT r√©pondant au mieux aux besoins du business port√© par la/le Product Owner (M√©tiers/Fonctions) en cherchant toujours la maximisation de la valeur g√©n√©r√©e\nAccompagner les √©quipes dans les migrations Cloud\nENVIRONNEMENT TECHNIQUE\nPython\nPandas\nScirpting Big Data\nCulture DevOps (Jenkins, Maven, Ansible)\nPROFIL\nComp√©tences Techniques et Fonctionnelles requises\nMaitrise obligatoire de l‚Äôanglais\nShow more\nShow less",
        "details": {
            "JobDetail": [],
            "TypeContract": "",
            "Salary": "",
            "Level": "",
            "Experience": null
        },
        "title": "data engineer",
        "skills": {
            "ProgLanguage": [
                "Python"
            ],
            "DataAnalytics": [
                "Pandas"
            ],
            "DevTools": [
                "Jenkins"
            ],
            "Automation": [
                "Ansible"
            ],
            "Other": [
                "Cloud",
                "Big Data",
                "DevOps"
            ]
        }
    },
    {
        "source": "LinkedIn",
        "company": "Apside",
        "location": "Nantes, Pays de la Loire, France",
        "link": "https://fr.linkedin.com/jobs/view/data-engineer-at-apside-3909772916?position=8&pageNum=5&refId=ta7dp2AfGVWmvLdIA1X0jA%3D%3D&trackingId=KiWiQcocdp%2B9zcfFjDOmIw%3D%3D&trk=public_jobs_jserp-result_search-card",
        "description": "Offre d'Emploi : DATA ENGINEER H/F chez Apside\nDescription du poste :\nNous sommes √† la recherche d'un Data Engineer passionn√© pour rejoindre notre √©quipe dynamique. Si vous avez une expertise dans le Big Data, la Data Science, l'analyse de donn√©es et l'architecture de donn√©es, cette opportunit√© est faite pour vous. Int√©grer notre communaut√© Data, c‚Äôest l‚Äôassurance de progresser, innover, partager, vous certifier et rendre service √† nos clients.\nVos missions :\nD√©veloppement des jobs Spark pour la collecte et la transformation des donn√©es comptables disponibles dans les bucket S3.\nOptimisation des jobs Spark.\nD√©veloppement des batchs Java et √©criture des donn√©es au formats comptables.\n√âcriture et ordonnancement des DAGs Airflow.\nSupport du d√©veloppement Spark Scala.\nMaintenance applicative.\nProduction des √©v√©nements d√©di√©s √† la plateforme de donn√©es.\n.\nVotre r√¥le, vos comp√©tences :\nVous ma√Ætrisez au minimum un langage de programmation appliqu√© √† l‚Äôanalyse de donn√©es (SQL, Scala, Python, Java).\nVous √™tes passionn√© par le Big Data et le Machine Learning.\nVous concevez et mettez en ≈ìuvre des strat√©gies s√©curis√©es d'acquisition et d'int√©gration de donn√©es.\nVous configurez des r√©f√©rentiels de donn√©es √† la pointe de la technologie dans des environnements distribu√©s, majoritairement dans le cloud (Google Cloud Platform, Azure, AWS) et/ou en environnement Hadoop (distribution MapR, Cloudera, Hortonworks).\nEnvironnement technique :\nSQL\nPython/Spark\nCloud AWS: AWS Glue, AWS Lambda (possibilit√© de vous former sur AWS)\nStockage objet (AWS S3)\nOrchestration et scheduling de t√¢ches (Apache Airflow)\nBases analytiques et bases NoSQL (ElasticSearch, AWS Athena)\nVotre profil :\nFort de 4 ann√©es d‚Äôexp√©rience en Data Engineer/ DATA ANALYST\nTitulaire d‚Äôune formation sup√©rieure IT.\nCapacit√© √† s‚Äôint√©grer dans un cadre technique client tout en √©tant √† m√™me de proposer des pistes d‚Äôam√©liorations pertinentes.\nAutonome dans la gestion des projets.\nCurieux et impliqu√©, vous √™tes bon communicant avec les clients et les acteurs de culture technique diff√©rente.\nDe bonnes raisons de rejoindre Apside ?\nUn esprit start-up avec la stabilit√© d‚Äôun grand groupe, qui favorise l‚Äôagilit√©, le travail d‚Äô√©quipe et la proximit√©. Alors qu‚ÄôApside ne cesse d‚Äôagrandir sa famille d√©j√† forte de plus de 3000 consultants, nous sommes √† la recherche de nos nouveaux talents !\nCDI + package salarial avantageux (Mutuelle offerte, RTT, Tickets Restaurant, Int√©ressement ...)\nParticipez et animez nos soir√©es techniques (Project Lab, Test Lab‚Ä¶),\nDevenez speaker (Devoxx, DevFest, NCraft‚Ä¶),\nFormez vous avec l‚ÄôAcademy By Apside (e-learning, formation, certification).\nD√©veloppez votre r√©seau (Soir√©es trimestrielles, Afterwork, Soir√©es d‚Äôint√©gration‚Ä¶),\nInt√©grez notre Communaut√©s d‚ÄôExperts et testez les derni√®res innovations techniques sur notre Bac √† Sable !\nApside s‚Äôengage en faveur de l‚Äôemploi des personnes en situation de handicap avec sa filiale Apsid‚ÄôEA : 1√®re entreprise adapt√©e totalement int√©gr√©e √† une ESN !\nPour aller plus loin avec APSIDE !\nhttps://www.apside.com/fr/nos-offres-emploi/?_joboffer-agency=17833&_paged=2\nCe poste de DATA ENGINEER est fait pour vous !\nShow more\nShow less",
        "details": {
            "JobDetail": [],
            "TypeContract": "CDI",
            "Salary": "17833",
            "Level": "",
            "Experience": null
        },
        "title": "data engineer",
        "skills": {
            "ProgLanguage": [
                "Java",
                "Scala",
                "Python"
            ],
            "DataBase": [
                "Elasticsearch",
                "SQL",
                "NoSQL"
            ],
            "BigData": [
                "Hadoop",
                "Apache Airflow",
                "Spark"
            ],
            "CloudComputing": [
                "AWS",
                "Google Cloud Platform",
                "Azure"
            ],
            "Automation": [
                "Airflow"
            ],
            "Other": [
                "Machine Learning",
                "Cloud",
                "Big Data"
            ]
        }
    },
    {
        "source": "LinkedIn",
        "company": "AXA en France",
        "location": "Hauts-de-Seine, √éle-de-France, France",
        "link": "https://fr.linkedin.com/jobs/view/data-engineer-senior-at-axa-en-france-3884386043?position=9&pageNum=5&refId=ta7dp2AfGVWmvLdIA1X0jA%3D%3D&trackingId=JA%2FYt%2BTcyAXjKeciB27Q5g%3D%3D&trk=public_jobs_jserp-result_search-card",
        "description": "Environnement\nEn tant que\nSenior Data Engineer F/H\n, vous allez contribuer directement aux projets des directions m√©tier (ex : fraude sant√©, multi√©quipements, pricing IARD, optimisation du lead management, fragilit√© auto, ‚Ä¶) d‚ÄôAXA France et √† la construction du socle technique Big Data.\nVous allez int√©grer une √©quipe d'une dizaine de personne compos√©e de Data Engineer et des Tech Lead travaillant en mode Feature Team au sein des tribus m√©tier de la Direction Transformation Digital Tech et DATA (DT2).\nLa Direction Transformation Digital Tech et DATA d'AXA France en quelques mots :\n- Une organisation agile en feature teams : tribus, guildes, squads\n- Des projets sur des applications innovantes √† fort trafic (web, mobile‚Ä¶)\n- Des m√©thodologies craft (TDD, BDD, clean code, code review‚Ä¶) et DevOps\n- Une communaut√© de partage de bonnes pratiques (BBL, dojo, meetup, conf‚Ä¶)\nVotre r√¥le et vos missions\nVous aurez pour missions principales de d√©velopper les projets Big Data demand√©s par le m√©tier, et notamment :\nPasser de la donn√©e brute √† de la donn√©e exploitable, expos√©e sous forme de tables requ√™tables dans le datalake\nConsolider ces donn√©es au fur et √† mesure de leur alimentation r√©currente dans le data lake\nLes exploiter pour atteindre la finalit√© business (exposition de business view, r√©int√©gration des r√©sultats dans le SI, service de scoring, ‚Ä¶)\nDe travailler √† la cr√©ation du socle technique Big Data et industrialiser le cycle de d√©veloppement de l'√©quipe\nDe mettre en place et de garantir le respect dans la dur√©e d'un processus qualit√© sur l'ensemble du cycle de DEV (documents, tests unitaires / int√©gration / fonctionnels, commentaires, versionning, etc.)\nVotre profil\nVous justifiez de plusieurs exp√©riences significatives (+ de 5 ans) sur du\nd√©veloppement big data, en particulier sur du PySpark.\nComp√©tences techniques :\nConnaissances avanc√©es en d√©veloppement en\nPySpark\n(Spark avec le langage Python)\nMaitrise de l'environnement\nMicrosoft Azure\nConnaissances avanc√©es d'outils de BI comme\nPowerBI\nComp√©tences transverses :\nCapacit√© √† interagir avec des parties prenantes diverses : Business analyst, Architectes, M√©tier\nExp√©rience en mode de delivery Agile (Scrum, Kanban, etc...)\nDriver et accompagner des Data Engineer junior sur les aspects technique\nEt Id√©alement :\nDes Connaissances sur Azure DevOps, Azure Pipeline, GIT, JIRA\nMaitrise des Traitements Big Data en mode Streaming\nMaitrise des Bases de donn√©es relationnelles et NoSQL\nUne exp√©rience professionnelle avec des outils comme Azure Databricks, Azure Data Lake Storage ou encore Azure Data Factory\nQui sommes nous ?\nAXA est un des leaders de l‚Äôassurance et de la gestion d‚Äôactifs dans le monde.\nNous aidons nos 108 millions de clients √† traverser les petites et grandes difficult√©s de la vie.\nChaque jour, nous agissons ensemble pour inventer la meilleure mani√®re de les prot√©ger et voulons donner √† chacun les moyens de vivre une vie meilleure.\nUn challenge qui donne le sourire et envie de se lever le matin !\nChez AXA, nous sommes persuad√©s que pour bien prendre soin de nos clients, nous devons commencer par bien prendre soin de nos collaborateurs. C‚Äôest pour cette raison que nous menons une politique RH engag√©e qui favorise la diversit√©, qui pr√©serve l‚Äô√©quilibre vie priv√©e-vie professionnelle et acc√©l√®re le d√©veloppement des comp√©tences et des carri√®res.\nAinsi, en rejoignant AXA France vous travaillerez dans une entreprise responsable, offrant une v√©ritable culture d‚Äôexpertise, acc√©l√©rant le d√©veloppement des comp√©tences de chacun et proposant une r√©mun√©ration attractive.\nPourquoi nous rejoindre ?\nVous √™tes porteur d‚Äôid√©es et d‚Äôinitiatives innovantes ? Vous proposez des solutions et √™tes au service du client ? Faites partie de notre grande famille en rejoignant\nUn leader mondial offrant des opportunit√©s de carri√®res int√©ressantes\nUne entreprise qui donne une place de choix √† l‚Äôinnovation, √† l‚Äôinitiative et aux actions solidaires (notamment via l‚Äôassociation AXA Atout C≈ìur)\nUn environnement inclusif √† tous les niveaux (mixit√©, handicap, initiatives pour favoriser l‚Äôinsertion des jeunes, orientation sexuelle, etc.)\nUn acc√®s √† de multiples avantages (cong√©s, temps partiel, t√©l√©travail, etc.)\nUn cadre stimulant, qui permet de rencontrer des collaborateurs performants et d‚Äôenrichir ses comp√©tences\nVictime ou t√©moin, en cas de discrimination, vous pouvez adresser vos signalements et/ou alertes discrimination √† alerte.discrimination.harcelement@axa.fr\nShow more\nShow less",
        "details": {
            "JobDetail": [
                "Junior",
                "Senior"
            ],
            "TypeContract": "",
            "Salary": "",
            "Level": "",
            "Experience": "5 an(s)"
        },
        "title": "data engineer",
        "skills": {
            "ProgLanguage": [
                "Python"
            ],
            "DataBase": [
                "NoSQL"
            ],
            "BigData": [
                "Databricks",
                "Spark"
            ],
            "CloudComputing": [
                "Azure"
            ],
            "DevTools": [
                "Git"
            ],
            "Collaboration": [
                "Teams",
                "JIRA"
            ],
            "Other": [
                "Big Data",
                "DevOps"
            ],
            "EnSoftSkils": [
                "Initiative"
            ]
        }
    },
    {
        "source": "LinkedIn",
        "company": "Beelix",
        "location": "Paris, √éle-de-France, France",
        "link": "https://fr.linkedin.com/jobs/view/data-engineer-at-beelix-3865239426?position=10&pageNum=5&refId=ta7dp2AfGVWmvLdIA1X0jA%3D%3D&trackingId=xgTZ8s7KT%2BRRnLHwJ5y8rA%3D%3D&trk=public_jobs_jserp-result_search-card",
        "description": "Qui sommes-nous ?\nDepuis 2016, nous accompagnons nos clients sur des probl√©matiques de Product Management, Data et Design Thinking. Beelix contribue √† fa√ßonner le monde de demain en participant aux grandes avanc√©es des secteurs suivants:\nüöóAutomobile\n‚ö°Energie\nüì°M√©dias & T√©l√©coms\nüëóLuxe & Retail\nüí∂ Banque, Finance & Assurance\n‚úàÔ∏èD√©fense\nAujourd‚Äôhui, Beelix compte plus de 200 collaborateurs motiv√©s et dynamiques. Lab√©lis√©e Great Place To work en 2023, Beelix est aussi une entreprise engag√©e o√π il fait bon vivre.\nDans le cadre de notre d√©veloppement, nous recherchons un Data Engineer en √éle-de-France.\nQuelles missions au quotidien ?\nVous aurez pour missions principales de d√©velopper les projets Big Data demand√©s par le m√©tier, et notamment :\nPasser de la donn√©e brute √† de la donn√©e exploitable, expos√©e sous forme de tables requ√™tables dans le Datalake\nConsolider ces donn√©es au fur et √† mesure de leur alimentation r√©currente dans le Datalake\nLes exploiter pour atteindre la finalit√© business (exposition de Business View, r√©int√©gration des r√©sultats dans le SI, service de scoring, ‚Ä¶)\nDe mettre en place et de garantir le respect dans la dur√©e d'un processus qualit√© sur l'ensemble du cycle de DEV (documents, tests unitaires / int√©gration / fonctionnels, commentaires, versionning, etc.)\nAccompagner les Data Engineers sur son p√©rim√®tre pour garantir la qualit√© des livrables\nExpertise souhait√©e\nExpertise en SPARK et PySpark\nExpertise sur Databricks\nUne exp√©rience sur un cloud provider public comme Azure (id√©alement), AWS, ou GCP\nConnaissances avanc√©es d'outils de BI comme PowerBI (id√©alement) ou Spotfire\nCapacit√© √† interagir avec des parties prenantes diverses : Business analyst, Architectes, M√©tier\nEtre expert dans les pratiques du Software Craftsmanship (Test Driven Development, Behavior Driven Development, Clean Code, Code Reviews, etc.)\nDes Connaissances sur Azure DevOps, Azure Pipeline, GIT\nMaitrise des Traitements Big Data en mode Streaming\nMaitrise des Bases de donn√©es relationnelles et NoSQL\nUne exp√©rience professionnelle avec des outils comme Azure Databricks, Azure Data Lake Storage ou encore Azure Data Factory\nA propos de vous ?\nDipl√¥m√© d'une √©cole d'ing√©nieurs ou √©quivalent\nAu moins 3 ans d'exp√©rience en tant que Data Engineer\nExp√©rience en mode de Delivery Agile (Scrum, Kanban, etc.‚Ä¶)\nVous avez un bon niveau d‚Äôanglais tant √† l‚Äô√©crit qu‚Äô√† l‚Äôoral\nPourquoi nous rejoindre ?\nUn suivi et un accompagnement au quotidien\nUn organisme de formation certifi√© Qualiopi, un abonnement linkedin learning pour chaque salari√© et des partenariats avec des sp√©cialistes pour d‚Äôautres expertises\nDe nombreux √©v√©nements : Afterworks, Communaut√©s m√©tiers, Happy talks‚Ä¶\nune Exp√©rience personnalis√©e bas√©e sur vos besoins gr√¢ce au Pr√©dictive Index\nNotre package ¬´ unBeelievable ¬ª : 100% du titre de transport, Tickets restaurants, CSE, Prime de participation ...\nNombreux √©v√®nements (afterworks, sport, etc) et des communaut√©s m√©tiers dynamiques\nLe processus de recrutement ?\n√âchange t√©l√©phonique (15 min)\nEntretien 1 RH pour apprendre √† vous conna√Ætre\nEntretien 2 avec votre futur N+1 pour appr√©hender la relation manag√©riale\nEntretien 3 avec un Responsable commercial pour avoir la vision strat√©gique\nShow more\nShow less",
        "details": {
            "JobDetail": [],
            "TypeContract": "",
            "Salary": "100",
            "Level": "",
            "Experience": "3 an(s)"
        },
        "title": "data engineer",
        "skills": {
            "DataBase": [
                "NoSQL"
            ],
            "BigData": [
                "Databricks",
                "Spark"
            ],
            "CloudComputing": [
                "GCP",
                "AWS",
                "Azure"
            ],
            "DevTools": [
                "Git"
            ],
            "Other": [
                "Cloud",
                "Big Data",
                "DevOps"
            ]
        }
    },
    {
        "source": "LinkedIn",
        "company": "Renault Group",
        "location": "Le Plessis-Robinson, √éle-de-France, France",
        "link": "https://fr.linkedin.com/jobs/view/data-engineer-h-f-at-renault-group-3904830231?position=1&pageNum=7&refId=m3%2FMjbsrRC0%2FAGJwy5bQNw%3D%3D&trackingId=HMXluzzoE9T1Sim4D7X%2BAg%3D%3D&trk=public_jobs_jserp-result_search-card",
        "description": "Votre environnement\nLe m√©tier Procurement de Renault est en pleine transformation et n√©cessite des outils performants pour g√©rer son r√©seau de fournisseurs, simuler des sc√©narios et anticiper les risques associ√©s (logistiques, qualit√©, manag√©riaux, sociaux-√©conomiques, √©cologiques).\nEn s‚Äôappuyant sur les partenariats strat√©giques de Renault avec\nGoogle Cloud\n(utilisant la pile compl√®te de donn√©es GCP), la fonction Procurement a d√©cid√© de cr√©er une nouvelle\nplateforme DATA et IA\nqui r√©pondent aux d√©fis actuels du secteur de la mobilit√©.\nC‚Äôest pourquoi, nous sommes donc √† la recherche d‚Äôun(e)\nData Engineer\nau sein de la\nDirection IS Procurement (Domaine Supplier Quotation & ESG)\n.\nCe r√¥le consistera √† mettre en place une plateforme pour la qualification de nos fournisseurs et la gestion des risques d‚Äôapprovisionnement futurs.\nCette plateforme inclura √©galement les nouveaux enjeux de r√©glementation ESG √† l‚Äô√©chelle mondiale.\nLe poste est bas√© au\nPlessis-Robinson (France) en CDI.\nVous b√©n√©ficiez de\n2 √† 3\njours\nde\nt√©l√©travail par semaine.\nVos missions\nEn qualit√© de\nData Engineer\nvous √™tes\ngarant.e de l‚Äôacc√®s qualitatif aux sources de donn√©es\n. Vous\nd√©veloppez\ndes outils permettant d‚Äôautomatiser les traitements autour de la data (ingestion, stockage, transformation) afin d‚Äôen faciliter son exploitation par les √©quipes Data ainsi que par le reste des √©quipes informatiques. Vos principales missions sont :\nConcevoir des solutions robustes permettant le traitement de volumes importants de flux de donn√©es\nAssurer l‚Äôint√©gration de donn√©es provenant de sources multiples (applications ou ext√©rieur √† l‚Äôentreprise)\nD√©finir et faire respecter les bonnes pratiques et r√®gles √† suivre autour des sujets d‚Äôingestion, stockage et de transformation de la donn√©e\nConstruire l‚Äôarchitecture relative aux plateformes data ainsi qu‚Äô√† ses composants\nEffectuer une veille technologique importante afin d‚Äôassurer que les plateformes data soient les plus efficientes possibles\nVous collaborerez au jour le jour avec les √©quipes m√©tiers ainsi qu‚Äôavec les autres fonctions du\nP√¥le Architecture & Data\n(Data Analysts et Scientists, architectes, ‚Ä¶), exploitant des t√©raoctets de donn√©es (√©v√©nements en mode streaming, traitements en batch et temps r√©els et les appels aux APIs) afin entre autres d‚Äôalimenter √† terme des mod√®les de machine learning (segmentation fournisseurs, d√©tection de risques, Tecno watch & market search‚Ä¶).\nVotre profil\nVous √™tes dipl√¥m√©(e) d‚Äôun BAC+5 en universit√© ou en √©cole d‚Äôing√©nieur avec\nun parcours significatif dans\nl‚Äôinformatique\n(Domaine DATA) avec\nau moins 5 ann√©es d‚Äôexp√©rience.\nVous avez une app√©tence pour la\nDATA\n: validation, transformation, analyse, valorisation, et vous disposez d‚Äôune\nsolide exp√©rience en d√©veloppement Java\n,\nScala\net\nPython\net\nrequ√™tage SQL\nsur des gros volumes de donn√©es.\nVous avez une exp√©rience de d√©veloppement et orchestration de chaines\nETL\ncomplexes via Composer (GCP), Airflow ou √©quivalent.\nVous savez utiliser des services cloud\nGoogle Cloud Platform\n(BigQuery, Cloud Storage, PubSub, Beam, Dataflow, Kubernetes, Composer, Big Table, Firestore), Git, JSON, Bash, Docker.\nVous avez fait de l‚Äô\nadministration\net\nconfiguration de syst√®mes\n.\nVous avez une forte capacit√© de\ntravailler dans un contexte multiculturel,\nvous avez un esprit orient√© ¬´\nutilisateur final\n¬ª et vous faites preuve\nd‚Äôautonomie\n. La pratique du\nframework Agile Scrum/Kanban est acquise\n.\nVous avez une grande\ncapacit√© d‚Äôanalyse\net savez prendre du recul. Vous faites preuve de\nrigueur\net d‚Äô\nesprit de synth√®se\n.\nVous avez un\nbon niveau d'anglais √©crit et oral\n, facteur cl√© de r√©ussite dans le poste (√©quipes internationales bas√©es en Inde, Roumanie...).\nVous vous reconnaissez dans cette annonce ? Alors ce poste est fait pour vous !\nRejoignez-nous ! #CarMakerCareMakers\nD√©couvrez notre processus de recrutement\n: https://www.renaultgroup.com/talents/nos-offres-dans-le-monde/\nShow more\nShow less",
        "details": {
            "JobDetail": [],
            "TypeContract": "CDI",
            "Salary": "",
            "Level": "Bac+5",
            "Experience": null
        },
        "title": "data engineer",
        "skills": {
            "ProgLanguage": [
                "Java",
                "Bash",
                "Scala",
                "Python"
            ],
            "DataBase": [
                "SQL"
            ],
            "DataSerialization": [
                "Json"
            ],
            "CloudComputing": [
                "GCP",
                "Google Cloud Platform"
            ],
            "DevTools": [
                "Git",
                "Docker"
            ],
            "DBMS": [
                "BigQuery"
            ],
            "Automation": [
                "Airflow",
                "Kubernetes"
            ],
            "Containers": [
                "Docker",
                "Kubernetes"
            ],
            "Other": [
                "Machine Learning",
                "Cloud"
            ]
        }
    },
    {
        "source": "LinkedIn",
        "company": "Devoteam Innovative Tech",
        "location": "Lyon, Auvergne-Rh√¥ne-Alpes, France",
        "link": "https://fr.linkedin.com/jobs/view/data-engineer-at-devoteam-innovative-tech-3889051125?position=2&pageNum=7&refId=m3%2FMjbsrRC0%2FAGJwy5bQNw%3D%3D&trackingId=IEJ4ZmL2g0XiUrCZk88fDg%3D%3D&trk=public_jobs_jserp-result_search-card",
        "description": "Company Description\nAvec pr√®s de 10 000 collaborateurs √† travers le monde, nous accompagnons les entreprises dans leur transformation num√©rique. Nous imaginons et concr√©tisons leurs ambitions gr√¢ce aux possibilit√©s infinies des plateformes digitales, pour faire √©voluer leur culture et leur mode de travail, et cr√©er de la valeur dans leurs organisations.\nPr√©sent dans 18 pays d‚ÄôEurope et du Moyen-Orient et fort de 25 ans d‚Äôexp√©rience, nous mettons la \"Technologie au service de l‚ÄôHomme\" afin de construire un monde plus humain et plus durable.\nTravailler chez Devoteam, c‚Äôest :\ntravailler aux c√¥t√©s de partenaires comme Google, Microsoft, AWS ou Salesforce dont nous impl√©mentons les solutions chez nos clients.\n√©voluer dans un groupe international qui vous accompagne dans le d√©veloppement de votre carri√®re avec des parcours de formation et de certification adapt√©s.\nrejoindre une √©quipe sp√©cialis√©e, accompagn√© par un manager de proximit√© qui saura vous guider dans vos choix et favoriser les √©changes avec vos pairs, que ce soit lors d'√©v√©nements techniques ou conviviaux.\ngrandir dans une entreprise qui challenge ses √©quipes en √©tant agile et ambitieuse, s‚Äôadaptant pour permettre les succ√®s individuels et collectifs.\nLa mission\nEn pleine transformation digitale, le client con√ßoit et fournit des produits et services digitaux pour accompagner la transformation digitale de ses entit√©s dans le monde entier.\nLe client souhaite renforcer les capacit√©s de d√©veloppements d‚Äôune des √©quipes\nsur la technologie de d√©veloppement Databricks (Databricks, Python, Spark SQL) dans un\nenvironnement 100% Cloud Azure. Une exp√©rience Azure pass√©e serait\nappr√©ci√©e.\nLes principales activit√©s sont :\n‚Ä¢ D√©veloppements de pipelines Data permettant la construction et l‚Äô√©volution de leur\nDatalake\n‚Ä¢ Participation aux d√©ploiements sur les environnements de test et de production\n‚Ä¢ Maintien en condition op√©rationnelle des √©l√©ments logiciels en production\nEn fonction des autres comp√©tences du candidats, d‚Äôautres activit√©s pourraient √™tre :\n‚Ä¢ Participation √† des r√©unions de conceptions et de chiffrages\n‚Ä¢ Participation √† des r√©unions de prises de d√©cisions techniques\n‚Ä¢ Conseils techniques au Tech Lead / Architecte de l‚Äô√©quipe ¬´ Data ¬ª et de la\nplateforme\nLe candidat devra pouvoir s‚Äôint√©grer dans un projet dynamique en m√©thodologie agile et\ndans une √©quipe de grande taille.\nComp√©tences techniques attendues:\nDatabricks\nPython\nTravailler en SCRUM\nEnvironnement Azure\nAdditional information\nLe Groupe Devoteam ≈ìuvre pour l'√©galit√© des chances, pour la promotion de ses collaboratrices et de ses collaborateurs au m√©rite et lutte activement contre toute forme de discrimination. Nous sommes persuad√©s que la diversit√© contribue √† la cr√©ativit√©, au dynamisme et √† l'excellence de notre organisation. Tous nos postes sont ouverts aux personnes en situation de handicap.\nShow more\nShow less",
        "details": {
            "JobDetail": [],
            "TypeContract": "",
            "Salary": "",
            "Level": "",
            "Experience": "25 an(s)"
        },
        "title": "data engineer",
        "skills": {
            "ProgLanguage": [
                "Python"
            ],
            "DataBase": [
                "SQL"
            ],
            "BigData": [
                "Databricks",
                "Spark"
            ],
            "CloudComputing": [
                "AWS",
                "Azure"
            ],
            "Other": [
                "Cloud"
            ]
        }
    },
    {
        "source": "LinkedIn",
        "company": "FRG Technology Consulting",
        "location": "√éle-de-France, France",
        "link": "https://fr.linkedin.com/jobs/view/data-engineer-data-ops-at-frg-technology-consulting-3913842168?position=3&pageNum=7&refId=m3%2FMjbsrRC0%2FAGJwy5bQNw%3D%3D&trackingId=fueQLWECQUoFhtWNsICVBQ%3D%3D&trk=public_jobs_jserp-result_search-card",
        "description": "Vous √™tes un expert passionn√© par la Data et √† la recherche de d√©fis excitants ? Mon client recherche actuellement un\nData Engineer\n/ Data Ops\ntalentueux pour rejoindre une √©quipe dynamique et humaine.\nMissions principales :\nParticipation active au d√©ploiement de la nouvelle plateforme sur Azure & Snowflake\nForte autonomie et gestion compl√®te des projets data\nAnalyse des besoins actuels et futurs\nCr√©ation de sp√©cifications fonctionnelles et techniques\nMod√©lisation de donn√©es\nD√©veloppement de packages SSIS\nInt√©gration des donn√©es dans SnowFlake & Azure,\nCr√©ation de rapports avec Power BI et Excel\nProfil recherch√© :\n3 √† 4 ans d'exp√©rience\nminimum\ndans la BI (SSIS, SQLServer, SSAS, SSRS) et/ou le cloud (Azure , Snowflake) ainsi qu'en SQL\nComp√©tences en\narchitecture sur Snowflake\nfortement appr√©ci√©es\n1 √† 2 ans d'exp√©rience en tant que DevOps ( CI/CD ; GitLab)\nAutonome, rigoureux et anglais courant\nShow more\nShow less",
        "details": {
            "JobDetail": [],
            "TypeContract": "",
            "Salary": "3",
            "Level": "",
            "Experience": "4 an(s)"
        },
        "title": "data engineer",
        "skills": {
            "DataBase": [
                "SQL"
            ],
            "DataVisualisation": [
                "Power BI"
            ],
            "CloudComputing": [
                "Azure"
            ],
            "DBMS": [
                "Snowflake"
            ],
            "Other": [
                "Cloud",
                "DevOps",
                "CI/CD"
            ]
        }
    },
    {
        "source": "LinkedIn",
        "company": "Mobiskill | WEFY Group",
        "location": "Paris, √éle-de-France, France",
        "link": "https://fr.linkedin.com/jobs/view/data-engineer-at-mobiskill-wefy-group-3907393935?position=4&pageNum=7&refId=m3%2FMjbsrRC0%2FAGJwy5bQNw%3D%3D&trackingId=orRfmeGxiNXVgrUdTGjoxQ%3D%3D&trk=public_jobs_jserp-result_search-card",
        "description": "La soci√©t√© :\nLe produit repose sur la data, leur solution bas√©e sur de l‚Äôintelligence artificielle permet de personnaliser le monde de la promotion et de la fid√©lisation. Ils viennent d'√™tre rachet√©s et ont une forte ambition pour leur expansion internationale.\nLes missions :\n- Travailler avec les data scientists pour apporter des solutions\n- Industrialiser les mod√®les\n- Optimiser la performance du produit\n- D√©velopper des outils big data pour scaler\n- Mentorer des profils plus juniors\nStack :\n- Scala\n- Spark / Spark Streaming\n- Kafka\n- GCP\n- Cassandra\n- Docker\nProfil recherch√© :\n- Entre 3 et 5 ans d'exp√©rience dans le Data Engineering\n- Exp√©rience en Scala/Spark\n- Exp√©rience sur cloud (tr√®s id√©alement GCP)\n- Pr√™t √† faire des missions polyvalentes\n- Ouvert √† d'autres technos (ils ont pour objectif d'impl√©menter prochainement des outils en Python)\nPourquoi les rejoindre :\n- Expansion internationale : USA, Br√©sil, Russie, Espagne‚Ä¶\n- Une stack √† la pointe et un champs d‚Äôaction pour POCer de nouvelles technos si il y a un int√©r√™t business\n- Un encadrement bienveillant : les 2 leads techniques sont deux excellents techs ET d‚Äôexcellents mentors avec qui √©changer sur comment faire avancer la soci√©t√© (tu serais le troisi√®me maillons de la chaine).\n- Politique remote hybride\n- Des bureaux dans Paris intra-Muros\n- Une r√©mun√©ration pouvant d√©passer 70k (avec package)\n- Une entreprise tr√®s tech, particuli√®rement orient√©e Data\nH√¢te de vous en dire plus rapidement !\nShow more\nShow less",
        "details": {
            "JobDetail": [
                "Hybride",
                "Remote",
                "Junior"
            ],
            "TypeContract": "",
            "Salary": "Package",
            "Level": "",
            "Experience": "5 an(s)"
        },
        "title": "data engineer",
        "skills": {
            "ProgLanguage": [
                "Scala",
                "Python"
            ],
            "DataBase": [
                "Cassandra"
            ],
            "BigData": [
                "Spark"
            ],
            "CloudComputing": [
                "GCP"
            ],
            "DevTools": [
                "Docker"
            ],
            "SoftBigDataProcessing": [
                "Cassandra"
            ],
            "Containers": [
                "Docker"
            ],
            "Other": [
                "Cloud",
                "Big Data"
            ]
        }
    },
    {
        "source": "LinkedIn",
        "company": "Equativ",
        "location": "Paris, √éle-de-France, France",
        "link": "https://fr.linkedin.com/jobs/view/data-engineer-at-equativ-3814251519?position=5&pageNum=7&refId=m3%2FMjbsrRC0%2FAGJwy5bQNw%3D%3D&trackingId=K3xNAWACEsa%2BL%2Fe8C6y7wQ%3D%3D&trk=public_jobs_jserp-result_search-card",
        "description": "üë´ About the team\nAt Equativ, we‚Äôre on a mission to develop advertising technologies that empower our customers to reach their digital business goals. This means that we rely on massively scalable, widely distributed, highly available, and efficient software systems; the platform deals with over 100 billions requests per day and above 40 Gbps of network traffic.\nOur innovation team based in Paris, Nantes, Limoges, Krak√≥w and Berlin is composed of 90 straightforward and energetic engineers working in an Agile environment and ready to tackle the most complex technical challenges.\nOur data engineering team is composed of 10 skilled engineers and is based in Paris. We are part of the R&D department which is composed of 140+ engineers spread across Paris, Nantes, Limoges, Krak√≥w and Berlin all working in an Agile environment and ready to tackle the most complex technical challenges.\nOur mission üëá\nData Engineering team is central to Equativ‚Äôs data centric business and is responsible to ingest, transform, model and redistribute all data coming from our adtech platform.\nWe aim at building scalable and robust Big Data platforms from ingestion to business actionable consumption. Our Big Data ecosystem must handle massive log ingestion (tens of billions per day), short & long term data storage, complex data modelling, real-time and batch ELT as well as providing external access through dedicated APIs.\nData Engineers serve Equativ data directly to our customers and throughout the company whether it is for BI analysis, data science algorithms (clustering and optimization), customer reporting, invoicing and more.\nEquativ Data Engineering team is engaged in an ambitious migration of its main data stack (Hadoop on-premise) to GCP with the objective to increase reporting features, lower maintenance time, improve performances and simplify the access to our raw data.\nWhat you'll do ‚úèÔ∏è\nAs a Big Data Engineer, you‚Äôll primarily focus on maintaining and enhancing the operationality of our on-premise and cloud data pipelines which feed our warehouses and APIs\n-Design, develop, test, promote and industrialize all data components from data ingestion to datawarehouse delivery (ClickHouse, BigQuery):\nPropose and develop innovative solutions to achieve the best levels of scalability and performance for our Big Data engines\nAutomate and streamline our real-time and batch data pipelines (on-premise and in the cloud) in order to simplify access to our data by other teams and lower amount of work spent by other teams on ETL processes\nPerform end-to-end monitoring to ensure high availability of production data processing, data quality and reliability\nApply best in class Devops guidelines and secure deployments\n-Brainstorm with other team members working on our data backend (datawarehouse modelling and data exposure through our reporting APIs) on optimizing our architecture and support them in the use of our pipelines\n-Contribute to data roadmap definition in coordination with other R&D and product teams in order to build a best in class data infrastructure that will generate insights for Equativ‚Äôs analytics\n-Take part in improving and deploy data engineering standards, procedures, processes and operational guidelines around target data components at Equativ\nüí™ About you\nMaster degree in Computer Science or similar technical field of study\n3+ years of software development with open source technologies\nFluent in Java and/or in Scala. SQL mastery\nVery good understanding of Devops principles (Gitlab, Docker, Kubernetes, Gradle, ci/cd)\nExperience with large-scale data engineering technologies (ClickHouse, Flink, Kafka, Hadoop, Spark, Hbase)\nExperience on building data pipelines on Google Cloud Platform (BigQuery, Dataflow, GCS, Cloud Run, Airflow ‚Ä¶) would be a big plus\nExperience in working with high QPS Rest APIs is a plus\nEntrepreneurial spirit and know-how to identify opportunities of improvement\nWorking proficiency and communication skills in verbal and written English\nPassion for playing with large volume of data\nüöÄ How you'll grow\nWithin 1 month:\nYou'll be just finishing your onboarding.\nYou'll probably have tackled a few small tasks in peer-coding\nWithin 4 months:\nYou'll have an overview of 50% of the stack, CI/CD and team‚Äôs main processes. You‚Äôll be able to work on more complex developments\nYou'll now have enough knowledge to participate to deployments of chosen applications\nWithin 9 months:\nYou'll be autonomous on most of our stack and will have participated to major projects\nYou‚Äôll be helping the team on production matters\nüëã About us\nEquativ is the new single name for Smart Adserver, DynAdmic, LiquidM and Nowtilus ‚Äî four proven innovators in advertising technology. The vertically integrated company provides brand and privacy-safe solutions that empower its clients to achieve maximum impact while respecting the rights of consumers. The union combines client expertise and engineering excellence to serve the interests of both the supply- side and demand-side with equal professionalism and technical sophistication.\nHeadquartered in Paris and New York, Equativ operates globally with a team of more than 550 people in 20 offices. Equativ offers the market its own independent ad server, SSP, buyer tools, and media services to fulfill the promise of advertising technology. Learn more at Equativ.com.\nThe company is ranked on the Deloitte Technology Fast 500 EMEA and in the Financial Times‚Äô FT 1000: Europe‚Äôs Fastest-Growing Companies.\nEquativ (formerly Smart AdServer) has been awarded the HappyIndex@Work label and is proud to be among the best companies in the ChooseMyCompany ranking, recognized for its flexible working environment.\nCome and lead the charge with us in building a transparent ecosystem based on quality!\nShow more\nShow less",
        "details": {
            "JobDetail": [],
            "TypeContract": "",
            "Salary": "",
            "Level": "",
            "Experience": null
        },
        "title": "data engineer",
        "skills": {
            "ProgLanguage": [
                "R",
                "Java",
                "Scala"
            ],
            "DataBase": [
                "SQL",
                "HBase"
            ],
            "DataAnalytics": [
                "R"
            ],
            "BigData": [
                "Hadoop",
                "Flink",
                "Spark"
            ],
            "CloudComputing": [
                "GCP",
                "Google Cloud Platform"
            ],
            "DevTools": [
                "Docker"
            ],
            "DBMS": [
                "BigQuery"
            ],
            "SoftBigDataProcessing": [
                "HBase"
            ],
            "Automation": [
                "Airflow",
                "Kubernetes"
            ],
            "Containers": [
                "Docker",
                "Kubernetes"
            ],
            "Collaboration": [
                "Teams"
            ],
            "Other": [
                "Cloud",
                "Big Data",
                "DevOps",
                "CI/CD"
            ],
            "EnSoftSkils": [
                "Communication"
            ]
        }
    },
    {
        "source": "LinkedIn",
        "company": "CGI",
        "location": "Niort, Nouvelle-Aquitaine, France",
        "link": "https://fr.linkedin.com/jobs/view/data-engineer-f-h-at-cgi-3902411140?position=6&pageNum=7&refId=m3%2FMjbsrRC0%2FAGJwy5bQNw%3D%3D&trackingId=JPIoTGBzLJTzxy%2BVAMsOUQ%3D%3D&trk=public_jobs_jserp-result_search-card",
        "description": "Big Data, Data Science, Data analyse, Data architecture ... √áa n‚Äôa pas de secret pour vous ?\nQue vous commenciez votre carri√®re professionnelle ou que vous soyez sp√©cialiste de l‚Äôune de ces disciplines, int√©grer notre communaut√© Data, c‚Äôest l‚Äôassurance de progresser, innover, partager, vous certifier et rendre service √† nos clients.\nSi vous souhaitez int√©grer nos √©quipes √† Niort et accompagner les plus grands acteurs du secteur des Assurances, cette annonce est susceptible de vous int√©resser.\nEn tant que Data Engineer, vous serez responsable de la conception, du d√©veloppement, de la gestion et de l'int√©gration des syst√®mes bas√©s sur les technologies AWS, Terraform, OpenShift, Kafka et Hadoop. Ce r√¥le implique la mise en place d'architectures √©volutives et hautement disponibles pour r√©pondre aux besoins de traitement et de stockage de donn√©es de l'entreprise.\nFonctions et responsabilit√©s\nVos responsabilit√©s seront les suivantes:\n-Maintenir et d√©velopper des solutions bas√©es sur les services AWS pour le stockage, le traitement et l'analyse de donn√©es\n-Utiliser les services AWS appropri√©s tels que Amazon EC2, S3, RDS, Lambda, etc., pour r√©pondre aux exigences du projet.\n-Cr√©er et maintenir les configurations Terraform pour la gestion de l'infrastructure en tant que code (IaC) sur AWS\n-Participer √† la maintenance et √† la mise en place d'environnements OpenShift pour l'h√©bergement d'applications et de services\n-G√©rer et administrer les clusters Kafka pour garantir la disponibilit√©, la performance et la s√©curit√© du syst√®me de messagerie\nParticiper √† l‚Äôassistance utilisateurs sur les briques de la plateforme Hadoop Cloudera Data\n-Travailler avec les projets et les devOps pour assurer un traitement efficace des donn√©es\nEn rejoignant CGI, vous b√©n√©ficiez notamment d‚Äôune offre compl√®te de formations (techniques, m√©tiers, d√©veloppement personnel,‚Ä¶), de flexibilit√© gr√¢ce √† notre accord t√©l√©travail (jusqu‚Äô√† 3 jours de t√©l√©travail par semaine), d‚Äôune politique de cong√©s avantageuse (27 jours de cong√©s pay√©s, RTT, cong√©s anciennet√© et enfant malade,‚Ä¶) et d‚Äôun package d‚Äôavantages int√©ressant (r√©gime d‚Äôachats d‚Äôactions, participation, CSE,...).\nQualit√©s requises pour r√©ussir dans ce r√¥le\nAyant une premi√®re exp√©rience en tant que Data Engineer, vous avez une premi√®re exp√©rience relative aux points suivants:\n-D√©veloppement et int√©gration sur les technologies AWS, Terraform, OpenShift, Kafka et Hadoop\n-Connaissance avanc√©e de l'administration Kafka, y compris la configuration, la gestion et la r√©solution des probl√®mes\n-Mise en ≈ìuvre de l'infrastructure en tant que code √† l'aide de Terraform\n-Bonne compr√©hension des bonnes pratiques de s√©curit√© pour les syst√®mes cloud, les clusters Kafka et les plateformes Hadoop\nCGI est un employeur inclusif et attentif aux candidatures des personnes en situation de handicap, √† l‚Äô√©volution de carri√®res des hommes et des femmes et au bien-√™tre de nos salari√©s LGBT+. Dans un souci d‚Äôaccessibilit√© et de clart√©, le point m√©dian n‚Äôest pas utilis√© dans cette annonce. Tous les termes employ√©s se r√©f√®rent aussi bien au genre f√©minin que masculin.\nShow more\nShow less",
        "details": {
            "JobDetail": [],
            "TypeContract": "",
            "Salary": "Package",
            "Level": "",
            "Experience": null
        },
        "title": "data engineer",
        "skills": {
            "BigData": [
                "Hadoop"
            ],
            "CloudComputing": [
                "AWS"
            ],
            "InfrastructureAsCode": [
                "Terraform"
            ],
            "Containers": [
                "OpenShift"
            ],
            "Other": [
                "Cloud",
                "Big Data",
                "DevOps"
            ]
        }
    },
    {
        "source": "LinkedIn",
        "company": "Groupe INGENA",
        "location": "Paris",
        "link": "https://fr.linkedin.com/jobs/view/data-engineer-h-f-at-groupe-ingena-3883689479?position=7&pageNum=7&refId=m3%2FMjbsrRC0%2FAGJwy5bQNw%3D%3D&trackingId=yIgRfMAvvjQ%2BhgrmzkPCRg%3D%3D&trk=public_jobs_jserp-result_search-card",
        "description": "Le groupe INGENA promeut la transition num√©rique en √©tant acteur d‚Äôun monde souhaitable.\nVotre mission :\nConcevoir, d√©velopper et tester des algorithmes de collecte et de traitement de gros volumes de donn√©es sous Scala, Python ou Java\nAutomatiser et optimiser les flux de donn√©es et leurs visualisations en dashboards\nIndustrialiser les traitements, la qualit√© et l‚Äôint√©grit√© des donn√©es\nParticiper √† la Mod√©lisation et √† la Gouvernance des donn√©es (process, normalisation, r√©f√©rentiel,‚Ä¶)\nContribuer √† la scalabilit√©, la s√©curit√©, la stabilit√© et la disponibilit√© des donn√©es de la plateforme\nAnalyser les donn√©es pour r√©pondre aux questions m√©tiers et participer √† l‚Äô√©volution de l‚Äôarchitecture Big Data\nConcevoir, D√©velopper et Industrialiser des mod√®les de Machine Learning, Deep Learning, en collaboration avec les Data Scientists\nAppliquer une d√©marche CI/CD (Git, Jira, Jenkins)\nLes comp√©tences techniques n√©cessaires sont :\nExp√©rience de 5 ans minimum en d√©veloppements Scala, Python ou Java\nExp√©rience de 2 ans minimum sur SPARK et sur le traitement des flux en streaming\nExpertise sur Hadoop (Hive, HBase, HDFS) sous distributions MapR ou Hortonworks\nExp√©rience souhait√©e sur ELK, Terraform, NoSQL,‚Ä¶\nFort background en Mod√©lisation de donn√©es ou ETL\nMa√Ætrise des briques analytiques des clouds AWS, GCP ou Azure\nSensibilisation √† la d√©marche CI/CD tools (Git, Jenkins)\nLa connaissance de Docker, Kubernetes et Ansible est un plus\nMise en ≈ìuvre des m√©thodes Agile (Scrum, Kanban,‚Ä¶)\nAnglais souhait√©\nGroupe INGENA\n:\nLe Groupe INGENA est sp√©cialis√© en Conseil M√©tier et en Int√©gration pour les march√©s de l‚Äôassurance, de la banque et de la Finance. INGENA intervient notamment sur les projets associ√©s √† la Data, aux Risques et √† la Distribution.\nLe groupe comprend √©galement la soci√©t√© DRiMS sp√©cialis√©e en Finance de March√©.\nNos valeurs : Engagement, Int√©grit√© et Bienveillance.\nLa mise en pratique du monde souhaitable, c‚Äôest pour nous une entreprise √©co-responsable, √©thique, inclusive, sociale, soucieuse du bien-√™tre, de l‚Äô√©volution et de l‚Äô√©panouissement de ses √©quipes. Ce sont aussi des offres pour un monde durable comme la ma√Ætrise des risques ou l‚ÄôESG.\nDans un esprit convivial et engag√©, nous faisons en sorte que chacun puisse √™tre acteur de l‚ÄôINGENA souhaitable.\nBureau √† Paris 9√®me (M√©tro Le Peletier). Clients √† Paris ou tr√®s proche banlieue.\nShow more\nShow less",
        "details": {
            "JobDetail": [],
            "TypeContract": "",
            "Salary": "",
            "Level": "",
            "Experience": "5 an(s)"
        },
        "title": "data engineer",
        "skills": {
            "ProgLanguage": [
                "Java",
                "Scala",
                "Python"
            ],
            "DataBase": [
                "HBase",
                "NoSQL"
            ],
            "BigData": [
                "Hadoop",
                "Spark"
            ],
            "CloudComputing": [
                "GCP",
                "AWS",
                "Azure"
            ],
            "DevTools": [
                "Git",
                "Docker",
                "Jenkins"
            ],
            "SoftBigDataProcessing": [
                "HBase"
            ],
            "Automation": [
                "Kubernetes",
                "Ansible"
            ],
            "InfrastructureAsCode": [
                "Terraform"
            ],
            "Containers": [
                "Docker",
                "Kubernetes"
            ],
            "Collaboration": [
                "JIRA"
            ],
            "Other": [
                "Machine Learning",
                "Big Data",
                "CI/CD"
            ],
            "EnSoftSkils": [
                "Collaboration"
            ]
        }
    },
    {
        "source": "LinkedIn",
        "company": "Mirakl",
        "location": "Paris, √éle-de-France, France",
        "link": "https://fr.linkedin.com/jobs/view/senior-data-engineer-at-mirakl-3904071960?position=8&pageNum=7&refId=m3%2FMjbsrRC0%2FAGJwy5bQNw%3D%3D&trackingId=SigrjGWkAlndnlAkvWWyaA%3D%3D&trk=public_jobs_jserp-result_search-card",
        "description": "Mirakl, leader et pionnier de l‚Äô√©conomie de plateforme, propose aux entreprises une suite unique de solutions leur permettant de transformer significativement leur e-commerce afin d'acc√©l√©rer de fa√ßon durable et rentable leur croissance. Depuis 2012, Mirakl accompagne les entreprises B2C et B2B avec la technologie la plus avanc√©e, s√©curis√©e et √©volutive leur permettant de digitaliser leur activit√© et d'√©largir leur offre via la marketplace ou le dropship, faciliter la gestion des catalogues et des paiements de leurs fournisseurs pour plus d'efficacit√©, offrir une exp√©rience d'achat personnalis√©e √† leurs clients, et augmenter leurs profits gr√¢ce au retail media. Bas√©e √† Paris et Boston, Mirakl est certifi√©e Great Place to Work.\nA propos de Mirakl Labs\nNos √©quipes techniques et produits, nomm√©es Mirakl Labs, sont principalement r√©parties entre nos 2 hubs situ√©s √† Paris et √† Bordeaux. Elles collaborent au quotidien afin d'adresser les probl√©matiques de nos clients et utilisateurs en r√©pondant √† diff√©rents challenges li√©s aux nouvelles fonctionnalit√©s, √† la scalabilit√©, la s√©curit√© et l‚Äôergonomie‚Ä¶\nElles op√®rent en mode agile et s'organisent en Squads compos√©es d'un Squad Lead, de 5 d√©veloppeurs, d'un Product Manager et d'un QA. Chaque Squad est sp√©cialis√©e sur un scope fonctionnel afin de concevoir et r√©aliser de nouvelles features, leurs √©volutions et des APIs (avec un d√©coupage en micro-services). Nos √©quipes Infrastructure, Architecture, S√©curit√©, Documentation, Product Design, Data et Support op√®rent en transverse en apportant leur expertise et de la coh√©rence sur l‚Äôensemble des produits.\nToutes les √©quipes sont responsables de leur p√©rim√®tre et chacun des collaborateurs apporte son exp√©rience et ses id√©es. Innovation, feedback et implication dans les prises de d√©cision sont au c≈ìur de notre philosophie.\nEt pour favoriser ce partage avec d‚Äôautres passionn√©s, nous sommes sponsors, speakers, et h√¥tes de diff√©rents √©v√©nements, meetups, et associations de la sc√®ne Tech en France. Au cours des derni√®res ann√©es, nous avons particip√© √† des √©v√©nements tels que Devoxx, ReactEurope, ProductConf et Flupa UX Days.\nA propos du job\nLa solution SaaS Mirakl est le moteur des marketplaces des plus importants e-commer√ßants √† travers le monde. Cette solution g√®re et produit de gros volumes de donn√©es qui pr√©sentent des challenges extr√™mement int√©ressants pour les sp√©cialistes de la donn√©e (produits, commandes, clients, niveaux de stock, prix, messages, appels API, donn√©es de navigation, s√©ries temporelles, donn√©es g√©olocalis√©es etc.).\nEn tant que (Senior) Data Engineer au sein de l‚Äô√©quipe Data Mirakl, vos principales missions seront de :\ncontribuer √† l'enrichissement de la Data Platform (ETL)\nam√©liorer la robustesse de nos pipelines de production pour nos applications Machine Learning (inf√©rence real time etc.)\nInt√©gr√©(e) dans une √©quipe de sp√©cialistes de la donn√©e (data engineers, machine learning engineers, data scientists, data analysts), vous √™tes un des acteurs cl√©s pour garantir la place de Mirakl comme solution dominante sur son march√©.\nNotre stack et nos outils\nApache Spark, Kafka, AWS, Databricks, Python, Airflow, Mlflow, Tensorflow, Delta lake, Superset, Kubernetes, Redshift, SQL, Terraform, Ansible\nAu quotidien, vous allez :\nParticiper √† la d√©finition et √† l‚Äôimpl√©mentation d‚Äôune architecture performante, robuste, scalable et aux co√ªts ma√Ætris√©s pour nos applications Spark ainsi que pour nos pipelines de production de Machine Learning (√©valuation des feature stores, refactoring de DAG Airflow)\nAccompagner les Data Scientists lors de leur mise en production (relecture de code, pair programming) et mettre en place les best practices\nOptimiser et am√©liorer la CI/CD de l‚Äô√©quipe en collaboration avec l‚Äô√©quipe SRE\nAssurer la mont√©e en comp√©tence des membres de l‚Äô√©quipe sur les sujets de MLOps et Data Engineering\nR√©fl√©chir √† la meilleure fa√ßon d'int√©grer les donn√©es Google Analytics dans la data platform\nPartager ses connaissances et pr√©senter les travaux devant toutes les √©quipes Labs\nCe qu‚Äôon peut vous apporter :\nDes projets data driven, divers et vari√©s (traitements massifs d‚Äôimages, de textes, time series etc.) pour des produits diff√©rents de Mirakl\nUne culture orient√©e sur la veille technologique\nDes projets qui ont un vrai impact business devant √™tre d√©ploy√©s sur des centaines de clients dans un contexte multilingue\nQuelques exemples de sujets en cours :\nEnrichissement des donn√©es produit √† partir des images et des descriptions\nMod√©ration automatique des produits\nMapping automatique des donn√©es produit\nIdentification des produits √† fort potentiels\nD√©tection de comportements frauduleux\nSentiment analysis sur les messages √©chang√©s entre clients et vendeurs et dans les √©valuations\nD√©termination de prix optimaux\nMonitoring de la qualit√© de service des vendeurs\nDes applications d‚Äôinf√©rence en synchrone de nos mod√®les de ML\nVous aimerez ce job si :\nVous √™tes passionn√©(e) par la data et les technologies modernes permettant d'en tirer partie\nVous vous int√©ressez √† la data science et avez des connaissances g√©n√©rales sur les algorithmes de Machine Learning\nVous avez un background en d√©veloppement et avez √©volu√© dans un environnement Data\nVous avez a minima 4 ans d‚Äôexp√©rience en environnement Machine Learning et/ou Data\nVous avez mis en production avec succ√®s des applications Big Data faisant appel √† du Machine Learning, du NLP, du traitement d‚Äôimages dans des projets d'envergure, √† fort volume de donn√©es\nVotre ma√Ætrisez Python, √™tes un pro des frameworks data de la fondation Apache et √™tes √† l'aise dans un environnement AWS\nVous ma√Ætrisez au moins un outil d‚Äôorchestration (Airflow, Data Pipeline ou tout autre outil similaire)\nVous pr√©sentez vos travaux de mani√®re simple et accessible\nVous fa√Ætes preuve d'un bon relationnel et vous aimez mentorer des collaborateurs\nVous parlez couramment anglais et fran√ßais\nLes plus pour le poste :\nVous avez une exp√©rience significative dans le domaine du e-commerce\nVous avez d√©j√† mis en place un Data Lake, Data Warehouse ou une Data Platform\nVous avez d√©ploy√© des applicatifs en environnement Kubernetes\nVous avez mis en place des pipelines d'ingestion de donn√©es avec une approche CDC √† l'aide de Debezium ou autre\nVous ma√Ætrisez Java/Scala\nMirakl est engag√©e en faveur de la diversit√©, de l‚Äô√©galit√© des chances et de l‚Äôinclusion. Nous c√©l√©brons nos diff√©rences car nous sommes convaincus que les qualit√©s visibles et invisibles de chaque Mirakl Worker sont une source de force et d‚Äôinnovation. Dans le cadre de cet engagement, nous √©tudions toutes les candidatures sans distinction de : genre, ethnicit√©, religion, orientation sexuelle, handicap, √¢ge ou toute autre caract√©ristique prot√©g√©e par la loi.\nShow more\nShow less",
        "details": {
            "JobDetail": [
                "Senior"
            ],
            "TypeContract": "",
            "Salary": "",
            "Level": "",
            "Experience": "4 an(s)"
        },
        "title": "data engineer",
        "skills": {
            "ProgLanguage": [
                "Java",
                "Scala",
                "Python"
            ],
            "DataBase": [
                "SQL"
            ],
            "BigData": [
                "Databricks",
                "Spark"
            ],
            "MachineLearning": [
                "TensorFlow"
            ],
            "CloudComputing": [
                "AWS"
            ],
            "Automation": [
                "Airflow",
                "Kubernetes",
                "Ansible"
            ],
            "InfrastructureAsCode": [
                "Terraform"
            ],
            "Containers": [
                "Kubernetes"
            ],
            "Other": [
                "ML",
                "Machine Learning",
                "Big Data",
                "CI/CD"
            ],
            "EnSoftSkils": [
                "Collaboration"
            ]
        }
    },
    {
        "source": "LinkedIn",
        "company": "ALFI : Financial Markets Consultancy Services",
        "location": "Paris, √éle-de-France, France",
        "link": "https://fr.linkedin.com/jobs/view/data-engineer-at-alfi-financial-markets-consultancy-services-3916552424?position=9&pageNum=7&refId=m3%2FMjbsrRC0%2FAGJwy5bQNw%3D%3D&trackingId=Upxx%2BSq7mrkfa3H4edVMzw%3D%3D&trk=public_jobs_jserp-result_search-card",
        "description": "Le Data Engineer intervient au sein de l‚Äô√©quipe Engineering Open Big Data du D√©partement Guilde Data, qui regroupe l‚Äôensemble des expertises technologiques li√©es √† l‚Äôing√©nierie de la donn√©e, de l‚Äôautomatisation et √† l‚Äôexploitation des mod√®les de Machine Learning.\nVotre r√¥le et vos missions :\nVous aurez pour missions principales de d√©velopper les projets Big Data demand√©s par le m√©tier, et notamment :\nPasser de la donn√©e brute √† de la donn√©e exploitable, expos√©e sous forme de tables requ√™tables dans le Datalake\nConsolider ces donn√©es au fur et √† mesure de leur alimentation r√©currente dans le Datalake\nLes exploiter pour atteindre la finalit√© business (exposition de Business View, r√©int√©gration des r√©sultats dans le SI, service de scoring, ‚Ä¶)\nDe mettre en place et de garantir le respect dans la dur√©e d'un processus qualit√© sur l'ensemble du cycle de DEV (documents, tests unitaires / int√©gration / fonctionnels, commentaires, versionning, etc.)\nAccompagner les Data Engineers sur son p√©rim√®tre pour garantier la qualit√© des livrables\nExpertise souhait√©e\nComp√©tences techniques :\nExpertise en SPARK et PySpark\nExpertise sur Databricks\nUne exp√©rience sur un cloud provider public comme Azure (id√©alement), AWS, ou GCP\nConnaissances avanc√©es d'outils de BI comme PowerBI (id√©alement) ou Spotfire\nComp√©tences transverses :\nCapacit√© √† interagir avec des parties prenantes diverses : Business analyst, Architectes, M√©tier\nExp√©rience en mode de Delivery Agile (Scrum, Kanban, etc.‚Ä¶)\nEtre expert dans les pratiques du Software Craftsmanship (Test Driven Development, Behavior Driven Development, Clean Code, Code Reviews, etc.)\nEt :\nDes Connaissances sur Azure DevOps, Azure Pipeline, GIT\nMaitrise des Traitements Big Data en mode Streaming\nMaitrise des Bases de donn√©es relationnelles et NoSQL\nUne exp√©rience professionnelle avec des outils comme Azure Databricks, Azure Data Lake Storage ou encore Azure Data Factory\nConform√©ment √† la r√®glementation, et √† notre politique d‚Äô√©galit√© professionnelle, tous nos postes sont ouverts aux personnes en situation de handicap.\nShow more\nShow less",
        "details": {
            "JobDetail": [],
            "TypeContract": "",
            "Salary": "",
            "Level": "",
            "Experience": null
        },
        "title": "data engineer",
        "skills": {
            "DataBase": [
                "NoSQL"
            ],
            "BigData": [
                "Databricks",
                "Spark"
            ],
            "CloudComputing": [
                "GCP",
                "AWS",
                "Azure"
            ],
            "DevTools": [
                "Git"
            ],
            "Other": [
                "Machine Learning",
                "Cloud",
                "Big Data",
                "DevOps"
            ]
        }
    },
    {
        "source": "LinkedIn",
        "company": "BforBank",
        "location": "Paris",
        "link": "https://fr.linkedin.com/jobs/view/data-engineer-confirm%C3%A9-h-f-at-bforbank-3918327555?position=10&pageNum=7&refId=m3%2FMjbsrRC0%2FAGJwy5bQNw%3D%3D&trackingId=%2Fu5Xq4NFwA%2B3skuO1G0f5Q%3D%3D&trk=public_jobs_jserp-result_search-card",
        "description": "Sur le mod√®le d'une\n\"Tech company\",\nBforBank place\nl'humain et le digital\nau c≈ìur de sa transformation. Notre mission,\noffrir √† nos clients une exp√©rience bancaire incomparable\npour r√©pondre √† leurs besoins et usages mobile. üåü üì±\nRejoindre BforBank c‚Äôest\nrejoindre une √©quipe engag√©e\ndans un\ngrand projet de d√©veloppement strat√©gique en France et en Europe.\nNous sommes aujourd‚Äôhui 350 passionn√©(e)s et\nrecherchons nos talents pour construire la banque de demain\n. üöÄ\nNous croyons en la force du collectif, chaque jour rassembl√©s autour de nos valeurs, de simplicit√©, d'optimisme et d‚Äôengagement, encourageant chacun √† oser, essayer et accepter d‚Äô√©chouer.\nüéØ Au sein de la Direction Technologie, la Data Factory a pour objectifs de piloter, d√©finir, d√©ployer et op√©rer les meilleures solutions technologiques r√©pondant aux cas d‚Äôusage data et d‚Äôautomatisations de processus de la banque au travers de plateformes. √âgalement, la Data Factory contribue au d√©veloppement des produits, √† la cristallisation et √† la diffusion des pratiques au sein des Squads BforBank sur les usages data dans la banque.\nTu rejoindras une squad en charge de r√©soudre des probl√©matiques m√©tiers en cr√©ant des solutions applicatives utilisant les donn√©es, des data products, avec pour finalit√©s la prise de d√©cision via des moteurs de calcul ou des dashboards, la cr√©ation de flux r√©glementaires, la cr√©ation de data layer ou de reportings.\nüöÄ Tes missions principales sont les suivantes :\n¬∑ Participer aux analyses, √©tudes d‚Äôimpacts et cadrage techniques\n¬∑ Concevoir des solutions en respectant les bonnes pratiques d‚Äôarchitecture data et d√©veloppement\n¬∑ R√©aliser le d√©veloppement de nouveaux data products et assurer la maintenance √©volutive et corrective des data products existants\n¬∑ R√©diger la documentation technique des data products\n¬∑ Assurer un support aux testeurs\n¬∑ Reporter de ton activit√© √† ta Squad et travailler dans une d√©marche d‚Äôefficacit√© collective\nConcr√®tement tu seras amen√©(e) √† produire les livrables suivants :\n¬∑ R√©aliser du code applicatif √† l‚Äô√©tat de l‚Äôart sur notre nouvelle Data Platform\n¬∑ Cr√©er des data layer et des rapports sur notre outil de Data Visualisation\n¬∑ R√©diger les documentations techniques li√©es √† ta solution, incluant le mod√®le de donn√©es, les proc√©dures, l‚Äôordonnancement\nCe que tu ma√Ætrises :\n¬∑ Maitrise des services manag√©s de GCP (BigQuery, dataproc, dataflow, CloudSQL ‚Ä¶)\n¬∑ Maitrise du langage Python, Pandas, Spark\n¬∑ Maitrise de la mod√©lisation de base de donn√©es et du langage SQL\n¬∑ Maitrise d‚Äôune chaine CI/CD (GitLab‚Ä¶)\n¬∑ Bonne connaissance de Kafka\n¬∑ Bonne connaissance d‚Äôun outil d‚Äôint√©gration de donn√©es type ETL (Informatica‚Ä¶)\n¬∑ Connaissance de l‚Äôinfra as code (Terraform)\n¬∑ Connaissance d‚Äôun outil de reporting (Looker, BO‚Ä¶)\nü§ù Ce poste est fait pour toi si :\n¬∑ Tu es passionn√©(e) par la Data et leurs usages\n¬∑ Tu es orient√© r√©solution de probl√®me, est curieux(se) et force de proposition\n¬∑ Tu appr√©cies le travail en √©quipe\n¬∑ Tu as un bon relationnel et est rigoureux(se)\n¬∑ Tu as une bonne capacit√© d‚Äôanalyse et r√©dactionnelle\n¬∑ Tu t‚Äôadaptes rapidement aux changements\nüéì\nFormation :\nTu es dipl√¥m√©(e) d‚Äôun master en √©cole de commerce, √©cole d‚Äôing√©nieur ou √©quivalent.\nChez BforBank nous recherchons avant tout des comp√©tences. Tu ne disposes pas du dipl√¥me requis mais as des exp√©riences √©quivalentes ? N'h√©site pas √† postuler !\nüíº\nExp√©rience :\nExp√©rience confirm√©e de 3 ans en tant que Data Engineer.\nEn rejoignant BforBank tu trouveras‚Ä¶\n¬∑ Un projet ambitieux de transformation digitale et culturelle √† l‚Äô√©chelon europ√©en, terrain d‚Äôinnovation et d‚Äôouverture d‚Äôesprit\n¬∑ Une organisation apprenante, proposant un large choix de formations toute l‚Äôann√©e, et qui favorise l‚Äô√©change avec les autres marques du Groupe\n¬∑ Une promo RSE multi-m√©tiers qui fait √©voluer en continu les actions de BforBank vers une banque plus responsable\n¬∑ Une organisation du travail en mode Agile, impliquant un degr√© √©lev√© de collaboration et d'autonomie tout en travaillant avec un groupe de pairs diversifi√©s.\n¬∑ Une Direction Technologie en pleine expansion, porteuse de nombreux d√©fis strat√©giques\nMais aussi‚Ä¶\nDe 2 jours √† 5 jours de t√©l√©travail modulables par semaine, dans la limite de 84 jours par an (frais de fonctionnement pris en charge)\n25 jours de cong√©s + 16 jours de RTT\n80% du co√ªt de la mutuelle d‚Äôentreprise pris en charge / couvert\nAvantages collaborateurs Cr√©dit Agricole : taux et tarifs pr√©f√©rentiels\nDes frais de transports rembours√©s √† 75%\nUn restaurant d‚Äôentreprise\nDes douches pour les sportifs et un tarif avantageux aupr√®s d‚Äôune salle de sport toute proche\nüìç Le poste est bas√© √† La D√©fense, dans des locaux flambant neufs !\nBforBank s'engage √† garantir l'√©galit√© des chances aux candidats car nous sommes convaincus de la richesse apport√©e par la diversit√© et l'inclusion dans nos √©quipes.\nRencontrons-nous !\nLe processus de recrutement se d√©roule en 4 √©tapes :\nüßëüèº‚Äçüíª\nCall de 30 minutes avec notre √©quipe Talent Acquisition\nEchange avec le Data Factory Manager et notre √©quipe Talent Acquisition (pr√©sentiel)\nEchange avec une personne de l‚Äô√©quipe avec qui tu seras amen√© √† travailler (visio)\nEchange avec le CTO (visio ou pr√©sentiel)\nNotre processus de recrutement dure en moyenne 3 semaines et l‚Äô√©quipe Talent Acquisition se tiendra √† ta disposition pour te donner un maximum de visibilit√© sur l‚Äôavanc√©e du process.\nShow more\nShow less",
        "details": {
            "JobDetail": [
                "Confirm√©"
            ],
            "TypeContract": "",
            "Salary": "",
            "Level": "",
            "Experience": "3 an(s)"
        },
        "title": "data engineer",
        "skills": {
            "ProgLanguage": [
                "Python"
            ],
            "DataBase": [
                "SQL"
            ],
            "DataAnalytics": [
                "Pandas"
            ],
            "BigData": [
                "Spark"
            ],
            "CloudComputing": [
                "GCP"
            ],
            "DBMS": [
                "BigQuery"
            ],
            "InfrastructureAsCode": [
                "Terraform"
            ],
            "Other": [
                "CI/CD"
            ],
            "EnSoftSkils": [
                "Collaboration"
            ]
        }
    },
    {
        "source": "LinkedIn",
        "company": "fifty-five",
        "location": "Paris, √éle-de-France, France",
        "link": "https://fr.linkedin.com/jobs/view/senior-data-cloud-engineer-h-f-at-fifty-five-3915044673?position=1&pageNum=10&refId=s3VlrhtbUrMVZp4kM4F1Ew%3D%3D&trackingId=TI0d5l99iWJiD%2B5Azqy3CA%3D%3D&trk=public_jobs_jserp-result_search-card",
        "description": "Senior Data & Cloud Engineer\nfifty-five est une data-company d'un genre nouveau qui aide les marques √† exploiter les donn√©es pour am√©liorer le marketing, les m√©dias et l'exp√©rience client gr√¢ce √† une combinaison de services de conseil et de technologie sp√©cialis√©s.\nEn tant que pilier data et marketing du Brandtech Group, nous offrons des services qui combinent le conseil en strat√©gie, les services de cloud, le conseil en m√©dia et l'exp√©rience client.\nfifty-five, c'est plus de 400 experts du num√©rique. Des digital consultants, des sp√©cialistes du tracking et du m√©dia, des ing√©nieurs et des data scientists, travaillent tous en √©troite collaboration pour fournir des conseils marketing de haut niveau et une assistance technique aux marques, dans tout type d'industrie, partout dans le monde.\nPartenaire des annonceurs de la collecte √† l'activation et l'exploitation des donn√©es, nous aidons les organisations √† devenir de v√©ritables entit√©s omnicanales ma√Ætrisant l'efficacit√© de leur √©cosyst√®me digital et ses synergies avec le monde physique.\nBas√© √† Paris, nous op√©rons sur 3 fuseaux horaires depuis nos 10 bureaux, situ√©s √† Paris, Londres, Gen√®ve, Milan, Shanghai, Hong Kong, Shenzhen, Taipei, Singapour et New York. fifty-five attache une importance particuli√®re au bien-√™tre de ses collaborateurs, ce qui lui a permis de figurer dans le classement Best Workplaces France en 2018.\nContexte :\nL'√©quipe d'ing√©nierie d√©veloppe et met en ≈ìuvre les solutions techniques permettant la r√©alisation de pipelines de donn√©es et l'impl√©mentation de data platform pour nos clients : r√©cup√©ration de datas sur de multiples sources de donn√©es (APIs, files, etc.), data cleaning, data processing, automation et monitoring de l'ensemble. L'√©quipe s'appuie sur des technologies r√©centes (docker, kubernetes, terraform, notebooks, etc.) et met en place ses projets dans les diff√©rents clouds du march√© (GCP, Azure, AWS...).\nMission :\nNous sommes √† la recherche d'une personne capable de r√©aliser des projets techniques pour r√©pondre aux besoins de nos clients (par exemple: syst√®me de recommandations de produits, d√©tection d'anomalies, ranking). Les activit√©s vont du chiffrage et du sizing technique √† la mise en ≈ìuvre des architectures, en passant par la revue des sp√©cifications fonctionnelles et la production de code. Le Data & Cloud Engineer sera √©paul√© par un Lead dans ses missions. Il sera √©galement amen√© √† participer √† la R&D et √† accompagner les √©quipes transverses dans la mise en place d'outils de travail internes (librairies pour les data scientists, environnement Notebooks pour les data analysts et data scientists, d√©veloppement de frameworks sur diff√©rents cloud providers, etc.).\nNous souhaitons trouver la bonne personne pour faire √©voluer ou cr√©er de nouvelles solutions dans ce cadre. Les missions comprennent aussi bien du prototypage rapide pour des d√©monstrateurs, que de la production de code robuste qui tourne en production tous les jours.\nComp√©tences et exp√©riences :\n4-5 ans d'exp√©rience en tant que Data Engineer\nMa√Ætrise de Python, SQL\nMa√Ætrise des environnements Cloud. Id√©alement certifi√© GCP, Azure ou AWS\nBonne connaissance de Docker/Kubernetes\nBonne connaissance d'au moins un data warehouse (BigQuery, Snowflake, etc)\nConnaissance autour des Notebooks (Jupyter)\nA l'aise avec des concepts li√©s aux APIs (OAuth, REST, etc.)\nA l'aise avec les notions d'Infrastructure as Code (Terraform)\nAu courant des pratiques GitOps et connaissances des concepts autour du CI/CD\nLa ma√Ætrise d'un orchestrateur, comme Apache Airflow, est un plus\nEsprit d'√©quipe (collaborer aux tests unitaires, revue de code, partage de code, sprints)\nBon niveau en fran√ßais et en anglais\nA d√©j√† travaill√© en mode projet avec des interlocuteurs vari√©s (consultant, data analyst, data scientist)\nUne exp√©rience en marketing digital est un plus\nNous proposons :\nun bureau au centre de Paris avec terrasse et jardin\nun environnement multiculturel avec des collaborateurs aux nationalit√©s multiples (France, Royaume-Uni, Etats-Unis, Chine, Tunisie, Italie et plus)\ndes projets avec nos bureaux √† Londres, Hong Kong, New York, Shanghai, Gen√®ve, Shenzhen et Taipei\ndes TGIF et supers soir√©es\nShow more\nShow less",
        "details": {
            "JobDetail": [
                "Senior"
            ],
            "TypeContract": "",
            "Salary": "",
            "Level": "",
            "Experience": "5 an(s)"
        },
        "title": "data engineer",
        "skills": {
            "ProgLanguage": [
                "R",
                "Python"
            ],
            "DataBase": [
                "SQL"
            ],
            "DataAnalytics": [
                "R"
            ],
            "BigData": [
                "Apache Airflow"
            ],
            "CloudComputing": [
                "GCP",
                "AWS",
                "Azure"
            ],
            "DevTools": [
                "Docker"
            ],
            "DBMS": [
                "BigQuery",
                "Snowflake"
            ],
            "Automation": [
                "Airflow",
                "Kubernetes"
            ],
            "InfrastructureAsCode": [
                "Terraform"
            ],
            "Containers": [
                "Docker",
                "Kubernetes"
            ],
            "Other": [
                "Cloud",
                "CI/CD"
            ],
            "EnSoftSkils": [
                "Collaboration"
            ]
        }
    },
    {
        "source": "LinkedIn",
        "company": "ATAWIZ",
        "location": "Paris",
        "link": "https://fr.linkedin.com/jobs/view/data-engineer-h-f-cdi-ou-freelance-at-atawiz-3913839795?position=2&pageNum=10&refId=s3VlrhtbUrMVZp4kM4F1Ew%3D%3D&trackingId=AURvP5OGbeKbtJbRzCZeqA%3D%3D&trk=public_jobs_jserp-result_search-card",
        "description": "Pour la petite histoire, Atawiz a √©t√© cr√©√© en 2016, pour devenir le cabinet d‚Äôexpertise que l‚Äôon conna√Æt aujourd‚Äôhui. Nous sommes Microsoft Solutions Partner dans plusieurs domaines de comp√©tences et partenaire Databricks. Les domaines d‚Äôexpertise d‚ÄôAtawiz s‚Äôadaptent aux nouveaux enjeux des entreprises : Time to Market, agilit√©, data, digitalisation des processus, ‚Ä¶\nNos consultant¬∑e¬∑s combinent ainsi agilit√©, approche DevOps pour soutenir nos clients dans la r√©alisation de leurs objectifs, et ce, depuis 2016 !\nAu-del√† d‚Äôun groupe d‚Äôexpert¬∑e¬∑s, nous sommes des passionn√©¬∑e¬∑s qui collaborent dans diff√©rents domaines d‚Äôexpertise :\nLe Cloud, sp√©cialement Azure\nDevOps\nLe Big Data\nLe d√©veloppement d‚Äôapplication mobile et web\nLes architectures micro-services\nAliment√©¬∑e par une forte culture d‚Äôentreprise, notre objectif est d‚Äôassurer la satisfaction de nos consultant¬∑e¬∑s autant que de celle de nos clients. Pour cela, nous s√©lectionnons avec attention nos projets pour que chacun de nos collaborateur¬∑rice¬∑s se sentent stimul√©(e)s et progressent rapidement.\nüìá Descriptif du poste\nNous avons de fortes demandes client et par cons√©quent besoin de renforcer notre √©quipe.\nL‚Äôaventure Atawiz, c‚Äôest aussi int√©grer une communaut√© d‚Äôune vingtaine d‚Äôexpert¬∑e¬∑s tous passionn√©¬∑e¬∑s. √Ä leurs c√¥t√©s, tu pourras √©voluer rapidement et d√©velopper de nouvelles comp√©tences.\nüéØMission propos√©e (longue dur√©e), en r√©gie chez notre client, grande entreprise du secteur de l‚Äô√©nergie (petite couronne ‚Äì proche Paris) :\nFreelance accept√©.\nEn tant que\nData Engineer H/F,\ntu seras rattach√©(e) au Responsable Data.\nüí° Enjeux du Poste\nAssurer le lead technique sur l‚Äôingestion, le chargement et la transformation des donn√©es dans la data plaform (Datalake, Datawarehouse)\nMod√©liser et impl√©menter les diff√©rents flux de donn√©es\nParticiper √† l‚Äôurbanisation de l‚Äôarchitecture de la plateforme avec le Tech Lead\nüë©‚Äçüíª La r√©partition des t√¢ches :\nPipelines de donn√©es :\nMise en place et optimisation des processus.\nR√©f√©rent technique pour l'ingestion, le loading et la transformation de donn√©es.\nD√©finition technique du mod√®le de donn√©es.\nD√©veloppement :\nPr√©paration des environnements techniques.\nD√©veloppement sur les assets selon les normes.\nCollaboration avec le support de la plateforme pour des expos en API.\nIng√©nierie de donn√©es :\nComp√©tences en mod√©lisation et cr√©ation de scripts.\nR√©flexions sur l'√©chelle, la disponibilit√© et l'optimisation des op√©rations.\nüíª Stack technique sur le projet :\nCloud : AWS (id√©alement) ou Azure\nDEV : Python, API, Git, Docker,\nDevOps (Terraform, CI/CD),\nDATA (SQL, NoSQL, DBT), BIGDATA (HDFS, SPARK).\nData Science (MLOPS),\nNotions : Scalabilit√©, Clustering, Data Mesh, Data Virt, Data Qualit√©, Analytique (Tableau, Dataiku).\n‚ú® Avantages de la mission :\nEn acceptant cette mission, tu b√©n√©ficieras d‚Äôun environnement de travail\nmotivant et coop√©ratif\n, o√π tu auras l‚Äôoccasion de t‚Äôimpliquer dans\ndes projets diversifi√©s et challengeants.\nDe plus, vous aurez des\npossibilit√©s d‚Äô√©volution de carri√®re.\nüîé Profil recherch√© :\nPassionn√©(e) de nouvelles technologies\net\nproactif(ve)\n, tu excelles en √©quipe dans un environnement dynamique. Ton engagement envers les meilleures pratiques et tes comp√©tences en communication font de toi la personne id√©ale pour cette mission.\nTu as\nminimum 5 ans d‚Äôexp√©riences\n, une\nsolide exp√©rience\ndans le domaine du data engineering en environnement cloud.\nUne exp√©rience sur le cloud AWS ou √©quivalent (Azure, GCP) est un plus.\nTon esprit d'√©quipe, ta pro activit√© font de toi un(e) candidat(e) id√©al(e) pour renforcer l‚Äô√©quipe.\nRejoins-nous ! üåü\nAvant d‚Äô√™tre en mission chez le client, tu es avant tout un(e) salari√©(e) d‚ÄôAtawiz üòä\n‚ú® La vie interne chez Atawiz:\nChez Atawiz, les opportunit√©s sont nombreuses, nous valorisons ton expertise et ton savoir-faire. Tu auras la possibilit√© de :\n‚úÖ D√©velopper tes comp√©tences et pour √ßa, tu b√©n√©ficieras d'une formation approfondie, de coaching manag√©rial et technique, et d'un accompagnement pour obtenir des certifications. üìö\n‚úÖ Participer activement √† la vie interne de l'entreprise, en partageant tes connaissances et ton expertise au travers d'articles techniques publi√©s sur notre blog et √† notre page LinkedIn.\nüëâ notre blog : https://blog.atawiz.fr/\nüëâ page LinkedIn : https://www.linkedin.com/company/atawiz/\n‚úÖ Suivre en mission et √™tre garant de l‚Äô√©volution de carri√®re de consultants juniors.\n‚úÖ Participer au process de recrutement, pour tester techniquement les candidats ou proposer des cooptations de personnes de ton r√©seau.\n‚úÖ Profiter d'avantages attractifs, tels que des √©v√©nements Microsoft, des bootcamps et des workshops & tech coffees r√©guliers, un mat√©riel performant, et bien plus encore ! üéâ\nBenefits:\nSalaire fixe entre 60k ‚Ç¨ et 65k ‚Ç¨ en fonction du profil pour un CDI\nPour Freelance TJM entre 600 et 650 ‚Ç¨ / jour\nStatut cadre\nRTT\nTitre de transport pris en charge √† 100%\nMutuelle Alan pris en charge √† 60 %\nLa pr√©voyance prise en charge √† 100 %\n7 ‚Ç¨ de panier repas par jour travaill√©\n2 jours de T√©l√©travail /semaine\nBudget t√©l√©travail\nDe beaux locaux √† Paris 9e, proche de la gare Saint-Lazare\nRejoins-nous d√®s maintenant dans nos bureaux situ√©s en plein c≈ìur de Paris üíº pour faire partie d'une √©quipe de passionn√©s, relever de nouveaux d√©fis et booster ta carri√®re. üöÄ\nInt√©ress√©(e) ? Postule d√®s √† pr√©sent et d√©couvre notre processus de recrutement interactif. Tu auras l'occasion de rencontrer notre √©quipe, d'√©changer avec nos expert¬∑e¬∑s techniques, et m√™me de discuter avec notre CEO et notre Sales Director.\nü§ù Notre processus de recrutement :\n1 - Postulez en ligne ! L‚Äô√©quipe Recrutement √©tudie avec attention ta candidature et te r√©pond dans les plus brefs d√©lais.\n2 - Premier √©change ! Tu √©changes avec notre Talent Acquisition Manager sur ton parcours, tes aspirations professionnelles ainsi que sur Atawiz et les opportunit√©s que nous proposons.\n3 - Un entretien technique avec l‚Äôun¬∑e de nos expert¬∑e¬∑s pour te challenger techniquement. C‚Äôest √©galement l‚Äôoccasion pour toi d‚Äôavoir son retour d‚Äôexp√©rience.\n4 - Dernier entretien : pour finir, tu rencontreras notre CEO. Tu pourras par ailleurs √©changer avec notre Sales Director.\nPendant tout le processus de recrutement, tu as la possibilit√© de participer √† des √©v√©nements organis√©s par Atawiz et d‚Äô√©changer avec des collaborateurs afin d‚Äôen apprendre plus sur nous !\nShow more\nShow less",
        "details": {
            "JobDetail": [
                "Junior"
            ],
            "TypeContract": "CDI",
            "Salary": "60k",
            "Level": "",
            "Experience": "5 an(s)"
        },
        "title": "data engineer",
        "skills": {
            "ProgLanguage": [
                "Python"
            ],
            "DataBase": [
                "SQL",
                "NoSQL"
            ],
            "BigData": [
                "Databricks",
                "Spark"
            ],
            "DataVisualisation": [
                "Tableau"
            ],
            "CloudComputing": [
                "GCP",
                "AWS",
                "Azure"
            ],
            "DevTools": [
                "Git",
                "Docker"
            ],
            "InfrastructureAsCode": [
                "Terraform"
            ],
            "Containers": [
                "Docker"
            ],
            "Other": [
                "Cloud",
                "Big Data",
                "DevOps",
                "CI/CD"
            ],
            "EnSoftSkils": [
                "Communication",
                "Collaboration"
            ]
        }
    },
    {
        "source": "LinkedIn",
        "company": "Orange Business",
        "location": "Lille",
        "link": "https://fr.linkedin.com/jobs/view/data-engineer-talend-f-h-at-orange-business-3916552363?position=3&pageNum=10&refId=s3VlrhtbUrMVZp4kM4F1Ew%3D%3D&trackingId=1c8SaftDClzn7NknZ4szxw%3D%3D&trk=public_jobs_jserp-result_search-card",
        "description": "L‚Äôambition d‚ÄôOrange Business est de devenir l‚Äôint√©grateur r√©seau et num√©rique de r√©f√©rence en Europe, en nous appuyant sur nos forces autour des solutions de connectivit√© nouvelle g√©n√©ration, du cloud et de la cybers√©curit√©.\nNos 30 000 femmes et hommes pr√©sents dans 65 pays, dont chaque voix compte, sont tous anim√©s par la m√™me d√©termination et le m√™me esprit d‚Äô√©quipe, pour construire les solutions digitales d‚Äôaujourd‚Äôhui et de demain et cr√©er un impact positif pour nos clients, pour leurs salari√©s et pour la plan√®te.\nNous offrons des opportunit√©s passionnantes gr√¢ce √† des projets innovants dans la data et le digital, le cloud, l‚ÄôIA, la cybers√©curit√©, l‚ÄôIoT, ou encore le digital workspace et le big data.\nVenez vivre cette aventure avec nous !\nAfin de d√©velopper notre √©quipe lilloise, nous recherchons aujourd'hui, un Ing√©nieur DATA √† m√™me d‚Äôaccompagner nos clients dans la structuration de leurs SI autour de la donn√©e.\nVos principales missions seront les suivantes\n:\n- Concevoir des solutions de traitement et collecter des volumes importants de donn√©es.\n- Participer √† des √©tudes de cadrage pour collecter le besoin m√©tier et concevoir les solutions qui r√©pondent au besoin du client.\n- Apporter son expertise sur des probl√©matiques pr√©cises rencontr√©es chez les clients.\n- Participer √† la veille technologique\n- R√©aliser les\nd√©veloppements TALEND\n- Rester inform√© et former sur les nouvelles solutions DATA\n- Contribuer aux phases d'avant-vente et au d√©veloppement business.\n- Participer √† la conception, l'√©volution et la pr√©sentation de nos offres DATA.\nVous\n:\n- √ätes issu(e) de formation bac+5 ?\n- Vous justifiez d'au moins 3 ans d'exp√©riences en qualit√© d'Ing√©nieur DATA sur la solution TALEND Enterprise (Data Integration) et avez id√©alement une connaissance des solutions Cloud d'AWS et d'AZURE ?\n- Vous √™tes intervenu sur des projets int√©grant des pratiques DevOps et AGILE ?\nAlors postulez, ce poste est fait pour vous !\nVos comp√©tences cl√©s\n:\n- Expertise sur l'outil\nETL TALEND\nEnterprise (administration et d√©veloppement)\n- Fortes connaissances des solutions de bases de donn√©es (SQL, NoSQL‚Ä¶)\n- Connaissances en langages objets ou scripts (notamment Java mais aussi Javascript, Scala, Python‚Ä¶)\n- Divers syst√®mes d'exploitation : UNIX, Windows\nAutonomie, rigueur, curiosit√©, dynamisme et sens du service sont des qualit√©s n√©cessaires pour ce poste.\nLes comp√©tences compl√©mentaires qui seraient appr√©ci√©es :\n- Connaissances d'autres modules Talend (MDM, ESB, Data Quality, Cloud‚Ä¶)\n- Ma√Ætrise des technologies du Big Data (Hadoop, Spark, Kafka‚Ä¶)\n- Expertise sur d'autres outils ETL (Informatica, SSIS, DataStage...)\n- Notions en architecture des Syst√®mes d'Information\n- Ma√Ætrise de l'anglais (oral et √©crit)\nShow more\nShow less",
        "details": {
            "JobDetail": [],
            "TypeContract": "",
            "Salary": "",
            "Level": "Bac+5",
            "Experience": "3 an(s)"
        },
        "title": "data engineer",
        "skills": {
            "ProgLanguage": [
                "Java",
                "Scala",
                "Python"
            ],
            "DataBase": [
                "SQL",
                "NoSQL"
            ],
            "BigData": [
                "Hadoop",
                "Spark"
            ],
            "MachineLearning": [
                "Orange"
            ],
            "CloudComputing": [
                "AWS",
                "Azure"
            ],
            "OS": [
                "Windows"
            ],
            "Other": [
                "Cloud",
                "Big Data",
                "DevOps"
            ]
        }
    },
    {
        "source": "LinkedIn",
        "company": "Capgemini",
        "location": "Toulouse, Occitanie, France",
        "link": "https://fr.linkedin.com/jobs/view/data-engineer-palantir-toulouse-at-capgemini-3889716121?position=4&pageNum=10&refId=s3VlrhtbUrMVZp4kM4F1Ew%3D%3D&trackingId=G8hCyH5UBuERAOY7nMXYqQ%3D%3D&trk=public_jobs_jserp-result_search-card",
        "description": "Capgemini en quelques mots\nChoisir Capgemini, c'est choisir une entreprise o√π vous serez en mesure de fa√ßonner votre carri√®re selon vos aspirations, o√π vous serez soutenu et inspir√© par une communaut√© d‚Äôexperts dans le monde entier, o√π vous pourrez r√©√©crire votre futur. Rejoignez-nous pour red√©finir les limites de ce qui est possible, contribuer √† lib√©rer la valeur de la technologie pour les plus grandes organisations et participez √† la construction d‚Äôun monde plus durable et inclusif.\nVos missions\nVous maitrisez au minimum un langage de programmation appliqu√© √† l‚Äôanalyse de donn√©es\n(Java, Python, Scala et les environnements Spark et / ou Hadoop)\net vous avez pu intervenir sur la\nsolution Palantir.\nVous √™tes passionn√© par le Big Data et le Machine Learning et l‚Äôanalyse de donn√©es\nVous concevez et mettez en ≈ìuvre des strat√©gies s√©curis√©es d'acquisition et d'int√©gration de donn√©es\nVous configurez des r√©f√©rentiels de donn√©es √† la pointe de la technologie dans des environnements distribu√©s\nVous construisez des pipelines de donn√©es pour collecter, transformer et traiter des donn√©es en collaboration avec des scientifiques de donn√©es afin de r√©pondre aux exigences de la mod√©lisation de donn√©es d'analyse avanc√©e\nVotre profil\nDipl√¥m√©(e) de Bac+5 en informatique\n4 ans d‚Äôexp√©rience\n(au sein d‚Äôune ESN ou chez un int√©grateur) en conseil client√®le\nUne solide culture technologique\nUn bon niveau d‚Äôanglais\n3 raisons de nous rejoindre\nQualit√© de vie au travail :\naccord de t√©l√©travail en France et √† l‚Äôinternational, accord sur l‚Äô√©galit√©\nprofessionnelle, la parentalit√©, l‚Äô√©quilibre des temps et la mobilit√© durable.\nApprentissage en continu :\ncertifications et formations en libre acc√®s, accompagnement sur mesure avec\nvotre carreer manager, parcours d‚Äôint√©gration sur 9 mois.\nAvantages groupe & CSE :\nplan actionnariat, activit√©s √† tarifs pr√©f√©rentiels, remboursement partiel\nvacances, remboursement de votre abonnement sportif ou culturel\nNos engagements et priorit√©s\nLe groupe Capgemini encourage une\nculture inclusive dans un cadre multiculturel et handi-accueillant.\nEn nous rejoignant, vous int√©grez un collectif qui valorise la diversit√©, d√©veloppe le potentiel de ses talents, s‚Äôengage dans des\ninitiatives solidaires avec ses partenaires, et se mobilise pour r√©duire son impact environnemental sur tous ses sites et aupr√®s de ses clients.\nCapgemini\nest un\nleader mondial\n, responsable et multiculturel, regroupant pr√®s de 350 000 personnes dans plus de 50 pays. Fort de\n55 ans d‚Äôexp√©rience,\nnous sommes un partenaire strat√©gique des entreprises pour la transformation de leurs activit√©s en tirant profit de toute la puissance de la technologie et des innovations dans les domaines en perp√©tuelle √©volution tels que le\ncloud, la data, l‚ÄôIntelligence Artificielle, la connectivit√©, les logiciels, l‚Äôing√©nierie digitale ou les plateformes.\nGet The Future You Want* | www.capgemini.com/fr-fr\n*Capgemini, le futur que vous voulez\nShow more\nShow less",
        "details": {
            "JobDetail": [],
            "TypeContract": "",
            "Salary": "",
            "Level": "Bac+5",
            "Experience": "4 an(s)"
        },
        "title": "data engineer",
        "skills": {
            "ProgLanguage": [
                "Java",
                "Scala",
                "Python"
            ],
            "BigData": [
                "Hadoop",
                "Spark"
            ],
            "Other": [
                "Machine Learning",
                "Cloud",
                "Big Data"
            ],
            "EnSoftSkils": [
                "Collaboration"
            ]
        }
    },
    {
        "source": "LinkedIn",
        "company": "Action for Market Transformation - A4MT",
        "location": "Paris, √éle-de-France, France",
        "link": "https://fr.linkedin.com/jobs/view/data-engineer-at-action-for-market-transformation-a4mt-3910049004?position=5&pageNum=10&refId=s3VlrhtbUrMVZp4kM4F1Ew%3D%3D&trackingId=Q8pyx%2BdNkBGihv0fWQrksw%3D%3D&trk=public_jobs_jserp-result_search-card",
        "description": "A4MT ‚Äì Action pour la Transformation des March√©s\nA4MT con√ßoit et impl√©mente des programmes d‚Äôengagement et de ¬´ Market Transformation ¬ª qui visent √† g√©n√©raliser des pratiques vertueuses ‚Äì au sens environnemental et soci√©tal ‚Äì en modifiant la donne du march√©, en reconfigurant le jeu d‚Äôacteurs, g√©n√©ralement via des actions collectives.\nCes programmes agissent sur la demande en suscitant de nouvelles pratiques individuelles et collectives. A4MT assure le r√¥le de pilote, orchestrant les plans d‚Äôaction des parties prenantes gr√¢ce √† une √©quipe de qualit√© √† caract√®re international, un savoir-faire sur la mise en ≈ìuvre des programmes, une connaissance technico-√©conomique experte des sujets trait√©s, et une capacit√© √† interpeller les d√©cideurs √† bon niveau.\nChampionnat de France des √©conomies d‚Äô√©nergie\nA4MT avec ses partenaires op√®re l‚Äôensemble des concours CUBE en France (Championnat de France des Economies d‚ÄôEnergies) et assure son d√©veloppement international (Europe, Asie, etc.). CUBE est un concours original d‚Äô√©conomies d‚Äô√©nergie et de CO2 pour les b√¢timents tertiaires et r√©sidentiels qui acc√©l√®re fortement l‚Äôaction de terrain gr√¢ce √† une intelligence collective sur le terrain.\nLe concours est aujourd‚Äôhui pr√©sent dans 8 pays et se d√©veloppe encore. Au-del√† des √©conomies les plus faciles, il s‚Äôagit de mettre en ≈ìuvre la trajectoire de gestion immobili√®re et d‚Äôinvestissement qui permettra, au-del√† des avanc√©es dans ce programme √† faible investissement, de progresser sur la trajectoire de la neutralit√© carbone.\nhttps://championnatdefrancedeseconomiesdenergie.org/\nMISSION\nRendant compte au directeur d‚ÄôA4MT et en √©troite collaboration avec le directeur technique A4MT, vous √™tes Data Engineer, vous serez responsable de la conception, du d√©veloppement et de la maintenance des bases de donn√©es, et des outils de reporting. Vous travaillerez en √©troite collaboration avec l'√©quipe de d√©veloppement (prestataire externe) et vous participez √† la structuration d‚Äôune √©quipe IT interne pour cr√©er des solutions innovantes r√©pondant aux besoins de l'entreprise.\nVotre mission s'articule autours des 3 axes ci-dessous:\n1/ Pilotage et et d√©veloppement\nd√©velopper et d√©ployer des reporting robustes et √©volutifs.\nle planning de d√©veloppement et le budget allou√©.\navec les √©quipes d‚Äôanimation et le back office technique du programme et avec les prestataires externes pour comprendre les exigences et les sp√©cifications du projet.\n√† la conception de l'architecture des bases de donn√©es et √† la prise de d√©cisions techniques.\nla qualit√© des donn√©es en effectuant des contr√¥les qualit√©.\nles performances des applications pour garantir une exp√©rience utilisateur fluide.\nla maintenance et les mises √† jour r√©guli√®res des applications existantes.\n√† l'aff√ªt des tendances et des technologies √©mergentes.\nVous serez responsable du process, de la ma√Ætrise d‚Äôouvrage li√©e √† la Data et garant(e) de la qualit√© de service.\n2/ Implication des √©quipes et de la sous-traitance\nVous serez impliqu√© dans une √©quipe informatique naissante et dans une √©quipe projet avec les diff√©rentes fonctions m√©tiers. Vous devrez faire le suivi de votre implication avec le responsable de programme et le directeur technique d‚Äô A4MT :\n3/ Gestion de projet\nVous tiendrez le tableau de bord des outils : budgets, engagements, planning, r√©sultats, d√©veloppements.\nPROFIL\nVous avez une exp√©rience significative d‚Äôau moins 3 ann√©es dans l‚Äô√©cosyst√®me de big data, des serveurs et bases de donn√©es dans des contextes de projets, d‚Äôexploitation de migration.\nCOMPETENCES\nBac +5 dipl√¥m√©(e) d‚Äôune grande √©cole d‚Äôing√©nieur ou √©quivalent, vous √™tes :\n+5 dipl√¥m√© (e) d‚Äôune √©cole d‚Äôing√©nieurs ou √©quivalent, en Data science, Informatique, g√©nie logiciel ou domaine connexe.\nprofessionnelle d√©montr√©e de 3 ans ou plus en tant que Data Engineer\ndes langages structur√©s (JavaScript, Scala, Python‚Ä¶),\navec les bases de donn√©es relationnelles (MySQL, PostgreSQL) et non relationnelles (MongoDB, Firebase).\nau moins un outil de reporting (Power BI, Tableau ‚Ä¶)\ndes services de d√©ploiement et d'h√©bergement cloud comme AWS, Azure ou Google Cloud Platform.\ncomp√©tences en d√©veloppement back-end avec des technologies comme Node.js, Python, Ruby on Rails, ou Java. et notamment en PHP sont recommand√©es\ndes langages de programmation front-end tels que HTML5, CSS3 et JavaScript (notamment frameworks: comme React, Angular ou Vue.js).\n√† travailler en √©quipe, √† communiquer efficacement et √† r√©soudre les probl√®mes de mani√®re autonome.\ndes principes de s√©curit√© des applications web et des meilleures pratiques en mati√®re de d√©veloppement s√©curis√© ainsi que le respect du RGPD.\nDate d‚Äôentr√©e et conditions\nLe poste est √† pourvoir imm√©diatement; il est bas√© au 54, rue de Clichy, Paris (IX√®me). Niveau de r√©mun√©ration selon exp√©rience.\nContact\nMerci d‚Äôadresser votre candidature compl√®te (CV, lettre de motivation, pr√©sentation du cursus en cours de conclusions et r√©f√©rences √©ventuelles) √† l‚Äôattention de M. Adrien Brunella sur le mail elisabeth.clement@a4mt.com\nShow more\nShow less",
        "details": {
            "JobDetail": [],
            "TypeContract": "",
            "Salary": "",
            "Level": "",
            "Experience": "3 an(s)"
        },
        "title": "data engineer",
        "skills": {
            "ProgLanguage": [
                "Java",
                "Scala",
                "Python"
            ],
            "DataBase": [
                "MongoDB"
            ],
            "DataVisualisation": [
                "Power BI",
                "Tableau"
            ],
            "CloudComputing": [
                "AWS",
                "Google Cloud Platform",
                "Azure"
            ],
            "DBMS": [
                "PostgreSQL",
                "MySQL"
            ],
            "Other": [
                "Cloud",
                "Big Data"
            ],
            "EnSoftSkils": [
                "Collaboration"
            ]
        }
    },
    {
        "source": "LinkedIn",
        "company": "ADVANCED Schema",
        "location": "Lille",
        "link": "https://fr.linkedin.com/jobs/view/data-engineer-at-advanced-schema-3539059697?position=6&pageNum=10&refId=s3VlrhtbUrMVZp4kM4F1Ew%3D%3D&trackingId=jTTsHcD39zslHD4GFXcERg%3D%3D&trk=public_jobs_jserp-result_search-card",
        "description": "ADVANCED SCHEMA\nest une soci√©t√© de services informatiques\nsp√©cialis√©e dans la donn√©e.\nDepuis 20 ans, nous cr√©ons des plateformes data sur mesure pour nos clients, orient√©es usages et alliant qualit√©, performance, s√©curit√© et gouvernance.\nADVANCED SCHEMA\na d√©velopp√© de nouvelles activit√©s pour r√©aliser l'ambition du groupe : devenir\nune entreprise end-to-end,\nen proposant une offre √† 360¬∞ √† nos clients pour les\naccompagner √† chaque √©tape de leurs projets.\n√Ä ce jour, nous sommes pr√®s de 220 passionn√©s r√©partis entre Paris, Lille, Nantes, Lyon mettant √† profit leur expertises aussi bien dans le domaine du retail, de la finance/assurance, du luxe, des m√©dias, de la sant√© et de l'industrie.\nAujourd‚Äôhui, nous souhaitons int√©grer de nouveaux renforts dans nos √©quipes Lilloises.\nEn tant que Data Engineer, vous aurez les missions suivantes :\nConcevoir des modeÃÅlisations physiques\nConstruire des mappings techniques et r√©daction de sp√©cifications d‚Äôalimentation.\nD√©velopper des flux des donn√©es\nContribuer au pilotage de projets, de proof of concepts\nParticiper aÃÄ des missions d‚Äôexpertise\nComp√©tences professionnelles & niveau d'√©tudes requis :\nVous √™tes titulaire d'un dipl√¥me Bac +3 minimum dans le domaine de la data\nVous poss√©dez minimum 2 ans d'exp√©rience dans le m√©tier\nPositif(ve), curieux(se), rigoureux(se) et dot√©(e) d'une bonne aisance relationnelle\n√ätre enthousiaste √† l'id√©e d'apprendre de nouvelles technologies\nExp√©rience de la m√©thodologie Agile / Scrum\nCapacit√© √† planifier et √† prioriser les t√¢ches et les activit√©s confi√©es en autonomie\nMa√Ætrise de l‚Äôanglais oral et technique obligatoire\nExp√©rience av√©r√©e dans l'√©criture de code propre avec 2 ou plusieurs des technologies suivantes : BASH, SQL, Java, Python, NoSQL\nNotre proposition :\nTemps plein en\nCDI\navec un\nsalaire attractif\n+ participation aux b√©n√©fices + prime(s) sur investissement personnel\nMode de\ntravail hybride\n(agence, site, t√©l√©travail selon projets/clients)\nTicket restaurant (Sodexo)\nMutuelle financ√©e √† 50%\nPr√©voyance\nComit√© entreprise\n5 jours d‚Äôonboarding plein temps via la\nADVANCED SCHEMA Academy\nNotre investissement :\nChez\nADVANCED SCHEMA\n, nous t‚Äôoffrons un environnement de travail stimulant et collaboratif ainsi que des possibilit√©s de croissance et de d√©veloppement professionnel. √âgalement un\naccompagnement/support au quotidien\npour te faire grandir et monter en comp√©tences, sur des projets qui r√©pondent √† de\nvrais enjeux pour nos clients\n. Si tu es passionn√©(e) par les donn√©es et pr√™t(e) √† relever de nouveaux d√©fis, alors nous aussi nous aimerions te rencontrer\nProcess de recrutement :\nSi ta candidature retient notre attention, nous te proposons :\nUn premier √©change t√©l√©phonique/visio\nUn entretien physique (+questionnaire d‚Äô√©valuation) avec un senior manager\nUn entretien final √† notre si√®ge Parisien afin de rencontrer le DG\nShow more\nShow less",
        "details": {
            "JobDetail": [
                "Hybride",
                "Temps plein",
                "Senior"
            ],
            "TypeContract": "CDI",
            "Salary": "50",
            "Level": "",
            "Experience": "20 an(s)"
        },
        "title": "data engineer",
        "skills": {
            "ProgLanguage": [
                "Java",
                "Bash",
                "Python"
            ],
            "DataBase": [
                "SQL",
                "NoSQL"
            ]
        }
    },
    {
        "source": "LinkedIn",
        "company": "Goaheadspace",
        "location": "Pantin, √éle-de-France, France",
        "link": "https://fr.linkedin.com/jobs/view/data-engineer-f-h-x-at-goaheadspace-3915359112?position=7&pageNum=10&refId=s3VlrhtbUrMVZp4kM4F1Ew%3D%3D&trackingId=btBBe8MUw%2FU67f8zq5gtgA%3D%3D&trk=public_jobs_jserp-result_search-card",
        "description": "MFG Labs est une soci√©t√© de conseil et r√©alisation experte en data, qui aide les entreprises √† am√©liorer leurs prises de d√©cision, √† automatiser leurs processus et √† cr√©er de nouveaux services gr√¢ce √† la data science, au design et √† l'utilisation des derni√®res technologies.\nMFG Labs intervient √† toutes les √©tapes de votre transformation data : de la cr√©ation d'une feuille de route de projets data, √† la d√©couverte d'insights, √† la mod√©lisation de probl√©matiques complexes, de la cr√©ation d'un mod√®le pr√©dictif √† l'impl√©mentation technique d'une solution data sur-mesure\nMFG Labs accompagne ses clients de diff√©rentes mani√®res :\nStrat√©gie\nSolutions\nFondations\nMFG Labs d√©ploie une approche holistique pluridisciplinaire, en m√™lant des data scientists, des designers, des data engineers et des consultants, afin d'apporter des solutions compl√®tes de bout en bout √† des probl√©matiques complexes.\nDans le cadre du d√©veloppement de l‚Äô√©quipe, nous recherchons un.e Data Engineer √†\nPantin (magasins g√©n√©raux).\nAu sein de l‚Äô√©quipe Data Technology, vous aurez pour mission de travailler sur des probl√©matiques de collecte de la donn√©e sur tout type de support digital : web, mobile, application, voire IoT.\nVotre r√¥le au sein de l‚Äô√©quipe :\nFaire partie d‚Äôune √©quipe pluridisciplinaire avec des talents en Design de Service, Consulting et Data science.\nD√©velopper des applications de production int√©grant diff√©rents outils : des Math√©matiques Appliqu√©s, Machine (Deep) Learning, Recherche Op√©rationnelle, Statistiques.\nD√©velopper des pipelines de traitement de donn√©es avec l‚Äô√©quipe de Data Science pour : ing√©rer, transformer et d√©livrer des donn√©es et mod√®les √† nos applications.\nD√©ployer des applications utilisant les derniers outils mis √† disposition par les diff√©rents Clouds publics.\n√Ä propos de vous :\nVous √™tes titulaire d'un niveau Bac +4/Bac +5 d'une √©cole d'ing√©nieur\nVous avez au minimum deux ans d'exp√©rience hors stage ou alternance\nVous √™tes rigoureux¬∑se vis-√†-vis de vous-m√™me et des autres quant √† la qualit√© du code.\nVous avez quelques connaissances et comp√©tences solides en d√©veloppement et en en Data Ing√©nierie au sens large.\nEn\nd√©veloppement\nPython 3 et SQL\nFramework de traitement de donn√©es (Spark ou √©quivalent)\nDocker\nGIT\nEn +\nFramework permettant de d√©ployer des APIs (Flask ou √©quivalent)\nCI/CD\nLa pratique d'au moins un cloud (AWS, GCP ou Azure) est appr√©ci√©e\nEn Data Ing√©nierie\nDatawarehouse ou Datalake\nData Pipelines Batch et/ou Straming\nEn +\nOutils de BI (Tableau, Power BI‚Ä¶)\nOutils MLOps (Sagemaker, VertexAI, etc.)\nSi vous vous reconnaissez dans cette annonce, n'h√©sitez pas √† postuler !\nShow more\nShow less",
        "details": {
            "JobDetail": [],
            "TypeContract": "",
            "Salary": "",
            "Level": "",
            "Experience": null
        },
        "title": "data engineer",
        "skills": {
            "ProgLanguage": [
                "Python"
            ],
            "DataBase": [
                "SQL"
            ],
            "BigData": [
                "Spark"
            ],
            "DataVisualisation": [
                "Power BI",
                "Tableau"
            ],
            "CloudComputing": [
                "GCP",
                "AWS",
                "Azure"
            ],
            "DevTools": [
                "Git",
                "Docker"
            ],
            "Containers": [
                "Docker"
            ],
            "Other": [
                "Statistiques",
                "Cloud",
                "CI/CD"
            ]
        }
    },
    {
        "source": "LinkedIn",
        "company": "Equativ",
        "location": "Paris, √éle-de-France, France",
        "link": "https://fr.linkedin.com/jobs/view/data-engineer-internship-at-equativ-3821045783?position=8&pageNum=10&refId=s3VlrhtbUrMVZp4kM4F1Ew%3D%3D&trackingId=aPcC2%2FvBFSIXODHnsxj2aw%3D%3D&trk=public_jobs_jserp-result_search-card",
        "description": "üë´ About the team\nAt Equativ, we‚Äôre on a mission to develop advertising technologies that empower our customers to reach their digital business goals. This means that we rely on massively scalable, widely distributed, highly available, and efficient software systems; the platform deals with over 3 millions requests per second managed by 3,000 servers.\nOur innovation team based in Paris, Nantes, Limoges, Krakow and Berlin is composed of 100+ straightforward and energetic engineers working in an Agile environment and ready to tackle the most complex technical challenges.\nOur data engineering team is composed of 8 skilled engineers and is based in Paris. We are part of the R&D department which is composed of 120+ engineers spread across Paris, Nantes, Limoges, Krakow and Berlin all working in an Agile environment and ready to tackle the most complex technical challenges.\nThe data engineers are split in two sub-teams working in close collaboration:\nPipeline team: Maintaining and enhancing the operationality of our on-premise and cloud data pipelines which feed our warehouses and APIs\nFeature team: Apply best in class data modeling and orchestrating data transformations in our warehouses, leading the day-to-day management of these warehouses\nOur Mission üëá\nOur Data Engineering team is central to Equativ‚Äôs data centric business and is responsible to ingest, transform, model and redistribute all data coming from our ad tech platform.\nWe aim at building scalable and robust Big Data platforms from ingestion to business actionable consumption. Our Big Data ecosystem must handle huge volumes (15 Tb per day), short & long term data storage, complex data modeling, real-time and batch ELT as well as providing external access through dedicated APIs.\nWe enhance and deliver Equativ data directly to our customers and throughout the company whether it is for BI analysis, data science models feeding, customer reporting, invoicing and more.\nWe rely on a top tier on-premise & cloud stack (Kafka, Flink, ClickHouse, Bigquery, Dataflow, Airflow, DBT‚Ä¶) and work hard to increase reporting capabilities, lower maintenance time, improve performances and simplify the access to our raw data.\nWhat you'll do ‚úèÔ∏è\nAs a data engineer intern, you will be supporting one of the two sub-team (pipeline or feature) in their tasks and projects:\nTake a leading part on a data engineering project such as but not limited to:\nProof of Concept of Clickhouse Cloud\nImprovement of the data transformation process with DBT, BigQuery and Airflow\nDevelopment of new functionalities on our internal tools (APIs, software applications)\nSetup a data lineage application (castor doc)\nSupport the data engineering team in their day-to-day activities:\nEnhance our DevOps process with CI/CD and testing framework\nMonitor performances and workflow of our applications using reporting tool (Grafana)\nTake part in improving and deploying data engineering standards, documentation and operational guidelines around data usage at Equativ\nüí™ About you\nMaster degree in Computer Science or similar technical field of study\nPrior experience in data or software development related environment is desired\nExperience with a cloud datawarehouse (BigQuery, Snowflake, Databrick,..) is a plus\nGood knowledge of SQL and one other data programming language (Java preferred, Python, Scala..).\nKnowledge on the software development process (Git, CI/CD, test, scrum)\nWorking proficiency and communication skills in verbal and written English\nStrong interest in big data and cloud computing technologies.\nüëã About us\nEquativ is the new single name for Smart Adserver, DynAdmic, LiquidM and Nowtilus ‚Äî four proven innovators in advertising technology. The vertically integrated company provides brand and privacy-safe solutions that empower its clients to achieve maximum impact while respecting the rights of consumers. The union combines client expertise and engineering excellence to serve the interests of both the supply- side and demand-side with equal professionalism and technical sophistication.\nHeadquartered in Paris and New York, Equativ operates globally with a team of more than 550 people in 20 offices. Equativ offers the market its own independent ad server, SSP, buyer tools, and media services to fulfill the promise of advertising technology. Learn more at Equativ.com.\nThe company is ranked on the Deloitte Technology Fast 500 EMEA and in the Financial Times‚Äô FT 1000: Europe‚Äôs Fastest-Growing Companies.\nEquativ (formerly Smart AdServer) has been awarded the HappyIndex@Work label and is proud to be among the best companies in the ChooseMyCompany ranking, recognized for its flexible working environment.\nCome and lead the charge with us in building a transparent ecosystem based on quality!\nEquativ is an equal opportunity employer. Equal access to employment, services, and programs are available to everyone, regardless of race, color, ancestry, religion, sex, national origin, sexual orientation, age, citizenship, marital status, disability, gender identity, or Veteran status. If you require reasonable accommodation throughout the application and/or interview process, please contact the recruitment team at ta-team@equativ.com\nShow more\nShow less",
        "details": {
            "JobDetail": [],
            "TypeContract": "",
            "Salary": "",
            "Level": "",
            "Experience": null
        },
        "title": "data engineer",
        "skills": {
            "ProgLanguage": [
                "R",
                "Java",
                "Scala",
                "Python"
            ],
            "DataBase": [
                "SQL"
            ],
            "DataAnalytics": [
                "R"
            ],
            "BigData": [
                "Flink"
            ],
            "DevTools": [
                "Git"
            ],
            "DBMS": [
                "BigQuery",
                "Snowflake"
            ],
            "Automation": [
                "Airflow"
            ],
            "Collaboration": [
                "Teams"
            ],
            "Other": [
                "Cloud",
                "Big Data",
                "DevOps",
                "CI/CD"
            ],
            "EnSoftSkils": [
                "Communication",
                "Collaboration"
            ]
        }
    },
    {
        "source": "LinkedIn",
        "company": "Mirakl",
        "location": "Bordeaux, Nouvelle-Aquitaine, France",
        "link": "https://fr.linkedin.com/jobs/view/senior-data-engineer-at-mirakl-3904074867?position=9&pageNum=10&refId=s3VlrhtbUrMVZp4kM4F1Ew%3D%3D&trackingId=fJPMHHthjSFBbS6NfY0iYA%3D%3D&trk=public_jobs_jserp-result_search-card",
        "description": "Mirakl, leader et pionnier de l‚Äô√©conomie de plateforme, propose aux entreprises une suite unique de solutions leur permettant de transformer significativement leur e-commerce afin d'acc√©l√©rer de fa√ßon durable et rentable leur croissance. Depuis 2012, Mirakl accompagne les entreprises B2C et B2B avec la technologie la plus avanc√©e, s√©curis√©e et √©volutive leur permettant de digitaliser leur activit√© et d'√©largir leur offre via la marketplace ou le dropship, faciliter la gestion des catalogues et des paiements de leurs fournisseurs pour plus d'efficacit√©, offrir une exp√©rience d'achat personnalis√©e √† leurs clients, et augmenter leurs profits gr√¢ce au retail media. Bas√©e √† Paris et Boston, Mirakl est certifi√©e Great Place to Work.\nA propos de Mirakl Labs\nNos √©quipes techniques et produits, nomm√©es Mirakl Labs, sont principalement r√©parties entre nos 2 hubs situ√©s √† Paris et √† Bordeaux. Elles collaborent au quotidien afin d'adresser les probl√©matiques de nos clients et utilisateurs en r√©pondant √† diff√©rents challenges li√©s aux nouvelles fonctionnalit√©s, √† la scalabilit√©, la s√©curit√© et l‚Äôergonomie‚Ä¶\nElles op√®rent en mode agile et s'organisent en Squads compos√©es d'un Squad Lead, de 5 d√©veloppeurs, d'un Product Manager et d'un QA. Chaque Squad est sp√©cialis√©e sur un scope fonctionnel afin de concevoir et r√©aliser de nouvelles features, leurs √©volutions et des APIs (avec un d√©coupage en micro-services). Nos √©quipes Infrastructure, Architecture, S√©curit√©, Documentation, Product Design, Data et Support op√®rent en transverse en apportant leur expertise et de la coh√©rence sur l‚Äôensemble des produits.\nToutes les √©quipes sont responsables de leur p√©rim√®tre et chacun des collaborateurs apporte son exp√©rience et ses id√©es. Innovation, feedback et implication dans les prises de d√©cision sont au c≈ìur de notre philosophie.\nEt pour favoriser ce partage avec d‚Äôautres passionn√©s, nous sommes sponsors, speakers, et h√¥tes de diff√©rents √©v√©nements, meetups, et associations de la sc√®ne Tech en France. Au cours des derni√®res ann√©es, nous avons particip√© √† des √©v√©nements tels que Devoxx, ReactEurope, ProductConf et Flupa UX Days.\nA propos du job\nLa solution SaaS Mirakl est le moteur des marketplaces des plus importants e-commer√ßants √† travers le monde. Cette solution g√®re et produit de gros volumes de donn√©es qui pr√©sentent des challenges extr√™mement int√©ressants pour les sp√©cialistes de la donn√©e (produits, commandes, clients, niveaux de stock, prix, messages, appels API, donn√©es de navigation, s√©ries temporelles, donn√©es g√©olocalis√©es etc.).\nEn tant que (Senior) Data Engineer au sein de l‚Äô√©quipe Data Mirakl, vos principales missions seront de :\ncontribuer √† l'enrichissement de la Data Platform (ETL)\nam√©liorer la robustesse de nos pipelines de production pour nos applications Machine Learning (inf√©rence real time etc.)\nInt√©gr√©(e) dans une √©quipe de sp√©cialistes de la donn√©e (data engineers, machine learning engineers, data scientists, data analysts), vous √™tes un des acteurs cl√©s pour garantir la place de Mirakl comme solution dominante sur son march√©.\nNotre stack et nos outils\nApache Spark, Kafka, AWS, Databricks, Python, Airflow, Mlflow, Tensorflow, Delta lake, Superset, Kubernetes, Redshift, SQL, Terraform, Ansible\nAu quotidien, vous allez :\nParticiper √† la d√©finition et √† l‚Äôimpl√©mentation d‚Äôune architecture performante, robuste, scalable et aux co√ªts ma√Ætris√©s pour nos applications Spark ainsi que pour nos pipelines de production de Machine Learning (√©valuation des feature stores, refactoring de DAG Airflow)\nAccompagner les Data Scientists lors de leur mise en production (relecture de code, pair programming) et mettre en place les best practices\nOptimiser et am√©liorer la CI/CD de l‚Äô√©quipe en collaboration avec l‚Äô√©quipe SRE\nAssurer la mont√©e en comp√©tence des membres de l‚Äô√©quipe sur les sujets de MLOps et Data Engineering\nR√©fl√©chir √† la meilleure fa√ßon d'int√©grer les donn√©es Google Analytics dans la data platform\nPartager ses connaissances et pr√©senter les travaux devant toutes les √©quipes Labs\nCe qu‚Äôon peut vous apporter :\nDes projets data driven, divers et vari√©s (traitements massifs d‚Äôimages, de textes, time series etc.) pour des produits diff√©rents de Mirakl\nUne culture orient√©e sur la veille technologique\nDes projets qui ont un vrai impact business devant √™tre d√©ploy√©s sur des centaines de clients dans un contexte multilingue\nQuelques exemples de sujets en cours :\nEnrichissement des donn√©es produit √† partir des images et des descriptions\nMod√©ration automatique des produits\nMapping automatique des donn√©es produit\nIdentification des produits √† fort potentiels\nD√©tection de comportements frauduleux\nSentiment analysis sur les messages √©chang√©s entre clients et vendeurs et dans les √©valuations\nD√©termination de prix optimaux\nMonitoring de la qualit√© de service des vendeurs\nDes applications d‚Äôinf√©rence en synchrone de nos mod√®les de ML\nVous aimerez ce job si :\nVous √™tes passionn√©(e) par la data et les technologies modernes permettant d'en tirer partie\nVous vous int√©ressez √† la data science et avez des connaissances g√©n√©rales sur les algorithmes de Machine Learning\nVous avez un background en d√©veloppement et avez √©volu√© dans un environnement Data\nVous avez a minima 4 ans d‚Äôexp√©rience en environnement Machine Learning et/ou Data\nVous avez mis en production avec succ√®s des applications Big Data faisant appel √† du Machine Learning, du NLP, du traitement d‚Äôimages dans des projets d'envergure, √† fort volume de donn√©es\nVotre ma√Ætrisez Python, √™tes un pro des frameworks data de la fondation Apache et √™tes √† l'aise dans un environnement AWS\nVous ma√Ætrisez au moins un outil d‚Äôorchestration (Airflow, Data Pipeline ou tout autre outil similaire)\nVous pr√©sentez vos travaux de mani√®re simple et accessible\nVous fa√Ætes preuve d'un bon relationnel et vous aimez mentorer des collaborateurs\nVous parlez couramment anglais et fran√ßais\nLes plus pour le poste :\nVous avez une exp√©rience significative dans le domaine du e-commerce\nVous avez d√©j√† mis en place un Data Lake, Data Warehouse ou une Data Platform\nVous avez d√©ploy√© des applicatifs en environnement Kubernetes\nVous avez mis en place des pipelines d'ingestion de donn√©es avec une approche CDC √† l'aide de Debezium ou autre\nVous ma√Ætrisez Java/Scala\nMirakl est engag√©e en faveur de la diversit√©, de l‚Äô√©galit√© des chances et de l‚Äôinclusion. Nous c√©l√©brons nos diff√©rences car nous sommes convaincus que les qualit√©s visibles et invisibles de chaque Mirakl Worker sont une source de force et d‚Äôinnovation. Dans le cadre de cet engagement, nous √©tudions toutes les candidatures sans distinction de : genre, ethnicit√©, religion, orientation sexuelle, handicap, √¢ge ou toute autre caract√©ristique prot√©g√©e par la loi.\nShow more\nShow less",
        "details": {
            "JobDetail": [
                "Senior"
            ],
            "TypeContract": "",
            "Salary": "",
            "Level": "",
            "Experience": "4 an(s)"
        },
        "title": "data engineer",
        "skills": {
            "ProgLanguage": [
                "Java",
                "Scala",
                "Python"
            ],
            "DataBase": [
                "SQL"
            ],
            "BigData": [
                "Databricks",
                "Spark"
            ],
            "MachineLearning": [
                "TensorFlow"
            ],
            "CloudComputing": [
                "AWS"
            ],
            "Automation": [
                "Airflow",
                "Kubernetes",
                "Ansible"
            ],
            "InfrastructureAsCode": [
                "Terraform"
            ],
            "Containers": [
                "Kubernetes"
            ],
            "Other": [
                "ML",
                "Machine Learning",
                "Big Data",
                "CI/CD"
            ],
            "EnSoftSkils": [
                "Collaboration"
            ]
        }
    },
    {
        "source": "LinkedIn",
        "company": "relevanC",
        "location": "Paris, √éle-de-France, France",
        "link": "https://fr.linkedin.com/jobs/view/senior-data-engineer-h-f-at-relevanc-3845776902?position=10&pageNum=10&refId=s3VlrhtbUrMVZp4kM4F1Ew%3D%3D&trackingId=ElXPjoEQ7Xk%2B0Qlsl75rVA%3D%3D&trk=public_jobs_jserp-result_search-card",
        "description": "relevanC est une filiale du Groupe Casino et a √©t√© fond√©e en 2017.\nNous avons des bureaux en France, au Br√©sil et en Colombie et op√©rons √† l'√©chelle mondiale.\nNos solutions de Retail Media permettent √† nos clients de g√©n√©rer de nouvelles sources de revenus publicitaires gr√¢ce √† des annonces pertinentes et personnalis√©es.\nEn tant que Data Engineer tu auras acc√®s aux donn√©es de nos clients internes (enseignes du groupe Casino) et externes √† traiter au sein de notre data warehouse. Tes missions seront les suivantes :\ntravailler en √©troite collaboration avec tous les autres membres de la squad\n√©crire / relire du code en respectant les bonnes pratiques de d√©veloppement ainsi que les tests unitaires et participer\nassurer la co-responsabilit√© du d√©roulement des d√©ploiements, des mises en production et du bon fonctionnement des applications avec les autres membres de la squad\nr√©diger la documentation technique quand cela est n√©cessaire\nmettre en ≈ìuvre les bonnes pratiques relatives au RGPD telles que d√©finies par le tech lead\nCe CDI bas√© √† Paris centre (1er arrondissement) d√©butera d√®s que possible.\nFaire partie de relevanC, qu‚Äôest-ce que √ßa signifie ?\nTravailler sur une stack technologique de pointe (Python, PySpark, Google BigQuery, Apache, Airflow‚Ä¶)\n√ätre membre √† part enti√®re d‚Äôune √©quipe dynamique et passionn√©e aux profils tr√®s vari√©s (chefs de projets, d√©veloppeurs, designers, animations commerciales)\nTravailler dans un environnement stimulant et relever des nouveaux d√©fis chaque jour\nRejoindre une entreprise en pleine expansion avec des opportunit√©s fortes de d√©veloppements et d‚Äôinnovation\nProfil recherch√©\nDipl√¥m√©(e) d‚Äôune grande √©cole d‚Äôing√©nieur ou profil universitaire sp√©cialis√© en Data / Informatique / Math / Stats.\n5 ans (et plus) d‚Äôexp√©rience en Data Engineering\nApp√©tence forte pour le marketing digital et le retail, force de proposition, business oriented et moteur d‚Äôinnovation\nUne maitrise parfaites des bonnes pratiques de d√©veloppement\nSolides comp√©tences en Python, Spark et SQL\nUne exp√©rience sur Google Cloud Platform est un plus\nLien vers notre politique de traitement des donn√©es : https://relevanc.com/fr/politique-de-protection-des-donn%C3%A9es-recrutemen\nShow more\nShow less",
        "details": {
            "JobDetail": [],
            "TypeContract": "CDI",
            "Salary": "",
            "Level": "",
            "Experience": "5 an(s)"
        },
        "title": "data engineer",
        "skills": {
            "ProgLanguage": [
                "Python"
            ],
            "DataBase": [
                "SQL"
            ],
            "BigData": [
                "Spark"
            ],
            "CloudComputing": [
                "Google Cloud Platform"
            ],
            "DBMS": [
                "BigQuery"
            ],
            "Automation": [
                "Airflow"
            ],
            "Other": [
                "Cloud"
            ],
            "EnSoftSkils": [
                "Collaboration"
            ]
        }
    }
]